{"m_szDocID":"102135","m_szDocTitle":"Toyota Mirai Hydrogen Fuel Cell Car – Just a \"Better Battery\", Says Exec - The Green Optimistic","m_szYear":"2015","m_szDocSumamry":"Benji Jerew January 28, 2015 Car industry , Hydrogen Power , Transportation Personally, I think both battery electric cars and hydrogen fuel cell cars, such as the Toyota Mirai, have a place in the future of transportation, but maybe the solution isn’t that clearly cut. Ahh, the age-old debate between battery electric cars and hydrogen fuel cell cars… Actually, can we call it an “age-old debate” if it’s only been going on for a few years? One would have to say that it’s been going on for at least a decade, even though the technologies behind modern battery electric cars and hydrogen fuel cell ","m_szDocBody":"benji jerew car industry hydrogen power transportation personally battery electric car hydrogen fuel cell car thetoyota mirai place future transportation solution isnt cut ahh ageold debate battery electric car hydrogen fuel cell car actually call ageold debate year decade technology modern battery electric car hydrogen fuel cell car back decade battery electric car back year course battery electric car hit stride tesla model nissan leaf spring mind first latecomerto greentransportation hydrogen fuel cell car honda clarity toyota mirai late make impression time hybrid electric car toyota mirai hydrogen fuel cell car backup battery fuel cell generate electricity ondemand battery electric car toyota mirai generate emission require minute refuel technology aside shot fired bow speak notably tesla motor ceo elon musk called foolcell car nissan ceo carlos ghosn expressed concern glaring lack hydrogen fuel cell supporting infrastructure still couple automaker pushing forward massmarket hydrogen fuel cell car result encouraging japan toyota confirmed order toyota mirai and united state development release time fire shot tesla motor bow then toyota senior vice president operation bob carter done offrecord official press release speech person astounding covering variety topic toyota mirai hydrogen fuel cell car carter expressed disappointment musk earlier statement suppose mean think musk shouldnt focus battery electric car solution egg basket making comment funny people conventional car infancy electric car infancy ","m_szGeo1":"Japan","m_szSourceType":"source_news","m_szSrcUrl":"http://www.greenoptimistic.com/toyota-mirai-hydrogen-fuel-cell-20150128/","m_Places":["Toyota","Japan","United States","Carter"],"m_People":["Benji Jerew","Even Nissan","Elon Musk","Carlos Ghosn","Bob Carter"],"m_Companies":["Honda","Tesla Motors"],"m_BiGrams":["electric car","fuel cell","hydrogen fuel","battery electric","cell car","toyota mirai","car hydrogen"],"m_TriGrams":["hydrogen fuel cell","battery electric car","fuel cell car","electric car hydrogen","car hydrogen fuel"],"m_SocialTags":[],"m_Topics":[],"m_Industry":[],"m_Technology":[],"m_BiCnt":[],"m_TriCnt":[],"m_iDocBodyWordCnt":218}
