{"m_szDocID":"102346","m_szDocTitle":"Go Automobile, China's Great Wall Motor in RM2b energy-efficient vehicle venture - Business News | The Star Online","m_szYear":"2014","m_szDocSumamry":"Thursday, 10 April 2014 | MYT 12:00 AM Go Automobile, China's Great Wall Motor in RM2b energy-efficient vehicle venture by eugene mahalingam International Trade and Industry Minister Datuk Seri Mustapa Mohamed (third from left) shaking hands with Go Automobile Manufacturing Sdn Bhd chief executive officer Ahmad Azam Sulaiman at a press conference announcing the granting of the first energy efficient vehicle license on April 9. Looking on (from left to right) are Malaysian Automotive Institute chairman Datuk Muhamad Noor Yacob, International Trade and Industry Ministry secretary general Datuk D","m_szDocBody":"thursday myt automobile chinas great wall motor rmb energyefficient vehicle venture eugene mahalingam international trade industry minister datuk seri mustapa mohamed third left shaking hand automobile manufacturing sdn bhd chief executive officer ahmad azam sulaiman press conference announcing granting energy efficient vehicle licence from left right malaysian automotive institute chairman datuk muhamad noor yacob international trade industry ministry secretary general datuk rebecca fatima sta maria malaysian automotive institute chief executive officer madani sahari state domestic trade consumer affair cooperative committee chairman datuk abdul rahman ismail great wall motor international division deputy general manager roger wang kuala lumpur malaysianowned automobile manufacturing sdn bhd gam partnership chinas great wall motor gwm investing rmbil manufacture energyefficient vehicle eevs country gam chief executive officer ahmad azam sulaiman investment phase financed external internal funding rmmil externally generated bank financial institution china told press conference yesterday gam original equipment manufacturer gwm company granted eev licence implementation national automotive policy january ahmad azam phase gam investment initial investment rmmil start produce eevs early september phase production capacity unit start mid final phase total production capacity unit ready said adding gam launching haval compact midsized sport utility vehicle suvs respectively reveal ontheroad price yet determining price structure said adding total investment expected create job plant eevs manufactured gam plant gurun kedah total rmmil spent research development upgrade facility currently plant annual capacity unit said adding partnership aimed export production asean country dealership arrangement existed thailand cambodia operation expected commence quarter year eevs defined vehicle meet set defined specification term carbon emission level fuel consumption eevs include fuelefficient vehicle hybrid electric vehicle alternatively fuelled vehicle compressed natural gas liquefied petroleum gas biodiesel ethanol hydrogen fuel cell international trade industry minister datuk seri mustapa mohamed launched event yesterday kedah state government turn gurun automotive hub government granting eev licence mustapa announcement year established gam coowned individual ahmad azam farok masom wan ahmad wan omar hong kong shanghailisted gwm founded chinas largest suv pickup manufacturer own haval great wall brand employ employee company production capacity unit company sold unit year making eighthlargest automaker china targeting sell unit year local front gwm small presence malaysia malaysian automotive association sold unit year compared unit separately government launched automotive supplier excellence programme yesterday programme aim transform improve vendor capability tierone tierzero level turning global player ","m_szGeo1":"Canada","m_szSourceType":"source_news","m_szSrcUrl":"http://www.thestar.com.my/business/business-news/2014/04/10/gam-to-invest-rm2bil-in-auto-sector-it-is-in-partnership-with-great-wall-motor-to-produce-energyeffi/","m_Places":["China","Kuala Lumpur","Thailand","Cambodia","Hong Kong","Shanghai","Malaysia"],"m_People":["Eugene Mahalingam","Mustapa Mohamed","Ahmad Azam Sulaiman","Muhamad Noor Yacob","Madani Sahari","Abdul Rahman Ku Ismail","Roger Wang","Ahmad Azam","Ahmad Wan Omar"],"m_Companies":["Go Automobile Manufacturing Sdn Bhd","Trade And Industry Ministry","Great Wall Motor Co Ltd International Division","Gam","Great Wall Motor Co Ltd","Gwm","Asean","Malaysian Automotive Association"],"m_BiGrams":["great wall","ahmad azam","capacity unit","wall motor","international trade","trade industry","malaysian automotive","production capacity","unit year"],"m_TriGrams":["great wall motor","international trade industry","production capacity unit"],"m_SocialTags":[],"m_Topics":[],"m_Industry":[],"m_Technology":[],"m_BiCnt":[4,4,4,3,3,3,3,3,3],"m_TriCnt":[3,3,3],"m_iDocBodyWordCnt":381}
