{"m_szDocID":"107119","m_szDocTitle":"Nanotechnology applications could provide the required energy breakthroughs","m_szYear":"2016","m_szDocSumamry":"Posted: Sep 25, 2008 Nanotechnology applications could provide the required energy breakthroughs (Nanowerk Spotlight) Nanotechnology applications could provide decisive technological breakthroughs in the energy sector and have a considerable impact on creating the sustainable energy supply that is required to make the transition from fossil fuels. Possibilities range from gradual short- and medium-term improvements for a more efficient use of conventional and renewable energy sources all the way to completely new long-term approaches for energy recovery and utilization. With enough political w","m_szDocBody":"posted nanotechnology application provide required energy breakthrough nanowerk spotlight nanotechnology application provide decisive technological breakthrough energy sector considerable impact creating sustainable energy supply required make transition fossil fuel possibility range gradual short mediumterm improvement efficient conventional renewable energy source completely longterm approaches energy recovery utilisation political funding nanotechnology make essential contribution sustainable energy supply global climate protection policy technological foundation there take political leadership create research investment condition make happen recent nanotechnology spotlight why nanotechnology apollo programme clean energy showed intriguing chart depicted vastly diverging energy consumption pattern north american economy major european country change petroleum consumption country change petroleum consumption country basis million barrel day compiled data russia breakup soviet union europe shown comparison data source department energy energy information administration compilation chart nanowerk current financial market meltdown foolishness reckless hand market political philosophy lack comprehensive decisive energy policy clean renewable energy result incommensurably bigger longterm cost affect entire planet stark contrast european country general germany particular provide deliberate informed forwardlooking government policy impacted oil lobbyist facilitate society move renewable energy although critic country enough germany instance sundrenched region established worldleading centre photovoltaic technology legislation designed encourage development strength technology germany reflected figure analyst place country largest market turnover billion euros approx billion expected doubledigit growth rate upcoming year invest germany big business eastern germany people begun predict overtake germany automotive industry size read german legislation generate photovoltaic leadership active role german government federal state level found page application nanotechnology energy sector brochure pdf download issued state hesse describe nanotechnology solution applied today issue solution medium long run goal trigger scientific corporate innovation processe industry political leader urgently required author nanotechnology provide potential enhance energy efficiency branches industry economically leverage renewable energy production technological solution optimised production technology nanotechnology innovation impact part valueadded chain energy sector example potential application nanotechnology valueadded chain energy sector source vdi gmbh click image enlarge areas energy chain detail the summary directly brochure source nanotechnology provide essential improvement potential development conventional energy source fossil nuclear fuel renewable energy source geothermal energy sun wind water tide biomass nanocoated wear resistant drill probe example optimization lifespan efficiency system development oil natural gas deposit geothermal energy saving cost example highduty nanomaterial lighter rugged rotor blade wind tidepower plant wear corrosion protection layer mechanically stressed component bearing gear boxe etc nanotechnology play decisive role intensified solar energy photovoltaic system case conventional crystalline silicon solar cell instance increase efficiency achievable antireflection layer higher light yield exajoule joule million barrel oil global potential renewable fossil fuel data referring global energy consumption data fischedick langni nitsch nach dem ausstieg zukunftskur erneuerbare energien hirzel verlag data source german federal institute geoscience natural resource foremost however development alternative cell type thinlayer solar cell among silicon material system dye solar cell polymer solar cell predominantly profit nanotechnology polymer solar cell potential supply portable electronic device due reasonablypriced material production method flexible design mediumterm development target efficiency approx lifespan year here example nanotechnology contribute optimization layer design morphology organic semiconductor mixture component structure long run utilisation nanostructure quantum dot wire solar cell efficiency conversion conversion primary energy source electricity heat kinetic energy require utmost efficiency efficiency increase fossilfired gas steam power plant avoid considerable amount carbon dioxide emission higher power plant efficiency however require higher operating temperature heatresistant turbine material improvement possible example nanoscale heat corrosion protection layer turbine blade power plant aircraft engine enhance efficiency increased operating temperature application lightweight construction material titanium aluminide nanooptimized membrane extend scope possibility separation climateneutral storage carbon dioxide power generation coalfired power plant order render important method power generation environmentally friendlier long run energy yield conversion chemical energy fuel cell stepped nanostructured electrode catalyst membrane result economic application possibility automobile building operation mobile electronic thermoelectric energy conversion comparably promising nanostructured semiconductor optimised boundary layer design contribute increase efficiency pave broad application utilisation waste heat automobile human body heat portable electronic textile distribution reduction energy losse current transmission hope exist extraordinary electric conductivity nanomaterial carbon nanotube utilised application electric cable power line furthermore nanotechnological approaches optimization superconductive material lossless current conduction long run option wireless energy transport lasermicrowave electromagnetic resonance future power distribution require power system providing dynamic load failure management demanddriven energy supply flexible price mechanism possibility feeding number decentralised renewable energy source nanotechnology contribute decisively realisation vision inter alia nanosensory device powerelectronical component cope extremely complex control monitoring grid storage utilisation nanotechnology enhancement electrical energy store battery supercapacitor turn downright promising due cell voltage outstanding energy power density lithiumion technology regarded promising variant electrical energy storage nanotechnology improve capacity safety lithiumion battery decisively ceramic heatresistant flexible separator highperformance electrode material company evonik pushes commercialization system application hybrid electric vehicle stationary energy storage long run hydrogen promising energy store environmentallyfriendly energy supply infrastructural adjustment efficient storage hydrogen regarded critical factor success hydrogen management current material chemical hydrogen storage meet demand automotive industry require hstorage capacity weight percent nanomaterial inter alia based nanoporous metalorganic compound provide development potential economically realisable regard operation fuel cell portable electronic device important field thermal energy storage energy demand building example significantly reduced phase change material latent heat store interesting economic point view adsorption store based nanoporous material zeolite applied heat store district heating grid industry adsorption water zeolite reversible storage release heat usage achieve sustainable energy supply parallel optimised development energy source improve efficiency energy avoid unnecessary energy consumption apply branches industry private household nanotechnology provide multitude approaches energy saving example reduction fuel consumption automobile lightweight construction material basis nanocomposite optimization fuel combustion wearresistant lighter engine component nanoparticular fuel additive nanoparticle optimised tyre low rolling resistance considerable energy saving realisable tribological layer mechanical component plant machine building technology great potential energy saving tapped example nanoporous thermal insulation material suitably applicable energetic rehabilitation building general control light heat flux nanotechnological component switchable glasse promising approach reducing energy consumption building realworld example demonstrate report author live cloudcuckooland brochure list example organisation state hesse apply nanotechnology practical energy application nanostructured catalyst efficient membrane fuel cell umicore nanotechnology energy research darmstadt energy centre brochure include raft research programme financing funding opportunity europe germany ahead download read informative brochure load data chart technical example put practical context demonstrate politician engage responsible energy policy michael berger copyright nanowerk llc subscribe receive convenient notification nanowerk nanotechnology spotlight post spotlight guest author published scientific paper exciting development share nanotechnology community publish nanowerkcom ","m_szGeo1":"Russia","m_szSourceType":"source_news","m_szSrcUrl":"http://www.nanowerk.com/spotlight/spotid=7424.php","m_Places":["Russian Federation","Soviet Union","Europe","United States","Germany"],"m_People":["M. Fischedick","J. Nitsch","S. Hirzel","Michael Berger"],"m_Companies":["G7","Energy Information Administration","Pv Technology","Indeed","Source: Vdi Tz Gmbh","Lifespan","Natural Resources","Boundary","Future Power","Darmstadt Energy Center","Copyright Nanowerk Llc"],"m_BiGrams":["renewable energy","energy source","solar cell","energy supply","long run","energy sector","energy consumption","energy saving","power plant","sustainable energy","nanotechnology provide","portable electronic","fuel cell","energy storage"],"m_TriGrams":["sustainable energy supply","renewable energy source"],"m_SocialTags":[],"m_Topics":[],"m_Industry":[],"m_Technology":[],"m_BiCnt":[],"m_TriCnt":[],"m_iDocBodyWordCnt":1051}
