{"m_szDocID":"108382","m_szDocTitle":"New Plasmonic Polymer Solar Cells Achieve Record Efficiency Of 8.92% | CleanTechnica","m_szYear":"2013","m_szDocSumamry":"New Plasmonic Polymer Solar Cells Achieve Record Efficiency Of 8.92% May 10th, 2013 by James Ayre Â  A new polymer solar cells designed by researchers at the Ulsan National Institute of Science and Technology has achieved a record for the highest efficiency of any plasmonic PSCs that utilize metal nanoparticles. The new record is not far off of the 10% conversion efficiency level that the researchers think will allow the technology to break through into the commercial market. Image Credit: UNIST For some background: Polymer solar cells (PSCs) are a type of thin-film solar cell that are manufact","m_szDocBody":"plasmonic polymer solar cell achieve record efficiency jame ayre polymer solar cell designed researcher ulsan national institute science technology achieved record highest efficiency plasmonic psc utilise metal nanoparticle record conversion efficiency level researcher technology break commercial market image credit unist background polymer solar cell psc type thinfilm solar cell manufactured polymer create electricity photovoltaic effect now solar energy market dominated silicon solar cell type solar cell significant advantage silicon type psc psc lightweight inexpensive fabricate flexible customizable molecular level argued lower negative environmental impact silicon solar cell which minimal environmental impact compared electricity generation competitor barrier commercialization primary power conversion efficiency low upside technology significant enough though lot time research addressing low efficiency record press release ulsan national institute science technology unist specific solar cell design maximise pce light absorption active layer increased thick bulk heterojunction bhj film however thickness active layer limited low carrier mobility bhj material therefore way minimise thickness bhj film maximising light absorption capability active layer research team employed surface plasmon resonance spr effect multipositional silicacoated silver nps increase light absorption silica shell preserve spr effect nps preventing oxidation core ambient condition eliminate concern exciton quenching avoiding direct contact core active layer multipositional property refer ability nps introduced type layer type interface polymer fullerenebased bhj psc due silica shell jin young kim soojinpark associate professor interdisciplinary school green energy ulsan national institute science technology unist ulsan south korea led work professor jin young kim associate professor interdisciplinary school green energy unist said report introducing metal nps hole transport layer active layer enhancing device performance multipositional solutionsprocessable property surface plasmon resonance spr material offer possibility multiple plasmonic effect introducing metal nanoparticle spatial location highperformance optoelectronic device mass production technique professor soojin park added work meaningful develop metal nanoparticle reach efficiency material continuously focus optimising work commercialization psc realisation dream cleantechnicas completely free electric car report electric car early adopter follower date hottest cleantech new subscribing free cleantech newsletter eye sectorspecific new also free solar energy newsletter electric vehicle newsletter wind energy newsletter tag bhj korea solar energy research plasmodia polymer solar cell plasmonic polymer solar cell polymer solar cell highest efficiency polymer solar cell polymer solar panel psc solar cell psc psc psc pce solar cell efficiency solar cell efficiency record solar cell efficiency record solar cell research solar cell alternative silicon solar cell plastic spr ulsan national institute science technology unist jame ayre background predominantly geopolitic history obsessive interest pretty everything early life spent imperial free city dortmund jame river ruhr cofbuokheim attended university astnide briefly considered entering coal mining business write living broad variety subject ranging science politic military history renewable energy follow work google related post ","m_szGeo1":"South Korea","m_szSourceType":"source_news","m_szSrcUrl":"http://cleantechnica.com/2013/05/10/new-plasmonic-polymer-solar-cells-achieve-record-efficiency-of-8-92-highest-for-any-plasmonic-polymer-solar-cells-utilizing-metal-nanoparticles/","m_Places":["Ulsan","South Korea","Korea","Free City","Dortmund"],"m_People":["James Ayre","Jin Young Kim","Professor Soojin"],"m_Companies":["Ulsan National Institute Of Science And Technology","Unist","University Of Astnide","Google"],"m_BiGrams":["solar cell","polymer solar","active layer","ulsan national","national institute","institute science","science technology","metal nanoparticle","solar energy","silicon solar","efficiency record","technology unist","light absorption","cell efficiency"],"m_TriGrams":["polymer solar cell","ulsan national institute","national institute science","institute science technology","silicon solar cell","science technology unist","solar cell efficiency"],"m_SocialTags":[],"m_Topics":[],"m_Industry":[],"m_Technology":[],"m_BiCnt":[19,8,5,4,4,4,4,3,3,3,3,3,3,3],"m_TriCnt":[7,4,4,4,3,3,3],"m_iDocBodyWordCnt":442}
