{"m_szDocID":"113535","m_szDocTitle":"Inventiveness fills Union Station for annual Maker Faire | The Kansas City Star","m_szYear":"2015","m_szDocSumamry":"June 27, 2015 3:48 PM Inventiveness fills Union Station for annual Maker Faire Brigid Reilly, 3, of Belton, reacted to the costume worn by James Bink from the movie \"Predator,\" at the fifth annual Maker Faire at Union Station on Saturday. DAVID EULITT deulitt@kcstar.com Raymond Hadlock, left, holds a snake skin computer case, and Mark Tovar, owner of Eden Bio-Creations, holds a shedded snake skin at the Maker Faire Saturday in Kansas City. Tovar created a polymerizing process that preserves snake skins and crafts them into durable cell phone cases. Other uses are in the works. Karl Ramberg, 15","m_szDocBody":"inventiveness fill union station annual maker faire brigid reilly belton reacted costume worn jame bink movie predator annual maker faire union station saturday david eulitt raymond hadlock left hold snake skin computer case mark tovar owner eden biocreation hold shedded snake skin maker faire kansas city tovar created polymerizing process preserve snake skin craft durable cell phone case work karl ramberg kirksville wore oculus rift headset sampling virtual reality equipment immerse user realistic video game environment head movement annual maker faire union station saturday david eulitt skylar mann month photograph droid movie star war lobby union station annual maker faire david eulitt calen hoffman propcustomz dressed charactergroot movie guardian galaxy waited pose visitor annual maker faire union station david eulitt leah dandrea kessel runner racing nashville raced electric vehicle herbie love bug makeshift track parking lot union station afternoon qualifying race annual maker faire david eulitt sibling ben crawford alyssa crawford right merriam fenced demonstration creative anachronism member annual maker faire union station david eulitt breanna hampton kansas city kansas reacted touched hand van graaff generator institute electrical electronic engineer booth annual maker faire union station saturday david eulitt ben hutcheson omaha piloted electric electric vehicle minecart video game mineshaft makeshift track parking lot union station afternoon qualifying race annual maker faire david eulitt ","m_szGeo1":"United States","m_szSourceType":"source_news","m_szSrcUrl":"http://www.kansascity.com/news/local/article25669153.html","m_Places":["Belton","Kansas City","Kirksville, Mo.","Kessel","Nashville, Tn","Kansas City, Kansas","Omaha"],"m_People":["Brigid Reilly","David Eulitt","Raymond Hadlock","Mark Tovar","Eden Bio","Karl Ramberg","Skylar Mann","Leah D'andrea","Ben Crawford","Alyssa Crawford","Breanna Hampton","Van De Graaff","Ben Hutcheson"],"m_Companies":["Union Station","Oculus","R2","Racing","Institute Of Electrical And Electronics Engineers"],"m_BiGrams":["maker faire","union station","annual maker","david eulitt","faire union","station saturday","saturday david","snake skin","faire david"],"m_TriGrams":["annual maker faire","maker faire union","faire union station","union station saturday","station saturday david","saturday david eulitt","maker faire david","faire david eulitt"],"m_SocialTags":[],"m_Topics":[],"m_Industry":[],"m_Technology":[],"m_BiCnt":[10,9,9,8,5,3,3,3,3],"m_TriCnt":[9,5,5,3,3,3,3,3],"m_iDocBodyWordCnt":214}
