{"m_szDocID":"114074","m_szDocTitle":"California Green Innovation Index goes global: Golden State ranks top among countries worldwide - Oil & Gas 360","m_szYear":"2015","m_szDocSumamry":"textArticle -------------------- California Green Innovation Index goes global: Golden State ranks top among countries worldwide  May 18, 2015 - 11:00 AM EDT close yes               California Green Innovation Index goes global: Golden State ranks top among countries worldwide State is among world's least carbon-intensive economies; in top ten renewable energy generation, clean tech investment and energy productivity SAN FRANCISCO, May 18, 2015 /PRNewswire/ -- In advance of the historic United Nations Climate Change Conference (COP21) in Paris this year, the California Green Innovation Index, ","m_szDocBody":"california green innovation index global golden state rank top country worldwide edt close california green innovation index global golden state rank top country worldwide state world carbonintensive economy top renewable energy generation clean tech investment energy productivity san francisco advance historic united nation climate change conference cop paris year california green innovation index time analyse rank golden state economic energy performance comparison world largest greenhouse gas ghg emitting nation california green innovation index international edition chart gdp emission energy productivity renewable energy generation clean tech investment key metric california collectively lead world critical indicator with world largest economy california growing gdp shrinking carbon footprint prime decoupling economic growth energy beginning happen world productive nation noel perry businessman founder nonpartisan nonprofit observance climate week paris eve business climate summit unesco headquarter perry report finding international audience including business government leader journalist reception hotel talleyrand paris finding california include rank top nation worldwide total renewable energy generation share electricity renewable source highest energy productivity lowest carbon intensity emission gdp world carbonintensive economy dollar good service california emit carbon nation france world energy productivity gdp relative total energy consumption generated percent gdp unit energy consumed unit energy state produced billion gdp compared billion gdp attracted half billion clean tech global venture capital investment second whole percent increase investment generated percent electricity renewable source half fourth large emitter total share electricity renewable top emitter energy electricity capita cut electricity capita percent total energy capita percent cut ghg emission capita percent increased gdp capita percentthe with california cut emission capita percent increased gdp capita percent average monthly residential electricity bill decreased percent industrial declined percent commercial increased percent california established ghg agreement multiple nation china peru mexico israel this year california green innovation index track clear shift clean energy world fossil fuel represent significant portion energy use analyst reached important tipping pointglobally adding capacity renewable power annually fossil fuel doug henton chairman ceo collaborative economic developed california green innovation index international edition california green innovation index international edition show transition playing world top emitter ghg nation california france california italy lowest carbon intensive economy world nigeria italy japan united kingdom california lead world energy productivity japan south korea germany california lead world clean tech patent clean tech venture capital funding rose percent billion funding fell percent billion onethird global electric vehicle sold country half sale happened california electricity capita increased percent increased percent total energy capita fell percent week mark kick climate week parisa historic gathering worldwide business policy leader event business climate summit unesco office paris leader highlight business policy solution decarbonizing economy event wake international energy agency announcement suggesting process decoupling economic growth ghg emission underway global economy grew carbon emission not business climate summit string international event building momentum climate agreement key climate summit held year paris share index finding twitter led #cleantech innovation global patent #giicleanfact howd that generated gdp #energy consumed #giicleanfact growing #gdp faster #energy #giicleanfact independent nonpartisan organisation educate engage empower californian improve state future focus intersection economy environment quality life employ research leading expert complex state issue create portfolio nonpartisan educational material foster deeper understanding critical issue affecting state collaborative economic collaborative economic developed california green innovation index silicon valleybased research consulting organisation coecon work businesse foundation government education community sector leading edge innovation clean economy analysis state region country contact edt ","m_szGeo1":"United States","m_szSourceType":"source_industry","m_szSrcUrl":"http://www.oilandgas360.com/california-green-innovation-index-goes-global-golden-state-ranks-top-among-countries-worldwide/","m_Places":["California","Paris","United States","France","China","Peru","Mexico","Israel","France , California","Italy","Nigeria","Japan","United Kingdom","South Korea","Germany","Silicon Valley"],"m_People":["F. Noel Perry","Doug Henton"],"m_Companies":["Collaborative Economics","Eu","Unesco","International Energy Agency","Twitter","Www.coecon.com"],"m_BiGrams":["california green","green innovation","innovation index","clean tech","energy productivity","capita percent","climate summit","golden state","rank top","renewable energy","energy generation","index international","international edition","lead world","business climate","electricity renewable","total energy","electricity capita","percent increased","increased percent","collaborative economic"],"m_TriGrams":["california green innovation","green innovation index","renewable energy generation","innovation index international","index international edition","business climate summit"],"m_SocialTags":[],"m_Topics":[],"m_Industry":[],"m_Technology":[],"m_BiCnt":[8,8,8,5,5,5,4,3,3,3,3,3,3,3,3,3,3,3,3,3,3],"m_TriCnt":[8,8,3,3,3,3],"m_iDocBodyWordCnt":555}
