{"m_szDocID":"115891","m_szDocTitle":"Apple Pay isn’t ready to replace your wallet - MarketWatch","m_szYear":"2014","m_szDocSumamry":"Latest News Dow 16,454 +257.42 +1.59% Nasdaq 4,534 +98.11 +2.21% S&P 500 1,927 +31.24 +1.65% 10:48 P.M. ET Aston Martin teams with China’s LeEco to build electric car 10:34 P.M. ET Updated Obama to visit Cuba in March 10:22 P.M. ET Asian markets rise, riding wave of U.S. gains 9:54 P.M. ET China's consumer inflation sped up in January 8:47 P.M. ET Spain raids China’s ICBC offices in money-laundering probe 8:36 P.M. ET Pope Francis issues emotional plea for migrants on U.S. border 7:45 P.M. ET Japanese exports plunge 13% in January 7:43 P.M. ET Fed’s Bullard speaks against further interest-rate","m_szDocBody":"latest new dow nasdaq s&p aston martin team chinas leeco build electric car updated obama visit cuba asian market rise riding wave gain chinas consumer inflation sped spain raid chinas icbc office moneylaundering probe pope francis issue emotional plea migrant border japanese export plunge fed bullard speak interestrate hike updated nikki haley endorse marco rubio president ceo apple fight fbi encryption yahoo close digital magazine burbank office turkish leader cancel migration meeting deadly bombing fbi wanted apple government collect student debt updated apple escalate war silicon valley barrick gold post big loss impairment charge updated havent learned financial crisis marathon oil post annual loss year nvidia profit rose revenue exceeded guidance william swing unexpected loss netapp cut worker amid earning decline log home new viewer video radio podcast game portfolio marketwatch new viewer market market stream east emerging market asia canada column market snapshot mover shaker currency future mover premarket new tool earning wall market overview ipo calendar earning calendar currency tool future contract market screener hulbert interactive investing stock mutual fund etf option bond commodity currency future hedge trade started marketwatch adviser column option trader revolution investing tool stock screener fund finder etf screener option screener ipo calendar earning calendar more trading deck personal finance big spender real estate spending saving taxe column moneyologist brett arend bill bischoff amy hoak chuck jaffe jennifer openshaw jennifer water tool fund finder today rate retirement retirementor encore taxe retire here howto guide social security estate planning event column robert powell retirement portfolio andrea coombess working retirement tool retirement planner long money last economy federal reserve capitol report economic report column darrell delamaide irwin kellner rex nutting tool economic calendar real estate location scout realtorcom marketwatch portfolio watchlist alert game log home industry service box alert opinion apple pay isnt ready replace wallet steve shear published share battle digital wallet beginning steveshear food market apple pay capture imagination consumer wouldnt idea leaving wallet home waving cell phone checkout counter pay something feel spending money retailer that too but problem leave home wallet apple pay reader universally available raise question successful apple pay limited number retailer accepting mobile phone payment turn out timing apple pay planned introduction currentc payment app backed retailer merchant customer exchange mcx consortium walmart store wmt incredibly wellplanned entire paymentssystem backbone major overhaul year ahead key deadline magnetic stripe back credit card palm pilot replaced card embedded microchip transition costly disruptive retailer market maintain strength year end geoffrey rogow browning discuss market handle endoftheyear stretch mike ramsey auto sale cost upgrade estimated billion javelin strategy research majority expense retailer businesse accept credit card upgrade pointofsale equipment tune billion skirmish emerging apple aapl retailer credit card company gain upperhand advantage upgrade cvs health cvs rite aid rta member mcx consortium back currentc disabled ability accept apple pay terminal example apple pay based credit card system currentc based directdeposit technology allowing retailer pay lower fee significant change pay store lifetime payment fee grab race huge potential marketing opportunity phone shop walk store precious customer spending data update creditcard processing standard europay mastercard visa emv fraudprevention measure emv designed make massive data breaches plaguing retailer target tgt home depot harder pull off deadline force retailer card issuer move payment system rule liable case fraud retailer accept payment emv card nonemv compliant pointofsale device assume liability event fraud essentially retailer upgrade liability card fraud devastating business essentially move payment economy analogue digital fact significant change pay store lifetime simplifying checkout counter expect bit confusion year two apple retailer credit card company control point sale data move system consumer pay watch closely checkout counter accepting technology opt data collection time leave wallet home steve shear vice president manager treasury management western trust develop customised solution business client effectively manage financial function including liquidity risk mitigation marketwatch quote reference wmt aapl cvs rta tgt show reference new marketwatch top storey trending recommended havent learned financial crisis here speculation china massselling treasury true indicator suggest week stockmarket rally wont ted cruz overtake donald trump nationally latest republican presidential poll pope francis issue emotional plea migrant border marketwatch partner centre hear join conversation comment economy politic learned financial crisis sponsored barron trouble timing market mansion global julia robert cut price kauai beach home million personal finance ceo explain apple defiance court order sponsored headline marketwatch index topic feedback newsroom roster media archive premium product mobile company company info code conduct correction advertising media kit advertise locally licence broker centre choice dow jone network wsjcom barron online bigchart virtual stock exchange financial new online wsjcom small business realtorcom mansion global back top copyright marketwatch inc right reserved agree term service privacy policy cookie policy intraday data provided financial information subject term use historical current endofday data provided financial information intraday data delayed exchange requirement jone indice dow jone company inc quote local exchange time real time sale data provided nasdaq information nasdaq traded symbol current financial status intraday data delayed minute nasdaq minute exchange jone indice dow jone company inc sehk intraday data provided financial information minute delayed quote local exchange time advanced walmart store inc nyse wmt volume open low ratio div yield market cap apple inc nasdaq aapl volume open low ratio div yield market cap cvs health corp nyse cvs volume open low ratio div yield market cap rite aid corp germany frankfurt rta volume open low ratio div yield market cap mastercard inc nyse volume open low ratio div yield market cap visa inc nyse volume open low ratio div yield market cap target corp nyse tgt volume open low ratio div yield market cap home depot inc nyse volume open low ratio div yield market cap latestnew","m_szGeo1":"United States","m_szSourceType":"source_investments","m_szSrcUrl":"http://www.marketwatch.com/story/apple-pay-isnt-ready-to-replace-your-wallet-2014-11-04","m_Places":["China","Leeco","Cuba","United States","Spain","Bullard","Silicon Valley","District Of Columbia","Take","Europe","Middle East","Asia","Canada","Hulbert","Mobile","Germany","Frankfurt"],"m_People":["Nikki Haley","Marco Rubio","Brett Arends","Bill Bischoff","Amy Hoak","Chuck Jaffe","Jennifer Openshaw","Robert Powell","Andrea Coombes","Darrell Delamaide","Irwin Kellner","Rex Nutting","Geoffrey Rogow","Mike Ramsey","Ted Cruz","Donald Trump","Julia Roberts"],"m_Companies":["Nasdaq","Aston Martin","Google","Apple","Fbi","Yahoo","Eu","Barrick Gold","Marathon Oil","Nvidia","Williams","Netapp","Marketwatch","Shakers","Revolution","Social Security","Federal Reserve","Box","Whole Foods Market","Wal-mart Stores","Palm","Cvs Health","Cvs","Rite Aid","Mastercard","Target","Home Depot","U.s. Treasurys","Barron's","Marketwatch, Inc.","Six Financial","Dow Jones & Company, Inc.","Wal-mart Stores Inc.","Apple Inc.","Cvs Health Corp.","Rite Aid Corp.","Mastercard Inc.","Visa Inc.","Target Corp","Home Depot Inc."],"m_BiGrams":["volume open","open low","low ratio","ratio div","div yield","yield market","market cap","apple pay","credit card","intraday data","data provided","inc nyse","learned financial","financial crisis","checkout counter","dow jone","provided financial","financial information","nyse volume"],"m_TriGrams":["volume open low","open low ratio","low ratio div","ratio div yield","div yield market","yield market cap","learned financial crisis","data provided financial","provided financial information","inc nyse volume","nyse volume open"],"m_SocialTags":[],"m_Topics":[],"m_Industry":[],"m_Technology":[],"m_BiCnt":[],"m_TriCnt":[],"m_iDocBodyWordCnt":942}
