{"m_szDocID":"116004","m_szDocTitle":"Robo-annuities are coming soon - MarketWatch","m_szYear":"2015","m_szDocSumamry":"Latest News Dow 16,454 +257.42 +1.59% Nasdaq 4,534 +98.11 +2.21% S&P 500 1,927 +31.24 +1.65% 10:48 P.M. ET Aston Martin teams with China’s LeEco to build electric car 10:34 P.M. ET Updated Obama to visit Cuba in March 10:22 P.M. ET Asian markets rise, riding wave of U.S. gains 9:54 P.M. ET China's consumer inflation sped up in January 8:47 P.M. ET Spain raids China’s ICBC offices in money-laundering probe 8:36 P.M. ET Pope Francis issues emotional plea for migrants on U.S. border 7:45 P.M. ET Japanese exports plunge 13% in January 7:43 P.M. ET Fed’s Bullard speaks against further interest-rate","m_szDocBody":"latest new dow nasdaq s&p aston martin team chinas leeco build electric car updated obama visit cuba asian market rise riding wave gain chinas consumer inflation sped spain raid chinas icbc office moneylaundering probe pope francis issue emotional plea migrant border japanese export plunge fed bullard speak interestrate hike updated nikki haley endorse marco rubio president ceo apple fight fbi encryption yahoo close digital magazine burbank office turkish leader cancel migration meeting deadly bombing fbi wanted apple government collect student debt updated apple escalate war silicon valley barrick gold post big loss impairment charge updated havent learned financial crisis marathon oil post annual loss year nvidia profit rose revenue exceeded guidance william swing unexpected loss netapp cut worker amid earning decline log home new viewer video radio podcast game portfolio marketwatch new viewer market market stream east emerging market asia canada column market snapshot mover shaker currency future mover premarket new tool earning wall market overview ipo calendar earning calendar currency tool future contract market screener hulbert interactive investing stock mutual fund etf option bond commodity currency future hedge trade started marketwatch adviser column option trader revolution investing tool stock screener fund finder etf screener option screener ipo calendar earning calendar more trading deck personal finance big spender real estate spending saving taxe column moneyologist brett arend bill bischoff amy hoak chuck jaffe jennifer openshaw jennifer water tool fund finder today rate retirement retirementor encore taxe retire here howto guide social security estate planning event column robert powell retirement portfolio andrea coombess working retirement tool retirement planner long money last economy federal reserve capitol report economic report column darrell delamaide irwin kellner rex nutting tool economic calendar real estate location scout realtorcom marketwatch portfolio watchlist alert game log retirementor powered retirementor feature retirement advice financial professional staff journalist home retirementor annuity roboannuity coming stan haithcock published share stanhaithcock stan annuity man annuity specialist nationally recognised annuity critic stan highly acclaimed book annuity stanifesto year experience financial service industry developed unique proprietary annuity strategy adopted annuity industry stan annuity man specialise providing clarity bestfit annuity option customised deliver guaranteed portion portfolio independent noncaptive annuity resource focuse asset protection solution lifetime income legacy full control longterm care stan annuity man called national consumer advocate annuity speak country annuity properly work portfolio stan annuity man live ponte vedra beach florida client nationwide learn stantheannuitymancom stan latest post annuity upfront bonuse country stand line annuity week backtesting potential return indexedannuity joke dont annuity world killer app handcuff powered getty image financial landscape consumer changing light speed technology demographic customer demand creating perfect storm permanent people buy financial product invest retirement money back year ago nightandday comparison happening now however financial category stuck technological time warp eventually forced consumer change well guessed annuity industry wearing digital leisure suit roboadvisor clearing roboadvisor phenomenon started money raised platform wakeup call traditional human distribution method broker advisor agent rias master universe pay attention dismiss gamechanging trend people tired sold political tea leave angst change totally neverending status quo politic precursor type change demanded financial consumer people tired its done fresh ideas establishment think wall street annuity carrier eventual annuity agent extinction political speak annuity company rid agent army second agent walking talking liability carrier control said pitched promised carrier realise direct model eventual trend annuity agent join extinct category travel agent encyclopaedia salesmen product pricing common sense remove agent compensation middlemen cut carrier provide product pricing consumer directtoconsumer annuity model higher contractual guarantee board annuity type consumer educated fact directsale model change happen swiftly simplicity win roboannuity directtoconsumer model simplistic noannualfee annuity finally dominate annuity landscape single premium annuity spias fixedrate annuity mygas qualified longevity annuity contract qlac deferred income annuity diaslongevity annuity primary product purchased pure transferofrisk solution simplicity fullproduct transparency finally demanded annuity consumer uber disruption future largest transportation company country vehicle company uber largest hotel chain country property company airbnb largest retailer country store talking amazon amzn year ago case company legitimate industry disruption prove consumer category remain same technology creativity pure entrepreneurial spirit eventually rule day include stodgy annuity industry agent kitchen table anymore annuity industry delusion people agent meet customer kitchen table part buying process truth generation consumer expect kind fact face superficial service dying replaced digitally savvy buyer fact information term show steve job prophetically people show them right hold true distribution financial product consumer buy them fascinating watch process evolve year annuity category adapt predictable consumer trend happen roboannuity annuity direct consumer model dominate vast majority annuity purchased good new happen opinion marketwatch quote reference amzn new marketwatch top storey trending recommended havent learned financial crisis here speculation china massselling treasury true indicator suggest week stockmarket rally wont ted cruz overtake donald trump nationally latest republican presidential poll pope francis issue emotional plea migrant border marketwatch partner centre hear join conversation comment economy politic learned financial crisis sponsored barron trouble timing market mansion global julia robert cut price kauai beach home million personal finance ceo explain apple defiance court order sponsored headline marketwatch index topic feedback newsroom roster media archive premium product mobile company company info code conduct correction advertising media kit advertise locally licence broker centre choice dow jone network wsjcom barron online bigchart virtual stock exchange financial new online wsjcom small business realtorcom mansion global back top copyright marketwatch inc right reserved agree term service privacy policy cookie policy intraday data provided financial information subject term use historical current endofday data provided financial information intraday data delayed exchange requirement jone indice dow jone company inc quote local exchange time real time sale data provided nasdaq information nasdaq traded symbol current financial status intraday data delayed minute nasdaq minute exchange jone indice dow jone company inc sehk intraday data provided financial information minute delayed quote local exchange time advanced amazoncom inc nasdaq amzn volume open low ratio div yield market cap latestnew","m_szGeo1":"United States","m_szSourceType":"source_investments","m_szSrcUrl":"http://www.marketwatch.com/story/robo-annuities-are-coming-soon-2015-10-27","m_Places":["China","Leeco","Cuba","United States","Spain","Bullard","Silicon Valley","District Of Columbia","Take","Europe","Middle East","Asia","Canada","Hulbert","Ponte","Florida","Wall Street","Mobile"],"m_People":["Nikki Haley","Marco Rubio","Brett Arends","Bill Bischoff","Amy Hoak","Chuck Jaffe","Jennifer Openshaw","Robert Powell","Andrea Coombes","Darrell Delamaide","Irwin Kellner","Rex Nutting","Stan Haithcock","Ted Cruz","Donald Trump","Julia Roberts"],"m_Companies":["Nasdaq","Aston Martin","Google","Apple","Fbi","Yahoo","Eu","Barrick Gold","Marathon Oil","Nvidia","Williams","Netapp","Marketwatch","Shakers","Revolution","Social Security","Federal Reserve","Nationwide","Getty Images","Uber","Airbnb","Amazon","U.s. Treasurys","Barron's","Marketwatch, Inc.","Six Financial","Dow Jones & Company, Inc.","Amazon.com Inc"],"m_BiGrams":["stan annuity","annuity man","annuity industry","intraday data","data provided","learned financial","financial crisis","dow jone","provided financial","financial information"],"m_TriGrams":["stan annuity man","learned financial crisis","data provided financial","provided financial information"],"m_SocialTags":[],"m_Topics":[],"m_Industry":[],"m_Technology":[],"m_BiCnt":[],"m_TriCnt":[],"m_iDocBodyWordCnt":971}
