{"m_szDocID":"116091","m_szDocTitle":"El-Erian bets against Wall Street - MarketWatch","m_szYear":"2014","m_szDocSumamry":"Latest News Dow 16,454 +257.42 +1.59% Nasdaq 4,534 +98.11 +2.21% S&P 500 1,927 +31.24 +1.65% 10:48 P.M. ET Aston Martin teams with China’s LeEco to build electric car 10:34 P.M. ET Updated Obama to visit Cuba in March 10:22 P.M. ET Asian markets rise, riding wave of U.S. gains 9:54 P.M. ET China's consumer inflation sped up in January 8:47 P.M. ET Spain raids China’s ICBC offices in money-laundering probe 8:36 P.M. ET Pope Francis issues emotional plea for migrants on U.S. border 7:45 P.M. ET Japanese exports plunge 13% in January 7:43 P.M. ET Fed’s Bullard speaks against further interest-rate","m_szDocBody":"latest new dow nasdaq s&p aston martin team chinas leeco build electric car updated obama visit cuba asian market rise riding wave gain chinas consumer inflation sped spain raid chinas icbc office moneylaundering probe pope francis issue emotional plea migrant border japanese export plunge fed bullard speak interestrate hike updated nikki haley endorse marco rubio president ceo apple fight fbi encryption yahoo close digital magazine burbank office turkish leader cancel migration meeting deadly bombing fbi wanted apple government collect student debt updated apple escalate war silicon valley barrick gold post big loss impairment charge updated havent learned financial crisis marathon oil post annual loss year nvidia profit rose revenue exceeded guidance william swing unexpected loss netapp cut worker amid earning decline log home new viewer video radio podcast game portfolio marketwatch new viewer market market stream east emerging market asia canada column market snapshot mover shaker currency future mover premarket new tool earning wall market overview ipo calendar earning calendar currency tool future contract market screener hulbert interactive investing stock mutual fund etf option bond commodity currency future hedge trade started marketwatch adviser column option trader revolution investing tool stock screener fund finder etf screener option screener ipo calendar earning calendar more trading deck personal finance big spender real estate spending saving taxe column moneyologist brett arend bill bischoff amy hoak chuck jaffe jennifer openshaw jennifer water tool fund finder today rate retirement retirementor encore taxe retire here howto guide social security estate planning event column robert powell retirement portfolio andrea coombess working retirement tool retirement planner long money last economy federal reserve capitol report economic report column darrell delamaide irwin kellner rex nutting tool economic calendar real estate location scout realtorcom marketwatch portfolio watchlist alert game log home industry banking marketwatch alert elerian bet wall street david weidner published share peertopeer lending highprofile vote confidence davidweidner columnist bloomberg mohamed elerian san francisco marketwatch evangelist normal signalling future financial service look surprise bank doesnt involve bank free constraint pacific investment management bond guru mohamed elerian lead investor million fund raising payoffcom inc latest entry peertopeer lending space peertopeer lender offer loan backed investor deposit payoff peertopeer lender prosper marketplace lending club corp part wave financialservice alternative created silicon valley began decade ago technology industry gradually covering spectrum retail financial service payment system apple inc aapl apple pay ebay inc ebay paypal venmo onlinetrading firm including etrade financial corp etfc alternative currency bitcoin peertopeer lending stand direct challenge banking industry core business taking deposit making loan lender borrower pay creditcard highinterest loan disrupt bank fee income generated traditional product socalled ridesharing provider uber lyft challenged taxi limousine industry course lender reach critical mass that theyll support trusted identifiable participant elerian investment important validation alternative financial service widely respected elerian bring attention authenticity fledgling business lending step closer shedding alternative label normal marketwatch quote reference aapl ebay etfc new marketwatch top storey trending recommended havent learned financial crisis here speculation china massselling treasury true indicator suggest week stockmarket rally wont ted cruz overtake donald trump nationally latest republican presidential poll pope francis issue emotional plea migrant border david weidner david weidner cover wall street marketwatch follow marketwatch partner centre david weidner david weidner cover wall street marketwatch follow hear join conversation comment economy politic learned financial crisis sponsored barron trouble timing market mansion global julia robert cut price kauai beach home million personal finance ceo explain apple defiance court order sponsored headline marketwatch index topic feedback newsroom roster media archive premium product mobile company company info code conduct correction advertising media kit advertise locally licence broker centre choice dow jone network wsjcom barron online bigchart virtual stock exchange financial new online wsjcom small business realtorcom mansion global back top copyright marketwatch inc right reserved agree term service privacy policy cookie policy intraday data provided financial information subject term use historical current endofday data provided financial information intraday data delayed exchange requirement jone indice dow jone company inc quote local exchange time real time sale data provided nasdaq information nasdaq traded symbol current financial status intraday data delayed minute nasdaq minute exchange jone indice dow jone company inc sehk intraday data provided financial information minute delayed quote local exchange time advanced apple inc nasdaq aapl volume open low ratio div yield market cap ebay inc nasdaq ebay volume open low ratio div yield market cap etrade financial corp nasdaq etfc volume open low ratio div yield market cap latestnew","m_szGeo1":"United States","m_szSourceType":"source_investments","m_szSrcUrl":"http://www.marketwatch.com/story/el-erian-bets-against-wall-street-2014-10-22","m_Places":["China","Leeco","Cuba","United States","Spain","Bullard","Silicon Valley","District Of Columbia","Take","Europe","Middle East","Asia","Canada","Hulbert","Wall Street","Mobile"],"m_People":["Nikki Haley","Marco Rubio","Brett Arends","Bill Bischoff","Amy Hoak","Chuck Jaffe","Jennifer Openshaw","Robert Powell","Andrea Coombes","Darrell Delamaide","Irwin Kellner","Rex Nutting","Mohamed El-erian","David Weidner","Ted Cruz","Donald Trump","Julia Roberts"],"m_Companies":["Nasdaq","Aston Martin","Google","Apple","Fbi","Yahoo","Eu","Barrick Gold","Marathon Oil","Nvidia","Williams","Netapp","Marketwatch","Shakers","Revolution","Social Security","Federal Reserve","Pacific Investment Management Co","Prosper Marketplace","Lending Club Corp.","Apple Inc.","Ebay Inc.","Ebay","Paypal","Venmo","E-trade","Financial Corp","Uber","Lyft","Critical Mass","U.s. Treasurys","Twitter","Barron's","Marketwatch, Inc.","Six Financial","Dow Jones & Company, Inc.","E*trade Financial Corp"],"m_BiGrams":["david weidner","intraday data","data provided","learned financial","financial crisis","wall street","peertopeer lending","financial service","dow jone","provided financial","financial information","volume open","open low","low ratio","ratio div","div yield","yield market","market cap"],"m_TriGrams":["learned financial crisis","data provided financial","provided financial information","volume open low","open low ratio","low ratio div","ratio div yield","div yield market","yield market cap"],"m_SocialTags":[],"m_Topics":[],"m_Industry":[],"m_Technology":[],"m_BiCnt":[5,4,4,3,3,3,3,3,3,3,3,3,3,3,3,3,3,3],"m_TriCnt":[3,3,3,3,3,3,3,3,3],"m_iDocBodyWordCnt":735}
