{"m_szDocID":"116099","m_szDocTitle":"The unique risks of ‘sharing economy’ companies - MarketWatch","m_szYear":"2014","m_szDocSumamry":"Latest News Dow 16,454 +257.42 +1.59% Nasdaq 4,534 +98.11 +2.21% S&P 500 1,927 +31.24 +1.65% 10:48 P.M. ET Aston Martin teams with China’s LeEco to build electric car 10:34 P.M. ET Updated Obama to visit Cuba in March 10:22 P.M. ET Asian markets rise, riding wave of U.S. gains 9:54 P.M. ET China's consumer inflation sped up in January 8:47 P.M. ET Spain raids China’s ICBC offices in money-laundering probe 8:36 P.M. ET Pope Francis issues emotional plea for migrants on U.S. border 7:45 P.M. ET Japanese exports plunge 13% in January 7:43 P.M. ET Fed’s Bullard speaks against further interest-rate","m_szDocBody":"latest new dow nasdaq s&p aston martin team chinas leeco build electric car updated obama visit cuba asian market rise riding wave gain chinas consumer inflation sped spain raid chinas icbc office moneylaundering probe pope francis issue emotional plea migrant border japanese export plunge fed bullard speak interestrate hike updated nikki haley endorse marco rubio president ceo apple fight fbi encryption yahoo close digital magazine burbank office turkish leader cancel migration meeting deadly bombing fbi wanted apple government collect student debt updated apple escalate war silicon valley barrick gold post big loss impairment charge updated havent learned financial crisis marathon oil post annual loss year nvidia profit rose revenue exceeded guidance william swing unexpected loss netapp cut worker amid earning decline log home new viewer video radio podcast game portfolio marketwatch new viewer market market stream east emerging market asia canada column market snapshot mover shaker currency future mover premarket new tool earning wall market overview ipo calendar earning calendar currency tool future contract market screener hulbert interactive investing stock mutual fund etf option bond commodity currency future hedge trade started marketwatch adviser column option trader revolution investing tool stock screener fund finder etf screener option screener ipo calendar earning calendar more trading deck personal finance big spender real estate spending saving taxe column moneyologist brett arend bill bischoff amy hoak chuck jaffe jennifer openshaw jennifer water tool fund finder today rate retirement retirementor encore taxe retire here howto guide social security estate planning event column robert powell retirement portfolio andrea coombess working retirement tool retirement planner long money last economy federal reserve capitol report economic report column darrell delamaide irwin kellner rex nutting tool economic calendar real estate location scout realtorcom marketwatch portfolio watchlist alert game log home investing stock david weidner writing wall alert unique risk sharing economy company david weidner published share opinion airbnb uber face business regulatory hurdle davidweidner columnist getty image airbnb website displayed laptop san francisco marketwatch investor digesting wave offering silicon valley socalled sharing economy company homesharing service airbnb inc ridesharing service uber technology inc nearing late stage startup youth wont long hit public market grown wave debate validity legality company participate what collaborative economy official including york state attorney general eric schneiderman question slick technologydisguised attempt circumvent regulation uber all operate highly regulated world taxi limousine service airbnb hotel lodging industry investor fundamental question company deserve lofty valuation assigned marketplace malibu top list recalled car uber reportedly talk round funding company billion airbnb completed round funding valued similar level coming them including loan service lending club billion sharingeconomy company pose significant problem investor traditional fundamental revenue earning growth assign businesse reflect full potential potential pitfall unique critical question friction company creating rub traditional guard overused silicon valley term sharingeconomy company potential disruptive instance carsharing vehicle road reduce number vehicle people revenue loss average auto maker report jeremiah owyang consultant researcher altimeter partner addition car sharing vast impact auto loan car insurance fuel auto part industry owyang say traditional company ahead even sharing wave toyota motor corp experimenting sharing programme car lot outdoor clothing company patagonia worked online sharing marketplace called yerdle investor shift stark tremendous growth potential sharing company time equally enormous potential loss company wedded traditional model that course regulatory question arise sharing company offer greater and desire global good drive sharingeconomy customer regulatory safeguard built traditional system way sharing economy struggle issue facing bitcoin cryptocurrency criticised facilitation money laundering criminal activity lack safety buyer currency sharing businesse growing pain fatal flaw ultimately sharing economy easeofuse proposition consumer win out technology drive commercial change investor dotcom bust timing critical company uber airbnb critical stage prove untested business model navigate existing business regulatory structure amazoncom amzn webvan winner loser entrant border walmart store inc wmt traditional company adapt can clarity sharing model work dont investor shouldnt read valuation theyre seeing uber worth billion transform industry expand service run regulatory ditch ride over marketwatch big investor betting housing climate science hoax big oil gop god doomandgloomer totally wrong marketwatch quote reference amzn wmt new marketwatch top storey trending recommended havent learned financial crisis here speculation china massselling treasury true indicator suggest week stockmarket rally wont ted cruz overtake donald trump nationally latest republican presidential poll pope francis issue emotional plea migrant border data provided today interest rate mortgage equity saving auto credit card fixed jumbo fixed fixed fixed fixed refi fixed refi arm arm refi national average bankratecom heloc heloc heloc heloc home equity loan home equity loan home equity loan home equity loan national average bankratecom mma mma mma saving mma saving jumbo national average bankratecom car car car car car car auto refi auto refi national average bankratecom avg week month low interest business student balance transfer airline cash back reward instant approval bad credit source creditcardscom david weidner david weidner cover wall street marketwatch follow marketwatch partner centre david weidner david weidner cover wall street marketwatch follow hear join conversation comment economy politic learned financial crisis sponsored barron trouble timing market mansion global julia robert cut price kauai beach home million personal finance ceo explain apple defiance court order sponsored headline marketwatch index topic feedback newsroom roster media archive premium product mobile company company info code conduct correction advertising media kit advertise locally licence broker centre choice dow jone network wsjcom barron online bigchart virtual stock exchange financial new online wsjcom small business realtorcom mansion global back top copyright marketwatch inc right reserved agree term service privacy policy cookie policy intraday data provided financial information subject term use historical current endofday data provided financial information intraday data delayed exchange requirement jone indice dow jone company inc quote local exchange time real time sale data provided nasdaq information nasdaq traded symbol current financial status intraday data delayed minute nasdaq minute exchange jone indice dow jone company inc sehk intraday data provided financial information minute delayed quote local exchange time advanced toyota motor corp adr nyse volume open low ratio div yield market cap amazoncom inc nasdaq amzn volume open low ratio div yield market cap walmart store inc nyse wmt volume open low ratio div yield market cap latestnew","m_szGeo1":"United States","m_szSourceType":"source_investments","m_szSrcUrl":"http://www.marketwatch.com/story/the-unique-risks-of-sharing-economy-companies-2014-05-23","m_Places":["China","Leeco","Cuba","United States","Spain","Bullard","Silicon Valley","District Of Columbia","Take","Europe","Middle East","Asia","Canada","Hulbert","New York State","Malibu","Wall Street","Mobile"],"m_People":["Nikki Haley","Marco Rubio","Brett Arends","Bill Bischoff","Amy Hoak","Chuck Jaffe","Jennifer Openshaw","Robert Powell","Andrea Coombes","Darrell Delamaide","Irwin Kellner","Rex Nutting","David Weidner","Eric Schneiderman","Jeremiah Owyang","Ted Cruz","Donald Trump","Julia Roberts"],"m_Companies":["Nasdaq","Aston Martin","Google","Apple","Fbi","Yahoo","Eu","Barrick Gold","Marathon Oil","Nvidia","Williams","Netapp","Marketwatch","Shakers","Revolution","Social Security","Federal Reserve","Airbnb","Uber","Getty Images","Airbnb Inc.","Uber Technologies Inc.","Lending Club","$3.8 Billion","Toyota Motor Corp","Patagonia","May Indeed Offer","Amazon.com","Wal-mart Stores Inc.","May Indeed Be","U.s. Treasurys","Bankrate.com","Creditcards.com","Twitter","Barron's","Marketwatch, Inc.","Six Financial","Dow Jones & Company, Inc.","Amazon.com Inc"],"m_BiGrams":["david weidner","data provided","sharing economy","national average","average bankratecom","home equity","equity loan","intraday data","silicon valley","learned financial","financial crisis","loan home","dow jone","provided financial","financial information","volume open","open low","low ratio","ratio div","div yield","yield market","market cap"],"m_TriGrams":["national average bankratecom","home equity loan","learned financial crisis","equity loan home","loan home equity","data provided financial","provided financial information","volume open low","open low ratio","low ratio div","ratio div yield","div yield market","yield market cap"],"m_SocialTags":[],"m_Topics":[],"m_Industry":[],"m_Technology":[],"m_BiCnt":[],"m_TriCnt":[],"m_iDocBodyWordCnt":1017}
