{"m_szDocID":"116235","m_szDocTitle":"This bitcoin alternative is a threat to Wall Street - MarketWatch","m_szYear":"2014","m_szDocSumamry":"Latest News Dow 16,454 +257.42 +1.59% Nasdaq 4,534 +98.11 +2.21% S&P 500 1,927 +31.24 +1.65% 11:06 P.M. ET Australia job losses may signal interest-rate cut 10:48 P.M. ET Aston Martin teams with China’s LeEco to build electric car 10:34 P.M. ET Updated Obama to visit Cuba in March 10:22 P.M. ET Asian markets rise, riding wave of U.S. gains 9:54 P.M. ET China's consumer inflation sped up in January 8:47 P.M. ET Spain raids China’s ICBC offices in money-laundering probe 8:36 P.M. ET Pope Francis issues emotional plea for migrants on U.S. border 7:45 P.M. ET Japanese exports plunge 13% in January","m_szDocBody":"latest new dow nasdaq s&p australia job losse signal interestrate cut aston martin team chinas leeco build electric car updated obama visit cuba asian market rise riding wave gain chinas consumer inflation sped spain raid chinas icbc office moneylaundering probe pope francis issue emotional plea migrant border japanese export plunge fed bullard speak interestrate hike updated nikki haley endorse marco rubio president ceo apple fight fbi encryption yahoo close digital magazine burbank office turkish leader cancel migration meeting deadly bombing fbi wanted apple government collect student debt updated apple escalate war silicon valley barrick gold post big loss impairment charge updated havent learned financial crisis marathon oil post annual loss year nvidia profit rose revenue exceeded guidance william swing unexpected loss log home new viewer video radio podcast game portfolio marketwatch new viewer market market stream east emerging market asia canada column market snapshot mover shaker currency future mover premarket new tool earning wall market overview ipo calendar earning calendar currency tool future contract market screener hulbert interactive investing stock mutual fund etf option bond commodity currency future hedge trade started marketwatch adviser column option trader revolution investing tool stock screener fund finder etf screener option screener ipo calendar earning calendar more trading deck personal finance big spender real estate spending saving taxe column moneyologist brett arend bill bischoff amy hoak chuck jaffe jennifer openshaw jennifer water tool fund finder today rate retirement retirementor encore taxe retire here howto guide social security estate planning event column robert powell retirement portfolio andrea coombess working retirement tool retirement planner long money last economy federal reserve capitol report economic report column darrell delamaide irwin kellner rex nutting tool economic calendar real estate location scout realtorcom marketwatch portfolio watchlist alert game log home industry banking david weidner writing wall alert bitcoin alternative threat wall street david weidner published share peertopeer loan imperil bank cryptocurrency finish job davidweidner columnist lending club san francisco marketwatch wall street greatest threat isnt regulation meltdown weve past year government central bank enable protect status quo cost threat isnt traditional source technology socalled cryptocurrency including one bitcoin eventually dislodge power bank brokerage financial institution system digital currency circumvent fee roadblock traditional financial service possibility underdeveloped world enormous trillion asset locked global economy freed international monetary fund bigger scale centralised power institution diminish key message future money summit forwardthinking pioneer digitalcurrency space san francisco tuesday bitcoin communitybased central bank someday winner emerge bitcoin rival yetcrafted currency problem isnt happen anytime soon stuff ready prime time usable people organisation attendee bitcoin finance power project underdeveloped nation complained currency wild valuation swing lack trust and well fact enthusiast mother bitcoin cryptocurrency biggest endgame threat biggest threat distinction breed banking isnt technology focused all called peertopeer lending simply put platform people invest money lend people borrow biggest wellknown company lendingclub corp provided detail planned initial public offering raise roughly million top range lendingclub business doubled facilitated billion loan billion filing company lendingclub prosper marketplace inc connect investor borrower uber lyft connect rider driver simple platform cheque borrower credit history assign interest rate investor paid risk call want lending moneysharing whatever taking deposit making loan party transparency process word oldfashioned banking borrower rate bank investor rate return lending path rapid growth arent brickandmortar branches support arent massive overhead cost middle management pay lender operate amazoncom inc amzn better actually logistic issue lending disruptive platform challenge wall street fast business grow regulator ultimately big model survive city deciding embrace costandconvenience benefit uber lyft protect established taxi limousine industry guess antibank movement inevitable rumbling financial service corporate world cut wall street middlemen crowd funding alternative venture capital silicon valley happening isnt ironic vcs created end future hard imagine shortterm assault linked ultimate killer cryptocurrency cut bank altogether shift business company cryptocurrency space operate cooperative arent chief executive specific duty worker gather solve problem management flow chart maidsafe cryptocurrency security company noodle soup time future finance shake out but now banking displaced currency next work interact next happen mom benefit compelling doesnt choice read david weidner ferguson decision money bad worse wall street bank traded lending oil gas nuke quote reference amzn new marketwatch top storey trending recommended havent learned financial crisis here speculation china massselling treasury true indicator suggest week stockmarket rally wont ted cruz overtake donald trump nationally latest republican presidential poll pope francis issue emotional plea migrant border david weidner david weidner cover wall street marketwatch follow marketwatch partner centre david weidner david weidner cover wall street marketwatch follow hear join conversation comment economy politic learned financial crisis sponsored barron trouble timing market mansion global julia robert cut price kauai beach home million personal finance ceo explain apple defiance court order sponsored headline marketwatch index topic feedback newsroom roster media archive premium product mobile company company info code conduct correction advertising media kit advertise locally licence broker centre choice dow jone network wsjcom barron online bigchart virtual stock exchange financial new online wsjcom small business realtorcom mansion global back top copyright marketwatch inc right reserved agree term service privacy policy cookie policy intraday data provided financial information subject term use historical current endofday data provided financial information intraday data delayed exchange requirement jone indice dow jone company inc quote local exchange time real time sale data provided nasdaq information nasdaq traded symbol current financial status intraday data delayed minute nasdaq minute exchange jone indice dow jone company inc sehk intraday data provided financial information minute delayed quote local exchange time advanced amazoncom inc nasdaq amzn volume open low ratio div yield market cap latestnew","m_szGeo1":"United States","m_szSourceType":"source_investments","m_szSrcUrl":"http://www.marketwatch.com/story/this-bitcoin-alternative-is-a-threat-to-wall-street-2014-12-04","m_Places":["Australia","China","Leeco","Cuba","United States","Spain","Bullard","Silicon Valley","District Of Columbia","Take","Europe","Middle East","Asia","Canada","Hulbert","Wall Street","Mobile"],"m_People":["Nikki Haley","Marco Rubio","Brett Arends","Bill Bischoff","Amy Hoak","Chuck Jaffe","Jennifer Openshaw","Robert Powell","Andrea Coombes","Darrell Delamaide","Irwin Kellner","Rex Nutting","David Weidner","Ted Cruz","Donald Trump","Julia Roberts"],"m_Companies":["Nasdaq","Signal","Aston Martin","Google","Apple","Fbi","Yahoo","Eu","Barrick Gold","Marathon Oil","Nvidia","Williams","Marketwatch","Shakers","Revolution","Social Security","Federal Reserve","Lending Club","Central Banks","International Monetary Fund","Central Bank","Lendingclub Corp.","Prosper Marketplace Inc.","Uber","Lyft","Path","Amazon.com Inc","Guess","U.s. Treasurys","Twitter","Barron's","Marketwatch, Inc.","Six Financial","Dow Jones & Company, Inc."],"m_BiGrams":["david weidner","wall street","intraday data","data provided","learned financial","financial crisis","dow jone","provided financial","financial information"],"m_TriGrams":["learned financial crisis","data provided financial","provided financial information"],"m_SocialTags":[],"m_Topics":[],"m_Industry":[],"m_Technology":[],"m_BiCnt":[],"m_TriCnt":[],"m_iDocBodyWordCnt":918}
