{"m_szDocID":"116352","m_szDocTitle":"Start-ups aim to change how you bank - MarketWatch","m_szYear":"2011","m_szDocSumamry":"Latest News Dow 16,454 +257.42 +1.59% Nasdaq 4,534 +98.11 +2.21% S&P 500 1,927 +31.24 +1.65% 11:06 P.M. ET Australia job losses may signal interest-rate cut 10:48 P.M. ET Aston Martin teams with China’s LeEco to build electric car 10:34 P.M. ET Updated Obama to visit Cuba in March 10:22 P.M. ET Asian markets rise, riding wave of U.S. gains 9:54 P.M. ET China's consumer inflation sped up in January 8:47 P.M. ET Spain raids China’s ICBC offices in money-laundering probe 8:36 P.M. ET Pope Francis issues emotional plea for migrants on U.S. border 7:45 P.M. ET Japanese exports plunge 13% in January","m_szDocBody":"latest new dow nasdaq s&p australia job losse signal interestrate cut aston martin team chinas leeco build electric car updated obama visit cuba asian market rise riding wave gain chinas consumer inflation sped spain raid chinas icbc office moneylaundering probe pope francis issue emotional plea migrant border japanese export plunge fed bullard speak interestrate hike updated nikki haley endorse marco rubio president ceo apple fight fbi encryption yahoo close digital magazine burbank office turkish leader cancel migration meeting deadly bombing fbi wanted apple government collect student debt updated apple escalate war silicon valley barrick gold post big loss impairment charge updated havent learned financial crisis marathon oil post annual loss year nvidia profit rose revenue exceeded guidance william swing unexpected loss log home new viewer video radio podcast game portfolio marketwatch new viewer market market stream east emerging market asia canada column market snapshot mover shaker currency future mover premarket new tool earning wall market overview ipo calendar earning calendar currency tool future contract market screener hulbert interactive investing stock mutual fund etf option bond commodity currency future hedge trade started marketwatch adviser column option trader revolution investing tool stock screener fund finder etf screener option screener ipo calendar earning calendar more trading deck personal finance big spender real estate spending saving taxe column moneyologist brett arend bill bischoff amy hoak chuck jaffe jennifer openshaw jennifer water tool fund finder today rate retirement retirementor encore taxe retire here howto guide social security estate planning event column robert powell retirement portfolio andrea coombess working retirement tool retirement planner long money last economy federal reserve capitol report economic report column darrell delamaide irwin kellner rex nutting tool economic calendar real estate location scout realtorcom marketwatch portfolio watchlist alert game log home personal finance spending saving startup aim change bank kim hjelmgaard published share financial firm offer way exchange save borrow money kimhjelmgaard reuter show selection euro bank note swiss franc note london marketwatch informal exchange club transferwise cofounder taavet hinrikus describe early day londonbased moneychanging startup cofounded january hinrikus who business partner kristo kaarmann estonian moved year ago advocate call consumer finance referred bank traditional consumer banking ripped player hinrikus employee internettelephony firm skype creditcard purchase internet example people suspicious putting card number called browser said transferwise peertopeer currency exchange internet similar phase transferwise transferwise currencyexchange service grew specific moneychanging cofounder broadly defined consumer finance formulated hinrikus other growing category financial service purely online inclined collaboration strive transparency alter financialservice universe current buzzword parlance technology startup los angele moscow consumer finance disruptive seek fill consumer need but technologydriven enterprise equally behaviorshifting possibility afforded innovation transferwise hinrikus kaarmann started paid estonia living london continuing pay rent apartment baltic state disrupt what more developed founder specific domestic circumstance hated fact time transferred money back estonia bank losing transfer hinrikus transferred pound pay example transaction fee bank charge form completely hidden exchange rate estonian londonliving friend faced similar regular crossborder frustration thought this hinrikus marketwatch currency tool current midmarket foreignexchange rate here with example kaarmann needed send fund london back home pay estonian rent hinrikus wanted move money order draw estonianpaid salary kaarmann transfer set amount london account hinrikuss london account hinrikus turn transfer fund bank estonia kaarmann account estonia midmarket exchange rate reuter instance determine fair exchange rate hinrikus said paid made rent felt ripped off today informal exchange club blossomed potentially marketchanging proposition monthly transaction volume approaching million october transferwise grew month month customer repeat hinrikus transferwise saved user approximately starting close year ago financial service meet social media financial service increasingly social consumer share financial information risk stacey delo report finovate banking service meet technology small print straightforward transferwise charge flat fee transaction vow conduct exchange midmarket exchange rate arrange midmarket rate essentially wholesale rate retail rate found bank broker airport exchange booth like hinrikus guarantee specific rate midmarket exchange rate time transaction through service require user hold bank account territory exchange money peertopeer element concept arguably interesting restrictive further transferwise limited transaction moving euros pound this limit transfer early amount raised regionalize service point hinrikus concede dollar component website year larger point consumer simply dont ripped currency transaction airport bank make transfer hinrikus said people basic transaction good service paul dimambro british independent financialservice company hargreave lansdown operate currency service reality bank charge wide spread said straight comparison total cost excluding important variable early midday london time exchange transferwise cost rate published midmarket rate pound euro taavet hinrikus right kristo kaarmann estonian cofounder londonbased currency service transferwise midmarket rate confirmed currency websiteon reuterss currency marketwatch currency tool hargreave lansdown cost rate pound euro dimambro hsbc holding plc hbc charge fee offer rate pound euro fee barclay plc bcs currency service offered rate travelex run popular currency exchange service airport world offering pound euro website early november similar time day differential midmarket rate transferwise lowest sell rate offered period question barclayss approximately recently transferwise introduce tiered fee structure financial service crossroad capacity disruption financialservice arena limited currency exchange either wonga example onlineonly british microlender transforming credit market fully automated provider consumer credit john moorwood wongas communication director company set prove make lending decision using put cold public data relying bank manager lender callcenter representative wonga ask prospective borrower piece information algorithm matches publicly available including data held uks main credit bureaus moorwood detail algorithm didnt wonga perform credit cheque part application process wonga wonga loan repaid immediately borrower track account website phone however differentiate wonga model conventional bank lender make small shortterm loan charging set interest rate day firsttime applicant initial borrowing limit average loan period day moorwood said maximum loan period day app wongas homepage consist slider potential customer lockstep repayment commitment based duration amount marketing brochure wonga disrupting uks billion consumer credit market moorwood people wonga made million loan cost fully transparent quick dont fully control traditional lender devising financial service customer lender moorwood said youre traditional lending environment around said basic difference trick said total flexibility still areas wonga concept drawn criticism moorwood said interest rate run thousand annual percentage rate basis traditional metric assessing affordable loan moorwood model simply isnt good assessing wongas business model misleading measure applied small shortterm loan respect though wonga loan resemble paydaytype loan borrower exchange postdated cheque small cash advance earlier year wongas founder errol damelin won uks ernst young entrepreneur year award ecommerce category argument solve common problem good way way youre well moorwood parent bank portland orebased simple launched limited form month firm fall consumer finance rubric joshua reich simple chief executive wrote post financial service designed replace bank week added simple replace bank bank replaced week simple name previously travelled banksimple marketwatch reuter economy shrank fourth quarter good new simple representation aspire release constraint industry desperate innovation reich said statement linkedin simple finance technology corp parent company simple founder frustrated current banking relationship modern technology free legacy system provide customer simpler experience lower cost simple aim put customer service heart doe including range fee penalty automating saving goal cofounded employee twitter good irreverent world social internet colliding prescribed financial realm demo website simple ask money safely spend now afford phone shoe eating out watch video demo simple writing american banker bankthink recently brett king book bank said bank longer place banking contextual measured term utility easily bank product service accomplish task shopping travelling buying car home bank insist physicality risk irrelevant customer longer cherish traditional processe king run strategy financialservice consultancy developing movenbank create thirdgeneration banking experience announcing online bank alpha testing website month king told web technology blog reboot banking movenbank combine aspect financialservice provider customerfocused tech startup integrating mobile online engagement social media gamification kind customer experience banking product emailed comment king thirdgeneration banking link traditional vestige banking branches application form plastic movenbank banking completely reimagined behave nearterm bank everyday king added bank way return culture smalltown bank turn century strong social connexion customer strong service culture service connexion digital facetoface one patrick cox head agora financial breakthrough technology alert newsletter wrote recently client that moving rapidly developing electronic infrastructure enable brandnew form banking cox said wont detail banking function now however warn shouldnt surprised completely transformed financial institution occupier wall street london oakland note marketwatch quote reference hbc bcs new marketwatch top storey trending recommended havent learned financial crisis here speculation china massselling treasury true indicator suggest week stockmarket rally wont ted cruz overtake donald trump nationally latest republican presidential poll pope francis issue emotional plea migrant border powered provided bankrate compile rate data financial institution bankrate paid financial institution user display advertisement rate table listing enhanced feature logos navigation link toll free number dow jone receive share revenue user paid placement newsfrom partner altfi rebranding personal loan evenfinancialcom credit card moving endangered specy list evenfinancialcom bank false sense security evenfinancialcom ditch stock earn return marketplace lender evenfinancialcom top money market cds saving account smartassetcom data provided today interest rate mortgage equity saving auto credit card fixed jumbo fixed fixed fixed fixed refi fixed refi arm arm refi national average bankratecom heloc heloc heloc heloc home equity loan home equity loan home equity loan home equity loan national average bankratecom mma mma mma saving mma saving jumbo national average bankratecom car car car car car car auto refi auto refi national average bankratecom avg week month low interest business student balance transfer airline cash back reward instant approval bad credit source creditcardscom marketwatch partner centre hear join conversation comment economy politic learned financial crisis sponsored barron trouble timing market mansion global julia robert cut price kauai beach home million personal finance ceo explain apple defiance court order sponsored headline marketwatch index topic feedback newsroom roster media archive premium product mobile company company info code conduct correction advertising media kit advertise locally licence broker centre choice dow jone network wsjcom barron online bigchart virtual stock exchange financial new online wsjcom small business realtorcom mansion global back top copyright marketwatch inc right reserved agree term service privacy policy cookie policy intraday data provided financial information subject term use historical current endofday data provided financial information intraday data delayed exchange requirement jone indice dow jone company inc quote local exchange time real time sale data provided nasdaq information nasdaq traded symbol current financial status intraday data delayed minute nasdaq minute exchange jone indice dow jone company inc sehk intraday data provided financial information minute delayed quote local exchange time advanced hudson bay canada toronto hbc volume open low ratio div yield market cap barclay plc adr nyse bcs volume open low ratio div yield market cap latestnew","m_szGeo1":"United States","m_szSourceType":"source_investments","m_szSrcUrl":"http://www.marketwatch.com/story/start-ups-aim-to-change-how-you-bank-2011-11-14","m_Places":["Australia","China","Leeco","Cuba","United States","Spain","Bullard","Silicon Valley","District Of Columbia","Take","Europe","Middle East","Asia","Canada","Hulbert","London","U.k.","Los Angeles","Moscow","Estonia","Portland, Ore.","Best","Mobile","Wall Street","Oakland","Toronto"],"m_People":["Nikki Haley","Marco Rubio","Brett Arends","Bill Bischoff","Amy Hoak","Chuck Jaffe","Jennifer Openshaw","Robert Powell","Andrea Coombes","Darrell Delamaide","Irwin Kellner","Rex Nutting","Kim Hjelmgaard","Kristo Kaarmann","Stacey Delo","Paul Dimambro","John Moorwood","Errol Damelin","Joshua Reich","Brett King","Ted Cruz","Donald Trump","Julia Roberts"],"m_Companies":["Nasdaq","Signal","Aston Martin","Google","Apple","Fbi","Yahoo","Eu","Barrick Gold","Marathon Oil","Nvidia","Williams","Marketwatch","Shakers","Revolution","Social Security","Federal Reserve","Ups","Reuters","Transferwise","Skype","Facebook","Booths","Hsbc Holdings Plc","Barclays Plc","Travelex","Barclays","Ernst & Young","Linkedin","Simple Finance Technology Corp.","Twitter","American Banker","Agora","U.s. Treasurys","Bankrate.com","Creditcards.com","Barron's","Marketwatch, Inc.","Six Financial","Dow Jones & Company, Inc.","Hudson's Bay Co"],"m_BiGrams":["financial service","exchange rate","data provided","consumer finance","financial information","midmarket rate","pound euro","dow jone","national average","average bankratecom","home equity","equity loan","intraday data","learned financial","financial crisis","currency tool","personal finance","currency exchange","midmarket exchange","currency service","rate pound","interest rate","moorwood said","financial institution","loan home","provided financial"],"m_TriGrams":["national average bankratecom","home equity loan","learned financial crisis","rate pound euro","equity loan home","loan home equity","data provided financial","provided financial information"],"m_SocialTags":[],"m_Topics":[],"m_Industry":[],"m_Technology":[],"m_BiCnt":[],"m_TriCnt":[],"m_iDocBodyWordCnt":1746}
