{"m_szDocID":"116436","m_szDocTitle":"When you should hold cash in your brokerage account - MarketWatch","m_szYear":"2015","m_szDocSumamry":"Latest News Dow 16,454 +257.42 +1.59% Nasdaq 4,534 +98.11 +2.21% S&P 500 1,927 +31.24 +1.65% 11:06 P.M. ET Australia job losses may signal interest-rate cut 10:48 P.M. ET Aston Martin teams with China’s LeEco to build electric car 10:34 P.M. ET Updated Obama to visit Cuba in March 10:22 P.M. ET Asian markets rise, riding wave of U.S. gains 9:54 P.M. ET China's consumer inflation sped up in January 8:47 P.M. ET Spain raids China’s ICBC offices in money-laundering probe 8:36 P.M. ET Pope Francis issues emotional plea for migrants on U.S. border 7:45 P.M. ET Japanese exports plunge 13% in January","m_szDocBody":"latest new dow nasdaq s&p australia job losse signal interestrate cut aston martin team chinas leeco build electric car updated obama visit cuba asian market rise riding wave gain chinas consumer inflation sped spain raid chinas icbc office moneylaundering probe pope francis issue emotional plea migrant border japanese export plunge fed bullard speak interestrate hike updated nikki haley endorse marco rubio president ceo apple fight fbi encryption yahoo close digital magazine burbank office turkish leader cancel migration meeting deadly bombing fbi wanted apple government collect student debt updated apple escalate war silicon valley barrick gold post big loss impairment charge updated havent learned financial crisis marathon oil post annual loss year nvidia profit rose revenue exceeded guidance william swing unexpected loss log home new viewer video radio podcast game portfolio marketwatch new viewer market market stream east emerging market asia canada column market snapshot mover shaker currency future mover premarket new tool earning wall market overview ipo calendar earning calendar currency tool future contract market screener hulbert interactive investing stock mutual fund etf option bond commodity currency future hedge trade started marketwatch adviser column option trader revolution investing tool stock screener fund finder etf screener option screener ipo calendar earning calendar more trading deck personal finance big spender real estate spending saving taxe column moneyologist brett arend bill bischoff amy hoak chuck jaffe jennifer openshaw jennifer water tool fund finder today rate retirement retirementor encore taxe retire here howto guide social security estate planning event column robert powell retirement portfolio andrea coombess working retirement tool retirement planner long money last economy federal reserve capitol report economic report column darrell delamaide irwin kellner rex nutting tool economic calendar real estate location scout realtorcom marketwatch portfolio watchlist alert game log home investing hold cash brokerage account cullen roche published share holding cash cost investor huge sum evidence doesnt support cullenroche shutterstockcom fight broke recent day result charle schwab entrance socalled roboadvisory business schwab schw unveiled product virtually identical roboadvisory firm including betterment wealthfront big difference schwab service free internal fund fee schwab essentially making money underlying fund issue robos compete charge internal etf fee which dont own advisory fee basic level schwab huge competitive advantage make sense robos added fee schwab offering basic product lower cost robo youre giving money away naturally schwab product ticked robos established footing niche adam nash ceo wealthfront wrote scathing post claiming schwab merrill lynch gist schwab advertise free product hit fee back end worked merrill lynch owned bank america bac fully aware fee structure banking operation financial crisis adam hyperbolic least charle schwab merrill lynch further ironic wealthfront quick disparage false advertising company claim website generate estimated additional return passiveindexing strategy risk someone somewhere risking holding cash passiveindexing strategy definition designed capture market return beat talk false advertising showed review roboadviser performance wealthfront aggressive portfolio nearperfect replication vanguard total world stock index fund vtwsx firm charging fee version closetindexing strategy badmouthing competitor financial marketing best bigger concern raised nash cash position schwab hold account nash schwab deceptive charging holding cash cost investor huge sum gist schwab holding cash reinvest higher rate schwab called nash misleading tend agree nash yearold long time horizon hold cash forgoe gain year problem schwab platform doesnt recommend yearold hold cash fact schwab asset allocation cash nash assert schwab underhanded management cash this too misleading end holding cash end day practise sweep account standard industry practise abnormal evil schwab cash sweep account nash aware wealthfront isnt brokerdealer doesnt deal stuff sure schwab gave option eliminate cash position investor wanted big deal nash make risk someone somewhere risking holding cash firm sweeping wealthfront choose risk leave someone somewhere holding cash schwab believe small cash position make sense assetallocation component big deal schwab defended position cash good historical position platform isnt designed time interest rate rise fall that again true clear cash brokerage account doesnt physical cash generally sweep account hold treasury bill shortterm note historically cash position well cash account generated nominal average annual return obviously hasnt case recent year schwab isnt time market cash position dont unreasonable position cullen roche dont schwab platform doesnt give investor option eliminate cash position firm flexibility remove etf model portfolios wont remove cash dont bit generally people understanding cash wrong sell stock else cash position dont remove cash system exchange share anything end holding cash equivalent matter what startup raising big money china investor china pumping record amount cash technology startup paying dearly hot deal wsjs rick carew talk latest dealmaking china investor choice youd prefer hold cash remove personally bit cash hand optionality warren buffett small cash position fine youre ignore comparison cashless benchmark remain patient historically cash fine holding prefer optionality fine holding rate overall love backandforth competition work biggest player financialservice industry forced innovate compete smaller player disruption positive aggregate loser frankly dont roboadviser platform special compared vanguard account rejecting schwab robos fun watch innovation rise lowfee product filtering sophisticated investment option everyone cullen roche founder orcam financial llc financialservice firm offering assetmanagement privateadvisory institutionalconsulting educational service pragmatic capitalism investor understand money finance understanding modern monetary system marketwatch quote reference schw bac vtwsx new marketwatch top storey trending recommended havent learned financial crisis here speculation china massselling treasury true indicator suggest week stockmarket rally wont ted cruz overtake donald trump nationally latest republican presidential poll pope francis issue emotional plea migrant border data provided today interest rate mortgage equity saving auto credit card fixed jumbo fixed fixed fixed fixed refi fixed refi arm arm refi national average bankratecom heloc heloc heloc heloc home equity loan home equity loan home equity loan home equity loan national average bankratecom mma mma mma saving mma saving jumbo national average bankratecom car car car car car car auto refi auto refi national average bankratecom avg week month low interest business student balance transfer airline cash back reward instant approval bad credit source creditcardscom marketwatch partner centre hear join conversation comment economy politic learned financial crisis sponsored barron trouble timing market mansion global julia robert cut price kauai beach home million personal finance ceo explain apple defiance court order sponsored headline marketwatch index topic feedback newsroom roster media archive premium product mobile company company info code conduct correction advertising media kit advertise locally licence broker centre choice dow jone network wsjcom barron online bigchart virtual stock exchange financial new online wsjcom small business realtorcom mansion global back top copyright marketwatch inc right reserved agree term service privacy policy cookie policy intraday data provided financial information subject term use historical current endofday data provided financial information intraday data delayed exchange requirement jone indice dow jone company inc quote local exchange time real time sale data provided nasdaq information nasdaq traded symbol current financial status intraday data delayed minute nasdaq minute exchange jone indice dow jone company inc sehk intraday data provided financial information minute delayed quote local exchange time advanced charle schwab corp nyse schw volume open low ratio div yield market cap bank america corp nyse bac volume open low ratio div yield market cap vanguard total world stock index fundinvestor mutual fund vtwsx volume open low ratio div yield market cap latestnew","m_szGeo1":"United States","m_szSourceType":"source_investments","m_szSrcUrl":"http://www.marketwatch.com/story/when-you-should-hold-cash-in-your-brokerage-account-2015-03-13","m_Places":["Australia","China","Leeco","Cuba","United States","Spain","Bullard","Silicon Valley","District Of Columbia","Take","Europe","Middle East","Asia","Canada","Hulbert","Mobile"],"m_People":["Nikki Haley","Marco Rubio","Brett Arends","Bill Bischoff","Amy Hoak","Chuck Jaffe","Jennifer Openshaw","Robert Powell","Andrea Coombes","Darrell Delamaide","Irwin Kellner","Rex Nutting","Cullen F Hoffmann-la Roche Ltd","Adam Nash","Rick Carew","Warren Buffett","Ted Cruz","Donald Trump","Julia Roberts"],"m_Companies":["Nasdaq","Signal","Aston Martin","Google","Apple","Fbi","Yahoo","Eu","Barrick Gold","Marathon Oil","Nvidia","Williams","Marketwatch","Shakers","Revolution","Social Security","Federal Reserve","Charles Schwab","Wealthfront","Merrill Lynch","Bank Of America","Vanguard","Treasury","Orcam Financial Group Llc","U.s. Treasurys","Bankrate.com","Creditcards.com","Barron's","Marketwatch, Inc.","Six Financial","Dow Jones & Company, Inc.","Charles Schwab Corp.","Bank Of America Corp."],"m_BiGrams":["holding cash","cash position","data provided","financial crisis","hold cash","national average","average bankratecom","home equity","equity loan","intraday data","learned financial","cullen roche","charle schwab","merrill lynch","someone somewhere","sweep account","loan home","dow jone","provided financial","financial information","volume open","open low","low ratio","ratio div","div yield","yield market","market cap"],"m_TriGrams":["national average bankratecom","home equity loan","learned financial crisis","equity loan home","loan home equity","data provided financial","provided financial information","volume open low","open low ratio","low ratio div","ratio div yield","div yield market","yield market cap"],"m_SocialTags":[],"m_Topics":[],"m_Industry":[],"m_Technology":[],"m_BiCnt":[],"m_TriCnt":[],"m_iDocBodyWordCnt":1184}
