{"m_szDocID":"123377","m_szDocTitle":"Calorimeters | Compare, Review, Quotes (RFQ) from Calorimeters Manufacturers, Suppliers","m_szYear":"2016","m_szDocSumamry":"Home Home Articles News Directory Equipment Software Market Reports Experts Books Journals Blogs Podcasts Videos Events Courses News 3D Printing Adhesives and Sealants Aerospace Materials Aluminum / Aluminium Automotive Materials Biomaterials Building and Construction Business Ceramic Materials Chemistry Clean Technology Coatings and Thin Films Composites Control Systems Corrosion Crystallography Design and Innovation Electronics Energy Events Ferrous Alloys and Metals Fibers Fuel Cell Graphene Iron and Steel Materials Analysis Materials Processing Materials Research Materials Science Material","m_szDocBody":"home home article new directory equipment software market report expert book journal blog podcast videos event course new printing adhesive sealant aerospace material aluminium aluminium automotive material biomaterial building construction business ceramic material chemistry clean technology coating thin film composite control system corrosion crystallography design innovation electronic energy event ferrous alloy metal fibre fuel cell graphene iron steel material analysis material processing material research material science material testing mineral mining modelling simulation nanomaterial nanotechnology product nonferrous alloy metal packaging petrochemical photonic photovoltaic pittcon plastic polymer precious metal rubber elastomer semiconductor sustainable technology titanium tribology article latest article thought leader insight industry azojomo material material supplier application industry metal store equipment chemical analysis atomic absorption spectrometer aas atomic optical emission spectrometer oes benchtop nmr spectrometer electrochemical analysis electron paramagnetic resonance epr spectrometer elemental analyzer ftir accessory ftir spectrophotometer ftnir fourier transform spectrometer fuel lubricant testing gas analyzer gas chromatography gel permeation chromatography handheld raman analyzer handheld xrf analyzer ion chromatography liquid chromatography mass spectrometer nmr spectroscopy analyzer pharmaceutical analysis equipment raman spectrometer secondary ion mass spectrometry sim spectrometer spectroscopy accessory titrator vapour pressure measurement xray gamma ray detector xray diffractometer xray fluorescence analyzer xray optic xray photoelectron spectroscopy xps xrf spectrometer coating deposition atomic layer deposition system thermal evaporation equipment thin film deposition system coating testing adhesion tester coating thickness gauge coating film deposition consumable eddy current tester ellipsometer glossmeter thin film characterization system electrical property electrical property characterization equipment hall effect measurement system scanning kelvin probe seebeck coefficient measurement system vibrating sample magnetometer vsm zeta potential analyzer equipment testing calibration battery testing solar cell testing fixing fastener bonding fastener flow controller metre field flow fractionation equipment heat treatment ageing oven industrial furnace oven laboratory furnace kiln vacuum furnace laboratory process equipment controlled atmosphere processing environment cryogenic evaporator concentrator laboratory gas generator laboratory heating cooling apparatus laboratory testing sample preparation equipment laboratory water purification system mixer shaker pcb smt handling workstation scientific illumination light source vacuum pump material processing manufacturing printing equipment material accessory boring machine mill particle size reduction plastic processing equipment ultrasonic welding equipment mechanical testing automatic material testing machine biomaterial testing equipment brittleness tester civil engineering material testing equipment cutter grinder polisher drop weight testing machine durometer fatigue testing machine force gauge gauge hardness testing machine impact testing machine material characterization equipment pipe burst hydrostatic tester plastic rubber testing equipment portable hardness tester scratch tester tensile testing machine torque gauge gauge tribometer friction wear tester universal material testing machine microscope acoustic microscope atom probe atomic force microscope afm electron beam source fibre analyzer ion beam microscope metallurgical microscope microscopy accessory consumable optical microscope polarising microscope raman microscope sample preparation equipment scanning electrochemical microscope secm scanning electron microscope sem scanning probe microscope scanning transmission electron microscope stem stereo microscope transmission electron microscope tem nondestructive testing ndt coating thickness gauge gas analyzer handheld xrf analyzer laser micrometre measurement nondestructive testing ndt equipment portable hardness tester scientific cameras sheet board counter ultrasonic flaw detector xray scattering system saxs waxs optical inspection acoustic microscope borescope ccd cameras colorimeter electron multiplying charge coupled device emccd ellipsometer monochromator optical comparator optical noncontact profiler measurement polarimeter polariscope refractometer scientific cameras oven furnace kiln ageing oven industrial furnace oven laboratory furnace kiln physical property testing adhesion tester analytical test sieve borescope chemisorption analyzer civil engineering material testing equipment density metre diffusivity tester dynamic vapour sorption dvs environmental test chamber extensometer extruded profile measurement system ferrography flexometer goodrich flexometer fogging tester gas pycnometer gas solubility analyzer glossmeter laser micrometre measurement light scattering instrument melt flow index tester metal testing equipment moisture analyzer optical noncontact profiler measurement particle counter particle size analyzer permeameter pharmaceutical analysis equipment plasma processing equipment pore size analyzer profilometer pycnometer rheometer metrology tool sheet board counter shock vibration test system spectrophotometer surface area analyzer surface energy gas chromatograph thickness gauge gauge vapour sorption analyzer viscometer wafer mapping system water sorption analyzer zeta potential analyzer plasma processing plasma diagnostic tool plasma processing equipment process control extruded profile measurement system flow controller metre lubricant condition monitor process control system radiation detector testing geiger counter liquid scintillation counter multichannel analyzer proportional counter radio chemistry sensor detector data logger control system controller data logger gas detector level sensor moisture sensor temperature sensor thermocouple thermal analysis calorimeter differential scanning calorimeter dsc dilatometer flash analysis lfa melting point metre peltier thermostat temperature measurement equipment temperature retraction tester thermal analysis equipment thermal conductivity system thermomechanical analyzer tma product software market report book alloy aluminium asm handbook biomaterial ceramic chemical engineering chemistry clean technology coating composite condensed matter conference proceeding copper corrosion design elastomer electronic engineering fluid fuel cell glass glaze heat treatment instrumentation iron magnetism material processing material science material testing measurement science mechanic mem metallurgy metal microscopy nanotechnology optic photonic cell physic plastic polymer semiconductor soft matter spectroscopy steel thermodynamic thermoplastic titanium welding journal biomaterial ceramic material chemistry coating thin film composite corrosion crystallography energy material processing material science metal alloy mineral nanotechnology polymer solgel videos adhesive bonding axaa conference biomaterial carbon fibre future direction interview ceramic material coating composite material corrosion emc manchester ferrous alloy functional material gas chromatography graphene hard material temperature material iconn interview light alloy m&m phoenix arizona usa machining mass spectrometry material austceram material processing material science technology mst material science technology mst material testing characterisation metal casting foundry mrs fall meeting video interview mrs fall meeting mrs fall meeting mrs fall meeting video interview nanomaterial nonferrous alloy pittcon interview pittcon interview pittcon interview pittcon pittcon precious metal recycled sustainable material rubber elastomer spectrometer stainless steel structural material thermoplastic thermosetting polymer welding brazing course course event contact meet team term advertise browse bymaterialsapplicationsindustry advertise term equipment thermal analysis calorimeter calorimeter calorimeter instrument measuring calorimetry science measuring heat chemical reaction physical change calorimeter defined type reaction calorimeter heat flow calorimeter heat balance calorimeter bomb calorimeter constantpressure calorimeter differential scanning calorimeter isothermal titration calorimeter xray microcalorimeter heatloss calorimeter highenergy particle calorimeter request quote calorimeter source quotation calorimeter here submitted place contact suitable calorimeter supplier hour featured equipment measuring heat flux convection radiation temperature combustion gase model model flame intensity calorimeter probe iti measuring heat flux convection radiation temperature combustion gase watercooled instrument directly immersed flame front read quote model thermoelectric calorimeter iti iti offer sery thermal gradient microcalorimeter exclusively designed offer precise measurement radioisotope heat release rate read quote tam air microcalorimeter sensitive stable heat flow measurement instrument instrument tam air microcalorimeter specifically designed stable sensitive measurement heat flow device configured channel channel calorimeter read quote equipment tam iii multichannel isothermal microcalorimetric system instrument instrument introduced tam iii multichannel isothermal microcalorimetric system level flexibility sensitivity performance read quote measuring intramolecular stability structured macromolecule microcal vpdsc malvern malvern microcal vpdsc highly sensitive differential scanning calorimeter designed studying sample solution read quote dsc pegasus hightemperature dsc differential scanning calorimeter netzsch dsc pegasus hightemperature differential scanning calorimeter designed exact determination specific heat highperformance material temperature concept dsc pegasus configuration furnace type easily interchangeable user wide temperature range read quote characterising protein biomolecule stability microcal vpcapillary dsc malvern malvern instrument introduced fully automated highthroughput highsensitivity differential scanning calorimeter called microcal vpcapillary dsc read quote arsst calorimeter fauske associate complete calorimeter hazard screening vent sizing read quote cosa combustion calorimeter cosa unmatched term accuracy speed response stability measurement cosa designed application requiring continuous fast response measurement analyzer installed directly outdoor additional shelter read quote accelerating rate calorimeter netzsch netzsch accelerating rate calorimeter arc offer adiabatic calorimetry information safe controlled laboratory setting read quote coleparmer ika calorimeter system ika calorimeter system accurately determine gross calorific gcv sample liquid solid state digital display simple programming method selection unit suitable low throughput laboratory teaching training technical school university industrial laboratory analyse read quote discovery dsc differential scanning calorimeter diffusionbonded sensor instrument discovery dsc unmatched precision accuracy industryleading sensitivity resolution read quote dsc pegasus hightemperature dsc netzsch read quote dsc phoenix highpressure dsc netzsch dsc phoenix highpressure differential scanning calorimeter thermal effect sample tested based type gas atmosphere sample chamber dynamic static read quote photodsc phoenix differential scanning calorimeter curing netzsch netzsch photodsc phoenix differential scanning calorimeter work temperature range instrument gastight measuring cell purge gas control regulated mass flow controller mfc photodsc phoenix standard industry laboratory lamp cationic radically curing material system used read quote systag calo calorimeter new universal range reaction calorimeter safety investigation scaleup calorimeter calo eco base pro suitable safety investigation scaleup application read quote microcal itc malvern sensitivity measurement binding parameter malvern instrument introduced microcal itc low volume isothermal titration calorimeter analysis biomolecular interaction read quote mettlertoledo differential scanning calorimeter dsc mettler toledo thermal analysis premium excellence line differential scanning calorimeter modular design making ideal choice automatic manual operation industrial development academic research production quality assurance read quote sta jupiter simultaneous tgdsc netzsch sta jupiter combine unlimited configuration flexibility unmatched performance instrument read quote investigating biomolecular interaction microcal vpitc malvern malvern microcal vpitc highly sensitive easytouse isothermal titration calorimeter ability study biomolecular interaction read quote aptac automatic pressure tracking adiabatic calorimeter netzsch aptac take testing chemical reactivity step forward enabling acquire faster temperature pressure rise data earlier design aptac function highperformance closedcell adiabatic calorimeter hightemperature highpressure reaction calorimeter open test cell effluent discharged analysed emergency relief system study dier methodology american institute chemical engineer read quote microcal peaqitc sensitivity measurement binding parameter malvern microcal peaqitc malvern sensitivity calorimeter labelfree solution analysis biomolecular interaction read quote dsc phoenix differential scanning calorimeter netzsch versatile premium dsc phoenix fascinate unique concept essential operational component integrated instrument optional addon installed anytime site read quote semiautomatic isoperibol calorimeter leco semiautomatic isoperibol calorimeter gross calorific content set standard future calorimetry instrument semiautomated operation combined thermodynamic truspeed obtain rapid analysis calorific increased instrument throughput sacrificing accuracy instrument precision new ergonomically designed lightweight combustion vessel assure ease operation greatly reducing operator strain read quote accelerating rate calorimeter arc netzsch accelerating rate calorimeter arc designed safe accurate measurement quantity rate heat release relating processing storage chemical instrument earlier named tiax arc read quote ibc isothermal battery calorimeter netzsch thermal management battery pack isothermal battery calorimeter ibc designed examining performance safety energy storage device large lithium ion battery widely airplane electric vehicle stationary power backup storage application read quote temperature coin cell module mmc nexus netzsch offer exchangeable calorimeter module mmc nexus dedicated coin cell battery study read quote netzsch sta jupiter simultaneous thermal analysis system tgatgadsc tgadta netzsch sta jupiter simultaneous thermal analyzer combine benefit true differential scanning calorimeter sensitive thermobalance read quote mmc nexus multiple module calorimeter netzsch mmc nexus netzsch multiple module calorimeter include part base unit builtin electronic exchangeable calorimeter module read quote sponsor trending material storey shapememory polymer react body heat hold promise medical application scientist demonstrate fabrication live tissue structure customdesigned printer harm health productivity caused led flicker cannabis oil extraction interview jame white york fashion week feature revolutionary printed dresse created stratasy threeasfour epfl scientist discover determine efficiency perovskite solar cell sponsor insight industry nondestructive ultrasonic flaw testing syncscan interview cindy zheng measuring preventing flicker led interview steven goetstouwer cannabis oil extraction interview jame white latest material article characterising organic inorganic metallic particle semiconductor structural chemical analyzer sem invia raman microscope analysing silicon carbide sic nondestructive ultrasonic flaw testing syncscan interview cindy zheng preparing unmounted ferrous steel minute planarmet planar grinder preparing surface treated steel sample minute planarmet planar grinder home new article directory equipment software market report expert book journal blog podcast videos event course azomcom azonetwork owned operated azomcom limited copyright azomcom information service accordance term condition cooky continuing browse agreeing cooky here","m_szGeo1":"United Kingdom","m_szSourceType":"source_industry","m_szSrcUrl":"http://www.azom.com/materials-equipment.aspx?cat=30","m_Places":["Hall","Kilns","Boring","Surface Area","Manchester","Uk","United States","Malvern","Toledo","Printer","New York"],"m_People":["Nir Fourier","Eddy Current","Perovskite Solar","Diffusivity Tester","Systag Calo","Cindy Zheng","Steven Goetstouwers"],"m_Companies":["Plastics","Sec","Shakers","Particle","Plastic","Force Gages","Torque","Gages","Universal","Atom","Goodrich","Asm","Emc","M&m","Phoenix, Arizona","Tam","Macromolecules","Pegasus","Malvern Instruments","Fauske Associates","Phoenix","Mettler-toledo","Itc","American Institute","Nexus","Stratasys","Particles","On Semiconductors","Planar"],"m_BiGrams":["read quote","differential scanning","scanning calorimeter","material testing","testing machine","calorimeter netzsch","material processing","material science","testing equipment","thermal analysis","thin film","processing material","measurement system","quote dsc","dsc pegasus","accelerating rate","rate calorimeter","dsc phoenix","biomolecular interaction","sta jupiter","mmc nexus","software market","market report","ceramic material","control system","analysis equipment","thickness gauge","flow controller","furnace kiln","processing equipment","electron microscope","ultrasonic flaw","plasma processing","pittcon interview","interview pittcon","measuring heat","reaction calorimeter","heat flow","isothermal titration","titration calorimeter","pegasus hightemperature","calorimeter arc","photodsc phoenix","phoenix differential","interaction read","jupiter simultaneous","netzsch sta"],"m_TriGrams":["differential scanning calorimeter","read quote dsc","accelerating rate calorimeter","software market report","isothermal titration calorimeter","dsc pegasus hightemperature","rate calorimeter arc","phoenix differential scanning","biomolecular interaction read","interaction read quote","sta jupiter simultaneous","netzsch sta jupiter"],"m_SocialTags":[],"m_Topics":[],"m_Industry":[],"m_Technology":[],"m_BiCnt":[29,14,14,7,7,6,5,5,5,5,4,4,4,4,4,4,4,4,4,4,4,3,3,3,3,3,3,3,3,3,3,3,3,3,3,3,3,3,3,3,3,3,3,3,3,3,3],"m_TriCnt":[14,4,4,3,3,3,3,3,3,3,3,3],"m_iDocBodyWordCnt":1910}
