{"m_szDocID":"124485","m_szDocTitle":"Characterisation of Functional Materials on the Nanoscale Using Raman Imaging, SPM and TERS","m_szYear":"2016","m_szDocSumamry":"Home Home Articles News Directory Equipment Software Market Reports Experts Books Journals Blogs Podcasts Videos Events Courses News 3D Printing Adhesives and Sealants Aerospace Materials Aluminum / Aluminium Automotive Materials Biomaterials Building and Construction Business Ceramic Materials Chemistry Clean Technology Coatings and Thin Films Composites Control Systems Corrosion Crystallography Design and Innovation Electronics Energy Events Ferrous Alloys and Metals Fibers Fuel Cell Graphene Iron and Steel Materials Analysis Materials Processing Materials Research Materials Science Material","m_szDocBody":"home home article new directory equipment software market report expert book journal blog podcast videos event course new printing adhesive sealant aerospace material aluminium aluminium automotive material biomaterial building construction business ceramic material chemistry clean technology coating thin film composite control system corrosion crystallography design innovation electronic energy event ferrous alloy metal fibre fuel cell graphene iron steel material analysis material processing material research material science material testing mineral mining modelling simulation nanomaterial nanotechnology product nonferrous alloy metal packaging petrochemical photonic photovoltaic pittcon plastic polymer precious metal rubber elastomer semiconductor sustainable technology titanium tribology article latest article thought leader insight industry azojomo material material supplier application industry metal store equipment chemical analysis atomic absorption spectrometer aas atomic optical emission spectrometer oes benchtop nmr spectrometer electrochemical analysis electron paramagnetic resonance epr spectrometer elemental analyzer ftir accessory ftir spectrophotometer ftnir fourier transform spectrometer fuel lubricant testing gas analyzer gas chromatography gel permeation chromatography handheld raman analyzer handheld xrf analyzer ion chromatography liquid chromatography mass spectrometer nmr spectroscopy analyzer pharmaceutical analysis equipment raman spectrometer secondary ion mass spectrometry sim spectrometer spectroscopy accessory titrator vapour pressure measurement xray gamma ray detector xray diffractometer xray fluorescence analyzer xray optic xray photoelectron spectroscopy xps xrf spectrometer coating deposition atomic layer deposition system thermal evaporation equipment thin film deposition system coating testing adhesion tester coating thickness gauge coating film deposition consumable eddy current tester ellipsometer glossmeter thin film characterization system electrical property electrical property characterization equipment hall effect measurement system scanning kelvin probe seebeck coefficient measurement system vibrating sample magnetometer vsm zeta potential analyzer equipment testing calibration battery testing solar cell testing fixing fastener bonding fastener flow controller metre field flow fractionation equipment heat treatment ageing oven industrial furnace oven laboratory furnace kiln vacuum furnace laboratory process equipment controlled atmosphere processing environment cryogenic evaporator concentrator laboratory gas generator laboratory heating cooling apparatus laboratory testing sample preparation equipment laboratory water purification system mixer shaker pcb smt handling workstation scientific illumination light source vacuum pump material processing manufacturing printing equipment material accessory boring machine mill particle size reduction plastic processing equipment ultrasonic welding equipment mechanical testing automatic material testing machine biomaterial testing equipment brittleness tester civil engineering material testing equipment cutter grinder polisher drop weight testing machine durometer fatigue testing machine force gauge gauge hardness testing machine impact testing machine material characterization equipment pipe burst hydrostatic tester plastic rubber testing equipment portable hardness tester scratch tester tensile testing machine torque gauge gauge tribometer friction wear tester universal material testing machine microscope acoustic microscope atom probe atomic force microscope afm electron beam source fibre analyzer ion beam microscope metallurgical microscope microscopy accessory consumable optical microscope polarising microscope raman microscope sample preparation equipment scanning electrochemical microscope secm scanning electron microscope sem scanning probe microscope scanning transmission electron microscope stem stereo microscope transmission electron microscope tem nondestructive testing ndt coating thickness gauge gas analyzer handheld xrf analyzer laser micrometre measurement nondestructive testing ndt equipment portable hardness tester scientific cameras sheet board counter ultrasonic flaw detector xray scattering system saxs waxs optical inspection acoustic microscope borescope ccd cameras colorimeter electron multiplying charge coupled device emccd ellipsometer monochromator optical comparator optical noncontact profiler measurement polarimeter polariscope refractometer scientific cameras oven furnace kiln ageing oven industrial furnace oven laboratory furnace kiln physical property testing adhesion tester analytical test sieve borescope chemisorption analyzer civil engineering material testing equipment density metre diffusivity tester dynamic vapour sorption dvs environmental test chamber extensometer extruded profile measurement system ferrography flexometer goodrich flexometer fogging tester gas pycnometer gas solubility analyzer glossmeter laser micrometre measurement light scattering instrument melt flow index tester metal testing equipment moisture analyzer optical noncontact profiler measurement particle counter particle size analyzer permeameter pharmaceutical analysis equipment plasma processing equipment pore size analyzer profilometer pycnometer rheometer metrology tool sheet board counter shock vibration test system spectrophotometer surface area analyzer surface energy gas chromatograph thickness gauge gauge vapour sorption analyzer viscometer wafer mapping system water sorption analyzer zeta potential analyzer plasma processing plasma diagnostic tool plasma processing equipment process control extruded profile measurement system flow controller metre lubricant condition monitor process control system radiation detector testing geiger counter liquid scintillation counter multichannel analyzer proportional counter radio chemistry sensor detector data logger control system controller data logger gas detector level sensor moisture sensor temperature sensor thermocouple thermal analysis calorimeter differential scanning calorimeter dsc dilatometer flash analysis lfa melting point metre peltier thermostat temperature measurement equipment temperature retraction tester thermal analysis equipment thermal conductivity system thermomechanical analyzer tma product software market report book alloy aluminium asm handbook biomaterial ceramic chemical engineering chemistry clean technology coating composite condensed matter conference proceeding copper corrosion design elastomer electronic engineering fluid fuel cell glass glaze heat treatment instrumentation iron magnetism material processing material science material testing measurement science mechanic mem metallurgy metal microscopy nanotechnology optic photonic cell physic plastic polymer semiconductor soft matter spectroscopy steel thermodynamic thermoplastic titanium welding journal biomaterial ceramic material chemistry coating thin film composite corrosion crystallography energy material processing material science metal alloy mineral nanotechnology polymer solgel videos adhesive bonding axaa conference biomaterial carbon fibre future direction interview ceramic material coating composite material corrosion emc manchester ferrous alloy functional material gas chromatography graphene hard material temperature material iconn interview light alloy m&m phoenix arizona usa machining mass spectrometry material austceram material processing material science technology mst material science technology mst material testing characterisation metal casting foundry mrs fall meeting video interview mrs fall meeting mrs fall meeting mrs fall meeting video interview nanomaterial nonferrous alloy pittcon interview pittcon interview pittcon interview pittcon pittcon precious metal recycled sustainable material rubber elastomer spectrometer stainless steel structural material thermoplastic thermosetting polymer welding brazing course course event contact meet team term advertise browse bymaterialsapplicationsindustry advertise term sponsor trending material storey shapememory polymer react body heat hold promise medical application scientist demonstrate fabrication live tissue structure customdesigned printer harm health productivity caused led flicker cannabis oil extraction interview jame white york fashion week feature revolutionary printed dresse created stratasy threeasfour epfl scientist discover determine efficiency perovskite solar cell sponsor insight industry nondestructive ultrasonic flaw testing syncscan interview cindy zheng measuring preventing flicker led interview steven goetstouwer cannabis oil extraction interview jame white latest material article characterising organic inorganic metallic particle semiconductor structural chemical analyzer sem invia raman microscope analysing silicon carbide sic nondestructive ultrasonic flaw testing syncscan interview cindy zheng preparing unmounted ferrous steel minute planarmet planar grinder preparing surface treated steel sample minute planarmet planar grinder supplier profile supplier new supplier article request quote characterisation functional material nanoscale raman imaging spm ter sponsored renishaw raman spectroscopy table introduction characterisation sic wafer ter imaging graphene functionalised carbon nanotube conclusion introduction crucial functional material graphene silicon carbide sic comprehensively characterised green energy application for lithium ion battery inverter application automotive power control system show raman spectroscopy effective continuing development functional material flexible spatial resolutionspanning millimetre submicrometrerenishaw invia raman microscope powerful proven tool investigation electronic property chemical property homogeneity strain material characterisation sic wafer sic promising material power electronic compared siliconbased device sic device work higher temperature voltage making promising drive train electric vehicle however largescale growth sic challenging wafer inclusion polytype defect considerably affect performance final device powerful tool characterising sic raman spectroscopy capable distinguishing sic polytype quickly easily detect defect determine strain electronic property invia raman microscope renishaw proprietary technology characterise entire wafer hour resolution data point collected highlight speed increase order magnitude past year making perform raman analysis timescale needed quality control wafer show composite raman image composite raman image blue image illustrate change peak position fto raman mode directly related stress wafer hexagonal strain feature seen allowing micropipe centre dislocation detected spatial spectral resolution invia demonstrated ability image small strain feature hsic inclusion highlighted red region growth defect shown yellow inset spectra polytype sic highlight easy differentiate polytype invia raman microscope ter imaging graphene functionalised carbon nanotube tip enhanced raman spectroscopy ter integrate scanning probe microscopy spm raman measurement enable collection raman data nano scale important technique suitable studying chemical property nanomaterial make analyse material scale micro raman spectroscopy limited diffraction lateral resolution graphene carbon nanotube cnt important nanomaterial targeted application energy industry analysis ter technique applied material evaluate homogeneity figure show comparison ter afm imaging ter afm imaging graphene functionalised cnt ter red field raman spectra graphene blue result demonstrate enhancement signal provided ter ter image showing diffraction limit ratio graphene sample ratio estimate cvd graphene thickness significant ratio length scale showing graphene variation nanoscale afm image cnt cluster image size cluster determined provide chemical information bter image highlighting distribution functionalized cnt cluster red region functionalised cnt clear mixing functionalised functionalised cnt uniform cluster conclusion show renishaw advanced powerful invia raman microscope effectively determining material chemical property macroscale nanoscale show raman spectroscopy robust surface characterisation tool characterise sic wafer demonstrating ability identify defect region detect polytype evaluate stress inspect homogeneity sic wafer ter innovative technique make obtain chemical data sample nanometre resolution prove studying graphene cnt emerging carbon material information sourced reviewed adapted material provided renishaw raman spectroscopy information source visit renishaw raman spectroscopy date added updated renishaw plc article invia raman microscope analysing silicon carbide sic characterising organic inorganic metallic particle semiconductor structural chemical analyzer sem invia raman microscope analyse silicon carbide sic invia confocal raman microscope analyse graphene raman spectroscopy forensic science development raman spectroscopy inside raman interview martin davy controlling orientation edge geometry thickness chemical vapour deposition graphene raman spectroscopy carbon industry analyse diamond dlc carbon nanotube related renishaw plc new inside raman held renishaw innovation centre kwansei gakuin university hyogo japan raman microscopy study crystallographic defect silicon carbide wafer renishaw spectroscopy product division relocate company headquarter combining sem raman archaeological textile analysis ucla renishaw add raman analysis scanning electron microscopy university sydney australia renishaw raman microscope rijksmuseum conservation department renishaw paper lead workshop year microscience microscopy congress mmc renishaw raman system study material boston university renishaw bruker team workshop ter colocalised afm raman pittcon new renishaw add comprehensive imaging option invia confocal raman microscope renishaw receive queen award spectroscopy development website raman spectroscopy launched renishaw renishaw win queen award invia ultrafast raman imaging microscope rapid collection large amount raman data enabled renishaw option renishaw announce inside raman seminar manchester conference centre thth renishaw invia raman microscope helping develop large defectfree film graphene inside raman held stfc rutherford appleton laboratory site renishaw host successful raman seminar natural history museum london renishaw continue expansion china aerospace manufacturer choose renishaw axis measuring system speed production ensure quality renishaw show machine increase manufacturing performance upcoming event renishaw help achieve accuracy grinding giant wind turbine bearing renishaw open manufacturing facility laser sintered cobaltchrome detal framework ultra compact lathe inspection touch probe renishaw measuring large object degree accuracy renishaw milling machine reduce cost produce zirconia dental framework renishaw extend range machine tool testing calibration system renishaw release ballbar system renishaw inspection system lead huge time saving oil gas fully automated surface finish inspection probe option renishaw renishaw coordinate measuring machine feature improved repeatability stability axis cmm inspection system halve measurement time ultra compact accuracy touch probe cnc win renishaw prestigious award renishaw launch sery first control siemen speed cutting solution medical implant ntmdt renishaw join force nanotechnology researcher renishaw appoint leading swedish metrology industry improving machine tool accuracy design renishaw open demonstration training centre india support metrology raman client world leading measurement company open office taiwan magnetic linear encoder renishaw comment question question article cancel reply comment leave feedback logout public question private question supplier submit home new article directory equipment software market report expert book journal blog podcast videos event course azomcom azonetwork owned operated azomcom limited copyright azomcom information service accordance term condition cooky continuing browse agreeing cooky here","m_szGeo1":"United Kingdom","m_szSourceType":"source_industry","m_szSrcUrl":"http://www.azom.com/article.aspx?ArticleID=12188","m_Places":["Hall","Kilns","Boring","Surface Area","Manchester","Uk","United States","Printer","New York","Hyogo","Japan","Australia","London","China","Zirconia","India","Taiwan"],"m_People":["Nir Fourier","Renishaw Raman","Eddy Current","Perovskite Solar","Diffusivity Tester","Cindy Zheng","Steven Goetstouwers","Confocal Raman","Martin Davies","Rutherford Appleton"],"m_Companies":["Plastics","Sec","Shakers","Particle","Plastic","Force Gages","Torque","Gages","Universal","Atom","Goodrich","Asm","Emc","M&m","Phoenix, Arizona","Stratasys","Particles","On Semiconductors","Planar","Cnts","Signal","Renishaw Plc","Related Renishaw Plc","Gakuin University","University Of Sydney","Rijksmuseum","Conservation Department","Congress","Mmc","Boston University","Ters And Co","Rapid","Natural History Museum","Axis","Ge Oil And Gas","Renishaw Co","Cnc","Measurement Company"],"m_BiGrams":["raman microscope","raman spectroscopy","invia raman","material testing","testing machine","material processing","material science","testing equipment","silicon carbide","renishaw raman","thin film","control system","processing material","measurement system","functional material","carbide sic","sic wafer","carbon nanotube","inside raman","software market","market report","ceramic material","analysis equipment","thickness gauge","furnace kiln","processing equipment","electron microscope","ultrasonic flaw","plasma processing","pittcon interview","interview pittcon","imaging graphene","graphene functionalised","chemical property"],"m_TriGrams":["invia raman microscope","silicon carbide sic","software market report","renishaw raman spectroscopy","imaging graphene functionalised"],"m_SocialTags":[],"m_Topics":[],"m_Industry":[],"m_Technology":[],"m_BiCnt":[12,12,8,7,7,5,5,5,5,5,4,4,4,4,4,4,4,4,4,3,3,3,3,3,3,3,3,3,3,3,3,3,3,3],"m_TriCnt":[8,4,3,3,3],"m_iDocBodyWordCnt":1924}
