{"m_szDocID":"126294","m_szDocTitle":"BASF's Historic BMW Microcar Purchased for â‚¬26,099 in eBay Auction","m_szYear":"2016","m_szDocSumamry":"Home Home Articles News Directory Equipment Software Market Reports Experts Books Journals Blogs Podcasts Videos Events Courses News 3D Printing Adhesives and Sealants Aerospace Materials Aluminum / Aluminium Automotive Materials Biomaterials Building and Construction Business Ceramic Materials Chemistry Clean Technology Coatings and Thin Films Composites Control Systems Corrosion Crystallography Design and Innovation Electronics Energy Events Ferrous Alloys and Metals Fibers Fuel Cell Graphene Iron and Steel Materials Analysis Materials Processing Materials Research Materials Science Material","m_szDocBody":"home home article new directory equipment software market report expert book journal blog podcast videos event course new printing adhesive sealant aerospace material aluminium aluminium automotive material biomaterial building construction business ceramic material chemistry clean technology coating thin film composite control system corrosion crystallography design innovation electronic energy event ferrous alloy metal fibre fuel cell graphene iron steel material analysis material processing material research material science material testing mineral mining modelling simulation nanomaterial nanotechnology product nonferrous alloy metal packaging petrochemical photonic photovoltaic pittcon plastic polymer precious metal rubber elastomer semiconductor sustainable technology titanium tribology article latest article thought leader insight industry azojomo material material supplier application industry metal store equipment chemical analysis atomic absorption spectrometer aas atomic optical emission spectrometer oes benchtop nmr spectrometer electrochemical analysis electron paramagnetic resonance epr spectrometer elemental analyzer ftir accessory ftir spectrophotometer ftnir fourier transform spectrometer fuel lubricant testing gas analyzer gas chromatography gel permeation chromatography handheld raman analyzer handheld xrf analyzer ion chromatography liquid chromatography mass spectrometer nmr spectroscopy analyzer pharmaceutical analysis equipment raman spectrometer secondary ion mass spectrometry sim spectrometer spectroscopy accessory titrator vapour pressure measurement xray gamma ray detector xray diffractometer xray fluorescence analyzer xray optic xray photoelectron spectroscopy xps xrf spectrometer coating deposition atomic layer deposition system thermal evaporation equipment thin film deposition system coating testing adhesion tester coating thickness gauge coating film deposition consumable eddy current tester ellipsometer glossmeter thin film characterization system electrical property electrical property characterization equipment hall effect measurement system scanning kelvin probe seebeck coefficient measurement system vibrating sample magnetometer vsm zeta potential analyzer equipment testing calibration battery testing solar cell testing fixing fastener bonding fastener flow controller metre field flow fractionation equipment heat treatment ageing oven industrial furnace oven laboratory furnace kiln vacuum furnace laboratory process equipment controlled atmosphere processing environment cryogenic evaporator concentrator laboratory gas generator laboratory heating cooling apparatus laboratory testing sample preparation equipment laboratory water purification system mixer shaker pcb smt handling workstation scientific illumination light source vacuum pump material processing manufacturing printing equipment material accessory boring machine mill particle size reduction plastic processing equipment ultrasonic welding equipment mechanical testing automatic material testing machine biomaterial testing equipment brittleness tester civil engineering material testing equipment cutter grinder polisher drop weight testing machine durometer fatigue testing machine force gauge gauge hardness testing machine impact testing machine material characterization equipment pipe burst hydrostatic tester plastic rubber testing equipment portable hardness tester scratch tester tensile testing machine torque gauge gauge tribometer friction wear tester universal material testing machine microscope acoustic microscope atom probe atomic force microscope afm electron beam source fibre analyzer ion beam microscope metallurgical microscope microscopy accessory consumable optical microscope polarising microscope raman microscope sample preparation equipment scanning electrochemical microscope secm scanning electron microscope sem scanning probe microscope scanning transmission electron microscope stem stereo microscope transmission electron microscope tem nondestructive testing ndt coating thickness gauge gas analyzer handheld xrf analyzer laser micrometre measurement nondestructive testing ndt equipment portable hardness tester scientific cameras sheet board counter ultrasonic flaw detector xray scattering system saxs waxs optical inspection acoustic microscope borescope ccd cameras colorimeter electron multiplying charge coupled device emccd ellipsometer monochromator optical comparator optical noncontact profiler measurement polarimeter polariscope refractometer scientific cameras oven furnace kiln ageing oven industrial furnace oven laboratory furnace kiln physical property testing adhesion tester analytical test sieve borescope chemisorption analyzer civil engineering material testing equipment density metre diffusivity tester dynamic vapour sorption dvs environmental test chamber extensometer extruded profile measurement system ferrography flexometer goodrich flexometer fogging tester gas pycnometer gas solubility analyzer glossmeter laser micrometre measurement light scattering instrument melt flow index tester metal testing equipment moisture analyzer optical noncontact profiler measurement particle counter particle size analyzer permeameter pharmaceutical analysis equipment plasma processing equipment pore size analyzer profilometer pycnometer rheometer metrology tool sheet board counter shock vibration test system spectrophotometer surface area analyzer surface energy gas chromatograph thickness gauge gauge vapour sorption analyzer viscometer wafer mapping system water sorption analyzer zeta potential analyzer plasma processing plasma diagnostic tool plasma processing equipment process control extruded profile measurement system flow controller metre lubricant condition monitor process control system radiation detector testing geiger counter liquid scintillation counter multichannel analyzer proportional counter radio chemistry sensor detector data logger control system controller data logger gas detector level sensor moisture sensor temperature sensor thermocouple thermal analysis calorimeter differential scanning calorimeter dsc dilatometer flash analysis lfa melting point metre peltier thermostat temperature measurement equipment temperature retraction tester thermal analysis equipment thermal conductivity system thermomechanical analyzer tma product software market report book alloy aluminium asm handbook biomaterial ceramic chemical engineering chemistry clean technology coating composite condensed matter conference proceeding copper corrosion design elastomer electronic engineering fluid fuel cell glass glaze heat treatment instrumentation iron magnetism material processing material science material testing measurement science mechanic mem metallurgy metal microscopy nanotechnology optic photonic cell physic plastic polymer semiconductor soft matter spectroscopy steel thermodynamic thermoplastic titanium welding journal biomaterial ceramic material chemistry coating thin film composite corrosion crystallography energy material processing material science metal alloy mineral nanotechnology polymer solgel videos adhesive bonding axaa conference biomaterial carbon fibre future direction interview ceramic material coating composite material corrosion emc manchester ferrous alloy functional material gas chromatography graphene hard material temperature material iconn interview light alloy m&m phoenix arizona usa machining mass spectrometry material austceram material processing material science technology mst material science technology mst material testing characterisation metal casting foundry mrs fall meeting video interview mrs fall meeting mrs fall meeting mrs fall meeting video interview nanomaterial nonferrous alloy pittcon interview pittcon interview pittcon interview pittcon pittcon precious metal recycled sustainable material rubber elastomer spectrometer stainless steel structural material thermoplastic thermosetting polymer welding brazing course course event contact meet team term advertise browse bymaterialsapplicationsindustry advertise term trending material storey shapememory polymer react body heat hold promise medical application scientist demonstrate fabrication live tissue structure customdesigned printer harm health productivity caused led flicker cannabis oil extraction interview jame white york fashion week feature revolutionary printed dresse created stratasy threeasfour epfl scientist discover determine efficiency perovskite solar cell sponsor insight industry nondestructive ultrasonic flaw testing syncscan interview cindy zheng measuring preventing flicker led interview steven goetstouwer cannabis oil extraction interview jame white latest material article characterising organic inorganic metallic particle semiconductor structural chemical analyzer sem invia raman microscope analysing silicon carbide sic nondestructive ultrasonic flaw testing syncscan interview cindy zheng preparing unmounted ferrous steel minute planarmet planar grinder preparing surface treated steel sample minute planarmet planar grinder posted energy automotive material new storey related new related article supplier profile request quote basf historic bmw microcar purchased ebay auction published basf concept car mysetta handed today owner historic bmw microcar purchased ebay auction basf rounding donating entire sum child right organisation save children partnered basf project project partnership agreed creator space tour stop mumbai creator space tour cornerstone basf anniversary celebration isetta bmw classic car presented turin motor show basf purchased model classic car reinterpreting innovative basf product naming mysetta concept car sery event basf collaborate partner solution global challenge stop mumbai shanghai york paulo barcelona tour conclude ludwigshafen germany philipp appel manager corporate partnership foundation save children germany accepted cheque proceed auction today ludwigshafen basf developed measure improve clean drinking water children india happy money build communitymanaged sanitation facility indias capital delhi appel isetta bmw classic car presented turin motor show microcar affectionately nicknamed bubble car gained cult status famous fan car included elvis presley cary grant basf purchased model classic car reinterpreting innovative basf product naming mysetta concept car mysetta show car basf year appeared trade fair decided auction ebay order reach potential buyer achieve highest proceed save children elisabeth schick senior vice president communication government relation basf group bidding mysetta place winning bid firm emtec design company special connexion classic car seat interior lining car newly furnished innovative cover basf produced basf valuretm system solution special transfer coating technology unique softtouch surface flexible design option emtec design licencing partner valure technology europe michael einhaus managing director emtec design heinz einhaus managing director parent company einhaus gmbh picked mysetta today microcar twotone finish specially developed division basf coating waterborne specialeffect paint composed colour big white metallic blue bluetta basf colour designer created mysetta interior entire set equipment create drivein theatre wall including parcel shelf equipped stereo speaker video projector mysetta attentiongrabbing car ready drive registered project partner basf save children basf save children worked kenya india develop solution pressing challenge field water nutrition project carried empathic design cocreation method expert team basf basf stiftung german charitable foundation save children worked closely affected population develop approaches addressing local challenge turkana kenya team local resident established measure improve livelihood food security mumbai expert solution provide children clean drinking water participant project reported experience workshop held closing creator space tour ludwigshafen creator space basf hosting activity event world celebrate cocreate bringing ideas collaborative energy basf employee customer scientist member community addition creator space tour key element include creator space online global internet platform creator space science symposia ludwigshafen smart energy chicago food shanghai urban living information under basf basf create chemistry year portfolio range chemical plastic performance product crop protection product oil gas world leading chemical company combine economic success environmental protection social responsibility science innovation enable customer industry meet current future society product solution contribute conserving resource ensuring nutrition improving quality life summed contribution corporate purpose create chemistry sustainable future basf sale billion employee end year basf share traded stock exchange frankfurt bas london bfa zurich information basf internet related basf corporation new basf make investment strengthen global production network pigment dunlop basf partner develop breakthrough power flex technology padel bat basf expand compounding capacity engineering plastic europe paste seminar basf highlight innovative tailing management solution basf yankee stadium undertake zerowaste initiative era pinstripe bowl basf inaugurate automotive coating plant china whirlpool utilise polyurethane insulation system hfo foam blowing agent refrigerator basf automotive refinish exhibit nace car expo alpek basf enter agreement poliole eps business flat laminating line insulating panel basf basf sponsored blue ridge school student finishes fourth place national chemistry challenge basf share styrolution acquired ineos micronal pcm latent heat storage material facilitate intelligent temperature management basf undertake capacity expansion project performance material shanghai pudong basf develop relest powder pur antisticker coating basf introduce build exterior protective coating tersus colour coat linde basf intend cooperate developing onpurpose production butadiene basf announce construction plant pagbased lubricant ludwigshafen pigmented topcoat decorative industrial application basf basf begin commercial production lfp cathode material weimar germany basf switches xps production plant polymeric flame retardant merck basf increase stake innovationlab basf utilise renewable raw material performance polyamide basf electronic material sampling development facility open hillsboro basf start plant hexamoll dinch nonphthalate plasticizer ludwigshafen basf highlight sustainable solution energy cure market radtech neopentylglycol production plant built basf sinopec verbund basf emission control system combining lnt csf showcased vienna motor symposium basf basotect melamine foam commuter enjoy quieter relaxed travel montreal subway car basf named automotive new premier automotive supplier contribution excellence award winner basf expand global production network amine plant ludwigshafen ecoat conference basf expert technical paper basf invest million expand waterborne automotive coating production brazil demarchi basf highlight plastic solution chinaplas basf showcase technology product american coating conference show basf subsidiary inge enter strategic cooperation aquasource basf toda kogyo propose cathode active material basf superabsorbent polymer index basf supply versatile plastic bmw electric vehicle basf multidisciplinary research institute focuse inorganic material basf awarded gmp certification cosmetic ingredient basf introduce superabsorbent polymer unique property basf total petrochemical start furnace steam cracker facility port arthur basf present powder liquid coating paintexpo buick riviera rivision featuring basf onyx paint win ridler award basf brilliance programme launched international roofing exposition basf jointly establishes network advanced material open research basf crystal speed hardening concept win honour ulmer betontage trade fair basf invest million global r&d centre india basf expand production setup ludwigshafen performance polyamide basf corporation article infinergy technology adidas running shoe waterborne coating method benefit application comment review update add new storey cancel reply comment leave feedback logout public comment private feedback azomcom submit latest new thermo fisher scientific acquire xray diffraction provider inel expand capability material science structural characterization marke international launches sorbent tube hazardous air pollutant metalmaster furnace delivered southwest installation worldwide scott bader extend relationship infor trademark approval granted cortec biobased rust preventative biocorr popular new diamond tip boost electron gun power factor silicon drift detector edxrf elemental analyzer enable faster analysis limit detection method semiconductor testing developed efficiently accurately measure uniformity conductivity class material make smartphone display affordable researcher develop class superhydrophobic material home new article directory equipment software market report expert book journal blog podcast videos event course azomcom azonetwork owned operated azomcom limited copyright azomcom information service accordance term condition cooky continuing browse agreeing cooky here","m_szGeo1":"United Kingdom","m_szSourceType":"source_industry","m_szSrcUrl":"http://www.azom.com/news.aspx?newsID=44846","m_Places":["Hall","Kilns","Boring","Surface Area","Manchester","Uk","United States","Printer","New York","Mumbai","Mumbai, Shanghai, New York","SÃ£o Paulo","Barcelona","Germany","India","Delhi","Cary","Europe","Kenya","Chicago","Shanghai","Frankfurt","London","Zurich","China","Enter","Linde","Weimar","Hillsboro","Winner","Brazil","Toda","Ulmer"],"m_People":["Nir Fourier","Eddy Current","Perovskite Solar","Diffusivity Tester","Cindy Zheng","Steven Goetstouwers","Basf R","Philipp Appel","Elvis Presley","Elisabeth Schick","Michael Einhaus","Heinz Einhaus","Scott Bader"],"m_Companies":["Plastics","Sec","Shakers","Particle","Plastic","Force Gages","Torque","Gages","Universal","Atom","Goodrich","Asm","Emc","M&m","Phoenix, Arizona","Stratasys","Particles","On Semiconductors","Planar","Bmw","Ebay","Save The Children","Basf Group","Valure Technology","Einhaus Gmbh","Basf Stiftung","Basf Corporation","Flex Technology","Whirlpool","Ineos","Montreal Subway","Automotive News","Plastics Solutions","I3","Research Institute","Adidas","Thermo Fisher Scientific","Eu"],"m_BiGrams":["material testing","testing machine","creator space","material science","save children","material processing","testing equipment","classic car","thin film","control system","processing material","measurement system","space tour","software market","market report","ceramic material","analysis equipment","thickness gauge","furnace kiln","processing equipment","electron microscope","ultrasonic flaw","plasma processing","pittcon interview","interview pittcon","concept car","emtec design","basf expand","basf highlight"],"m_TriGrams":["creator space tour","software market report"],"m_SocialTags":[],"m_Topics":[],"m_Industry":[],"m_Technology":[],"m_BiCnt":[7,7,7,6,6,5,5,5,4,4,4,4,4,3,3,3,3,3,3,3,3,3,3,3,3,3,3,3,3],"m_TriCnt":[4,3],"m_iDocBodyWordCnt":2104}
