{"m_szDocID":"126255","m_szDocTitle":"Saint-Gobain Seals Presents Technical Paper on Cold Temperature Sealing at SAE A-5/A-6 Committee Meeting","m_szYear":"2016","m_szDocSumamry":"Home Home Articles News Directory Equipment Software Market Reports Experts Books Journals Blogs Podcasts Videos Events Courses News 3D Printing Adhesives and Sealants Aerospace Materials Aluminum / Aluminium Automotive Materials Biomaterials Building and Construction Business Ceramic Materials Chemistry Clean Technology Coatings and Thin Films Composites Control Systems Corrosion Crystallography Design and Innovation Electronics Energy Events Ferrous Alloys and Metals Fibers Fuel Cell Graphene Iron and Steel Materials Analysis Materials Processing Materials Research Materials Science Material","m_szDocBody":"home home article new directory equipment software market report expert book journal blog podcast videos event course new printing adhesive sealant aerospace material aluminium aluminium automotive material biomaterial building construction business ceramic material chemistry clean technology coating thin film composite control system corrosion crystallography design innovation electronic energy event ferrous alloy metal fibre fuel cell graphene iron steel material analysis material processing material research material science material testing mineral mining modelling simulation nanomaterial nanotechnology product nonferrous alloy metal packaging petrochemical photonic photovoltaic pittcon plastic polymer precious metal rubber elastomer semiconductor sustainable technology titanium tribology article latest article thought leader insight industry azojomo material material supplier application industry metal store equipment chemical analysis atomic absorption spectrometer aas atomic optical emission spectrometer oes benchtop nmr spectrometer electrochemical analysis electron paramagnetic resonance epr spectrometer elemental analyzer ftir accessory ftir spectrophotometer ftnir fourier transform spectrometer fuel lubricant testing gas analyzer gas chromatography gel permeation chromatography handheld raman analyzer handheld xrf analyzer ion chromatography liquid chromatography mass spectrometer nmr spectroscopy analyzer pharmaceutical analysis equipment raman spectrometer secondary ion mass spectrometry sim spectrometer spectroscopy accessory titrator vapour pressure measurement xray gamma ray detector xray diffractometer xray fluorescence analyzer xray optic xray photoelectron spectroscopy xps xrf spectrometer coating deposition atomic layer deposition system thermal evaporation equipment thin film deposition system coating testing adhesion tester coating thickness gauge coating film deposition consumable eddy current tester ellipsometer glossmeter thin film characterization system electrical property electrical property characterization equipment hall effect measurement system scanning kelvin probe seebeck coefficient measurement system vibrating sample magnetometer vsm zeta potential analyzer equipment testing calibration battery testing solar cell testing fixing fastener bonding fastener flow controller metre field flow fractionation equipment heat treatment ageing oven industrial furnace oven laboratory furnace kiln vacuum furnace laboratory process equipment controlled atmosphere processing environment cryogenic evaporator concentrator laboratory gas generator laboratory heating cooling apparatus laboratory testing sample preparation equipment laboratory water purification system mixer shaker pcb smt handling workstation scientific illumination light source vacuum pump material processing manufacturing printing equipment material accessory boring machine mill particle size reduction plastic processing equipment ultrasonic welding equipment mechanical testing automatic material testing machine biomaterial testing equipment brittleness tester civil engineering material testing equipment cutter grinder polisher drop weight testing machine durometer fatigue testing machine force gauge gauge hardness testing machine impact testing machine material characterization equipment pipe burst hydrostatic tester plastic rubber testing equipment portable hardness tester scratch tester tensile testing machine torque gauge gauge tribometer friction wear tester universal material testing machine microscope acoustic microscope atom probe atomic force microscope afm electron beam source fibre analyzer ion beam microscope metallurgical microscope microscopy accessory consumable optical microscope polarising microscope raman microscope sample preparation equipment scanning electrochemical microscope secm scanning electron microscope sem scanning probe microscope scanning transmission electron microscope stem stereo microscope transmission electron microscope tem nondestructive testing ndt coating thickness gauge gas analyzer handheld xrf analyzer laser micrometre measurement nondestructive testing ndt equipment portable hardness tester scientific cameras sheet board counter ultrasonic flaw detector xray scattering system saxs waxs optical inspection acoustic microscope borescope ccd cameras colorimeter electron multiplying charge coupled device emccd ellipsometer monochromator optical comparator optical noncontact profiler measurement polarimeter polariscope refractometer scientific cameras oven furnace kiln ageing oven industrial furnace oven laboratory furnace kiln physical property testing adhesion tester analytical test sieve borescope chemisorption analyzer civil engineering material testing equipment density metre diffusivity tester dynamic vapour sorption dvs environmental test chamber extensometer extruded profile measurement system ferrography flexometer goodrich flexometer fogging tester gas pycnometer gas solubility analyzer glossmeter laser micrometre measurement light scattering instrument melt flow index tester metal testing equipment moisture analyzer optical noncontact profiler measurement particle counter particle size analyzer permeameter pharmaceutical analysis equipment plasma processing equipment pore size analyzer profilometer pycnometer rheometer metrology tool sheet board counter shock vibration test system spectrophotometer surface area analyzer surface energy gas chromatograph thickness gauge gauge vapour sorption analyzer viscometer wafer mapping system water sorption analyzer zeta potential analyzer plasma processing plasma diagnostic tool plasma processing equipment process control extruded profile measurement system flow controller metre lubricant condition monitor process control system radiation detector testing geiger counter liquid scintillation counter multichannel analyzer proportional counter radio chemistry sensor detector data logger control system controller data logger gas detector level sensor moisture sensor temperature sensor thermocouple thermal analysis calorimeter differential scanning calorimeter dsc dilatometer flash analysis lfa melting point metre peltier thermostat temperature measurement equipment temperature retraction tester thermal analysis equipment thermal conductivity system thermomechanical analyzer tma product software market report book alloy aluminium asm handbook biomaterial ceramic chemical engineering chemistry clean technology coating composite condensed matter conference proceeding copper corrosion design elastomer electronic engineering fluid fuel cell glass glaze heat treatment instrumentation iron magnetism material processing material science material testing measurement science mechanic mem metallurgy metal microscopy nanotechnology optic photonic cell physic plastic polymer semiconductor soft matter spectroscopy steel thermodynamic thermoplastic titanium welding journal biomaterial ceramic material chemistry coating thin film composite corrosion crystallography energy material processing material science metal alloy mineral nanotechnology polymer solgel videos adhesive bonding axaa conference biomaterial carbon fibre future direction interview ceramic material coating composite material corrosion emc manchester ferrous alloy functional material gas chromatography graphene hard material temperature material iconn interview light alloy m&m phoenix arizona usa machining mass spectrometry material austceram material processing material science technology mst material science technology mst material testing characterisation metal casting foundry mrs fall meeting video interview mrs fall meeting mrs fall meeting mrs fall meeting video interview nanomaterial nonferrous alloy pittcon interview pittcon interview pittcon interview pittcon pittcon precious metal recycled sustainable material rubber elastomer spectrometer stainless steel structural material thermoplastic thermosetting polymer welding brazing course course event contact meet team term advertise browse bymaterialsapplicationsindustry advertise term sponsor trending material storey shapememory polymer react body heat hold promise medical application scientist demonstrate fabrication live tissue structure customdesigned printer harm health productivity caused led flicker cannabis oil extraction interview jame white york fashion week feature revolutionary printed dresse created stratasy threeasfour epfl scientist discover determine efficiency perovskite solar cell sponsor insight industry nondestructive ultrasonic flaw testing syncscan interview cindy zheng measuring preventing flicker led interview steven goetstouwer cannabis oil extraction interview jame white latest material article characterising organic inorganic metallic particle semiconductor structural chemical analyzer sem invia raman microscope analysing silicon carbide sic nondestructive ultrasonic flaw testing syncscan interview cindy zheng preparing unmounted ferrous steel minute planarmet planar grinder preparing surface treated steel sample minute planarmet planar grinder posted aerospace material new storey related new supplier profile saintgobain seal present technical paper cold temperature sealing sae committee meeting published saintgobain seal presented technical paper sae international joint technical committee event titled cold temperature hydraulic seal aerospace hydraulic system strut coupling seal panel joint committee meeting technical paper discussed development testing initiative design pressure hydraulic sealing solution part phase small business innovation research sbir solicited programme sbir programme support technological innovation investment federal research fund encouraging businesse engage federal research development r&d sbir solicitation addresse dynamic sealing solution operate temperature due advancement unmanned air vehicle demanding requirement higher altitude hydraulic system cold soaked prone leakage saintgobain seal technical paper detailed testing elastomer seal oring backup ring tseal omniseal seal party company compared elastomer seal study showed omniseal seal retained pressure lower temperature limit test campaign seal limited cold temperature limitation property included low temperature retraction compression set compression set recovery dissimilar thermal response final test result identified technical feasibility omniseal seal design maintain sealing seal gland extended cold soaking return ambient temperature saintgobain seal presented technical paper participated tabletop exhibition displaying omniseal seal product extensively aerospace critical application jet engine apus flight control landing gear space vehicle recently developed extremely large cryogenic seal more feet wide nasa space launch system sls project exploration mission highperformance achievement based slss future demanding payload omniseal raco cryogenic seal mark continuation saintgobain seal fifty year providing sealing polymer product space exploration collaboration nasa project cryogenic seal nasa exploration mission which handle extreme pressure temperature condition saintgobain seal proactively attending industry event sae event share aerospace community demanding application omniseal seal utilised aerospace hydraulic system aforementioned learn saintgobain seal omniseal product line product line strategic business unit visit here follow connect linkedin related saintgobain seal new saintgobain seal design manufacture extraordinary cryogenic seal nasa space launch system sls project supporting effort propel human being deeper space saintgobain seal showcase temperature sealing polymer solution paris air show highlighting critical part jet engine apus industrial valve summit saintgobain seal highlight wide range sealing solution oil gas industry achema saintgobain highlight sealing barrier solution saintgobain seal continue effort increase partnership north american oil gas industry saintgobain seal oil gas sealing solution hpht condition nace corrosion conference saintgobain performance plastic invest million building wertheim headquarter saintgobain seal launches polyamideimide pai based meldin sery part meldin product line saintgobain seal meldin landing gear bearing sliding ring touch helicopter flight test programme saintgobain performance plastic gmbh extended meldin product line cti symposium saintgobain seal bieglo coexhibiting fakuma show showcase meldin thermoset polyimide material saintgobain seal rulon polymer material improve performance highend rear shock absorber bicycle saintgobain seal omniseal springenergized seal qualified helicopter rotorhead application student visit saintgobain seal spanish aerospace market utilise saintgobain seal omnigasket sealing solution deicing telescopic duct system rulon polymer material saintgobain seal utilised bogie sery train omniseal saintgobain seal approved static seal rocket engine saintgobain seal rulon material comply stringent medical device requirement saint gobain seal acquire polymer component manufacturer kunststofftechnologie sery geared jet engine utilise saintgobain seal group dynamic static sealing component saintgobain diaphragm recently certified usp class compliant saintgobain showcase sealing polymer solution pittcon saintgobain seal technical paper nextgeneration material edinburgh omniseal springenergized metalband seal saintgobain seal qualify aerospace application saintgobain seal renew iso certification sustainable solution handheld surgical power tool saintgobain seal continue development sealing polymer solution electric vehicle meldin thermoplastic material tribological application launched saintgobain seal sery saintgobain seal qualified backup ring hole drilling application saintgobain seal part falcon atlas successful launches saintgobain seal omniseal certified chemical injection pump oil gas application saintgobain omniseal raco polymer springenergized seal offshore lng transfer successful launch delta heavy rocket saintgobain seal bearing saintgobain springenergized seal bearing benefit chemical analyzer saintgobain seal showcase polymer solution show dsseldorf environmentallyfriendly industrial dyeing machine saintgobain springenergized seal saintgobain announce qualification omniseal seal rotary union application unfilled polyimide meldin thermoset material saintgobain seal clear flammability test saintgobain seal group rulon recently certified mass transit application saintgobain seal receive certification fluoroloy food application saintgobain seal exhibiting product paris air show comment review update add new storey cancel reply comment leave feedback logout public comment private feedback azomcom submit latest new thermo fisher scientific acquire xray diffraction provider inel expand capability material science structural characterization marke international launches sorbent tube hazardous air pollutant metalmaster furnace delivered southwest installation worldwide scott bader extend relationship infor trademark approval granted cortec biobased rust preventative biocorr popular new diamond tip boost electron gun power factor silicon drift detector edxrf elemental analyzer enable faster analysis limit detection method semiconductor testing developed efficiently accurately measure uniformity conductivity class material make smartphone display affordable researcher develop class superhydrophobic material home new article directory equipment software market report expert book journal blog podcast videos event course azomcom azonetwork owned operated azomcom limited copyright azomcom information service accordance term condition cooky continuing browse agreeing cooky here","m_szGeo1":"United Kingdom","m_szSourceType":"source_industry","m_szSrcUrl":"http://www.azom.com/news.aspx?newsID=45025","m_Places":["Hall","Kilns","Boring","Surface Area","Manchester","Uk","United States","Printer","New York","Edinburgh","Düsseldorf","Friendly"],"m_People":["Nir Fourier","Eddy Current","Perovskite Solar","Diffusivity Tester","Cindy Zheng","Steven Goetstouwers","Sae A-5","Omniseal Raco","Colt Delta Elite Iv","Scott Bader"],"m_Companies":["Plastics","Sec","Shakers","Particle","Plastic","Force Gages","Torque","Gages","Universal","Atom","Goodrich","Asm","Emc","M&m","Phoenix, Arizona","Stratasys","Particles","On Semiconductors","Planar","Saint-gobain","Sae International","Joint Committee","Nasa","Sae","Twitter","Linkedin","Paris Air Show","Barrier Solutions","S Gmbh","Bieglo Co","Gobain Seals Group","Seals Group","Iso","Eu","Thermo Fisher Scientific"],"m_BiGrams":["saintgobain seal","material testing","testing machine","material science","technical paper","omniseal seal","material processing","testing equipment","sealing solution","application saintgobain","thin film","processing material","measurement system","cryogenic seal","sealing polymer","product line","polymer solution","oil gas","springenergized seal","software market","market report","ceramic material","control system","analysis equipment","thickness gauge","furnace kiln","processing equipment","electron microscope","ultrasonic flaw","plasma processing","pittcon interview","interview pittcon","cold temperature","hydraulic system","jet engine","seal omniseal","material saintgobain"],"m_TriGrams":["application saintgobain seal","software market report","saintgobain seal omniseal","sealing polymer solution","material saintgobain seal"],"m_SocialTags":[],"m_Topics":[],"m_Industry":[],"m_Technology":[],"m_BiCnt":[38,7,7,6,6,6,5,5,5,5,4,4,4,4,4,4,4,4,4,3,3,3,3,3,3,3,3,3,3,3,3,3,3,3,3,3,3],"m_TriCnt":[4,3,3,3,3],"m_iDocBodyWordCnt":1864}
