{"m_szDocID":"126442","m_szDocTitle":"Symbio FCell Selected Impact Coatings' Ceramic MaxPhase for New Automotive Fuel Cell","m_szYear":"2016","m_szDocSumamry":"Home Home Articles News Directory Equipment Software Market Reports Experts Books Journals Blogs Podcasts Videos Events Courses News 3D Printing Adhesives and Sealants Aerospace Materials Aluminum / Aluminium Automotive Materials Biomaterials Building and Construction Business Ceramic Materials Chemistry Clean Technology Coatings and Thin Films Composites Control Systems Corrosion Crystallography Design and Innovation Electronics Energy Events Ferrous Alloys and Metals Fibers Fuel Cell Graphene Iron and Steel Materials Analysis Materials Processing Materials Research Materials Science Material","m_szDocBody":"home home article new directory equipment software market report expert book journal blog podcast videos event course new printing adhesive sealant aerospace material aluminium aluminium automotive material biomaterial building construction business ceramic material chemistry clean technology coating thin film composite control system corrosion crystallography design innovation electronic energy event ferrous alloy metal fibre fuel cell graphene iron steel material analysis material processing material research material science material testing mineral mining modelling simulation nanomaterial nanotechnology product nonferrous alloy metal packaging petrochemical photonic photovoltaic pittcon plastic polymer precious metal rubber elastomer semiconductor sustainable technology titanium tribology article latest article thought leader insight industry azojomo material material supplier application industry metal store equipment chemical analysis atomic absorption spectrometer aas atomic optical emission spectrometer oes benchtop nmr spectrometer electrochemical analysis electron paramagnetic resonance epr spectrometer elemental analyzer ftir accessory ftir spectrophotometer ftnir fourier transform spectrometer fuel lubricant testing gas analyzer gas chromatography gel permeation chromatography handheld raman analyzer handheld xrf analyzer ion chromatography liquid chromatography mass spectrometer nmr spectroscopy analyzer pharmaceutical analysis equipment raman spectrometer secondary ion mass spectrometry sim spectrometer spectroscopy accessory titrator vapour pressure measurement xray gamma ray detector xray diffractometer xray fluorescence analyzer xray optic xray photoelectron spectroscopy xps xrf spectrometer coating deposition atomic layer deposition system thermal evaporation equipment thin film deposition system coating testing adhesion tester coating thickness gauge coating film deposition consumable eddy current tester ellipsometer glossmeter thin film characterization system electrical property electrical property characterization equipment hall effect measurement system scanning kelvin probe seebeck coefficient measurement system vibrating sample magnetometer vsm zeta potential analyzer equipment testing calibration battery testing solar cell testing fixing fastener bonding fastener flow controller metre field flow fractionation equipment heat treatment ageing oven industrial furnace oven laboratory furnace kiln vacuum furnace laboratory process equipment controlled atmosphere processing environment cryogenic evaporator concentrator laboratory gas generator laboratory heating cooling apparatus laboratory testing sample preparation equipment laboratory water purification system mixer shaker pcb smt handling workstation scientific illumination light source vacuum pump material processing manufacturing printing equipment material accessory boring machine mill particle size reduction plastic processing equipment ultrasonic welding equipment mechanical testing automatic material testing machine biomaterial testing equipment brittleness tester civil engineering material testing equipment cutter grinder polisher drop weight testing machine durometer fatigue testing machine force gauge gauge hardness testing machine impact testing machine material characterization equipment pipe burst hydrostatic tester plastic rubber testing equipment portable hardness tester scratch tester tensile testing machine torque gauge gauge tribometer friction wear tester universal material testing machine microscope acoustic microscope atom probe atomic force microscope afm electron beam source fibre analyzer ion beam microscope metallurgical microscope microscopy accessory consumable optical microscope polarising microscope raman microscope sample preparation equipment scanning electrochemical microscope secm scanning electron microscope sem scanning probe microscope scanning transmission electron microscope stem stereo microscope transmission electron microscope tem nondestructive testing ndt coating thickness gauge gas analyzer handheld xrf analyzer laser micrometre measurement nondestructive testing ndt equipment portable hardness tester scientific cameras sheet board counter ultrasonic flaw detector xray scattering system saxs waxs optical inspection acoustic microscope borescope ccd cameras colorimeter electron multiplying charge coupled device emccd ellipsometer monochromator optical comparator optical noncontact profiler measurement polarimeter polariscope refractometer scientific cameras oven furnace kiln ageing oven industrial furnace oven laboratory furnace kiln physical property testing adhesion tester analytical test sieve borescope chemisorption analyzer civil engineering material testing equipment density metre diffusivity tester dynamic vapour sorption dvs environmental test chamber extensometer extruded profile measurement system ferrography flexometer goodrich flexometer fogging tester gas pycnometer gas solubility analyzer glossmeter laser micrometre measurement light scattering instrument melt flow index tester metal testing equipment moisture analyzer optical noncontact profiler measurement particle counter particle size analyzer permeameter pharmaceutical analysis equipment plasma processing equipment pore size analyzer profilometer pycnometer rheometer metrology tool sheet board counter shock vibration test system spectrophotometer surface area analyzer surface energy gas chromatograph thickness gauge gauge vapour sorption analyzer viscometer wafer mapping system water sorption analyzer zeta potential analyzer plasma processing plasma diagnostic tool plasma processing equipment process control extruded profile measurement system flow controller metre lubricant condition monitor process control system radiation detector testing geiger counter liquid scintillation counter multichannel analyzer proportional counter radio chemistry sensor detector data logger control system controller data logger gas detector level sensor moisture sensor temperature sensor thermocouple thermal analysis calorimeter differential scanning calorimeter dsc dilatometer flash analysis lfa melting point metre peltier thermostat temperature measurement equipment temperature retraction tester thermal analysis equipment thermal conductivity system thermomechanical analyzer tma product software market report book alloy aluminium asm handbook biomaterial ceramic chemical engineering chemistry clean technology coating composite condensed matter conference proceeding copper corrosion design elastomer electronic engineering fluid fuel cell glass glaze heat treatment instrumentation iron magnetism material processing material science material testing measurement science mechanic mem metallurgy metal microscopy nanotechnology optic photonic cell physic plastic polymer semiconductor soft matter spectroscopy steel thermodynamic thermoplastic titanium welding journal biomaterial ceramic material chemistry coating thin film composite corrosion crystallography energy material processing material science metal alloy mineral nanotechnology polymer solgel videos adhesive bonding axaa conference biomaterial carbon fibre future direction interview ceramic material coating composite material corrosion emc manchester ferrous alloy functional material gas chromatography graphene hard material temperature material iconn interview light alloy m&m phoenix arizona usa machining mass spectrometry material austceram material processing material science technology mst material science technology mst material testing characterisation metal casting foundry mrs fall meeting video interview mrs fall meeting mrs fall meeting mrs fall meeting video interview nanomaterial nonferrous alloy pittcon interview pittcon interview pittcon interview pittcon pittcon precious metal recycled sustainable material rubber elastomer spectrometer stainless steel structural material thermoplastic thermosetting polymer welding brazing course course event contact meet team term advertise browse bymaterialsapplicationsindustry advertise term sponsor trending material storey shapememory polymer react body heat hold promise medical application scientist demonstrate fabrication live tissue structure customdesigned printer harm health productivity caused led flicker cannabis oil extraction interview jame white york fashion week feature revolutionary printed dresse created stratasy threeasfour epfl scientist discover determine efficiency perovskite solar cell sponsor insight industry nondestructive ultrasonic flaw testing syncscan interview cindy zheng measuring preventing flicker led interview steven goetstouwer cannabis oil extraction interview jame white latest material article characterising organic inorganic metallic particle semiconductor structural chemical analyzer sem invia raman microscope analysing silicon carbide sic nondestructive ultrasonic flaw testing syncscan interview cindy zheng preparing unmounted ferrous steel minute planarmet planar grinder preparing surface treated steel sample minute planarmet planar grinder posted ceramic material clean technology fuel cell new storey related new related article supplier profile request quote symbio fcell selected impact coating ceramic maxphase automotive fuel cell published french company symbio fcell manufacture fuel cell powertrain range extender car commercial vehicle producer chosen ceramic maxphase coating impact coating fuel cell stack fuel cell expected ready launch alp range extender ceramic maxphase enhance performance lifetime metal bipolar plate fuel cell pvd physical vapour deposition coating proven stateoftheart proton exchange membrane fuel cell pemfc direct methanol fuel cell dmfc offering unique combination low contact resistance corrosion resistance low cost exceed performance cost reduction target set department energy symbio fcell product range extender battery powered electric vehicle main source power fuel cell electrical vehicle typical user today commercial fleet depart return location hydrogen gas fuel station placed symbio fcell technology poste france targeting zeroemission quiet city operation industry expect tipping point automotive fuel cell application private car small truck impact coating support symbio fcell development fuel cell technology range extender full power including fuel cell truck heavyduty vehicle fuel cell stack include ceramic maxphase coating planned ready initially impact coating supply ceramic maxphase coating service symbio fcell company partner cobra fuel cell development project funded fuel cell hydrogen joint undertaking fch eus seventh framework programme research cobra project partner are borit cea cidetec insa lyon impact coating impact coating develop commercialise innovative technology pvd surface treatment pvd method vacuumcoat thin film metal ceramic company main product deposition system inlinecoater plasticoater reelcoater targeting leanorganized component manufacturing involving pvd system surface treatment broad spectrum application including opportunity replace chromium plating plastic gold plating electrical contact addition company developed complete technology portfolio surface treatment bipolar plate fuel cell target customer primarily component manufacturer electronic automotive industry company founded period development establishing product service company expanding globally impact coating share traded nasdaq omx stockholm north related impact coating new impact coating fci announce board connector ecofriendly silver maxphase finish integrated pvd metallization passat fci enter agreement impact coating commercialise silver maxphase contact finishing solution lean production metallized plastic fakuma show silver maxphase coating gold plating replacement electronic granted patent harder sharper cost effective test probe pcb impact coating impact coating article chromium plating plastic replacement lean integration injection moulding vacuum metallization lacquer physical vapour deposition pvd lean production flow interview torsten rosell injection moulding improving reflector manufacturing coating material reducing fuel cell cost low cost alternative gold electronic application comment review update add new storey cancel reply comment leave feedback logout public comment private feedback azomcom submit latest new thermo fisher scientific acquire xray diffraction provider inel expand capability material science structural characterization marke international launches sorbent tube hazardous air pollutant metalmaster furnace delivered southwest installation worldwide scott bader extend relationship infor trademark approval granted cortec biobased rust preventative biocorr popular new diamond tip boost electron gun power factor silicon drift detector edxrf elemental analyzer enable faster analysis limit detection method semiconductor testing developed efficiently accurately measure uniformity conductivity class material make smartphone display affordable researcher develop class superhydrophobic material home new article directory equipment software market report expert book journal blog podcast videos event course azomcom azonetwork owned operated azomcom limited copyright azomcom information service accordance term condition cooky continuing browse agreeing cooky here","m_szGeo1":"United Kingdom","m_szSourceType":"source_industry","m_szSrcUrl":"http://www.azom.com/news.aspx?newsID=44454","m_Places":["Hall","Kilns","Boring","Surface Area","Manchester","Uk","United States","Printer","New York","France","Stockholm","Eco-friendly"],"m_People":["Nir Fourier","Eddy Current","Perovskite Solar","Diffusivity Tester","Cindy Zheng","Steven Goetstouwers","Insa Lyon","Torsten Rosell","Scott Bader"],"m_Companies":["Plastics","Sec","Shakers","Particle","Plastic","Force Gages","Torque","Gages","Universal","Atom","Goodrich","Asm","Emc","M&m","Phoenix, Arizona","Stratasys","Particles","On Semiconductors","Planar","Us Department Of Energy","Power Fc","Eu","Borit Nv","Target","Nasdaq Omx","Thermo Fisher Scientific"],"m_BiGrams":["fuel cell","impact coating","material testing","testing machine","material science","symbio fcell","thin film","material processing","testing equipment","ceramic maxphase","ceramic material","processing material","measurement system","range extender","maxphase coating","software market","market report","clean technology","control system","analysis equipment","deposition system","thickness gauge","furnace kiln","processing equipment","electron microscope","ultrasonic flaw","plasma processing","pittcon interview","interview pittcon","coating impact","surface treatment","silver maxphase"],"m_TriGrams":["software market report","ceramic maxphase coating"],"m_SocialTags":[],"m_Topics":[],"m_Industry":[],"m_Technology":[],"m_BiCnt":[19,12,7,7,6,6,5,5,5,5,4,4,4,4,4,3,3,3,3,3,3,3,3,3,3,3,3,3,3,3,3,3],"m_TriCnt":[3,3],"m_iDocBodyWordCnt":1597}
