{"m_szDocID":"130126","m_szDocTitle":"Major Advance Towards Practical Application of Solid-State Energy-Storage/Heat-Release Materials","m_szYear":"2016","m_szDocSumamry":"Home Home Articles News Directory Equipment Software Market Reports Experts Books Journals Blogs Podcasts Videos Events Courses News 3D Printing Adhesives and Sealants Aerospace Materials Aluminum / Aluminium Automotive Materials Biomaterials Building and Construction Business Ceramic Materials Chemistry Clean Technology Coatings and Thin Films Composites Control Systems Corrosion Crystallography Design and Innovation Electronics Energy Events Ferrous Alloys and Metals Fibers Fuel Cell Graphene Iron and Steel Materials Analysis Materials Processing Materials Research Materials Science Material","m_szDocBody":"home home article new directory equipment software market report expert book journal blog podcast videos event course new printing adhesive sealant aerospace material aluminium aluminium automotive material biomaterial building construction business ceramic material chemistry clean technology coating thin film composite control system corrosion crystallography design innovation electronic energy event ferrous alloy metal fibre fuel cell graphene iron steel material analysis material processing material research material science material testing mineral mining modelling simulation nanomaterial nanotechnology product nonferrous alloy metal packaging petrochemical photonic photovoltaic pittcon plastic polymer precious metal rubber elastomer semiconductor sustainable technology titanium tribology article latest article thought leader insight industry azojomo material material supplier application industry metal store equipment chemical analysis atomic absorption spectrometer aas atomic optical emission spectrometer oes benchtop nmr spectrometer electrochemical analysis electron paramagnetic resonance epr spectrometer elemental analyzer ftir accessory ftir spectrophotometer ftnir fourier transform spectrometer fuel lubricant testing gas analyzer gas chromatography gel permeation chromatography handheld raman analyzer handheld xrf analyzer ion chromatography liquid chromatography mass spectrometer nmr spectroscopy analyzer pharmaceutical analysis equipment raman spectrometer secondary ion mass spectrometry sim spectrometer spectroscopy accessory titrator vapour pressure measurement xray gamma ray detector xray diffractometer xray fluorescence analyzer xray optic xray photoelectron spectroscopy xps xrf spectrometer coating deposition atomic layer deposition system thermal evaporation equipment thin film deposition system coating testing adhesion tester coating thickness gauge coating film deposition consumable eddy current tester ellipsometer glossmeter thin film characterization system electrical property electrical property characterization equipment hall effect measurement system scanning kelvin probe seebeck coefficient measurement system vibrating sample magnetometer vsm zeta potential analyzer equipment testing calibration battery testing solar cell testing fixing fastener bonding fastener flow controller metre field flow fractionation equipment heat treatment ageing oven industrial furnace oven laboratory furnace kiln vacuum furnace laboratory process equipment controlled atmosphere processing environment cryogenic evaporator concentrator laboratory gas generator laboratory heating cooling apparatus laboratory testing sample preparation equipment laboratory water purification system mixer shaker pcb smt handling workstation scientific illumination light source vacuum pump material processing manufacturing printing equipment material accessory boring machine mill particle size reduction plastic processing equipment ultrasonic welding equipment mechanical testing automatic material testing machine biomaterial testing equipment brittleness tester civil engineering material testing equipment cutter grinder polisher drop weight testing machine durometer fatigue testing machine force gauge gauge hardness testing machine impact testing machine material characterization equipment pipe burst hydrostatic tester plastic rubber testing equipment portable hardness tester scratch tester tensile testing machine torque gauge gauge tribometer friction wear tester universal material testing machine microscope acoustic microscope atom probe atomic force microscope afm electron beam source fibre analyzer ion beam microscope metallurgical microscope microscopy accessory consumable optical microscope polarising microscope raman microscope sample preparation equipment scanning electrochemical microscope secm scanning electron microscope sem scanning probe microscope scanning transmission electron microscope stem stereo microscope transmission electron microscope tem nondestructive testing ndt coating thickness gauge gas analyzer handheld xrf analyzer laser micrometre measurement nondestructive testing ndt equipment portable hardness tester scientific cameras sheet board counter ultrasonic flaw detector xray scattering system saxs waxs optical inspection acoustic microscope borescope ccd cameras colorimeter electron multiplying charge coupled device emccd ellipsometer monochromator optical comparator optical noncontact profiler measurement polarimeter polariscope refractometer scientific cameras oven furnace kiln ageing oven industrial furnace oven laboratory furnace kiln physical property testing adhesion tester analytical test sieve borescope chemisorption analyzer civil engineering material testing equipment density metre diffusivity tester dynamic vapour sorption dvs environmental test chamber extensometer extruded profile measurement system ferrography flexometer goodrich flexometer fogging tester gas pycnometer gas solubility analyzer glossmeter laser micrometre measurement light scattering instrument melt flow index tester metal testing equipment moisture analyzer optical noncontact profiler measurement particle counter particle size analyzer permeameter pharmaceutical analysis equipment plasma processing equipment pore size analyzer profilometer pycnometer rheometer metrology tool sheet board counter shock vibration test system spectrophotometer surface area analyzer surface energy gas chromatograph thickness gauge gauge vapour sorption analyzer viscometer wafer mapping system water sorption analyzer zeta potential analyzer plasma processing plasma diagnostic tool plasma processing equipment process control extruded profile measurement system flow controller metre lubricant condition monitor process control system radiation detector testing geiger counter liquid scintillation counter multichannel analyzer proportional counter radio chemistry sensor detector data logger control system controller data logger gas detector level sensor moisture sensor temperature sensor thermocouple thermal analysis calorimeter differential scanning calorimeter dsc dilatometer flash analysis lfa melting point metre peltier thermostat temperature measurement equipment temperature retraction tester thermal analysis equipment thermal conductivity system thermomechanical analyzer tma product software market report book alloy aluminium asm handbook biomaterial ceramic chemical engineering chemistry clean technology coating composite condensed matter conference proceeding copper corrosion design elastomer electronic engineering fluid fuel cell glass glaze heat treatment instrumentation iron magnetism material processing material science material testing measurement science mechanic mem metallurgy metal microscopy nanotechnology optic photonic cell physic plastic polymer semiconductor soft matter spectroscopy steel thermodynamic thermoplastic titanium welding journal biomaterial ceramic material chemistry coating thin film composite corrosion crystallography energy material processing material science metal alloy mineral nanotechnology polymer solgel videos adhesive bonding axaa conference biomaterial carbon fibre future direction interview ceramic material coating composite material corrosion emc manchester ferrous alloy functional material gas chromatography graphene hard material temperature material iconn interview light alloy m&m phoenix arizona usa machining mass spectrometry material austceram material processing material science technology mst material science technology mst material testing characterisation metal casting foundry mrs fall meeting video interview mrs fall meeting mrs fall meeting mrs fall meeting video interview nanomaterial nonferrous alloy pittcon interview pittcon interview pittcon interview pittcon pittcon precious metal recycled sustainable material rubber elastomer spectrometer stainless steel structural material thermoplastic thermosetting polymer welding brazing course course event contact meet team term advertise browse bymaterialsapplicationsindustry advertise term sponsor trending material storey shapememory polymer react body heat hold promise medical application scientist demonstrate fabrication live tissue structure customdesigned printer harm health productivity caused led flicker cannabis oil extraction interview jame white york fashion week feature revolutionary printed dresse created stratasy threeasfour epfl scientist discover determine efficiency perovskite solar cell sponsor insight industry nondestructive ultrasonic flaw testing syncscan interview cindy zheng measuring preventing flicker led interview steven goetstouwer cannabis oil extraction interview jame white latest material article characterising organic inorganic metallic particle semiconductor structural chemical analyzer sem invia raman microscope analysing silicon carbide sic nondestructive ultrasonic flaw testing syncscan interview cindy zheng preparing unmounted ferrous steel minute planarmet planar grinder preparing surface treated steel sample minute planarmet planar grinder posted sustainable technology material research energy material science material analysis new storey major advance practical application solidstate material published imagine clothing could demand release heat warm cosy allowing dial back thermostat setting stay comfortable cooler room picture car windshield store sun energy release burst heat melt layer ice layerbylayer solar thermal fuel polymer film comprise distinct layer micron thickness each crosslinking layer enable building film tunable thickness courtesy researcher team researcher mit scenarios long material store solar energy day release heat needed transparent polymer film applied surface window glass clothing sun virtually inexhaustible source energy half time daylight sun major power provider human need efficient save nighttime stormy day effort focused storing recovering solar energy form electricity finding provide highly efficient method storing sun energy chemical reaction releasing heat finding mit professor jeffrey grossman postdoc david zhitomirsky graduate student eugene cho paper advanced energy material key enabling longterm stable storage solar heat team say store form chemical change storing heat itself heat inevitably dissipate time matter good insulation chemical storage system retain energy indefinitely stable molecular configuration release triggered small jolt heat light electricity molecule configuration key molecule remain stable configuration exposed sunlight energy light kick molecule charged configuration stay long period then triggered specific temperature stimulus molecule snap back original shape giving burst heat process chemicallybased storage material solar thermal fuel stf developed before including previous work grossman team earlier effort limited utility solidstate application designed liquid solution capable making durable solidstate film zhitomirsky say approach based solidstate material case polymer based inexpensive material widespread manufacturing technology work present exciting avenue simultaneous energy harvesting storage single material ted sargent university professor university toronto involved research manufacturing material require twostep process simple scalable cho system based previous work aimed developing solar cooker store solar heat cooking sundown challenge that say team realised heatstoring material made form thin film incorporated material say including glass fabric make film capable storing amount heat ensure manufactured easily reliably team started material called azobenzene change molecular configuration response light azobenzene stimulated tiny pulse heat revert original configuration release heat process researcher modified material chemistry improve energy density amount energy stored weight ability form smooth uniform layer responsiveness activating heat pulse shedding ice material ended highly transparent make deicing car windshield grossman morton claire goulder family professor environmental system professor material science engineering car fine heating wire embedded rear window purpose block front window forbidden law thin wire transparent film made material sandwiched layer glass bonding polymer prevent piece broken glass flying accident provide deicing effect blockage german auto company bmw sponsor research interested potential application say window energy stored polymer time car sit sunlight then trigger small amount heat provided heating wire puff heated air blast heat grossman say test show heat drop ice windshield accomplishing that explain doesnt require ice melted ice closest glass melt provide layer water release rest ice slide gravity pushed windshield wiper team continuing work improving film property grossman say material slight yellowish tinge researcher working improving transparency release burst degree celsius surrounding temperature sufficient icemelting application boost degree already system exist significant boon electric car devote energy heating deicing driving range drop percent cold condition polymer significantly reduce drain grossman say approach innovative distinctive sargent university toronto research major advance practical application solidstate material scientific engineering point view work supported nserc canada banting fellowship bmw source comment review update add new storey cancel reply comment leave feedback logout public comment private feedback azomcom submit latest new thermo fisher scientific acquire xray diffraction provider inel expand capability material science structural characterization marke international launches sorbent tube hazardous air pollutant metalmaster furnace delivered southwest installation worldwide scott bader extend relationship infor trademark approval granted cortec biobased rust preventative biocorr popular new diamond tip boost electron gun power factor silicon drift detector edxrf elemental analyzer enable faster analysis limit detection method semiconductor testing developed efficiently accurately measure uniformity conductivity class material make smartphone display affordable researcher develop class superhydrophobic material home new article directory equipment software market report expert book journal blog podcast videos event course azomcom azonetwork owned operated azomcom limited copyright azomcom information service accordance term condition cooky continuing browse agreeing cooky here","m_szGeo1":"United Kingdom","m_szSourceType":"source_industry","m_szSrcUrl":"http://www.azom.com/news.aspx?newsID=44956","m_Places":["Hall","Kilns","Boring","Surface Area","Manchester","Uk","United States","Printer","New York","Most"],"m_People":["Nir Fourier","Eddy Current","Perovskite Solar","Diffusivity Tester","Cindy Zheng","Steven Goetstouwers","Jeffrey Grossman","David Zhitomirsky","Eugene Cho","Ted Sargent","Claire Goulder","Nserc Canada","Scott Bader"],"m_Companies":["Plastics","Sec","Shakers","Particle","Plastic","Force Gages","Torque","Gages","Universal","Atom","Goodrich","Asm","Emc","M&m","Phoenix, Arizona","Stratasys","Particles","On Semiconductors","Planar","Stf","University Of Toronto","Bmw","Thermo Fisher Scientific","Eu"],"m_BiGrams":["material science","material testing","testing machine","thin film","material processing","testing equipment","processing material","measurement system","software market","market report","ceramic material","material chemistry","control system","science material","analysis equipment","thickness gauge","furnace kiln","processing equipment","electron microscope","ultrasonic flaw","plasma processing","energy material","pittcon interview","interview pittcon","solidstate material","release heat","grossman say"],"m_TriGrams":["software market report"],"m_SocialTags":[],"m_Topics":[],"m_Industry":[],"m_Technology":[],"m_BiCnt":[8,7,7,5,5,5,4,4,3,3,3,3,3,3,3,3,3,3,3,3,3,3,3,3,3,3,3],"m_TriCnt":[3],"m_iDocBodyWordCnt":1752}
