{"m_szDocID":"14499","m_szDocTitle":"The woes of Beijing's electric taxi drivers | South China Morning Post","m_szYear":"2014","m_szDocSumamry":"The woes of Beijing's electric taxi drivers Poor battery life and long recharge times severely hurt business, drivers insist PUBLISHED : Tuesday, 14 January, 2014, 7:44pm UPDATED : Tuesday, 14 January, 2014, 7:48pm Your FREE copy of Home Essentials 2016 now! A group of electric taxis lined up in the Tongzhou district of Beijing. Photo: CFP, via Global Times Electric taxi drivers in Beijing suffer from battery problems, with overly long charging sessions cutting into time that could be spent driving passengers. Waiting in queues at charging stations is now the norm for many drivers, and chargin","m_szDocBody":"woe beijing electric taxi driver poor battery life long recharge time severely hurt business driver insist published tuesday january updated tuesday january free copy home essential now electric taxis lined tongzhou district beijing photo cfp global time electric taxi driver beijing suffer battery problem overly long charging session cutting time spent driving passenger waiting queue charging station norm driver charging vehicle hour reported chinese financial new portal caixin additional report beijing today vehicle charge daily order maintain satisfying income level point time electric taxis street tongzhou district beijing driver surnamed cheng interviewed caixin truth road time queue waiting charged express station charge vehicle half hour cut battery life half simply queuing express station process hour furthermore freshly charged electric taxis travel kilometre driver noted colder autumn winter month car heater affect power consumption require recharge kilometre order combat battery depletion driver chosen restrict route order ensure charging station reach begun rejecting passenger requested destination away nowaday china pushing electric car driver surnamed zhang told caixin passenger too battery life car reach kilometre single charge problem wouldnt problem anymore current statistic electric taxis roaming district beijing total charging station located city generally charging station service vehicle time local beijing government aggressively sponsored privately owned electric taxis mean curbing air pollution vehicle eligible subsidy yuan month share ","m_szGeo1":"China","m_szSourceType":"source_news","m_szSrcUrl":"http://www.scmp.com/news/china-insider/article/1405513/woes-beijings-electric-taxi-drivers","m_Places":["Beijing","Beijing Today"],"m_People":["Cheng","Zhang"],"m_Companies":["Beijing Today"],"m_BiGrams":["electric taxis","charging station","battery life","district beijing"],"m_TriGrams":[],"m_SocialTags":[],"m_Topics":[],"m_Industry":[],"m_Technology":[],"m_BiCnt":[],"m_TriCnt":[],"m_iDocBodyWordCnt":215}
