{"m_szDocID":"14512","m_szDocTitle":"Zhang Tianren Of Tianneng Group Puts Forth A Proposal For Transforming The... -- HUZHOU, China, March 19, 2014 /PRNewswire/ --","m_szYear":"2007","m_szDocSumamry":"Ã— A panoramic view of Tianneng Group.  (PRNewsFoto/Tianneng Group) HUZHOU, China, March 19, 2014 /PRNewswire/ -- Tianneng Group chairman Zhang Tianren, one of the leading players in the new energy field, continues to make waves across the industry, this time focusing on the recycling of used lead acid batteries. He recently put forth a proposal to strengthen the regulations surrounding the proper handling of disposed lead acid batteries at the National People's Congress and Chinese People's Political Consultative Congress. The business of the recovery of disposed lead acid batteries is now in ","m_szDocBody":"panoramic tianneng group group huzhou china tianneng chairman zhang tianren leading player energy field continue make wave industry time focusing recycling lead acid battery recently put proposal strengthen regulation surrounding proper handling disposed lead acid battery national people congress chinese people political consultative congress business recovery disposed lead acid battery complete disarray zhang hope the sector winter spring come pioneer lead acid battery industry zhang led team development industry longlife cycle battery sending shock wave industry directly contributing industry transformative round development every year china produce million tonne scrap lead acid battery major treasure trove utilised efficiently hand major source pollution handled disposed properly zhang said added that year development year rigorous regulation pollution production lead acid battery addressed focus shifting battery recovery scrap lead acid battery waiting spring regulation place scrap lead acid battery enter spring season generally speaking chinas lead acid battery manufacturer involved recovery battery however zhang believe industry leader shoulder responsibility set good example tianneng built large industrial park based concept virtuous circular production line specialising recovery disposed battery metal recovery rate lead park percent higher site traditional method recovery zhang suggested china undertake research recovery disposed lead acid battery developing industrial cluster recycling metal move promote successful demonstration project supporting management system boost development industry whole tianneng founded tianneng focuse manufacturing electric vehicle battery engaged thedevelopment production sale nickel metal hydride lithium ion wind solar energy storage battery recovery secondary lead energy resource company chinas power battery firm list hong kong main board large international company tianneng billion yuan total asset employee spread chinabased whollyowned subsidiary business unit overseas tianneng maintained number position peer china consecutive year term production output sale volume core product making leading green power source provider country sale revenue exceeded billion yuan approx billion tianneng key hightech firm government support china core member administration storage battery standardisation china global energy firm chinas top manufacturer chinas top privatelyowned firm chinas top cell maker boast statelevel postdoctoral workstation stateregistered corporate technology centre company developed statelevel key product developed tested standard achieved innovation patent recent year visit official website ","m_szGeo1":"United States","m_szSourceType":"source_news","m_szSrcUrl":"http://www.prnewswire.com/news-releases/zhang-tianren-of-tianneng-group-puts-forth-a-proposal-for-transforming-the-handling-of-disposed-lead-acid-batteries-250957551.html","m_Places":["Huzhou","Hong Kong"],"m_People":["Zhang"],"m_Companies":["Tianneng Group"],"m_BiGrams":["lead acid","acid battery","disposed lead","recovery disposed","scrap lead","chinas top"],"m_TriGrams":["lead acid battery","disposed lead acid","scrap lead acid"],"m_SocialTags":[],"m_Topics":[],"m_Industry":[],"m_Technology":[],"m_BiCnt":[10,10,3,3,3,3],"m_TriCnt":[10,3,3],"m_iDocBodyWordCnt":345}
