{"m_szDocID":"14604","m_szDocTitle":"Chinese Solar Stocks Surge With WTO Ruling Against US-Imposed Tariffs | CleanTechnica","m_szYear":"1994","m_szDocSumamry":"Chinese Solar Stocks Surge With WTO Ruling Against US-Imposed Tariffs July 16th, 2014 by James Ayre   A number of prominent China-based solar energy companies saw their stock rise substantially on Monday (July 14), thanks to the World Trade Organization’s recent ruling against the US imposition of tariffs on Chinese solar modules, steel products, and other exports. According to the WTO, tariffs violate global trade rules — being inconsistent with obligations under the 1994 Marrakesh accord. Notably, though, the WTO also rejected some of the arguments being used by Chinese proponents against th","m_szDocBody":"chinese solar stock surge wto ruling usimposed tariff jame ayre number prominent chinabased solar energy company stock rise substantially july world trade organisation recent ruling imposition tariff chinese solar module steel product export wto tariff violate global trade rule inconsistent obligation marrakesh accord notably though wto rejected argument chinese proponent tariff image credit flag china yangtze river shutterstock solar stock rallied monday yingli green energy rose china sunenergy renesola trina solar jinko solar usbased company solarcity rely heavily imported chinesemodule rose reuter more billion chinese case panel found washington overstepped mark justifying socalled countervailing duty imposed response alleged subsidy exporting firm chinas government marrakesh accord set wto duty levied clear evidence stateowned partially stateowned enterprise passing subsidy public body panel found washington produced insufficient evidence this fault calculation subsidy chinese firm producing item kitchen shelving grass cutter citric acid reportedly weighing option matter trade representative michael froman provided bit spin subject minor victory rejection chinas argument concluding respect finding panel report administration carefully evaluating option step ensure remedy unfair subsidy remain strong effective related new china world largest solar market global energy development report eastern powerhouse surpassed germany top spot interesting finding report solar capacity installed total installed china increase previous year eastern manufacturing powerhouse trade war china important appear glance time changing youd attend cleantechnica solar event date hottest cleantech new subscribing free cleantech newsletter eye sectorspecific new also free solar energy newsletter electric vehicle newsletter wind energy newsletter tag china solar stock solar trade war trade war jame ayre background predominantly geopolitic history obsessive interest pretty everything early life spent imperial free city dortmund jame river ruhr cofbuokheim attended university astnide briefly considered entering coal mining business write living broad variety subject ranging science politic military history renewable energy follow work google related post chinese solar panel manufacturer dont chinese government difference bobwallace businesse china privately owned joseph hall privately owned communist china money company start end communist government isnt trade war about communist flooding market chinese government funded solar panel under bobwallace chinese government subsidised industry government subsidised industry government subsidy owned government thing served reading objective information current state government industry china sound current source old dogeared pamphlet john birch society joseph hall hold bob prosolar system issue let face fact chinese communist yeah talk good capitalistic game way end theyre communist china desperate energy theyre gaming system hurting solar panel manufacturer part world bobwallace hundred chinese solar panel manufacturer bankrupt closed industry shakeout year back government owned wouldnt happened dont think yes chinese government playing tough game breaking rule blatantly country chinese solar manufacturer driven manufacturer country business combination cheap labour low environmental safety practise apparently illegal government subsidy add significant industrial spying pushed back put duty imported chinese panel communism longer mean communism meant socialism left china lot central government control joseph hall really doubt chinese government market force yingli jinko trina theyd step immediately stop primarily panel regardless stop communism china changed stripe hold election prove bobwallace first china large number small inefficient manufacturer under giving information show manufacturer china afloat government second stepping save major manufacturer weve car industry third understand difference strong central government weak central government democracy socialism capitalism youre talking century china read some understand operating now cold war version china joseph hall big problem china country nowaday growing communism evil period ussr collapsed usa wiped hand said communism dead turn business china theyre capitalist theyre not dont compare usa saving car industry financial industry entire economy chinese playing twofaced game changed china noticed hasnt changed party rule communist good discussion agree disagree good nonetheless bobwallace communism essentially dead small pocket remain place cuba castro boy kick china capitalism nastiest supported capitalism break rule profit not unlike lot corporation china basically big corporation army back boarder smaller powerful corporation capitalism market force china now joseph hall ","m_szGeo1":"China","m_szSourceType":"source_news","m_szSrcUrl":"http://cleantechnica.com/2014/07/16/chinese-solar-stocks-surge-wto-ruling-us-imposed-tariffs/?utm_source=feedburner&utm_medium=feed&utm_campaign=Feed%3A+IM-cleantechnica+%28CleanTechnica%29","m_Places":["Washington","Germany","Free City","Dortmund","Ussr","Usa","Cuba"],"m_People":["James Ayre","Trina Solar","Jinko Solar","Michael Froman","Joseph Hall"],"m_Companies":["World Trade Organization","Solarcity","Reuters","Astnide","Google","Us Government","Sounds","John Birch Society"],"m_BiGrams":["chinese solar","chinese government","joseph hall","trade war","solar panel","solar stock","panel manufacturer","central government"],"m_TriGrams":["solar panel manufacturer"],"m_SocialTags":[],"m_Topics":[],"m_Industry":[],"m_Technology":[],"m_BiCnt":[5,5,5,4,4,3,3,3],"m_TriCnt":[3],"m_iDocBodyWordCnt":637}
