{"m_szDocID":"147745","m_szDocTitle":"Sandia National Laboratories: News Releases  : Tech transfer awards salute innovation, commercialization at Sandia Labs","m_szYear":"2014","m_szDocSumamry":"August 14, 2014 Tech transfer awards salute innovation, commercialization at Sandia Labs ALBUQUERQUE, N.M. â€” Sandia National Laboratories won four regional awards from the Federal Laboratory Consortium (FLC) for its work to develop and commercialize innovative technologies. Mike Heroux of Sandia National Laboratories, co-lead of the Federal Laboratory Consortium award-winning Mantevo project, shows the code from the Mantevo miniapp MiniFE. (Photo by Randy Montoya) Click on the thumbnail for a high-resolution image. The FLC is a nationwide network of more than 300 members that provides the foru","m_szDocBody":"tech transfer award salute innovation commercialization sandia lab albuquerque sandia national laboratory won regional award federal laboratory consortium flc work develop commercialise innovative technology mike heroux sandia national laboratory colead federal laboratory consortium awardwinning mantevo project show code mantevo miniapp minife photo randy montoya thumbnail highresolution image flc nationwide network member forum develop strategy opportunity linking laboratory mission technology expertise marketplace region honoured mantevo software recently won r&d award excellence technology transfer nanostabilized enzymatic membrane capture notable technology development hfirst effort increase number fueling station hydrogen cell electric vehicle outstanding regional partnership involving sandia national renewable energy laboratory california fuel cell partnership california governor office business economic development california air resource board proud work technology development technology transfer partnership jackie kerby moore sandias manager technology economic development lab representative flc honoured recognised alongside partner work areas detail sandia winner nmsba helping hand small business small company county participated year nmsba publicprivate partnership sandia los alamos national laboratory state mexico connect small business owner scientist engineer provide technical assistance programme contract mexico manufacturing extension partnership university mexico management technology programme anderson school management arrowhead centre mexico state university mexico tech department management nmsba provided million worth assistance mexico small businesse year nmsba bringing small businesse scientist engineer sandia los alamos national laboratory year grateful principal investigator work mexicos small businesse kerby moore said implementing innovative ideas stimulating state economy nmsba created state legislature bring national laboratory technology expertise small businesse promoting economic development emphasis rural areas programme provided small company mexico county million worth research hour material job created retained result nmsba mantevo nextgeneration computing mantevo integrated collection small software programme miniapp model performance fullscale application yetrequire code fraction size designed improve highperformance computing mantevo project grew laboratory directed research development won r&d award pioneered miniapp concept mantevo suite integrated collection fullfeatured miniapp sandia brought mantevo miniapp made freely opensource software package major computer vendor dozen university research team mantevo design nextgeneration system tool work collaboration with otherslos alamos lawrence livermore national laboratoriesand santa clarabased nvidia corp changing rapidly computing industry computer scientist mike heroux sandia colead project richard barrett satisfying work impact design development computing system application capture emission bay electricitygenerating plant coalfired plant industrial activity generate carbon dioxide face environmental protection agency regulation limiting emission nanostabilized enzymatic membrane capture provide simple compact energyefficient approach capture conventional method process remove percent emitted gas mixture expected save coal industry billion year enzymatic membrane technology computational modelling design nanofabrication technique synthesise membrane thin narrow airtight liquid layer embedding enzyme convert gas soluble form liquidlayered membrane efficiently capture power plant flue gas researcher sandia university mexico partnered develop technology growing concern global warming caused greenhouse gas emission urgent efficient capture reuse application enhanced oil recovery sandia nanobiologist susan rempe gratifying recognised flc team effort provide solution capture work framework coal industry daniel dedrick sandia national laboratory hydrogen programme manager hfirst partner catherine dunwoody california fuel cell partnership working instal fueling station hydrogen fuel cell car photo juan contreras california fuel cell partnership thumbnail highresolution image hfirst place refuel hydrogen cell electric car hydrogen fuel cell vehicle continue roll increasing number infrastructure fueling expand well project launched department energy led sandia national renewable energy laboratory work support husa publicprivate partnership introduced doe industry stakeholder address challenge hydrogen infrastructure established fuel cell technology office office energy efficiency renewable energy hydrogen fueling infrastructure research station technology hfirst project draw existing emerging core ability national lab reduce cost time fueling station construction improve station availability reliability partner include agency state california widely regarded thenation epicentre zeroemission vehicle goal accelerate support widespread deployment hydrogen fuel cell electric vehicle toyota recently announced begin selling fuel cell vehicle general motor honda announced plan jointly develop hydrogen fuel cell car hyundai version california success hydrogen fuel cell electric vehicle largely depend station available including neighbourhood work driver easily refuel daniel dedrick hydrogen programme manager sandia hfirst road making happen quickly sandia national laboratory multiprogram laboratory operated sandia corporation wholly owned subsidiary lockheed martin corp department energy national nuclear security administration main facility albuquerque livermore calif sandia major r&d responsibility national security energy environmental technology economic competitiveness sandia new media contact nancy salem article sandia new release email ","m_szGeo1":"United States","m_szSourceType":"source_government","m_szSrcUrl":"https://share.sandia.gov/news/resources/news_releases/flc/","m_Places":["Albuquerque, N.m.","California","New Mexico","Los Alamos","Santa Clara","Toyota","Calif."],"m_People":["Sandia","Mike Heroux","Randy Montoya","Far West","Nano","Jackie Kerby Moore","Kerby Moore","Richard Barrett","Susan Rempe","Daniel Dedrick","Catherine Dunwoody","Juan Contreras","Honda","Nancy Salem"],"m_Companies":["Sandia National Laboratories","Nationwide","National Renewable Energy Laboratory","California Air Resources Board","Los Alamos National Laboratory","State Of New Mexico","University Of New Mexico","School Of Management","New Mexico State University","Los Alamos National Laboratories","Lawrence Livermore National Laboratories","Nvidia Corp","Environmental Protection Agency","State Of California","General Motors","Hyundai","Sandia Corporation","Lockheed Martin Corp","National Nuclear Security Administration"],"m_BiGrams":["fuel cell","national laboratory","sandia national","hydrogen fuel","cell electric","small businesse","enzymatic membrane","fueling station","electric vehicle","renewable energy","california fuel","cell partnership","economic development","university mexico"],"m_TriGrams":["hydrogen fuel cell","sandia national laboratory","cell electric vehicle","california fuel cell","fuel cell partnership"],"m_SocialTags":[],"m_Topics":[],"m_Industry":[],"m_Technology":[],"m_BiCnt":[10,7,6,5,4,4,3,3,3,3,3,3,3,3],"m_TriCnt":[5,4,3,3,3],"m_iDocBodyWordCnt":696}
