{"m_szDocID":"147810","m_szDocTitle":"Sandia National Laboratories: News Releases  : Electric Car Challenge sparks students’ STEM interest","m_szYear":"2014","m_szDocSumamry":"November 20, 2014 Electric Car Challenge sparks students’ STEM interest ALBUQUERQUE, N.M. — Aspiring automotive engineers from 27 middle schools across New Mexico will compete in the New Mexico Electric Car Challenge on Saturday, Nov. 22, from 9 a.m. to 3:30 p.m. at the Highland High School gymnasium in Albuquerque. Forty-six teams will participate in a race, a design competition and an optional oral presentation. Two McKinley Middle School students meet after school to design and build the model car they will race in this year’s New Mexico Electric Car Challenge on Nov. 22 at Albuquerque’s Hi","m_szDocBody":"electric car challenge spark student stem interest albuquerque aspiring automotive engineer middle school mexico compete mexico electric car challenge saturday nov highland school gymnasium albuquerque fortysix team participate race design competition optional oral presentation mckinley middle school student meet school design build model car race year mexico electric car challenge nov albuquerque highland school photo randy montoya thumbnail highresolution image mexico electric car challenge mexico hydrogen fuel challenge presented sandia national laboratory los alamos national laboratory lanl public service company mexico pnm albuquerque public school intel air force research laboratory afrl northrop grumman corp goal challenge science math concept student fun exciting way encourage team building stimulate creative thinking develop student writing presentation skill event introduce student engineering career student discover that engineering isnt answer dont expected amy tapia sandias manager community involvement registration team received lithiumion battery directcurrent motor power vehicle student received kit chassis wheel gear required use challenge encourage student experiment body style material improve car performance metre racetrack what new conference electric car challenge race award ceremony when event new conference start saturday nov where highland school gymnasium coal ave albuquerque who media representative rsvp steve sandoval los alamos national laboratory volunteer judge evaluate design innovation craftsmanship appearance rate student oral presentation katrina groth reliability engineer sandia judged challenge year returning year student start project toolkit evidence make bigger better theyve thought creatively logically improve started with said optional oral presentation student talk challenge faced design marketing batterypowered electric car student research understand electric car related national interest discuss learned process groth krystal irby science teacher mckinley middle school albuquerque coaching team year challenge team sixth seventhgrader team eighthgrader irby team work electric car week school make challenge priority benefit student approach challenge discover interest undeveloped talent capacity solve problem competition rise selfconfidence completed project raced presented design important opportunity student age said race involve qualifying run final headtohead elimination tournament trophy awarded race design presentation category winner receive trophy winning team school receive cash award mexico electric car challenge result collaboration commitment partner advance science technology engineering math stem programme opportunity schoolchildren major employer mexico including sandia lanl pnm afrl northrop grumman stem education mexico proclamation proclamation pledge increase number certified science math teacher increase school student proficiency mathematic improve college graduation rate stem field prepare generation stem educator partnership continue inspire cultivate curiosity student stem career option kurt steinhaus director community programme office lanl proclamation emphasise importance working grow meet workforce mexico sandia national laboratory multiprogram laboratory operated sandia corporation wholly owned subsidiary lockheed martin corp department energy national nuclear security administration main facility albuquerque livermore calif sandia major r&d responsibility national security energy environmental technology economic competitiveness sandia new media contact valerie larkin article sandia new release email ","m_szGeo1":"United States","m_szSourceType":"source_government","m_szSrcUrl":"https://share.sandia.gov/news/resources/news_releases/electric_car/","m_Places":["Albuquerque, N.m.","New Mexico","Albuquerque","Calif."],"m_People":["Randy Montoya","Amy Tapia","Sandia","Steve Sandoval","Katrina Groth","Groth","Krystal Irby","Irby","Kurt Steinhaus","Valerie Larkin"],"m_Companies":["Sandia National Laboratories","Los Alamos National Laboratory","Public Service Company Of New Mexico","Albuquerque Public Schools","Intel","Air Force Research Laboratory","Northrop Grumman Corp","Rsvp","Northrop Grumman","Sandia Corporation","Lockheed Martin Corp","National Nuclear Security Administration"],"m_BiGrams":["electric car","car challenge","mexico electric","national laboratory","middle school","highland school","oral presentation"],"m_TriGrams":["electric car challenge","mexico electric car"],"m_SocialTags":[],"m_Topics":[],"m_Industry":[],"m_Technology":[],"m_BiCnt":[9,6,4,4,3,3,3],"m_TriCnt":[6,3],"m_iDocBodyWordCnt":455}
