{"m_szDocID":"149059","m_szDocTitle":"ABB Measurement & Analytics - Analytical Measurement Products : Quotes, Address, Contact","m_szYear":"2016","m_szDocSumamry":"Home Home Articles News Directory Equipment Software Market Reports Experts Books Journals Blogs Podcasts Videos Events Courses News 3D Printing Adhesives and Sealants Aerospace Materials Aluminum / Aluminium Automotive Materials Biomaterials Building and Construction Business Ceramic Materials Chemistry Clean Technology Coatings and Thin Films Composites Control Systems Corrosion Crystallography Design and Innovation Electronics Energy Events Ferrous Alloys and Metals Fibers Fuel Cell Graphene Iron and Steel Materials Analysis Materials Processing Materials Research Materials Science Material","m_szDocBody":"home home article new directory equipment software market report expert book journal blog podcast videos event course new printing adhesive sealant aerospace material aluminium aluminium automotive material biomaterial building construction business ceramic material chemistry clean technology coating thin film composite control system corrosion crystallography design innovation electronic energy event ferrous alloy metal fibre fuel cell graphene iron steel material analysis material processing material research material science material testing mineral mining modelling simulation nanomaterial nanotechnology product nonferrous alloy metal packaging petrochemical photonic photovoltaic pittcon plastic polymer precious metal rubber elastomer semiconductor sustainable technology titanium tribology article latest article thought leader insight industry azojomo material material supplier application industry metal store equipment chemical analysis atomic absorption spectrometer aas atomic optical emission spectrometer oes benchtop nmr spectrometer electrochemical analysis electron paramagnetic resonance epr spectrometer elemental analyzer ftir accessory ftir spectrophotometer ftnir fourier transform spectrometer fuel lubricant testing gas analyzer gas chromatography gel permeation chromatography handheld raman analyzer handheld xrf analyzer ion chromatography liquid chromatography mass spectrometer nmr spectroscopy analyzer pharmaceutical analysis equipment raman spectrometer secondary ion mass spectrometry sim spectrometer spectroscopy accessory titrator vapour pressure measurement xray gamma ray detector xray diffractometer xray fluorescence analyzer xray optic xray photoelectron spectroscopy xps xrf spectrometer coating deposition atomic layer deposition system thermal evaporation equipment thin film deposition system coating testing adhesion tester coating thickness gauge coating film deposition consumable eddy current tester ellipsometer glossmeter thin film characterization system electrical property electrical property characterization equipment hall effect measurement system scanning kelvin probe seebeck coefficient measurement system vibrating sample magnetometer vsm zeta potential analyzer equipment testing calibration battery testing solar cell testing fixing fastener bonding fastener flow controller metre field flow fractionation equipment heat treatment ageing oven industrial furnace oven laboratory furnace kiln vacuum furnace laboratory process equipment controlled atmosphere processing environment cryogenic evaporator concentrator laboratory gas generator laboratory heating cooling apparatus laboratory testing sample preparation equipment laboratory water purification system mixer shaker pcb smt handling workstation scientific illumination light source vacuum pump material processing manufacturing printing equipment material accessory boring machine mill particle size reduction plastic processing equipment ultrasonic welding equipment mechanical testing automatic material testing machine biomaterial testing equipment brittleness tester civil engineering material testing equipment cutter grinder polisher drop weight testing machine durometer fatigue testing machine force gauge gauge hardness testing machine impact testing machine material characterization equipment pipe burst hydrostatic tester plastic rubber testing equipment portable hardness tester scratch tester tensile testing machine torque gauge gauge tribometer friction wear tester universal material testing machine microscope acoustic microscope atom probe atomic force microscope afm electron beam source fibre analyzer ion beam microscope metallurgical microscope microscopy accessory consumable optical microscope polarising microscope raman microscope sample preparation equipment scanning electrochemical microscope secm scanning electron microscope sem scanning probe microscope scanning transmission electron microscope stem stereo microscope transmission electron microscope tem nondestructive testing ndt coating thickness gauge gas analyzer handheld xrf analyzer laser micrometre measurement nondestructive testing ndt equipment portable hardness tester scientific cameras sheet board counter ultrasonic flaw detector xray scattering system saxs waxs optical inspection acoustic microscope borescope ccd cameras colorimeter electron multiplying charge coupled device emccd ellipsometer monochromator optical comparator optical noncontact profiler measurement polarimeter polariscope refractometer scientific cameras oven furnace kiln ageing oven industrial furnace oven laboratory furnace kiln physical property testing adhesion tester analytical test sieve borescope chemisorption analyzer civil engineering material testing equipment density metre diffusivity tester dynamic vapour sorption dvs environmental test chamber extensometer extruded profile measurement system ferrography flexometer goodrich flexometer fogging tester gas pycnometer gas solubility analyzer glossmeter laser micrometre measurement light scattering instrument melt flow index tester metal testing equipment moisture analyzer optical noncontact profiler measurement particle counter particle size analyzer permeameter pharmaceutical analysis equipment plasma processing equipment pore size analyzer profilometer pycnometer rheometer metrology tool sheet board counter shock vibration test system spectrophotometer surface area analyzer surface energy gas chromatograph thickness gauge gauge vapour sorption analyzer viscometer wafer mapping system water sorption analyzer zeta potential analyzer plasma processing plasma diagnostic tool plasma processing equipment process control extruded profile measurement system flow controller metre lubricant condition monitor process control system radiation detector testing geiger counter liquid scintillation counter multichannel analyzer proportional counter radio chemistry sensor detector data logger control system controller data logger gas detector level sensor moisture sensor temperature sensor thermocouple thermal analysis calorimeter differential scanning calorimeter dsc dilatometer flash analysis lfa melting point metre peltier thermostat temperature measurement equipment temperature retraction tester thermal analysis equipment thermal conductivity system thermomechanical analyzer tma product software market report book alloy aluminium asm handbook biomaterial ceramic chemical engineering chemistry clean technology coating composite condensed matter conference proceeding copper corrosion design elastomer electronic engineering fluid fuel cell glass glaze heat treatment instrumentation iron magnetism material processing material science material testing measurement science mechanic mem metallurgy metal microscopy nanotechnology optic photonic cell physic plastic polymer semiconductor soft matter spectroscopy steel thermodynamic thermoplastic titanium welding journal biomaterial ceramic material chemistry coating thin film composite corrosion crystallography energy material processing material science metal alloy mineral nanotechnology polymer solgel videos adhesive bonding axaa conference biomaterial carbon fibre future direction interview ceramic material coating composite material corrosion emc manchester ferrous alloy functional material gas chromatography graphene hard material temperature material iconn interview light alloy m&m phoenix arizona usa machining mass spectrometry material austceram material processing material science technology mst material science technology mst material testing characterisation metal casting foundry mrs fall meeting video interview mrs fall meeting mrs fall meeting mrs fall meeting video interview nanomaterial nonferrous alloy pittcon interview pittcon interview pittcon interview pittcon pittcon precious metal recycled sustainable material rubber elastomer spectrometer stainless steel structural material thermoplastic thermosetting polymer welding brazing course course event contact meet team term advertise browse bymaterialsapplicationsindustry advertise term sponsor trending material storey shapememory polymer react body heat hold promise medical application scientist demonstrate fabrication live tissue structure customdesigned printer harm health productivity caused led flicker cannabis oil extraction interview jame white york fashion week feature revolutionary printed dresse created stratasy threeasfour epfl scientist discover determine efficiency perovskite solar cell sponsor insight industry nondestructive ultrasonic flaw testing syncscan interview cindy zheng measuring preventing flicker led interview steven goetstouwer cannabis oil extraction interview jame white add company add company latest material article characterising organic inorganic metallic particle semiconductor structural chemical analyzer sem invia raman microscope analysing silicon carbide sic nondestructive ultrasonic flaw testing syncscan interview cindy zheng preparing unmounted ferrous steel minute planarmet planar grinder preparing surface treated steel sample minute planarmet planar grinder profile article new equipment videos request quote abb measurement analytic analytical measurement product rue pierreardouin qubec qubec canada email visit abb measurement analytic analytical measurement product website request quote information primary activity laboratory process analyzer manufacturer half century abb developed manufactured installed analyzer laboratory process industry company background abb leader power automation technology enable utility industry customer improve performance lowering environmental impact abb company operate country employ people process analytic abb capability embrace largest process emission laboratory analyzer portfolios world performing realtime analysis chemical composition physical property process sample stream abb advanced solution combine analyzer advanced process control process application knowledge improve process performance productivity capacity safety customer processe abb integrated analyzer system reduce cost increase reliability plantwide process analytic founded abb analytical measurement formerly bomem inc design manufacture market highperformance affordable ftir ftnir spectrometer turnkey analytical solution petroleum chemical life science semiconductor academic metallurgy oem industry spectroradiometer remote market abb capability encompass largest portfolios market laboratory atline process analyzer perform realtime analysis chemical composition physical property process sample stream abb advanced solution combine analyzer advanced process control data management process application knowledge improve operational performance productivity capacity safety industrial processe customer lowering environmental impact abb measurement analytic analytical measurement product article ftir insitu monitoring polyurethane synthesis related abb measurement analytic analytical measurement product new abb introduce taly asp sery refinery petrochemical process analyzer abb establishes leedcertified hightech measurement analytic facility quebec city abb laboratory germany achieve accreditation independent testing calibration gas analyzer abb announce partnership volvo codevelop electric hybrid buse terra charger abb pass european certification process abb announce mbch polyol analyzer abb produce video navigator sery analyzer water monitoring power plant archived abb measurement analytic analytical measurement product new abb announced strategic collaboration shenzhen byd daimler technology denise stanislawczyk operation manager abb receive women manufacturing step award los gatos research ultraportable trace gas analyzer environmental industrial application abb release white paper chemical injection well pipeline abb introduce touchscreen data recorder paperless process management minute combined charging system ccs abb abb complete acquisition los gatos research mountain view california world largest nationwide network fastcharging station built abb leaflet abb measurement product coriolismaster mass flowmeter installation maintenance cut abb flowmeter family abb launches terra multistandard fast charging station support range electric car abb launches cost effective fast charger americas market fibre optic based industrial ftnir analyzer abb generation infrared camera canadian force developed abb abb measurement analytic analytical measurement product videos abb measurement analytic analytical measurement product company presentation fourier transform infrared analysis system abb mbch ftnir oleochemical analyzer abb mbch ftnir chemical analyzer abb mbhp ftnir hydrocarbon analyzer abb mbrx analyzer insitu reaction monitoring abb abb measurement analytic analytical measurement product equipment process hydrogen analyzer polyol derivative analysis mbch ftnir solid analyzer mbch process ftnir analyzer taly asp sery abb taly asp wet bath monitoring analyzer abb ftpaph ftnir process multipoint analyzer abb mbch chemical laboratory analyzer abb mbch chemical laboratory analyzer abb mbch oleochemical laboratory analyzer abb mbrx insitu reaction monitor abb ftnir laboratory analyzer abb ftir laboratory analyzer abb home new article directory equipment software market report expert book journal blog podcast videos event course azomcom azonetwork owned operated azomcom limited copyright azomcom information service accordance term condition cooky continuing browse agreeing cooky here","m_szGeo1":"United Kingdom","m_szSourceType":"source_industry","m_szSrcUrl":"http://www.azom.com/suppliers.aspx?SupplierID=11919","m_Places":["Hall","Kilns","Boring","Surface Area","Manchester","Uk","United States","Printer","New York","Québec","Canada","Germany","Shenzhen","Mountain View, California","America","Bath"],"m_People":["Nir Fourier","Eddy Current","Perovskite Solar","Diffusivity Tester","Cindy Zheng","Steven Goetstouwers","Rue Pierre-ardouin","Nir Oleochemicals","Denise Stanislawczyk"],"m_Companies":["Plastics","Sec","Shakers","Particle","Plastic","Force Gages","Torque","Gages","Universal","Atom","Goodrich","Asm","Emc","M&m","Phoenix, Arizona","Stratasys","Add Company","Your Company","Particles","On Semiconductors","Planar","Abb","Abb Group","Bomem Inc","Volvo","Daimler New Technology Co., Ltd","Nationwide Network","Qa"],"m_BiGrams":["analyzer abb","measurement analytic","analytical measurement","measurement product","analytic analytical","material testing","testing machine","abb measurement","laboratory analyzer","material processing","material science","testing equipment","abb mbch","thin film","processing material","gas analyzer","measurement system","process control","software market","market report","ceramic material","control system","analysis equipment","thickness gauge","furnace kiln","laboratory process","processing equipment","electron microscope","ultrasonic flaw","physical property","plasma processing","pittcon interview","interview pittcon","process analyzer","taly asp","mbch ftnir"],"m_TriGrams":["measurement analytic analytical","analytic analytical measurement","analytical measurement product","abb measurement analytic","laboratory analyzer abb","analyzer abb mbch","software market report"],"m_SocialTags":[],"m_Topics":[],"m_Industry":[],"m_Technology":[],"m_BiCnt":[14,9,9,9,8,7,7,7,6,5,5,5,5,4,4,4,4,4,3,3,3,3,3,3,3,3,3,3,3,3,3,3,3,3,3,3],"m_TriCnt":[8,8,8,6,5,4,3],"m_iDocBodyWordCnt":1600}
