{"m_szDocID":"153631","m_szDocTitle":"Materials news, April 2014 - Materials Today","m_szYear":"2014","m_szDocSumamry":"Our website uses cookies Cookies enable us to provide the best experience possible and help us understand how visitors use our website. By browsing Materials Today, you agree to our use of cookies. Okay, I understand Learn more Log in / Sign up MT PLUS 中文版 Contacts Advertising About   Select topic Materials Science Amorphous materials Biomaterials Carbon Characterization Composites Computation and theory Crystalline materials Electronic properties Energy Materials chemistry Mechanical properties Metals and alloys Nanomaterials Optical materials Polymers and soft materials Surface science Reinf","m_szDocBody":"website cooky cooky enable provide experience understand visitor website browsing material today agree cooky okay understand learn log contact advertising select topic material science amorphous material biomaterial carbon characterization composite computation theory crystalline material electronic property energy material chemistry mechanical property metal alloy nanomaterial optical material polymer soft material surface science reinforced plastic carbon fibre composite application composite industry composite part composite processing metal powder report additive manufacturing hardmetal ceramic metal finishing metal industry metal processing moulding pressing powder application topic new home new article webinar comment feature podcast product event job journal home new material new new archive airtech introduce vacuum gauge mark holme comment lpw technology present research recycling powder comment composite evolution appoint distributor mark holme comment proto lab open manufacturing facility comment novainstitute composite europe collaborate biobased composite amanda jacob comment guide setting aluminium powder plant comment spaser david bradley comment diamond put shine nanoresonator cordelia sealy comment composite launching composite assured practitioner cap scheme mark holme comment ati result comment chair lightweight engineering polymer technology appointed technische universitt dresden mark holme comment formax instal multiaxial machine dedicated volume automotive application mark holme comment carpenter result comment huntsman rtm system aid research composite cryogenic storage liquid hydrogen mark holme comment impurity interesting impact superconductor efficiency nina notman comment proto lab acquire printer comment cuag alloy wear cordelia sealy comment week top reinforced plastic storey agy glass reinforcement manufacturing thermoset composite boeing airbus amanda jacob comment cloaked dna nanodevice survive pilot mission comment hardide coating invest pretreatment comment producing highquality graphene large quantity laurie donaldson comment catia composite design application assist bmw electric car mark holme comment union process earn iso comment dolphitech launches ndt software mark holme comment basf showcase china comment nanomaterial outsmart ion comment nanosphere omnidirectional solar cell laurie winkless comment atk secure contract united launch alliance composite launch vehicle structure mark holme comment faruk establishes demonstration manufacturing facility mark holme comment heat resistant nanostructure rna comment sandvik coromant named partner year comment creative pultrusion market manufacture transonite panel system mark holme comment plastic fantastic bridge data storage transmission david bradley comment arc launches online quoting system printing comment hexagon composite win lpg cylinder order iraq amanda jacob comment airborne oil gas win order onesubsea mark holme comment arc acquire magnesium injection moulder comment hexagon composite awarded major order qatar mark holme comment hitachi chemical absorb subsidiary comment vascular system selfhealing composite material laurie donaldson comment feng xinde polymer prize winner announced laurie donaldson comment carbon nanotube supercapacitor portable electronic laurie winkless comment composite repair amanda jacob comment week top reinforced plastic storey amanda jacob comment tech specific deposition tungsten nanoparticle comment world titanium production exceed million tonne comment sme announce manager printing comment metaldyne win supplier award comment latest ctruk wind farm vessel designed work offshore amanda jacob comment skf quarter report comment samsung pattern energy complete canadas largest wind project reg tucker comment effect processing nanocarrier drug delivery comment ultrafast snapshot lightdriven superconductivity comment union process make attritor grinding alumina comment composite manufacture part ferno patient transfer system amanda jacob comment nanocrystalline cellulose viral inhibitor comment exciton observed action time comment stratasy move metal arena comment lanxess econcore partner thermoplastic sandwich structure amanda jacob comment element hitchin develop flawdetecting equipment thermoplastic composite pipe amanda jacob comment canadian facility produce graphene powder printing comment miba triple size china comment auckland harbour bridge await composite skypath amanda jacob comment malaysian event focus advanced material comment tencate advanced composite performance polymer solution partner aerospace material amanda jacob comment comb light accelerate communication comment tunable semiconductor solar cell comment gurit see good start amanda jacob comment ceratizit buy carbide tool producer comment gkn acquire manufacturer energy storage system comment week top reinforced plastic storey amanda jacob comment alstom bfg france wind turbine manufacturing deal reg tucker comment hutchinson launches composite technical centre mark holme comment industry veteran join picodeon ceo comment manipulating light invisible range comment sunlight generate hydrogen porous silicon comment airtech introduce wrightlease mark holme comment march top metal powder storey comment biocomposite technology overview amanda jacob comment gkn named premium supplier schaeffler continental comment paradigm unconventional superconductor comment synthetic collagen promote natural clotting comment automotive consortium target material intelligence mark holme comment arburg retire comment attwater reach upgrade mark holme comment gel promote bone growth comment proto lab launches quickturn mim process comment composite germany join eucia mark holme comment kennametal ceo call understanding manufacturing comment aniform suite officially launched mark holme comment starck challenging year strong growth comment optomec printing repair comment bct introduce automated option composite repair mark holme comment safran albany inaugurate plant composite aircraft engine part amanda jacob comment cover printing material comment voetsch develop air tempering oven carbon fibre aviation part mark holme comment optical diode enhance information processing comment hydrogenbond hinge moving gear comment pew report offshore wind propelled clean energy investment growth reg tucker comment mitsubishi material aim dominate hardmetal market comment week top reinforced plastic storey amanda jacob comment airtech introduce airflex mark holme comment dieffenbacher introduce compress lite mark holme comment bridging led green gap comment ozone sensor comment printing market grow billion comment dow introduce polyurethane sery infrastucture mark holme comment mpif reveal special interest programme comment composite firm airborne establishes legal presence france tidal energy aspiration amanda jacob comment harper awarded contract carbon fibre production system mark holme comment lightheated water deliver drug polymeric particle comment wto rule china rare earth export restriction comment john manville introduce chopped strand glass fibre mark holme comment pyrogenesis metal powder system agreement comment mhi vestas offshore wind operational amanda jacob comment owen corning introduce roving fabric wind turbine rotor blade mark holme comment laser printing make ear implant comment markos increase wind turbine nacelle production mark holme comment cremer gmbh acquire german furnace manufacturer comment bayer sell carbon nanotube patent futurecarbon amanda jacob comment morgan composite defence system appoint business development director mark holme comment magnetic mim part improve generator efficiency comment borealis borouge tailor fibremod jaguar ftype mark holme comment nanoworld comment phononic crystal altered real time comment top material new zara preston comment ati rename business unit comment march top reinforced plastic storey amanda jacob comment new archive connect viewed new lpw begin plasma spheroidization powder metal comment new youre invited submit material science research heliyon comment new selfcleaning gecko feet inspire micromanipulator cordelia sealy comment new growing singlecrystal graphene fast cordelia sealy comment new graphene think box cordelia sealy comment what coming lightweight vehicle manufacturing joining forming focus detroit usa functional oxide thin film advanced energy information technology conference cancn mexico featured event ecobio rotterdam netherland international symposium advanced plasma science application nitride nanomaterial nagoya japan material today material today community dedicated creation sharing material science knowledge experience supported elsevier publish impact peerreviewed journal organise academic conference broadcast educational webinar more material today meet team advertise contact hear you support creation sharing information arent doing better know grow comment ideas contact feed privacy policy term condition cooky map copyright elsevier ltd right reserved website designed intuitiv","m_szGeo1":"","m_szSourceType":"source_industry","m_szSrcUrl":"http://www.materialstoday.com/news/2014-04/","m_Places":["United States","Europe","Uk","China","Iraq","Qatar","Hitachi","Canada","Auckland","Combs","Germany","Albany","France","Harper","Vestas","Preston","Most","Mexico","Japan"],"m_People":["April 2014nina Notman","Feng Xinde","Bfg France","H.c. Starck"],"m_Companies":["Plastics","Lpw Technology","Proto Labs Inc","Sealy","Ati","Technische Universität Dresden","Huntsman","Agy","Boeing","Airbus","Donaldson","Bmw","I3","Iso","United","Alliance","Sandvik","Plastic","Arc Group","Metaldyne","Skf","Samsung","Stratasys","Lanxess","Alstom","Continental","Arburg","Kennametal","Hinges","Gap","Wto","Johns Manville","Owens Corning","Cremer Gmbh","Jaguar","Phononic","Elsevier","Elsevier Ltd."],"m_BiGrams":["mark holme","holme comment","amanda jacob","jacob comment","reinforced plastic","comment composite","cordelia sealy","sealy comment","top reinforced","plastic storey","comment new","material today","comment week","week top","storey amanda","material science","carbon fibre","metal powder","airtech introduce","comment proto","proto lab","laurie donaldson","donaldson comment","printing comment","reg tucker","tucker comment","wind turbine"],"m_TriGrams":["mark holme comment","amanda jacob comment","cordelia sealy comment","top reinforced plastic","reinforced plastic storey","comment week top","week top reinforced","plastic storey amanda","storey amanda jacob","comment proto lab","laurie donaldson comment","reg tucker comment"],"m_SocialTags":[],"m_Topics":[],"m_Industry":[],"m_Technology":[],"m_BiCnt":[30,30,20,20,6,6,5,5,5,5,5,4,4,4,4,3,3,3,3,3,3,3,3,3,3,3,3],"m_TriCnt":[30,20,5,5,5,4,4,4,4,3,3,3],"m_iDocBodyWordCnt":1163}
