{"m_szDocID":"153643","m_szDocTitle":"Materials news, August 2013 - Materials Today","m_szYear":"2013","m_szDocSumamry":"Our website uses cookies Cookies enable us to provide the best experience possible and help us understand how visitors use our website. By browsing Materials Today, you agree to our use of cookies. Okay, I understand Learn more Log in / Sign up MT PLUS 中文版 Contacts Advertising About   Select topic Materials Science Amorphous materials Biomaterials Carbon Characterization Composites Computation and theory Crystalline materials Electronic properties Energy Materials chemistry Mechanical properties Metals and alloys Nanomaterials Optical materials Polymers and soft materials Surface science Reinf","m_szDocBody":"website cooky cooky enable provide experience understand visitor website browsing material today agree cooky okay understand learn log contact advertising select topic material science amorphous material biomaterial carbon characterization composite computation theory crystalline material electronic property energy material chemistry mechanical property metal alloy nanomaterial optical material polymer soft material surface science reinforced plastic carbon fibre composite application composite industry composite part composite processing metal powder report additive manufacturing hardmetal ceramic metal finishing metal industry metal processing moulding pressing powder application topic new home new article webinar comment feature podcast product event job journal home new material new new archive macdermid add raymond tinnerman network zinklad applicator metal finishing comment fundamental sizedependence nanocrystal undergoing phase transition comment core moulding technology introduce airilite low density smc amanda jacob comment blue suit crew seek perfect paint finish metal finishing comment building nanotube specific predictable atomic structure comment polymer help medication reach bloodstream comment toho tenax carbon fibre manufacture solar car amanda jacob comment washington bridge fitted composite advantage fiberspan deck amanda jacob comment thomas hartmann appointed managing director basf coating gmbh metal finishing comment akzonobel name head integrated supply chain reg tucker comment liquid calcium carbonate comment ultrathin carbon membrane comment boeing roll dreamliner amanda jacob comment system expand portfolio comment exone build german plant comment metaldyne earn regional ranking comment aviation start testing gex composite fan blade amanda jacob comment ceo pmg indiana comment sandvik participate global compact comment north american tungsten result comment arcelormittal zenica finalise sinter project comment sifco asc achieve nadcap approval chemical processing metal finishing comment decc make annual list nation fastestgrowing private companiesagain metal finishing comment laserlike xray light solid comment gold standard cell penetration comment solid concept produce inconel part aerospace comment exone print bonded tungsten comment funding laser sintering comment composite europe industry challenge amanda jacob comment walter surface technology inaugurate million campus biocircle facility metal finishing comment matrix composite deliver wind tunnel turbine blade spacer air force amanda jacob comment week top reinforced plastic storey amanda jacob comment vestas receive order ukraine comment sherwinwilliam supplying protective coating massive cleveland innerbelt bridge project metal finishing comment hentzen coating celebrate year business metal finishing comment michael cash head axalta industrial coating businesse metal finishing comment solar sponge comment plasmatreated nano philtre comment brazil approve wind farm comment system acquire crdm comment call paper comment carbon nanotube thermoplastic amanda jacob comment sherwinwilliam add epoxy aerosol primer military heavy equipment application metal finishing comment reis robotic deliver preform system carbon fibre composite amanda jacob comment graphene comment strange state light comment ctruk develop thor composite multipurpose military vessel amanda jacob comment technic lynn michaelson phd upcoming ipc conference component technology metal finishing comment chromalloy announce honeywell agreement aircraft engine system service metal finishing comment graphene nanoscroll comment tying knot liquid crystal comment ccais finishing pavilion conference fabtech break record metal finishing comment emea wind power market set contract amanda jacob comment gkn build comment sigma lab moved metal based comment composite europe industry challenge amanda jacob comment dynamic liquid metal particle nanoscale comment rechargeable flow battery comment dong university research reducing offshore cost comment abaris complete composite training british airway airbus amanda jacob comment acma manufacturing institute partner address skill gap amanda jacob comment mvp distribution amanda jacob comment week top reinforced plastic storey thermoplastic wind turbine blade industry challenge amanda jacob comment enthone publishes osp performance guide metal finshing comment tpi composite produce nordex wind turbine blade turkey amanda jacob comment superconducting wire unprecedented performance comment copper doping improve thinfilm photovoltaic comment composite europe industry challenge amanda jacob comment industrial production hold metal finishing comment axson acquire cass polymer amanda jacob comment axalta expand coating technology centre metal finishing comment build resistive memory device comment asymmetry topological insulator comment quickstep target auto industry automated rst process carbon fibre part amanda jacob comment zoltek report quarter loss amanda jacob comment osborn expand california facility metal finishing comment material biobased hydrogen synthesis comment twist graphene storey comment ppg china laboratory win certification amanda jacob comment ikea buy irish wind farm gail rajgor comment composite europe industry challenge amanda jacob comment winona powder coating expand etna green indiana facility metal finishing comment osha niosh hazard alert bromopropane metal finishing comment valspar complete acquisition inver metal finishing comment signature captured piezophototronic led comment magnum venus plastech cease business operation amanda jacob comment week top reinforced plastic storey oil gas pipe zoltek carbon fibre lamborghini repair amanda jacob comment blog biggest challenge facing composite industry today amanda jacob comment class solid comment ultraversatile raman laser comment seaenergy rgu improve offshore wind lifecycle cost comment oak ridge national laboratory combine foam powder comment carpenter introduce stainless steel swissstyle screw machine comment lighter material key meeting auto regulation comment molycorp financial show slight decrease comment hexcel report strong quarter result amanda jacob comment metokote revamp website metal finishing comment technique study radiation damage comment cobalt make solar cell sustainable comment grolman distribute inchem phenoxy resin europe amanda jacob comment ati financial affected challenging condition comment timken consider separation steel business comment general moly report increased loss comment basf miner win georgia award comment guest blog bmw trailblazing composite electric car amanda jacob comment proposed astm metal corrosion standard test potential coating sewer environment metal finishing comment hydrogel robotic comment brunswick sell hatteras cabo boat brand amanda jacob comment crystal colour comment wind energy pricing alltime low comment unitech composite qualify airbus supplier amanda jacob comment western coating symposium kick oct las vegas metal finishing comment abakan announce incorporation mesocoat coating service inc metal finishing comment airbus military deliver french air force amanda jacob comment titanium europe technical paper comment carpenter technology announce solid fourth quarter comment rio tinto sell copper mine china moly comment titanium growth prospect good comment kennametal seal emura deal comment gasbarre expand staff comment alloy steel international ceo comment nanosteel prove potential lightweight steel comment image single stationary len comment mini mona lisa comment zoltek panex carbon fibre meet automotive industry frost sullivan amanda jacob comment donald moeller territory sale manager metal finishing passe metal finishing comment ppg reinstate coraflon brand feve architectural powder coating metal finishing comment american coating submit comment utah proposed aim rule metal finishing comment nonthermal plasma technique inexpensive solar cell comment understanding interface property pave graphene application comment plasmonic black metal solar energy comment ashland supply derakane resin russian lpg cylinder production plant amanda jacob comment cent increase renewable energy comment week top reinforced plastic storey lamborghini azl bmw amanda jacob comment powder metallurgy india hold pim workshop reg tucker comment lamborghinis flying doctor care carbon fibre repair amanda jacob comment spatial composite solution win contract south east asia amanda jacob comment sifco asc launches brand identity website metal finishing comment top material new zara preston comment nanosensor detect numerous protein simultaneously comment astm distribute standard award comment acma sampe show camx composite advanced material expo amanda jacob comment month top reinforced plastic storey thermoplastic pipe volkswagen bombardier csery amanda jacob comment new archive connect viewed new lpw begin plasma spheroidization powder metal comment new youre invited submit material science research heliyon comment new selfcleaning gecko feet inspire micromanipulator cordelia sealy comment new growing singlecrystal graphene fast cordelia sealy comment new graphene think box cordelia sealy comment what coming lightweight vehicle manufacturing joining forming focus detroit usa functional oxide thin film advanced energy information technology conference cancn mexico featured event ecobio rotterdam netherland international symposium advanced plasma science application nitride nanomaterial nagoya japan material today material today community dedicated creation sharing material science knowledge experience supported elsevier publish impact peerreviewed journal organise academic conference broadcast educational webinar more material today meet team advertise contact hear you support creation sharing information arent doing better know grow comment ideas contact feed privacy policy term condition cooky map copyright elsevier ltd right reserved website designed intuitiv","m_szGeo1":"","m_szSourceType":"source_industry","m_szSrcUrl":"http://www.materialstoday.com/news/2013-08/","m_Places":["United States","Washington Dc","Zenica","Uk","Europe","Vestas","Ukraine","Brazil","Turkey","Axson","Cass","China","Winona","Etna","Indiana","Georgia","Cabo","Las Vegas","Abakan","Brand","Utah","South East Asia","Preston","Most","Mexico","Japan"],"m_People":["Raymond Tinnerman","Thomas Hartmann","Pmg Indiana","Lynn Michaelson","Mona Lisa","Donald Moeller"],"m_Companies":["Plastics","Toho","Basf Coatings Gmbh","Akzonobel","Boeing","Metaldyne","Ge Aviation","Sandvik","Un","Arcelormittal","Surface Technologies","Matrix","Us Air Force","Sherwin-williams","Sigma","British Airways","Airbus Uk","Manufacturing Institute","Gap","Tpi Composites","Ikea","Valspar","Inver Group","Lamborghini","Oak Ridge National Laboratory","Ati","Timken","General Moly","Bmw","I3","Brunswick","Unitech","Mesocoat Coating Services Inc.","Airbus","French Air Force","Carpenter Technology","Rio Tinto","Kennametal","Frost & Sullivan","American Coatings Association Submits","Ashland","Metallurgy Association Of India","Volkswagen","Sealy","Elsevier","Elsevier Ltd."],"m_BiGrams":["amanda jacob","jacob comment","metal finishing","finishing comment","carbon fibre","reinforced plastic","industry challenge","challenge amanda","top reinforced","plastic storey","comment new","material today","comment composite","composite europe","europe industry","comment week","week top","material science","facility metal","turbine blade","cordelia sealy","sealy comment"],"m_TriGrams":["amanda jacob comment","metal finishing comment","industry challenge amanda","challenge amanda jacob","top reinforced plastic","reinforced plastic storey","comment composite europe","composite europe industry","europe industry challenge","comment week top","week top reinforced","facility metal finishing","jacob comment week","cordelia sealy comment"],"m_SocialTags":[],"m_Topics":[],"m_Industry":[],"m_Technology":[],"m_BiCnt":[40,40,29,27,7,6,5,5,5,5,5,4,4,4,4,4,4,3,3,3,3,3],"m_TriCnt":[40,27,5,5,5,5,4,4,4,4,4,3,3,3],"m_iDocBodyWordCnt":1297}
