{"m_szDocID":"153692","m_szDocTitle":"Materials news, September 2011 - Materials Today","m_szYear":"2011","m_szDocSumamry":"Our website uses cookies Cookies enable us to provide the best experience possible and help us understand how visitors use our website. By browsing Materials Today, you agree to our use of cookies. Okay, I understand Learn more Log in / Sign up MT PLUS 中文版 Contacts Advertising About   Select topic Materials Science Amorphous materials Biomaterials Carbon Characterization Composites Computation and theory Crystalline materials Electronic properties Energy Materials chemistry Mechanical properties Metals and alloys Nanomaterials Optical materials Polymers and soft materials Surface science Reinf","m_szDocBody":"website cooky cooky enable provide experience understand visitor website browsing material today agree cooky okay understand learn log contact advertising select topic material science amorphous material biomaterial carbon characterization composite computation theory crystalline material electronic property energy material chemistry mechanical property metal alloy nanomaterial optical material polymer soft material surface science reinforced plastic carbon fibre composite application composite industry composite part composite processing metal powder report additive manufacturing hardmetal ceramic metal finishing metal industry metal processing moulding pressing powder application topic new home new article webinar comment feature podcast product event job journal home new material new new archive energy composite ssp enter wind turbine blade partnership kari williamson comment foam injection varicose vein comment redefining kilogramme ampere comment latin american composite material established amanda jacob comment cutting offshore wind cost kari williamson comment epa release final health assessment tce metal finishing comment sinovel deliver wind turbine brazil kari williamson comment improving quality graphene comment unusual quasiparticle trilayer graphene comment york invest usm renewable energy project kari williamson comment technic engineered powder complete analytical laboratory renovation metal finishing comment scientist turn back clock adult stem cell ageing comment close microbial vaccination programme comment microwave oven key energy production wasted heat comment teijin aramid introduce black twaron fibre amanda jacob comment incertec expand custom plating operation mexico metal finishing comment boeing ana celebrate dreamliner delivery metal finishing comment financing secured anholt offshore wind farm kari williamson comment nanoparticle design cancer therapy comment lamborghini produce sesto elemento amanda jacob comment elg acquire recycled carbon fibre amanda jacob comment exploring structure smallest crystal comment lithiumion battery comment week top storey amanda jacob comment lisa airplane launches akoya light aircraft amanda jacob comment fabricator metalformer keen fourthquarter outlook reg tucker comment rick holland columbia chemical announce retirement metal finishing comment ppg hold premiere electrocoat conference china metal finishing comment university western ontario fraunhofer team composite research centre amanda jacob comment amsc accuse sinovel theft breach contract kari williamson comment uks public hydrogen refuelling station open honda facility swindon steve barrett comment redefinition kelvin comment vacuumlike device make cellular exploration easier comment tsc open virgin galactic spaceship build facility amanda jacob comment hampson showcase advanced composite structure aviation expo china amanda jacob comment composite offer benefit modular housing design amanda jacob comment chinas fastgrowing industry park opportunity seized kari williamson comment protonbased transistor comment key gene cooperate make healthy skin comment gurit establishes engineered structure business unit amanda jacob comment wireless solar power kari williamson comment team develop breakthrough technology identification prostate cancer cell comment scientist solve longstanding plant biochemistry mystery comment reichhold announce gelcoat price increase europe amanda jacob comment composite europe set exhibitor record amanda jacob comment volkswagen name metokote service part coater choice metal finishing comment expert shine light detection bacterial infection comment xwb wing lower cover delivered amanda jacob comment mem device generate energy small vibration comment biochemical cell signal quantified time comment week top storey amanda jacob comment rwe innogy open italian wind farm kari williamson comment iit showcase milling technology composite engineering show amanda jacob comment wind produce record amount electricity kari williamson comment serfilco announce management metal finishing comment sabic join automotive innovation joint venture inpro amanda jacob comment electronic bucket brigade boost solar cell voltage comment synthesis chromosome arm scratch comment tackling wake effect wind turbine kari williamson comment formtech composite bae system collaborate military project amanda jacob comment cancerkilling cell detail comment industrial production percent metal finishing comment gamesa wind sweden kari williamson comment composite solar roofing offer lower installation cost amanda jacob comment global prepreg market reach amanda jacob comment stable rna nanoscaffold virus core comment uks inspirational technician comment crashsafe composite battery housing electric car amanda jacob comment dow coating name west coast sale manager metal finishing comment lockheed martin groundbreaking cryogenic titanium machining process metal finishing comment prototek sheet metal fabrication expand capability metal finishing comment controlling stem cell form determine fate comment good wind europe kari williamson comment sphigh modulus introduce pvcell gfoam marine core amanda jacob comment pedalpowered composite boat project torpedalo amanda jacob comment bmw recruiting personnel work future technology amanda jacob comment safe storage rock comment metyx composite announce tooling centre amanda jacob comment basf establishes lightweight composite team automotive industry amanda jacob comment reach gathering brussel richard felton comment miba sale profit stagnate richard felton comment multilayer analysis thin film richard felton comment machine tool sale pace exceed forecast metal finishing comment boost liion technology richard felton comment ferroelectric pave ultralow power computing comment spin pumping effect proven time comment gurit report half result amanda jacob comment nordex instal wind romania kari williamson comment oxford instrument plc enter ftse comment critical similarity stem cell comment week top storey amanda jacob comment move freeman richard felton comment caterpillar prefer ppg metal finishing comment ahlstrom start cooperation negotiation karhula mikkeli plant amanda jacob comment doe usm geothermal technology development kari williamson comment seaweed polymer electrode comment pledge usm spur offshore wind kari williamson comment richmond aerovac open liaison office india amanda jacob comment method growing synthetic collagen comment ashland acquire isp comment tungsten corp file improved result comment carpenter plan build facility aerospace energy product comment sandvik strategy developed improve company position comment henkel pur adhesive speed wind turbine blade bonding amanda jacob comment acma propose ansi standard pultruded frp structure amanda jacob comment nanosensor made dna light path cancer test drug comment owen corning showcase composite technology china composite expo amanda jacob comment sale china rise percent metal finishing comment pmi index dip metal finishing comment profiler cellular level comment nanocable light future comment owen corning plan opening china composite centre amanda jacob comment beagle technology complete upgrade amanda jacob comment gerber launches gerbercutter china composite expo amanda jacob comment yorkbased trojan powder coating open facility sarasota fla metal finishing comment light graphene metamaterial comment acg present defence portfolio dsei amanda jacob comment composite core material launches airex amanda jacob comment automated dynamic test laser heating fibre placement composite material amanda jacob comment detecting fluorescent twist comment code win hungarian sailing race amanda jacob comment doe award usm solar technology kari williamson comment artificial biomineral comment cooking cell comment lanxess invest antwerp glass fibre plant amanda jacob comment renewable energy financing hit political uncertainty financial woe kari williamson comment bmw sgl joint venture open carbon fibre plant amanda jacob comment scientist observe smallest atomic displacement comment magnetic carbon comment week top storey amanda jacob comment mecmesin introduce testing system composite engineering show amanda jacob comment norplexmicarta introduce wavemax solder pallet material amanda jacob comment insituform technology acquire north american business fyfe amanda jacob comment inexpensive technique quality nanowire solar cell comment researcher create retinas jello comment nanocomposite film cvd comment month top storey amanda jacob comment brazilian wind power rise kari williamson comment scott bader exhibit speciality product china composite expo amanda jacob comment chromalloy name zmyndak director operation metal finishing comment brittleness ageing bone comment iron vein comment point comment wind power forecast downgraded kari williamson comment pilot line lithiumion battery comment mim market reach billion comment cabot sell tantalum business million comment epma club project comment molycorp make rare earth supply agreement hitachi metal comment cdi launches tip programme china composite expo amanda jacob comment new archive connect viewed new lpw begin plasma spheroidization powder metal comment new youre invited submit material science research heliyon comment new selfcleaning gecko feet inspire micromanipulator cordelia sealy comment new growing singlecrystal graphene fast cordelia sealy comment new graphene think box cordelia sealy comment what coming lightweight vehicle manufacturing joining forming focus detroit usa functional oxide thin film advanced energy information technology conference cancn mexico featured event ecobio rotterdam netherland international symposium advanced plasma science application nitride nanomaterial nagoya japan material today material today community dedicated creation sharing material science knowledge experience supported elsevier publish impact peerreviewed journal organise academic conference broadcast educational webinar more material today meet team advertise contact hear you support creation sharing information arent doing better know grow comment ideas contact feed privacy policy term condition cooky map copyright elsevier ltd right reserved website designed intuitiv","m_szGeo1":"","m_szSourceType":"source_industry","m_szSrcUrl":"http://www.materialstoday.com/news/2011-09/","m_Places":["United States","Brazil","New York","Mexico","Anholt","Outlook","Columbia","China","Uk","Swindon","Europe","Sweden","Most","Brussels","Felton","Romania","India","Antwerp","Atmosphere","Hitachi","Japan"],"m_People":["Boeing, Ana","Rick Holland","Na Tungsten Corp","Scott Bader"],"m_Companies":["Plastics","Epa","Lamborghini","Recycled Carbon Fibre Ltd","University Of Western Ontario","Virgin Galactic","Volkswagen","Iit Showcases","Bae Systems","Lockheed Martin","Sp","Bmw","Oxford Instruments Plc","Caterpillar","Ahlstrom","Seaweed","Ashland","Sandvik","Henkel","Frp","Path","Owens Corning Showcases","Pmi","Owens Corning","Technology Group","Gerber","Lanxess","Insituform Technologies","Fyfe Group","Cabot","Cdi","Sealy","Elsevier","Elsevier Ltd."],"m_BiGrams":["amanda jacob","jacob comment","kari williamson","williamson comment","metal finishing","finishing comment","top storey","storey amanda","richard felton","felton comment","china composite","comment new","material today","wind turbine","comment week","week top","comment composite","cell comment","composite expo","expo amanda","material science","carbon fibre","offshore wind","comment scientist","stem cell","centre amanda","plant amanda","cordelia sealy","sealy comment"],"m_TriGrams":["amanda jacob comment","kari williamson comment","metal finishing comment","top storey amanda","storey amanda jacob","richard felton comment","comment week top","week top storey","china composite expo","composite expo amanda","expo amanda jacob","centre amanda jacob","jacob comment composite","plant amanda jacob","cordelia sealy comment"],"m_SocialTags":[],"m_Topics":[],"m_Industry":[],"m_Technology":[],"m_BiCnt":[49,49,20,20,19,18,5,5,5,5,5,5,4,4,4,4,4,4,4,4,3,3,3,3,3,3,3,3,3],"m_TriCnt":[49,20,18,5,5,5,4,4,4,4,4,3,3,3,3],"m_iDocBodyWordCnt":1338}
