{"m_szDocID":"153713","m_szDocTitle":"Materials news, August 2010 - Materials Today","m_szYear":"2010","m_szDocSumamry":"Our website uses cookies Cookies enable us to provide the best experience possible and help us understand how visitors use our website. By browsing Materials Today, you agree to our use of cookies. Okay, I understand Learn more Log in / Sign up MT PLUS 中文版 Contacts Advertising About   Select topic Materials Science Amorphous materials Biomaterials Carbon Characterization Composites Computation and theory Crystalline materials Electronic properties Energy Materials chemistry Mechanical properties Metals and alloys Nanomaterials Optical materials Polymers and soft materials Surface science Reinf","m_szDocBody":"website cooky cooky enable provide experience understand visitor website browsing material today agree cooky okay understand learn log contact advertising select topic material science amorphous material biomaterial carbon characterization composite computation theory crystalline material electronic property energy material chemistry mechanical property metal alloy nanomaterial optical material polymer soft material surface science reinforced plastic carbon fibre composite application composite industry composite part composite processing metal powder report additive manufacturing hardmetal ceramic metal finishing metal industry metal processing moulding pressing powder application topic new home new article webinar comment feature podcast product event job journal home new material new new archive zyvax partner frp service china amanda jacob comment million composite programme australia amanda jacob comment pne wind complete repowering project kari williamson comment airbus start green flight trial amanda jacob comment shell cosan sugarcane ethanol kari williamson comment gurit inaugurate red maple blade tooling amanda jacob comment southern metal finishing conference keynote speaker announced metal finishing comment opportunity composite construction amanda jacob comment week top storey amanda jacob comment tpi composite plan wind blade development centre massachusett amanda jacob comment subsieve autosizer faster fisher number generation comment polymerchemie establishes company comment vale mine produce nickel metal project comment hardmetal meeting world congress comment repower open wind power technology centre kari williamson comment recycled carbon fibre launches website amanda jacob comment modulus exhibit monaco yacht show amanda jacob comment material today virtual conference carbon era demand now comment chinese wind turbine production northern ireland kari williamson comment scottish offshore wind worth kari williamson comment basf exhibit turbine product husum windenergy amanda jacob comment wind farm training course turkey kari williamson comment motive unveil kestrel biocomposite electric vehicle amanda jacob comment drinkdriving whisky biofuel car kari williamson comment celanese increase fortron pps production amanda jacob comment lincoln introduce epoxybased surfacing film amanda jacob comment univar distribution agreement celanese emulsion polymer amanda jacob comment biogas central europe kari williamson comment week top storey amanda jacob comment metalformer anticipate consistent business short term metal finishing comment laser inspection technique adhesive bond amanda jacob comment ccais finishing technology pavilion conference debut fabtech metal finishing comment mirteq announce north american distribution agreement composite amanda jacob comment morocco build wind farm kari williamson comment airborne receive million holland private equity amanda jacob comment jeol correlative microscope win award comment columbia chemical receive gmw chemical approval metal finishing comment gkn win technical paper award comment production resume tungsten mine comment nuclear award metal powder shield comment sureblade take vestas left elizabeth block comment largest ocean energy device installed water operate successfully amanda jacob comment epa set emission limit cement plant amanda jacob comment industrial production inches upward metal finishing comment dow venture capital invest blade dynamic amanda jacob comment vestas fall loss kari williamson comment firm manufacture composite tank saudi arabia amanda jacob comment pmi index remain strong metal finishing comment transporting wind turbine blade kari williamson comment huber acquire kemgard flame retardant business amanda jacob comment floating offshore wind scotland kari williamson comment danish mega wind turbine test centre kari williamson comment gurit launches pvc core range chinese wind market amanda jacob comment material today cover competition comment inaugural nasf chicago briefing set metal finishing comment hexion report higher quarter sale amanda jacob comment material today writing competition comment global renewable energy expand rapidly kari williamson comment doe target offshore wind kari williamson comment ireland renewable energy kari williamson comment indian theni wind farm fully commissioned kari williamson comment week top storey amanda jacob comment registration open england surface finishing regional conference metal finishing comment david crimp named executive vice president enthone europe metal finishing comment ipc military conference target reg tucker comment zcl composite report quarter result amanda jacob comment wind simplicity wind turbine designed recycling kari williamson comment atlantis tidal turbine emec kari williamson comment composite europe showcase dutch composite industry amanda jacob comment carpenter specialty metal extend market blade material comment burying silver particle improve organic electronic comment platinum catalyst improve fuel cell comment scm support growing asian copper market comment tale twist untwist comment breakthrough biofuel reported comment directwrite approach comment watch grow comment delayed time comment quantum computer comment white graphene rescue comment nanomaterial home comment nanotube pass acid test comment magnet trump metallic comment graphene oxide green comment creating biomimetic surface comment greener car opportunity chemical company amanda jacob comment hgcapital buy wind farm sweden kari williamson comment vestas deliver wind turbine australia kari williamson comment acrastrip resin cleaner wipe amanda jacob comment closed moulding demos ibex amanda jacob comment creative pultrusion supply composite distribution pole los angele amanda jacob comment auto sale heat manufacturer metal finishing comment tai deliver large complex composite structure amanda jacob comment siemen supply wind turbine oklahoma kari williamson comment abmaco organise composite world cup seminar amanda jacob comment window solar thinfilm efficiency potential kari williamson comment zoltek report strong quarter sale amanda jacob comment making biooil efficient diesel kari williamson comment week top storey amanda jacob comment online attend southern metal finishing conference metal finishing comment coventya complete integration consolidation metal finishing comment automated dynamic deliver machine gkn aerospace amanda jacob comment acta materialia gold medal comment recipient acta student award comment spraying system launches website metal finishing comment pro ventum build thai wind farm kari williamson comment softer introduce natural fibre reinforced composite amanda jacob comment uyemura boost west coast resource metal finishing comment study shed light wind power market david hopwood comment tungsten conference call paper comment royal metal powder start production comment gtp invest million tungsten powder production comment lion gate hire mining specialist comment offshore wind demo site announced kari williamson comment owen corning report quarter result amanda jacob comment fossil fuel subsidy time support renewable study show david hopwood comment energy composite receive composite tank order amanda jacob comment acciona energy invest canadian wind farm kari williamson comment chemtrend celebrate anniversary amanda jacob comment carl zeiss offer online promotion comment compact scanning electron microscope comment supply sell ameron upole composite utility pole amanda jacob comment role ppg industry executive metal finishing comment online hotel reservation nai coating show metal finishing comment thermoplastic composite trunk liner porsche amanda jacob comment week top storey amanda jacob comment poland offshore wind kari williamson comment repower repower german wind farm kari williamson comment icon aircraft select composite structure supplier icon amanda jacob comment preview composite europe amanda jacob comment reinforced plastic editorial calendar amanda jacob comment new archive connect viewed new lpw begin plasma spheroidization powder metal comment new youre invited submit material science research heliyon comment new selfcleaning gecko feet inspire micromanipulator cordelia sealy comment new growing singlecrystal graphene fast cordelia sealy comment new graphene think box cordelia sealy comment what coming lightweight vehicle manufacturing joining forming focus detroit usa functional oxide thin film advanced energy information technology conference cancn mexico featured event ecobio rotterdam netherland international symposium advanced plasma science application nitride nanomaterial nagoya japan material today material today community dedicated creation sharing material science knowledge experience supported elsevier publish impact peerreviewed journal organise academic conference broadcast educational webinar more material today meet team advertise contact hear you support creation sharing information arent doing better know grow comment ideas contact feed privacy policy term condition cooky map copyright elsevier ltd right reserved website designed intuitiv","m_szGeo1":"","m_szSourceType":"source_industry","m_szSrcUrl":"http://www.materialstoday.com/news/2010-08/","m_Places":["United States","China","Australia","Massachusetts","Fisher","Monaco","Northern Ireland","Husum","Turkey","Central","Europe","Morocco","Columbia","Vestas","Saudi Arabia","Scotland","Chicago","Atmosphere","Ireland","District Of Columbia","Sweden","Los Angeles","Most","Oklahoma","Hopwood","Lions","Uk","Mexico","Japan"],"m_People":["Red Maple","Vale Mine","Jd Lincoln"],"m_Companies":["Plastics","Zyvax Partners","Frp","Airbus","Keynote","Tpi Composites","Congress","Recycled Carbon Fibre Ltd","Sp","Celanese","Pps","Epa","Venture","Dynamics Ltd","Pmi","Europe Showcases","Hgcapital","Diesel","Spraying Systems Co.","Owens Corning","Acciona","Zeiss","Ppg Industries","Sealy","Elsevier","Elsevier Ltd."],"m_BiGrams":["amanda jacob","jacob comment","kari williamson","williamson comment","metal finishing","finishing comment","material today","wind farm","wind turbine","comment week","week top","top storey","storey amanda","offshore wind","comment new","farm kari","material science","metal powder","comment material","award comment","cordelia sealy","sealy comment"],"m_TriGrams":["amanda jacob comment","kari williamson comment","metal finishing comment","comment week top","week top storey","top storey amanda","storey amanda jacob","wind farm kari","farm kari williamson","jacob comment material","comment material today","williamson comment week","cordelia sealy comment"],"m_SocialTags":[],"m_Topics":[],"m_Industry":[],"m_Technology":[],"m_BiCnt":[],"m_TriCnt":[],"m_iDocBodyWordCnt":1201}
