{"m_szDocID":"15912","m_szDocTitle":"Morgan Stanley hikes Tesla stock price target on driverless car potential - Business - CBC News","m_szYear":"2016","m_szDocSumamry":"Morgan Stanley hikes Tesla stock price target on driverless car potential Company could unveil some sort of ride-sharing plans using driverless cars within a year, Adam Jonas says CBC News Posted: Aug 17, 2015 12:39 PM ET Last Updated: Aug 17, 2015 2:52 PM ET Morgan Stanley hiked its target price for Tesla because it thinks the electric car company is close to unveiling a self-driving ride-sharing service. (Robert Galbraith/Reuters) Related Stories Tesla Motors inks deal to build 400 charging stations in China An analyst with Morgan Stanley says the stock price of electric car maker Tesla coul","m_szDocBody":"morgan stanley hike tesla stock price target driverless car potential company unveil sort ridesharing plan driverless car year adam jonas cbc new posted updated morgan stanley hiked target price tesla think electric car company close unveiling selfdriving ridesharing service robert related storey tesla motor ink deal build charging station china analyst morgan stanley stock price electric car maker tesla worth largely potential selfdriving car consumer rent demand uber ina research note client mondayadam jonas raised target price tesla share cent target level stock closed friday ridesharing app jonas main reason optimism business segment company yet ridesharing service driverless car worldwide human drive trillion kilometresevery year car made company practicing yearold business model humandriven privately owned internalcombustion vehicle jonas saidthis fundamentally changing robot driver good riddance human tesla leader electric car world sell fraction hundred million car major gasolinepoweredplayer toyota volkswagen sell year company track sellinga million car year decade cry leader selfdriving car tesla advantage business area entered yet jonas say selfdriving car ondemand mobility service jonas idea business work bit ridesharing app uber populated selfdriving teslas call division tesla mobility unlike conventional car teslas todayalready legup autonomous driving vehicle fully electric wirelessly connected learn software update established automaker today said make lot easier company roll selfdriving vehicle company jonas expect entire car business shift current owneroperator model autonomous future people driven robot vehicle them tesla launches powerwall home battery system selling car ridesharingcompany tesla theoretically middle man sell service directly customer themselve business opportunity potentially additive teslas existing model selling humandriven car private owner potential model conceivably triple company potential revenue jonas say althoughthe company officially plan similar tesla mobility unit jonas envision analyst surprised tesla share formalised business plan shared mobilitywithin month driverless ondemand teslas hit road time said don pittis tesla electric car passing lane future happen idea worth billion jonas price target midpoint base case assumption share worth business stay share revenue stream pass car company stand now worth share jonas say recently announcedbattery division adding share jonas optimistic battery unit increase share share nonexistent ridesharing unit top core electric car business tesla make good mission accelerate world transition sustainable transport move shared mobility model critical jonas said ","m_szGeo1":"China","m_szSourceType":"source_news","m_szSrcUrl":"http://www.cbc.ca/news/business/morgan-stanley-hikes-tesla-stock-price-target-on-driverless-car-potential-1.3193541","m_Places":["Tesla","Toyota","Teslas"],"m_People":["Adam Jonas","Robert Galbraith","Jonas","Don Pittis"],"m_Companies":["Morgan Stanley","Target","Reuters","Tesla Motors","Uber","Volkswagen"],"m_BiGrams":["electric car","morgan stanley","driverless car","selfdriving car","jonas say"],"m_TriGrams":[],"m_SocialTags":[],"m_Topics":[],"m_Industry":[],"m_Technology":[],"m_BiCnt":[],"m_TriCnt":[],"m_iDocBodyWordCnt":362}
