{"m_szDocID":"176530","m_szDocTitle":"Better Buy: Ford vs. General Motors -- The Motley Fool","m_szYear":"2015","m_szDocSumamry":"Fool.com Fool.com Fool.co.uk Fool.com.au Fool.ca Fool.sg Fool.de Hi, Fool! Premium Advice Help Fool Answers Contact Us Login MENU Stock Picks Learn More News Investing News Fool Podcasts Guides Investing Get Started Investing How to Invest Retirement Retire in Style 401(k) IRAs Asset Allocation Personal Finance Motley Fool Answers Find a Broker Community Discussion Boards CAPS More About Help My Fool My Fool My Profile My Watchlist My Scorecard My Boards My CAPS My Reports My Subscriptions My Settings Premium Advice My Services None Other Services None Help Fool Answers Contact Us Login Better","m_szDocBody":"foolcom foolcom foolcouk foolcomau foolca foolsg foolde fool premium advice fool answer contact menu stock pick learn new investing new fool podcast guide investing started investing invest retirement retire style iras asset allocation personal finance motley fool answer broker community discussion board cap fool fool profile watchlist scorecard board cap report subscription setting premium advice service service fool answer contact buy ford general motor battle detroit heavyweight fool analyst make pick buy motley fool staff themotleyfool ford stolen week auto show detroit sexy sport car ceo mary barra countered electric car chevy bolt turn lot significant long run source general motor difference decade make year ago ford nysef general motor nysegm looked doomed ford mortgaged including famous blue oval logo loan give thennew ceo alan mulally resource needed longshot attempt saving company meanwhile hail mary fell short economic crisis hit famously notoriously crashed bankruptcy court now though company good financial health made huge stride muchimproved product cost structure bet investor now fool top auto mind john rosevear daniel miller offer view below daniel miller ford business wellknown factor ford upside ford upside span globe multiple way first ford trail china term sale sale surging couple year fact ford joint venture sold million vehicle time automaker surpassed million sale good gain compared ford upside limited sale china automaker pouring capital luxury lineup increase top bottomline performance recently leap ahead competition forwardlooking aluminumbodied ford newfor began rolling dearborn factory november early demand truck strong source ford motor also ford made outstanding progress critical obligation automotive debt underfunded pension plan recently ford pension plan underfunded billion obligation valued automotive debt end year however obligation cut half roughly billion meanwhile ford debt expected billion future context mean ford balance sheet shape decade also important ford ability cash spend paying debt funding pension plan dish shareholder instead fact ford paid billion dividend spent billion paying pension fund alone forward ford spend fraction amount pension plan free capital triple returned shareholder future talk competitive advantage ford first month ihs automotive announced loyalty awardsgiving ford top honour overall loyalty manufacturer overall loyalty make mean consumer buy ford purchase ford brand huge competitive advantage huge advantage ly ford credit division essentially act bank ford credit take massive amount capital dishes back consumer dealership making significant profit process fact ford credit ford secondmostprofitable entity north america region automaker close ford credit remain significant advantage forward invest company placing trust management make decision increase business ford big trick sleeve not family ford family interest aligned everyday shareholder ford family including executive chairman bill ford exclusive owner class share mean good ford family good shareholder furthermore ford management proven extremely capable worst time financial crisis brought crosstown rival fiat chrysler automobile general motor bankruptcy ford survived dime choice clear ford bet investor dollar detroit john rosevear case general motor way lose ford stock company poised good year money now interesting bet pretty badly beaten rightfully argue massive expensive recall scandal ceo mary barras sluggish initial response mess help barra programme made strong move crisis opportunity push big make general responsive safety issue make gms future product better cadillac chief johan nysschen promised week cadillac ctsv beat german luxury brand game gms recent track record make credible threat source general motor recall mess grabbed headline and dented gms stock price gms underlying business looked good year made huge improvement recent product mean gms dealer sell fat discount resort past turn mean gms profit margin north america soared factor cost recall gms operating profit margin north america quarter ford lot rival recall drama fade rearview mirror improvement start visible investor meanwhile barra sharp team continue whip part shape moneytorching european operation turn profit solid profit china gms sale volkswagen fatter add suvs luxury car mix couple year innovation hot autoindustry buzzword brilliant research development department rival feared stepping big way selfdriving car gms super cruise system market year radical weightsaving construction technique among innovation patented technique welding aluminium highstrength steel showing longadmired potential finally harnessed nutshell reason buy year industry observer profitminting powerhouse act together now barra team finally happening year world finally catches apple watch revealed real winner inside apple recently revealed product secretdevelopment dream team apple watch secret out early viewer claiming everyday impact trump ipod iphone ipad fact abi research predict million type device sold year small company make apple gadget possible stock price unlimited room run earlyintheknow investor them opportunity real money made here daniel miller own share apple ford general motor john rosevear own share apple ford general motor motley fool recommend apple ford general motor own share apple ford foolish newsletter service free day fool hold opinion diverse range insight make investor motley fool disclosure policy comment motley fool staff themotleyfool info industrial stock ford nysef general motor nysegm read market reward general motor record profit selloff automaker continue surge europe ford motor company notches doubledigit sale gain critical market slide ford credit boost mean key fourthquarter takeaway general motor investor compare broker feedback motley fool site love hear you copyright trademark patent information term privacy policy read term condition motley fool right reserved bat data provided realtime nyse nasdaq nysemkt data delayed minute realtime price provided bat bzx market data provided interactive data company fundamental data provided morningstar earning estimate analyst rating key statistic provided zack sec filing insider transaction provided edgar online powered implemented interactive data managed solution term condition","m_szGeo1":"United States","m_szSourceType":"source_investments","m_szSrcUrl":"http://www.fool.com/investing/general/2015/01/25/better-buy-ford-vs-general-motors.aspx?source=isesitlnk0000001&mrr=0.13","m_Places":["Uk","Us","Detroit","China","Means","North America","U.s.","Europe"],"m_People":["Mary Barra","Alan Mulally","John Rosevear","Daniel Miller","Johan","De Nysschen"],"m_Companies":["Iras","Motley Fool","General Motors","Motley Fool Staff","Ford Motor Co","Ford Family","Fiat Chrysler Automobiles","Cadillac","Volkswagen","Apple","Abi Research","Ford Motor Company","Nasdaq","Morningstar","Sec","Edgar Online"],"m_BiGrams":["general motor","motley fool","ford credit","ford general","pension plan","apple ford","fool answer","john rosevear","daniel miller","ford upside","fact ford","north america","ford family","own share","share apple","data provided"],"m_TriGrams":["ford general motor","own share apple","share apple ford","apple ford general"],"m_SocialTags":[],"m_Topics":[],"m_Industry":[],"m_Technology":[],"m_BiCnt":[12,7,5,4,4,4,3,3,3,3,3,3,3,3,3,3],"m_TriCnt":[4,3,3,3],"m_iDocBodyWordCnt":894}
