{"m_szDocID":"189350","m_szDocTitle":"US7422666B2 - Photovoltaically powered cathodic protection system for automotive vehicle          - Google Patents","m_szYear":"2006","m_szDocSumamry":"Sign in Photovoltaically powered cathodic protection system for automotive vehicle US7422666B2 US Grant Download PDF Find Prior Art Legal statusThe legal status is an assumption and is not a legal conclusion. Google has not performed a legal analysis and makes no representation as to the accuracy of the status listed. Active, expires 2026-11-11 Application number US11383610 Other versions US20070267290A1 (application) Inventor James Richardson Current AssigneeThe listed assignees may be inaccurate. Google has not performed a legal analysis and makes no representation or warranty as to the accu","m_szDocBody":"photovoltaically powered cathodic protection system automotive vehicle usb grant download prior art legal statusthe legal status assumption legal conclusion performed legal analysis make representation accuracy status listed active expire application number version usa application inventor jame richardson current assigneethe listed assignee inaccurate performed legal analysis make representation warranty accuracy list ford global technology llc original assignee ford global technology llc priority datethe priority date assumption legal conclusion performed legal analysis make representation accuracy date listed filing date date grant date info patent citation cited published legal event similar document external link uspto uspto assignment espacenet discuss photovoltaically powered cathodic protection system automotive vehicle electrical energy arising photovoltaic array positioned exterior surface vehicle cathodic protection current controlled controller connected electrical storage device electrogalvanic cell sensor controller sensor function assure sufficient charge passe conductor applied body vehicle maintain cathodic protection consistent basis classification description background invention field invention invention relate cathodic corrosion protection system automotive vehicle electrical energy required power cathodic system provided photovoltaic array mounted exterior surface vehicle system include battery controller monitoring vehicle electrical potential adjusting applied anticorrosion voltage disclosure information cathodic protection metallic structure year pat illustrate solar powered cathodic corrosion protection system buried structure cathodic protection moveable structure has however generally confined marine application course source electrical current provided power cathodic protection system expense energy expenditure designer cathodic protection system attempted mitigate energy consumption system photovoltaic array advantageously convert sunlight electrical energy powered cathodic protection has however stationary structure shown patent system invention advantageously array battery storage power cathodic protection system automotive vehicle prevent corrosion vehicle vehicle body increasing fuel consumed vehicle power plant summary invention photovoltaically powered cathodic protection system automotive vehicle include photovoltaic array adapted mounting exterior surface vehicle array load terminal conductor adapted extend terminal portion vehicle portion vehicle physically separated generally comprise portion welded metallic body vehicle metallic body automotive vehicle generally joined mean welding numerous conduction path created stamping encompass vehicle body case unitized construction utilised vehicle separate construction welded metal body metal frame body frame vehicle numerous electrical interconnect result excellent electrical conduction part vehicle body combined achieved system produce level cathodic corrosion protection photovoltaically powered cathodic protection system include electrical storage device embodied battery ultracapacitor type storage device skilled art suggested disclosure controller operatively connected electrical storage device photovoltaic array body sensor control current flowing conductor vehicle body chassis aspect invention method providing cathodic protection body automotive vehicle include step providing photovoltaic array located exterior surface vehicle body array plurality connecting terminal providing plurality conductor extending connecting terminal distributed portion vehicle body method include providing electrical storage device operatively bonded connecting terminal array providing controller operatively array electrical storage device control flow current array electrical storage device vehicle body event storage device accumulated charge excess predetermined threshold charge entire current flowing array flow vehicle body aspect invention primary secondary grounding employed primary grounding accomplished vehicle tyre secondary grounding centralised grounding point vehicle body itself advantage method system invention active cathodic protection provided automotive vehicle increased consumption fuel required generate electrical current cathodic protection advantage system cathodic protection vehicle manufactured readily recyclable steel essence cathodic protection offered inventive system supplant anticorrosion coating steel metal render metal recyclable example galvanised coating coating cold rolled steel stock prevent steel readily recycled turn adverse economic impact manufacturer vehicle vehicle purchaser advantage system system controller sensor provide feedback vehicle body respecting applied voltage requirement permitting safe electrical discharge level advantage object feature invention apparent reader specification description drawing fig perspective vehicle cathodic protection system invention fig block showing component part cathodic protection system invention detailed description preferred embodiment vehicle shown fig metallic body system form unitized body frame system separate architecture vehicle photovoltaic array mounted top vehicle array comprise integrated photovoltaic appliqu sunroof clear roof module integrated solar collector additional panel applied top conductor connected top serve convenient central location bonding conductor vehicle conductor extend sunroof remote distributed separated location vehicle thus conductor extend forward portion vehicle body conductor extend rear quarter vehicle purpose conductor assure desired electric current reaches required portion metallic structure vehicle primary system ground established tyre secondary ground established vehicle chassis body ground commonly point vehicle starting battery grounded skilled art disclosure sunroof comprise vitreous nonvitreous sunroof type fixed movable panel solar collection material integrated dispersed applied film applied surface appliqu positioned exterior top panel vehicle ready target impingement solar energy array fig show controller electrical storage device mounted vehicle convenient location function device explained conjunction fig below shown fig controller connected body conductor storage device array controller grounded vehicle body tyre storage device drawn plurality device storage battery ultracapacitor device commonly storing electrical energy storage device operatively connected central electrical storage device vehicle primary function controller place electrical potential vehicle body sufficient produce active cathodic protection providing voltage adjusted feedback corrosion cell sensor sensor fig include nanosensor located location greater likelihood affected electrogalvanic corrosion sensor sense presence active electrogalvanic cell sensing microcurrent voltage cell number sensor employed provide feedback controller corrosion potential portion vehicle body manner anticorrosion current applied defined portion controller function maintain storage device suitably charged state assure cathodic protection continue period current generated array insufficient power cathodic protection system desired level night overcast day storage device charged level exceeding predetermined threshold controller programmed direct entirety current flowing array conductor manner cathodic protection provided consistent basis adversely impacting fuel economy vehicle alternative previously system storage device charged mean installed vehicular electrical system arrangement avoid cost array increased fuel consumption ongoing invention connexion embodiment thereof understood modification alteration adaptation made skilled art departing spirit scope invention set claim claim photovoltaically powered cathodic protection system automotive vehicle comprising photovoltaic array adapted mounting exterior surface vehicle array load terminal conductor adapted extend terminal photovoltaic array portion vehicle conductor adapted extend terminal photovoltaic array portion vehicle electrical storage device connected terminal photovoltaic array controller operatively connected electrical storage device photovoltaic array controlling current flowing conductor controller operatively connected sensor sensing presence active electrogalvanic cell vehicle photovoltaically powered cathodic protection system portion vehicle portion vehicle physically separated photovoltaically powered cathodic protection system electrical storage device comprise battery photovoltaically powered cathodic protection system electrical storage device comprise ultracapacitor cathodic corrosion protection system automotive vehicle comprising electrical power source load terminal conductor adapted extend terminal electrical power source electrical ground vehicle conductor adapted extend terminal electrical power source portion vehicle protective current established vehicle controller controlling protective current sensor operatively connected controller sensing presence active electrogalvanic cell vehicle cathodic protection system electrical power source comprise photovoltaic array electrical storage device operatively connected photovoltaic array cathode protection system electrical power source comprise electrical storage device patent citation number priority date date assignee usa galberth robert power output control circuit solarpowered cathodic protection system usa siemen solar industry method fabricating photovoltaic module ushh united state america represented secretary navy method apparatus providing continuous cathodic protection solar power usa stilley troy solar powered cathodic corrosion protection system usa solar method making utilising partially cured photovoltaic assembly usb powerlight corporation electric vehicle photovoltaic roof assembly usb envitech inc metal corrosion prevention system nonsacrificial photoanode sunlight usb arvinmeritor gmbh cover constructed solar generator closing opening bodywork vehicle usa david woodhouse solar panel configuration vehicle cited examiner cited party cited citing patent number priority date date assignee usa shuyi zhu solarpowered hybrid vehicle cited examiner cited party published number date type usa application similar document date usa photovoltaic solar cell laminated vehicle windshield usa electrical system motor vehicle including supercapacitor usb vehicle supplemental energy storage system engine cranking usa hybrid vehicle low voltage solar panel charging voltage battery sery charger separately charge individual cell sery connected battery usa pole battery switches usa electrically driven vehicle usb power distribution apparatus distributing power electrical load woa motor vehicle electric system usb system method safely efficiently capturing power produced power supply power electrical device truck engine turned usa hybrid vehicle adjustable modular solar panel increase charge generation usb power supply automotive vehicle usb charging control electric vehicle usa battery recharging solar cell arrangement automotive vehicle usa cathodic protection system motor vehicle jpha reversecurrent preventive device rectifying device photovoltaic power generation system usa parking power charging system woa improved transport system usa sliding roof motor vehicle usa vehicle usa fast charge station electric vehicle areas limited power availabilty jpa method system levelling power load usa cost effective system supplying solar electricity extended range electric vehicle nearby building jpa hybrid vehicle jpa independent photovoltaic power generation system method jpa electric power system electric vehicle legal event date code description assignment owner name ford global technology llc michigan free format text assignment assignor interestassignorford motor effective date owner name ford motor company michigan free format text assignment assignor interestassignorrichardson jame effective date fpay fee payment year fee payment ","m_szGeo1":"United States","m_szSourceType":"source_patents","m_szSrcUrl":"https://patents.google.com/patent/US7422666","m_Places":["United States","Llc, Michigan","Michigan"],"m_People":["Richardson, James L.","Robert L Power","Troy R Solar","David Woodhouse Solar","Shuyi Zhu Solar"],"m_Companies":["Prior Art","Google","Ford Global Technologies Llc","Target","Navy","Amoco","Enron","Powerlight Corporation","Arvinmeritor Gmbh","Ford Motor Company"],"m_BiGrams":["cathodic protection","protection system","storage device","photovoltaic array","electrical storage","vehicle body","automotive vehicle","powered cathodic","portion vehicle","photovoltaically powered","system automotive","operatively connected","exterior surface","surface vehicle","cathodic corrosion","corrosion protection","conductor adapted","adapted extend","extend terminal","electrical power","power source","electric vehicle","vehicle usa","vehicle electrical","electrical energy","electrogalvanic cell","power cathodic","system invention","controller operatively","current flowing","system electrical","system usa","hybrid vehicle","motor vehicle","vehicle usb","performed legal","legal analysis","analysis make","make representation","ford global","global technology","technology llc","priority date","vehicle cathodic","connected electrical","vehicle array","load terminal","terminal conductor","metallic body","skilled art","device photovoltaic","connecting terminal","device operatively","array electrical","vehicle conductor","conductor extend","presence active","active electrogalvanic","terminal photovoltaic","solar panel"],"m_TriGrams":["cathodic protection system","electrical storage device","powered cathodic protection","photovoltaically powered cathodic","protection system automotive","system automotive vehicle","exterior surface vehicle","cathodic corrosion protection","conductor adapted extend","adapted extend terminal","electrical power source","corrosion protection system","protection system electrical","ford global technology","global technology llc","vehicle cathodic protection","connected electrical storage","power cathodic protection","load terminal conductor","terminal conductor adapted","controller operatively connected","portion vehicle body","storage device operatively","array electrical storage","presence active electrogalvanic","active electrogalvanic cell","terminal photovoltaic array"],"m_SocialTags":[],"m_Topics":[],"m_Industry":[],"m_Technology":[],"m_BiCnt":[],"m_TriCnt":[],"m_iDocBodyWordCnt":1440}
