{"m_szDocID":"1963","m_szDocTitle":"Surrender at Ft. Calhoun","m_szYear":"2007","m_szDocSumamry":"textArticle -------------------- Surrender at Ft. Calhoun The nation’s smallest nuclear power plant, at 479 MW, threw in the towel this week Ft. Calhoun surrounded by Missouri River flood waters June 2011 The management of Omaha Public Power District (OPPD) has recommended that the single-unit Fort Calhoun nuclear power station in Nebraska be permanently shut down. Rising costs, record low natural gas prices, and flat or declining demand for electricity made it impossible to run the reactor in the black. OPPD CEO Tim Burke told the company’s board of directors that he is recommending the react","m_szDocBody":"surrender calhoun nation smallest nuclear power plant threw towel week calhoun surrounded missouri river flood water management omaha public power district oppd recommended singleunit fort calhoun nuclear power station nebraska permanently shut down rising cost record low natural gas price flat declining demand electricity made impossible run reactor black oppd ceo tim burke told company board director recommending reactor began commercial operation cease operation end begin process decommissioning decade complete burke utility position financial untenable economic analysis show continued operation fort calhoun nuclear station financially sustainable analysis considered market condition economy scale proposed clean power plan vector wrong direction plant electricity increasing natural gas price record low level federal government effort impose limit emission due court challenge utility suffered significant financial setback starting flood missouri river long period service implement corrective action meet nrc safety requirement oppd board review burke recommendation vote scheduled fort calhoun nuclear power plant nebraska account onethird oppd total electricity generation owned omaha public power district fort calhoun operated agreement exelon generation reactor located nebraska mile north omaha plant began commercial production electricity received licence extension nuclear regulatory commission licenced operate employ people rough half decade oppd proposal close plant tumultuous half decade experienced major flood stringent oversight nrc false rumour blown flood stricken calhoun reactor postponed restart shut scheduled fuel outage rising flood water missouri river damaged plant reactor switch yard remained dry plant management initially resisted demand nrc strengthen flood barrier installed short time rising missouri river feet overtopping inflatable boom water reactor turbine building plant switchyard predawn hour fork lift punctured foot high long boom flood water plant plant operator started emergency diesel generator flood water approached switchyard plant grid emergency repair prevented significant damage facility plant restart flood receded nrc resident inspector found numerous deficiency plant operation imposed stiff set requirement agency calhoun plant fulfil long list safety requirement nrc power back speed along oppd hired exelon operate plant green light nrc restart reactor generate electricity revenue utility oppd cancelled plan power uprate citing multiple safety issue facing plant burke correct assessment financial situation fact utility senior management unable address nrc finding resulted hiring expert exelon job them history closure due poor response flood long imposed outage safety concern revenue coming result contributed utility plan plant decommissioning plant service oppd annual report estimated cost decommission fort calhoun million utility million hand cost mean reactor fuel removed put cooling pond eventually dry cask however year longer complete process fund money fund move forward plant put safe configuration maintained skeleton staff calhoun number reactor closing oppd decision close calhoun latest sery plant closing reactor announced plan shut similar economic reason service closed plant dominion kewaunee entergy vermont yankee planned closure energy pilgrim and fitzpatrick reactor southern california edison san onfre nuclear power station shut technical failure steam generator also york governor cuomo continue pursue campaign close indian point nuclear power station environmental ground impetus effort appear coming environmental group contribute governor political reelection effort nei response latest closing reactor washington nuclear energy institute nei senior director business policy matt crozat proposed closure calhoun demonstrate policy preserve existing nuclear power plant necessary announcement reflect fact nuclear power plant country vulnerable weak market condition smaller facility competitive market crozat said urgent develop policy prevent additional premature nuclear plant retirement economic environmental consequence incredibly detrimental nuclear energy summit held week department energy nei ceo marvin fertel nuclear power plant risk year blamed low power price brought auction deregulated market competition natural gas government subsidy solar wind energy plant federal state level fertel reactor exelon quad city nuclear plant illinois risk shutting year legislature doesnt address issue added change needed federal energy regulatory commission long favoured renewable energy source nuclear logged post comment logged post comment energy collective column coming soon latest comment engineer poet fast market electric vehicle grow limit biofuel approach though not tall oil great compe may jarmo fast market electric vehicle grow native finland government decided fastest route cut transport emission may joe deely natural gasfired power plant construction major shale play clear bob version nat gassolar wind reduced coal consumption gwh may bobmeinetz natural gasfired power plant construction major shale play hop paper generating nuclear synfuel mit centre advanced nuclear energy sys may advisory panel scott edward anderson consultant blogger media commentator blog green sceptic christine hertzog consultant author professional explainer focused smart grid elias hinckley strategic advisor energy finance energy policy investor energy company government gary hunt gary executiveinresidence deloitte investment extensive experience energy utility industry jesse jenkin graduate student researcher mit expertise energy technology policy innovation jim pierobon help trade government agency company communicate cleaner energy solution geoffrey style managing director gsw strategy group llc awardwinning blogger featured contributor may may ","m_szGeo1":"United Kingdom","m_szSourceType":"source_industry","m_szSrcUrl":"http://www.theenergycollective.com/dan-yurman/2379056/surrender-at-ft-calhoun?utm_source=feedburner&utm_medium=feed&utm_campaign=The+Energy+Collective+%28all+posts%29","m_Places":["Missouri River","Fort Calhoun","Nebraska","Omaha","United States","Kewaunee, Wi","Fitzpatrick, Ny","Southern California","New York","Washington, Dc","Quad Cities","Illinois","Finland","Gary"],"m_People":["Tim Burke","Cuomo","Matt Crozat","Marvin Fertel","Joe Deely","Scott Edward","Christine Hertzog","Elias Hinckley","Hunt Gary","Jesse Jenkins","Jim Pierobon","Geoffrey Styles"],"m_Companies":["Omaha Public Power District","Oppd","U.s. Nuclear Regulatory Commission","Diesel","Dominion","Entergy","Vermont Yankee","Nei","Nuclear Energy Institute","Department Of Energy","Federal Energy Regulatory Commission","Deloitte","Strategy Group, Llc"],"m_BiGrams":["nuclear power","power plant","fort calhoun","missouri river","flood water","calhoun nuclear","power station","natural gas","nuclear energy"],"m_TriGrams":["nuclear power plant","fort calhoun nuclear","nuclear power station"],"m_SocialTags":[],"m_Topics":[],"m_Industry":[],"m_Technology":[],"m_BiCnt":[8,7,5,4,4,3,3,3,3],"m_TriCnt":[5,3,3],"m_iDocBodyWordCnt":780}
