{"m_szDocID":"211674","m_szDocTitle":"President Obama Regrettably Approves Oil Drilling in the Arctic Ocean","m_szYear":"2015","m_szDocSumamry":"textArticle -------------------- President Obama Regrettably Approves Oil Drilling in the Arctic Ocean May 18, 2015 by Henry Auer 1 Comment The Obama administration granted conditional approval to Shell Oil Company to begin exploratory drilling in the Arctic Ocean off the North Slope of Alaska on May 11, 2015. In addition to generating grave misgivings about possible environmental damage from drilling accidents, this decision represents a major compromise with the Presidentâ€™s own policies directed toward limiting global warming. Burning any fossil fuel, such as the oil sought in this project, ","m_szDocBody":"president obama regrettably approve oil drilling arctic ocean henry auer comment obama administration granted conditional approval shell oil company begin exploratory drilling arctic ocean north slope alaska addition generating grave misgiving environmental damage drilling accident decision represent major compromise president policy directed limiting global warming burning fossil fuel oil sought project add carbon dioxide atmosphere worsening burden greenhouse gase added earth air inaugural address jan president committed respond threat climate change knowing failure betray children future generation noting recurrence severe weather climate event stated avoid devastating impact raging fire crippling drought powerful storm order combat trend president summoned nation resist transition sustainable energy source lead developing technology power job industry president state union address year january pursued theme stated highly profound basic motivation attacking problem global warming climate change fact children children eye leave safer stable world source energy yes did nevertheless spite lofty goal president obama stated march energy strategy century trap past energy strategy future alloftheabove strategy century develop source americanmade energy alloftheabove energy strategy intended promote economic growth job creation enhance energy security develop lowcarbon energy economy extent ensuring energy security rely century strategy based fossil fuel alloftheabove pit continued exploitation fossil fuel smaller rapidly growing renewable energy industry president credit set policy reduce emission source emission passenger vehicle lower fuel efficiency standard car light truck reach average level mpg standard heavyduty truck issued proposed clean power plan finalised lower emission large electricity generating plant level policy significant positive development path lowering emission produced hand obama administration made decision expand production fossil fuel extent approval exploratory drilling arctic ocean shell latest policy shift minimising emission greenhouse gase authorising extensive coal mining operation powder river basin wyoming montana announced lease oil exploration atlantic ocean east coast issued beginning decision approve keystone pipeline bring canadian tar sand oil pending expanded development fossil fuel require investment large amount capital expansion energy economy important question deploy investment order minimise emission greenhouse gase important direct investment renewable energy expansion fossil fuel resource decision extract fossil fuel longlasting consequence project year reach fruition lock greenhouse gas emission decade thereafter directly interfere achieving goal lowering greenhouse gas emission rate instead existing fossil fuelburning asset exhaust lifetime replace renewable energy resource coal worst fossil fuel term greenhouse gas efficiency burning coal generate half heat natural gas tonne emitted administration clean power plan effect phasing coalfired electric plant hand administration opting expand coal mining demand coal reduced clear newly mined coal destined export contributing expanded inefficient fuel abroad time international effort directed reduce greenhouse gas emission car powered internal combustion engine inefficient energy contained fuel burn approximately energy dissipated waste heat propel vehicle road illustrated graphic below electric vehicle efficient electrical energy gasolinefueled car generally mile gallon electric vehicle reported mile gallon equivalent less litre evaluated dept energy extent electrical energy supplied vehicle renewable source fossil fuel represent vast reduction greenhouse gas emission conclusion president obama made environmental mistake permitting shell explore oil arctic ocean action lead extraction fossil fuel project worsen earth burden greenhouse gas atmosphere decade field explored thought large supply oil shell arctic project powder river coal development exploration oil production eastern coast run counter president pledge lower ghg emission rate level emitted pledge made president meeting president jinping china nov world face critical reduce greenhouse gas emission coming decade providing energy support economic growth worldwide major component world economy company supplying fossil fuel provide significant fraction energy need company continue expand production resource control heed welfare planet considerable influence perpetuate role fossil fuel play energy economy opportunity arise investment capital supply energy economy decision made develop renewable energy source industry presently smaller fossil fuel industry expanding rapidly provide job worker generate profit company involved time great fossil fuel company world change business model resist easy decision continue usual way business invest renewable energy source instead economic policy promoted discourage continued development fossil fuel promote investment renewable energy nation world united nation involved negotiating worldwide climate agreement reduce greenhouse gas emission president obama permitting expansion fossil fuel extraction alloftheabove energy policy compromising leadership role playing bringing agreement successful conclusion president action lead doubt whether children children eye leave safer stable world source energy yes did coming soon latest comment bobmeinetz low price gas stagnant economy killing nuke dan found the low price gas curious attribution killing nuclear june bobmeinetz firstenergy fail test utility competition bailout bid grace idea electric utility heavily regulated state government myth june bobmeinetz treasure sierra nevada roger geoengineering scheme afloat appear merit most june grace adam firstenergy fail test utility competition bailout bid sound income care earn june advisory panel scott edward anderson consultant blogger media commentator blog green sceptic christine hertzog consultant author professional explainer focused smart grid elias hinckley strategic advisor energy finance energy policy investor energy company government gary hunt gary executiveinresidence deloitte investment extensive experience energy utility industry jesse jenkin graduate student researcher mit expertise energy technology policy innovation jim pierobon help trade government agency company communicate cleaner energy solution geoffrey style managing director gsw strategy group llc awardwinning blogger featured contributor jan ","m_szGeo1":"United Kingdom","m_szSourceType":"source_industry","m_szSrcUrl":"http://www.theenergycollective.com/henry-auer/2228191/president-obama-regrettably-approves-oil-drilling-arctic-ocean","m_Places":["Alaska","Wyoming","Atlantic Ocean","Most","China","United States","Bid","Gary"],"m_People":["Barack Obama","Henry Auer","Xi Jinping","Grace Adams","Scott Edward","Christine Hertzog","Elias Hinckley","Hunt Gary","Jesse Jenkins","Jim Pierobon","Geoffrey Styles"],"m_Companies":["Obama Administration","Shell Oil Company","Has Indeed Set Out Policies That Will Reduce Emissions Of","Path","Shell","U. S. Dept. Of Energy","Eastern U. S.","United Nations","Firstenergy","Bid Grace","Sierra Nevada","Deloitte","Strategy Group, Llc"],"m_BiGrams":["fossil fuel","greenhouse gas","renewable energy","gas emission","president obama","arctic ocean","energy economy","drilling arctic","greenhouse gase","energy source","energy strategy","reduce greenhouse"],"m_TriGrams":["greenhouse gas emission","drilling arctic ocean","reduce greenhouse gas"],"m_SocialTags":[],"m_Topics":[],"m_Industry":[],"m_Technology":[],"m_BiCnt":[16,8,6,6,4,4,4,3,3,3,3,3],"m_TriCnt":[6,3,3],"m_iDocBodyWordCnt":838}
