{"m_szDocID":"212087","m_szDocTitle":"False Dichotomy","m_szYear":"2008","m_szDocSumamry":"textArticle -------------------- False Dichotomy by Geoffrey Styles Leave a Comment The fate of the renewable electricity production tax credit (PTC), which provides incentives for power generated from wind, solar, and other alternative energy sources, is apparently still in doubt. Last month the US Senate approved a one-year extension of the credit as an amendment to a housing bill, but the House of Representatives is balking at the provisionâ€™s cost. Previous efforts to extend the credit and pay for it by revoking tax benefits for the oil industry failed . With oil companies earning record pr","m_szDocBody":"false dichotomy geoffrey style leave comment fate renewable electricity production tax credit ptc incentive power generated wind solar alternative energy source apparently doubt month senate approved oneyear extension credit amendment housing bill house representative baulking provision cost previous effort extend credit pay revoking tax benefit oil industry failed oil company earning record profit temptation tax pay alternative energy overwhelming reflect profound misunderstanding nature energy problem relative scale solution wind power oil expense other understand taxing oil industry subsidise wind solar power wont advance energy securitynever mind energy independence contribution additional wind power energy balance wind industry banner year adding wind capacity expanding installed wind power base represent important increment renewable energy reduce future greenhouse gas emission average capacity factor wind turbine added year generate approximately billion kilowatthour year operation substantial amount electricity represent trillion kwh electrical energy consumed relevant wind oil competition created congress however equivalent btus saved extra wind power assuming displace gasfired power generation equate barrel day oilthe output single mediumsized oil platform imposing higher taxe oil producer resulted oil project deferred cancelled energy contribution entire year worth wind capacity addition negated prioritise current energy challenge urgent large volume highpriced oil import competition developing economy asia middle east expand trade deficit drive inflation put pressure dollar vicious cycle option generating electricity producing transportation fuel ethanol facing concern competition food emerging worry water consumption large number plugin hybrid car electric vehicle electricity substitute oil transportation renewable energy option reducing greenhouse gas emission arguing ptc expire bad outcome reason number job potentially stake weakening economy instead convinced thriving renewable energy industry thriving domestic oil industry pitting terrible idea care energy security reducing economic geopolitical consequence oil import create false dichotomy owe politic cold assessment fact congress billion earmark cut fund ptc year putting future oil production risk problem bigger appear geoffrey style geoffrey style managing director gsw strategy group llc energy environmental strategy consulting firm served consultant advisor helping organisation executive address systemslevel challenge industry experience include year texaco inc culminating senior position texacos leadership team strategy development focused global refining marketing transportation alternative energy businesse global issue climate change previously held senior position alliance management planning supply distribution risk management served nasas senior management oversight committee space solar power earned mba university california berkeley chemical engineering davis energy outlook quoted frequently wall street named top eco blog time london filed under uncategorised logged post comment logged post comment energy collective column coming soon latest comment bobmeinetz low price gas stagnant economy killing nuke dan found the low price gas curious attribution killing nuclear june bobmeinetz firstenergy fail test utility competition bailout bid grace idea electric utility heavily regulated state government myth june bobmeinetz treasure sierra nevada roger geoengineering scheme afloat appear merit most june grace adam firstenergy fail test utility competition bailout bid sound income care earn june advisory panel scott edward anderson consultant blogger media commentator blog green sceptic christine hertzog consultant author professional explainer focused smart grid elias hinckley strategic advisor energy finance energy policy investor energy company government gary hunt gary executiveinresidence deloitte investment extensive experience energy utility industry jesse jenkin graduate student researcher mit expertise energy technology policy innovation jim pierobon help trade government agency company communicate cleaner energy solution geoffrey style managing director gsw strategy group llc awardwinning blogger featured contributor june june ","m_szGeo1":"United Kingdom","m_szSourceType":"source_industry","m_szSrcUrl":"http://www.theenergycollective.com/geoffrey-styles/28849/22307","m_Places":["United States","Asia","Middle East","Outlook","Bid","Gary"],"m_People":["Geoffrey Styles","Grace Adams","Scott Edward","Christine Hertzog","Elias Hinckley","Hunt Gary","Jesse Jenkins","Jim Pierobon"],"m_Companies":["Us Senate","House Of Representatives","Congress","Strategy Group, Llc","Texaco Inc","Texaco","Alliance","Nasa","Oversight Committee","University Of California","Wall Street Journal","Times Of London","Firstenergy","Bid Grace","Sierra Nevada","Deloitte"],"m_BiGrams":["geoffrey style","wind power","alternative energy","oil industry","renewable energy"],"m_TriGrams":[],"m_SocialTags":[],"m_Topics":[],"m_Industry":[],"m_Technology":[],"m_BiCnt":[4,4,3,3,3],"m_TriCnt":[],"m_iDocBodyWordCnt":549}
