{"m_szDocID":"212442","m_szDocTitle":"Tesla’s $5B Giga Battery Factory and Deep Politics in AZ, TX, NV, and NM","m_szYear":"2014","m_szDocSumamry":"textArticle -------------------- Tesla’s $5B Giga Battery Factory and Deep Politics in AZ, TX, NV, and NM April 3, 2014 by Eric Wesoff 6 Comments The yet unnamed location of Elon Musk’s outrageously ambitious $5 billion Tesla battery factory has been narrowed down to Texas, Arizona, New Mexico or Nevada for a while now. Construction potentially starts this year. Electric vehicle pioneer Tesla Motors has suggested it will be building 500,000 cars per year by 2020 and hitting a scale that will drive down the cost of its 60 kilowatt-hour battery-pack by 30 percent to about $10,000. The project ai","m_szDocBody":"teslas giga battery factory deep politic eric wesoff comment unnamed location elon musk outrageously ambitious billion tesla battery factory narrowed texas arizona mexico nevada now construction potentially start year electric vehicle pioneer tesla motor suggested building car year hitting scale drive cost kilowatthour batterypack percent project aim disrupt battery cost impact distributed storage industry teslas giga factory sprawl acre land situated highway rail space hundred megawatt solar panel wind turbine state win factory billion direct investment potential job politician state attract world largest lithiumion battery factory tool disposal tax payer money promise luring tesla incentive secret meeting texas san antonio expressnew report unnamed tesla executive met mayor san antonio county top elected official economic development folk local utility company texas banning direct sale tesla vehicle state contender race factory appear state leadership inclined change governor rick perry referred antiquated car dealer franchise law appearance fox business new city san antonio remain consideration lubbock west texas windpower numerous report arizona opposition auto dealer arizonas state legislature bill direct sale phoenix business journal tucson mayor jonathan rothschild told arizona daily star potential selected city state city tax incentive package offered reported city mesas mayor scott smith running arizona governor tesla ceo elon musk invitation visit phoenix business journal tesla benefit state incentive offered apple plant mesa namely gov brewer business group support bill eliminate taxe energy manufacturer arizonas offer include percent property tax rate well state lawmaker bill give income tax break company manufacturing facility powered solar renewable source report mexico albuquerque report mexico governor susana martinez republican special legislative session work economic package tesla factory report democratic legislative leader special session woo tesla unprecedented mexico evidence teslas pick albuquerque close tesla roadster factory nevada month reno gazette reported tesla exec site northern part nevada month northern nevada front runner phoenix business journal report reno area northern nevada oddson favourite land tesla plant citing multiple business political source phoenix renostead airport suggested thousand acre development rail access reason tesla choose texas gtm katie tweed reported legislative effort number state shut tesla selling directly consumer store forcing company follow law prohibit factoryowned dealership york agreed electric vehicle maker companyowned outlet open permit expansion deal made ohio limit number tesla outlet three acrimonious conflict jersey tesla favourable court decision massachusett pioneer won round court skirmishes minnesota direct sale banned state customer visit tesla gallery arent allowed talk price test drive texas twomonth effort pass bill legislature tesla motor sell electric car directly consumer effort died summer lawmaker failed vote adjourning legislature meet texas gov rick perry recipient traditional car dealer campaign contribution bucked donor bit interview fox business channel teslas big project told maria bartiromo cachet put manufacturing facility state hard pass perry added think pros allowing happen outweigh con ban direct sale conversation worth happening giga factory fact figure tesla announced billion convertible debt offering tesla offer million convertible senior note due million due build world largest battery factory elon musk predict factory produce battery vehicle tesla expect send kilowatthour price battery percent plan construction start production beginning facility hold worker million square feet factory space plant provide recycling capability battery pack musk panasonic supplying hundred million cell tesla join factory commitment made here rendering proposed plant tesla financial tesla revenue million percent gross margin firm sold record model vehicle period expecting ship model unit representing percent growth production expected increase current level car week car week end year firstquarter production expected vehicle battery cell supply continue constrain production half year improve significantly half tesla new week national highway traffic safety administration nhtsa closed investigation fire involving teslas model road debris piercing batterypack nhtsa report read teslas revision vehicle ride height addition increased underbody protection reduce frequency underbody strike resultant fire risk defect trend identified accordingly investigation closed greentech media gtm produce industryleading new research conference businesstobusiness greentech market coverage areas include solar smart grid energy efficiency wind nonincumbent energy market information visit greentechmediacom follow twitter facebook related post coming soon latest comment bobmeinetz low price gas stagnant economy killing nuke dan found the low price gas curious attribution killing nuclear june bobmeinetz firstenergy fail test utility competition bailout bid grace idea electric utility heavily regulated state government myth june bobmeinetz treasure sierra nevada roger geoengineering scheme afloat appear merit most june grace adam firstenergy fail test utility competition bailout bid sound income care earn june advisory panel scott edward anderson consultant blogger media commentator blog green sceptic christine hertzog consultant author professional explainer focused smart grid elias hinckley strategic advisor energy finance energy policy investor energy company government gary hunt gary executiveinresidence deloitte investment extensive experience energy utility industry jesse jenkin graduate student researcher mit expertise energy technology policy innovation jim pierobon help trade government agency company communicate cleaner energy solution geoffrey style managing director gsw strategy group llc awardwinning blogger featured contributor ","m_szGeo1":"United Kingdom","m_szSourceType":"source_industry","m_szSrcUrl":"http://www.theenergycollective.com/eric-wesoff/361561/teslas-5b-giga-battery-factory-and-deep-politics-az-tx-nv-and-nm","m_Places":["Tesla","Texas","Arizona","New Mexico","Nevada","San Antonio","Lubbock","West Texas","Tucson","Mesa","Mesa, Az","Brewer","Albuquerque","Northern Nevada","Reno","New York","Ohio","New Jersey","Massachusetts","Minnesota","United States","Bid","Gary"],"m_People":["Eric Wesoff","Elon Musk","Rick Perry","Mayor Jonathan","Mayor Scott","Susana Martinez","Katie Tweed","Maria Bartiromo","Grace Adams","Scott Edward","Christine Hertzog","Elias Hinckley","Hunt Gary","Jesse Jenkins","Jim Pierobon","Geoffrey Styles"],"m_Companies":["Az","Tesla Motors","2020","Luring","San Antonio Express-news","Phoenix Business Journal","Arizona Daily Star","Apple","Reno Gazette","Phoenix","Fox Business Channel","Panasonic","U.s. National Highway Traffic Safety Administration","Nhtsa","Facebook","Firstenergy","Bid Grace","Sierra Nevada","Deloitte","Strategy Group, Llc"],"m_BiGrams":["battery factory","direct sale","elon musk","san antonio","phoenix business","business journal"],"m_TriGrams":["phoenix business journal"],"m_SocialTags":[],"m_Topics":[],"m_Industry":[],"m_Technology":[],"m_BiCnt":[4,4,3,3,3,3],"m_TriCnt":[3],"m_iDocBodyWordCnt":801}
