{"m_szDocID":"227473","m_szDocTitle":"Solar Power Funding Healthy in Q2 Despite Industry Turmoil - CleanTechnica","m_szYear":"2012","m_szDocSumamry":"Solar Power Funding Healthy in Q2 Despite Industry Turmoil August 22nd, 2012 by Andrew     Total funding in the solar energy sector amounted to more than $4.3 billion spread across 66 transactions in the second quarter of 2012, with strong results in venture capital funding, debt funding, and corporate funding in particular, according to a Mercom Capital Group report. Mercom’s 2Q solar energy market research results are especially encouraging given reports “of solar companies downsizing or going out of business seemingly every day.” That was the case for venture capital (VC) funding in Q2, for","m_szDocBody":"solar power funding healthy industry turmoil andrew total funding solar energy sector amounted billion spread transaction quarter strong result venture capital funding debt funding corporate funding particular mercom capital report mercom solar energy market research result encouraging report solar company downsizing business seemingly day case venture capital funding example million transaction slightly higher average size investment solar energy sector dropping consistently large deal rare mercom point solar funding m&a report billion solarfocused investment fund decline largescale project funding indicative solar energy solid longterm fundamental clean tech solarfocused investment fund total capital commitment billion announced mercom count ranking top list frankfurtbased prime capital million prime renewable targeting investment europe usbased private equity firm denham capital management allocating million capital denham commodity partner fund renewable power company kleiner perkin caufield byer kpcb venture fund dubbed kpcb focusing making investment earlystage digital consumer enterprise green technology life science company largescale solar power project funding declined slightly quarteroverquarter totaling billion transaction compared billion largescale solar power project funding announcement solar combined funding total million concentrated solar power csp frequently referred solar thermal power accounted million largescale project funding thinfilm project totaled million top largescale solar power project funding included moroccan solar agency arranging million funding ouarzazate csp project million financing concluded luxcara briest solar park germany sempra energy raising million copper mountain solar project noteworthy solar power project financing abengoa raising million solana csp project canadian solar raising million solar power project ontario accounted singlelargest portion largescale solar power project financing largescale solar power project funded total million india ranked project funding concluded israel two morocco ranked term dollar amount million israel third million raised finance solar power project quarter debt funding solar energy spiked quartertoquarter reaching billion transaction compared million deal masraf rayan invested billion debt security qatar solar technology china development bank loaned million yingli green energy china development bank extended yingli term loan million investor vcs turn downstream solar balanceofsystem investing venture capital activity cig copper indium gallium selenide solar company continue popular investor mercom top deal nanosolar raising million cig manufacturing solar company sunrun raising million investor firm investing downstream solar company solar downstream company slightly ahead funding million compared million raised cig company midyear mercom reported solar investment thin film company million panel price falling percent period solar downstream company attractive play report author wrote quarter finally investment catch downstream receiving funding balanceofsystem bos company represent significant opportunity investment innovation cost reduction fall price bos largest slice solar system pie investment bos surprisingly low solar bankruptcy insolvency m&a turning solar energy merger acquisition m&a mercom tracked total transaction disclosing transaction total million big drop compared m&a transaction total totaled billion downside mercom recorded bankruptcy insolvency thinfilm company company announced restructuring downsizing major bankruptcy announcement germany qcell colorados abound solar germanus solar trust america organic pioneer konarka technology contrast solar project m&a increased transaction totaling million completed compare transaction totaling million transaction amount disclosed transaction total mercom reported canadian solar acquiring solar project combined capacity million topped rank solar project m&a transaction quarter wattner million acquisition torno iii solar power plant total capacity included top solar power project m&a transaction luxcaras million acquisition edf energie nouvelle beguey plant nextera energy million purchase proposed blythe solar project solar trust america forveis million acquisition solarias plant million cleantechnicas completely free electric car report electric car early adopter follower want youd attend electric vehicle solar power event conducted cleantechnica date hottest cleantech new subscribing free cleantech newsletter eye sectorspecific new also free solar energy newsletter electric vehicle newsletter wind energy newsletter tag abengoa solar abound solar blythe solar power project briest solar canadian solar china development bank clean energy finance clean tech finance copper mountain solar cs\\p investment denham capital management edf forvei keiner perkin konarka technology luxcara masraf rayan morocco solar nextera energy ouarzazate csp prime capital prime renewable fund qcell qatar solar renewable energy finance sempra energy solana csp solar bankruptcy solar downsizing solar energy debt finance solar energy finance solar energy project finance solar energy venture capital kpcb solar insolvency solar investment fund solar investment solar m&a solar power funding solar power project finance solar project m&a solar finance solar investment solar thermal power solar trust america solaria solar solar investment wattner solar yingli solar andrew reporting writing wide range topic nexus economic technology year now asiapacific europe americas africa middle east issue related broad topical areas pose tremendous opportunity challenge define quality live relationship natural environment related post ","m_szGeo1":"United States","m_szSourceType":"source_industry","m_szSrcUrl":"http://cleantechnica.com/2012/08/22/solar-energy-finance-shows-strong-in-q2-despite-industry-turmoil/","m_Places":["Frankfurt","Europe","Us","Germany","Mw Copper Mountain","Ontario","India","Israel","Morocco","Qatar","America","Asia","Africa","Middle East"],"m_People":["Yingli Solar","Masraf Al Rayan","Atmosphere Blythe","Blythe Solar"],"m_Companies":["Capital Group","Indicative","Denham","Kleiner Perkins Caufield & Byers","Sempra Energy","Abengoa","Solar Technologies","China Development Bank","Nanosolar","Slice","Konarka Technologies","Nextera Energy","Nexus"],"m_BiGrams":["solar power","solar energy","power project","project funding","solar project","finance solar","largescale solar","raising million","venture capital","solar company","solar investment","project m&a","funding solar","investment solar","investment fund","total million","canadian solar","china development","development bank","transaction total","m&a transaction","solar trust","trust america","million acquisition","energy finance"],"m_TriGrams":["solar power project","largescale solar power","power project funding","china development bank","solar project m&a","finance solar energy"],"m_SocialTags":[],"m_Topics":[],"m_Industry":[],"m_Technology":[],"m_BiCnt":[16,11,11,6,6,6,5,5,4,4,4,4,3,3,3,3,3,3,3,3,3,3,3,3,3],"m_TriCnt":[11,5,3,3,3,3],"m_iDocBodyWordCnt":739}
