{"m_szDocID":"228079","m_szDocTitle":"UK Pension Fund to Offer Healthy Returns, Free Solar Power for Social Housing - CleanTechnica","m_szYear":"2012","m_szDocSumamry":"UK Solar Pension Fund to Offer Healthy Returns, Free Solar for Social Housing September 5th, 2012 by Andrew     CleanTechnica’s been reporting on investors’ increasing comfort level and investments  — both direct and indirect — in the still fast-growing solar, wind, and renewable energy sectors. Along those lines, UK-based BusinessGreen on Aug. 31 reported that London-based Goldfield Partners has launched what’s thought to be the UK’s first pension fund dedicated to financing the purchase, installation, and maintenance of residential solar power systems for social housing residents. What stand","m_szDocBody":"solar pension fund offer healthy return free solar social housing andrew cleantechnicas reporting investor increasing comfort level investment direct indirect fastgrowing solar wind renewable energy sector line ukbased businessgreen aug reported londonbased goldfield partner launched what thought uks pension fund dedicated financing purchase installation maintenance residential solar power system social housing resident stand make goldfield partner proposed million million solar green energy fund unit trust appealing investor stable inflationadjusted return return based investor benefiting uks solar feedin tariff fit retail investor havent participate directly point time stand make appealing living governmentsupported housing solar photovoltaic system installed free bringing solar power masse goldfield partner confident meet solar green energy fund initial million subscription target company contract residential solar system installer place entire amount hope fund lot free solar people afford equipment place goldfield partner chief executive david gammond told businessgreen raise expect fund bigger certainly challenge pitfall peculiar generic investor put capital work upandcoming renewable energy sector make good business sense institutional investor significant way term longterm investment return performance term social environmental responsibility moreover renewable energy sector investor benefit greatly government representative regulator banking finance accounting industry association tweaked tax accounting rule regulation provide equal opportunity solar wind renewable energy project developer advantage wider range investment vehicle master limited partnership accelerated depreciation schedule advantage oil gas company project developer taking advantage decade underpinning supporting federal state energy policy true government country renewable energy socially environmentally responsible engine economic growth development goldfield partner gammond acknowledged uks fit force solar green energy fund management reassess economic social housing solar power system project weve worked hard good price equipment installation social housing economy scale street once quoted saying feedin tariff change dramatically price equipment pre obama administration worked fought hard steadfastly erect mutually reinforcing proactive framework energy policy move boldly cleaner sustainable energy ecosystem economy driven renewable energy system technology hes met fierce wellfunded opposition federal energy policy remain hand oil gas nuclear industry interest force ramping spending public relation campaign vote determine road head down out voice heard vote candidate envision cleaner healthier sustainable economy future all cleantechnicas completely free electric car report electric car early adopter follower want youd attend electric vehicle solar power event conducted cleantechnica date hottest cleantech new subscribing free cleantech newsletter eye sectorspecific new also free solar energy newsletter electric vehicle newsletter wind energy newsletter tag affordable solar businessgreen clean energy economy clean energy fund clean energy investment community solar housing environmentally responsible investing free solar goldfield partner green building socially responsible investing solar energy fund solar energy investment solar feedintariff solar fit solar green energy fund solar housing solar pension fund sri sustainable development clean energy investing energy policy government housing pension fund residential solar social housing solar energy solar feedin tariff solar fit unit trust carbon economy andrew reporting writing wide range topic nexus economic technology year now asiapacific europe americas africa middle east issue related broad topical areas pose tremendous opportunity challenge define quality live relationship natural environment related post ","m_szGeo1":"United States","m_szSourceType":"source_industry","m_szSrcUrl":"http://cleantechnica.com/2012/09/05/uk-solar-pension-fund-to-offer-healthy-returns-free-solar-for-social-housing/","m_Places":["Uk","Along","London","Us","Asia","Europe","Africa","Middle East"],"m_People":["David Gammond","Obama"],"m_Companies":["Pension Fund","Goldfield Partners","Target","Ramping","Uk Government","Nexus"],"m_BiGrams":["renewable energy","goldfield partner","energy fund","social housing","pension fund","free solar","solar power","solar green","green energy","housing solar","energy policy","solar energy","clean energy","energy sector","residential solar","feedin tariff"],"m_TriGrams":["solar green energy","green energy fund","renewable energy sector"],"m_SocialTags":[],"m_Topics":[],"m_Industry":[],"m_Technology":[],"m_BiCnt":[6,6,6,5,4,4,4,4,4,4,4,4,4,3,3,3],"m_TriCnt":[4,4,3],"m_iDocBodyWordCnt":496}
