{"m_szDocID":"228198","m_szDocTitle":"Breaking Into The Top 20 US Car Sales (Poll Results) | CleanTechnica","m_szYear":"2014","m_szDocSumamry":"Breaking Into The Top 20 US Car Sales (Poll Results) August 19th, 2014 by Zachary Shahan   Answers are still trickling in, but I think it’s a good time to report on where things stand now. 11 days ago, I published a story on how Nissan LEAF sales compare with the sales of the top 20 cars in the US . I ended with a poll, asking you intelligent readers when you think an electric car (100% electric or plug-in hybrid/extended-range electric) will first break into the top 20 of US car sales. This is actually very similar to a poll I conducted in July/August 2013, so I was curious to see how they co","m_szDocBody":"breaking top car sale poll result zachary shahan answer trickling good time report stand now day ago ipublished storey nissan leaf sale compare sale top car ended poll intelligent reader electric car electric plugin electric break top car sale similar poll iconducted curious compared poll question electric car break top global auto sale result match pretty well year won poll decent spread year side year slightly easier challenge winning option lot people choosing lot choosing pretty selected thought plugin car break top carsale electric car thinking nissan leaf tesla model iii agree you tonne reader answered poll havent chimed ahead change considerably ill write update thought poll course chime below half fun comment sectionimho cleantechnicas completely free electric car report electric car early adopter follower want youd attend electric vehicle solar power event conducted cleantechnica date hottest cleantech new subscribing free cleantech newsletter eye sectorspecific new also free solar energy newsletter electric vehicle newsletter wind energy newsletter tag nissan nissan leaf tesla tesla model iii top car sale top car zachary shahan tryin and specy letter time spend time cleantechnica director chief editor otherwise enthusiastically fulfilling duty obsession gas solar love planetsave bikocity president important media zach recognised globally solar energy electric car energy storage wind energy expert speak related conference event connect social media zacharyshahancom related post mandate carbon taxe teslas quarterly conference call cleantech talk cmcnestt matter hard core bev fan pip roomy person fact average american not average american male lbs waist midsize car prefer full size car real world mile range sufficient buying population greatly expand bev market mile real world range include total mile real world range break cover minimum population insist gasoline car huge tank diesel mile range legitimate reason regional travelling salesmen western state psychological disorder extreme range anxiety bobwallace current mile range work driver mile work mile make evs work driver youre overestimating people drive day bobwallace legitimate reason regional travelling salesmen western state psychological disorder extreme range anxiety travelling sale people dont stop lunch driving mile western state suspect short year supercharger mile spot contiguous mint current mile range work driver define work people rarely mile day ability conveniently drive part fundamental allure car data great rational businesse lot important irrational consumer bobwallace number household vehicle day vehicle driving mile blue moon rental used number people simply drive long distance rare rental work youre pushing desire mint dont convince convince car buyer step back car market abundance luxury cost premium saving couple second etc combination desire disposable income crazy buy car eat majority depreciation cost jouni valkonen gen tesla model alternatively model tesla model iii tesla horizontal bar vertical bar make sense china japan character underline international imago tesla teslas stylized also kyle field neat sharing love double meaningit confuse heck americansbut tesla cool theyll learn know kyle field winner pure range imho doesnt matter tesla iii leaf volt gen announced offgridman agree pure aspect mile range cut big share highway speed fast charge minute make long trip family kid feasible adding trip time excessively happened city car hour trip order break mass market sale compare ice range size big factor subcompact isnt cut people foot more fast food belly elbow room longer trip kid squabbling ear reason sale bigger vehicle successful smart musk make model modified suv kyle field lol fast food belly found bmw fantastically roomybigger prius term passenger room storage capacity tiny improvement passenger space sufficient imho agree range tipping point masse bobwallace suspect sery tipping point rock solid mile range mile worst driving condition heater turned high larger extra digit mile minute charging good point put mile destination convenient range charging stop weekend trip mile make driving day increase range bring adopter offgridman reason thinking range stepping point trip state state state mile time year family holiday take hour depending traffic interstate speed problem stretching hour accommodate charging time taking longer kid stop night someplace add expense messe schedule day travel lost school holiday time range need condition apply time year bobwallace mile range youre destination hour couple minute charge stop worst driving fuel machine minute fuel stop minute food stop sort typical thinking charging time people tend forget stop make driving solid mile grocery store back let onecharge hop san francisco stroke offgridman accounting stop depending fall asleep part journey longer meal walking dog perfect charging time car trip gas stop filled mile kind spoiled aspect worth extra couple hour filled free panel leave supercharger way add mile catch them ready production wont mine year due signing offgridman found earlier model prius comfortable move seat couple notches adult sit driver trunk space reasonable people lot luggage was driving airport shuttle hill live hour trip roomier betterhavent opportunity one doesnt electric range needed folk live country kyle field drive prius youll plenty room iperhap gen mileage scaled bit offgridman need needing wheel drive time year space haul stuff back feed store month counting mile range long trip time year waiting model reservation through sell car leave truck parked year show sooner similar capability quality lower price reconsider drive mile day week errand taking kid extracurricular activity charging infrastructure panel isnt meet yet mint rex great solution now guessing youre waiting model offgridman extender meet all bring bag animal food back feedstore month doesnt wheel drive quarter mile driveway snowed couple time year state year hundred mile closest charging infrastructure away number time needed stop charge add lot time trip gas roomy accommodate myself son medium big dog luggage well boy arent big yet headed way planned future waiting tesla reservation model requirement made back february time pre order front year production mine expensive meet couple tonne firewood couple time year diesel truck that plan car buy mean replacing battery pack point mint cool itll hit youll enjoy sorry didnt recent post detail replied post primary concern range longer trip point thing lament refuel frequently trip make year kind thinking people buying evs take trip year decade give people pause teslas model inflexion point evs people driving day average offgridman excuse extended reply then disqus making reply original explanation putting panel year ago interested point lot research converting golf picked purpose great capability warranty aspect commercially djr big factor subcompact market home charging home crowd averse limit home charging urban areas moot point bobwallace driver place plug work expand opportunity work school portion evs plugged day benefit utility give nice dispatchable load smooth problem outlet apartment condos curbside charging grow well offgridman part country atlanta georgia area beginning covered atlanta city california encouraging evs time new year apartment complexe charging station local listing rental separate section provide fee basis included rent similar practise city speak atlanta due living hour drive away remember pleased made charge point showing gas station fifteen year ago commuted mint something crowd small segment car market fact year old comprise market nowaday ","m_szGeo1":"United States","m_szSourceType":"source_industry","m_szSrcUrl":"http://cleantechnica.com/2014/08/19/breaking-top-20-us-car-sales-poll-results/","m_Places":["Us","Tesla","Take","China","Japan","Atlanta , Georgia","Atlanta","California"],"m_People":["Zachary Shahan","So Tesla","Jouni Valkonen"],"m_Companies":["Cleantech","I3","Diesel","The Thing","Volt","Bmw","Seat"],"m_BiGrams":["mile range","electric car","time year","top car","kyle field","car sale","break top","tesla model","model iii","real world","western state","work driver","charging time"],"m_TriGrams":["top car sale"],"m_SocialTags":[],"m_Topics":[],"m_Industry":[],"m_Technology":[],"m_BiCnt":[8,6,6,5,4,3,3,3,3,3,3,3,3],"m_TriCnt":[3],"m_iDocBodyWordCnt":1138}
