{"m_szDocID":"228974","m_szDocTitle":"Clean Car & Bike News Roundup | CleanTechnica","m_szYear":"2012","m_szDocSumamry":"Clean Car & Bike News Roundup September 23rd, 2012 by Zachary Shahan     There’s so much going on in the world of clean(er) cars and bike news. Here’s a roundup of some stories from around the interwebs from the past week or so that we haven’t yet covered (see our Clean Transportation category for more): Clean Cars ChargePoint is giving away (yes, giving away… for $0) electric car chargers. “ Until Monday, October 15, 2012,  ChargePoint says it will give away a free charging station and offer discounted installation costs to any company looking to install electric car charging stations for its","m_szDocBody":"clean car bike new roundup zachary shahan world cleaner car bike new here roundup storey interweb past week havent covered see clean transportation category more clean car chargepoint giving yes giving electric car charger monday chargepoint give free charging station offer discounted installation cost company instal electric car charging station employee visitor chance win design bmw else local motor teaming bmw offer grand prize design urban car concept good ultimate driving machine coda grab market californiabased automaker plan electric car nationwide coming year working dealer network span coast coast daimler betting lower cost attracting people electric vehicle company smart car mercedesbenz offer cheapest electric car market delivery esmart sent esmart offer mile driving charge mile smart car owner drive europe lowest price point euros dollar smart coollooking concept car calledsmart forstar carsallelectric drivetrain famed mercede tuner brabus chris demorro inform interesting smart car offer mile range kwh battery pack pretty pic gas tesla table reportedly small crossover sport car tesla motor crossover sport car set hit market then alreadyunveiled model suv start rolling factory entrylevel sedan point elon musk ceo tesla hope roll allelectric supercar toyota rav leasing down wellqualified lessee driving toyota rav month yup thatll cost you good deal youd pay buy rav bmw hybrid bmw frontwheel drive car bmw concept active tourer hasnt officially fwd designation mind you speculation comment bmw executive point case concept active tourer litre turbocharged cylinder gas generator charge lithiumion battery pack good mile evonly driving that gas generator kick active tourer reportedly mph second hybrid upcoming porsche spyder hybrid brochure leaked car have horsepower getting mpg leaked brochure pretty hybrid car gas interestingly hybrid car save money hybrid car tested industry analyst reportedly save money long run lincoln mkz hybrid saving buyer chevrolet tahoe hybrid cost buyer than comparably equipped conventional vehicle hot weather killing nissan leaf battery independent test arizonan car showing wouldnt verified yet test owner legit heat arizona decreasing lifespan battery faster nissan promised smith electric vehicle announced pursuing ipo quickly pulled plan intend withdraw registration statementwe received significant interest potential investor however unable complete transaction valuation size interest company existing shareholder bryan hansel smith chief executive officer elected pursue private financing opportunity support execution business plan mercede classy electric concept car gawk mercede bclass electric drive horsepower electric motor lithiumion battery unmentioned size give bclass range mileswith volt volt recharge port bclass electric drive recharged hour however bclass mile mile baseclass tesla model sedan speaking model youre lost soul doesnt evs fun cheque great video ofpike peak racing legend monster tajima driving tesla model bike trike interbike looked lot fun gass susanna schick interesting note conference share taster here start article bicycle car sold year past year exponential rise commuter cycling recession inspired people walk life save gas money car bikethe benefit increased commuter cycling outweigh risk daredevil endorphin body traffic list polaris electric bike unveiled interbike course big product launch interbike evs polariss electric bicycle ebike theyre launching full line electrified bicycle model designed meet broad range rider need peugeot companion vehicle upcoming dieselelectric peugeot onyx supercar threewheeled plugin hybrid onyx scooter concept cool bondesque trike transform now transforming bit onyx scooter concept feature centermounted clip box removed onyx scooter urban mode make like well scooter clip box onyx scooter superbike scooter also threewheel cannondale cerv abike adjust geometry respond straight hill rider doesnt interesting different jos detail gas image too ill share demonstrate bike adjusted cleantechnicas completely free electric car report electric car early adopter follower want youd attend electric vehicle solar power event conducted cleantechnica date hottest cleantech new subscribing free cleantech newsletter eye sectorspecific new also free solar energy newsletter electric vehicle newsletter wind energy newsletter tag hybrid car hybrid electric car hybrid bmw bmw concept active tourer bmw electric vehicle charger bmw electric vehicle bmw hybrid electric vehicle brabus cannondale cannondale cerv cerv chargepoint coda coda electric car coda electric vehicle daimler daimler electric car daimler electric vehicle electric vehicle charger businesse charger free electric vehicle charger interbike interbike local motor mercede mercede bclass electric drive mercede electric car mercede electric vehicle monster tajima nissan leaf nissan leaf battery nissan leaf battery hot weather onyx scooter peugeot peugeot electric vehicle peugeot onyx peugeot onyx scooter polaris porsche porsche spyder hybrid porsche electric car porsche electric vehicle rav scooter smart smart electric car smart electric vehicle smart forstar smartfortwo smith electric vehicle tesla tesla model toyota electric vehicle toyota rav videos zachary shahan tryin and specy letter time spend time cleantechnica director chief editor otherwise enthusiastically fulfilling duty obsession gas solar love planetsave bikocity president important media zach recognised globally solar energy electric car energy storage wind energy expert speak related conference event connect social media zacharyshahancom related post ","m_szGeo1":"United States","m_szSourceType":"source_industry","m_szSrcUrl":"http://cleantechnica.com/2012/09/23/clean-car-bike-news-roundup/","m_Places":["California","Europe","Us","Tesla","Best","Arizona","Monster","Toyota"],"m_People":["Zachary Shahan","Urban Mode","Mercedes-benz B-class","Chris Demorro","Elon Musk","Porsche , Porsche","Bryan Hansel","Susanna Schick","Cannondale Cerv"],"m_Companies":["Bmw","Nationwide","Mercedes-benz","Brabus","Tesla Motors","Lifespan","Volt","Polaris","Peugeot"],"m_BiGrams":["electric vehicle","electric car","onyx scooter","active tourer","hybrid car","nissan leaf","smart car","toyota rav","concept active","leaf battery","bclass electric","electric drive","peugeot onyx","vehicle charger"],"m_TriGrams":["concept active tourer","bclass electric drive"],"m_SocialTags":[],"m_Topics":[],"m_Industry":[],"m_Technology":[],"m_BiCnt":[17,13,6,4,4,4,3,3,3,3,3,3,3,3],"m_TriCnt":[3,3],"m_iDocBodyWordCnt":785}
