{"m_szDocID":"229045","m_szDocTitle":"UK Electric Car Sales Skyrocketing! | CleanTechnica","m_szYear":"2015","m_szDocSumamry":"UK Electric Car Sales Skyrocketing! Originally published on EV Obsession . Electric vehicle (EV) registrations in the UK between January and May of 2015 are already roughly equal to total EV registrations in 2014, based on the most recent figures from the Society of Motor Manufacturers and Traders (SMMT). Apparently, there have already been 11,842 ultra-low-emission vehicles (ULEVs) registered in the UK this year (as of the end of May). This compares to 2,838 units registered during January–May 2014 — which means that more than 4 times the number of ULEVs have been registered this year as comp","m_szDocBody":"electric car sale skyrocketing originally published obsession electric vehicle registration roughly equal total registration based recent figure motor manufacturer trader smmt apparently ultralowemission vehicle ulevs registered year end may compare unit registered januarymay mean time number ulevs registered year compared ulevs registered impressively allelectric vehicle making yearonyear improvement period record year ulev sale number show exponential trend year continue year well altogether alternatively fuelled vehicle alternatively fueled vehicle sold show number rising rise specific ulev category down smmt representative fact consumer acquainted advantage ulevs and reality existence general and also tothe increased offering market ulevs model now compared back remarkable growth demand plugin vehicle expected continue range ultralow emission vehicle sale increase stated mike hawe chief executive smmt image credit motor manufacturer trader cleantechnicas completely free electric car report electric car early adopter follower want youd attend electric vehicle solar power event conducted cleantechnica date hottest cleantech new subscribing free cleantech newsletter eye sectorspecific new also free solar energy newsletter electric vehicle newsletter wind energy newsletter tag sale electric car sale electric car sale jame ayre background predominantly geopolitic history obsessive interest pretty everything early life spent imperial free city dortmund jame river ruhr cofbuokheim attended university astnide briefly considered entering coal mining business write living broad variety subject ranging science politic military history renewable energy follow work google related post electrified london black cab surpass legal challenge wattleberry great new timely recognition larger saving made based huge difference pump price agree fully comment ampera failing lack versatility brian alf smmt web registration number standard petrol deisel car compared may figure dag johansen mitsubishi outlander phev responsible big surge reason chevy ampera mitsubishi outlander phev huge hit bring usa asap phev suvs huge usa model available ampera longer sale here found recently arrange test drive one told withdrawn sale due lack demand advertised more reason lack sale produced vauxhall opal mainland europe doesnt great reputation reliability lot vauxhall road though inexpensive car think damien vigneron agree main problem seater only small boot size low dashboard cheap easy use generation volt fix problem car orlando sold more european people small roomy car waiting hybrid honda hrv reach europe jameswimberley chart phevs grew faster bevs older nonplugin hybrid stalled british buyer suffer range anxiety change charger network rolled out england opposed scotland wale densely populated wide charger coverage quickly dag johansen success mitsubishi outlander phev steve grinwis sparsely populated canada charging network rolling fast mikedyke selling point phev pushed fact electric power line lot faster pure ice version car environment nice bonus phev electric range phev car pure electric mode save fill petrol persuading buyer completely pure electric pay backup ice car havent month bobwallace yep phevs gateway drug stefanor love tesla responsible jump remember launch time year martin good new day registration total registration year world scale reason whatsoever ice moter running sitting city traffic ","m_szGeo1":"United States","m_szSourceType":"source_industry","m_szSrcUrl":"http://cleantechnica.com/2015/06/13/uk-electric-car-sales-skyrocketing/","m_Places":["Uk","Free City","Dortmund","U.s.","Usa","Vauxhall","Europe","Vauxhalls","Orlando","England","Scotland","Wales","Canada","Tesla"],"m_People":["Mike Hawes","James Ayre","Electrified London","Dag Johansen","Chevy Volt","Damien Vigneron","Steve Grinwis"],"m_Companies":["University Of Astnide","Google","Volt","Honda"],"m_BiGrams":["electric car","car sale","electric vehicle","ulevs registered","mitsubishi outlander","outlander phev"],"m_TriGrams":["electric car sale","mitsubishi outlander phev"],"m_SocialTags":[],"m_Topics":[],"m_Industry":[],"m_Technology":[],"m_BiCnt":[5,3,3,3,3,3],"m_TriCnt":[3,3],"m_iDocBodyWordCnt":474}
