{"m_szDocID":"229738","m_szDocTitle":"Japanese Solar Energy Sector Fast Approaching Cost-Revenue Parity | CleanTechnica","m_szYear":"2015","m_szDocSumamry":"Japanese Solar Energy Sector Fast Approaching Cost-Revenue Parity June 18th, 2015 by James Ayre   Japan’s solar energy sector is fast approaching profitability, ahead of impending feed-in-tariff (FiT) cuts, according to the Japan Renewable Energy Foundation. To be more specific here, the Japan Renewable Energy Foundation (JREF) is expecting cost-revenue parity to be reached, and profitability to be achieved, sometime earlier than the second half of 2015. Given that Japan’s Ministry of Economy, Trade, and Industry, will be cutting FiT rates by 16% in July, the prediction is especially worth not","m_szDocBody":"japanese solar energy sector fast approaching costrevenue parity jame ayre japan solar energy sector fast approaching profitability ahead impending feedintariff fit cut japan renewable energy foundation specific here japan renewable energy foundation jref expecting costrevenue parity reached profitability achieved earlier half japan ministry economy trade industry cutting fit rate july prediction worth noting jref trend prediction partly due supportive governmental policy fukushima nuclear power plant disaster back policy intended country move nuclear energy altogether disaster country added impressive gigawatt renewable energy capacity number fromsolar energy project industry matured great deal there help economy scale bring consumer acquisition cost solar age japan replacing imported uranium fossil fuel stated jref executive board chairman tomas kaberger protect fossil fuel nuclear plant japan electric power company delay development here worth regard residential solar energy production cost fallen half country sitting kwh based current exchange rate mean solar energy residential electricity price average one year country interesting observe outsider big nearing image credit public domain cleantechnicas completely free electric car report electric car early adopter follower want youd attend electric vehicle solar power event conducted cleantechnica date hottest cleantech new subscribing free cleantech newsletter eye sectorspecific new also free solar energy newsletter electric vehicle newsletter wind energy newsletter tag japan japan renewable energy japan renewable energy foundation japan solar energy jame ayre background predominantly geopolitic history obsessive interest pretty everything early life spent imperial free city dortmund jame river ruhr cofbuokheim attended university astnide briefly considered entering coal mining business write living broad variety subject ranging science politic military history renewable energy follow work google related post solar power continue make headway japan world spain supported solar criminal offence law happen japan australia make solar criminal offence retrospective fine owner coley nice abbot team feasibility study type coley vensonata math formula make rate cent kwh estimate tend vary widely depending year production anywhere interest rate calculation soft cost permitting inverter replacement estimate subject relentless scrutiny make magic number false example inverter replacement calculated year micro inverter warrantied year string inverter falling year replacement cost cost inverter financing method reduce interest calculation inflation factor guessed etc etc etc ronald brakel dont forget habit knocking house year japan gotta smart working cost mind you effective interest rate household gotta help calamityjean builder habit including roof house ivor oconnor fit fit pay currently average residential price kwh percentage electricity supplied solar altairiv dont apply country fall standard kansai electric residential plan simple tiered system charge approximately yen flat fee kwh yen kwh yen kwh yen kwh small flat fee tacked well number rising slowly steadily crisis theyve approved rate hike full effect autumn ivor oconnor detail jameswimberley cost international standard germany small roof land price utility red tape preference highcost domestic supplier matt residential solar energy production home roof top instal dont land cost roof brett pretty japan expensive jurisdiction dont stat compare consumer price indexe country cost rent japan checked tokyo cheapest bedroom apartment approx month bang buck doesnt unbelievable jacob japan corrupt closed brazil issue import taxe bobwallace sort money cheap studio san franciso city brett san francisco stupid expensive family member living couple year paying month crap apartment good location real estate point comparison electricity dont proxy demonstrate variability cost living altairiv price central tokyo dont reflect rest country experience pay half sized room kitchen apartment osaka larger bit suburb cost living personal experience guesstimate yen will average give purchasing power cent typical american city hard compare though variable electronic arent expensive food entertainment cost more ","m_szGeo1":"United States","m_szSourceType":"source_industry","m_szSrcUrl":"http://cleantechnica.com/2015/06/18/japanese-solar-energy-sector-fast-approaching-cost-revenue-parity-according-japan-renewable-energy-foundation/","m_Places":["Japan","Fukushima","Gw","Atmosphere","Free City","Dortmund","Spain","Australia","Germany","Tokyo","Brazil","Osaka","U.s."],"m_People":["James Ayre","Tomas Kaberger","Ronald Brakels","Ivor O’connor"],"m_Companies":["Japanese Solar Energy","Ministry Of Economy","Public Domain","University Of Astnide","Google"],"m_BiGrams":["solar energy","renewable energy","japan renewable","energy foundation","kwh yen","yen kwh"],"m_TriGrams":["japan renewable energy","renewable energy foundation"],"m_SocialTags":[],"m_Topics":[],"m_Industry":[],"m_Technology":[],"m_BiCnt":[7,6,3,3,3,3],"m_TriCnt":[3,3],"m_iDocBodyWordCnt":581}
