{"m_szDocID":"229973","m_szDocTitle":"EV Battery Use Trumps Hybrid Battery Use","m_szYear":"2014","m_szDocSumamry":"EV Battery Use Trumps Hybrid Battery Use September 7th, 2014 by Cynthia Shahan   Plug-in electric cars are still a very small percentage of the market compared to conventional hybrid cars, but their battery capacity is not so small. With plug-in car sales growing in leaps and bounds , their annual battery use already trump the annual battery use of hybrids, but what about all time use? According to one  Green Car Reports  calculation, “electric cars to date have used as much battery capacity as every hybrid built in the past 17 years.” Green Car Reports asked two of its contributors to estimat","m_szDocBody":"battery trump hybrid battery cynthia shahan plugin electric car small percentage market compared conventional hybrid car battery capacity smallwith plugin car sale growing leap bound annual battery trump annual battery hybrid time use green car report calculation electric car date battery capacity hybrid built past year green car report asked itscontributor estimate relative battery capacity totalfor electriccar versus hybrid sale tackled sale tackled total cumulative sale john brigg looked sale single year estimated average hybrid batterypack size kwh listed highestselling model weighted plugin sale pack size andconcluded battery capacity plugin electric vehicle versus hybrid vehicle follow plugin electric vehicle kwh hybrid vehicle kwh brian henderson worked total vehicle sale worldwide which whenthetoyota prius market japan naturally challenging calculation henderson estimate ratio electricvshybrid pack size john voelcker green car report considered bit lowdue size plugin pack size varying hybrid pack hard calculation make john estimate based topselling car bracket taking toyotas kwh hybrid pack kwh pack world bestselling electric car nissan leaf representative average ratio slice though harder assumption make plugin car side today plugin pack range kwh toyota prius plugin hybrid kwh pack top tesla model size difference timeshybrid pack vary kwh honda mild hybrid kwh large fullhybrid suv john noted based brian assumption plugin car surpass hybrid end year based john happened month ago primary focus ofthe query realise demand lithiumion battery purchase plugin electric car increase increase lot yearstesla finalised itslocation gigafactory company track toproduce affordable model electric car big sale battery cost dropping fast general plenty electric car manufacturer reach capacity well company jumping electric vehicle market note foxconn ceo terry gou electric car price company reputation question hasreached deal byd start rental car business june sound foxcon similarly inspired elon musk intend achieve teslasgigafactory related storey ","m_szGeo1":"United States","m_szSourceType":"source_industry","m_szSrcUrl":"http://cleantechnica.com/2014/09/07/ev-battery-use-vs-hybrid-battery-use/","m_Places":["Japan","Henderson","Toyota","Tesla"],"m_People":["Cynthia Shahan","John C. Briggs","Brian Henderson","John Voelcker","Terry Gou","Elon Musk"],"m_Companies":["Slice","Honda"],"m_BiGrams":["electric car","plugin electric","battery capacity","plugin car","green car","car report","pack size","electric vehicle"],"m_TriGrams":["green car report"],"m_SocialTags":[],"m_Topics":[],"m_Industry":[],"m_Technology":[],"m_BiCnt":[7,4,4,3,3,3,3,3],"m_TriCnt":[3],"m_iDocBodyWordCnt":290}
