{"m_szDocID":"229950","m_szDocTitle":"Honda HRV Popularity Hints At Opportunity For Tesla","m_szYear":"2015","m_szDocSumamry":"Honda HRV Popularity Hints At Opportunity For Tesla June 18th, 2015 by Guest Contributor   Originally published on TeslaMondo . People obviously relish small hatch-SUV-wagon things with optional AWD. Honda just sold almost 6,500 HRVs in its two debut weeks, even though the vehicle offers the sex appeal of an Amish water closet, and even though Honda hasn’t yet run a single advertisement for this sub-CRV entry. Fast forward circa 2017: Tesla apparently will release an AWD crossover version of the Model III. So says the WSJ today — while providing neither a link nor a direct quote. Apparently we","m_szDocBody":"honda hrv popularity hint opportunity tesla guest contributor originally published teslamondo people relishsmall hatchsuvwagon optional awd honda sold hrvs debut week vehicle offer thesex appeal ofan amish water closet honda hasnt run single advertisement subcrv entry fast forward circa tesla apparently release anawd crossover version model iii wsj today providingneither link nora direct quote apparently supposed wsjs word anyway letsassume crossover model iiiisindeed adventurous version musk hinted overnight success hondas flaccid blobsuggeststeslas virilealternative possibly arrive enough undoubtedly toyota rush back space pulling plug matrix year ago developed further doh here window opportunity tesla toenter hot segment sleeping giant wake sure teslas entry cost more teslas brand cachet people digging sofa pillow change tesla fund reprinted permission cleantechnicas completely free electric car report electric car early adopter follower want youd attend electric vehicle solar power event conducted cleantechnica date hottest cleantech new subscribing free cleantech newsletter eye sectorspecific new also free solar energy newsletter electric vehicle newsletter wind energy newsletter tag crossover honda honda hrv tesla tesla motor guest contributor many people publish number guest post expert large variety field contributor account special people related post mandate carbon taxe teslas quarterly conference call cleantech talk jonesey green functional golf tdi mpg highway mpg overall acceleration honda improvement tenyearold car frustrating automaker yes article point tesla hatchback affordable lifetime cost range put city car category drove mile today stop longer minute half tank fuel ill put deposit heartbeat adrian nice subaru forester generation bigger yes ive wanting small hybrid awd cuv forester recently updated allelectric bring tesla soon eveee taking close rear hatch opening smaller lower typical boxe aerodynamic approval good loading compromise claimed mileage exemplary newnodm top selling car traditional door sedan rear trunk unexciting true martin lot door sedan trunk folding part folding rear seat carry bulky long tuck trailer michael simply false top selling truck long while here top figure truck suvs sedan newnodm car michael ahh selling door sedan trunk door sedan trunk point being kevin mckinney coupe pretty moribund michael thank clear explained kevin mckinney brook bridge distinction what car miss point truck sold function solely mean ferry passenger around theyre frequently door functionally theyre door car open truck bed occasionally car couldnt carry crappy gas mileage ridiculous newnodm billybob call pickup car brook bridge quack car walk car acting car called totally stupid current reality guess truck perform truck function time rest show blame back future foxs character wanting pickup character reflecting trend taking off bobwallace guess truck perform truck function time criterion drove pickup year hauled back time needed hauling ability pickup haul couldnt put back crossover small suv brook bridge understand work friend share truck working far boat trailer occasionally small trailer haul kayak junk time time bobwallace lifestyle unique haul stuff building material horse poop garden firewood typical person ive roll fence wire coil plastic pipe back mine now people zip truck pick curb needed bobwallace agree pickup today door version short bed harder full sized bed truck door pickup suvs leaky rear roof theft protection brook bridge hah dag johansen well tesla people stupid theyve closely looked sale statistic realised wise bring sedan cuv easily skateboard platform model brought quickly market flown close sun falconwing door newnodm dont model originally announced panic lacked confidence selling model paul dag bang tesla made traditional suv door hatch existing model platform selling today updated towing version introduced later mistake tesla surely learn from jason honda build stellar engine dam jeez made chainsaw hope transition making quality electric power system reliability durability michael make lot chainsaw reason sold asia afaik alibaba trust chinese version amazon eveee sofa change amish water closet flaccid blob head spinning car trifecta mpg suv mean quadfecta add awd people buy suv awd space junk door too awd model fail rest appealing crowd all michael hrv door exterior handle rear door hidden upper back corner eveee water closet michael wcs door handmade wood simple style naivete lend understated elegance entire experience eveee ","m_szGeo1":"United States","m_szSourceType":"source_industry","m_szSrcUrl":"http://cleantechnica.com/2015/06/18/honda-hrv-popularity-hints-at-opportunity-for-tesla/","m_Places":["Tesla","Toyota","Us","Nice","U.s.","Brooks","Most","Well","Asia"],"m_People":["Michael G","Kevin Mckinney","Dag Johansen"],"m_Companies":["Honda","Hatch","Indeed","Matrix","Cleantech","Tesla Motors","Mpg","Seat","Guess","Alibaba","Amazon"],"m_BiGrams":["door sedan","brook bridge","water closet","sedan trunk"],"m_TriGrams":["door sedan trunk"],"m_SocialTags":[],"m_Topics":[],"m_Industry":[],"m_Technology":[],"m_BiCnt":[4,4,3,3],"m_TriCnt":[3],"m_iDocBodyWordCnt":660}
