{"m_szDocID":"230287","m_szDocTitle":"Tesla Model X Spy Shots Compilation | CleanTechnica","m_szYear":"2015","m_szDocSumamry":"Tesla Model X Spy Shots Compilation Originally published on EV Obsession . Update: At the request of the photographer, the first two photos in this compilation have been removed. I know — none of us can get enough Tesla Model X spy shots, and none of them are good enough. Still, by now, we’re getting a pretty good look at the thing from different angles and with different degrees of revelation. (Note that most of the picture below come from the Tesla Motors Club forum .) First of all, here are the new spy shots: And here are previous ones that we’ve shared:     Get CleanTechnica’s 1st (complet","m_szDocBody":"tesla model spy shot compilation originally published obsession update request photographerthe photos compilation removed tesla model spy shot good enough still now pretty good angle degree revelation note picture tesla motor club forum all spy shot previous weve shared cleantechnicas completely free electric car report electric car early adopter follower want youd attend electric vehicle solar power event conducted cleantechnica date hottest cleantech new subscribing free cleantech newsletter eye sectorspecific new also free solar energy newsletter electric vehicle newsletter wind energy newsletter tag tesla tesla model tesla model spy pic tesla model spy shot zachary shahan tryin and specy letter time spend time cleantechnica director chief editor otherwise enthusiastically fulfilling duty obsession gas solar love planetsave bikocity president important media zach recognised globally solar energy electric car energy storage wind energy expert speak related conference event connect social media zacharyshahancom related post mandate carbon taxe teslas quarterly conference call cleantech talk wattleberry matter interest narrower itll sell universally bobwallace couple guesstimate yesterday same soon wattleberry thank bob doesnt surprise all vehicle generally bulkier wide norwegian reg part spain huge wider commercial exciting neck wood rawlasvegan nice thank zach shane exterior show car ive before dont oval shape fauxgrille backed area fastback wagonback suvs wagonback storage aerodynamic wagonback vehicle poor leaf wagonback dag johansen picture show door open row seat tilted forward row model bloated model ttman doesnt suv seen basis called suv dag johansen tall allwheel drive vehicle greater clearance ability tow zachary shahan people tesla motor club forum person big suv called cuv see mogget remind people hurry slightly taller model door handy applied sedan ride height useful hurt performance comfort people buy suvs hotcake dont understand why valakos soccer mom mogget fit plenty soccer kid dog back station car dont rockcrawing capability soccer field suvs lousy offroad anyway kraylin agree dont necessarily understand people buy simple fact prove obsessed larger vehicle remain obsession large vehicle carry electric car market zachary shahan some extra head room some prefer sitting bit higher other some simply look mogget odd ungainly bulk suv people for zachary shahan ideas tie including status comfort dag johansen people buy suvs hotcake answered question buy suvs big help crashes people allwheel drive vehicle hold people mogget point suvs safe offroady spacious people paid attention fact crash testing show size isnt object concrete wall lot suvs substandard crash rating undersized brake habit rolling over plenty sedan awd advanced differential rallyinspired car make tall suvs snow ice audi car fly past suvs completely stuck snow real limitedslip differential deceiving epik design road crap kerb front spoiler touch ivor oconnor drag coefficient power relative use more ","m_szGeo1":"United States","m_szSourceType":"source_industry","m_szSrcUrl":"http://cleantechnica.com/2015/06/22/tesla-model-x-spy-shots-compilation/","m_Places":["Tesla","Us","Most","Spain","Nice"],"m_People":["Zachary Shahan","Dag Johansen","Ivor O’connor"],"m_Companies":["Cleantech","I3","Seat","Remind","Audi"],"m_BiGrams":["tesla model","model spy","spy shot","electric car","zachary shahan","dag johansen","people buy","buy suvs"],"m_TriGrams":["tesla model spy","model spy shot"],"m_SocialTags":[],"m_Topics":[],"m_Industry":[],"m_Technology":[],"m_BiCnt":[4,4,4,4,4,3,3,3],"m_TriCnt":[3,3],"m_iDocBodyWordCnt":437}
