{"m_szDocID":"230514","m_szDocTitle":"Video: Meet Sparky, The Nissan LEAF Pickup | CleanTechnica","m_szYear":"2014","m_szDocSumamry":"Published on September 19th, 2014 | by Christopher DeMorro Video: Meet Sparky, The Nissan LEAF Pickup September 19th, 2014 by Christopher DeMorro Â  Elon Musk may have mentioned one day selling an electric pickup truck in passing , but leave it to Nissan to actually build one. Meet Sparky, the offspring of a Nissan LEAF and a Nissan Frontier pickup truck, built by engineers at the Nissan Technical Center in Stanfield, Arizona. Sparky was built to help engineers move themselves and various pieces of equipment around the over 3,000-acre campus. Built by Roland Schellenberg and Arnold Moulinet, th","m_szDocBody":"published christopher demorro video meet sparky nissan leaf pickup christopher demorro elon musk mentioned day selling electric pickup truck passing leave nissan build one meet sparky offspring nissan leaf nissan frontier pickup truck built engineer nissan technical centre stanfield arizona sparky built engineer move piece equipment acre campus built roland schellenberg arnold moulinet project schellenberg was lack word bored needed project team building activity bring team together truck drive around shop truck schellenberg schellenberg teamed moulinet spent day fleshing design spec eventually figured fit nissan frontier short pickup bed rear nissan leaf project supposed secret visitor drawn sparky idea electric pickup truck strike chord american dont sparky dealership lot anytime soon oneoff project designed specifically driving arizona campus job site worry though nissan env electric work van recently launched europe beginning test pilot programme pickup truck step directionperhap sparky serve inspire generation nissan engineer make electric pickup truck masse carry spare tyre slick truck tough boy boy heart put together share bit there schellenberg cleantechnicas completely free electric car report electric car early adopter follower want youd attend electric vehicle solar power event conducted cleantechnica date hottest cleantech new subscribing free cleantech newsletter eye sectorspecific new also free solar energy newsletter electric vehicle newsletter wind energy newsletter tag arizona frontier leaf nissan frontier nissan leaf nissan technical centre sparky stanfield christopher demorro writer gearhead love automotive hybrid hemis chris found wrenching writing else running crazy people enjoyment running insane distance related post rebate impact supercharging ecosystem tesla gigafactory mythbusting cleantech talk useful truck bed minimum capacity hold sheet plywood offgridman depend truck for people construction trade bigger space needed haul bag animal food back feed store month sufficient variety size truck ice driven variety truck trunk back seat car aerodynamic meet nicely abortion offgridman hauling car now pain kid safety seat put back vacuum dust leaked chicken pig mash leak burlap sacking afterward reservation list tesla model room passenger carry plenty cargo space call abortion wish doesnt change fact suitable people need evs stop fossil fuel transportation variety vehicle people taste bobwallace teslas great approach going put battery motor steering suspension frame unit bolt body configuration market want offgridman brought truck point easiest tesla manufacturer ground convert ice truck remember musk future possibility tesla here hoping truck end quality performance model through model bet covering %of need pull trailer couple tonne log load cover retire farm truck car small truck time tell put kid this truck good truck waste effort sell worthwhile offgridman expert market condition people want corporate head automotive manufacturer secret run toyota ford dont understand market dynamic what ill put bet see light day discontinued due low order year put you offgridman not stupid involved random bet gambling early retirement fifty lot model small seat pickup truck ice powered wait year doesnt happen evs talk then thought offgridman thought exactly development production continue year market excepted petty wager year time inflation make worth chump change wouldnt worth tracking collect thought weaselling put shut expected though joseph dubeau sparky cool offgridman determined electric truck leaf part scrap yard reasonable total cost labour isnt accounted for expensive conversion ice small truck part battery controller available wont aerodynamic american great enthusiasm time truck styled vehicle manufacturer start producing evs jbw leaf ugly wanted electric car time lack option canada decided jetta hybrid leaf spark pretty cool predecessor ","m_szGeo1":"United States","m_szSourceType":"source_industry","m_szSrcUrl":"http://cleantechnica.com/2014/09/19/video-meet-sparky-nissan-leaf-pickup/","m_Places":["Stanfield, Arizona","Arizona","Europe","Us","Stanfield","Tesla","Canada"],"m_People":["Christopher Demorro","Elon Musk","Nissan Frontier","Roland Schellenberg","Toyota, Ford","Joseph Dubeau"],"m_Companies":["Nissan","Nissan Technical Center","Cleantech","Seat"],"m_BiGrams":["pickup truck","nissan leaf","christopher demorro","electric pickup","leaf nissan","nissan frontier","electric car"],"m_TriGrams":["electric pickup truck"],"m_SocialTags":[],"m_Topics":[],"m_Industry":[],"m_Technology":[],"m_BiCnt":[6,4,3,3,3,3,3],"m_TriCnt":[3],"m_iDocBodyWordCnt":557}
