{"m_szDocID":"230911","m_szDocTitle":"Mitsubishi Outlander Plug-In Hybrid Finally Coming To The USA | CleanTechnica","m_szYear":"2015","m_szDocSumamry":"Mitsubishi Outlander Plug-In Hybrid Finally Coming To The USA There’s no doubt about it — the  Mitsubishi Outlander Plug-In Hybrid has been a hit in many of the markets where it’s been available. It has been a huge seller in the Netherlands , the UK , Germany (where it has actually taken #1 from several German manufacturers), Sweden , and elsewhere. In Europe as a whole, the Outlander Plug-In is clearly the #1 top-selling plug-in car in 2015 so far . Unfortunately, for US buyers, the Mitsubishi Outlander Plug-In has been delayed for years . But a US release is apparently around the corner. (I ","m_szDocBody":"mitsubishi outlander plugin hybrid finally coming usa doubt mitsubishi outlander plugin hybrid hit market available huge seller netherland germany where german manufacturer sweden elsewhere europe whole outlander plugin topselling plugin car unfortunately buyer mitsubishi outlander plugin delayed year release apparently corner know weve heard before hopeful new real time mitsubishi mitsubishi outlander plugin arrive shore spring season away guessed reason theoutlander plugin hybrid long popularity overseas initially supposed arrive unveiled auto show huge sale europe japan ate battery supply made impractical mitsubishi release vehicle increase supply demand trailed europe japan doesnt demand trailing off presume mitsubishis battery supplier battery day themitsubishi outlander plugin hybrid midcycle refresh updated version popular suv kwh battery pack theoutlander pluginjust mile kilometre range europeandriving cycle mean realworld electric range closer mile that live gasoline still though mile trip offering joy efficiency electric driving spacious suv course plugin suv market arrive tesla model start hitting garage arrival the bmw xdrive plugin hybrid suv hurt sale maybe updated model electricityaware public andmitsubishi sale momentum experience europe japan make sale lost increased competition eager model suvloving image zachary shahan obsession cleantechnica bysa cleantechnicas completely free electric car report electric car early adopter follower want youd attend electric vehicle solar power event conducted cleantechnica date hottest cleantech new subscribing free cleantech newsletter eye sectorspecific new also free solar energy newsletter electric vehicle newsletter wind energy newsletter tag mitsubishi mitsubishi outlander mitsubishi outlander phev zachary shahan tryin and specy letter time spend time cleantechnica director chief editor otherwise enthusiastically fulfilling duty obsession gas solar love planetsave bikocity president important media zach recognised globally solar energy electric car energy storage wind energy expert speak related conference event connect social media zacharyshahancom related post ","m_szGeo1":"United States","m_szSourceType":"source_industry","m_szSrcUrl":"http://cleantechnica.com/2015/06/27/mitsubishi-outlander-plug-in-hybrid-finally-coming-to-the-usa/","m_Places":["Usa","Uk","Germany","Sweden","Europe","Us","Japan","Tesla"],"m_People":["Zachary Shahan"],"m_Companies":["Cycle","Bmw X5"],"m_BiGrams":["outlander plugin","plugin hybrid","mitsubishi outlander","europe japan","electric car"],"m_TriGrams":["mitsubishi outlander plugin","outlander plugin hybrid"],"m_SocialTags":[],"m_Topics":[],"m_Industry":[],"m_Technology":[],"m_BiCnt":[6,5,4,3,3],"m_TriCnt":[3,3],"m_iDocBodyWordCnt":282}
