{"m_szDocID":"231041","m_szDocTitle":"2014 Porsche Cayenne Plug-In Hybrid Electric Vehicle In The Works | CleanTechnica","m_szYear":"2012","m_szDocSumamry":"2014 Porsche Cayenne Plug-In Hybrid Electric Vehicle In The Works November 28th, 2012 by Zachary Shahan     This article has been reposted from EV Obsession with full permission (with minor modifications). When I see Porsche or Ferrari electric vehicles , for some reason, I think, “Wow, that is awesome!” (Oh yeah, that’s because they are awesome.) Porsche Cayenne S Hybrid Electric Vehicle Not only are they awesome because these vehicles are beauties of human workmanship and care, but also because such cars will inspire more people to love electric vehicles . It opens people’s minds to the fact","m_szDocBody":"porsche cayenne plugin hybrid electric vehicle work zachary shahan reposted obsession full permission with minor modification porsche ferrari electric vehicle reason think wow awesome yeah awesome porsche cayenne hybrid electric vehicle awesome vehicle beauty human workmanship care car inspire people love electric vehicle open people mind fact electric vehicle arent simply greeny save money gas and save country oil war everyone open people mind fact electric vehicle fast fun hot sexy beautiful shape size want porsche cayenne plugin hybridelectric phevsuv released wont greenest vehicle there wont cut oil like impact certainly perception impact porsche sellscayenne panamera hybrid cayenne hybrid pic below phev technology step forward clean vehicle future notably however evonly mode cayenne phev expected range mile wait sure youre market luxury suv recommend tesla model beyond fully electric model falcon door supporting traditional car company effort green offering worth something telling neighbour porsche suv electric vehicle porsche cayenne phev new love hate dont give crap image current porsche cayenne hybrid porsche cleantechnicas completely free electric car report electric car early adopter follower want youd attend electric vehicle solar power event conducted cleantechnica date hottest cleantech new subscribing free cleantech newsletter eye sectorspecific new also free solar energy newsletter electric vehicle newsletter wind energy newsletter tag post plug hybrid electric vehicle plugin electric vehicle porsche porsche cayenne porsche cayenne hybrid porsche cayenne phev porsche cayenne plug hybrid porsche porsche suv porsche hybrid electric vehicle porsche phev porsche phev suv porsche plug hybrid electric vehicle zachary shahan tryin and specy letter time spend time cleantechnica director chief editor otherwise enthusiastically fulfilling duty obsession gas solar love planetsave bikocity president important media zach recognised globally solar energy electric car energy storage wind energy expert speak related conference event connect social media zacharyshahancom related post ","m_szGeo1":"United States","m_szSourceType":"source_industry","m_szSrcUrl":"http://cleantechnica.com/2012/11/28/2014-porsche-cayenne-plug-in-hybrid-electric-vehicle-in-the-works/","m_Places":["Cayenne","Tesla"],"m_People":["Zachary Shahan","I See Porsche"],"m_Companies":["Phev Technology"],"m_BiGrams":["electric vehicle","porsche cayenne","hybrid electric","cayenne hybrid","cayenne phev","vehicle porsche","hybrid porsche","electric car","plug hybrid"],"m_TriGrams":["hybrid electric vehicle","electric vehicle porsche"],"m_SocialTags":[],"m_Topics":[],"m_Industry":[],"m_Technology":[],"m_BiCnt":[13,8,5,4,3,3,3,3,3],"m_TriCnt":[5,3],"m_iDocBodyWordCnt":292}
