{"m_szDocID":"231008","m_szDocTitle":"Ford Fusion Energi Price Announced, BMW i3 Concept Unveiled, Tesla Wins Lawsuit, Tesla Model S Price Increasing (+ More Clean Transport News) | CleanTechnica","m_szYear":"2012","m_szDocSumamry":"Published on November 27th, 2012 | by Zachary Shahan 0 Ford Fusion Energi Price Announced, BMW i3 Concept Unveiled, Tesla Wins Lawsuit, Tesla Model S Price Increasing (+ More Clean Transport News) November 27th, 2012 by Zachary Shahan     Some more clean transport news from the past few days or so: EVs Ford Fusion Energi Priced At $39,495 : “Marching forward with its plans to launch a slew of plug-in hybrid vehicles this year, Ford has finally put a price and details to the much-anticipated 2013 Ford Fusion Energi plug-in hybrid. Starting at $39,495 before tax credits, does the Energi have wha","m_szDocBody":"published zachary shahan ford fusion energi price announced bmw concept unveiled tesla win lawsuit tesla model price increasing clean transport new zachary shahan clean transport new past day evs ford fusion energi priced marching forward plan launch slew plugin hybrid vehicle year ford finally put price detail muchanticipated ford fusion energi plugin hybrid starting tax credit energi take overtake favourite chevy volt toyota prius plugin tesla win dealership lawsuit course judge side loved tesla actuality tesla deserved win state prohibit automaker owning dealership compete local franchise key point tesla doesnt sell vehicle dealership competing them dealership salespeople chris demorro note paid oncommission order tesla model website nonetheless themassachusett state automobile dealer msada sue tesla lost tesla model price bump coming day cheap model super duper expensive model coming close minor were yet model start before tax credit cost change tesla motor confirmed couple week price tesla model sedan dont worry youre people model reserve tesla confirmed making model purchase date affected price increase automaker regularly raise price year order inflation squeeze buck profit consumer tesla make equipment option standard forward company option higher price bmw coupe concept unveiled ahead auto show bmw officially begin selling ibrand electric vehicle german automaker isnt teasing consumer cool concept behold latest pure electric vehicle bmw coupe concept coupe concept make official debut week auto show biking million win biking walking harrisonburg september community member participated advocacy advance action workshop harrisonburg virginia jumpstart region effort fund local bicycle pedestrian projectssince then theyve giant leap meeting goal million invested bicycle pedestrian infrastructure hour cargo bike history svajere copenhagen tonne picture interesting history cargo bike copenhagen really post worth stroll chicago build bikeshare system work everyone exciting time chicago city gear major bikeshare launch spring make bike station publiccity official thinking ahead avoid problem plagued system namely failure make bikeshare resident walk life john greenfield grid chicago describe local official ensure affluent reap benefit bikeshare windy city limit parking promote bicycling transit rapidly developing neighbourhood columbia height adam morgan street corridor department transportation ddot eliminating half visitor parking space weekday make parking resident transit include creating bicycle lane setting hundred metered parking space disabled biofuel algae replace petroleum soybean diesel ethanol lost lot support past year variety reason biggest knock cornderived ethanol reduced horsepower fuel economy causing wary alternative fuel promise study show algaebased biodiesel horsepower torque output petrol soybean diesel cleantechnicas completely free electric car report electric car early adopter follower want youd attend electric vehicle solar power event conducted cleantechnica date hottest cleantech new subscribing free cleantech newsletter eye sectorspecific new also free solar energy newsletter electric vehicle newsletter wind energy newsletter tag algae algae diesel algae oil bike sharing programme bmw bmw bmw bmw coupe cargo bike history cargo bike chicago chicago bike sharing chicago bike sharing programme chicago biking copenhagen copenhagen cargo bike copenhagen history biking dot dcdot ford ford fusion ford fusion energi harrisonburg auto show plugin electric vehicle soybean diesel soybean oil tesla tesla dealership lawsuit tesla lawsuit tesla model tesla model price zachary shahan tryin and specy letter time spend time cleantechnica director chief editor otherwise enthusiastically fulfilling duty obsession gas solar love planetsave bikocity president important media zach recognised globally solar energy electric car energy storage wind energy expert speak related conference event connect social media zacharyshahancom related post ","m_szGeo1":"United States","m_szSourceType":"source_industry","m_szSrcUrl":"http://cleantechnica.com/2012/11/27/ford-fusion-energi-price-announced-bmw-i3-concept-unveiled-tesla-wins-lawsuit-tesla-model-s-price-increasing-more-clean-transport-news/","m_Places":["Tesla","Starting","Massachusetts","L.a.","Harrisonburg","Harrisonburg, Virginia","Copenhagen","Chicago","District Of Columbia","Columbia Heights","Adams Morgan"],"m_People":["Zachary Shahan","Chevy Volt","Chris Demorro","John Greenfield"],"m_Companies":["Bmw","I3","Dealers Association","Msada","Tesla Motors","Stroll","D.c. Department Of Transportation","Ddot","Diesel"],"m_BiGrams":["tesla model","electric vehicle","cargo bike","ford fusion","fusion energi","zachary shahan","lawsuit tesla","model price","coupe concept","auto show","soybean diesel","electric car","bike sharing"],"m_TriGrams":["ford fusion energi"],"m_SocialTags":[],"m_Topics":[],"m_Industry":[],"m_Technology":[],"m_BiCnt":[6,5,5,4,4,3,3,3,3,3,3,3,3],"m_TriCnt":[3],"m_iDocBodyWordCnt":550}
