{"m_szDocID":"231636","m_szDocTitle":"World's Cheapest Solar Power Lands In Austin, Texas -- Under 4¢/kWh! (Sort Of) | CleanTechnica","m_szYear":"2015","m_szDocSumamry":"Yep, and also remember wind power is super cheap. Will E Germany has a political deal, yesterday, to transport their cheap Wind Power from the North to the South, Bayern. Now the car makers must start to make BMW, Mercedes and Audi all Electric cars with cheap Wind Power from the North. or a Tesla Giga factory can be build in Niedersachsen, Bremen, Hamburg. That would be nice. Lots of cheap Wind Power. mike_dyke Do they have the other deal as well – Solar from South to North? Calamity_Jean If they don’t, they should. Ulenspiegel The Bavarian excess generation with PV not so high, the existing ","m_szDocBody":"yep remember wind power super cheap germany political deal yesterday transport cheap wind power north south bayern car maker start make bmw mercede audi electric car cheap wind power north tesla giga factory build niedersachsen bremen hamburg nice lot cheap wind power mikedyke deal solar south north calamityjean dont should ulenspiegel bavarian excess generation high existing transmission capacity sufficient contrast wind capacity added northern rural state create demand mikedyke deal increase transmission capacity wind power main grid calamityjean thought power purchase agreement bayern cheap wind power russell solar tariff paying them real cost lower jameswimberley multigigawatt bid town university state government else texan desert bobwallace austin music world texas state capital lot needed offset hot air stever city million people including surrounding million people theyre utility smart city cost right talk profit cost renewable profit renewable web renewable make lot profit germany wirtschaftswunder renewable billion flowing economy austin texas billion flowing economy solar bid mikedyke profit renewable purely business point saving made current cost electricity youre paying ukp year math simple say buy generating equipment ukp give ukp profit difference ukp ukp ukp year figure year expensive year make sense profit year ukp ukp etc ukp year and case solar year real extra cost added bonus cheaper generating equipment help save world climate problem compared expensive equipment whos pay say ukp spare electricity produce profit zachary shahan thank needed reminder dudebuddypal dont youre nyc austin worthy city interesting history great people lot austin isnt worthy attitude people listen nyc austin subtropical zone reasonable amount rain green year dont youre talking about yeah hot here calamityjean mind read write english comment matter live know wimberley australia south africa great britain bobwallace jame european spend time south america impression austin texan indication reputation texas created greater world long texas take pride ignorance elect people perry cruz expect viewed state full buffoon super bad reputation led greater world disinvesting rural suburban reactionary teaching lesson yahoos brutal way scapegoat city shift cost them kristallnacht coming super population grown half million today desert frank realised back renewable important cost competitive are better epa cost add cost externality generation prevent generator energy locking year deal avoid competing renewable know dreaming externality economically nice invisible hand pushing forward slowing down matt frank call crazy real proof back cost external added developed world full cost first tipping point game halve developed world external wto approved tariff not reason join also bobwallace doubt external cost add ffs work spreading word public understanding coal oil industry tentacle bank account minimum people renewable deal thought true renewable deal politic law regulation renewable scare people solar problem spain change politic law regulation solar international formula price solar kwh panel differ size panel differ effectiveness kwpeak mgw installation panel that produced mgw solar installation solar radiation index everywhere time production rumour state year power production solar panel price differ everywhere state solar power cent cent cent formula make people understand believe panel rooftop solar sri year production kwh installation cost euro euro divided kwh cent kwh price cent kwh sri divide cent cent kwh production time year year divide cent kwh installation cost fall euro euro cent kwh kwh price kwh aske math professor formula cost solar power today hottest day netherland celcius vensonata will formulas include mysterious cost money interest rate house added mortgage payment pay cash cash earned investment etc reflected price kwh funny happen inflation taxe wild card poker game called real cost energy contract signed people make money make money solar texas good solar resource cent kwh yes remember cent price return profit vensonata sunshot landed small step man measure sunshot aim cent kwh arrived year early battery rushing rearview mirror delightful rate combined rate storage hit cent grid retail average barrier gone nakedchimp cool leigh goodson start working home google byfar job had brand bmw cheque week past began month ago immediately bringing home hour ","m_szGeo1":"United States","m_szSourceType":"source_industry","m_szSrcUrl":"http://cleantechnica.com/2015/07/02/worlds-cheapest-solar-power-lands-in-austin-texas-under-4%c2%a2kwh-sort-of/","m_Places":["Germany","Bremen","Hamburg","Austin","Texas","Austin Texas","Nyc","Australia","South Africa","Great Britain","South America","Spain","U.s."],"m_People":["Zachary Shahan","Wimberley","Leigh Goodson"],"m_Companies":["Bmw","Audi","Yahoos","Epa","Wto","Google"],"m_BiGrams":["wind power","cent kwh","cheap wind","ukp year"],"m_TriGrams":["cheap wind power"],"m_SocialTags":[],"m_Topics":[],"m_Industry":[],"m_Technology":[],"m_BiCnt":[6,6,4,3],"m_TriCnt":[4],"m_iDocBodyWordCnt":647}
