{"m_szDocID":"233343","m_szDocTitle":"EV Revolution (& Fleet Workshop Tomorrow in Vancouver)","m_szYear":"2014","m_szDocSumamry":"EV Revolution (& Fleet Workshop Tomorrow in Vancouver) Clean Energy Canada . This coming Monday, Clean Energy Canada and the Fraser Basin Council—in collaboration with Electric Mobility Canada—are presenting  Electrify Your Fleet  in Vancouver, as part of Electric Mobility Canada’s national  EV2014VE conference . This preview by Jeremy Moorhouse and Charlotte Argue outlines why electric vehicles and fleets make for a perfect match. Electric vehicles have emerged from the garages of gearheads and landed in the nation’s auto malls. And though the numbers aren’t yet threatening the gasmobiles, th","m_szDocBody":"revolution fleet workshop tomorrow vancouver clean energy canada coming monday clean energy canada fraser basin councilin collaboration electric mobility canadaare presenting electrify fleet vancouver part electric mobility canadas national evve conference previewby jeremy moorhouse charlotte argueoutline electric vehicle fleet make fora perfect match electric vehicle emerged garage gearhead landed nation auto mall number arent threatening gasmobile early adopter snapping evs proven car practical choice many pure electric vehicle perfect road people made switch reaping reward year individual driver save fuel maintenance cost commercial private fleet positioned advantage switch fleet driver follow regular route set schedule central dispatchall ideal condition turn out battery power financial benefit too sevenyear lifetime fleet vehicle operator save more higher upfront price tag addition substantial decrease fuel cost cost driven electric car require maintenance oil brake wear tear fleet manager enjoy predictable static electricity price relative daily gas diesel price ninety percent fleetsready electrify course fleet ready extension cord example electric eighteen wheeler hit market said study consultancy fleetcarma found percent vehicle fleet assessed evready past july fleet manager oregon gathered workshop identify electric vehicle greatest benefit flagged predictable route short regular trip quiet noidling operation highuse vehicle city vancouver local success storey year electric met percent city newvehicle need city councillor raymond louie ideal commute city staff emerging business case cost saving proven successe business case cost saving barrier adoption linger fleet manager upfront cost range anxiety lack familiarity limited number model choose remain real concern barrier adoption coming image credit cargo bit bit barrier coming down market grow vehicle cost continue fall price batteriesan evs mostexpensive componenthas fallen percent year bloomberg energy finance expect price halve early cushion hit sweet spot government offering rebate ontario offer consumer depending size battery pack similarly quebec rebate range boosted incentive lower battery cost automaker introducing battery electric plugin hybrid vehicle model year fullsize suvs pickup truck van market canada fleet manager interested integrating evs wider range resource support year ago british columbia government california oregon washington committed pursue goal percent vehicle purchased public private fleet zeroemission goal sound modest some potential make big impact realised year vehicle purchased provincial local government company operating province emit carbon pollution whatsoever add evs roaming province electric vehicle everywherefrom taxis delivery van carshare electrify fleet workshop coming vancouver pacific coast collaborative partnership west coast government overseeing percent fleet target recently developed toolkit company government electric vehicle fit them include cost calculator vehicle incentive resource fleet vehicle falling cost wealth resource available time fleet manager adopting electric vehicle facilitate step clean energy canada fraser basin council collaboration electric mobility canada presenting electrify fleet vancouver part electric mobility canadas national evve conference expert hand keen dive detail fleet electric vehicle speaker dissect barrier electric vehicle procurement environmental financial benefit integrating zeroemission car existing fleet government lead percent target rest pick ball run reap benefit electric vehicle bring source clean energy canada reprinted permission cleantechnicas completely free electric car report electric car early adopter follower want youd attend electric vehicle solar power event conducted cleantechnica date hottest cleantech new subscribing free cleantech newsletter eye sectorspecific new also free solar energy newsletter electric vehicle newsletter wind energy newsletter ","m_szGeo1":"United States","m_szSourceType":"source_industry","m_szSrcUrl":"http://cleantechnica.com/2014/10/26/ev-revolution-fleet-workshop-tomorrow-vancouver/","m_Places":["Vancouver","Canada","Charlotte","Oregon","Ontario","Quebec","California","Washington"],"m_People":["Jeremy Moorhouse","Raymond Louie"],"m_Companies":["Diesel","British Columbia Government","Target","Ball"],"m_BiGrams":["electric vehicle","fleet manager","clean energy","energy canada","electric mobility","electrify fleet","electric car"],"m_TriGrams":["clean energy canada"],"m_SocialTags":[],"m_Topics":[],"m_Industry":[],"m_Technology":[],"m_BiCnt":[12,5,4,4,4,3,3],"m_TriCnt":[4],"m_iDocBodyWordCnt":523}
