{"m_szDocID":"234227","m_szDocTitle":"17 Fastest Electric Cars... Er, Quickest | CleanTechnica","m_szYear":"2015","m_szDocSumamry":"July 19th, 2015 by Zachary Shahan   Originally published on Gas2 . What’s the fastest electric car on the market? I think you can guess, but what about #2–17? First of all, let’s get a little perspective in here. A car’s quickness is generally rated by how fast it goes from o mph to 60 mph (or 0 km/h to 100 km/h outside of the USA and a few other places). But there are other ways to measure it — o mph to 30 mph, o mph to 15 mph, etc. The thing about electric cars is that they have instant torque, which gives them a huge jolt of power right off the line, something that conventional gasmobiles s","m_szDocBody":"zachary shahan originally published gas what fastest electric car market guess all let perspective herea car quickness generally rated fast mph mph usa place way measure mph mpho mph mph etc electric car instant torque huge jolt power line conventional gasmobile simply match visualise bit here simple graph designnew via union concerned scientist tesla model smoke ferrari lamborghini line instant torque benefit offer key reason electric car quickly automobile market reason anyhow car time standard typicallymeasure quick fast youre precise language car rank top quickest electric car market instant torque mind share graph uninitiated gearhead friend intro point jumping list put electric car market quotation mark car supposedly market basically unattainable million rimac conceptone example wonderful car supposedly mph second one million car list way plugin hybrid electric car subset electric car eye included ranking disclaimer way quickest electric car market chevy volt second note volt second top quickest electric car wanted bit man territory volt realm price tag msrp theus federal tax credit evs state local incentive sharplooking car tonne love owner past severalyear offer good balance performance comfort price fiat second fiat bit spunky cute look snappy line road track named electric car incentive affordable category electric car test drive havent largely fiatchrysler ceo sergio marchionne doesnt sell california live poland day ford cmax energi second surprised ford cmax energi and fusion sibling list mean isaw number updating comprehensive electric car month ago didnt remember itbeating electric model family car eye doesnt scream fast decent acceleration sale steadily top usa affordable msrp doesnt hurt either sure renault zoe second love renault zoe realise response affordable simple car love thing finding decent time second make better naturally hard choose zoe tesla model moreexpensive car list savemoney zoe awesome choice course market popular electric car europe year quickest top three way price home country france price including leasing battery ford fusionenergi second cmax energi fusion energi surprise family car surprised list bestselling electric car half june due benefit fast spacious affordable good other bit allelectric range ahem price btw mercede bclass electric second tesla organ mercede badge surprising bclass electric show list however expensive weve far msrp detail bclass electric recommend review mercede bclass electric drive review month exclusive cadillac elr second expensive talking about extra and admittedly thing cadillac elr add granted big reason sale pretty lousy compared model list hey broke top truth offer bit luxury volkswagen golf gte second back realm car average man afford well price bit average volkswagen golf gte start havent guessed now market selling hotcake europe monthsof rose video review above loved audi etron second audi etron tied golf gte basically car cover basically price essentially thefeature plugin hybrid themoney fork them deciding factor basically prefer audi volkswagen sort choosing chiquita banana dole banana know good new etron hit shore guessing california chevy spark second torque ferrari italia chevy spark didnt trouble landing list impressing test driver owner yeah second mph isnt amazing remember graph top page adjust car incentive after recent price cut spark cheapest list thousand dollar average newcar price counting federal tax credit evs zev rebate california youd selling crazy wasnt producing car meet demand advertising bmw second credit zachary shahan obsession cleantechnica bysa full disclosure love bmw agreed arent rimac conceptone bmw car drive wonderfully impressive acceleration line comfy spacious efficient car market green getout price mercede bclass electric closest competitor crushed bclass electric line well second faster mph plenty debate car better thiscomparison comparison heck tweet competing article same mercede second mercede glc matic plugin suv beast reportedly hitting mph faster mom ouch hit european market pluginhybridloving netherland bestselling electric car june havent searched price yet cheap volvo plugin hybrid second luxurious highperformance volvo phevisa close competitor respect barely inches drive mph price tag scare buyer offer solid grip sale spot europe btw porsche cayenne ehybrid second hard fastest car list porschestrutting stuff cayenne ehybrid mixture performance luxury cool butwhat expect porsche logo record until tesla model arrive porsche squeezed mile electric range vehicle porsche panameras ehybrid second credit zachary shahan obsession cleantechnica bysa sharing technology porsche panameras ehybrid steal bronze medal thecayenne ehybrid panamera ehybrid account panamera sale heard deserve more whatev people slow catch trend btw porsche havet driven drop line bmw second credit zachary shahan obsession cleantechnica bysa eating porsches lunch time bmw beauty car pull people vehicular cheetah problem price tag minimal mile electric range still beauty btw bmw havet driven drop line tesla model second credit zachary shahan obsession cleantechnica bysa knew along course tesla model massmanufactured car planet time motor trendrecently named top american car time come call everything oil industry pissing pant make carson road golf cart noted top burn ferraris lamborghinis line reasonable price wonderthe model topselling car class usa unfortunately test driving recordbreaking tesla ruined car cleantechnicas completely free electric car report electric car early adopter follower want youd attend electric vehicle solar power event conducted cleantechnica date hottest cleantech new subscribing free cleantech newsletter eye sectorspecific new also free solar energy newsletter electric vehicle newsletter wind energy newsletter tag audi audi etron bmw bmw bmw cadillac elr chevy spark chevy volt fiat fiat ford ford cmax energi ford fusion energi mercede mercede mercede bclass electric porsche porsche cayenne ehybrid porsche panamera porsche panamera ehybrid renault renault zoe tesla model tesla model volkswagen volkswagen golf gte volvo volvo plugin hybrid zachary shahan tryin and specy letter time spend time cleantechnica director chief editor otherwise enthusiastically fulfilling duty obsession gas solar love planetsave bikocity president important media zach recognised globally solar energy electric car energy storage wind energy expert speak related conference event connect social media zacharyshahancom related post ","m_szGeo1":"United States","m_szSourceType":"source_industry","m_szSrcUrl":"http://cleantechnica.com/2015/07/19/17-fastest-electric-cars-er-quickest/","m_Places":["Us","Usa","California","Europe","France","Uk","Tesla","Netherlands","Cayenne"],"m_People":["Zachary Shahan","Chevy Volt","Sergio Marchionne","Renault Zoe","Mercedes-benz B-class","Mercedes-benz , Mercedes-benz","Ford , Ford C-max Energi"],"m_Companies":["Guess","The Thing","Union Of Concerned Scientists","Lamborghini","Volt","Road & Track","Renault","Zoe","Cadillac","Audi A3","Audi","Volkswagen","Dole","Bmw","I3","Volvo","Motor Trend"],"m_BiGrams":["electric car","tesla model","bclass electric","zachary shahan","car market","plugin hybrid","cmax energi","mercede bclass","golf gte","second credit","credit zachary","shahan obsession","obsession cleantechnica","cleantechnica bysa","instant torque","quickest electric","car list","price tag","cadillac elr","chevy spark","cayenne ehybrid"],"m_TriGrams":["electric car market","mercede bclass electric","second credit zachary","credit zachary shahan","zachary shahan obsession","shahan obsession cleantechnica","obsession cleantechnica bysa","quickest electric car"],"m_SocialTags":[],"m_Topics":[],"m_Industry":[],"m_Technology":[],"m_BiCnt":[18,7,7,6,5,4,4,4,4,4,4,4,4,4,3,3,3,3,3,3,3],"m_TriCnt":[4,4,4,4,4,4,4,3],"m_iDocBodyWordCnt":939}
