{"m_szDocID":"234554","m_szDocTitle":"Tesla Power Train Lifetime Goal = 1 Million Miles! | CleanTechnica","m_szYear":"2015","m_szDocSumamry":"Tesla Power Train Lifetime Goal = 1 Million Miles! Originally published on EV Obsession . With all the hype about the new Tesla Model S Ludicrous mode and its record-breaking sprint to 60 mph (see this , this , and this ), it seems that most of us have glossed over a bigger announcement. The first line under “Luuudicrous Mode” in Elon Musk’s blog post reads like this: “While working on our goal of making the power train last a million miles, we came up with the idea for an advanced smart fuse for the battery.” Wait a second, what? One million miles? As “ onesecond ,” who highlighted this line ","m_szDocBody":"tesla power train lifetime goal million mile originally published obsession hype tesla model ludicrous mode recordbreaking sprint mph see glossed bigger announcement line underluuudicrous mode elon musk blog post read this working goal making power train million mile idea advanced smart fuse battery wait second what million mile onesecond highlighted line rightly pushed piece write step consuming throw despicable environmental impact tesla car forever offer upgrade achieve that total change inphilosophyfrom car maker buy car asap andtherefore roll minor cosmetic make car old tesla improving actual car way lot coverage said coverage have part offer upgrade comment exciting battery capacity booster imho understood tesla annually offer option upgrading battery higher capacity year price course tremendously environmentally friendly upgrade entire car electric car manufacturer offer yet onesecond note industry mindset enticing practically forcing consumer newest yeah aim amillionmile tesla power train company insane second write tmc forum continue compare tesla automaker goal this tesla league planet aim consumer planet operating completely big automaker rewarded result people love tesla should course tesla highlighting benefit electric vehicle fewer moving partsandsimpler inside electric vehicle longer conventional gasmobile akin moving trash can gasmobile power train legitimately million mile electric one maybe tesla prove what new cleantechnicas completely free electric car report electric car early adopter follower want youd attend electric vehicle solar power event conducted cleantechnica date hottest cleantech new subscribing free cleantech newsletter eye sectorspecific new also free solar energy newsletter electric vehicle newsletter wind energy newsletter tag elon musk tesla tesla model zachary shahan tryin and specy letter time spend time cleantechnica director chief editor otherwise enthusiastically fulfilling duty obsession gas solar love planetsave bikocity president important media zach recognised globally solar energy electric car energy storage wind energy expert speak related conference event connect social media zacharyshahancom related post tesla autopilot steer car barrier autobahn construction zone wayne williamson hope part gigafactory dedicated recycling one lithium battery cheaper raw mined bobwallace ive read cost recover lithium fresh build recycling charge system order insure battery recycled neroden ill make point here automaker follow alfred sloan model planned obsolescence selling replacement car teslas goal maximise number electric car road making electric car forever way tesla road adding number electric car road replacing tesla lead business problem tesla car world electric time worry onece happen meantime tesla market stay hot carmaker watch out car competing used teslas ivor oconnor call harvard mba model killing golden goose quarterly profit tony reye tesla ratchet warranty coverage year support million mile goal stuart susceptible teslas water damage test vehicle immersed fresh water hour declared write off voluntary standard steve grinwis live worry this dont live jeffhre lol yep stuart doesnt worry that designer concerned waste simply save dollar manuf cost car drowned weather extreme sea level rising suvs mandatory vehicle voluntary time being long term reduced insurance premium cover extra design manuf cost anyway also design produce reliable vehicle easier due simplicity ice vehicle neroden tesla model drove slowly water immerse bottom car explicitly dont manual fine florida iirc flooding event joe viocoe probable solid state battery coming degradation battery past steve grinwis degradation battery past imho past leaf complete lack thermal management system traction battery holding well complete nonissue longer range car coming out reduction range year tracy mcdonald earning money online easy now freelance internet earn buck hour time family job require computer internet home effort handsome earning dream illuminati aluminium frame body tesla long service life gco total change philosophy car maker buy car asap roll minor cosmetic make car old course manufacturer tweaking feature model year nefarious purpose tesla roll more prominently dualmotor kindaauto pilot kwh battery possibly impact desirability older model zach wrote sarcasm hypocrisy simply hopelessly caught tesla reality distortion field apple fan are also taking musk goal laudable reality already wise remember pev manufacturer didnt make bold claim drivetrain longevity issue eveee pev jeffhre folk understand rest either gco pev abbreviation carb plugin electric vehicle wasnt clear context refer plugin general including plugin hybrid electric vehicle eveee thank super add feature existing tesla make computer industry betterperforming component update desktop ditching worth way completely car company altering body grille aftermarket duplicate gco aware option add update hardware model purchase exception twin charger and recall correctly elon musk made clear sensor hardware autopilot couldnt retrofitted older car neroden hardware upgrade price mind you parking sensor available power folding mirror secondgeneration fog light myself autopilot hardware deemed step impact expensive aluminium body part eveee eye battery wheel suspension tyre windshield wiper replacement battery low tech really odd throwback ahead vehicle model long lasting lighter low voltage lithium battery lifep longer give service back million mile doubt unit show insane acceleration run daily basis fast charging longest lasting tesla skewed favour making large pack giving battery thermal management favour making standard charge soc average battery favourable soc range temperature result support conclusion model capable easily exceeding mile degradation capacity sweet spot average driver seldom discharge battery fully often result obtained far initial loss mile loss flat mile initial loss continued mile jameswimberley french tgv trainset mile year link expected year millionmile goal simpler stressed car powertrain utopian rest car wear first chandy pand interior subtle simple console digital mean software changed display colour doesnt outdated thought past battery car easily good year bsw cab driver montreal million kms diesel mercede car long auto maker dont make guy hockey team work material engineer tasked making hub cap specific date began rust fker bobwallace engineer stuff longer cost more icev shot mile body rusted made sense engineer door handle mile super engine mile them smallblock chevy production year reflected older value engineering community dating back henry ford rest car fell prey planned obsolescence intentional styling fad part durability declined also conversion unit body highstrength steel made car prone rust surplus engine hotrodder busy year import forced detroit act package then bobwallace lot engine state constant rebuilding acquired mileage generator water pump fuel pump head gasket valve job carb rebuild drop oil pan ring bearing job basically block held neroden ahem planned obsolescence deliberate strategy pushed alfred sloan mastermind designing part fall date explicitly business model sloan foresaw day car buy made car fall deliberately car sale tesla isnt that tesla eventually face business headwind world own tesla year point musk declare victory retire ivor oconnor realise tesla monitoring car sold real time mileage car total mileage car combined interest much real point like year mile maintenance item costing total maintenance cost hhl impractical that mile spread year year question kind maintenance needed warranty period impractical question nobody tesla current goal motor mile car mentioned above recycling reuse etc secondary refurb car etc ivor oconnor yeah impractical crazy personally people commute mile day time week totally insane year sranger people statistically important super time ridiculous commute common invent word exurb describe housing mile core city hear people commute west virginia crash chastened sprawl mania dont learned lesson eveee yes maintenance schedule timing belt hose oil change brake fluid atf brake pad tyre windshield wiper coolant coolant flushes battery air oil philtre replacement item smog cheque ice manufacturer rarely state repair however example alternator out water pump heater core catalytic converter exhaust radiator electrical bulb out kind sensor map timing position sensor pollution control computer pollution control stuff error code ignition cylinder bad windshield crack lost key recall make recommendation water hose replaced experience recommended schedule there good ice experience lot evs pollution stuff vanishes big relief anderlan mean afford tesla financing year right hello financial demigod opportunity calling ttman model cost condo house lot part country super house land worth desirable streetcar suburb guess create formula estimating worth put versus house based likelihood longer commute paid house bobwallace move selfdriving car evs make cheaper drive mile number people moving city work work commute basically desk steering wheel pull place driving work time credit what hour hour half commute mile cent mile cost people pay drive mile spend hour home back home couple hour day youre interrupted office mate productive expect real estate city climb heck let toss steering wheel steer computer tracking ball hate mousesesese joystick drive wire system ttman live due complete coverage land building commercial development continuing tear higher people drive hour half gas engine real estate afford stop people freeway clog half hour flow mile mile hour hour commute hour hit stop traffic nicer built commercial spread fashion traditional hub wheel way bobwallace back lived people neighbour drove hour work bought toyota rvs morning couple kid climb wearing pjs dress kid feed breakfast drop daycare adult turn driving dressed ate breakfast meant live nice affordable house cramped apartment neroden nobody build commercial spread fashion economic phenomenon business clustering jeffhre kid morning great life bobwallace spend hour home back home time commuting minute hour stint office neroden dont bank agree teslas road year problem crashes shorten lifespan car lot jeffhre bank agree that equity house piggy bank real estate crash panel roof pay credit back energy saving anderlan insurance ivor oconnor shock suspension joint brake spin replacement mile maintenance cost stay top stuff tesla handle hope list expect pay maintenance make million mile year anybody year vehicle warranty expire ivor oconnor battery warrantied year unlimited mile point entitled battery pack paid ahead hhl engineered fail warranty end gas car fine year warranty mile ivor oconnor true car maintenance sometime mercede here recommended maintenance required warranty turn bank robber mechanic tesla customer short hair make sense charge maintenance put million mile car hhl pretty tyre brake etc anywhere tesla short hair powertrain battery car electronic basically question boil battery cost dy powertrain expected million mile car mile motor tesla answered battery question partly opening upgrade existing user motor secondary refurbished car refurbished electronic buy car component refurb battery motor off people upgrade battery motor recycled sranger unlike traditional dealer tesla stated time intend service centre profit centre cost typically traditional dealer ivor oconnor yes ive heard that day automation expect too eveee bank robber mechanic people swear employment shift ivor oconnor though perfect condition banger vehicle eveee yes sportscar pickup truck dilemma bobwallace preferred solution needed pickup part sportscar really spitfire needed work drive bobwallace musk stated tesla owner problem driving mile current battery year mile year icevs year warranty expect crush icev year ivor oconnor musk number marketing purpose make dont online stat personal information removed making point steve grinwis build car sell already engage risky marketing ivor oconnor that queue smaller hired sale chief risky marketing doubt much huge barrel full option ideas pull barrel ricegf goal sell car year pretty good reason aggressively market now jeffhre customer meantime sleepover store shadow projection model proflie camp song smore neroden practise long part until lasted long model mile make statement from oldest model year old part wear year ivor oconnor totally accurate adrian roughly average annual drive cycle mile day mph continuously surprised taxis sort utilisation tesla million mile goal work ahead them rate replacement drive unit main contactor suspension bushing anecdotally forum tesla motor club battery well theyre part driveline actual independent data impossible far consumer report statistically significant maintenance data year model put larger automotiveaverage load suspension due vehicle weight power certain current vehicle engineered sustain load million mile suspect present there probably question when reflected warranty point ivor oconnor suppose tesla stat showing mile car driven theyll open start showing real time data public clean great marketing part show data totally unheard but well logical move tesla neroden drive unit replacement fail due mismanufactured drive unit problem developed driving infant mortality fairly common problem motor bad factory tesla reduce rate long drive unit last tesla redesigned main contactor eliminate identified failure mode battery problem significantly deeper design problem tesla replace lithiumion battery longer lifespan problem originate vampire load drawn car parked problem vensonata roll royce year unlimited mileage warranty tesla that remember rocky mountain institute design hypercar idea year carbon fibre body etc well tesla task ivor oconnor hope neroden people put mile model ses major part replacement ill fail first theyll announce tesla motor club replace usual wear part brake pad tyre windshield wiper windshield wiper fluid air philtre replacing air philtre unduly expensive far cost down ivor oconnor love website show owner replaced cost them tracking real maintenance cost neroden well awful lot warranty replacement part redesigned count longterm maintenance cost though tesla considered substandard part design the part redesigned arent supposed require replacement design teething issue earlymodelyear car teslas handled issue company have list stuff recurring routine replacement lot shorter battery big hope tesla eventually deal wearandtear interior upholstery part mentioned before dont big part wear out nobody wear out failure designproblem newdesignshouldfixit variety oscar martn bus driver buse that make trip spain country cheque million including complete cleaning engine suppose value reachable great problem ice vehicle too heavy maintenance course new explicit policy tesla normal average personal car maintenance lot cheaper electric car benefit adopt politic add car making usable battery replacement make recycling battery renewable replaced battery partial lowering price replacement neroden boy clicked millionmile powertrain lifetime tesla sell powertrain commercial vehicle market buse truck etc market demand heavier mile personal auto market tesla wont build that awful lot chassis design preferred powertrain supplier antipirate buying tesla idea ever musk incredible contribution zachary shahan yeah reason choose model bolt leaf here big one nissan bmw step gco reason concretely what goal hope car exist yet bolt leaf closer actual product nissan arent step beat tesla market itd foolish whod waiting model materialise teslas history indication itll longer priced higher people hope hand musk lot promote electrification small part creating desirable halo car hurting overly optimistic deadline cost making promise company keep bobwallace teslas history indication itll longer priced higher people hope teslas history taking longer originally stated roadster bit delayed supplier delivered substandard drive train modx release date has think pushed back some example unaware cost rising example gco tesla roadster tested patience holder trust company elon musk raise price the documentary revenge electric car include footage event car initial target model late well importantly elon musk initially stated car follow tesla roadster cost half much person capable dividing understood incentive small thing vampire draw reduction valet mode chademo adapter battery swapping dramatically longer expectation tesla created battery swapping isnt vast majority customer important absence betray teslas flashy announcement sleazy thought programme claiming start something assuming people spend age gas station forfeiting taxexempt job upcoming powerwall depending version statement compatible existing inverter one guy instal hour solarcity talked backup version model announced incentive wait gas saving now claim equally colourful dose salt cleantechnicas great staff well bobwallace model late well importantly elon musk initially stated car follow tesla roadster cost half much person capable dividing understood incentive give link claim recall tesla delivering mod june month late significant evidence earlier delivery date cost half much person capable dividing understood incentive tesla offered sold lower range mod bit discontinued kwh model low demand source found stated tesla announced base price introduced mod missed price mod subsidy well btw cheque powerwall price teslas powerwall page gco solarcity offer powerwall backup only installed year link bottom article doesnt bode existing inverter onehour installation claim revealing back teslas ceo statement good context current announcement eveee fair point solarcity installation cost add musk chastised installation cost lower dollar apply existing system inverter simple switchover lack detail imo biggest culprit lack clear information understandable investor meeting technically sketchy public clamouring detailed information powerwall dont specific inverter hint alliance solaredge fronius dont battery electrical connexion like gco independently used adding backup power home what solarcity require installing separate breaker panel load centre moving critical circuit there california based that required permit inspection exceed already musk estimate cruel joke eveee detect emotion analysis problem investor meeting website market blurb scant give info anxiously awaiting concrete detail solarcity lease buy emergency backup include separate panel breaker make sense musk emergency backup app powerwall made clear app powerwall app musk referred simple grid tied solar storage bobwallace sorry dont early speculation product announcement powerwall listed depending model tesla site tesla produce kwh mod higher capacity mod disconnected part pack sold offered kwh price tesla produced real kwh mod people wanted purchase one sorry claim seriously gco speculation elon musk post tweet shouldnt considered point people media prime above that public comment company ceo set expectation though met past expectation future tesla product continue set way expect kind discrepancy well bobwallace people criticism tesla matter trivial issue start myth tesla expensive time unimportant support myth wave data explain late delivered timely manner give credit close difference insignificant type character assassination neroden happy owner tesla model tesla routinely late nice hear gigafactory ahead schedule model delivered timeline announced year lot delay due learning curve startup tesla past them meanwhile tesla competitor similar delay neroden tesla sell kwh model theyre software limited kwh model early reservation holder dogphlap dogphlap purchaser feel buy vehicle mile range working global fast charging network ","m_szGeo1":"United States","m_szSourceType":"source_industry","m_szSrcUrl":"http://cleantechnica.com/2015/07/21/tesla-power-train-lifetime-goal-1-million-miles/","m_Places":["Tesla","Most","Us","Well","Barrier","Teslas","Florida","Montreal","Detroit","Look","West Virginia","Toyota","Spain","California"],"m_People":["1 Million Miles","Luuudicrous Mode","Elon Musk","One Million Miles","Million Mile","So Tesla","Zachary Shahan","Wayne Williamson","Alfred Sloan","Ivor O’connor","Tony Reyes","Steve Grinwis","Joe Viocoe","Tracy Mcdonald","Oscar Martín"],"m_Companies":["Lifetime","Sprint","Harvard","Indeed","Apple","Diesel","Sloan","Atf","Guess","Ball","Lifespan","Consumer Reports","Rocky Mountain Institute","Pirate","Bmw","Target","Solarcity","The Alliances"],"m_BiGrams":["ivor oconnor","million mile","electric car","elon musk","electric vehicle","power train","windshield wiper","maintenance cost","mile car","drive unit","tesla model","buy car","planned obsolescence","steve grinwis","tyre windshield","mile year","real estate","higher people","teslas history","tesla roadster","cost half","half much","much person","person capable","capable dividing","dividing understood","understood incentive","kwh model"],"m_TriGrams":["tyre windshield wiper","cost half much","half much person","much person capable","person capable dividing","capable dividing understood","dividing understood incentive"],"m_SocialTags":[],"m_Topics":[],"m_Industry":[],"m_Technology":[],"m_BiCnt":[14,11,9,7,6,4,4,4,4,4,3,3,3,3,3,3,3,3,3,3,3,3,3,3,3,3,3,3],"m_TriCnt":[3,3,3,3,3,3,3],"m_iDocBodyWordCnt":2820}
