{"m_szDocID":"234551","m_szDocTitle":"World’s Cheapest Solar Power Project In Dubai Achieves Financial Closure | CleanTechnica","m_szYear":"2015","m_szDocSumamry":"World’s Cheapest Solar Power Project In Dubai Achieves Financial Closure July 21st, 2015 by Smiti Mittal   The world’s cheapest solar power project being built in Dubai is one step closer to commercial operation, the Dubai Electricity and Water Authority has reported. The 200 MW second phase of the Mohammad Bin Rashid Al Maktoum Solar Park being implemented by Saudi Arabia-based ACWA Power has achieved financial closure. The project was awarded to ACWA Power earlier this year at a record-low tariff of US¢5.98/kWh. The 200 MW capacity would add to the 13 MW phase I project that is already opera","m_szDocBody":"world cheapest solar power project dubai achieve financial closure smiti mittal world cheapest solar power project built dubai step closer commercial operation dubai electricity water authority reported phaseof mohammad bin rashid maktoum solar park implemented saudi arabiabased acwa power achieved financial closure project awarded acwa power earlier year recordlow tariff capacity add phase project operational phase expected achieve commercial operation project higher debt component compared solar power project funding project comingthrough debt financing rest willbe equity investment march acwa power announced secured debt financing loan worth million project year loan provided abu dhabis gulf bank saudi bank national commercial bank samba financial grouppaddy padmanathan chief executive officer acwa power announced abu dhabi sustainability week company secure debt financing low interest rate dewa plan invest billion dollar expansion mohammed bin rashid maktoum solar park authority upgraded plan installed capacity solar park initial target dewa plan installed capacity park solar power park central dewas target source dubais total power output renewable energy source cleantechnicas completely free electric car report electric car early adopter follower want youd attend electric vehicle solar power event conducted cleantechnica date hottest cleantech new subscribing free cleantech newsletter eye sectorspecific new also free solar energy newsletter electric vehicle newsletter wind energy newsletter tag dewa solar power park dubai dubai electricity water authority dubai solar power park mohammad bin rashid maktoum solar park smiti mittal work senior solar engineer reputed engineering management consultancy conducted due diligence solar project india southeast asia keen interest renewable energy green building environmental sustainability biofuel reside delhi india related post phineasjw clarify cent kwh price consumer pay price utility paying bobwallace ppa power purchase agreement price contract utility pay seller utility add cost distribution operating etc top wholesale price jameswimberley longer world cheapest buffett signed ppa nevada reported link bobwallace buffett ppa unlike other solar ppas built inflation factor cost year life contract average cost year lifetime ronald brakel assumed ppas cpi adjustment built them thought australia weird without mean wind power cheaper australia cheaper mean lot room improvment isnt bad thing information bobwallace dont wind ppas read noninflating price solar ppas zach info awea bobwallace here public document discusse buffet ppa inflate sun power ppa start higher price fixed life contract neroden inflation couple year insane contract inflator didnt tie cpiw something bobwallace you inflating price average cost life contract higher fixed price contract matt history raise electric cost ran number looked foggy crystal ball thought option paying start end folatt state cost dollar megawatthour megawatthour year home calculation lot easier cost paid megawatthour mean people dubai electricity cheaper zachary shahan ","m_szGeo1":"United States","m_szSourceType":"source_industry","m_szSrcUrl":"http://cleantechnica.com/2015/07/21/worlds-cheapest-solar-power-project-dubai-achieves-financial-closure/","m_Places":["Dubai","Saudi Arabia","Us","Abu Dhabi","Gw","Atmosphere","India","Southeast Asia","New Delhi","Nevada","Australia"],"m_People":["Smiti Mittal","Mohammad Bin Rashid","Al Maktoum Solar","Mohammad Bin Rashid Al Maktoum Solar","Ronald Brakels","Zachary Shahan"],"m_Companies":["Gulf Bank","National Commercial Bank","Samba","Financial Group","Target"],"m_BiGrams":["solar power","solar park","acwa power","world cheapest","power project","bin rashid","rashid maktoum","maktoum solar","debt financing","power park","life contract"],"m_TriGrams":["solar power project","bin rashid maktoum","rashid maktoum solar","maktoum solar park","solar power park"],"m_SocialTags":[],"m_Topics":[],"m_Industry":[],"m_Technology":[],"m_BiCnt":[7,4,4,3,3,3,3,3,3,3,3],"m_TriCnt":[3,3,3,3,3],"m_iDocBodyWordCnt":428}
