{"m_szDocID":"235017","m_szDocTitle":"June EV Sales: Europe vs North America vs China | CleanTechnica","m_szYear":"2015","m_szDocSumamry":"June EV Sales: Europe vs North America vs China Originally published on EV Obsession . Following sales reports on June US electric car sales , Europe electric car sales , and China electric car sales , I thought it would be interesting to compare the powerhouses (and throw Canada on top of the US to make it “North America” since it’s all basically one economic region). So, below is a chart and table comparing (and also adding up these regions). The general take-home point, I think, is that Europe is now leading the world (driven largely by the large markets of Norway , France , the UK , the Ne","m_szDocBody":"sale europe north america china originally published obsession sale report electric car sale europe electric car sale china electric car sale thought interesting compare powerhouse and throw canada top make north america basically economic region chart tablecomparing and adding region general takehome point think isthat europe leading world driven largely large market norway france netherland germany electric car sale half north america china storey similar smaller scale europe showing electric car sale china north america course relative factor make comparison interesting capita sale total car sale gdp sale etc ill leave day maybe economic powerhouse cleantechnicas completely free electric car report electric car early adopter follower want youd attend electric vehicle solar power event conducted cleantechnica date hottest cleantech new subscribing free cleantech newsletter eye sectorspecific new also free solar energy newsletter electric vehicle newsletter wind energy newsletter tag china china electric car china electric vehicle china sale europe europe electric car europe electric vehicle europe sale north america north america electric car north america electric vehicle north america sale electric car electric vehicle sale zachary shahan tryin and specy letter time spend time cleantechnica director chief editor otherwise enthusiastically fulfilling duty obsession gas solar love planetsave bikocity president important media zach recognised globally solar energy electric car energy storage wind energy expert speak related conference event connect social media zacharyshahancom related post chinese tesla model reservation holder invited configure bubba nicholson gasoline heavily taxed europe electricity cost there generous subsidy isnt surprising evs thrive there larmion electricity retail western europe roughly double rate gasoline cost gallon half cost europe spread explain much gasoline electricity expensive europe importantly driver drive mile european one mean fixed upfront insurance cost account bigger share total running cost europe policy government well norway other support evs generously government doe shorter commute good railway network long distance travel make easier make limited range nonurbanite wattleberry yes afraid bring change youll possibly experience cheaper motoring again vic hristov curious number compare gasoline car sale coboll found million usa auto probably include light truck suvs sale year doesnt give ending date sale climbing note low year million autos sold year bobwallace here long global car light weight truck sale bobwallace electric car sale miniscule compared icevs icev sale compared number horse road henry bought rate sale sale acceleration tell jameswimberley annual increment global car sale wikipedia article vary bit average vehicle revolution start make impact sale exceed this mean ice fleet started fall cagr just number unstable define proper trend year talking early bobwallace tesla mod bolt start selling pretty safe guess imo year earlier zach report correct faster nevs produced china alone renewable energy deployment china wildcard bobwallace the general royal arent paying attention chinese evs imagine china replacing japan major supplier affordable good quality car chinese evs ford losing lot market share china chrysler finally dying zachary shahan curious byd qin tang hugely popular china china bobwallace expect chinese company concentrate country sale first product mature start manufacturing country start shipping chinese plant order build recognition market china largely ignore western european market while dominate asia develop low cost moderate range south america africa manufacture local market expensive labour jameswimberley wikipedia link highwaycapable plugin electric passenger car utility van sold worldwide add which leave smaller market million passed round october jburt world vehicle wayne williamson kind agree imply billion autos people planet automobilejust sayn ","m_szGeo1":"United States","m_szSourceType":"source_industry","m_szSrcUrl":"http://cleantechnica.com/2015/07/25/june-ev-sales-europe-vs-north-america-vs-china/","m_Places":["Europe","North America","China","Us","Canada","“north America”","Norway","France","Uk","Germany","Most","Tesla","Holders","Shorter","Usa","Japan","Asia","South America","Africa"],"m_People":["Ev Sales","Zachary Shahan","Bubba Nicholson","Vic Hristov","Wayne Williamson"],"m_Companies":["Eu Governments","Us Government","Wikipedia","Revolution","2020s","Guess","Link"],"m_BiGrams":["electric car","car sale","north america","electric vehicle","sale europe"],"m_TriGrams":["electric car sale"],"m_SocialTags":[],"m_Topics":[],"m_Industry":[],"m_Technology":[],"m_BiCnt":[13,9,8,6,3],"m_TriCnt":[6],"m_iDocBodyWordCnt":559}
