{"m_szDocID":"23535","m_szDocTitle":"Edison & Tesla Video Interview (EEI's Ted Craver & Tesla's Elon Musk & JB Straubel, That Is) | CleanTechnica","m_szYear":"2015","m_szDocSumamry":"textArticle -------------------- July 26th, 2015 by Cynthia Shahan   Things being better — that’s what this conversation with Ted Craver, Elon Musk, and JB Straubel (the first video below) is all about. This interview took place at an Edison Electric Institute event and is a conversation worth adding to any collection of Elon Musk or Tesla Motors videos (Nikola Tesla is briefly mentioned by Craver as well). Craver, Chairman of the Edison Electric Institute, leads the interview with Musk, CEO and Product Architect of Tesla Motors, and Straubel, Chief Technical Officer of Tesla Motors. Musk shar","m_szDocBody":"cynthia shahan conversation ted craver elon musk straubel the video below about interview tookplace edison electric institute event conversation worth adding collection elon musk tesla motor videos nikola tesla briefly mentioned craver well craver chairman edison electric institute lead theinterview musk ceo product architect tesla motor straubel chief technical officer tesla motor musk share energy vision eei annual convention talking profound commonality tesla spacex mention commonality work solar longterm sustainable energy source however believe solar relevant longterm sustainable source energy mention electric car key solution air pollution musk refer solar energy keylongterm source sustainable energy mention nuclear hydrothermal hydro wind whilethere form energy generation capable sustained long term though stresse believe primary mean solar long run make point that include clear area nuclear power plant typically today solar power panel spread area generate electricitythan nuclear space business type not video interesting discussion business ted craver mba bachelor degree economic international relation university southern california lead discussion teslas business belief ethic valid reason business type end organic farm ethic centralto teslas drive andi segmentsabout ethic interesting recommended tesla model picture videos communication touched video discussion interview reveal musk interest good communication discussion musk highlight avert communication loss sake good business standard broken telephonemusk explain that layer voice information processed through possibility information changing good intention called broken telephone musk choose word carefully discussion doe discusse value focus action ethic continue echo musk discusse list made early wasa student business innovation musk mention list made list believed affect future internet space exploration sustainable energy artificial intelligence genetic engineering add two artificial intelligence genetic engineering wrong room full laugh kiddingaccording new radio show listened pacifica npr trusted newsworthy noteworthy programme tortuously wrong stephen hawking reddit ama potentially wrong tomorrow july straubel chimed point highlight teslas engineering team visit spacex learn better spacex engineering team visit tesla purpose end recommended tesla gigafactory picture craver interest conversation lead musk style business meeting musk reveal tesla meeting minimised size meeting employee stay meeting helping tesla employee employee give considered useless interfering impolite stay meeting tesla employee sheis contributing meeting respected polite leave thus returning productive work craver lead discussion disruption disruption mean transformative business technology displacementmusk respond conversation well fan disruption sake disrupted important future world disrupt dont disrupt disruption result fundamentally society lot people fan disruption fan disruption fan better video continuesbytouching relationship craver musk edison tesla discuss powerwalland powerpack bit ethic sprout end video musk respond misinformation confusion subsidy politely remark wouldnt call time wrote journalism craver ask musk continue explaining polite statement misrepresentation tesla subsidy time point gather lacking episode broken telephone innocent recommended tesla model rumour musk mention shareholder meeting listened briefly video wellin experience sustainability businesse read lifeboat metaphor small planet earth yes lifeboat lifeboat country country country lifeboat read ethical discussion stay lifeboat troubled country lifeboat lifeboat saving person helping country entail lifeboat vulnerable sinking more small country secure lifeboat chance sinking introduce lifeboat sequence adding video therecent tesla shareholder meeting tesla shareholder vegan address issue leather teslas leather however requirement choose leather shareholder successfully lifeboat metaphor educated question tesla shareholder group watch listen allhere tonne videos above encourage watch time cleantechnicas completely free electric car report electric car early adopter follower want date hottest cleantech new subscribing free cleantech newsletter eye sectorspecific new also free solar energy newsletter electric vehicle newsletter wind energy newsletter tag broken telephone business ethic edison edison tesla edison electric institute elon musk ethic straubel ted craver tesla motor tesla powerpack tesla powerwall tesla subsidy cynthia shahan organic farmer licenced acupuncturist anthropology study mother unconditionally loving spirit teacher environmentally conscious being lit decade related post ","m_szGeo1":"United States","m_szSourceType":"source_industry","m_szSrcUrl":"http://cleantechnica.com/2015/07/26/edison-tesla-video-interview-eeis-ted-craver-teslas-elon-musk-jb-straubel/","m_Places":["Tesla","Well","Teslas","Farmer"],"m_People":["Cynthia Shahan","Ted Craver","Elon Musk","Jb Straubel","Stephen Hawking"],"m_Companies":["Edison Electric Institute","Tesla Motors","Spacex","University Of Southern California","Pacifica","Npr","Reddit","Ama","La Times"],"m_BiGrams":["tesla motor","ted craver","elon musk","edison electric","electric institute","sustainable energy","electric car","recommended tesla","broken telephone","fan disruption","tesla shareholder"],"m_TriGrams":["edison electric institute"],"m_SocialTags":[],"m_Topics":[],"m_Industry":[],"m_Technology":[],"m_BiCnt":[4,3,3,3,3,3,3,3,3,3,3],"m_TriCnt":[3],"m_iDocBodyWordCnt":600}
