{"m_szDocID":"235732","m_szDocTitle":"HERO Financed $1 Billion of PACE Projects","m_szYear":"2015","m_szDocSumamry":"HERO Financed $1 Billion Of PACE Projects Originally published on the ECOreport Renovate America CEO J.P. McNeill does not give many press conferences. In fact, this is the first I have attended in the three years I have covered this company’s HERO PACE, but yesterday was a watershed. HERO financed $1 billion of PACE projects. Hero Has Financed $1 billion of PACE projects Comparison of value of projects financed and the amount of money saved as a result of those projects “Our industry organization PACE now … has identified a total of $1.05 billion in home improvements which have been financed ","m_szDocBody":"hero financed billion pace project originally published ecoreport renovate america ceo mcneill give press conference fact attended year havecoveredthis company hero pacebut yesterday watershed hero financed billion pace project hero financed billion pace project comparison project financed amount money saved result project industry organisation pace identified total billion home improvement financed property assessed clean energy pace united state renovate america partnership western riverside council government city county california today topped billion mark dollar financed mcneill billion financed heroare projected save homeowner billion lowerutility billsconserve billion kwh electricity reduce emission million tonne the equivalent taking suvs road year save billion gallon water the equivalent million shower hero created job generated local economic impact billion origin riverside county mcneill drew attention riverside county heropace programme started company completed project located rick bishop executive director western riverside council government number reason interested pace ultimately hero pace programme rick bishop executive director western riverside council government first city elected leader viewed hero programme bring contracting job western riverside county important thatthe area coming recession number job related construction industry disappeared secondly tremendous environmental benefit water conservation thirdly viewed pace programme potential national practise meet environmental goal providing economic advancement region fourthly programme improve region older housing stock western riverside county make appealing future homebuyer year ahead low water garden now residentialproject california august president obama named pace innovative voluntary tool meet country clean energy energy efficiency goal encouraged use conjunction federal housing authority insure mortgage announced developing guidance pace financing renovate america expanding state negotiation advanced florida state mcneill initially mentioned name subsequently confirmed company talking governor staff york room growth mcneill ceo renovate america roomforgrowth california passing billion mark show momentum represent home california mcneill year million million housing unit united state replace system heating ventilation air conditioning hvac window roof water heater case coming end life failing unfortunately majority homeowner select leastefficient solution homeowner long stay home result leastefficient solution end expensive taking account total cost ownership energy water cost factored morgan report highlight hvac system purchased meet minimum department energy efficiency standard mckinsey study reason affordable financing identify pace viable solution mckinsey study point out conventional financing simply failed decade address barrier significantly penetrate market homeownerschoose hero pace financing rainwater harvesting make energysaving home improvement pay money down finance loan year reduce size annual payment homeowner payment made property taxe hero programme require contractor licenced state good standing hero homeowner obtain required permit product labour meet fair pricing standard homeowner product certified efficient department energy waterconserving environmental protection agency payment made homeowner sign job successfully completed image courtesy renovate america cleantechnicas completely free electric car report electric car early adopter follower want youd attend electric vehicle solar power event conducted cleantechnica date hottest cleantech new subscribing free cleantech newsletter eye sectorspecific new also free solar energy newsletter electric vehicle newsletter wind energy newsletter ","m_szGeo1":"United States","m_szSourceType":"source_industry","m_szSrcUrl":"http://cleantechnica.com/2015/11/12/hero-financed-1-billion-pace-projects/","m_Places":["America","United States","California","Mcneill","Florida","New York"],"m_People":["J.p. Mcneill","Rick Bishop","Barack Obama"],"m_Companies":["Hero","Pace","Western Riverside Council","Conserve","Riverside County","Housing Authority","Jp Morgan","Environmental Protection Agency"],"m_BiGrams":["renovate america","western riverside","riverside county","hero financed","financed billion","billion pace","pace project","riverside council","council government"],"m_TriGrams":["hero financed billion","financed billion pace","billion pace project","western riverside council","riverside council government"],"m_SocialTags":[],"m_Topics":[],"m_Industry":[],"m_Technology":[],"m_BiCnt":[5,5,4,3,3,3,3,3,3],"m_TriCnt":[3,3,3,3,3],"m_iDocBodyWordCnt":472}
