{"m_szDocID":"236192","m_szDocTitle":"Elio Motors: Another Solution For Greener Transport","m_szYear":"2014","m_szDocSumamry":"Elio Motors: Another Solution For Greener Transport December 15th, 2014 by James Ayre   Gas prices are falling. As of this writing, the average price of gas in the United States is below $3 per gallon. That’s likely good news for most people’s bank accounts. But, what might it mean for the environment? After all, when fuel price goes down, SUV, pickup truck, and minivan sales go up. Consider some of the sales gains for several large vehicles in October: Lincoln Navigator sales were up by 38% GMC Sierra sales jumped 12.5% Ram pickup sales were up 33%. Meanwhile, the Ford C-Max Hybrid saw sales ","m_szDocBody":"elio motor solution greener transport jame ayre gas price falling writing average price gas united state gallon good new peoplesbank account but environment all fuel price down suv pickup truck minivan sale sale gain large vehicle october lincoln navigator sale gmc sierra sale jumped ram pickup sale meanwhile ford cmax hybrid sale fall toyota prius fell october clearly stat troubling clean vehicle movement american entrepreneur devised vehicle affordable toallow people large vehicle utility recreational purpose maintain environmental consciousness efficient commuting paul elio founder ceo elio motor launching vehicle mpg call vehicle people suv minivan pickup truck buy elio solo commuting elio said large vehicle place taking family lake weekend driving kid hockey practise picking supply home improvement project weekend valid reason but week drive twenty mile work make sense gasguzzling vehicle empty seat elio right commuting work census bureau people travel alone vehicle designed solo commute americanmade threewheeled elio slated hit market half width traditional passenger vehicle feature unique fronttoback twoperson seating interior cockpitlike feel travelling small aeroplane benefit design pretty simple half mass move half air winddrag biggest loss fuel efficiency cutting winddrag elio motor making big stride improving fuel efficiency potential saving pretty impressive suburban commuter live mile office mile day round trip mile week mile year gallon commuting elio cost annually commuting vehicle mpg cost annually annually cost elio average vehicle mention vehicle lowerthanaverage fuel economy environmental benefit there too elio environmentally friendly cow here math cow produce pound methane year burp flatulence methane time effective trapping heat year period cow pound methane multiplied equal pound coequivalent greenhouse gase elio driven mile produce pound making elio environmentally friendly cow vehicle potential reduce dependence foreign oil elio motor hit sale target expected toreduce total oil consumption united state paul elio remain big fan effort build mass market hybrid electric vehicle hes realist size product fit all see elio vehicle good supplement consumer prefer elio onefifth price leading hybrid company path apparently consumer agree people reserved spot line purchase elio roll assembly line this sponsored elio motor cleantechnicas completely free electric car report electric car early adopter follower want youd attend electric vehicle solar power event conducted cleantechnica date hottest cleantech new subscribing free cleantech newsletter eye sectorspecific new also free solar energy newsletter electric vehicle newsletter wind energy newsletter tag elio elio motor jame ayre background predominantly geopolitic history obsessive interest pretty everything early life spent imperial free city dortmund jame river ruhr cofbuokheim attended university astnide briefly considered entering coal mining business write living broad variety subject ranging science politic military history renewable energy follow work google related post half width traditional passenger vehicle railway coach guest elios working hype elios scam intention realeasing car will lot interest test vehicle havent done make custom engine supposed extending existent now date release stop hype start producing something stop dragging feet possibility potential make have company create similar hype fabulous smell bad madoff character prove wrong production assembly line made car doug goofy make idiot year test drove model competitor tesla toy ivan stock telsa elio hitting market elio option people efficient afford electric car tesla people stuck poor efficiency option scooter motorcycle atvs driven ideal weather safe tip enclosed lynne whelden elio guy bring prototype northeast sit one bad back easy out work outsidethebox ideas saving money cris cassity car cool star safety rating due body panel applied roll cage frame fact move hit absorbing impact due weighing lbselectric windowsair conditioning stereo standard equipment cruise snow offgridman star safety rating due tested elios get government turned needing motorcycle mentioned previously care driver driven tractor trailer airbag regular motorcycle one recent interstate trip big suv rolled big truck front suv back front seat flattened feet the size engine block obvious damage tractor trailer wouldnt happen elio star rating cris cassity humveeelioa big rig doesnt difference ivan fine ended enclosed motorcycle motorcycle licence highmpg motorcycle safer drive year cold climate pull cheaper motorcycle well idea efficient reduced passenger vehicle safer practical bike affordable version year affordable close nice elio pulled off offgridman hoping pull off say stay grand projected price disgusted extended wait heard back production supposed start additional holdup design engine contracting shelf part doesnt make sense end lasting year purchaser one convert electric imagine range mounting leaf motor battery conversion kit couple year ago elios perfect tide practical priced evs available starting coming time enclosed motorcycle elio preferred choice family man wanting vehicle provide inexpensive commute spend much empg higher elio family weekend coworker giving smirk unusual choice vehicle marion mead fact move hit absorbing impact due weighing lbs sudden change motion crush internal organ vehicle bounce minor damage body internal whiplash absorb impact brunt cris cassity buy voltthen youre ready anything elio isnt selling alternative mercede joseph dubeau make good dominion pizza delivery vehicle colour sort cheesy looking run burping farting cow road making elio environmentally friendly cow fight terrorism vehicle potential reduce dependence foreign oil tricycle freedom car bobwallace merican flag joseph dubeau perform crash test offgridman claim wonderfully company due encorporated airbag crush zone wheeler motorcycle doesnt regular testing car face time elio sort independent testing sceptic takata airbag offgridman understand reference airbag involved recall lately elio plan using read full comment doubt safety qualification elio avoid testing classify motorcycle djr long covered bike corner deposit show retail centre staffjust empty promise dont target date production hope fruition wouldnt give company cent actual product sale jeff wegerson doesnt add smart more vehicle wheel triple price difference then calamityjean smart parked neighbourhood driving around elio people pay real pocket full mumble simon garfunkel john cheapest wheel car market remove wheel door and reduced that easily reducing price probably bit more still cry elio estimate well engine smaller smart great parking aerodynamically possibly stupidest vehicle world wide long meaning pushes tonne air reason meaning powerful engine elio dont suspect counting volume sale wont get however sell attention jeff wegerson math guess city dweller parking aerodynamic fast commute parking dollar travel dollar sot led direction smart car benchmark ivan understood smart car inefficient small size explain thank problem price calculated year ago simple inflation make hard produce car price sold concept gladly pay vehicle commute mile day wait economy current civic hybrid kent hasnt inflation spite interest rate low wage keeping price cheque good thing inflation hurt everybody kent elio doesnt layer layer useless corporate overhead profit pay for ivan elio new end scooter motorcycle true common people buy new true elio well average car cost counterpart calculus elio cost average car hoping electric elio someday honestly time economic gas version surpassed while assuming built price bobwallace assuming built price perchance dream rub hamlet offgridman average car start drive train warranty mile more heard elio give mile warranty brand untested motor design unwilling guarantee staying running reasonable amount mile scared making deposit sell proposed price point early adopter decent mile their service plan pep boy work out reconsider one wont hold compared car limited warranty john elio powertrain warranty total warranty pretty standard median low priced car addition elios competition offer free warranty big competitor powertrain warranty level toyota honda ford mazda mini nissan hyundai kia vehicle standard powertrain warranty brand bargain brand elio compete with powertrain warranty dont transfer owner offgridman changed website then back released photos amazing block design that looked similar original cylinder design geo problem dealing heat dispersal offer warranty drive train lot statement changed year initial production start year ago power train warranty transferring owner buy car good start vehicle continuing run right vehicle running mile problem original purchaser tester prove possible made one kent elios free factor fuel saving greenmonkeypant new elio production started car doesnt exist weve hearing year now time make real elio marion mead big rig wont run one mphg volt beat driving commute volt effectively mpg daily commute mile elio design sell pure version mile charge sold cheap nicholaus volt cost time price elio drive volt year order break elio people afford volt upfront elio made for common working class family larmion common working class family car brand vehicle definition target common people car hand vehicle didnt cost elio trunk ronald brakel yeah that australia chap bought place mine worker ended selling didnt place park car bobwallace number your tend count arent sitting yard block weed growing them ronald brakel watch clip australia internet isnt give insight australian working class culture way camira torana commodore cortina car fact torana production model car named century spanish inquisition torturer decorous our single incidence shooting cleaning weapon video ronald brakel sorry internet speed clip totally left exchange darryl kerrigan steve move camira torana commodore steve kerrigan dad ill key cortina gunna move camira darryl kerrigan alright mate watch boat estimate familial communication australia consist conversation this pricing small gas car cost dollar leave engine out brake muffle out gastank out battery pack electric induction motor cost nothing cheap expensive kent ","m_szGeo1":"United States","m_szSourceType":"source_industry","m_szSrcUrl":"http://cleantechnica.com/2014/12/15/elio-motors-another-solution-greener-transport/","m_Places":["United States","Us","Free City","Dortmund","“tesla”","Look","Tesla","Well","Toyota","Australia"],"m_People":["Elio , Elio","James Ayre","Paul Elio","Lynne Whelden","Cris Cassity","Marion Meads","Joseph Dubeau","Ronald Brakels","Darryl Kerrigan","Steve Kerrigan"],"m_Companies":["Mpg","Us Census Bureau","Path","University Of Astnide","Google","Coach","Volt","Dominion","Target","Simon And Garfunkel","Guess","Pep Boys","Honda","Mazda","Hyundai"],"m_BiGrams":["elio motor","powertrain warranty","large vehicle","passenger vehicle","elio environmentally","environmentally friendly","friendly cow","electric vehicle","electric car","cris cassity","average car","working class","ronald brakel"],"m_TriGrams":["elio environmentally friendly","environmentally friendly cow"],"m_SocialTags":[],"m_Topics":[],"m_Industry":[],"m_Technology":[],"m_BiCnt":[5,4,3,3,3,3,3,3,3,3,3,3,3],"m_TriCnt":[3,3],"m_iDocBodyWordCnt":1479}
