{"m_szDocID":"236401","m_szDocTitle":"Electric Vehicle Sales June 2013 | CleanTechnica","m_szYear":"2013","m_szDocSumamry":"Electric Vehicle Sales June 2013 Here are the latest electric vehicle sales numbers from EV Obsession . Enjoy! Ready for our monthly US electric vehicle sales (including hybrid sales) update? How could you not be? Below is the full table, including comparisons between June 2013 sales and June 2012 sales as well as between 2013 YTD sales and 2012 sales for the same period. Following the table are my comments/thoughts on this month’s update. Tesla Caveat: since Tesla doesn’t release sales numbers, it’s not included below. Sorry — petition Tesla to release those numbers if you want to see them! C","m_szDocBody":"electric vehicle sale latest electric vehicle sale number obsession enjoy ready monthly electric vehicle sale including hybrid sale update full table including comparison sale sale ytd sale sale period table month update tesla caveat tesla doesnt release sale number included below petition tesla release number them enlarge created obsession ccbyncnd licence chevy volt credit chevy volt rise plugin vehicle evs phevs chevy volt month couple month sitting nissan leaf also compared june volt strong rise from year date compared period sale volt roll out attractive volt sale pop expect strong month volt see nissan leaf image credit nissan nissan leaf rockin volt inch plugin electric vehicle month nissan leaf excellent sale month furthermore compared sale roof sale totaling year date leaf sale note month number reason sale burst massive price cut cut leaf manufacturing moving leaf leader due relative low price great owner review adequate spec phevs split pie plugin hybrid electric vehicle phev category compare volt phevs couple thousand unit volt sale stood other split rest pie pretty evenly except lowselling honda accord phev direct comparison phevs sale total again honda accord phev ford toyota cleaning hybrid market conventional hybrid ford toyota cleaned been prius conventional hybrid totaled whopping sale camry hybrid sale avalon hybrid sale highlander hybrid sale lexus hybrid sale meanwhile well clear position ford raked money sale fusion hybrid sale cmax hybrid sale lincoln mkz hybrid honda honda continue lag green car sale total hybrid electric vehicle sale numerous individual model brand beat lineup overall month strong hybrid electric vehicle growth compared year earlier electric vehicle sale skyrocketed thank largely leaf electric vehicle sale compared from storey yeartodate sale similar increase good phevs januaryjune conventional hybrid electric vehicle januaryjune additional thought latest hybrid electric vehicle sale number cleantechnicas completely free electric car report electric car early adopter follower want youd attend electric vehicle solar power event conducted cleantechnica date hottest cleantech new subscribing free cleantech newsletter eye sectorspecific new also free solar energy newsletter electric vehicle newsletter wind energy newsletter tag electric vehicle sale acura acura ilx hybrid chevy volt electric car sale electric vehicle sale sale ford ford cmax energi ford cmax energi phev ford cmax energi plugin hybrid ford cmax hybrid ford electric vehicle ford escape hybrid ford focus electric ford fusion ford fusion energi ford fusion energi phev ford fusion energi plugin hybrid ford fusion hybrid ford hybrid electric vehicle ford plugin hybrid electric vehicle honda honda accord honda accord phev honda civic honda civic hybrid honda crz honda fit honda insight hybrid electric vehicle sale hybrid sale hybrid vehicle sale hybrid lincoln lincoln mkz hybrid mitsubishi mitsubishi nissan nissan leaf porsche porsche cayenne porsche cayenne hybrid porsche electric suv porsche panamera hybrid toyota prius toyota prius toyota prius liftback toyota prius phev toyota prius toyota rav volkswagen volkswagen jetta hybrid jetta jetta hybrid zachary shahan tryin and specy letter time spend time cleantechnica director chief editor otherwise enthusiastically fulfilling duty obsession gas solar love planetsave bikocity president important media zach recognised globally solar energy electric car energy storage wind energy expert speak related conference event connect social media zacharyshahancom related post ","m_szGeo1":"United States","m_szSourceType":"source_industry","m_szSrcUrl":"http://cleantechnica.com/2013/07/04/electric-vehicle-sales-june-2013/","m_Places":["Us","Tesla","Split","Toyota"],"m_People":["Chevy Volt","Ford , Ford C-max Energi","Zachary Shahan"],"m_Companies":["Volt","Pie","Honda","Honda Cr-z"],"m_BiGrams":["electric vehicle","vehicle sale","hybrid sale","hybrid electric","hybrid ford","ford fusion","toyota prius","chevy volt","plugin hybrid","electric car","sale number","nissan leaf","honda accord","accord phev","phev ford","conventional hybrid","cmax energi","ford cmax","fusion energi","sale hybrid","prius toyota"],"m_TriGrams":["electric vehicle sale","hybrid electric vehicle"],"m_SocialTags":[],"m_Topics":[],"m_Industry":[],"m_Technology":[],"m_BiCnt":[19,11,8,8,6,5,5,4,4,4,3,3,3,3,3,3,3,3,3,3,3],"m_TriCnt":[10,7],"m_iDocBodyWordCnt":519}
