{"m_szDocID":"237030","m_szDocTitle":"Crayola To Clean Energy -- COLORCYCLE Turns Markers Into Clean Energy","m_szYear":"2013","m_szDocSumamry":"August 6th, 2013 by James Ayre   Crayola is launching a nationwide used-marker recycling program in which the used markers will be directly transformed into energy. The COLORCYCLE program, as it’s been dubbed, will give students throughout the country the option of recycling any type of used marker through an in-school collection program. The markers that are collected will then be used, in combination with a “unique technology,” to create a usable fuel. Crayola’s COLORCYCLE recycling program at work. Image Credit: Crayola Crayola actually already has a number of other related recycling and cl","m_szDocBody":"jame ayre crayola launching nationwide usedmarker recycling programme marker directly transformed energy colorcycle programme dubbed give student country option recycling type marker inschool collection programme marker collected used combination unique technology create usable fuel crayolas colorcycle recycling programme work image credit crayola crayola number related recycling clean energy programme initiative similar colorcycleinclude utilising solar energy production incorporating recycled plastic product reforested wood coloured pencil aim programme word crayola conducted extensive research emerging technology company repurpose marker found efficient beneficial solution time plastic energy process company repurpose entire marker part colorcycle programme crayola developed unique offering classroom lesson plan designed teacher educate student important role sustainability play world lesson plan engage student environmental solution teaching protect planet relevant way encouraging environmental responsibility hand interested school colorcycle programme crayolas registering participating school classroom lesson plan begin collecting marker crayola write inschool programme coordinator print crayola funded prepaid fedex shipping label delivery collected marker conversion usable fuel colorcycle marker programme know box recycled marker create energy prepare breakfast consist brewing pot coffee frying egg making piece toast marker produce gallon fuel power suv consider mpg mile classroom recycle marker move city bus consider mpg mile cleantechnicas completely free electric car report electric car early adopter follower want youd attend electric vehicle solar power event conducted cleantechnica date hottest cleantech new subscribing free cleantech newsletter eye sectorspecific new also free solar energy newsletter electric vehicle newsletter wind energy newsletter tag colorcycle colorcycle crayola recycling programme crayola crayola clean energy recycling programme crayola marker recycling programme crayola marker clean energy programme jame ayre background predominantly geopolitic history obsessive interest pretty everything early life spent imperial free city dortmund jame river ruhr cofbuokheim attended university astnide briefly considered entering coal mining business write living broad variety subject ranging science politic military history renewable energy follow work google related post ","m_szGeo1":"United States","m_szSourceType":"source_industry","m_szSrcUrl":"http://cleantechnica.com/2013/08/06/crayola-clean-energy-colorcycle/","m_Places":["Free City","Dortmund"],"m_People":["James Ayre","Colorcycle Marker"],"m_Companies":["Crayola","Nationwide","Fedex","Mpg","University Of Astnide","Google"],"m_BiGrams":["recycling programme","programme crayola","colorcycle programme","clean energy","lesson plan"],"m_TriGrams":["recycling programme crayola"],"m_SocialTags":[],"m_Topics":[],"m_Industry":[],"m_Technology":[],"m_BiCnt":[5,4,3,3,3],"m_TriCnt":[3],"m_iDocBodyWordCnt":303}
