{"m_szDocID":"237015","m_szDocTitle":"All Green For Green Electric Vehicles (+ 530% Increase In EV Sales) | CleanTechnica","m_szYear":"2013","m_szDocSumamry":"All Green For Green Electric Vehicles (+ 530% Increase In EV Sales) August 4th, 2013 by Zachary Shahan   Here’s the exciting monthly EV & hybrid sales update from EV Obsession . Enjoy! The numbers are in for “mass-market” 100% electric vehicle (EV) , plug-in hybrid electric vehicle (PHEV) , and conventional hybrid electric vehicle sales. Well, the numbers are in from everyone but Tesla and Fiat. (The Tesla Model S total in the colorful spreadsheet below is an estimate based on quarterly sales updates, since the rockstar EV company doesn’t report monthly sales.) As you can see in the embedded s","m_szDocBody":"green green electric vehicle increase sale zachary shahan here exciting monthly hybrid sale update obsession enjoy number massmarket electric vehicle plugin hybrid electric vehicle phev conventional hybrid electric vehicle sale well number tesla fiat the tesla model total colourful spreadsheet estimate based quarterly sale update rockstar company doesnt report monthly sale embedded spreadsheet green highlighting show yearoveryear change positive red highlighting show negative paying attention complicated system green sale total evs phevs conventional hybrid ytd pretty nice tremendous growth electric vehicle the greenest bunch seen compared sale compared ytd sale otherwise big storey month imho were nissan leaf sale inched ahead chevy volt sale leaf continued show excellent performance compared which drop price tag acura acura ilx hybrid chevy spark chevy spark chevy spark sale chevy volt electric car sale fiat fiat ford ford cmax energi ford cmax energi phev ford cmax energi plugin hybrid ford cmax hybrid ford electric vehicle ford escape hybrid ford focus electric ford fusion ford fusion energi ford fusion energi phev ford fusion energi plugin hybrid ford fusion hybrid ford hybrid electric vehicle ford plugin hybrid electric vehicle honda honda accord honda accord phev honda civic honda civic hybrid honda crz honda fit honda insight hybrid car sale hybrid electric car hybrid lincoln lincoln mkz hybrid mitsubishi mitsubishi nissan nissan leaf phev sale porsche porsche cayenne porsche cayenne hybrid porsche electric suv porsche panamera hybrid toyota prius toyota prius toyota prius liftback toyota prius phev toyota prius toyota rav volkswagen volkswagen jetta hybrid jetta jetta hybrid zachary shahan tryin and specy letter time spend time cleantechnica director chief editor otherwise enthusiastically fulfilling duty obsession gas solar love planetsave bikocity president important media zach recognised globally solar energy electric car energy storage wind energy expert speak related conference event connect social media zacharyshahancom related post zac growth gold lol enjoy zachary shahan ","m_szGeo1":"United States","m_szSourceType":"source_industry","m_szSrcUrl":"http://cleantechnica.com/2013/08/04/all-green-for-green-electric-vehicles-500-increase-in-ev-sales/","m_Places":["Well","Tesla"],"m_People":["Ev Sales","Zachary Shahan","Chevy Volt","Ford , Ford C-max Energi"],"m_Companies":["Honda","Honda Cr-z"],"m_BiGrams":["electric vehicle","hybrid electric","hybrid ford","ford fusion","toyota prius","plugin hybrid","zachary shahan","chevy spark","electric car","cmax energi","ford cmax","fusion energi","prius toyota"],"m_TriGrams":["hybrid electric vehicle"],"m_SocialTags":[],"m_Topics":[],"m_Industry":[],"m_Technology":[],"m_BiCnt":[8,5,5,5,5,4,3,3,3,3,3,3,3],"m_TriCnt":[3],"m_iDocBodyWordCnt":306}
