{"m_szDocID":"237329","m_szDocTitle":"Tesla Model S Is Safest Car Ever Tested, Sets New Safety Records (Tesla Releases More Info) | CleanTechnica","m_szYear":"2013","m_szDocSumamry":"Tesla Model S Is Safest Car Ever Tested, Sets New Safety Records (Tesla Releases More Info) August 20th, 2013 by Zachary Shahan   We already reported that the Tesla Model S has received a 5-star safety rating from NHTSA . With the recent  Model S crash that knowcked out a power grid , it’s timely that Tesla has just release more details on the 5-star safety rating. Notably, the Model S has set a new NHTSA safety record. The details on why are quite interesting. Here they are via Tesla (also available on the Tesla website ): Tesla Model S Achieves Best Safety Rating Of Any Car Ever Tested Palo ","m_szDocBody":"tesla model safest car tested set safety record tesla release info zachary shahan reported tesla model received star safety rating nhtsa recent model crash knowcked power grid timely tesla release detail star safety rating notably model set nhtsa safety record detail interesting tesla also tesla website tesla model achieve safety rating car tested palo alto independent testing national highway traffic safety administration nhtsa awarded tesla model star safety rating overall subcategory exception approximately percent car tested federal government achieve star board nhtsa publish star rating safety level star captured vehicle safety score vss provided manufacturer model achieved combined record star vehicle tested including major make model approved sale united state model set record lowest likelihood injury occupant model sedan exceeded safety score suvs minivan score take account probability injury front side rear rollover accident model advantage front large gasoline engine block creating longer crumple zone absorb speed impact fundamentally force distance problem longer crumple zone time slow occupant load injury jumping pool water tall height pool deep rock model motor foot diameter mounted close rear axle front section gasoline engine trunk side pole intrusion test considered difficult pass model car good category top percent vehicle tested compared volvo star rated category model preserved percent driver residual space percent volvo tesla achieved outcome nesting multiple deep aluminium extrusion side rail car absorb impact energy similar approach apollo lunar lander transfer load rest vehicle pole sheared stop car pole hit occupant rear crash testing important optional row children seat this tesla factory instal double bumper row seat ordered needed order protect highway speed impact rear permanently disabling injury row occupant row safest location car frontal side injury model substantially rollover risk top vehicle approximately percent worse testing independent facility model refused turn normal method special mean needed induce car roll reason good outcome battery pack mounted floor pan providing low centre gravity simultaneously ensure exceptional handling safety note validation model roof crush protection independent commercial facility testing machine failed exact number uncertain due model breaking testing machine mean additional fully loaded model vehicle top owner car roof caving achieved primarily centre pillar reinforcement attached aerospace grade bolt result full storey game regulatory testing score degree strengthening car exact location regulatory testing machine verifying internal testing model achieve nhtsa star rating tesla analysed model determine weakest point car retested location car achieved star matter test equipment configured model lithiumion battery catch fire time before nhtsa testing worth mentioning production tesla lithiumion battery caught fire model roadster speed impact statistically remain case long term tesla unaware model roadster occupant fatality car ever graphic show statistical relative risk score rss model compared vehicle tested exceptionally difficult nhtsa standard standard revised upward make difficult achieve safety rating tesla tesla motor nasdaq tsla goal accelerate world transition sustainable transport full range increasingly affordable electric car californiabased tesla design manufacture evs powertrain component partner toyota mercede tesla delivered electric vehicle customer country cleantechnicas completely free electric car report electric car early adopter follower want youd attend electric vehicle solar power event conducted cleantechnica date hottest cleantech new subscribing free cleantech newsletter eye sectorspecific new also free solar energy newsletter electric vehicle newsletter wind energy newsletter tag nhtsa tesla tesla model nhtsa tesla model safety tesla model safety test zachary shahan tryin and specy letter time spend time cleantechnica director chief editor otherwise enthusiastically fulfilling duty obsession gas solar love planetsave bikocity president important media zach recognised globally solar energy electric car energy storage wind energy expert speak related conference event connect social media zacharyshahancom related post ","m_szGeo1":"United States","m_szSourceType":"source_industry","m_szSrcUrl":"http://cleantechnica.com/2013/08/20/tesla-releases-more-info-on-tesla-model-s-5-star-safety-rating-new-safety-records/","m_Places":["Tesla","Best","Palo Alto, Ca","United States","Lander","California","Toyota"],"m_People":["Zachary Shahan"],"m_Companies":["Nhtsa","National Highway Traffic Safety Administration","Pool","Volvo S60","Volvo","Seat","Tesla Motors","Nasdaq"],"m_BiGrams":["tesla model","safety rating","electric car","car tested","star safety","vehicle tested","speed impact","testing machine","electric vehicle"],"m_TriGrams":["star safety rating"],"m_SocialTags":[],"m_Topics":[],"m_Industry":[],"m_Technology":[],"m_BiCnt":[6,5,4,3,3,3,3,3,3],"m_TriCnt":[3],"m_iDocBodyWordCnt":588}
