{"m_szDocID":"237447","m_szDocTitle":"Shai Agassi's Third Article On The EV Revolution | CleanTechnica","m_szYear":"2013","m_szDocSumamry":"August 26th, 2013 by Zachary Shahan Â  Last week, Shai Agassi wrote and we shared two articles regarding how electric vehicles (and Tesla, in particular) are disrupting the automotive world, and will do so much more in the future. In his third article in this series, Shai makes some very interesting points about how new sales channels generally come with disruptive new technologies, why EV sales channels need to be separate from gasmobile sales channels, some excellent options for that, and much more. Have a read! Operators Wanted: Who Wins When the Electric Car Wins, Part III By Shai Agassi My","m_szDocBody":"zachary shahan week shai agassi wrote shared article electric vehicle and tesla particular disrupting automotive world future sery shai make interesting point sale channel generally disruptive technology sale channel separate gasmobile sale channel excellent option that more read operator wanted win electric car win part iii shai agassi post subject dealt lesson learned tesla volume auto maker respond manufacturing electric car mainstream emergence electric mile operator car industry gms ceo dan akerson model run mci nextel cell phone operator company bought bandwidth usually government massive contract sold operator infrastructure consumer paying monthly contract minute byte mileage operator buy massive amount battery electricity keeping cost ownership customer dealership car company balance sheet setting infrastructure offering simple monthly mileage contract consumer operator help complete experience grow massmarket appeal imagine people love buy insanely great car pay weekly contract effectively cost pay gas station refill car week offer superior performance drive mile month fixed fee allyoucandrive contract fit short distance urban driver barely move car fear losing parking spot fit million suburban commuter drive hour work back traffic fuel week operator car industry friend fact unlike gas station today operator eventually subsidise cost buying electric car replace government incentive subsidy repay original cost setting infrastructure cost battery continue decline feel at&t subsidising cost iphone subscriber year operator subsidy government eventually back support provide nascent market volume turn higher changing distribution big market disruption tend happen sale channel disrupted effect amazon book industry netflix video rental apple music sale apple store computer sale combination product category offered disruptive price sale channel real game changer price industry leader build direct sale channel channel dedicated sale sit sidebyside current dealer leverage service infrastructure differentiate sale people storefront space person walking dealership persuaded change mind pick gasoline car nissan experienced volt leaf launches buyer interested drive train hood emblem top alternative channel current mass volume distributor electric appliance channel buy extreme channel primarily web based price point parity car compete consumer enter dealership today car buyer ebay reason evs shouldnt offered ebay viable alternative car ebay sell hundred thousand million car price point year tesla contend past dealer contract existing dealer channel legal battle hand state franchise law protect dealership car company wishing cut dealer dealer made massive investment set expensive dealership industry work dealer them transition roll out dealer part invest service passing demand development investment back finally option carmaker investigate creation completely separate brand revive brand saturn ford chrysler revive create brand longer use channel owned apple store partnership automotive service network jiffy lube penske mover advantage mover cross mass volume threshold company make car capture sale mark year globally threshold set approximately million car year only threshold close car car platform supporting variant categorydefining car prius understand categorydefining car mean market carmaker alike historically similar category emerge seemingly overnight prior proof market demand back chrysler suv minivan car defined category chrysler bob lutz defied odd delivered insanely great car seemingly nonexistent demand materialised soccer mom suburban suv driver back century remember henry ford didnt run market survey cut price tag ford modelt result disruptive mass produced car priced time average market price defined category entire industry follow lesson model produce base version electric cross over make beautiful benefit great electric performance ford modelt game plan price car disruptive price battery included after operator subsidy government incentive volume price car making great profit carmaker support car operator deploy infrastructure making convenient gasoline car operator battery offer electric mile weekly cost parity average driver pay gasoline today service contract unlimited mile offer luxury version car option offered higher price point consumer offered insanely great car buy tonne addon generating margin carmaker mover benefit volume car industry volume production translate lower discount cheaper bill material word margin sale case modelt toyota prius teaches following brand define category carry volume profit category long while opportunity define market long rule set immensely harder disrupt leader computer maker build ipad market support carmaker category simply reality leader define market segment higher margin fast follower spend margin money attempting catch carmaker bring game back point strategy bring back category incumbent playing field target mass market producing volume lower price point made chevrolet americas car foundation created ford time modelt strategy underlying japanese car penetration market offer car lower price point sailing massive boat deal global supply chain quality production scale distributed service centre recall make design strategy leverage function build playbook take advantage strong wind undercurrent pushed tesla far plan current pick boat size power dont launch small boat deck lose inherent advantage lose talented sailor put satellite project massmarket carmaker car category defined natural offering hand tesla shouldnt run playbook play inherent strength current ford toyota easily ride volume strong teslas tender mast sail body tesla target segment year scaling experience end destructor them good tesla auto industry whole agile innovative tesla run ahead current magic price point wait part cleantechnicas completely free electric car report electric car early adopter follower want youd attend electric vehicle solar power event conducted cleantechnica date hottest cleantech new subscribing free cleantech newsletter eye sectorspecific new also free solar energy newsletter electric vehicle newsletter wind energy newsletter tag disruptive businesse disruptive technology shai agassi zachary shahan tryin and specy letter time spend time cleantechnica director chief editor otherwise enthusiastically fulfilling duty obsession gas solar love planetsave bikocity president important media zach recognised globally solar energy electric car energy storage wind energy expert speak related conference event connect social media zacharyshahancom related post ","m_szGeo1":"United States","m_szSourceType":"source_industry","m_szSrcUrl":"http://cleantechnica.com/2013/08/26/shai-agassis-third-article-on-the-ev-revolution/","m_Places":["Tesla","Us","America","Toyota"],"m_People":["Zachary Shahan","Shai Agassi","Dan Akerson","Henry Ford","Bob Lutz"],"m_Companies":["Mci","Nextel","At&t","Amazon","Netflix","Apple","Volt","Best Buy","Ebay","Penske","Target"],"m_BiGrams":["sale channel","electric car","shai agassi","electric vehicle","car industry","insanely great","great car"],"m_TriGrams":["insanely great car"],"m_SocialTags":[],"m_Topics":[],"m_Industry":[],"m_Technology":[],"m_BiCnt":[6,6,3,3,3,3,3],"m_TriCnt":[3],"m_iDocBodyWordCnt":908}
