{"m_szDocID":"237666","m_szDocTitle":"Tesla Quietly Releases Redesigned Model S Handle Mechanism | CleanTechnica","m_szYear":"2016","m_szDocSumamry":"Sure, volatility in TSLA is always going to be greater than for a  typical dividend stock. And many people have seen a general market correction coming for some time. Some of us even kept some money aside to buy into the correction. And I’m probably going to take another bet on Tesla early next week, before the Wednesday quarterly. BUT… There is no guarantee that Tesla will simply bounce back and then grow indefinitely in a similarly bouncy fashion. The valuation is predicated on the ability to deliver 500k cars in 2020, at a 20-25% gross margin. Some of the biggest bulls are starting to raise","m_szDocBody":"sure volatility tsla greater typical dividend stock people general market correction coming time money buy correction bet tesla early week quarterly guarantee tesla simply bounce back grow indefinitely similarly bouncy fashion valuation predicated ability deliver car gross margin biggest bull starting raise doubt projection real risk company mostly making threat heady growth projection survival company share fall zero happen fact number storey published recently expected move stock and have crucial threat mentioned external perceived competition internal dont bombard comment link ill post relevant new storey youre interested drop telsa significantly larger broader market larger volatile momentum stock specifically targeted sense fundamental shift sentiment general market pessimism starting creep public tesla narrative lot unnecessary complexity design flourishes potential production delay maintenance bottleneck potential recall resale guarantee liability hundred roadster road afford design iteratively customer generally wealthy people multiple car keen sense environmental mission and did tolerate number issue tesla producing ten thousand car year lot difficult expensive handle kind persistent maintenance issue widespread dealer service network customer stand massively inconvenienced tale long wait service centre routine maintenance production hundred thousand car year single recall seatbelt bolt conceivably destroy company bobwallace couple point first single recall destroying company bit melodramatic second doubt investor expecting gpm mod lower gpm expect move ladder profit move higher margin higher volume neroden market completely irrational lot risk factor tesla listed myself all fairly easy month ago price drop fundamental ever robwithab clearly real company magically shrink week real share price saying point out potential risk mapped month ago delay ramping production anticipated many due complexity effect elon noted month agothere literally information past week justify large movement unless secret information access opportunity load share basically half price compared month ago made fundamental calculation month ago set parameter constitute buying signal were basically model shipping customer tesla energy product shipping customer model launch date announced imminent elon alive insane competent cfo cto marketing leader place share price started buying tentatively delivery announcement adding position since share price increase year buy difference gain gain basically lucky that time decided step price falling falling significant change fundamental average price depending week nerve steel honestly suspect market irrationally optimistic share price shot level similarly suspect irrationally pessimistic now time tell neroden actually valuation doesnt depend that think based calculation car gross margin easily justify current valuation major bet course lot downside make valuation such people buying company electric car masse sucking tesla price war robwithab zachary shahan fortune piece hadnt one hadnt jonas lowered target dont explicit reason stock price dropped average day beginning year lot possibility clear warranting headline here what teslas long slow stock slide here choice sentence meanwhile analyst pacific crest lowered expectation teslas production suv model slower expected they else guessing fine guess adjust price accordingly highly speculative now seldom wrote tsla past skyrocketing clear effect arent start time soon speculative game market irrational robwithab reluctance comment share movement founded believe isnt valid cleantechnica new movement share price severe alter survival prospect company dont yet problem delayed delivery production people reported vehicle sitting service centre final inspection week partially informed rumour suggested wait final missing lot speculation sure delay real people upset cancel order reason bout partially irrational negativity interesting opening debate include valid criticism respectable analyst usual shorter fudder clear vested interest company fail longterm tesla fan finally speaking openly long term risk threat feel speak mind head bitten off theyre asked explain what guise posthoc analysis carte blanche speculate roadblock glorious future stuff emerging along lot wildly speculative uninformed rubbish course good this folk tesla dont realise deeper bargained unnecessary complexity model elon record admitting futuristic stuff respected analyst start talking prolbem tesla concrete step address issue announcing base version model bell whistle ahem #optionthedoor storey touched poor communication company wrt customer paid car waiting week month delivery addressed however new storey round traced back rumour started identified short stranger model launch reveal prototype sketches based single flippant answer elon context question french student paris event seeking alpha eating stuff commenter fuelled confusion media outlet link storey quoted mainstream outlet fact spouted wsj nyt ive thread obsessively couple week kinda way understand new formed thin air interesting tracking kind cyber detective layer layer inadvertent replication error deliberate obfuscation doubt short riding dip hard point close position zachary shahan problem delayed delivery production people reported vehicle sitting service centre final inspection week yes anecdote this sign delivery well guessing biggerthanexpected problem production scale basically reserve judgement tesla announce something reason bout partially irrational negativity interesting opening debate include valid criticism respectable analyst usual shorter fudder clear vested interest company fail definitely agree good this folk tesla dont realise deeper bargained unnecessary complexity model elon record admitting futuristic stuff agreed again dont simpler base model table tesla work bug which forget similar type issue beginning luxury suv market specifically cool tricky feature course fully recognise wrong concern distressingly valid communication yes teslas weakest area lot big huge communication fail past year however new storey round traced back rumour started identified short stranger model launch reveal prototype sketches based single flippant answer elon context question french student paris event seeking alpha eating stuff commenter fuelled confusion media outlet link storey quoted mainstream outlet fact spouted wsj nyt again completely agree furthermore evfocused site apparently fueled fire noticed havent posted opinion you eager unveiling arrive past speculation phase hand ive thread obsessively couple week kinda way understand new formed thin air interesting tracking kind cyber detective layer layer inadvertent replication error deliberate obfuscation imagine interesting media world today yeah great buying opportunity recommending publicly number risk dont carl raymond clear effect pretty sum stock market imho article title tsla today explain market forecast decline betting sheep run spooked investor worked model car tip proposition favour evs and tipping change world people worked reading scrap tesla new and gaining label fanboy fascinating watch sheep grass green bobwallace worked reading scrap tesla new and gaining label fanboy fascinating watch bobwallace downside stock price unrealistic upside stock pricing involve lot emotion scenario people start talking selfdriving car based couple elon casually say spun people mind fully autonomous car start buying stock make price rise people price make money trading upside price overshoot reality down price irrationally high optimistically high level information caused upward movement price dropped back reasonable level time general market correction neroden honestly hard put price company tsla adam jonass range think spread value there depending succeed fail bobwallace correct large amount uncertainty lot room unreasonable overvaluing unreasonable undervaluing lot people treat price peak real movement back closer median evaluation bad company bobwallace headline wrong crystal ball point folk tesla lot front company lot information knowledgeable people journalist isnt expert electric vehicle frank ill start worrying tesla start trouble selling car neroden silliness mainstream auto press teslas havent filled preorder stage model declared mistake reaction huh risk tesla arent people talking about stock market whacky anthony guess number inventory make care started issue start data solve make longer lasting eric lukackuruc you wuestenblitz cleantechnicacom clean technology important piece clean technology rise electric clean car clean piece automotive technology dealing big piece clean energy puzzle perfectly forum benjamin nead serious isnt battery efficient traction motor effectively deployed charging infrastructure silly motorised door handle knetter found interesting time spray everywhere benjamin nead time spray useless bullshit doesnt what genuinely important electric car technology levelled sentiment here found interesting good equally compelling topic knetter ahhh muffin fire wambulance friggin libertarian interesting hear car company making improvement car released youre fool apple doesnt bother time fix piss poor engineering flagship laptop decade multiple class action lawsuit spare dont dont fucking read stfu constructive time doesnt include stealing land benjamin nead sad intelligently debate merit adult trolling junior level insult dont sort electric car lease tell havent driven one bobwallace dialling back important release ahole save climate change denier koch brother wuestenblitz silly door handle ford agree leading market conventional door handle increase effeciency guess what problem fickle people everywhere mirror door handle fickle adopting drive train technology relevant theme site knetter wouldnt fix handle model out zachary shahan dont spell obvious maybe spending time jenny sommer why bobwallace day complained article energy pawan sharma yes article trump hillary ted berni site flamingo well commenter fling mud people deem lowly due political party affiliation article point important feature relative important company feature fix car warranty encourage sale adoption clean tech comment mentioned people bought car sillier reason zachary shahan hahaha eveee zach hit hard article critical enough thought talking telsa failure improvement balanced covering tesla everyone knetter fuck pleasing everyone enjoyed article show current iteration handle didnt work tesla stepped make improvement doesnt sound car company there havent forgotten model theyve rolled door eveee complaint there make request say imo discussion review evs phevs make sense people dont buy car evs although imo big selling factor buy good car frank vid day talking tesla acted software company minor patch big company recall thing good avoid model year implying fixing problem kyle field fully agree continuous improvement expect recall wide spread point affecting reliability safety obviously zachary shahan yes pleasing everyone fact large publish storey day isnt happy storey ironically tesla storey popular far attract unhappy reader odd dichotomy there eveee generally true controversial post reader reader there posting occasional odd post data bunch article bolt egolf other pretty balanced emphasis tesla leader lot lot tesla new site too bit odd tesla coverage doncha think zachary shahan thank yeah basically cover cleantech storey notable author themselve turn out tesla storey big one obvious and here tesla virtual ink fiat guess everyone eveee fiat that lol rodney dangerfield automotive seriously chrysler minivan phev announcement heard cool green website cover obscure green stuff doesnt tesla kraylin strange human phenomenon people love hate leader people top tesla anonymously internet bobwallace yes attempting tear successful commonly see situation jealous success attempt decrease distance successful finding often minor fault harping them found flaw didnt prevent good them hell better otis ironically tesla storey popular storey attract reader moan tesla attention company doesnt media love havent single owosso pulse magnasteyr mila totally didnt obscure fuel efficient vehicle dig link promise frank well tesla hasnt pleased model made pleased preparing model some aint pickup minivan subcompact hope make happy philip dont benjamin nead cleantechnica read drum roll clean technology lifestyle rich famous storey jeffhre yet read commented reading useless bullshit doesnt what genuinely important article hmmm philip clicked stated headline doorhandle youre weird dude lot article dont interest much dont complain ignore found interesting problem doorhandle past tesla owner relevant them jeffhre lol benjamin nead completely bound comment merit here hurling invective people opposing view defensiveness didnt extraordinary and case devolved immature personal attack fairly obvious blog set provide general coverage clean technology topic simply online hangout handful tesla owner havent figured comprehensive space people care detail vehicle interact share sort new start article clean technica talk aspect car tesla doesnt relate environmental impact technology doesnt relate car point point gasoline feeling posted site simple that zachary shahan posted reply well kyle longterm review tesla model cynthia longterm review leaf people planned chevy bolt chevy volt probably word popular evs market transportation account global warming emission urban air pollution evs critical solution tesla storey combination reason popular storey general popular storey day simply recommend recommended storey doesnt interest you skip one cover broad range topic now storey published day single storey wont interesting single reader making people happy broad coverage benjamin nead fair enough zach blog tesla cheerleading thick time though tarnish clean technicas objectivity reporting subject good luck zachary shahan dont cheerleading heck stuff interesting worth highlighting apparently matches largest number reader youre finding lot pushback above youve made point numerous time weve sort start feel trolling bobwallace give couple example article tesla tarnished site understand people unhappy tesla receive attention here benjamin nead dont speak issue clean technicas tesla coverage provide perspective regular email publicly inflame passion further anybody interest but yes dont hesitate drop line zach contact information thank bobwallace address let discuss tesla coverage let involved discussion make reasoned reasonable comment inflame anything pushback tesla people general favour evs green tech general interesting understand possibility brand loyalty isnt thing teslas class suspect unhappiness people long distance tesla follow spent mind holding back next what take what driving you dogphlap dogphlap dear bob wallace line cleantechnica reader feel coverage matter tesla blog excessive bobwallace lot people feel way tesla article lot view lot comment article topic love neutral read article interest skip dont lot site site publish read frequently quit looking dont understand concerned tesla article coverage xyz understand that concern tesla pushing deserving car page frank worst electric car cared fact tesla generate passion car buyer good thing conversation people brought electric car poo pooed mouth tesla why compromise range charging size performance bitch price model coming benjamin nead camp interested lot socalled low medium price evs road handful speedy luxurious one ecological quality life sake lot people car guy privileged few fewer car street bicycle light rail urban areas speed rail them perspective world importance american style consumer oneupmanship put odd people dedicated car enthusiast site main reason dont frequent often obsession speed acceleration callow grand scheme thing outsized emphasis luxury dont care about teslas raison dtre foreseeable future implore move important thing superfluous door handle technology concerned effort time expense model predict problematic positive company argument made isnt taking resource important model hear people exclaiming tesla small underdog compared big oem dollar count doubleheaded thesis fall flat tesla coverage site topic clean technology which assume derived from number issue expanded upon housing urban aquaponic agriculture socalled luxury car door handle inconsequential mildly annoying lost opportunity editor reach cover wider portfolio actual clean technology topic increasingly swept editorial table doesnt bait draw sex appeal factor new found internet clean technica instead morph poporiented appeal year ago important topic place well end expanded audience much replace one year radio broadcasting industry unique perspective work unchecked increasing bellicose internet tesla fan base here everywhere accusation contrary here dont comb numerous tesla article clean technica log snarky comment make known past month yourself back further spend day hyperfanaticized enthusiast doesnt way youre company youre not political world defined fascism declare antielectric car questioning logic tesla headed preposterous secretary eaa chapter medium sized metropolitan area tucson arizona telsa owner represented club presence participation organising event inception annual activity founding ive engineered couple largest public gathering car hundred mile direction recent event visit mayor sit model guided tour car feature owner volunteered advisory capacity representing southern arizona project tesla green chamber commerce process putting opportunity charging infrastructure city country didnt tesla highly important player wider adoption evs needing pad online resume further ill emphasise point again deeply insulting rabid vocal minority internet performance car fanboy sheepishly hide anonymous online profile express twitterlike sound bite paint corner questioning logic luxury door handle article importance discussed here tesla related otherwise audience site editor foster decision mine riely rumfort futurist party greater picture benjamin nead thank riley ive panasonic ncr bring electric car event inside model pack declare tesla triumph engineering wax door handle robwithab write well substantially sane youd penning cleantechnica important subject mentioned knetter upvoted tesla hater good job benjamin nead downvoted troll bravo robwithab realise this selectively critical feature action product person entity necessarily filled hatred target criticism playground and american party politic strictly dichotomous good guy bad guy narrative exist george youre rest thinking world tempted pick side simply sat thinking idiot real world nuanced that overly simplistic tendency lump people category hater opinion match doesnt free exchange information world survive tesla succeed especially financial investment success suspect enjoy elon musk company met him mean criticise aspect vehicle zachary shahan kyle longterm review tesla model cynthia longterm review leaf people planned chevy bolt chevy volt probably word popular evs market transportation account global warming emission urban air pollution evs critical solution tesla storey combination reason popular storey general popular storey day simply recommend recommended storey doesnt interest you skip one cover broad range topic now storey published day single storey wont interesting single reader making people happy broad coverage han place cleantechnica place luxurygoodstechnica boringdetailstechnica comforttechnica ronald brakel forgot lovehandle dot com oddly enough surprising amount traffic robwithab typing browser now right time scarred life life jeffhre comment redirected hanspetpeevesdotnet frank tesla designed model small make mass market car robwithab make normal door handle option normal people work trendy tech gimmick moment fear company future bobwallace people purchasing luxury good expect ordinary robwithab car extraordinary problematic door handle crevasse guess wanted luxury car loaded gimmick costly fixe inevitably south left engine out ronald brakel add bit car range improved areodynamic expect standard feature car suddenly electric window good reason benjamin nead hard design conventional car door handle flush aesthetically pleasing dont complex retractable hardware amount range extracted tesla handle design measurable jeffhre hard design conventional car door handle flush easy perspective year thousand iteration forward try benjamin nead said instead easy design overly complex mechanism impress people bit money pay car door handle greater aerodynamic spec work fine ronald brakel personally ive fangled electric starter wrong footman crank engine mind you rich crash afford toemen jonnyk bozos forgot advance spark crank kick back knock butt splash mud car eveee jeffhre difficult good since difficult guy automobile knowledge good arm robwithab knowledge dangerous completely armless kacey green camry car break completely normal climate hot cold people aggressively pull handle robwithab hate electric window bother car nowaday dont offer manual window option theyre fiddly difficult adjust correct level ball ache break inevitably make sense replace heavy winding mechanism required manual window lighter door lock simple light small aint broke dont fix tiny bit extra drag normal recessed door handle induce compared energy required aircon going dont aircon prefer simply drive window slightly open impossible electric window minority here people love gadget sake aerodynamic initial driver automated door handle reason retained gimmicky tech people impress neighbour benjamin nead stand either what surprising defend automaker continuing cram car gadgetry this know buy car longer manual window crank neroden door lock handle complicated finicky popout handle model complicated finicky door button model pretty simple dragon ive read opening window highway speed cool car energy due increased drag air conditioner robwithab recall episode mythbuster sure crank window open fully all open driver window inch back diagonally opposite similar amount pleasant cool breeze fresh air past face life good smell freshly cut grass sweet cow fart surrounding countryside notso sweet fart inside aircon lot energy depending temperature difference intuitively make sense feel energy noting warmth extracted big lump air similar amount energy wasted drive window slightly open sure window wide open speed hear feel buffeting clear lot vortice created warming sausage air slightly car kilometre small amount breeze past face draw similar amount power small electric fan dragon found mythbuster experiment referenced unfortunately lot variable didnt test air resistance bigger factor fuel speed increase mph beat open window efficiency suv higher drag model think opening window increase drag smaller percentage suv opening window model again efficient created equal expensive efficient increase range ice suv efficient efficiency isnt big selling point suvs smaller cabin space cool evs suvs power making car white black reduce not colour mythbuster suv was logical cracked window create drag fully open window absolutely tested somehow end idea efficient model track energy testing own robwithab mythbuster entertainment experiment generally lack rigour designed provide optimal display spectacular destruction karis tattoos tatas fun nonetheless factor didnt delta inside temperature tesla great testbed recreating experiment input accurate result curious hard data neroden yeah aerodynamic stated practical motivation model door button extreme aerodynamic jenny sommer doorhandle all benjamin nead exactly star trek transporter technology enter vehicle atomic structure deconstructed assembled side door ricegf tesla design electric motor vehicle production think jenny include physical door handle say open pod door hal command voice recognition physical button remote ambient noise jenny sommer cover push grip recessed flush handle design cheap reliable flush mechanical solution hey teslajust contact disqus neroden jenny youll note model door handle button frank minus extra belly fat robwithab indeed process automated handle redundant dont trusting simple automation ive trouble opening door myself jenny sommer pop door mechanically turning key door lock spring loaded cheap cover push open door recessed handle cover screwed hinge put personalised cover wood covered leather robwithab idea discreet personalised polished wooden door handle cover fill strange sense joy kacey green yes convert model style door button door power opening closing front door future order kyle field make normal gas car normal coal fired electricity change world rob change world benjamin nead youre losing perspective kyle electric car dont pollute exotic door handle rob exclaiming basically useless gingerbread tesla hard impress gadgetry upcoming model possibly cutting corner important simply meet price point theyre trouble kyle field model created splash door handle electric sexy second touchscreen sexy sell majority teslasnot fact electric nice most somy point fact abnormalthat cool sell themwhich turn people interested electric car drove leaf wife drive mercede bclass electric caresbut bought tesla people flipped electric that fantastic electric car robwithab make model sexiest car made imho bodywork proportion curve clean line bulge lack unnecessary ornamentation form function aimed lowering lot fact lot flexibility accommodate big lump engine gearbox fuel tank etc fact teaches trick ota update brilliant roadholding due millisecond response power allocation combination wheel blistering acceleration surefooted handling due low centre gravity free long distance travel life freedom anywhere please closet friend ultimate road trip vehicle range align internal organ drive past single filling station knowing ill validate crazy pathological ideology bin saud clan western flunky giving hardearned money maintenance until maintenance issue started cropping unnecessary complexity design car made sexy doesnt shout whisper make vehicle mouthwateringly sexy directly indirectly related fact car electric sure electric car tesla redesign notion car ground optimise strength electric mobility bunch smart engineer strong sense purpose spent lot time striving make perfect car turn out sort reason perfect car electric make better problem started let everyday work fine mission accelerating transition sustainable transportation reinvent too sometime smart people left run free pack stupid dragon youre quoting people online research ive literally heard walking car big screen havent heard comment handle yet assume noticed startling feature dont vehicle frunk assume catches attention feature provoke online research info mentioned body shape lovely ive plenty car share similar shape isnt grab attention again manager donut shop parked admire car shape help too zachary shahan robwithab devoted attention important stuff world changing fast coal fired electricity petroleum fired car engine enormous amount r&d time money devoted refining technology replace these greater scheme thing automated door handle and doorsare distraction people inclined buy tesla regular door handle threat longterm maintenance problem toracle hope model practical fancy door handle nice care that perttu lehtinen normal handle dont work cold finland cold robwithab interested hear this sort problem people encountering differing coefficient thermal expansion individual component water condense freeze inside door design door handle iced vehicle swedish automaker saab volvo aware found way solve solution use jenny sommer lock freeze prepare lock dont freeze winter broke lock golf winter door frozen shut pull open robwithab thank hadnt heard problem before zachary shahan word south africa robwithab yup hired mazda minivan eastern ontario parked night managed repeatedly problem cold door handle freeze shut physic process sort sleet ice involved mike rainyicysnow combination pure snowfall doesnt neroden roughly freezing point wet condensation freezing bobwallace ive frozen mechanical rain quickly falling temp neroden ive latch mechanism freeze lock working minnesota charle quintin year ago worked security northern big facility lot outbuilding winter water drip doorknob freeze propane torch standard equipment patrolling wed heat doorknob unlock building car door know still ice everything overengineered stuff bobwallace frozen car remote setting luckily cigarette lighter key part lock heat door open kick window wasnt happening rubber boot frank tesla bigger battery normal ice car electricity added resistive heating driver side door lock easily open cold icy day plenty range good robwithab not guy scenery chewer bob almosttzi wallace dragon assume tesla style handle freeze shut easily standard handle tesla handle heater turn heat phone half hour driving cabin heat philtre handle saturnv neroden stupid handle sold car extremely successful marketing time show car impressed handle theyre dumb myself argue incredible viral marketing success cost are pay marketing value maloo change time fitted version supply issue benjamin nead wouldnt chance followup storey eventually south sort helicopter technician flying replace subsequent one inquiring mind knetter spray everywhere year boy cialis robwithab dude fantasy life showing bit disturbing honest talking door handle youre dont benjamin nead day teslas greatest liability letting comment fan place conventional advertising lead jamset replaced free lamborghini huracan flush door handle also unlock car handle pop out tesla handle depend remote control touch sensor zachary shahan yeah covered warranty harrower similar behaviour model well unlock vehicle handle pop out fact recently added option driver handle software update ","m_szGeo1":"United States","m_szSourceType":"source_industry","m_szSrcUrl":"http://cleantechnica.com/2016/02/05/tesla-model-s-door-handles-changed-quietly-slight-important-way/","m_Places":["Us","Most","Well","Jonas","Paris","Hell","Owosso","Mila","Kyle","Tucson, Arizona","Arizona","Hal","Teslas","Ota","Finland","South Africa","Eastern Ontario","Minnesota"],"m_People":["Bob Wallace","X. Elon","Zachary Shahan","Carl Raymond","Adam Jonas","Eric Lukac-kuruc","Benjamin Nead","Mercedes-benz B-class","Jenny Sommer","Pawan Sharma","Rodney Dangerfield","Philip W","Chevy Volt","George W","Elon Musk","Ronald Brakels","Perttu Lehtinen","Charles Quintin","D. Harrower"],"m_Companies":["Tesla","Bulls","Real","Seat","Ramping","Signal","Target","Nyt","Guess","Apple","Flamingo","I3","Lot Of Tesla","Magna","Technica","Twitter","Panasonic","Ball","Delta","Indeed","Hinge","Volvo","Mazda","Lamborghini","Huracán"],"m_BiGrams":["door handle","benjamin nead","zachary shahan","electric car","clean technology","share price","jenny sommer","tesla storey","popular storey","car door","unnecessary complexity","tesla coverage","longterm review","door lock","general market","storey published","new storey","service centre","model launch","folk tesla","change world","tesla new","lot people","found interesting","make sense","kyle field","storey day","clean technica","tesla article","ronald brakel","electric window","tesla handle","manual window","door button","opening window","similar amount"],"m_TriGrams":["car door handle"],"m_SocialTags":[],"m_Topics":[],"m_Industry":[],"m_Technology":[],"m_BiCnt":[27,17,12,10,6,5,5,5,5,5,4,4,4,4,3,3,3,3,3,3,3,3,3,3,3,3,3,3,3,3,3,3,3,3,3,3],"m_TriCnt":[4],"m_iDocBodyWordCnt":4161}
