{"m_szDocID":"237749","m_szDocTitle":"100% Electric Vehicle & Plug-in Hybrid Electric Vehicle Sales Have Record Month! | CleanTechnica","m_szYear":"2013","m_szDocSumamry":"100% Electric Vehicle & Plug-in Hybrid Electric Vehicle Sales Have Record Month! Originally published on EV Obsession . As you can see in the table above, 100% electric cars, plug-in hybrid electric cars (PHEVs), and conventional hybrid electric cars continue to do better and better. 100% electrics were up 457.48% in August 2013 compared to August 2012. And they were up 515.51% January through August 2013 compared toÂ January through August 2012. PHEVs are also up considerably, as are conventional hybrids . The increases for each of the above (compared to 2012) are quite similar to the increase","m_szDocBody":"electric vehicle plugin hybrid electric vehicle sale record month originally published obsession table above electric car plugin hybrid electric car phevs conventional hybrid electric car continue better electric compared compared tojanuary phevs considerably conventional hybrid increase compared similar increase julyaugust month electric sale phev sale month ive conventional hybrid vehicle sale havent tracking long country month category big mover shaker changed leader hybrid sale tesla model continue exceptionally well nissan leaf chevy volt continue well broke monthly sale record volt leaf cumulative sale neck neck mistaken month row swapped place otherwise ford continue sale ford cmax hybrid ford fusion hybrid toyota prius offering hybrid plugin car leaf sale volt sale model sale toyota prius phev sale ford fusion energi phev sale cmax energi phev salesdid okay otherwise plugin car inching compliance car call them stand month thought sale compare sale cheque electric car hybrid sale summary cleantechnicas completely free electric car report electric car early adopter follower want youd attend electric vehicle solar power event conducted cleantechnica date hottest cleantech new subscribing free cleantech newsletter eye sectorspecific new also free solar energy newsletter electric vehicle newsletter wind energy newsletter tag acura acura ilx hybrid chevy spark chevy spark chevy spark sale chevy volt fiat fiat ford ford cmax energi ford cmax energi phev ford cmax energi plugin hybrid ford cmax hybrid ford electric vehicle ford escape hybrid ford focus electric ford fusion ford fusion energi ford fusion energi phev ford fusion energi plugin hybrid ford fusion hybrid ford hybrid electric vehicle ford plugin hybrid electric vehicle honda honda accord honda accord phev honda civic honda civic hybrid honda crz honda fcx clarity honda fit honda insight lincoln lincoln mkz hybrid mitsubishi mitsubishi nissan nissan leaf porsche porsche cayenne porsche cayenne hybrid porsche electric suv porsche panamera hybrid tesla tesla model toyota prius toyota prius toyota prius liftback toyota prius phev toyota prius toyota rav volkswagen volkswagen jetta hybrid jetta jetta hybrid zachary shahan tryin and specy letter time spend time cleantechnica director chief editor otherwise enthusiastically fulfilling duty obsession gas solar love planetsave bikocity president important media zach recognised globally solar energy electric car energy storage wind energy expert speak related conference event connect social media zacharyshahancom related post ","m_szGeo1":"United States","m_szSourceType":"source_industry","m_szSrcUrl":"http://cleantechnica.com/2013/09/07/100-electric-vehicle-plug-in-hybrid-electric-vehicle-sales-have-record-month/","m_Places":["Us","Toyota","Tesla"],"m_People":["Chevy Volt","Ford , Ford C-max Energi","Zachary Shahan"],"m_Companies":["Indeed","Shakers","Volt","Honda","Honda Cr-z"],"m_BiGrams":["electric vehicle","electric car","ford fusion","toyota prius","hybrid ford","plugin hybrid","hybrid electric","ford cmax","fusion energi","energi phev","cmax energi","conventional hybrid","phev sale","chevy spark","prius toyota"],"m_TriGrams":["plugin hybrid electric","ford fusion energi"],"m_SocialTags":[],"m_Topics":[],"m_Industry":[],"m_Technology":[],"m_BiCnt":[7,7,7,7,6,5,5,4,4,4,4,3,3,3,3],"m_TriCnt":[3,3],"m_iDocBodyWordCnt":369}
