{"m_szDocID":"237914","m_szDocTitle":"BP Will Never Abandon Fossil Fuels, Jonathon Porritt Acknowledges  | CleanTechnica","m_szYear":"2015","m_szDocSumamry":"BP Will Never Abandon Fossil Fuels, Jonathon Porritt Acknowledges January 18th, 2015 by James Ayre   One of the most senior figures in the UK’s environmental movement of recent decades, Jonathon Porritt, recently made the statement that it is now impossible for the large fossil fuel companies of today to adapt in “a timely and intelligent way to the imperative of radical decarbonization.” The statement, importantly, was accompanied by the announcement that his Forum for the Future institute was cutting its decades-long ties with BP and Shell — making the recent statements something more than j","m_szDocBody":"abandon fossil fuel jonathon porritt acknowledge jame ayre senior figure uks environmental movement recent decade jonathon porritt recently made statement impossible large fossil fuel company today adapt timely intelligent imperative radical decarbonization statement importantly accompanied announcement forum future institute cutting decadeslong ty shell making recent statement word potentially strong follow interview guardian jonathon poritt put pretty bluntly company senior manager know irrefutable fact current businessmodel threaten stability global economy longerterm prospect humankind whole true enormous issue facing human civilization fossil fuel climate change one business usual death sentence current social cultural order justreleased study published science international consortium numerous scientist field warned human activity pushed life planet dependent past point stability pointofnoreturn unpredictable consequence guaranteed occur nearfuture planetary boundary referenced researcher are change biosphere integrity biodiversity loss specy extinction endangered primate etc stratospheric ozone depletion biogeochemical flow phosphorus nitrogen cycle landsystem change deforestation desertification atmospheric aerosol loading microscopic particle atmosphere affect climate living organism introduction entity organic pollutant radioactive material nanomaterial microplastic porritt move divestment fossil fuel isnt earthshattering occurrence call positive one notable organisation individual havent yet but porritt noted time believing engagement passed painful journey personally badly wanted combination reason rigorous science good people enable elegant transition strategy emerge company learn company surely will future note worth mentioning global divestment day rapidly approaching lead image credit oil sand cleantechnicas completely free electric car report electric car early adopter follower want youd attend electric vehicle solar power event conducted cleantechnica date hottest cleantech new subscribing free cleantech newsletter eye sectorspecific new also free solar energy newsletter electric vehicle newsletter wind energy newsletter tag carbon emission climate change divestment fossil fuel divestment jonathon porritt planetary boundary shell oil jame ayre background predominantly geopolitic history obsessive interest pretty everything early life spent imperial free city dortmund jame river ruhr cofbuokheim attended university astnide briefly considered entering coal mining business write living broad variety subject ranging science politic military history renewable energy follow work google related post electric car dont pay gas taxe what pieter sieger fossil fuel company leave fossil fuel ground bad guy power business usual consumer power change lifestyle clean energy source happening slowly fossil fuel industry slowly crumble ups down price changing demand production choice change product disappear end shrink tiny entity beside filthy company succeed maintaining business usual planet make company wont future hope wont happen people realise job green one fossil fuel industry experience lack employee great difficulty maintaining business usual convinced clean energy source give brighter future thinking exceptional power have lower carbon footprint family single day kyle field climate change crisis summarised single sentence company senior manager know irrefutable fact current businessmodel threaten stability global economy longerterm prospect humankind whole michael differently voter change thing australia democracy continually vote climate change denier coal supporter cos wont change people majority havent kyle field boil number sayingdollar sense impact bottom line via carbon tax legislation etc change thing depressing accuratelet michael agree law make happen guy arent nicely suv sale feel forever some law some place people ghg priority list late michael nice blame put role shell exxon exec thinking scientist world sayng unsustainable anything exception world passing law spending money stop global warming preserve amazon switch renewable tax carbon etc etc transport biofuel cut ghg emission trick time entire country australia poland arguing burning coal biggest culprit supposed face massive indifference voting public close shell exxon divvy market share good ghg capita basis worst emitter democracy problem cos govt elect met enemy jburt robmf fossil fuel company putting extract burn business model thing essentially declared war human civilization life earth thinking conscientious compassionate being simply continue put risk wealth life future worth living blindness worst great atrocity history humankind fact simply excuse bearable pain exercise increasing brutality simply proof another better continued burning highhazard fuel jameswimberley future coal straightforward demand fall price drop production cost mine another coal company simply bust oil interesting demand holding simply electric vehicle revolution advanced renewable electricity one total ice vehicle sale rising however evs backed good half major manufacturer deep pocket engineering resource electric utility influential alliance worldwide rollout mobile phone revolution led big company even africa early decade wind solar aspect distinguishes oil coal cost marginal production boomandbust cycle trend decline boom profitable oil party end gas exit path sustainability transmission network valuable gas exceptionally convenient fuel peak electricity generation gas gradually switch sustainable source biomass catalysed hydrogen surplus electricity variable renewable robmf future fossil fuel renewable system viable hit greater greater economy scale essentially price war traditional fuel renewable benefit fuel source free deplete capture grow efficient marginal depleting resource put situation longer economically feasible produce call carbon fuel death spiral mike exxon spending billion year transition wind solar exxon stock holder company devalued believable plan let pes company xom ","m_szGeo1":"United States","m_szSourceType":"source_industry","m_szSrcUrl":"http://cleantechnica.com/2015/01/18/bp-will-never-abandon-fossil-fuels-jonathon-porritt-acknowledges/","m_Places":["Uk","Us","Free City","Dortmund","Australia","Africa"],"m_People":["Jonathon Porritt","James Ayre","Jonathon Poritt","Divestment Day","Pieter Siegers","Michael G"],"m_Companies":["Bp","Future Institute","Guardian","Boundaries","Flickr","University Of Astnide","Google","Ups","Exxon","Amazon","Revolution","Alliance","Path"],"m_BiGrams":["fossil fuel","climate change","business usual","jonathon porritt","fuel company","electric car","electric vehicle"],"m_TriGrams":["fossil fuel company"],"m_SocialTags":[],"m_Topics":[],"m_Industry":[],"m_Technology":[],"m_BiCnt":[11,4,4,3,3,3,3],"m_TriCnt":[3],"m_iDocBodyWordCnt":793}
