{"m_szDocID":"238220","m_szDocTitle":"VW Plug-in Hybrid Mid-Size SUV Seen At Detroit Auto Show | CleanTechnica","m_szYear":"2015","m_szDocSumamry":"VW Plug-in Hybrid Mid-Size SUV Seen At Detroit Auto Show January 22nd, 2015 by Jake Richardson Â  The 2015 Detroit Auto Show was the site of a preview for a new VW plug-in hybrid mid-size SUV. Called the Volkswagen Cross Coupe GTE Concept, it is a blend of the CrossBlue and CrossBlue Coupe concepts. If all this talk about concept cars means nothing to you, the Cross Coupe is going to be a five-passenger SUV. Production of this vehicle will begin at the Chattanooga, Tennessee, factory in 2016. The Cross Coupe is actually not a two-door vehicle. It only resembles a couple in its body shape. It is","m_szDocBody":"plugin hybrid midsize suv detroit auto show jake richardson detroit auto show preview plugin hybrid midsize suv called volkswagen cross coupe gte concept blend crossblue crossblue coupe concept talk concept car mean you cross coupe fivepassenger suv production vehicle begin chattanooga tennessee factory cross coupe twodoor vehicle resemble couple body shape lowerprofile midsize suv mean bear resemblance coupe design bulky boxy suv design example land rover taller sharper angle corner cross coupe lower rounded corner windshield swept gentle slope roof line taper back vehicle curve emphasised large wheel well effect modern slightly futuristic vehicle fact modern styling aligned vehicle technology current gas engine combined electric motor kilowatthour lithiumion battery pack gas engine electric motor power front wheel motor rear wheel yes suv allwheel drive powerful time second top speed mile hour electriconly range expected mile driving trip short distance range sufficient order reduce gasoline consumption mitsubishi plugin hybrid suv reportedly mile range driving electricity volvo expected produce plugin hybrid suv north american market too bmw image credit cleantechnicas completely free electric car report electric car early adopter follower want youd attend electric vehicle solar power event conducted cleantechnica date hottest cleantech new subscribing free cleantech newsletter eye sectorspecific new also free solar energy newsletter electric vehicle newsletter wind energy newsletter tag plugin hybrid suv tennessee jake richardson hello writing online time enjoy outdoor like follow related post nissan bmw greenlot roll fastcharging station offgridman sound nice byd offering disappointing chinese longer range priced evs can heard storey china canada set trade agreement include electric vehicle canada sneak back border year wait manufacturer bobwallace china buy byd drive while import car youll make pass safety standard wouldt put family didnt offgridman possibility trip stay shipping fee pretty negate financial advantage confirm true not byd advertising china claim safety standard good foreign import quality model daimler emission pollution requirement problem passing them kind daydreaming bob model meet requirement work travel vehicle commuter vehicle wife electric mean mile highway speed morning recharge day make back night day week crazy commute make long day paid ridiculous amount preferred working day week make money bobwallace mile highway speed back single charge leaf stay home post office offgridman rare blessing god afford model cargo towing wheel drive care here thankfully space kid dog luggage long trip time year electric long range too bolt possibly longer range leaf golf eagerly anticipated type requirement unusual circumstance wanting live twentyfive year mandatory life work limit though time left raise boy sunshine fresh air staying mountain bobwallace devil advocate wife make long commute safety luxury limited range local driving dont beat nice car ordinary trip grocery pickup hauling towing place ive year toyota driven mile year longer extended cab pile crew day week fit leaf make family trip day long family trip wife wont working anyway djr look visibility low roof though electric kinda lame smaller cyl engine battery sacrificing acceleration greener driving experience mike ugly ronald brakel mile electric range kilometre bad australia car driven average kilometre day people basically town driving electricity also hour completely charge battery pack ordinary power point hour long commute electricity charge work kilometre hour fairly typical average town driving speed here sure lot people longer electric range bad epicurus volt electric range mile model plug hybrid competitor half that kudos jenny sommer plugin sharan touran electric range volvo seater electric rangep mile electric stupid time fase hybrid line car electric rest gas car jeffhre electriconly range expected mile driving trip short distance range sufficient order reduce gasoline consumption stupid lol mile range day mile year pretty sizable chunk real estate actually mile range cut gas gas version marion mead short trip mile again prius mile range better estimated price contraption ","m_szGeo1":"United States","m_szSourceType":"source_industry","m_szSrcUrl":"http://cleantechnica.com/2015/01/22/vw-plug-hybrid-mid-size-suv-seen-detroit-auto-show/","m_Places":["Detroit","Chattanooga, Tennessee","Us","Tennessee","China","Canada","Toyota","Australia","Most"],"m_People":["Jake Richardson","Ronald Brakels","Jenny Sommer","Marion Meads"],"m_Companies":["Volkswagen","Land Rover","Volvo","Bmw","Google","Volt","Volvo Xc90"],"m_BiGrams":["plugin hybrid","cross coupe","mile range","electric range","midsize suv","hybrid suv","electric vehicle"],"m_TriGrams":["plugin hybrid suv"],"m_SocialTags":[],"m_Topics":[],"m_Industry":[],"m_Technology":[],"m_BiCnt":[5,4,4,4,3,3,3],"m_TriCnt":[3],"m_iDocBodyWordCnt":617}
