{"m_szDocID":"238313","m_szDocTitle":"447.95% -- Increase In 100% Electric Car Sales In US In 2013 | CleanTechnica","m_szYear":"2013","m_szDocSumamry":"Originally published on EV Obsession . August and September 2013 were funky months in the US auto industry. Basically, the reason for this is the auto industry’s funky calendar. The “last day” of the previous month on the auto industry’s calendar is actually the first weekday of the next calendar month. Because that “last day of the month of August” happened to be Labor Day this year (September 2), all those Labor Day auto sales were logged in August rather than September. (Yep, that’s a notable reason for why electric and hybrid car sales were up so much in August — sorry we missed that last ","m_szDocBody":"originally published obsession funky month auto industry basically reason auto industry funky calendar day previous month auto industry calendar weekday calendar month day month happened labour day year september labour day auto sale logged september yep notable reason electric hybrid car sale missed month confused read paragraph again confused proceed paragraph big labour day hit auto sale board compared including electric hybrid auto sale table bottom post hit hard honda hit hard toyota hit hard electric hybrid model brand hit hard notably however nissan leaf tesla model continued shine compared ford electric hybrid lineup continued perform thank highselling car introduced end bigger picture yeartodate sale interesting varied end compared end ford electric hybrid sale sale nissan electric nissan leaf sale up% sale toyotas electric hybrid sale up% sale competition teslas sale upto huge degree sale gms electric hybrid sale sale hondas electric hybrid sale aredown% sale porsches hybrid sale aredown% sale whole electric car sale huge degree plugin hybrid electric car sale fair degree conventional hybrid electric car sale bit combined hybrid electric car sale beginning end car sold considerably sold beginning end trend greenhere full table see tag acura acura ilx hybrid chevy spark chevy spark chevy spark sale chevy volt fiat fiat ford ford cmax energi ford cmax energi phev ford cmax energi plugin hybrid ford cmax hybrid ford electric vehicle ford escape hybrid ford focus electric ford fusion ford fusion energi ford fusion energi phev ford fusion energi plugin hybrid ford fusion hybrid ford hybrid electric vehicle ford plugin hybrid electric vehicle honda honda accord honda accord phev honda civic honda civic hybrid honda crz honda fcx clarity honda fit honda insight lincoln lincoln mkz hybrid mitsubishi mitsubishi nissan nissan leaf porsche porsche cayenne porsche cayenne hybrid porsche electric suv porsche panamera hybrid tesla tesla model toyota prius toyota prius toyota prius liftback toyota prius phev toyota prius toyota rav volkswagen volkswagen jetta hybrid jetta jetta hybrid zachary shahan tryin and specy letter time spend time cleantechnica director chief editor otherwise enthusiastically fulfilling duty obsession gas solar love planetsave bikocity president important media zach recognised globally solar energy electric car energy storage wind energy expert speak related conference event connect social media zacharyshahancom related post ","m_szGeo1":"United States","m_szSourceType":"source_industry","m_szSrcUrl":"http://cleantechnica.com/2013/10/04/447-95-increase-100-electric-car-sales-us-2013/","m_Places":["Us","Toyota","Tesla"],"m_People":["Ford , Ford C-max Energi","Chevy Volt","Zachary Shahan"],"m_Companies":["Honda","Honda Cr-z"],"m_BiGrams":["electric hybrid","car sale","hybrid sale","electric car","hybrid electric","hybrid ford","ford fusion","toyota prius","hit hard","plugin hybrid","auto industry","labour day","auto sale","ford electric","chevy spark","cmax energi","ford cmax","electric vehicle","fusion energi","prius toyota"],"m_TriGrams":["electric hybrid sale","electric car sale","hybrid electric car"],"m_SocialTags":[],"m_Topics":[],"m_Industry":[],"m_Technology":[],"m_BiCnt":[8,5,5,5,5,5,5,5,4,4,3,3,3,3,3,3,3,3,3,3],"m_TriCnt":[4,4,3],"m_iDocBodyWordCnt":368}
