{"m_szDocID":"238379","m_szDocTitle":"More Tesla Model X Pictures (14) & Videos (5) | CleanTechnica","m_szYear":"2015","m_szDocSumamry":"More Tesla Model X Pictures (14) & Videos (5) Originally published on EV Obsession . Tesla Model X  spy shots keep rolling in, and the past few days have seen some really interesting ones, including some colorful ones! Previously, we had just seen black and white mules, but this week has brought us blue, red, and titanium silver ones! Okay, I’ll just get on with it. Here are the pics and videos: There’s still plenty of debate regarding how much these Model X mules have in common with the final production Model X, and we’re yet to get a good glimpse of the interior, especially the back seats. W","m_szDocBody":"tesla model picture videos originally published obsession tesla model spy shot rolling past day interesting one including colourful one previously black white mule week brought blue red titanium silver one okay ill pic videos plenty debate model mule common final production model good glimpse interior back seat colourful model mule thinking production begun customer word street result tesla testing paint shop model test vehicle case close production launch model spy shot post publish see way image retrieved tesla motor club forum red instagram related cleantechnicas completely free electric car report electric car early adopter follower want youd attend electric vehicle solar power event conducted cleantechnica date hottest cleantech new subscribing free cleantech newsletter eye sectorspecific new also free solar energy newsletter electric vehicle newsletter wind energy newsletter tag tesla tesla model tesla model spy shot tesla model videos zachary shahan tryin and specy letter time spend time cleantechnica director chief editor otherwise enthusiastically fulfilling duty obsession gas solar love planetsave bikocity president important media zach recognised globally solar energy electric car energy storage wind energy expert speak related conference event connect social media zacharyshahancom related post mandate carbon taxe teslas quarterly conference call cleantech talk paolo moleman friend trevor guy work tesla supposed coming soon car pretty good falcon wing door needed illioilli pic show spoiler back guess retractable hadnt noticed before bvadel fugly and styling model suv crossover best zachary shahan people close big person pic great bestlooking subjective matter course michael berndtson guessing market wealthy family four dad drive model silicon valley management job cardiology practise mom drive kid playdate such fine line crossover straddling utility sexyness mom kid mobil safe make feel young hand dad sell model buy wife wife ceo company drive work pick kid gifted talented pre kindergarten marketing pain engineer insight angelafoste found lnk set profile explan leavng ther occupation hundred week beng made people valakos love black mule fab matt remind award winning pontiac aztec shane aztek beautiful car produced arnenl vote fiat multipla dag johansen cool hope skunkwork operation working version falconwing door though reduce cost simplify car rid weird door worried about etc hope lot rich people buy expensive version funky cool door valakos hmmm interesting offer version falconwing door preempt reviewer dont option wont open garage personally falcon wing door good idea offer option complain zachary shahan dont lot extra work teslas part reward gullwing door big attraction vehicle and least con valakos love falcon wing door great selling point people small children baby make easy access offering configuration devalue imo reviewer bitch imo should received majority zachary shahan yeah reviewer bitch guaranteed tax live lot carrying roof skis cargo shell bike etc falcon wing door that shane door gap annoy rich buyer arnenl fixed final production version frank dont worried price door dont standard door model worried cost giga factory supposed drop price ship bigger battery ","m_szGeo1":"United States","m_szSourceType":"source_industry","m_szSrcUrl":"http://cleantechnica.com/2015/08/23/more-tesla-model-x-pictures-14-videos-5/","m_Places":["Tesla","Trevor","Best","Silicon Valley"],"m_People":["Zachary Shahan","Paolo Moleman","Michael Berndtson","Dag Johansen","Rich Buyers"],"m_Companies":["Cleantech","Guess"],"m_BiGrams":["tesla model","zachary shahan","falcon wing","wing door","model spy","spy shot","electric car"],"m_TriGrams":["falcon wing door"],"m_SocialTags":[],"m_Topics":[],"m_Industry":[],"m_Technology":[],"m_BiCnt":[4,4,4,4,3,3,3],"m_TriCnt":[4],"m_iDocBodyWordCnt":477}
