{"m_szDocID":"238559","m_szDocTitle":"Mitsubishi Motors Unveiling 2 New Plug-in Hybrid Electric Concept Cars At Tokyo Motor Show 2013 | CleanTechnica","m_szYear":"2013","m_szDocSumamry":"Mitsubishi Motors Unveiling 2 New Plug-in Hybrid Electric Concept Cars At Tokyo Motor Show 2013 October 16th, 2013 by Zachary Shahan   It seems that the motor show circuit never ends. Motor shows in Frankfurt, New York, LA, Shanghai, Tokyo, and elsewhere fill the year with opportunities to unveil new concept cars. The 43rd Tokyo Motor Show is coming up in late November, and Mitsubishi Motors Corporation (MMC) is using the opportunity to put more toes in the electric vehicle waters . It is supposed to be unveiling two new plug-in hybrid electric concept cars at the show. Three Mitsubishi Concep","m_szDocBody":"mitsubishi motor unveiling plugin hybrid electric concept car tokyo motor show zachary shahan motor show circuit end motor show frankfurt york shanghai tokyo fill year opportunity unveil concept car tokyo motor show coming late november andmitsubishi motor corporation mmc opportunity put toe electric vehicle water supposed unveiling plugin hybrid electric concept car show mitsubishi concept vehicle phevs here concept car which technical arent car suvs green car congress the mitsubishi concept gcphev grand cruiser fullsize suv output phev plugin hybrid electric vehicle system phev equipped mmc sawc super wheel control integrated vehicle dynamic control system handling stability allterrain capability concept gcphev connected car offer nextgeneration preventive safety technology driver support technology wireless connectivity second mitsubishi concept xrphev cross runner compact suv loaded lightweight efficient phev system enhanced environmental performance mitsubishi concept xrphev offer nimble drivability body style resembling sport coupe mitsubishi concept gcphev currently mitsubishi electric vehicle market mitsubishi mitsubishi outlanderplugin hybrid themitsubishi outlander sale japan europe start ran production problem resulted production suspended month restarting august outlander expected hit market officially set yet mitsubishi sale year sale compare nissan leaf chevy volt related storey tag mitsubishi mitsubishi concept gcphev mitsubishi concept xrphev mitsubishi electric crossover mitsubishi gcphev mitsubishi gcphev cruiser mitsubishi gcphev grand cruiser mitsubishi grand cruiser mitsubishi motor mitsubishi xrphev tokyo motor show zachary shahan tryin and specy letter time spend time cleantechnica director chief editor otherwise enthusiastically fulfilling duty obsession gas solar love planetsave bikocity president important media zach recognised globally solar energy electric car energy storage wind energy expert speak related conference event connect social media zacharyshahancom related post ","m_szGeo1":"United States","m_szSourceType":"source_industry","m_szSrcUrl":"http://cleantechnica.com/2013/10/16/mitsubishi-motors-unveiling-2-new-plug-hybrid-electric-concept-cars-yokyo-motor-show-2013/","m_Places":["Tokyo","Frankfurt, New York","Shanghai, Tokyo","Japan","Europe","Us"],"m_People":["Zachary Shahan","Phev Grand","Chevy Volt"],"m_Companies":["Mitsubishi Motors","Mitsubishi Motors Corporation","Mmc","Congress","Awc"],"m_BiGrams":["mitsubishi concept","motor show","concept car","concept gcphev","plugin hybrid","hybrid electric","tokyo motor","electric vehicle","grand cruiser","concept xrphev","mitsubishi gcphev","cruiser mitsubishi"],"m_TriGrams":["plugin hybrid electric","tokyo motor show","mitsubishi concept xrphev"],"m_SocialTags":[],"m_Topics":[],"m_Industry":[],"m_Technology":[],"m_BiCnt":[6,5,4,4,3,3,3,3,3,3,3,3],"m_TriCnt":[3,3,3],"m_iDocBodyWordCnt":263}
