{"m_szDocID":"239038","m_szDocTitle":"Honey, I Shrunk the CFLs: Crazy-Small New Bulb from SYLVANIA | CleanTechnica","m_szYear":"2008","m_szDocSumamry":"Honey, I Shrunk the CFLs: Crazy-Small New Bulb from SYLVANIA May 23rd, 2008 by Timothy B. Hurst   The micro mini Twist CFL: Big light, small package. When it comes to the advent of the compact fluorescent light bulb (CFL), I am proud to say that I was an early adopter. And while I instantly noticed a reduction in my monthly electric bill, I also noticed that the compact fluorescent was not without its flaws. I found that the early compact fluorescents were often too bulky, preventing their use in certain fixtures; that they took a while to ‘warm up’ to full their full brightness; and that the ","m_szDocBody":"honey shrunk cfl crazysmall bulb sylvania timothy hurst micro mini twist cfl big light small package advent compact fluorescent light bulb cfl proud early adopter instantly noticed reduction monthly electric bill noticed compact fluorescent flaw found early compact fluorescent bulky preventing fixture warm full full brightness light put harsh compared warm glow edisonera incandescent light bulb time changed micromini twist sylvania evidence cfl dont big slow bright effective see also european union ban incandescent light bulb microminis size biggest appeal jumped away featuring ultrasmall inch tube diameter compact integral electronic ballast micromini smallest cfl today market bulb measure inches long half inch shorter standard incandescent lamp mere inches picture twist significantly smaller cfl homelighting arsenal bulb compact size make usable virtually lamp fixture large small bade cfl soft white micromini compact fluorescent light bulb feature warm colour temperature kelvin boast instanton capability micromini twist compact fluorescent lamp watt model mini cfl designed replace incandescent lamp boast average rated lamp life hour finally enjoyed instanton capability twist bathroom flip light cfl wont reach full luminescence time business thus cutting valuable crossword puzzle magazine time bulb however delay instantly bright flipped switch downside found bulb packaged bulb claiming energy saver printing picture tree useless cardboard tab show consumer real concern saving energy hope sylvania recognise inconsistency adjust packaging accordingly changing incandescent bulb cfl save average american dollar life bulb changing thirtysix bulb the number average american home amount saving life bulb investment small price pay substantial energy saving based year related post image tim hurst cleantechnicas completely free electric car report electric car early adopter follower want youd attend electric vehicle solar power event conducted cleantechnica date hottest cleantech new subscribing free cleantech newsletter eye sectorspecific new also free solar energy newsletter electric vehicle newsletter wind energy newsletter tag cfl compact fluorescent lightbulb timothy hurst founder ecopolitology executive editor liveoak media media network politic energy environment green business cleantech green living reading writing thinking talking environmental politic listen tim spend time skiing colorados country hiking dog dirty vegetable garden related post mercury greeny stop breathing tom currie full brightness rarely light output match claimed equivalent incandescent forget candelabra base socket ceiling fan put larger micro mini bulb ceiling fan single large globe guess depend design globe hard wont work fan bernice sylvania micro mini cfl great idea standardsized compact flurescent tall wall sconce dim watt equivalent produce light regular watt equivalent cfl replaced return sylvanias cheaper lowerwatt larger cfl bernice sylvania micro mini cfl great idea standardsized compact flurescent tall wall sconce dim watt equivalent produce light regular watt equivalent cfl replaced return sylvanias cheaper lowerwatt larger cfl willmore harding peak brightness turned difference full brightness human eye trouble telling difference amount brightness change periodunless sort reference say bulb warm bulb turn difference factor hard eye vastly folded type minute started full brightness and mercury discussion mercury bulb metalic mercury low bioavailability worried toxicity mercury worry organic mercury compound agrabusiness world benefit bulb due size allowing application cfl fit bought set light fixture bathroom regular cfl fit sticking assembly minitwist type fit there forward end low efficiency lighting fixture cost reduced longer withstand temp incandescent bulb willmore harding peak brightness turned difference full brightness human eye trouble telling difference amount brightness change periodunless sort reference say bulb warm bulb turn difference factor hard eye vastly folded type minute started full brightness and mercury discussion mercury bulb metalic mercury low bioavailability worried toxicity mercury worry organic mercury compound agrabusiness world benefit bulb due size allowing application cfl fit bought set light fixture bathroom regular cfl fit sticking assembly minitwist type fit there forward end low efficiency lighting fixture cost reduced longer withstand temp incandescent bulb robert harding sylvania cfl instanton give break measured relative brightness versus time every second minute initial turnon sylvania simple light brightness metre test performed degree lamp mounted upright table lamp fixture dark room light sensor located feet lamp result maximum brightness achieved second initial start maximum brightness brighter initial start brightness very noticeable nakedeye dont bright warmed also bulb tested stabilised brightness minute dropped maximum brightness achieved second instanton equal instant bright performance lifetest data blub robert harding sylvania cfl instanton give break measured relative brightness versus time every second minute initial turnon sylvania simple light brightness metre test performed degree lamp mounted upright table lamp fixture dark room light sensor located feet lamp result maximum brightness achieved second initial start maximum brightness brighter initial start brightness very noticeable nakedeye dont bright warmed also bulb tested stabilised brightness minute dropped maximum brightness achieved second instanton equal instant bright performance lifetest data blub mercury filling dentist office typical cfl problem cfl mercury people dont recycle mercury nasty pile landfill water etc large number case problem mercury filling dentist office typical cfl problem cfl mercury people dont recycle mercury nasty pile landfill water etc large number case problem didnt mercury filling odd ada alarm mercury filling mercury poison hmmm bobwallace stuff advise visit web site highly regarded regarded health institution cheque say example mayo clinic metal dental filling dental amalgam stable alloy made mercury silver tin copper possibly metal concern raised year safety mercury dental amalgam researcher proved concern unfounded american dental support dental amalgam safe reliable effective treatment dental decay people stop believing led wave future efficiency led isnt yet real fact led chip melt faily low temperature start led chip watt heat sink difficult achieve screw bulb normally make dedicated fixture led chip power supply heat sink talking lpw best cfl good now sylania talking nanotechnology incandescent bulb plan lpw bulb market lpw bulb surely render led small neich market people stop believing led wave future efficiency led isnt yet real fact led chip melt faily low temperature start led chip watt heat sink difficult achieve screw bulb normally make dedicated fixture led chip power supply heat sink talking lpw best cfl good now sylania talking nanotechnology incandescent bulb plan lpw bulb market lpw bulb surely render led small neich market mark home depot announced accepting cfl recycling purchase necessary starting tuesday chain store accepting them mercury pointed above incandescent put time mercury air cfl could cfl thrown out proper recycling mercury pollution cfl plummet ian best mark home depot announced accepting cfl recycling purchase necessary starting tuesday chain store accepting them mercury pointed above incandescent put time mercury air cfl could cfl thrown out proper recycling mercury pollution cfl plummet ian best uncle micro mini twist cfl delight price extended life too folk concerned contamination led light realistically priced lifeexpectancy wont shatter easily battery car benzine molecule free world put pink ribbon that america future embrace enthusiastically uncle micro mini twist cfl delight price extended life too folk concerned contamination led light realistically priced lifeexpectancy wont shatter easily battery car benzine molecule free world put pink ribbon that america future embrace enthusiastically carter replaced incandescent cfl bought sam club reason decided buy cost approximately set total bulb sylvania bulb notice made replaced month plan save them enviro freak care think saving earth bulb people care saving money cost efficient people spend hard earned money good save earth green mantra constantly chanted plus wake people time frame money saving limited oil gas electric company essence public utility lose due green movement youll adjust consumer price make continue earn money hybrid car gas price happen electric bill too price inflate people taxed save world youll million million cfl bulb ending landfill make new day part cfl backfire think important moderately conservative balanced approach energy consumption good steward money resource pure energy harmful byproduct realism good perspective pessimism carter replaced incandescent cfl bought sam club reason decided buy cost approximately set total bulb sylvania bulb notice made replaced month plan save them enviro freak care think saving earth bulb people care saving money cost efficient people spend hard earned money good save earth green mantra constantly chanted plus wake people time frame money saving limited oil gas electric company essence public utility lose due green movement youll adjust consumer price make continue earn money hybrid car gas price happen electric bill too price inflate people taxed save world youll million million cfl bulb ending landfill make new day part cfl backfire think important moderately conservative balanced approach energy consumption good steward money resource pure energy harmful byproduct realism good perspective pessimism carol frilegh joe schmoe cfl dont long advertised switched bunch bulb house half died month year life yeah right reliable conventional bulb joe schmoe cfl dont long advertised switched bunch bulb house half died month year life yeah right reliable conventional bulb michael surprised led bulb led bulb designed compact instant michael surprised led bulb led bulb designed compact instant maurice make minicfl chandelier base maurice make minicfl chandelier base jay life bulb significantly reduced cycling off cuff research based fact manufacturer release turn cfl minute youll pay bulb replacement cost save energy cost doesnt include cost disposal energy cost manufacture bulb jay life bulb significantly reduced cycling off cuff research based fact manufacturer release turn cfl minute youll pay bulb replacement cost save energy cost doesnt include cost disposal energy cost manufacture bulb rod adam dozen year ago opportunity visit edison home fort myer florida time today number incandescent light bulb burning installed home edison himself remember exact lifetime achieved thomas edison died bulb low wattage bulb worked decade use point short lifetime commercially incandescent bulb limitation basic technology result decision made manufacturing process development include item perfect make bulb frequently company hope people replace them evado eloquently cheap cheap btw electricity supplying incandescent bulb nuclear reactor risk mercury released environment rod adam dozen year ago opportunity visit edison home fort myer florida time today number incandescent light bulb burning installed home edison himself remember exact lifetime achieved thomas edison died bulb low wattage bulb worked decade use point short lifetime commercially incandescent bulb limitation basic technology result decision made manufacturing process development include item perfect make bulb frequently company hope people replace them evado eloquently cheap cheap btw electricity supplying incandescent bulb nuclear reactor risk mercury released environment picard wow bunch snotty green whiner youre convinced puny amount mercury cfl worse amount atmospheric mercury saved use free light lowimpact home organic flax oil lamp sit dark complain kindly stfu hysterical fearmongering good you kind regulated holierthanthough environmental movement year ghetto hippy dippy cultural irrelevancy achieve energy independence oil run out ktnxbye picard wow bunch snotty green whiner youre convinced puny amount mercury cfl worse amount atmospheric mercury saved use free light lowimpact home organic flax oil lamp sit dark complain kindly stfu hysterical fearmongering good you kind regulated holierthanthough environmental movement year ghetto hippy dippy cultural irrelevancy achieve energy independence oil run out ktnxbye neednewbedcom watt equivalent bit efficient usual watt smaller lose percent efficiency willfe god hotlycontested poorlyresearched rant year ago blowing epa guideline discussing clean broken tube long ceiling fixture store proportion suddenly pile idiot screaming terror shadow looming mercury demon lurking light fixture people grasp how many cfl broken obtain mercury airborne damage human body understand single watch battery time mercury cfl monkey realise cfl dont end live piece contamination emergency home cfl break broom dustpan sweep dispose friggin mercury thermostat six hundred cfl stop absolutely stupid irrational argument willfe god hotlycontested poorlyresearched rant year ago blowing epa guideline discussing clean broken tube long ceiling fixture store proportion suddenly pile idiot screaming terror shadow looming mercury demon lurking light fixture people grasp how many cfl broken obtain mercury airborne damage human body understand single watch battery time mercury cfl monkey realise cfl dont end live piece contamination emergency home cfl break broom dustpan sweep dispose friggin mercury thermostat six hundred cfl stop absolutely stupid irrational argument kevin bulb year longer incandescent year average people throw trash quit working people crushed landfill spill mercury total energy burden light bulb include energy required produce material recycle dispose waste used doubt better quit basing calculation case lifetimei quit year kevin bulb year longer incandescent year average people throw trash quit working people crushed landfill spill mercury total energy burden light bulb include energy required produce material recycle dispose waste used doubt better quit basing calculation case lifetimei quit year bob bunch research cfl insurance underwriter received potential productliabilty account cfl manufacturer reading tonne tonne data conclusion average cfl mercury emitted coal plant totally safe broken recycle local hazardous waste drop off put garbage broken advised remove children pet put large piece plastic bag tape pick smaller invisible piece put plastic bag hazardous waste facility circumstance vacuum broken blast microscopic mercury house said perfect solution led are step direction biggest concern cfl breaking home warehouse damaged mishandling mercury exposure why didnt write account also evado said quality bulb make big difference review read big difference varying bulb research suggested buying bunch them although post commercial honest comment jim incandescent nuclear power mercury incandescent wind power mercury incandescent solar power mercury incandescent geothermal power mercury ccfl mercury bob bunch research cfl insurance underwriter received potential productliabilty account cfl manufacturer reading tonne tonne data conclusion average cfl mercury emitted coal plant totally safe broken recycle local hazardous waste drop off put garbage broken advised remove children pet put large piece plastic bag tape pick smaller invisible piece put plastic bag hazardous waste facility circumstance vacuum broken blast microscopic mercury house said perfect solution led are step direction biggest concern cfl breaking home warehouse damaged mishandling mercury exposure why didnt write account also evado said quality bulb make big difference review read big difference varying bulb research suggested buying bunch them although post commercial honest comment jim incandescent nuclear power mercury incandescent wind power mercury incandescent solar power mercury incandescent geothermal power mercury ccfl mercury evado good reducing emmission buyer beware apply pay for pack cfl sam club ikea total crap made china train load quality control cheap cheap american made cfl tcp great company cheque video evado good reducing emmission buyer beware apply pay for pack cfl sam club ikea total crap made china train load quality control cheap cheap american made cfl tcp great company cheque video chris quit crying mercury energy usage recycling bulb inefficient incandescent big deal candle wait emit carbon you back mercury making thin air long longer will chris quit crying mercury energy usage recycling bulb inefficient incandescent big deal candle wait emit carbon you back mercury making thin air long longer will charlie haye waste buy cool instant bulb throw longlasting existing cfl bulb year cfl bulb die led bulb cheaper easier find charlie haye waste buy cool instant bulb throw longlasting existing cfl bulb year cfl bulb die led bulb cheaper easier find gulag safe bulb electricity cheque earthled bulb earthled make led light bulb watt produce light output watt bulb bulb replace watt incandescent watt part regular light bulb safe bulb electricity cheque earthled bulb earthled make led light bulb watt produce light output watt bulb bulb replace watt incandescent watt part regular light bulb yeah blend bob yeah blend robert popular mechanic crunched number mercury well approximately mercuryplus carbon dioxide sulphur dioxide nitrogen oxiderelease air kwh electricity coalfired power plant generate hour average range cfl then plant emit mercury sustain watt incandescent bulb mercury sustain watt cfl the lightning equivalent watt traditional bulb mercury contained cfl directly released atmosphere incandescent contribute milligramme mercury environment lifetime robert popular mechanic crunched number mercury well approximately mercuryplus carbon dioxide sulphur dioxide nitrogen oxiderelease air kwh electricity coalfired power plant generate hour average range cfl then plant emit mercury sustain watt incandescent bulb mercury sustain watt cfl the lightning equivalent watt traditional bulb mercury contained cfl directly released atmosphere incandescent contribute milligramme mercury environment lifetime ian mercury plus hundred nasty thing emitted coal burning plant country reducing amount electricity bulb use directly reducing amount mercury emitted atmosphere yes bulb mercury them reduce amount put enviroment ian mercury plus hundred nasty thing emitted coal burning plant country reducing amount electricity bulb use directly reducing amount mercury emitted atmosphere yes bulb mercury them reduce amount put enviroment sceptic great bulb shatter home shard which mercury pierce skin anticoal rally cfl suck sceptic great bulb shatter home shard which mercury pierce skin anticoal rally cfl suck blimey break mercury neurooxin contaminate home cfl supposed trash break supposed toxic waste dump blimey break mercury neurooxin contaminate home cfl supposed trash break supposed toxic waste dump son nguyen nice though also simpler safer dispose bulb son nguyen nice though also simpler safer dispose bulb mickey purchase magical micros dont sylvanias website mickey purchase magical micros dont sylvanias website david facing mercury issue emitted coalfired power plant mercury recovered spent bulb easier environment david facing mercury issue emitted coalfired power plant mercury recovered spent bulb easier environment neednewbedcom watt equivalent bit efficient usual watt smaller lose percent efficiency thad average bulb american home amount mercury add quickly mercury going facing mercury year come thad average bulb american home amount mercury add quickly mercury going facing mercury year come eric smallest cfl smallest smaller candelabra socket adapter mount regular socket ikea still bluish light efficiency good decade far nice lifetime creeping hour optomistic lost cfl service decade bought past year signif failure rate friend lasting rated life led light each paying cfl bought mercury life hope itll electronic eric smallest cfl smallest smaller candelabra socket adapter mount regular socket ikea still bluish light efficiency good decade far nice lifetime creeping hour optomistic lost cfl service decade bought past year signif failure rate friend lasting rated life led light each paying cfl bought mercury life hope itll electronic green sahm probably matter break cleanup simple instruction online saving energy pollution emitted power plant green sahm probably matter break cleanup simple instruction online saving energy pollution emitted power plant allison yeah mercury allison yeah mercury markvturner yes mercury released coal power plant light incandescent light bulb ","m_szGeo1":"United States","m_szSourceType":"source_industry","m_szSrcUrl":"http://cleantechnica.com/2008/05/23/honey-i-shrunk-the-cfls-crazy-small-new-bulb-from-sylvania/","m_Places":["Colorado","Most","Ada","Starting","America","Florida","China"],"m_People":["Sylvania Cfl","Timothy B. Hurst","Tim Hurst","Tom Currie","Robert Harding","Joe Schmoe","Rod Adams","Thomas Edison","Charlie Hayes","Son Nguyen"],"m_Companies":["Twist","Glow","European Union","Guess","Jm","Mayo Clinic","American Dental Association","Home Depot","Ea","Electric Companies","Picard","Epa","Ikea","Popular Mechanics","Suck"],"m_BiGrams":["light bulb","incandescent bulb","power mercury","power plant","micro mini","compact fluorescent","watt equivalent","maximum brightness","led chip","led light","cfl bulb","led bulb","amount mercury","mercury incandescent","bulb mercury","incandescent light","cfl dont","full brightness","life bulb","produce light","cfl fit","light fixture","brightness achieved","achieved second","initial start","mercury filling","cfl mercury","heat sink","lpw bulb","time mercury","cfl bought","sam club","energy cost","mercury cfl","home cfl","bulb year","mercury emitted","emitted coal","hazardous waste","plastic bag","big difference","watt incandescent","coalfired power","mercury sustain","sustain watt","reducing amount","facing mercury","bulb sylvania","mini twist","twist cfl","electric bill","smallest cfl","lamp fixture","mini cfl","saving energy","american home","home amount","solar power","light output","dental amalgam","mercury released"],"m_TriGrams":["power mercury incandescent","incandescent light bulb","maximum brightness achieved","brightness achieved second","coalfired power plant","mercury sustain watt","micro mini twist","mini twist cfl","american home amount"],"m_SocialTags":[],"m_Topics":[],"m_Industry":[],"m_Technology":[],"m_BiCnt":[13,11,8,7,6,6,6,6,6,6,6,6,6,6,6,5,5,5,4,4,4,4,4,4,4,4,4,4,4,4,4,4,4,4,4,4,4,4,4,4,4,4,4,4,4,4,4,3,3,3,3,3,3,3,3,3,3,3,3,3,3],"m_TriCnt":[6,4,4,4,4,4,3,3,3],"m_iDocBodyWordCnt":2962}
