{"m_szDocID":"239092","m_szDocTitle":"US Electric Car Sales Have Increased 361% In 2013 So Far | CleanTechnica","m_szYear":"2013","m_szDocSumamry":"US Electric Car Sales Have Increased 361% In 2013 So Far Originally published on EV Obsession . I would say that the strong growth of 100% electric car and plug-in hybrid electric car US sales is really no longer a story — they’ve been growing strongly month after month without a break. However, the odd thing is that there’s still all kinds of anti-hype. There are a lot of people in the media, especially “Big Media,” who are repeating the whole “electric vehicle sales are disappointing” meme. This is a case of two things, in my opinion. 1) This is largely a case of expectations being too high.","m_szDocBody":"electric car sale increased originally published obsession strong growth electric car plugin hybrid electric car sale longer storey theyve growing strongly month month break however odd kind antihype lot people media big media repeating electric vehicle sale disappointing meme case thing opinion largely case expectation high sure youre expecting growth growth disappointing but genuinely disappointing lot people dont number repeat myth unfortunately common humanity lot people people media talk make talking about repeat theyve heard sound informed place happy report month month fact electric car sale rocking track obama target million electric vehicle tremendous growth nonetheless youre curious arent target hit million vehicle target quickly give that realised thing word awesomeness electric vehicle take longer based evs merit lot people dont clue evs market evs market people predispositioned inaccurately opposed shortterm cost larger degree longterm cost which benefit gasmobile evs people talk big game hating oil oil dependency arent determined move even benefit medium longterm energy cost people accustomed conventional hybrid electric vehicle big step electric vehicle plug wall order fuel luckily word there people own electric car people coming benefit electric car uplifting stat straight stat above notable takehome point imho strong growth evs phevs all indicate awesome electric car growth compared october compared plugin electric car strong growth compared electric car impressive yeartodate growth growth strong ford strong growth ford continue extremely strong growth electric hybrid car sale compared growth date wow also ive previously attributed lot ford sale growth fact didnt ford fusion ford cmax model market late clear ford fusion conventional hybrid selling year year ford fusion ford cmax model increasingly competitive market suffering well suffering sale dropped sale lower yeartodate sale genuinely reason greatly heightened competition market phev market actually due pushing chevy spark hot awesome electric car market review put chevy spark chevy spark gasmobile car selling hotcake market drop sale noted chevy volt ndbestselling plugin car market barely toyota prius phev big price cut carry helpful prius name imagine dealer upselling people conventional prius turning phev buyer nissan leaf strong nissan leaf sale continue grow strongly growth growth year date pure electric pure awesome leaf barely trailing volt yeartodate sale close tesla alway dont exact monthly sale stat tesla theyre based quarterly sale notably teslas sale bit lower youd expect key attribution that tesla bit supply constrained resulting lower sale demand this worked out tesla moving european market ship number limited car europe customer well definitive monthly summary electric plugin hybrid electric sale hope enjoyed cleantechnicas completely free electric car report electric car early adopter follower want youd attend electric vehicle solar power event conducted cleantechnica date hottest cleantech new subscribing free cleantech newsletter eye sectorspecific new also free solar energy newsletter electric vehicle newsletter wind energy newsletter tag acura acura ilx hybrid chevy spark chevy spark chevy spark sale chevy volt electric car sale fiat fiat ford ford cmax energi ford cmax energi phev ford cmax energi plugin hybrid ford cmax hybrid ford electric vehicle ford escape hybrid ford focus electric ford fusion ford fusion energi ford fusion energi phev ford fusion energi plugin hybrid ford fusion hybrid ford hybrid electric vehicle ford plugin hybrid electric vehicle honda honda accord honda accord hybrid honda accord phev honda civic honda civic hybrid honda crz honda fcx clarity honda fit honda insight hybrid electric car sale lincoln lincoln mkz hybrid mitsubishi mitsubishi nissan nissan leaf plug car sale plug electric car sale porsche porsche cayenne porsche cayenne hybrid porsche electric suv porsche panamera hybrid tesla tesla model toyota prius toyota prius toyota prius liftback toyota prius phev toyota prius toyota rav volkswagen volkswagen jetta hybrid jetta jetta hybrid zachary shahan tryin and specy letter time spend time cleantechnica director chief editor otherwise enthusiastically fulfilling duty obsession gas solar love planetsave bikocity president important media zach recognised globally solar energy electric car energy storage wind energy expert speak related conference event connect social media zacharyshahancom related post ","m_szGeo1":"United States","m_szSourceType":"source_industry","m_szSrcUrl":"http://cleantechnica.com/2013/11/06/us-electric-car-sales-increased-361-2013-far/","m_Places":["Us","Well","Tesla","Europe"],"m_People":["Ford Strong","Ford , Ford C-max Energi","Chevy Volt","Zachary Shahan"],"m_Companies":["Target","Volt","Honda","Honda Cr-z"],"m_BiGrams":["electric car","electric vehicle","car sale","ford fusion","hybrid electric","chevy spark","toyota prius","strong growth","plugin hybrid","ford cmax","hybrid ford","lot people","fusion ford","spark chevy","cmax energi","fusion energi","prius toyota"],"m_TriGrams":["electric car sale","plugin hybrid electric"],"m_SocialTags":[],"m_Topics":[],"m_Industry":[],"m_Technology":[],"m_BiCnt":[16,10,8,8,6,6,6,5,5,5,5,4,3,3,3,3,3],"m_TriCnt":[6,3],"m_iDocBodyWordCnt":652}
