{"m_szDocID":"239740","m_szDocTitle":"Electric Vehicle News | CleanTechnica","m_szYear":"2015","m_szDocSumamry":"Electric Vehicle News Published on November 28th, 2015 | by Zachary Shahan 12 November 28th, 2015 by Zachary Shahan   As much as we obsessively cover electric vehicle news, we can’t get to everything that I think is worth sharing. Here’s a roundup of some top electric vehicles news and commentary from around the interwebs. Enjoy. Tesla News Custom Tesla Model X Thanks Company’s Veterans, Model S Too Seeing a Tesla Model X electric SUV on the roads at all is still a rare occurrence; seeing one in flat black is even rarer. That’s because there’s only one that looks like the Model X in these phot","m_szDocBody":"electric vehicle new published zachary shahan zachary shahan obsessively cover electric vehicle new worth sharing here roundup top electric vehicle new commentary interweb enjoy tesla new customtesla model company veteran model tesla model electric suv road rare occurrence flat black rarerthat model photos snapped supercharger day ago teslaowning george parrott autopilot tesla straight mobileye tesla mobileye sensor thought autopilot teslas proprietary software sensor video link similar autopilot wondering autopilot essentially rollout shelf mobileye package tweaking unique software tesla writing utilise sensor discoveredthe dislike model park car sun door handle hot fact burned fingerprint yesterday open afternoon farmer market ouch said discover design flaw wondering solution doesnt require glove mymodel ruined car here problem was gear head model ruined car possibly myself mechanical technical tear down inspect understand nut wire carburetor pump display more storey long back storey ill short tesla model owner past month ive enjoying incredibly quick quiet safe intergalactic space boat light wonder day ford escape merged gap fit older meaner geo metro thought loved car thought amazing iphone sliced bread invented long born world torn damage bumper think part dont know dont care point space boat week heroin addict quick fix ive slowly rotting inside soul crushed defeated horrendous act operating gasoline fueled automobile wont specific make model antique transportation device fault broken funnystory random driver challenging tesla owner race number storey weve published tesla owner racing gaspowered car year sorry whodont aspect site number considerably you pretty obvious lot people tesla model roadster challenge unseentidbit tesla autopark feature muchanticipated autopilot update attention autopark livein nyc parallel parking pro arent impressed youre doesnot regularly parallel park feature bea saviour efficient parker prefer busy city street impatient motorist waiting inevitably pressure misalign start overwhatever case unseen tidbit tesla autopark feature howdoe autopilot react disappearing lane marking autopilot live month autopilotenabled teslas road combine roughlya million mile driving day dont clarified mile autopilot total assume mile spent autopilot tesla gathered data mile driving fleet learning concept car learn fleet learn something make teslas model incremental improvement revolutionary made quickly software refined data impossible collect creating incredibly detailed map data collected car mythought year ownership wanted moment provide update ownership experience year mile year month exact ordered classic received month august time teslas arizona service centre operated small temporary facility ordered car test driven model solely read forum minivan practical reason kid family moving stuff picking friend suv work due driving safety handling space vehicle mobile office time built technology increase efficiency wheel drive winter safety car cost month gas utility vehicle car season car low maintenance dont time oil upsell synthetic yearold suv pay insurance car car fun drive life cool car innovative car car age strive car exhilarating drive good environment safest car say frunk dont show you say touch ludicrous button ready considered indulgence deeply practical car decision made tired compromise vehicle roomy mean poor fuel economy bad handling quick mean room person bag fuelefficient mean small exotic mean impractical season spring winter fall driving family man kid mean pretty ice vehicle compromise areas weighed pros con car tesla model modelx face bestial trial tesla apparently taking general order model start incentive counting samsonite gorilla test moment laymen mitt start monkeying falcon door happen fooled hitting anything hang them lift you kind thing monkey business abound autopilot videos attest aint nuthin yet fascinating door invite shenanigan primate orange suitcase human screw poor model natural tesla mention blackish week episode show blackish father convince daughter attend expensive collegehe hell give tesla excitedly replied falcon door fresh nissan leaf mountain enjoy adventure nissan featuring company pure snowlike white leaf accompanied pretty sky evening glow fresh allelectric nissan leaf take mountain fora cool evening outing driving sky city highlighting classleading mile range single charge audigeely ramp production here tale country plan put evs road federal subsidy designed make evs cost competitive conventional car charging infrastructure left manufacturer out china government taking lead building charging infrastructure dole incentive perquisite buyer make sense buy car dealer wont sell electric year ago president obama called million electric car road year vehicle gained large fan club environmentalist promote smart cut dangerous emission owner love pep gas money save apple jumped race build nextgeneration batterypowered car electric vehicle road answer ly unexpected powerful camp sceptic car dealer showing enthusiasm putting consumer electric car charging firstpublic ccs fast charger jersey action back posted announced opening fast charger east coast express charging corridor station installed hartford connecticut express charging corridor completed connect washington boston massachusett ccs fast charger located mile apart funded joint venture bmw volkswagen chargepoint spira mile range doesnt fancy supercar tesla model normal car nissan leaf desire electric smart car common sight large city perhap renault twizy europeon note recently made aware spira interestinglooking lowcost vehicle purchased electric gasmobile greenphev sticker calif solo close maxed thtime rate california plugin hybrid owner applying green soloaccess occupancy vehicle hov sticker remaining couple month sothis true state legislature raise cap sticker limit time already whenwill start tailpipe car morally wrong economist call externality theyre cost people action people communitiesbut people taking action dont pay cost harm other emission combusting fossil fuel prime example audiutilizing alstomproduced plugin hybrid shunting locomotive facility ingolstadt german automotive manufacturer audi utilising alstom horsepower plugin hybrid shunting locomotive facility ingolstadt recent reportsthe axle alstom plugin hybrid locomotive capable running diesel required conventional counterpart thereby lowering emission reportedly course considerably quieter bluesky return beijing time year strong central government done italy mussolini made train run time china communist party make sky turn blue torecently chinese government planneda celebration mark end world war problem was wanted clear sky occasion heavy smog hang city miamiorlandohigh speed rail project unveil train scheduled operation miamiorlando speed rail project carry passenger floridas largest international city link state touristyest destination project previously aboard florida recently unveiled train rendering new highly anticipated train terminal feel theyre done cleantechnicas completely free electric car report electric car early adopter follower want youd attend electric vehicle solar power event conducted cleantechnica date hottest cleantech new subscribing free cleantech newsletter eye sectorspecific new also free solar energy newsletter electric vehicle newsletter wind energy newsletter tag chevy volt chevy volt aboard florida alstom audi autopilot big bang theory blackish blueindy bmw bmw electric motorcycle bmw err bmw err electric motorcycle bmw bmw bmw chevy volt fast charger elon musk ferrari laferrari florida ford geely car electric car honda honda clarity laferrari mclaren mclaren mercede mercede bclass electric mercede bclass electric drive mobileye nissan nissan gtr nissan leaf nrg evgo porsche porsche spyder renault scott harden sharengo spira tesla tesla autopark tesla autopilot tesla autosteer tesla big bang theory tesla mobileye tesla model tesla model tesla model tesla teslapedia volkswagen motorcycle zachary shahan tryin and specy letter time spend time cleantechnica director chief editor otherwise enthusiastically fulfilling duty obsession gas solar love planetsave bikocity president important media zach recognised globally solar energy electric car energy storage wind energy expert speak related conference event connect social media zacharyshahancom related post ","m_szGeo1":"United States","m_szSourceType":"source_industry","m_szSrcUrl":"http://cleantechnica.com/2015/11/28/electric-vehicle-news-2/","m_Places":["Tesla","Nyc","Teslas","Arizona","Orange","Us","China","New Jersey","East Coast","Hartford, Connecticut","Washington, Dc","Boston, Massachusetts","Europe","California","Ingolstadt","Beijing","Italy","Miami","Orlando","Florida","Uk"],"m_People":["Zachary Shahan","George Parrott","Mercedes-benz B-class","Ev Buyers","Barack Obama","Chevy Volt","Elon Musk","Ferrari Laferrari"],"m_Companies":["Thanks Company","Gap","Tidbits","Samsonite","Youtube","Audi","Geely","Apple","Google","Bmw","Volkswagen","Alstom","Shunting","Diesel","Communist Party","Chinese Government","Theory","I3","Honda","Nrg","Renault"],"m_BiGrams":["tesla model","electric vehicle","electric car","model tesla","nissan leaf","fast charger","plugin hybrid","vehicle new","zachary shahan","autopilot tesla","chevy volt"],"m_TriGrams":["electric vehicle new"],"m_SocialTags":[],"m_Topics":[],"m_Industry":[],"m_Technology":[],"m_BiCnt":[8,6,6,4,4,4,4,3,3,3,3],"m_TriCnt":[3],"m_iDocBodyWordCnt":1162}
