{"m_szDocID":"239823","m_szDocTitle":"Mitsubishi Outlander Hybrid Scored Tech of the Year Award (w/ Video)","m_szYear":"2013","m_szDocSumamry":"November 25th, 2013 by Jo Borrás   Mitsubishi Outlander PHEV at EVS 27 in Barcelona. Image Credit: Zachary Shahan / CleanTechnica / EV Obsession (available for republishing under a CC BY-SA license). Mitsubishi has been quiet in recent years, with the Mitsubishi i-MiEV  runabout being, arguably, the most significant product launch for the company in the last five or six years. That’s all about to change, however, with the launch of the new Mitsubishi Outlander Plug-in Hybrid, a 7-passenger SUV that features all-wheel drive, thanks to a pair of electric motor packs, and a range-extending gas en","m_szDocBody":"borr mitsubishi outlander phev evs barcelona image credit zachary shahan cleantechnica obsession available republishing bysa licence mitsubishi quiet recent year mitsubishi imiev runabout being arguably significant product launch company year change however launch mitsubishi outlander plugin hybrid passenger suv feature allwheel drive pair electric motor pack rangeextending gas engine tech shown good win rjc tech year award week read below originally appeared gas mitsubishi outlander plugin hybrid pick tech award automotive researcher journalist conference rjc recently met japan award upcoming mitsubishi outlander plugin hybrid suv ultimate clean tech award rjc technology year award mitsubishi outlander hybrid system feature highcapacity battery send juice separate front rear motor gas engine primarily electrical generator gas engine engaged drive wheel ecu decide efficient moving suv forward driving condition chevy plugin hybrid volt allwheel drive room passenger year significant product offering mitsubishi bit roll late mirage cvt tested week light nimble fun town generally adequate highway bad highest mpg car buy that hybrid company outlander sport crossover recently received independent iih highest top safety pick safety rating honour share volvos teslas bersafe model sedan good them mitsubishis elegant plugin hybrid system video below extrabig awd voltish suv comment bottom page enjoy source automotive design cleantechnicas completely free electric car report electric car early adopter follower want youd attend electric vehicle solar power event conducted cleantechnica date hottest cleantech new subscribing free cleantech newsletter eye sectorspecific new also free solar energy newsletter electric vehicle newsletter wind energy newsletter ","m_szGeo1":"United States","m_szSourceType":"source_industry","m_szSrcUrl":"http://cleantechnica.com/2013/11/25/mitsubishi-outlander-hybrid-scored-tech-year-award/","m_Places":["Barcelona","Japan","Us","Tesla"],"m_People":["Jo Borrás","Zachary Shahan","Awd Volt-ish"],"m_Companies":["Volt","Mirage","Mpg","Volvos"],"m_BiGrams":["mitsubishi outlander","plugin hybrid","outlander plugin","gas engine"],"m_TriGrams":["mitsubishi outlander plugin","outlander plugin hybrid"],"m_SocialTags":[],"m_Topics":[],"m_Industry":[],"m_Technology":[],"m_BiCnt":[5,5,3,3],"m_TriCnt":[3,3],"m_iDocBodyWordCnt":242}
