{"m_szDocID":"240389","m_szDocTitle":"300% Increase In 100% Electric Car Sales In 2013 | CleanTechnica","m_szYear":"2013","m_szDocSumamry":"300% Increase In 100% Electric Car Sales In 2013 Originally published on EV Obsession . 100% electric car sales are up about 300% in 2013 so far, while plug-in hybrid electric car sales are up about 31% for the same period. Note that Tesla doesn’t report its sales on a monthly basis — only on a quarterly basis — so my numbers for its sales are an estimate (but a pretty confident one). Also note that Fiat doesn’t report sales of the Fiat 500e at all. The year-to-date sales increase in my spreadsheet is actually about 298% for pure electric cars, but with a good estimate of the 500e thrown in, i","m_szDocBody":"increase electric car sale originally published obsession electric car sale far plugin hybrid electric car sale period note tesla doesnt report sale monthly basis quarterly basis number sale estimate but pretty confident one note fiat doesnt report sale fiat all yeartodate sale increase spreadsheet pure electric car good estimate thrown increase here full table commentary top plugin car storey month course growth electric car sale huge storey bit cumulative total reported month huge solid yeartodate growth plugin hybrid electric ford hybrid electric boom levelling case year ford yeartodatehybrid electric car sale great deal introduction ford cmax hybrid ford cmax energi ford fusion hybrid ford fusion energi end year beginning year however advantage downswing weve catching time year introduced fact ford total lower total surviving uptrend reverse storey chevy volt sale year date barely sale considerably higher sale volt surely hit increasing competition phev pure electric car market sale held fairly steady survived onslaught competition far unfortunately bring chevy spark market great response car received far compliance car all honda fiat lame entrance good car interest commenting honda fiat built great plugin car fiat widely acclaimed honda fit excellent range great car the car fuel efficient car list reverse order limiting production small number selling car select market clear compliance car hondas pushing conventional hybrid vehicle success transition greener and awesome plugin car transition speaking toyota dominate hybrid inching plugin course toyota long clear leader conventional hybrid electric vehicle ride wave long possible sale bit sale hybrid electric car sale month top sale list month month also hybrid electric car sale car year date realm plugin car real focus love toyota isnt leader isnt laggard honda fiat toyota prius phev sale year date course great demand prius hybrid company ability upsell customer phev part that seemingly limiting production hundred vehicle company plugin car nissan leaf power nissan leaf powering great pace clear leader electric car market sale year period year november top sale spot plugin car swapping place chevy volt time year sale total nissan bit supply constrained producing leaf continuously bigger sale worked people aware tremendous performance benefit electric car tesla tesla supply constrained naturally tesla hot company plugin car world electric car company mass producing vehicle stock shot roof year model widely regarded massproduced car type world based estimate sale compared yeartodate sale however tesla supply constrained month nascent fastgrowing industry hoping resolved quarter let hope however entering european chinese market sale harder estimate decide stop including unfortunate volume sale contribute great consumer interest vehicle main thought november hybrid electric car sale result add cleantechnicas completely free electric car report electric car early adopter follower want youd attend electric vehicle solar power event conducted cleantechnica date hottest cleantech new subscribing free cleantech newsletter eye sectorspecific new also free solar energy newsletter electric vehicle newsletter wind energy newsletter tag acura acura ilx hybrid chevy spark chevy spark chevy spark sale chevy volt fiat fiat ford ford cmax energi ford cmax energi phev ford cmax energi plugin hybrid ford cmax hybrid ford electric vehicle ford escape hybrid ford focus electric ford fusion ford fusion energi ford fusion energi phev ford fusion energi plugin hybrid ford fusion hybrid ford hybrid electric vehicle ford plugin hybrid electric vehicle honda honda accord honda accord hybrid honda accord phev honda civic honda civic hybrid honda crz honda fcx clarity honda fit honda insight lincoln lincoln mkz hybrid mitsubishi mitsubishi nissan nissan leaf porsche porsche cayenne porsche cayenne hybrid porsche electric suv porsche panamera hybrid tesla tesla model toyota prius toyota prius toyota prius liftback toyota prius phev toyota prius toyota rav volkswagen volkswagen jetta hybrid jetta jetta hybrid zachary shahan tryin and specy letter time spend time cleantechnica director chief editor otherwise enthusiastically fulfilling duty obsession gas solar love planetsave bikocity president important media zach recognised globally solar energy electric car energy storage wind energy expert speak related conference event connect social media zacharyshahancom related post ","m_szGeo1":"United States","m_szSourceType":"source_industry","m_szSrcUrl":"http://cleantechnica.com/2013/12/06/300-increase-100-electric-car-sales-2013/","m_Places":["Tesla","Us","Toyota","Love — Toyota"],"m_People":["Ford , Ford C-max Energi","Chevy Volt","Zachary Shahan"],"m_Companies":["Volt","Honda","Honda Cr-z"],"m_BiGrams":["electric car","hybrid electric","car sale","plugin car","hybrid ford","ford fusion","electric vehicle","toyota prius","plugin hybrid","ford cmax","cmax energi","fusion energi","chevy spark","energi ford","chevy volt","sale year","year date","market sale","honda fiat","supply constrained","prius toyota"],"m_TriGrams":["electric car sale","hybrid electric car","plugin hybrid electric","ford cmax energi","ford fusion energi"],"m_SocialTags":[],"m_Topics":[],"m_Industry":[],"m_Technology":[],"m_BiCnt":[16,9,8,7,7,7,6,6,5,5,4,4,4,3,3,3,3,3,3,3,3],"m_TriCnt":[8,4,3,3,3],"m_iDocBodyWordCnt":651}
