{"m_szDocID":"240679","m_szDocTitle":"Plug-In Hybrid Electric Chrysler Minivan Coming | CleanTechnica","m_szYear":"2015","m_szDocSumamry":"Plug-In Hybrid Electric Chrysler Minivan Coming February 21st, 2015 by James Ayre   The creator (more or less) of the modern minivan, Chrysler, is apparently soon going to be bringing the first plug-in hybrid electric minivan to market in the US, according to recent reports. Quite fitting really — who better to do so than Chrysler? The news was revealed by the president and CEO of Chrysler for North America, Al Gardner, during a recent interview with the Detroit Bureau — where it was stated that a plug-in hybrid electric minivan was definitely part of the company’s future plans. And that, appa","m_szDocBody":"plugin hybrid electric chrysler minivan coming jame ayre creator more less modern minivan chrysler apparently bringing plugin hybrid electric minivan market recent report fitting reallywho chrysler new revealed president ceo chrysler north america gardner recent interview detroit bureau stated plugin hybrid electric minivanwas part company future plan that apparently chrysler minivan ready regal detroit international auto show bit detroit auto show though wasnt stated gardner head romeo fca sergio marcchione gas muse subject mystifying world car maker segment market long soccer mom vehicle transporting young family children gear lowly minivan year year industry sell million reason minivan ideal starting point plugin hybrid conversion too tend ride higher ground sedan offer lot place add battery electric motor pickup truck mention chrysler hit home run sedan lately success fca confidence chrysler brand thrive middle market offering uniquely american style latest technology segment dull supposed metoo vehicle gardner completely agree nobrainer chrysler make move electricminivan market wide open seemingly ready taking broader electric vehicle market continuing grow apparently openniche there wouldnt surprised offering priced competitively image credit cleantechnicas completely free electric car report electric car early adopter follower want youd attend electric vehicle solar power event conducted cleantechnica date hottest cleantech new subscribing free cleantech newsletter eye sectorspecific new also free solar energy newsletter electric vehicle newsletter wind energy newsletter tag chrysler chrysler phev minivan phev minivan jame ayre background predominantly geopolitic history obsessive interest pretty everything early life spent imperial free city dortmund jame river ruhr cofbuokheim attended university astnide briefly considered entering coal mining business write living broad variety subject ranging science politic military history renewable energy follow work google related post nissan tesla fiat sell zev credit california larry lee iacoca retired chrysler hasnt good idea running company purchase hybrid technology toyota end disaster bobwallace chrysler working electric vehicle while looked bringing phev pickup market time back ran problem battery overheating rapid recharging sebastian tristan nobrainer love day plugin minivan benjamin nead boy childraisin minivan drivin year mid plymouth voyage basically generally thought great good mileage day compact roomy mine though worn time hand couple year noticed then though current minivan day significantly larger quickly moving mini format original minivan started stretching fattening quickly easily call worst vehicle wife purchased ford aerostar allwheel drive eddie bauer edition year literally fell front eye front transaxle rear differential failed year owning dealer scour wrecking yard part year vehicle transmission started south engine shortly thereafter mpg finally rid describe hell wheel worst sense phrase mazda mpv month ago mixed feeling one lasted solid decade hard carpooling son friend everywhere started deteriorate quickly year mileage great fresh again minivan mini worse wear still aerostar how not time bought mazda regular hybrid prius etc coming scene assumed hybrid minivan corner were considered trading mid decadelong trek mazda save gas dice then figured plugin hybrid minivan showing nope oem made hybrid plugin hybrid past decade buzz larger format hybrid revolved suvs ergonomic doesnt work hauling true minivan suv hybrid bit ripoff milage pure ice minivan simply didnt point made minivan century drivetrain decade half century think great missed opportunity time automotive world son college weve downsized honda fit car horizon dont hauler anymore bad long plugin hybrid minivan here actuality isnt either coming pure electric minivan off pity jenny sommer waiting that bit huge side though ride toyota avensis verso compact minivan huge inside kmwill reach seat kid van thought bad sjc good idea martin waiting pure minivan work year jameswimberley nissan market peoplecarrier version env sold europe taxi thing range isnt great mile nissan assume purely urban use waiting wave battery range martin problem live canada pretty buy here knowhow converted mine year ago jamesjm chrysler add quality minivan buzz word farfetched concept vehicle lowest rating minivan jameswimberley renault early espace project chrysler origin oddly havent offered hybrid technology sector pure electric renaultnissan focus ronald brakel existing hybrid production understand hybrid parallel hybrid toyota prius pretty amazing piece technology cost lot money develop case technology licenced toyota company late stage game make sense straight electric vehicle serial hybrid simpler beast parallel hybrid sery hybrid electric car generator tacked ","m_szGeo1":"United States","m_szSourceType":"source_industry","m_szSrcUrl":"http://cleantechnica.com/2015/02/21/plug-hybrid-chrysler-minivan-coming/","m_Places":["Us","North America, Al Gardner","Detroit","Free City","Dortmund","Tesla","Most","California","Toyota","Plymouths","Hell","Europe","Canada"],"m_People":["James Ayre","Sergio Marcchione","Will Nissan","Lee Iacoca","Sebastian Tristan","Ev Van","Benjamin Nead","Jenny Sommer","Ronald Brakels"],"m_Companies":["Detroit Bureau","Detroit International Auto Show","University Of Astnide","Google","Plymouth Voyage","Eddie Bauer","Mazda Mpv","Mazda","Seat","Renault","Renault-nissan"],"m_BiGrams":["plugin hybrid","electric vehicle","hybrid electric","electric car","hybrid minivan"],"m_TriGrams":["plugin hybrid electric"],"m_SocialTags":[],"m_Topics":[],"m_Industry":[],"m_Technology":[],"m_BiCnt":[7,5,4,3,3],"m_TriCnt":[3],"m_iDocBodyWordCnt":683}
