{"m_szDocID":"24097","m_szDocTitle":"Solar Power Alive & Well in Spain; Electric Power Act Flawed - CleanTechnica","m_szYear":"2012","m_szDocSumamry":"textArticle -------------------- Solar Power is Alive and Kicking in Spain, but Flawed Electric Power Act Needs Correcting June 28th, 2012 by Andrew   Photo courtesy Abengoa A hangover of bad debts from a speculative real estate/property boom threatens to overwhelm Spain’s banks, the national government, and the entire economy, potentially bringing the demise of the single European currency, the euro, along with it. Generous feed-in tariff (FiT) rates for solar and wind energy also led to a boom in Spanish renewable energy, one that’s been deflated as a result of the fiscal austerity that the ","m_szDocBody":"solar power alive kicking spain flawed electric power act correcting andrew photo courtesy abengoa hangover bad debt speculative real boom threaten overwhelm spain bank national government entire economy potentially bringing demise single european currency euro generous feedin tariff fit rate solar wind energy led boom spanish renewable energy deflated result fiscal austerity spanish government subsequently forced take fit hasnt created lasting benefit spanish spanish commercial enterprise spanish installation utilityscale distributed solar wind energy system produce clean renewable electrical power decade come helping insulate consumer rising fossil fuel cost theyre making big cut greenhouse gas emission form environmental pollution fossil fuel bring mention political pecadillos use euphemism here avoided renewable energy rare bright spot spain term investment job creation stand starkly unemployment rate spanish company abengoa gamesa iberdrola other leading multinational player solar wind renewable energy clean technology market contributing significantly growing renewable energy world bright spot gloomy picture solar wind installation continue built spain crisis abengoa yesterday announced helios parabolic trough concentrated solar power csp plant live castillala mancha solar complex castillala mancha solar complex consist identical csp plant outfitted parabolic solar collector installed approximately hectare acre area helios produce clean renewable electricity power spanish household substantially avoiding greenhouse gas emission tonne year company abengoas world solar power leader installed base solar capacity totaling commercial operation construction europe africa time history spain occupy position leadership major technologicalindustrial sector growing importance worldwide country renewable sector directly employ people generate gdp invest contribution gdp r&d double national average write abengoa chairman felipe benjumea spain world leader solar thermal technology employment people vast majority job found region higher unemployment rate enable curbing burdensome import fossil fuel spanish company building solar thermal plant abroad inside spain maintaining higher valueadded activity country resulting development sector payment taxe job creation exportation cuttingedge technology electric power act flaw benefit nuclear hydropower consumer environment expense spain rely volatile increasingly expensive polluting fossil fuel power need overwhelming majority imported moreover fit solar renewable energy contributed significantly spain socalled tariff deficit debt problem anything flaw spain electric power act nuclear hydro power provider charge rate indexed rising cost fossil fuel added spain fiscal shortfall benjumea fit rate premium spanish nuclear hydro provider inflated allowing sell electricity nuclear hydropower plant consumer public government rate correlated cost production market price oil sold energy price benefiting rising oil price producing paradox higher price oil dearer sale price hydro nuclear energy spain caused million deficit recent year benjumea course happened previous government tackled problem year ago step spanish government remedy situation alleviate spain debt crisis government deduct amount overpaid nuclear hydropower provider year what owed them benjumea assert right light fact spain electric power act was glance formulated boost sustainable economic job growth enhance spain energy security reduce greenhouse gas emission environmental degradation cleantechnicas completely free electric car report electric car early adopter follower want date hottest cleantech new subscribing free cleantech newsletter eye sectorspecific new also free solar energy newsletter electric vehicle newsletter wind energy newsletter tag abengoa emission reduction debt crisis renewable energy solar energy gamesa green economic growth iberdrola solar fit spain clean energy spain debt crisis spain electric power act spain energy policy spain fit spain fossil fuel spain green economy spain greenhouse gas emission spain hydropower spain nuclear power spain renewable energy spain renewable energy fit spain solar energy spain solar fit spain solar power spain solar subsidy spain tariff deficit spanish debt crisis sustainable development andrew reporting writing wide range topic nexus economic technology year now asiapacific europe americas africa middle east issue related broad topical areas pose tremendous opportunity challenge define quality live relationship natural environment related post ","m_szGeo1":"United States","m_szSourceType":"source_industry","m_szSrcUrl":"http://cleantechnica.com/2012/06/28/solar-power-alive-kicking-spain-flawed-electric-power-act-needs-correcting/","m_Places":["Spain","Europe","United States","Africa","Asia","Middle East"],"m_People":["Felipe Benjumea"],"m_Companies":["Abengoa","Spanish Government","Helios","Eu","Nexus"],"m_BiGrams":["renewable energy","fossil fuel","electric power","power act","solar power","solar wind","greenhouse gas","gas emission","energy spain","debt crisis","fit spain","spain solar","wind energy","nuclear hydropower","spain electric","solar energy"],"m_TriGrams":["electric power act","greenhouse gas emission","spain electric power"],"m_SocialTags":[],"m_Topics":[],"m_Industry":[],"m_Technology":[],"m_BiCnt":[8,6,5,5,4,4,4,4,4,4,4,4,3,3,3,3],"m_TriCnt":[5,4,3],"m_iDocBodyWordCnt":601}
