{"m_szDocID":"241186","m_szDocTitle":"Global Energy Trends and Implications for India: The Need to Consume Less Oil","m_szYear":"2016","m_szDocSumamry":"textArticle -------------------- Global Energy Trends and Implications for India: The Need to Consume Less Oil April 14, 2015 by Tobias Engelmeier Leave a Comment The global energy system is in a period of rapid transformation: electricity plays an ever more important role, as do renewables, distributed generation and electric vehicles. Energy efficiency is improving. Emissions are a large and growing concern. New technologies and business models are disrupting and challenging a traditionally risk-averse and slow-moving industry. The International Energy Agency (IEA) has just published its new","m_szDocBody":"global energy trend implication india consume oil tobias engelmeier leave comment global energy system period rapid transformation electricity play important role renewable distributed generation electric vehicle energy efficiency improving emission large growing concern technology business model disrupting challenging traditionally riskaverse slowmoving industry international energy agency iea published energy technology perspective outlining global trend refer key finding implication india substantial reduction oil consumption needed achieve climate goal oil consumption reduced higher efficiency fuel switching gas electricity india desire reduce air pollution city significant additional driver global context order global warming degree radical action respect oil business usual degree trajectory oil consumption increase degree scenario decrease efficiency gain fuel switching driver change cost volatility oil price concern supply security future carbon price pollution climate change business model play interesting role instance carsharing businesse share electric vehicle evs fleet compared evs market also company thinking entering automotive market technologically disruptive chance success typically prefer electric motorization concept petrol engine existing car company spent decade perfecting tesla indias reva effort perhap apple challenge moving oil required energy density vehicle fuel energy concentrated limited amount space electric battery storage viable route gridconnected urban areas however fuel switching challenging offgrid longdistance heavyduty vehicle truck air plane ship current technology biofuel fuel cell option interestingly iea project fuel switching vehicle technology reduce oil demand transport sector considerably increasing consumption power modelling aggressive rate electrification transport share electricity demand exceed implication india oil consumption rise india economy population grow major headache government india import fuel oil price fairly low rise again drive inflation open large trade deficit government decide step subsidise oil again quickly major cost position budget addition terrible air pollution indias city increase demand cleaner vehicle addition stricter regulation vehicle efficiency pollution main lever fuel switching gas cng electric vehicle china example city suffer heavily air pollution million electric wheeler road thus moving oil quickly indias core interest china frontrunner transition related post logged post comment logged post comment energy collective column coming soon latest comment schalk cloete seeking consensus externalised cost gas data average externalised cost transport fuel natural gas calculated june schalk cloete seeking consensus externalised cost gas data average externalised cost heat natural gas calculated article june schalk cloete seeking consensus externalised cost gas data global average externalised cost gas fired electricity plant june roger arnold treasure sierra nevada noticed map lake lahontan talked survive june advisory panel scott edward anderson consultant blogger media commentator blog green sceptic christine hertzog consultant author professional explainer focused smart grid elias hinckley strategic advisor energy finance energy policy investor energy company government gary hunt gary executiveinresidence deloitte investment extensive experience energy utility industry jesse jenkin graduate student researcher mit expertise energy technology policy innovation jim pierobon help trade government agency company communicate cleaner energy solution geoffrey style managing director gsw strategy group llc awardwinning blogger featured contributor june june ","m_szGeo1":"United Kingdom","m_szSourceType":"source_industry","m_szSrcUrl":"http://www.theenergycollective.com/tobias-engelmeier/2215896/global-energy-trends-and-implications-india-need-consume-less-oil","m_Places":["India","Reva","China","Gary"],"m_People":["Tobias Engelmeier","Tesla , India","Roger Arnold","Scott Edward","Christine Hertzog","Elias Hinckley","Hunt Gary","Jesse Jenkins","Jim Pierobon","Geoffrey Styles"],"m_Companies":["New Technologies","International Energy Agency","Iea","Google","Apple","Sierra Nevada","Deloitte","Strategy Group, Llc"],"m_BiGrams":["externalised cost","fuel switching","oil consumption","cost gas","implication india","electric vehicle","air pollution","schalk cloete","cloete seeking","seeking consensus","consensus externalised","gas data","average externalised"],"m_TriGrams":["externalised cost gas","schalk cloete seeking","cloete seeking consensus","seeking consensus externalised","consensus externalised cost","cost gas data","average externalised cost"],"m_SocialTags":[],"m_Topics":[],"m_Industry":[],"m_Technology":[],"m_BiCnt":[6,5,4,4,3,3,3,3,3,3,3,3,3],"m_TriCnt":[4,3,3,3,3,3,3],"m_iDocBodyWordCnt":473}
