{"m_szDocID":"241329","m_szDocTitle":"America’s First Oil Sands Producer and Other Natural Resources Surprises: Interview with Peter Epstein","m_szYear":"2014","m_szDocSumamry":"textArticle -------------------- America’s First Oil Sands Producer and Other Natural Resources Surprises: Interview with Peter Epstein August 16, 2014 by Jim Patrick Leave a Comment In 2011, CFA Peter Epstein left his senior analyst position at a $3B hedge fund and formed MockingJay Inc., a consultancy for companies in the natural resources space and an informal investment adviser to high-net-worth investors, family offices and funds. The company’s mission is to increase awareness of select natural resource companies. Epstein’s areas of expertise include uranium, coal, potash, gold and oil & ","m_szDocBody":"americas oil sand producer natural resource surprise interview peter epstein jim patrick leave comment cfa peter epstein left senior analyst position hedge fund formed mockingjay inc consultancy company natural resource space informal investment adviser highnetworth investor family office fund company mission increase awareness select natural resource company epstein areas expertise include uranium coal potash gold oil gas published hundred article investment site seeking alpha motley fool auwirecom energy report excited oil gas space now peter epstein oil gas unique hasnt budged commodity fallen precipitously price coking coal price example multiyear low iron ore price fallen tonne uranium spot price fallen nineyear low oil price held range west texas intermediate crude year steady strong natural gas price collapsed back fairly strong recently giving back bit gain oil gas strong commodity talk slowdown china lot commodity fall oil gas stick there ter oil gas mining industry tarred brush environmental advocate describe dirty polluting environmentally destructive industry made attractive investor put premium environmental consideration company learning hard social licence operate address increasingly long list permitting environmental hurdle extractive industry dirty polluting clean act problem yearsor decadesdepending jurisdiction negative impact company longer time frame production created myriad factor environmental consideration longer time frame mean difficulty funding project lower net value project hurdle rate rise account higher risk longer time frame mean industrywide cost curve increase commodity price rise response margin squeezed somewhat company enjoy higher commodity price long term ter company sacrifice achieve environmental goal company give profit meet reality company approach dirty polluting industry innovative way frequently technological advance rewarded example american sand energy corp amseotcbb company extract bitumen oil sand located utah company propose approachin fact approach chance american sand energy operate company proprietary solvent separate bitumen sand water process arid eastern utah extremely important factor water required oil sand deposit utah alberta canada canada oil sand mixture water sand bitumen utah deposit bitumen sandno water american sand energy perfect company winner mitigating environmental factor company approach dirty polluting industry innovative way technological advance rewarded company graphite resource inc gphtsxv project alaska everyone heard tesla motor inc tslanasdaq gigafactory produce large number battery electric vehicle time teslas big announcement february outcry group contended large quantity sourced graphite dirty polluting mine china played role teslas announcing source key material battery north america graphite graphite play graphite massive graphite resource significantly sized portion mined surface company plan infill mined areas fully reclaim disturbed areas graphite worth watching fact unique graphite company opportunity apply loan state alaska programme alaska miningfriendly ensure prudent environmental standard followed ter graphite company like big north graphite corp nrttsxv rehabilitating existing operating facility mexico mention environmentalist like company start production job and importantly clean mess done now mine eyesore damaged earth big north graphite reclaim end ter company excited about aroway energy inc arwtsxv arwjfotcqx heavy oil property saskatchewan light oil property central alberta own land kerrobert area westcentral saskatchewan storey fascinate company week drilling kerrobert area back april stock trading today company month closer potentially finding blockbuster field located mile away private company called caltex resource ltd producing reported cumulative dozen well aroway hit late august stock double triple subsequent month ter uranium price stalled bet rise again couldnt lower stalled again make uranium mining profitable attractive again time april spot price handle consulting quoting aug appear spot uranium bottomed spot price rebound bullish sentiment uranium junior point spot price longterm price utility contract make mistake nineyear low depressed price uranium mine world business analyst price greenfield project green light sound high month leading terrible fukushima disaster longterm uranium price steady globally cost pound produce uranium past year mining cost generally increasing factor weve discussed permitting cost time frame environmental concern etc market higher uranium price higher uranium price question when pundit point restart japanese reactor offline agree positive sentiment booster move uranium price much opinion market higher uranium price higher uranium price question when focusing japan market watching china india generate electricity nuclear power changeand will severe air pollution problem chinese build reactor fast can continue ramping hydropower wind solaryou nuclear power generation china larger part growing pie china sitting trillion treasury happily buy hard asset form uranium uranium enrichment facility chinese active stateowned entity level term building nuclear power station analyst point insitu recovery operation potentially profitable low cost profitable uranium price say size project typically small move needle globally finally point utility contracting longterm supply uranium feel urgency change utility wait contract uranium supply year utility back market longterm price rise commodity hit nineyear low uranium favour lot uranium stock oversold opportunity small name ter projection nuclear power plant construction china suggest construction country wont exceed total power need greatly increase uranium demand china expect start building reactor year year ramping question long electricity nuclear power year china think long term lot dollar transform hard asset chinese actively uranium nuclear power russia well india way china india active building hydroelectric dam kind construction unbelievable amount scrutiny term environment fact ten hundred thousand people moved village build dam hydroelectric development china india quicker end people realise then course coal world bank international monetary fund major international body theyre fund world coal power plant anymore factor lead nuclear power development ter company youd mention cbd energy ltd nasdaqcbde interesting because addition solar stock company work wind energy management system installation australia moving australia home solar estimated solar extremely competitive company installing rooftop solar panel penetration solar rooftop individual home low cbd energy funded strong management team long track record fact licenced westinghouse solar trademark people real brand name exciting part storey solar company trade revenue competitive crowded space hard kind multiple fair bubble case cbd however geographically diversified fastgrowing small company trading multiple revenue ter potash space shaken year collapse cartel russia affecting potash space north america today potash generic term refer potassiumbearing mineral naturally occurring potassium salt product produced salt potash plant main source potassium fertiliser muriate potash mop price collapsed event couple month potash price fell tonne tonne price differ world benchmark price lot people refer oil gas space unique hasnt budged commodity fallen precipitously price mop widely type farming chloride ion detrimental plant growth fruit vegetable sulphate potash sop different sop improve yield quality taste shelf life attribute valuable farmer sop trade premium price mop sop price barely moved all theyre product sop specialty product onetenth market mop thirdparty study commissioned potash ridge corp prktsx potrfotcqx suggest demand sop time greater existing user ensure security supply user introduced sop versus mop premium sop mop moved bit sop price virtually unchanged russian cartel turmoil mop price fell make sop mop feedstock start with start mop spend money process margin strong expensive process company mop market metric sop market million tonne potash ridge blawn mountain project utah hand produce sop directly extracting mineral ore starting sop company pipeline ability potash ridge competitive advantage offer lower sop price company advantage well nearsurface resource state land federal land interaction bureau land management mop saskatchewan alone huge amount production plus number junior bhp billiton ltd bhpnyse bhplfotcpk rio tinto plc rionyse rioasx riolse rtppfotcpk project bring online ter extremely diverse portfolio company follow offer advice investor build kind portfolio themselve investor natural resource happy camper year important stick company cash balance sheet stick company portfolio theyre good management team committed company management team involved company once watch cash burn company cash burn minimal company live fight day ter peter time insight read energy report interview this free enewsletter youll learn article published recent interview industry analyst commentator visit streetwise interview page disclosure tom armistead conducted interview streetwise report llc publisher gold report energy report life science report mining report service streetwise report independent contractor own family own share company mentioned interview none company mentioned interview sponsor streetwise report aroway energy inc uranerz energy corp streetwise report accept stock exchange service peter epstein own family own share company mentioned interview american sand energy corp potash ridge corp cbd energy ltd big north graphite corp aroway energy inc graphite resource inc personally family paid company mentioned interview none company financial relationship company mentioned interview american sand energy corp paid streetwise report participating interview comment opinion expressed comment opinion opportunity review interview accuracy date interview responsible interview interview edited clarity streetwise report make editorial comment change expert statement consent interview constitute investment advice reader encouraged consult individual financial professional action reader take result information presented responsibility opening page reader accept agree streetwise report term full legal disclaimer time time streetwise report llc director officer employee member family person interviewed article interview site long short position security mentioned director officer employee member family prohibited making purchase sale security open market uptofourweek interval time interview publishes company mentioned amseotcbb arwtsxv arwjfotcqx nrttsxv nasdaqcbde gphtsxv prktsx potrfotcqx logged post comment logged post comment energy collective column coming soon latest comment schalk cloete seeking consensus externalised cost gas data average externalised cost transport fuel natural gas calculated june schalk cloete seeking consensus externalised cost gas data average externalised cost heat natural gas calculated article june schalk cloete seeking consensus externalised cost gas data global average externalised cost gas fired electricity plant june roger arnold treasure sierra nevada noticed map lake lahontan talked survive june advisory panel scott edward anderson consultant blogger media commentator blog green sceptic christine hertzog consultant author professional explainer focused smart grid elias hinckley strategic advisor energy finance energy policy investor energy company government gary hunt gary executiveinresidence deloitte investment extensive experience energy utility industry jesse jenkin graduate student researcher mit expertise energy technology policy innovation jim pierobon help trade government agency company communicate cleaner energy solution geoffrey style managing director gsw strategy group llc awardwinning blogger featured contributor june june ","m_szGeo1":"United Kingdom","m_szSourceType":"source_industry","m_szSrcUrl":"http://www.theenergycollective.com/streetwiser/463731/americas-first-oil-sands-producer-and-other-natural-resources-surprises-peter-eps","m_Places":["America","West Texas","China","United States","Utah","Alberta","Canada","Alaska","Tesla","North America","Mexico","Saskatchewan","Most","Fukushima","Japan","India","Russian Federation","Australia","Blawn Mountain","Gary"],"m_People":["Peter Epstein","Jim Patrick","Tom Armistead","Roger Arnold","Scott Edward","Christine Hertzog","Elias Hinckley","Hunt Gary","Jesse Jenkins","Jim Pierobon","Geoffrey Styles"],"m_Companies":["Natural Resources","Mockingjay Inc.","Motley Fool","American Sands Energy Corp.","Graphite One Resources Inc.","Tesla Motors Inc.","Nasdaq","State Of Alaska","Big North Graphite Corp.","Aroway Energy Inc.","Blockbuster","Caltex Resources Ltd.","Ramping","U.s. Treasuries","World Bank","International Monetary Fund","Cbd Energy Ltd.","North America Today","Mop","Potash Ridge Corp.","Russian Cartel","U.s. Bureau Of Land Management","Bhp Billiton Ltd.","Rio Tinto Plc","Streetwise Reports Llc","Aroway Energy Inc., Uranerz Energy Corp.","Sierra Nevada","Deloitte","Strategy Group, Llc"],"m_BiGrams":["uranium price","streetwise report","oil gas","nuclear power","company mentioned","externalised cost","dirty polluting","american sand","sand energy","mentioned interview","oil sand","natural resource","peter epstein","spot price","time frame","energy corp","higher uranium","potash ridge","cost gas","energy report","nineyear low","natural gas","longer time","ter company","graphite resource","big north","north graphite","aroway energy","energy inc","china india","cbd energy","management team","sop price","schalk cloete","cloete seeking","seeking consensus","consensus externalised","gas data","average externalised"],"m_TriGrams":["american sand energy","company mentioned interview","higher uranium price","externalised cost gas","longer time frame","sand energy corp","big north graphite","aroway energy inc","schalk cloete seeking","cloete seeking consensus","seeking consensus externalised","consensus externalised cost","cost gas data","average externalised cost"],"m_SocialTags":[],"m_Topics":[],"m_Industry":[],"m_Technology":[],"m_BiCnt":[8,8,7,7,6,6,5,5,5,5,4,4,4,4,4,4,4,4,4,3,3,3,3,3,3,3,3,3,3,3,3,3,3,3,3,3,3,3,3],"m_TriCnt":[5,5,4,4,3,3,3,3,3,3,3,3,3,3],"m_iDocBodyWordCnt":1607}
