{"m_szDocID":"24177","m_szDocTitle":"Deja Vu All Over Again: Republicans Intent on Nixing Wind, Clean Energy Growth - Clean Technica","m_szYear":"2012","m_szDocSumamry":"textArticle -------------------- Deja Vu All Over Again: Congressional Republicans Intent on Nixing Wind, Renewable Energy Growth February 18th, 2012 by Andrew   Congressional Republicans this past week scuttled an effort to extend the production tax credit (PTC) for wind energy as part of a bill that renews Pres. Obama’s payroll tax cut and unemployment benefits extension. Both Democrats and Republicans want economic growth and development—just ask any one or the other any time. It’s abundantly clear that they have irreconcilable differences as to just what kind of growth is good growth, as w","m_szDocBody":"deja again congressional republican intent nixing wind renewable energy growth andrew congressional republican past week scuttled effort extend production tax credit ptc wind energy part bill renew pre obamas payroll tax cut unemployment benefit extension democrat republican economic growth developmentjust time abundantly clear irreconcilable difference kind growth good growth fostering current economic social environment however wind energy ptc boon market industry youthful growing pain helped attract billion dollar investment helped create thousand good job emerging industry prove vital decade ahead yielded substantial avoidance greenhouse gas emission air water land pollution improved health condition clearly republican wont stand thing socialism cry unfair subsidy government deficit huge debt matter hyperbole rhetoric fall flat public representative refuse vote similarly eliminate subsidy time size scope wind renewable energy ptc adding insult injury longstanding federal subsidy continue benefit largest profitable industry industrial other ageoil gas outrageous hypocrisy voter buy politic movieland murder mystery cherchez moneycorporate pac superpac lobbying money case perk enjoyed boughtandpaidfor congressional representativesjunket business trip paidfor conference vacation discrete timely deposit bank account offshore tax haven know sky limit know circus merrygoround political system big corporate donor paid back time over history energy production tax credit ptc wind renewable energy power production recent creation established energy policy act intended stimulate renewable technology power production providing productionbased credit year project operation beginning cent kilowatthour kwh adjusted upward inflation future year explain ryan wiser mark bolinger galen barbose ernest orlando lawrence berkeley national laboratory paper entitled federal production tax credit build durable market wind power united state wind closedloop biomass originally eligible ptc company emerging solar geothermal industry eligible receive investment tax credit itc inflationadjusted ptc cent kwh megawatthour mwh expanded include geothermal hydro power landfill gas municipal solidwastetoenergy system made eligible ptc half rate nonrenewable energy source including refined coal indian coal nuclear power eligible ptc solar energy eligible ptc briefly american wind energy awea summarise principal federal subsidy supporting wind energy industry law ptc income tax credit production electricity utilityscale wind turbine ptc set expire additionally section american recovery reinvestment act wind project developer choose receive investment tax credit itc place ptc project service construction begin end developer elect receive equivalent cash payment department treasury itc dramatic economic impact wind energy ptc extension lapse time berkeley lab paper written wind power met electricity need stimulative effect ptc clear positive effect renewable energy industry substantial renewable energy source part eligible ptc short period time author noted paper author wrotethe ptc reduce price windgenerated electricity roughly year levelized basis making wind attractive electric utility investor fact ptc wind power economically attractive region country relative moreconventional electricity source creating boombust cycle time clear alternating lapse renewal wind energy ptc typically year period created cycle boom bust wind energy industry however author partly result ptc led world newly installed wind power capacity year billion invested wind project and ptc began wind plant addition represent aggregate investment roughly billion contrast sharp decline wind energy investment case ptc lapsed period time subsequently extended substantially dampening development activity wind development surely occur federal ptc due state policy effort factor historical experience suggest ptc alternative policy crucial significant nearterm growth wind market desired author stated peering future national renewable energy lab model specifically designed forecast wind deployment author noted result extending ptc stimulate wind power serve nation electricity supply ongoing congressional battle renewal wind energy ptc continued boombust cycle here chart american wind energy aweaclearly illustrating boombust cycle wind industry repercussion future action instability federal wind energy ptc severe negative repercussion wind energy market industry back repercussion hold true today congressional republican continue thwart effort renew wind energy ptc them berkeley lab paper author listed slowed wind development greater reliance foreign manufacturing difficulty rationally planning transmission expansion reduced private r&d expenditure awea recently released navigant consulting research report examining wideranging potential impact renewing wind energy ptc allowing expire have numerous study energy policy expert clear wind energy ptc large wideranging benefit economy increased wind energy investment project development sorely needed bright spot term investment economic growth green job creation time reducing dependence imported petroleum significantly increasing amount clean renewable energy produced consumed domestically yielded substantial tax revenue local state federal government passing longterm extension wind renewable energy ptc enable build trend allowing expire threaten above beg question congressional representative voting cleantechnicas completely free electric car report electric car early adopter follower want date hottest cleantech new subscribing free cleantech newsletter eye sectorspecific new also free solar energy newsletter electric vehicle newsletter wind energy newsletter tag awea berkeley lab lawrence livermore national laboratory nrel renewable energy political economy renewable energy politic renewable energy ptc wind energy wind energy policy wind energy subsidy wind energy ptc wind ptc andrew reporting writing wide range topic nexus economic technology year now asiapacific europe americas africa middle east issue related broad topical areas pose tremendous opportunity challenge define quality live relationship natural environment related post ","m_szGeo1":"United States","m_szSourceType":"source_industry","m_szSrcUrl":"http://cleantechnica.com/2012/02/18/deja-vu-all-over-again-congressional-republicans-intent-on-nixing-wind-renewable-energy-growth/","m_Places":["United States","Reliance","Asia","Europe","Africa","Middle East"],"m_People":["Nixing Wind","Obama","Ryan Wiser","Mark Bolinger","Galen Barbose"],"m_Companies":["Deja Vu","Democrats","Itc","Solar Energy","American Wind Energy Association","Awea","Department Of Treasury","Bust","2020","Navigant Consulting","Lawrence Livermore National Laboratory","Nexus"],"m_BiGrams":["wind energy","energy ptc","renewable energy","tax credit","ptc wind","wind power","eligible ptc","wind renewable","congressional republican","production tax","energy policy","energy industry","berkeley lab","boombust cycle"],"m_TriGrams":["wind energy ptc","wind renewable energy","production tax credit","renewable energy ptc"],"m_SocialTags":[],"m_Topics":[],"m_Industry":[],"m_Technology":[],"m_BiCnt":[21,12,11,6,5,5,5,4,3,3,3,3,3,3],"m_TriCnt":[9,4,3,3],"m_iDocBodyWordCnt":809}
