{"m_szDocID":"242340","m_szDocTitle":"EV Sales Up 228.88% In 2013 In US (2013 Electric & Hybrid Vehicle Sales Report) | CleanTechnica","m_szYear":"2014","m_szDocSumamry":"EV Sales Up 228.88% In 2013 In US (2013 Electric & Hybrid Vehicle Sales Report) Originally published on EV Obsession . Hybrid and electric car sales for December and 2013 as a whole have all finally come in. You can see the specific numbers above, as well as a chart showing the leading models (for Dec 2013, Dec 2012, all of 2013, and all of 2012). When you’re done having fun with the interactive chart above, below is my commentary on December sales and 2013 sales as a whole. The big, overall news is that 100% electric car sales increased 228.88% in 2013 compared to 2012. To a lesser extent — b","m_szDocBody":"sale electric hybrid vehicle sale report originally published obsession hybrid electric car sale finally specific number above chart showing leading model for youre fun interactive chart above commentary sale sale whole big new electric car sale increased% compared lesser extent notable growth plugin hybrid electric sale increased time period end annual sale electric car reached annual sale ofplugin hybrid electric vehicle wrote couple day ago biggest storey year sale rivalry nissan leaf chevy volt kicked gear price nissan leaf dropped manufacturing starting read rivalry link above exclude conventional hybrid electric vehicle which plan monthly sale report conventional hybrid simply dont benefit plugin car handful model worth term sale nissan leaf chevy volt are tesla model toyota prius plugin ford energi model sale plugin car drop steeply that tesla model sold sedan nissan leaf well sale limited supply demand battery production production part ramp bit there chevy volt andtoyota prius plugin sale dropped slightly compared due increasing competition sale ford cmax energi ford fusion energi started end beginning respectively vehicle well surely sale previously released phevs chevy toyota combined ford energi vehicle sold toyota prius plugin furthermore chevy prius plugin buyer nissan leaf nissan leaf buyer chevy prius plugin similar big nissan leaf price drop year lured potential phev customer primarily plugin car sale trend basically both however point make reason plugin car low sale poor option low sale sale market production severely limited deceiving plugin car sale artificially lower manufacturer treated seriously big year electric car model bmw egolf tesla model and mercedesbenz class electric drive bring game level increasing production capacity tesla model nissan leaf manufacturer late game that market suffer cleantechnicas completely free electric car report electric car early adopter follower want youd attend electric vehicle solar power event conducted cleantechnica date hottest cleantech new subscribing free cleantech newsletter eye sectorspecific new also free solar energy newsletter electric vehicle newsletter wind energy newsletter tag electric car sale sale hybrid car sale plug car sale acura acura ilx hybrid chevy spark chevy spark chevy spark sale chevy volt electric car sale sale fiat fiat ford ford cmax energi ford cmax energi phev ford cmax energi plugin hybrid ford cmax hybrid ford electric vehicle ford escape hybrid ford focus electric ford fusion ford fusion energi ford fusion energi phev ford fusion energi plugin hybrid ford fusion hybrid ford hybrid electric vehicle ford plugin hybrid electric vehicle honda honda accord honda accord hybrid honda accord phev honda civic honda civic hybrid honda crz honda fcx clarity honda fit honda insight hybrid car sale lincoln lincoln mkz hybrid mitsubishi mitsubishi nissan nissan leaf plug car sale porsche porsche cayenne porsche cayenne hybrid porsche electric suv porsche panamera hybrid tesla tesla model toyota prius toyota prius toyota prius liftback toyota prius phev toyota prius toyota rav volkswagen volkswagen jetta hybrid jetta jetta hybrid zachary shahan tryin and specy letter time spend time cleantechnica director chief editor otherwise enthusiastically fulfilling duty obsession gas solar love planetsave bikocity president important media zach recognised globally solar energy electric car energy storage wind energy expert speak related conference event connect social media zacharyshahancom related post ","m_szGeo1":"United States","m_szSourceType":"source_industry","m_szSrcUrl":"http://cleantechnica.com/2014/01/07/ev-sales-228-88-2013-2013-electric-hybrid-vehicle-sales-report/","m_Places":["Us","Sale","Toyota","Tesla"],"m_People":["Ev Sales","Chevy Volt","Ford , Ford C-max Energi","Zachary Shahan"],"m_Companies":["Bmw","I3","Mercedes-benz","Honda","Honda Cr-z"],"m_BiGrams":["car sale","electric car","nissan leaf","electric vehicle","toyota prius","hybrid electric","ford fusion","plugin car","prius plugin","hybrid ford","plugin hybrid","chevy volt","tesla model","ford cmax","cmax energi","fusion energi","energi ford","chevy spark","prius toyota"],"m_TriGrams":["electric car sale","hybrid electric vehicle","ford cmax energi","ford fusion energi"],"m_SocialTags":[],"m_Topics":[],"m_Industry":[],"m_Technology":[],"m_BiCnt":[10,9,8,7,7,6,6,5,5,5,4,4,4,4,4,4,3,3,3],"m_TriCnt":[4,3,3,3],"m_iDocBodyWordCnt":518}
