{"m_szDocID":"242429","m_szDocTitle":"The Federal Solar Tax Credit Extension: Can We Win if We Lose? | CleanTechnica","m_szYear":"2015","m_szDocSumamry":"The Federal Solar Tax Credit Extension: Can We Win if We Lose? September 9th, 2015 by John Farrell   Originally posted at ilsr.org . In 16 months, the solar industry faces the end of the line for the 30% federal tax credit. The Investment Tax Credit will fall to 10% for businesses and to zero for residential solar customers. Some have called this the “solar cliff.” There may be a silver lining in this tax credit expiration cloud, but it’s still a bad idea. A Good Deal with a Wall St. Hitch The 30%-off-solar-via-your-taxes deal has been available for almost 10 years, following an 8-year extensi","m_szDocBody":"federal solar tax credit extension win lose john farrell originally posted ilsrorg month solar industry face end line federal tax credit investment tax credit fall businesse residential solar customer called solar cliff silver lining tax credit expiration cloud bad idea good deal wall hitch %offsolarviayourtaxe deal year year extension crucial tool made solar energy costcompetitive conventional electricity generation encouraging deployment solar pushed hardware price installer experience also lowering cost chart show tax credit lowered cost solar energy compared tax credit drawback potential solar owner ineligible lacked sufficient tax liability american dont annual tax liability absorb year including city county nonprofit organisation forprofit businesse insufficient tax liability sought tax equity partner wall street bank seeking way offset massive profitinduced tax bill course tax equity partner price contribute capital solar project exchange tax incentive required aftertax return drove project cost end cent dollar tax incentive the credit depreciation absorbed solar project itself wall street partner additionally complexity accessing tax incentive led contract party rooftop solar array inflate cost solar one tax credit based cost system giving developer capture tax credit incentive inflate system price evidence thatusing tax law trickerysolar developer bank second competing solar quote complicated timeconsuming party competing incumbent utility developer thus price low give electric customer deal utility pocketing difference chart show solar purchase agreement save customer money compared buying utility provider claiming saving assume electricity price rise year ppa price rise year dark cloud losing tax credit drawback article energy trade press noted potential impact losing federal tax credit reducing competitiveness solar killing marginal market state california york chart show loss tax credit holding equal reduce competitiveness solar energy utility electric price state changed loss tax credit significantly reduced development solar glide path alternative biggest problem sudden change solar incentive disappeared before utility offer solar rebate incentive payment state programme shut down california solar initiative illustration transparency predictability incentive stepped market growth stepped see chart below consideration regional difference solar resource hawaii york arizona longer tax incentive solar compete grid electricity price see gtm chart above state tax credit allowed expire resident solar competitive state number continue grow solar cost continued fall silver lining losing tax credit solar market benefit ending tax incentive efficiency gain method expiration undesirable impact shortterm benefit solar industry one make efficient comment sunedison ceo jigar shah top percent solar provider time volume percent player business simply software tool efficient eliminating middlemen additionally cutting tax equity middleman offset tax credit camilo patrignani ceo greenwood energy made wave assertion early postitc solar developer easier bring debt financing project increase levered return investor itc attract investor reducing project cost adding tax benefit complicate deal adding tax equity investor equation solar cost fall project packaged simplified traditional investment debt equity secured asset longterm return data back national renewable energy laboratory released study showing power purchase agreement ppa financing term combining party ownership tax equity mean higher price residential customer year power purchase agreementbuying solar energy party solar array rooftop costly loan return requirement equity partner similar monthly payment commercial customer difference stark year power purchase price premium year loan comparable annual payment are course factor customer prefer party ownership businesse purchasing party benefit businesse transaction balance sheet inverter replacement unlikely maintenance handled party although cost replacement included model year finally party arrangement mean solar customer doesnt sufficient tax liability absorb tax credit although customer level income lack creditworthiness secure party deal factor favour ownership interest rate loan affected customer fico score credit customer loan interest rate point lower poor credit customer rate point higher change cost estimate kilowatthour direction though enough itself change outcome solar loan deductible interest lower cost ownership confer longer term benefit life solar array year person financing solar loan year free energy lowering annual average cost increasing lowcost financing big promise lowcost solar financing crowd financing institutional investor represent individual grasp complexity solar invest traditional channel federal state law remove barrier crowd financing clean energy and businesse crowd funding investment opposed donation model kickstarter slow develop institutional investor pension college endowment fund large portfolios diverse stable return attracting potentially lowcost investor arent interested return based tax incentive smallscale investment solar security invest multimillion dollar pool solar loan lease similar risk profile slow develop far party financier solarcity securitized residential solar asset pooled solar securitization held back largely lack standardised documentation difficulty analysing creditworthiness disparate developer source say additionally focus tax equity financing federal tax credit drawn attention lowcost financing investor solar security tax credit barrier financing loss gain let tension lowcost financing tax credit kilowatt residential solar project len residential project tucson installed watt year financing cost federal tax credit cost solar electricity kilowatthour tax credit financing year chosen lower monthly payment cost solar electricity higher additionally availability lowcost longterm financing and lack hassle filing tax credit residential commercial electric customer instal solar owner party arrangement marginally higher cost offset saving cutting middleman here remake chart comparing ownership ppa earlier filled cost figure tucson assume electricity price inflation ppa price inflation solar tax credit depart heart democratise ownership solar market continue grow bottom line killing tax credit favour coal gas nuclear number solar survive thrive federal tax incentive let real key role tax credit fix market failure fossil fuel and nuclear electric power provider allowed socialise pollution cost extraction combustion longterm waste storage contrast solar socialise sunshine word killing incentive solar tax code reward political contribution fossil fuel industry tax credit remain lousy provide incentive clean energy way fix fossil fuel favouritism energy market sunset solar tax incentive originally posted ilsrorg timely update follow john farrell democratic energy weekly update photo creditsfossil fuel externality left right nate dispatch york time mark gallagher flickr cleantechnicas completely free electric car report electric car early adopter follower want youd attend electric vehicle solar power event conducted cleantechnica date hottest cleantech new subscribing free cleantech newsletter eye sectorspecific new also free solar energy newsletter electric vehicle newsletter wind energy newsletter tag electricity financing itc securitization solar itc solar tax credit tax credit john farrell direct democratic energy programme ilsr focuse energy policy development expand benefit local ownership dispersed generation renewable energy seminal paper democratising electricity system describe blast roadblock distributed renewable energy generation smallscale renewable energy project key biggest stride renewable energy development farrell authored landmark report energy selfreliant state serve definitive energy atlas united state detailing statebystate renewable electricity generation potential farrell regularly discussion analysis distributed renewable energy policy blog energy selfreliant state energyselfreliantstatesorg article regularly syndicated grist renewable energy world john farrell found related post ","m_szGeo1":"United States","m_szSourceType":"source_industry","m_szSrcUrl":"http://cleantechnica.com/2015/09/09/federal-solar-tax-credit-extension-can-win-lose/","m_Places":["Wall Street","California","New York","Hawaii","Arizona","Barrier","Tucson, Az","Tucson","United States"],"m_People":["John Farrell","Jigar Shah","Camilo Patrignani","Nate Beeler"],"m_Companies":["Sunedison","Itc","National Renewable Energy Laboratory","Fico","Institutional Investors","Solarcity","Pooled","Bottom Line","Twitter","Columbus Dispatch","New York Times","Flickr"],"m_BiGrams":["tax credit","tax incentive","renewable energy","tax equity","solar tax","federal tax","solar energy","john farrell","cost solar","tax liability","residential solar","chart show","equity partner","solar project","solar array","electricity price","power purchase","solar loan","lowcost financing","fossil fuel"],"m_TriGrams":["federal tax credit"],"m_SocialTags":[],"m_Topics":[],"m_Industry":[],"m_Technology":[],"m_BiCnt":[28,8,7,6,5,5,5,4,4,4,3,3,3,3,3,3,3,3,3,3],"m_TriCnt":[4],"m_iDocBodyWordCnt":1079}
