{"m_szDocID":"242773","m_szDocTitle":"Cybersecurity is Key to our Clean Energy Future","m_szYear":"2014","m_szDocSumamry":"textArticle -------------------- Cybersecurity is Key to our Clean Energy Future March 10, 2014 by NRDC Switchboard Leave a Comment Allison Clements, Senior Attorney, Project for Sustainable FERC Energy Policy, New York Noting that experts generally agree the risk of a large-scale cyber attack on America’s electricity transmission grid “is significant and must be addressed,” a new report by the Bipartisan Policy Center (BPC)’s Electric Grid Cybersecurity Initiative recommends that government and industry work together to put strong protections in place. This week, Department of Energy (DOE) Se","m_szDocBody":"cybersecurity key clean energy future nrdc switchboard leave comment allison clement senior attorney project sustainable ferc energy policy york noting expert generally agree risk largescale cyber attack americas electricity transmission grid significant addressed report bipartisan policy centre bpc electric grid cybersecurity initiative recommend government industry work put strong protection place week department energy doe secretary moniz underscored make progress boosting funding proposed budget cybersecurity work focus role federal energy regulatory commission ferc play transformation lowcarbon future clean energy economy worth stepping standard fare highlight critical importance cybersecurity achieve clean resilient grid addressing cyber threat head first cyber attack dont youd surprised definition cyber attack bpc report released week define cyber attack transmission grid attempt variety malicious actor for example terrorist organisation external hacker foreign nation disrupt grid operation damage infrastructure steal information grid system bpc report fbis cyber attack eclipsing terrorism primary threat facing united state electric grid regulator ferc nerc state subjected transmission grid owner strong reliability protection address unexpected increase customer demand electricity unexpected generation transmission line outage and increasingly ensure resilience face bad weather however cyber attack represent threat grid reliability unpredictable number way create massive power disruption widespread areas country short existing reliability protection arent sufficient defence wellexecuted cyber attack protect cyber attack emerging cyber threat grid owner regulator policymaker working hard wise protection implemented quickly bpc initiative put expert assess threat including cochair general ret michael hayden director cia curt hebert ferc chairman susan tierney department energy assistant secretary massachusett regulator make recommendation strengthen grid increase potential attack preparedness including development publicprivate partnership improve information flow government industry innovative incentive insurance market improve cybersecurity tool utility economic regulator evaluate cybersecurity investment clarity government chain command event attack cyber security relate clean lowcarbon grid climate change cyber threat pose potentially dire risk national security modernising creating clean lowcarbon grid hand hand accomplished increase protection grid cyber threat installation smart grid hardware software key requirement decarbonizing modernization technology grid operator data system increase efficiency resiliency increase role rooftop solar panel electric vehicle appliance distributed onsite generation higher grid efficiency marginal fossilfueled generation online way advantage clean cheap renewable power wind solar technology strengthen grid reliability making robust face severe weather resilient response however bpc report recognise intelligent grid system add layer complexity contribute grid vulnerability face cyber attack recognising protect cyber threat integrating smart grid technology broadly ensure exposure minimum bpc bipartisan thinking informed intersection environmental reliability policy year now served cochair bpc previous electric grid initiative produced set policy recommendation achieve cleanenergy future maintaining grid reliability week report cybersecurity bpc produced excellent roadmap grid future see doe secretary moniz person washington interested reading bpc work logged post comment logged post comment energy collective column coming soon latest comment schalk cloete seeking consensus externalised cost gas data average externalised cost transport fuel natural gas calculated june schalk cloete seeking consensus externalised cost gas data average externalised cost heat natural gas calculated article june schalk cloete seeking consensus externalised cost gas data global average externalised cost gas fired electricity plant june roger arnold treasure sierra nevada noticed map lake lahontan talked survive june advisory panel scott edward anderson consultant blogger media commentator blog green sceptic christine hertzog consultant author professional explainer focused smart grid elias hinckley strategic advisor energy finance energy policy investor energy company government gary hunt gary executiveinresidence deloitte investment extensive experience energy utility industry jesse jenkin graduate student researcher mit expertise energy technology policy innovation jim pierobon help trade government agency company communicate cleaner energy solution geoffrey style managing director gsw strategy group llc awardwinning blogger featured contributor june june ","m_szGeo1":"United Kingdom","m_szSourceType":"source_industry","m_szSrcUrl":"http://www.theenergycollective.com/nrdcswitchboard/351461/cybersecurity-key-our-clean-energy-future","m_Places":["New York","America","United States","Massachusetts","Washington","Gary"],"m_People":["Allison Clements","Moniz","Michael Hayden","Curt Hebert","Susan Tierney","Roger Arnold","Scott Edward","Christine Hertzog","Elias Hinckley","Hunt Gary","Jesse Jenkins","Jim Pierobon","Geoffrey Styles"],"m_Companies":["Energy Future","Ferc","Policy Center","Bpc","Department Of Energy","Doe","Federal Energy Regulatory Commission","Fbi","Nerc","Cia","Sierra Nevada","Deloitte","Strategy Group, Llc"],"m_BiGrams":["cyber attack","externalised cost","cyber threat","cost gas","transmission grid","electric grid","bpc report","grid reliability","smart grid","schalk cloete","cloete seeking","seeking consensus","consensus externalised","gas data","average externalised"],"m_TriGrams":["externalised cost gas","schalk cloete seeking","cloete seeking consensus","seeking consensus externalised","consensus externalised cost","cost gas data","average externalised cost"],"m_SocialTags":[],"m_Topics":[],"m_Industry":[],"m_Technology":[],"m_BiCnt":[9,6,5,4,3,3,3,3,3,3,3,3,3,3,3],"m_TriCnt":[4,3,3,3,3,3,3],"m_iDocBodyWordCnt":595}
