{"m_szDocID":"242980","m_szDocTitle":"Fuel Economy Continues Upward Climb to New Record","m_szYear":"2014","m_szDocSumamry":"textArticle -------------------- Fuel Economy Continues Upward Climb to New Record October 10, 2014 by NRDC Switchboard Leave a Comment Luke Tonachel, Vehicles Analyst, New York City The U.S. Environmental Protection Agency has crunched the numbers and the fleet of cars and light trucks sold with model year 2013 hit a new record of 24.1 miles per gallon (mpg). The latest Fuel Economy Trends report finds that automakers are producing more fuel-saving vehicles to keep up with clean car and fuel economy standards. This is good news for the environment. By burning less fuel, the more efficient new","m_szDocBody":"fuel economy continue upward climb record nrdc switchboard leave comment luke tonachel vehicle analyst york city environmental protection agency crunched number fleet car light truck sold model year hit record mile gallon mpg latest fuel economy trend report find automaker producing fuelsaving vehicle clean car fuel economy standard good new environment burning fuel efficient car fleet avoid emission million tonne carbon pollution year consumer benefit too year earlier passenger car averaged mpg assuming gas price gallon mpg jump mpg save typical driver year driving credit epa fuel economy trend surprise consumer fuel economy recent survey national automobile dealer association fuel economy number factor considered shopper car light truck purchase consumer federation america expect ongoing trend car buyer seek higher fuel efficiency purchase fuel economy leader laggard exception ford toyota manufacturer increased fleet average fuel economy shown below nissan achieved biggest improvement mpg boost moved automaker ranking hyundai kia presented table epa reaches full resolution prior improper fuel economy data submittal vehicle included actual performance expected put top credit epa fuel economy trend compared ford improved fuel economy car truck shift higher truck production volume reduced fleet average similarly improvement toyota truck fuel economy greater production share larger lower fuel economy vehicle reduced manufacturer fleet average preliminary data model year fleet average expected make modest increase mpg watch context potentially larger improvement model year vehicle arriving showroom now multiyear product design cycle fleet improvement dont follow trajectory year year fuel efficient option consumer recently model clear consumer choose expanding list fuelefficient car light truck car model achieving mpg tripled year car model exceeding mpg increased factor due growth hybrid plugin hybrid electric battery electric vehicle offered credit epa fuel economy trend fuelsaving technology deployment performance sacrifice automaker ramping fuel economy increasing deployment technology conventional internal combustion engine vehicle introduced limited model efficient gasoline direct injection engine roughly fleet transmission advanced gear engine operate frequently efficient point road condition change percent transmission speed now percent speed percent speed percent transmission continuously variable allowing efficiency optimization fuel economy trend data show fuel efficiency achieved maintaining vehicle performance measure mile hour acceleration compared calculation starting fleet epa expect vehicle fastest mph time averaging second credit epa fuel economy trend building future clean car fuel economy standard continue strengthen reaching equivalent mpg laboratory test standard set clear trajectory market certainty guide auto industry investment fuelsaving technology promote continued innovation shown below significant portion current fleet meet future standard credit epa fuel economy trend fuel economy reaching height year automobile guzzling gas saving consumer money reducing carbon pollution producing cleaner efficient car move direction helping strengthen economy protect environment related post logged post comment logged post comment energy collective column coming soon latest comment schalk cloete seeking consensus externalised cost gas data average externalised cost transport fuel natural gas calculated june schalk cloete seeking consensus externalised cost gas data average externalised cost heat natural gas calculated article june schalk cloete seeking consensus externalised cost gas data global average externalised cost gas fired electricity plant june roger arnold treasure sierra nevada noticed map lake lahontan talked survive june advisory panel scott edward anderson consultant blogger media commentator blog green sceptic christine hertzog consultant author professional explainer focused smart grid elias hinckley strategic advisor energy finance energy policy investor energy company government gary hunt gary executiveinresidence deloitte investment extensive experience energy utility industry jesse jenkin graduate student researcher mit expertise energy technology policy innovation jim pierobon help trade government agency company communicate cleaner energy solution geoffrey style managing director gsw strategy group llc awardwinning blogger featured contributor june june ","m_szGeo1":"United Kingdom","m_szSourceType":"source_industry","m_szSrcUrl":"http://www.theenergycollective.com/nrdcswitchboard/2137861/fuel-economy-continues-upward-climb-new-record","m_Places":["New York City","Toyota","Gary"],"m_People":["Luke Tonachel","Roger Arnold","Scott Edward","Christine Hertzog","Elias Hinckley","Hunt Gary","Jesse Jenkins","Jim Pierobon","Geoffrey Styles"],"m_Companies":["U.s. Environmental Protection Agency","Epa","National Automobile Dealers Association","Consumer Federation Of America","Hyundai","Ramping","Sierra Nevada","Deloitte","Strategy Group, Llc"],"m_BiGrams":["fuel economy","economy trend","externalised cost","credit epa","epa fuel","fleet average","cost gas","car light","light truck","model year","schalk cloete","cloete seeking","seeking consensus","consensus externalised","gas data","average externalised"],"m_TriGrams":["fuel economy trend","credit epa fuel","epa fuel economy","externalised cost gas","car light truck","schalk cloete seeking","cloete seeking consensus","seeking consensus externalised","consensus externalised cost","cost gas data","average externalised cost"],"m_SocialTags":[],"m_Topics":[],"m_Industry":[],"m_Technology":[],"m_BiCnt":[20,7,6,5,5,4,4,3,3,3,3,3,3,3,3,3],"m_TriCnt":[7,5,5,4,3,3,3,3,3,3,3],"m_iDocBodyWordCnt":591}
