{"m_szDocID":"243361","m_szDocTitle":"Planes, Trains, & Pretty Much Everything Else More Efficient Than Cars | CleanTechnica","m_szYear":"2014","m_szDocSumamry":"Planes, Trains, & Pretty Much Everything Else More Efficient Than Cars January 14th, 2014 by Joshua S Hill   A new report released by a research professor at the University of Michigan Research Institute looking at data collected from 1970 to 2010 has shown that pretty much every form of transportation is more efficient than the good old-fashioned light-duty vehicle. Michael Sivak examined recent trends to determine the energy needed to transport a single person a given distance in a light-duty vehicle — ie, cars, SUVs, pickups, and vans — or on a scheduled airline flight. His analysis was mea","m_szDocBody":"plane train pretty efficient car joshua hill report released research professor university michigan research institute data collected shown pretty form transportation efficient good oldfashioned lightduty vehicle michael sivak examined recent trend determine energy needed transport single person distance lightduty vehicle car suvs pickup van scheduled airline flight analysis measured btu person mile found entire fleet lightduty vehicle improve mile gallon efficiency increase vehicle load person person flight easy achieve change sivak fuel economy vehicle continuously improving accelerate corporate average fuel economy standard fuel economy long time substantially influence fuel economy entire fleet take long time turn fleet long turn fleet lightduty vehicle sold million vehicle amounted teh entire fleet light vehicle road historical perspective illustrate daunting task said improvement percent vehicle fuel economy entire fleet lightduty vehicle required vehicle fuel economy improved percent important recognise energy intensity flying continue improve sivak said future energy intensity flying calculation underestimate improvement achieved order driving energyintensive flying all unsurprising car inefficient are sivak analysis found that btu person mile driving versus flying thenamtrak train motorcycle transit buse cleantechnicas completely free electric car report electric car early adopter follower want youd attend electric vehicle solar power event conducted cleantechnica date hottest cleantech new subscribing free cleantech newsletter eye sectorspecific new also free solar energy newsletter electric vehicle newsletter wind energy newsletter tag university michigan joshua hill christian nerd geek pretty quickly directing planetearth hell handbasket write fantasy book review couk found writing article variety site cheque aboutme more related post survey reveal american attitude energy environment justdoit airplane efficient those actually airplane passenger car buse ferry sad equivalent highest level airplane surprising source eklad true why guest airplane efficient actually airplane passenger car buse ferry sad equivalent highest level airplane surprising source hari year clean technica commented electric vehicle developed solely public transport individual use stick car inefficent mode transport create pollution dirty engine oil dangerous speed stop wasting time scarce resource creating electric car individual use design highly efficient mass transport systemsfor public moving road benjamin nead ive study comparing air travel train travel car conclusion and yes dont jetliner corner grocery store train make good transoceanic vehicle long ago however addresse inefficient aspect travelling plane amount fuel needed simply taxi airport pre post flight electrified set landing gear wheel touted make significant fuel saving large jet aircraft move ground bigwu evs consume mile btus mile based number article single driver efficient flying efficient riding amtrak eject depend bit calculate mile btu battery btu charge battery create power place sort life cycle analysis plane train hard beat constantly going dont buy plane train sitting perfectly happy car doing plane spend time air sitting around make initial energy investment broken life cycle small train plane makeover service decade big recycling efficient life cycle bobwallace subtract energy lost battery charging rest doesnt apply btu doesnt include energy lost fuel eject lot lost charging cheque forum people measure plug stored battery random blog post number hand list drawn battery replace still beat petrol huge margin lot single phase wallbox efficient realistic scenario home owner phase charging efficient higher power submitted require heatpump running car heat battery mre efficient charging warmer battery temperature depending type battery resistance increase losse leading increase temperature sort consideration fueling mode transport well stated depend calculated complex topic simply car matter technology propel beat proper sized aeroplane mode transport climbing amount energy needed maintain speed stated minimum distance needed beat car depend lot variable neroden loss charging tesla pretty bad energy losse theyre due vampire drain basically electronic operating car isnt moving steeple dissect flight range make sense efficient fly long distance cruising time offset inefficiency climb out range mile flying energy efficient tibi stibi indeed taking plane grocery efficient neroden dream personal aircraft running errand crazy stuff jouni valkonen ","m_szGeo1":"United States","m_szSourceType":"source_industry","m_szSrcUrl":"http://cleantechnica.com/2014/01/14/planes-trains-pretty-much-everything-else-efficient-cars/","m_Places":["Uk","Tesla"],"m_People":["Joshua S Hill","Michael Sivak","Benjamin Nead","Jouni Valkonen"],"m_Companies":["University Of Michigan","Research Institute","Amtrak","Technica","Indeed"],"m_BiGrams":["fuel economy","lightduty vehicle","entire fleet","plane train","fleet lightduty","electric car","electric vehicle","mode transport","life cycle"],"m_TriGrams":["fleet lightduty vehicle"],"m_SocialTags":[],"m_Topics":[],"m_Industry":[],"m_Technology":[],"m_BiCnt":[6,5,4,3,3,3,3,3,3],"m_TriCnt":[3],"m_iDocBodyWordCnt":628}
