{"m_szDocID":"243688","m_szDocTitle":"YieldCos Could Cut Renewables Costs by 20%, Study Finds","m_szYear":"2013","m_szDocSumamry":"textArticle -------------------- YieldCos Could Cut Renewables Costs by 20%, Study Finds June 30, 2014 by Katherine Tweed Leave a Comment Financial innovation has unlocked distributed solar and helped to drive down costs in recent years, but there is also ample room for new investment vehicles for large-scale wind and solar, according to a new study. Widespread use of YieldCos should allow for wind and solar costs to drop by more than 20 percent compared to current project finance models, according to the Climate Policy Initiative’s paper, Roadmap to a Low Carbon Electricity System .   YieldCo","m_szDocBody":"yieldcos cut renewable cost study find katherine tweed leave comment financial innovation unlocked distributed solar helped drive cost recent year ample room investment vehicle largescale wind solar study widespread yieldcos wind solar cost drop percent compared current project finance model climate policy initiative paper roadmap low carbon electricity system yieldcos earn cash flow based real asset earning dividend offering yield investor lowercost capital renewable energy project yieldcos launched recently including offering nrg yield greencoat energy pattern energy nextera yieldco limitation utility financing funding renewable energy project utility face potentially pressing one transmission distribution investment system balancing market operation area utility business model ripe transformation research climate policy initiative found reason utility financing suited renewable energy project current model adapted financing fossil fuel asset uday varadarajan senior analyst climate policy initiative asset profile risk reward solar wind project operational risk fuel risk fossil fuel plant paying industry premium operating lowerrisk asset varadarajan utilityscale renewable energy project funded project finance developer set project company borrow money cash flow project investorowned utility independent power producer equity borrowing power finance project billion total billion lowcarbon investment including renewable energy energy efficiency electric vehicle project balance sheet financing projectlevel financing cpi growing pain yieldcos paper bullish ability yieldcos drive cost largescale renewable outline challenge persist yieldcos renewable market ppas support continued growth yieldco market asked varadarajan institutional investor biting these limitation growing pain yieldcos renewable energy novel issue work coming year cpi outlined feature yieldco have provide highly predictable longterm cash flow include paying free cash generated underlying project yieldco owner retaining substantial portion invest project owning diversified set project investing operational asset provide liquidity investment yieldco exchangetraded large set investor attract financial sector analysis provide investment low fee cpi note drawback institutional investor current yieldcos cost fee established part portfolio option institutional investor way growing pain yieldcos work investor financial regulator develop yieldco asset class maturity deal issue varadarajan adding ideally yieldcos spin closed fund yieldcos mature rapidly role green bank connecticut york added varadarajan question yieldcos vehicle unlock midtier market renewable smaller utility scale larger residential yieldcos large izzet bensusan founder ceo karbone renewable energy finance forum wall street wednesday mean broad project selection live investor expectation role municipality yieldcos play interesting role utilityscale renewable project coming year potential role municipality cpi found wind solar bondlike investment varadarajan municipal bond financing renewable project pointed los angele department water power prepaid powerpurchase agreement wind power milford wind farm utah southern california public power authority municipal taxexempt bond approach attractive europe noted unlike institutional investor municipality invest directly renewable energy project liquidity concern invest infrastructure study author wrote municipal financing supported infrastructure green bank smaller municipality capital report focuse largescale renewable project areas market financial innovation needed yieldcos directly finance asset gridbalancing technology energy efficiency yieldcos trojan horse rest this varadarajan yieldcos demandside shift coming rest follow rational investor response greentech media gtm produce industryleading new research conference businesstobusiness greentech market coverage areas include solar smart grid energy efficiency wind nonincumbent energy market information visit greentechmediacom follow twitter facebook related post logged post comment logged post comment energy collective column coming soon latest comment schalk cloete seeking consensus externalised cost gas data average externalised cost transport fuel natural gas calculated june schalk cloete seeking consensus externalised cost gas data average externalised cost heat natural gas calculated article june schalk cloete seeking consensus externalised cost gas data global average externalised cost gas fired electricity plant june roger arnold treasure sierra nevada noticed map lake lahontan talked survive june advisory panel scott edward anderson consultant blogger media commentator blog green sceptic christine hertzog consultant author professional explainer focused smart grid elias hinckley strategic advisor energy finance energy policy investor energy company government gary hunt gary executiveinresidence deloitte investment extensive experience energy utility industry jesse jenkin graduate student researcher mit expertise energy technology policy innovation jim pierobon help trade government agency company communicate cleaner energy solution geoffrey style managing director gsw strategy group llc awardwinning blogger featured contributor june june ","m_szGeo1":"United Kingdom","m_szSourceType":"source_industry","m_szSrcUrl":"http://www.theenergycollective.com/katherinetweed/409221/yieldcos-could-cut-renewables-costs-20-study-finds","m_Places":["Most","Connecticut","New York","Wall Street","Milford","Utah","Southern California","Europe","United States","Gary"],"m_People":["Katherine Tweed","Uday Varadarajan","Izzet Bensusan","Roger Arnold","Scott Edward","Christine Hertzog","Elias Hinckley","Hunt Gary","Jesse Jenkins","Jim Pierobon","Geoffrey Styles"],"m_Companies":["Nrg","The Thing","Karbone Group","Los Angeles Department Of Water And Power","Facebook","Sierra Nevada","Deloitte","Strategy Group, Llc"],"m_BiGrams":["renewable energy","externalised cost","energy project","institutional investor","cost gas","wind solar","climate policy","policy initiative","cash flow","growing pain","pain yieldcos","renewable project","schalk cloete","cloete seeking","seeking consensus","consensus externalised","gas data","average externalised"],"m_TriGrams":["renewable energy project","externalised cost gas","climate policy initiative","growing pain yieldcos","schalk cloete seeking","cloete seeking consensus","seeking consensus externalised","consensus externalised cost","cost gas data","average externalised cost"],"m_SocialTags":[],"m_Topics":[],"m_Industry":[],"m_Technology":[],"m_BiCnt":[8,6,5,4,4,3,3,3,3,3,3,3,3,3,3,3,3,3],"m_TriCnt":[5,4,3,3,3,3,3,3,3,3],"m_iDocBodyWordCnt":662}
