{"m_szDocID":"243787","m_szDocTitle":"China’s Installed PV To Reach 10 GW By End Of Year","m_szYear":"2013","m_szDocSumamry":"textArticle -------------------- China’s Installed PV To Reach 10 GW By End Of Year December 11, 2013 by Joshua Hill 1 Comment   Chinese state news has announced that the country’s on-grid solar power capacity will reach 10 GW by the end of 2013, a 200% increase from a year ago, based on figures forecast by the National Energy Administration. The total energy generation capacity of the Chinese power grid is expected to reach 1,235 GW by the end of this year, with solar’s 10 GW making up an estimated 69.9% — down from 2012′s 71.5%, despite growth — while hydro is expected to make up 25.5%, grid","m_szDocBody":"chinas installed reach end year joshua hill comment chinese state new announced country ongrid solar power capacity reach end increase year ago based figure forecast national energy administration total energy generation capacity chinese power grid expected reach end year solar making estimated growth hydro expected make grid wind nuclear state new agency xinhua noted china number measure including increasing investment clean energy boost share nonfossil fuel power structure npd solarbuzz projected year china top deployment predicting combined demand china japan expected reach half record level shipment china japan coincide corporate margin returning positive territory final shakeout phase uncompetitive manufacturer nearing completion finlay colville vice president npd solarbuzz entered highly cautious outlook tierone supplier poised exit year restored confidence ahead optimistic shipment margin guidance year china stated intended add solar power year year boosting coutnry solar capacity china recently announced intended stretch distributedsolar capacity target time date latest electric vehicle insight new closely watching solar power channel subscribing solar power newsletter coming soon latest comment schalk cloete seeking consensus externalised cost gas data average externalised cost transport fuel natural gas calculated june schalk cloete seeking consensus externalised cost gas data average externalised cost heat natural gas calculated article june schalk cloete seeking consensus externalised cost gas data global average externalised cost gas fired electricity plant june roger arnold treasure sierra nevada noticed map lake lahontan talked survive june advisory panel scott edward anderson consultant blogger media commentator blog green sceptic christine hertzog consultant author professional explainer focused smart grid elias hinckley strategic advisor energy finance energy policy investor energy company government gary hunt gary executiveinresidence deloitte investment extensive experience energy utility industry jesse jenkin graduate student researcher mit expertise energy technology policy innovation jim pierobon help trade government agency company communicate cleaner energy solution geoffrey style managing director gsw strategy group llc awardwinning blogger featured contributor june ","m_szGeo1":"United Kingdom","m_szSourceType":"source_industry","m_szSrcUrl":"http://www.theenergycollective.com/joshshill/314226/china-s-installed-pv-reach-10-gw-end-year","m_Places":["China","Atmosphere","Japan","Gary"],"m_People":["Joshua Hill","Finlay Colville","Roger Arnold","Scott Edward","Christine Hertzog","Elias Hinckley","Hunt Gary","Jesse Jenkins","Jim Pierobon","Geoffrey Styles"],"m_Companies":["National Energy Administration","Xinhua","Npd","Target","Sierra Nevada","Deloitte","Strategy Group, Llc"],"m_BiGrams":["externalised cost","solar power","cost gas","reach end","schalk cloete","cloete seeking","seeking consensus","consensus externalised","gas data","average externalised"],"m_TriGrams":["externalised cost gas","schalk cloete seeking","cloete seeking consensus","seeking consensus externalised","consensus externalised cost","cost gas data","average externalised cost"],"m_SocialTags":[],"m_Topics":[],"m_Industry":[],"m_Technology":[],"m_BiCnt":[6,4,4,3,3,3,3,3,3,3],"m_TriCnt":[4,3,3,3,3,3,3],"m_iDocBodyWordCnt":306}
