{"m_szDocID":"243822","m_szDocTitle":"Would GOP Budget Ax Cut Clean Tech?","m_szYear":"2011","m_szDocSumamry":"textArticle -------------------- Would GOP Budget Ax Cut Clean Tech? January 6, 2011 by Josh Freed Leave a Comment Taking House Republicans at face value on their pledge to cut 20% of  all non-defense discretionary spending, we took a quick look at what  cuts might mean for America’s ability to compete in the $2 trillion  clean energy market.  While there are certainly areas of the nation’s  energy budget that should get cut or eliminated, to achieve $100 billion  in savings every program — even those that help fuel the economic  growth the new majority says it wants — is going to suffer. Than","m_szDocBody":"gop budget cut clean tech josh freed leave comment taking house republican face pledge cut nondefense discretionary spending quick cut americas ability compete trillion clean energy market areas nation energy budget cut eliminated achieve billion saving programme fuel economic growth majority suffer smart government investment clean energy businesse ground expanding mean job created dow battery plant michigan nissan electric vehicle tennessee southern company build nuclear reactor georgia chop like billion cut federal loan guarantee programme potentially cripple muchneeded nuclear renaissance time china planning fivefold expansion decade loan guarantee wed building nuclear power plant year creating job georgia today million arpae meagre million budget gutting funding advanced energy storage generation nuclear power microbattery technology military eliminating million grant company innovating renewable energy advanced vehicle technology battery storage kill emerging clean energy businesse potential century google general electric exxon slicing million r&d investment school purdue university penn state university wisconsin iowa state university developing generation innovator ideas spawn businesse job conservative columnist george ringing alarm bell warned house freshmen making government lean cutting defensible productive federal spending akin making overweight aircraft flightworthy removing engine cutting uss meagre innovation budget troubling vacuum clean energy crowded global marketplace economic competitor china south korea japan increasing clean tech funding fuel growth making tough decision areas slash budget deficit related post logged post comment logged post comment energy collective column coming soon latest comment schalk cloete seeking consensus externalised cost gas data average externalised cost transport fuel natural gas calculated june schalk cloete seeking consensus externalised cost gas data average externalised cost heat natural gas calculated article june schalk cloete seeking consensus externalised cost gas data global average externalised cost gas fired electricity plant june roger arnold treasure sierra nevada noticed map lake lahontan talked survive june advisory panel scott edward anderson consultant blogger media commentator blog green sceptic christine hertzog consultant author professional explainer focused smart grid elias hinckley strategic advisor energy finance energy policy investor energy company government gary hunt gary executiveinresidence deloitte investment extensive experience energy utility industry jesse jenkin graduate student researcher mit expertise energy technology policy innovation jim pierobon help trade government agency company communicate cleaner energy solution geoffrey style managing director gsw strategy group llc awardwinning blogger featured contributor june june ","m_szGeo1":"United Kingdom","m_szSourceType":"source_industry","m_szSrcUrl":"http://www.theenergycollective.com/joshfreed/49468/would-gop-budget-ax-cut-clean-tech","m_Places":["America","United States","Michigan","Tennessee","Georgia","China","Uk","South Korea","Japan","Gary"],"m_People":["Roger Arnold","Scott Edward","Christine Hertzog","Elias Hinckley","Hunt Gary","Jesse Jenkins","Jim Pierobon","Geoffrey Styles"],"m_Companies":["House Republicans","Southern Company","Georgia Today","Us Military","Google","General Electric","Exxon","Purdue University","Penn State","University Of Wisconsin","Iowa State University","Sierra Nevada","Deloitte","Strategy Group, Llc"],"m_BiGrams":["externalised cost","clean energy","cost gas","schalk cloete","cloete seeking","seeking consensus","consensus externalised","gas data","average externalised"],"m_TriGrams":["externalised cost gas","schalk cloete seeking","cloete seeking consensus","seeking consensus externalised","consensus externalised cost","cost gas data","average externalised cost"],"m_SocialTags":[],"m_Topics":[],"m_Industry":[],"m_Technology":[],"m_BiCnt":[6,4,4,3,3,3,3,3,3],"m_TriCnt":[4,3,3,3,3,3,3],"m_iDocBodyWordCnt":371}
