{"m_szDocID":"243823","m_szDocTitle":"ARPA-E: The Little Program that Can","m_szYear":"2010","m_szDocSumamry":"textArticle -------------------- ARPA-E: The Little Program that Can October 4, 2010 by Josh Freed Leave a Comment Imagine a program that turns a relatively small initial investment into billions of dollars of U.S. economic growth, thousands of new Americans jobs, and groundbreaking technologies that change the way we use energy in this country and around the world. It would be a darling of innovators, the private sector, and policymakers. Sounds impossible for such a little program to generate such big results? Just like the little engine in the childrenâ€™s story that pulled the train over the","m_szDocBody":"arpae programme josh freed leave comment imagine programme turn small initial investment billion dollar economic growth thousand american job groundbreaking technology change energy country world darling innovator private sector policymaker sound impossible programme generate big result engine children storey pulled train mountain small venture generate big result called advanced research project agency energy simply arpae hailed arpae bureaucratic equivalent death sentence congress failed pass budget real budget congress direct agency continue amount money received year mean arpae funding effectively dry arpae created spur innovation groundbreaking technology set united state rest world leader clean energy economy modelled darpa defence research agency responsible internet global positioning system gps unmanned aerial vehicle darpa small rotating staff expert minimal funding arpae assembling similarly nimble team scientist engineer innovator make big impact small budget competing rest world piece yes trillion dollar clean energy market china investing billion year beat market cheap clean energy technology afford stand wretched economy true federal funding extremely tight initial funding level million arpae potential create wealth prosperity generation battery technology electric vehicle carbon capture technology coalfired power plant liquid transportation fuel microorganism petroleum biomass convert carbon dioxide back liquid fuel technology change world energy technology give birth company create thousand job technology provide push investment clean energy market waiting explode programme create energy world equivalent gps internet longer congress month fund arpae eliminating funding arpae tantamount engine children storey refused pull broken train ceding billion dollar economic growth china south korea japan question think continue support crucial venture coming year arpae vehicle unleash innovation groundbreaking technology push top clean energy market ourselve related post logged post comment logged post comment energy collective column coming soon latest comment schalk cloete seeking consensus externalised cost gas data average externalised cost transport fuel natural gas calculated june schalk cloete seeking consensus externalised cost gas data average externalised cost heat natural gas calculated article june schalk cloete seeking consensus externalised cost gas data global average externalised cost gas fired electricity plant june roger arnold treasure sierra nevada noticed map lake lahontan talked survive june advisory panel scott edward anderson consultant blogger media commentator blog green sceptic christine hertzog consultant author professional explainer focused smart grid elias hinckley strategic advisor energy finance energy policy investor energy company government gary hunt gary executiveinresidence deloitte investment extensive experience energy utility industry jesse jenkin graduate student researcher mit expertise energy technology policy innovation jim pierobon help trade government agency company communicate cleaner energy solution geoffrey style managing director gsw strategy group llc awardwinning blogger featured contributor june june ","m_szGeo1":"United Kingdom","m_szSourceType":"source_industry","m_szSrcUrl":"http://www.theenergycollective.com/joshfreed/44635/arpa-e-little-program-can","m_Places":["United States","China","South Korea","Japan","Gary"],"m_People":["Roger Arnold","Scott Edward","Christine Hertzog","Elias Hinckley","Hunt Gary","Jesse Jenkins","Jim Pierobon","Geoffrey Styles"],"m_Companies":["Congress","Darpa","Sierra Nevada","Deloitte","Strategy Group, Llc"],"m_BiGrams":["externalised cost","clean energy","cost gas","groundbreaking technology","energy market","energy technology","schalk cloete","cloete seeking","seeking consensus","consensus externalised","gas data","average externalised"],"m_TriGrams":["externalised cost gas","clean energy market","schalk cloete seeking","cloete seeking consensus","seeking consensus externalised","consensus externalised cost","cost gas data","average externalised cost"],"m_SocialTags":[],"m_Topics":[],"m_Industry":[],"m_Technology":[],"m_BiCnt":[6,5,4,3,3,3,3,3,3,3,3,3],"m_TriCnt":[4,3,3,3,3,3,3,3],"m_iDocBodyWordCnt":420}
