{"m_szDocID":"244868","m_szDocTitle":"Solar Industry Has a Record Year, but Expecting to Climb Much Higher in 2010 | CleanTechnica","m_szYear":"2010","m_szDocSumamry":"Solar Industry Has a Record Year, but Expecting to Climb Much Higher in 2010 March 31st, 2010 by Zachary Shahan Â  [social_buttons] The European Photovoltaic Industry Association (EPIA) released figures yesterday showing that the global solar photovoltaic industry had a record year in 2009. But it is expecting a lot from 2010 as well. EPIA reported that global installed capacity increased to 20GW last year, an increase of 6.4GW. It is expecting another increase of at least 40% in total installed capacity in 2010. The largest global market continued to be Germany, which has a total capacity of a","m_szDocBody":"solar industry record year expecting climb higher zachary shahan socialbutton european photovoltaic industry epia released figure yesterday showing global solar photovoltaic industry record year expecting lot well epia reported global installed capacity increased year increase expecting increase total installed capacity largest global market continued germany total capacity now installed cutting feedin tariff solar suspected leader end year italy working completing largest solar farm world year number worldwide total capacity year epia expect lot growth market year due conto energia incentive japan rounded top installed capacity leader expected continue growth rapid pace due government support industry japan capacity grew lot expected continue growing fast basically worldwide solar industry expected grow substantially coming year epia expecting global installed capacity increase course depend government support industry government world continue rapid growth trend hit blow past that see now epias estimate good one image credit voicereason licence cleantechnicas completely free electric car report electric car early adopter follower want youd attend electric vehicle solar power event conducted cleantechnica date hottest cleantech new subscribing free cleantech newsletter eye sectorspecific new also free solar energy newsletter electric vehicle newsletter wind energy newsletter tag epia european photovoltaic industry germany installed capacity italy japan solar photovoltaic solar photovoltaic solar usa zachary shahan tryin and specy letter time spend time cleantechnica director chief editor otherwise enthusiastically fulfilling duty obsession gas solar love planetsave bikocity president important media zach recognised globally solar energy electric car energy storage wind energy expert speak related conference event connect social media zacharyshahancom related post wind turbine order drnuthakki radhakrishna change habit rise early sleep early change opening closing time day sunrise sunset sunlight maximum save minimum enrgy required lighting dark night survey availability sunlight world production solar energy increased concerted effort availability duration day year solar farm internationally assisted technolgy transfer aid offender climate change soft loan clean energy produced lowering energy fossil fuel world beneficial total world motsatt ouellette youre solar panel made silicon oxide witch abundance rare earth metal needed manufacturing process make panel work load information care crush dream realistic survive upcomming energy cataclysm big chance research development global warming sceptic doesnt matter climate change true drop ocean compared expect oil era end reason afraid end industrialised modern world hell earth dont give money gore research development greeny agw real worry green solution heard suck happy clap hand jesus ouellette motsatt above wrong vast majority solar cell made silicon oxide principal semiconducting material rare earth metal fact abundant material earth price kilo continue fall absolutely sustainable solution western world short run joe dave above right cost issue typical gridtied system cost installed payback time yrs depending solar radiation however people routinely spend home improvement deck addition etc generate revenue all fact cost time due maintenance requirement people spend money depreciate car luxury item etc time heard payback time suv buy motsatt solar panel make rare earth metal china export rest world scarce metal planning cut export gradualy end completely national demand bad new solar windmill cellphone computer electronic sustainable solution western world short run global patriot encouraged rapid growth solar energy feel united state top list sad commentary politician remain resistance clean energy hall congress taylen sad spain fell radar guess good country stepping instead doug joe money month cost electricity cost solar power down today take year breakeven solar roof however year fall year year that year system released can lowinterest loan bank installed immediately pay itself person country screaming day comingsoonbut today dave brown youve meant annual incremental installed capaicity wouldnt stretch dave political cost cost reason dont solar panel roof big investment joe piervincenti amaze human society global village taking advantage solar power simply case made tooling cost money doesnt garbage drive shoddy workmanship car house poor quality day talk cost end outrageous utility bill capitalise solar power electric company affected theyve affected decade step aside end political case utility give solar joe piervincenti ","m_szGeo1":"United States","m_szSourceType":"source_industry","m_szSrcUrl":"http://cleantechnica.com/2010/03/31/solar-industry-has-a-record-year-but-expecting-to-climb-much-higher-in-2010/","m_Places":["Germany","Italy","Japan","Us","Usa","Atmosphere","U.s.","China","United States","Spain"],"m_People":["Zachary Shahan","Nuthakki Radhakrishna","J.p. Ouellette","Said Jesus","Joe Piervincenti"],"m_Companies":["Industry Association","Epia","Congress","Guess"],"m_BiGrams":["installed capacity","solar power","solar energy","photovoltaic industry","solar photovoltaic","electric car","solar panel","rare earth","earth metal"],"m_TriGrams":["rare earth metal"],"m_SocialTags":[],"m_Topics":[],"m_Industry":[],"m_Technology":[],"m_BiCnt":[5,4,4,3,3,3,3,3,3],"m_TriCnt":[3],"m_iDocBodyWordCnt":646}
