{"m_szDocID":"246051","m_szDocTitle":"Top 10 Analyses From EU Energy Prices And Costs | CleanTechnica","m_szYear":"2014","m_szDocSumamry":"Top 10 Analyses From EU Energy Prices And Costs Originally published by EnergyPost by Sonja van Renssen Retail energy prices are rising dramatically across Europe even as wholesale prices and consumption are coming down. Taxes and levies – set by national governments – are the main culprit, says the European Commission. Energy Post offers a sneak preview of an analysis of energy prices and costs expected from the European Commission on 22nd January. The European Commission has nearly finalised its policy paper on energy prices and costs, plus an analysis of their drivers and implications. Belo","m_szDocBody":"top analyse energy price cost originally published energypost sonja van renssen retail energy price rising dramatically europe wholesale price consumption coming down taxe levy set national government main culprit european commission energy post offer sneak preview analysis energy price cost expected european commission ndjanuary european commission finalised policy paper energy price cost analysis driver implication below energy post top selection insight analysis based latest draught paper due formally approved commissioner january issued alongside industrial policy europe see climate policy bump competitiveness europe climate energy proposal nonbinding guideline shale gas development electricity retail price rising wholesale price coming downwholesale electricity price declined retail price rose industry household wholesale price converged energy policy retail price continue diverge commission plant launch action plan retail market summer gas price industry increased inflationthey grew year household grew year comparison retail electricity price rose year industry year household taxe levy primarily responsible driving european electricity pricessince component retail price greatest increase household industry not counting exemption helped competitiveness electricity gas taxation higher world electricity gas price lot competitiveover half household face kind electricity price regulation curb scope competition potential drop wholesale price reflected retail price vulnerable consumer ideally protected social industrial policy half gas europe indexed oil energy cost household industry increased consumption decreasedenergy efficiency improvement insufficient rising price household share budget energy grew electricity consumption dropped gas consumption industry consumed electricity paid total retail price diverging converging europethe gap highest lowest price paid electricity gas consumer member state grown time household consumer expensive member state pay time cheapest european average hide tremendous variationnational increase household electricity price range average gas price rose year industry reported rise network cost hardest understandgas difficult electricity great variation member state driven national difference network tariff physical infrastructure place energy price gap major partner growingeu industry gas price time india russia china industrial electricity price double russia china although japan commission posit european electricity supply reliable elsewhere however energyintensive good dominate global export marketsthis true widening disparity energy price international energy agency iea predict share down energy price driving factor include recession europe global shift demand underpinning european commission paper energy price cost detailed analysis prepared commission economic financial affair department energy post follow week indepth analysis make energy price tick europe compare rest world cleantechnicas completely free electric car report electric car early adopter follower want youd attend electric vehicle solar power event conducted cleantechnica date hottest cleantech new subscribing free cleantech newsletter eye sectorspecific new also free solar energy newsletter electric vehicle newsletter wind energy newsletter ","m_szGeo1":"United States","m_szSourceType":"source_industry","m_szSrcUrl":"http://cleantechnica.com/2014/01/30/top-10-analyses-eu-energy-prices-costs/","m_Places":["Europe","Us","India","Russia","China","Japan"],"m_People":["Sonja Van Renssen"],"m_Companies":["Eu","European Commission","The Gap","Gap","International Energy Agency","Iea"],"m_BiGrams":["energy price","retail price","electricity price","price cost","wholesale price","european commission","gas price","energy post","price rose","electricity gas","member state"],"m_TriGrams":["energy price cost"],"m_SocialTags":[],"m_Topics":[],"m_Industry":[],"m_Technology":[],"m_BiCnt":[9,6,5,4,4,4,4,3,3,3,3],"m_TriCnt":[4],"m_iDocBodyWordCnt":418}
