{"m_szDocID":"247260","m_szDocTitle":"Internal Combustion Engines Are Still 85% Inefficient | CleanTechnica","m_szYear":"2010","m_szDocSumamry":"Internal Combustion Engines Are Still 85% Inefficient August 7th, 2010 by Susan Kraemer   You might be surprised to hear, that after all this time, with so many  compelling reasons to make vehicles more energy efficient, that the  internal combustion engine still only uses 15% of the energy it receives  from gasoline. I sure was. [social_buttons] A century ago, when the internal combustion engine was invented,  climate change and peak oil were hardly on the radar. But even today, a  century later, with all we know now, a solid 85% of the energy derived from oil is still wasted on the gas car. ","m_szDocBody":"internal combustion engine inefficient susan kraemer surprised hear time compelling reason make vehicle energy efficient internal combustion engine energy receive gasoline was socialbutton century ago internal combustion engine invented climate change peak oil radar today century later now solid energy derived oil wasted gas car epa loss drive line wasted idling braking waste friction wheel bearing lose air resistance stereo power window electric vehicle finally reenter market year technology abandoned quickly century ago installation trolley car system nation that running legislation california forced auto company revisit idea order reduce greenhouse gase now initial decade legal action lieu innovation auto company technology finally turning showroom electric vehicle efficient electricity live state largely coalpowered indiana wyoming kentucky electricity inefficiently produced coalfired power utility typically efficient solar power roof option powering electric car live state solar panel cheaper utility solar lease power purchase agreement sunrun california arizona colorado jersey massachusett solar city oregon california texas gro solar pennsylvania california solar efficient either wasted energy doesnt climate change peak sunshine billion year image flikr roger moore cleantechnicas completely free electric car report electric car early adopter follower want youd attend electric vehicle solar power event conducted cleantechnica date hottest cleantech new subscribing free cleantech newsletter eye sectorspecific new also free solar energy newsletter electric vehicle newsletter wind energy newsletter tag inefficient internal combustion engine susan kraemer write cleantechnica csptoday renewable energy world published wind energy update pvinsider greenprophet ecoseed nrdc onearth matternetwork celsius energynow scientific american serial entrepreneur product design susan bring innovator perspective inventing carbonconstrained civilization necessity mother invention solving climate change mother necessitiesas lover history scifi enjoy chronicling strange future creating interesting time follow susan related post small mojave desert town solar paul borner air resistance stereo greatest amount energy fast moving vehical air resistance developed internal combustion engine bess paulbornercom california solar engineering worst part exciting update renewable energy dont touch transportation fuel biggest cut fuel consumed truck clean fuel ship average food mile reaches plate place rest step rom change correctly reflect loss entire car engine car math brake drive train etc electric car radios leave out also build electric car affect amount waste efficiency well motor wheel waste drive train example big supporter electric drive car information put accurate bring unwarranted negative attention rick dworsky see drive train gas tank matter detail real problem living civilised world facing severe fossil fuel shortage end life electric car solve problem chance global economy imploding havent begun accelerate side peak fossil resource heck member civilization supposed afford electric car global rare earth mineral ore build electric car china banned export material raw sell finished product simple easy nonfunctional answer make sense uninformed sufficient fossil fuel encountering big problem grow ship store cook food oil natural gas expect famine unprecedented scale massive epidemic water civilised world pumped energy derived fossil fuel medicine plastic paint stuff comprise civilization made moved with fossil fuel least fossil fuel causing catastrophic climate unchecked extinction dont die change susan kraemer thank fixed good point trouble right stuff asphalt road drive made oil jth efficient generation transmission losse let rest idling solved traffic control instant control variable displacement engine shut cylinder needed regenerative braking hybrid drivetrain bit better place motor hub but nasty suspension issue unsprung weight bad rolling resistance tyre trade traction rolling resistance proper inflation major moot air resistance apply vehicle moot stereo apply moot let energy make battery disposal carrying excess weight battery partially discharged conclusion inconclusive distributed solar key charging evs transmission line losse roof lose some again wasted solar energy heating habitat notis care explain wasted gas tank doubting epas number annoyed ambiguous reported article additionally citing actual solar efficiency instead theyre efficient dull sharp twinge propaganda here rewording wasted solar energy sunshine doesnt climate change all greenhouse gase dont greenhouse effect solar radiation trap evs renewable energy source dont bad reporting ben developing significant efficiency superior engine patrick system drive electric truck gas gallon nice free fuel daniel swanson lot work problem wont start finder itching keyboard starting headline supportive assume good job thankful people discussing energy issue discussion lead accurate understanding issue bring write dan jeff wolfe sell financed system working sunrun financing provide electric rate similar lower utility supplying clean safe solar power roof time instal solar power power electric home solar reliable simple battery affordable everywhere dont offer financing yet system affordable create inexpensive electricity jeff wolfe ceo grosolar ","m_szGeo1":"United States","m_szSourceType":"source_industry","m_szSrcUrl":"http://cleantechnica.com/2010/08/07/internal-combustion-engines-are-still-85-inefficient/","m_Places":["Us","California","Indiana, Wyoming","Kentucky","Arizona","New Jersey","Massachusetts","Solar City","Oregon","Texas","Pennsylvania","Mojave Desert Town","Most","China","Ca, Ma, Nj","Ny"],"m_People":["Susan Kraemer","Roger Moore","Paul Börner","Rick Dworsky","Daniel J Swanson","Jeff Wolfe"],"m_Companies":["Epa","Scientific American","Twitter","Fossil"],"m_BiGrams":["electric car","internal combustion","combustion engine","fossil fuel","climate change","air resistance","electric vehicle","solar power","susan kraemer","solar energy","renewable energy","drive train"],"m_TriGrams":["internal combustion engine"],"m_SocialTags":[],"m_Topics":[],"m_Industry":[],"m_Technology":[],"m_BiCnt":[8,5,5,5,4,4,4,4,3,3,3,3],"m_TriCnt":[5],"m_iDocBodyWordCnt":729}
