{"m_szDocID":"248526","m_szDocTitle":"Electric Car Sales In Netherlands, Canada, & Ireland (January 2014) | CleanTechnica","m_szYear":"2014","m_szDocSumamry":"Electric Car Sales In Netherlands, Canada, & Ireland (January 2014) Originally published on EV Obsession . Following up on my Norway, Sweden, and Denmark January 2014 electric car sales reports , here are reports for the Netherlands, Ireland, and Canada. For other January 2014 electric car sales or 2013 electric car sales, see the stories linked on the bottom of this article. Netherlands EV Sales Clearly, the Dutch like their PHEVs. Take note that due to an important EV inventive expiring at the end of 2013, there was a huge rush of orders in December. Over 9,000 electrified cars & SUVs were s","m_szDocBody":"electric car sale netherland canada ireland january originally published obsession norway sweden denmark electric car sale report report netherland ireland canada electric car sale electric car sale storey linked bottom article netherland sale clearly dutch phevs note due important inventive expiring end huge rush order december electrified car suvs sold including mitsubishi outlander phevs sale hit pretty hard hangover slowly back normal coming month canada sale canadayou thus you congrat chevy volt holding steady ireland sale ireland doesnt yet basically nissan leaf let hope green country evs soon said youre irish reader irish person handful great model put history book itching more cheque out sale report spreadsheet chart feel free european canada japan china sale spreadsheet sale spreadsheet jose ponte rounding number netherland canada directing ireland number cleantechnicas completely free electric car report electric car early adopter follower want youd attend electric vehicle solar power event conducted cleantechnica date hottest cleantech new subscribing free cleantech newsletter eye sectorspecific new also free solar energy newsletter electric vehicle newsletter wind energy newsletter tag bmw bmw chevrolet chevy volt mitsubishi mitsubishi outlander phev nissan nissan leaf opel opel ampera renault renault zoe tesla tesla model toyota toyota prius toyota prius phev volvo volvo volvo phev zachary shahan tryin and specy letter time spend time cleantechnica director chief editor otherwise enthusiastically fulfilling duty obsession gas solar love planetsave bikocity president important media zach recognised globally solar energy electric car energy storage wind energy expert speak related conference event connect social media zacharyshahancom related post tesla autopilot steer car barrier autobahn construction zone offib damn ross beat anyway irish reader ytd sale increase leaf unit sold unfortunately month evs hammering stab clueless independent irish time didnt mention sale time biassed journalist review car good year january wouldnt surprised delivered sold inventory left sale strong amount interest sale decrease rest market ross ireland sale figure small far sold general market arnenl silver lining sale figure netherland fully electric vehicle sale increased compared fact sale occurred pulled forward december total sale including phevs compared year ago expected double that hopeful sale rebound level albeit yearend rush rick kargaard people forget compare canada california for example week typical car trip mile appproimate wind chill peak pricing electricity time year hrs low angle sun solar panel worse december true live rural area parking electric work problem love electric safety sake price difference compact approach mile gallon driven carefully economy mind stranded desert charge bad standing windchill bobwallace cold climate areas charging spot plugged prewarmed grid power mean battery power warm passenger compartment battery underway battery generate heat discharge warm cold climate areas make adjustment block heater engine warm start park heated garage snow plough salt truck snow tyre chain part living cold rick kargaard true low population density bit make electric economical fact charging station range dont dealership electric test drive switch eventually meantime manufacturer concentrating electric make sense rightly can fast practical miss point great deal ghg situation car driving changing current infrastructure bobwallace dont miss point served current evs mile unpaved unplowed steep road paved ploughed highway mile grocery store suspect long time charger small niche people larger easier serve segment good option first time come reason met evs rick kargaard sound situation grid solution make sense make practical need economic deciding factor bobwallace grid cost bring power pole set solar minimise driving purchase short trip wouldnt pay year rick kargaard situation mine similiar economic consideration hybrid car near end life second vehicle case make sense then kentcarboy astronomical bring power pole door year that thing cmaximal central canada pct canadian live colder normal and normal aint hot clean ice storm happening toronto suspect car sale result ","m_szGeo1":"United States","m_szSourceType":"source_industry","m_szSrcUrl":"http://cleantechnica.com/2014/02/12/electric-car-sales-netherlands-canada-ireland-january-2014/","m_Places":["Netherlands","Canada","Ireland","Norway","Sweden","Denmark","Japan","China","Us","Tesla","Toyota","Barrier","California","Central Canada","Toronto"],"m_People":["Ev Sales","Chevy Volt","Jose Pontes","Zachary Shahan","Rick Kargaard"],"m_Companies":["Bmw","I3","Renault","Volvo","Irish Times"],"m_BiGrams":["electric car","car sale","rick kargaard","electric vehicle","make sense"],"m_TriGrams":["electric car sale"],"m_SocialTags":[],"m_Topics":[],"m_Industry":[],"m_Technology":[],"m_BiCnt":[7,5,4,3,3],"m_TriCnt":[4],"m_iDocBodyWordCnt":610}
