{"m_szDocID":"250754","m_szDocTitle":"Faraday Future, Tesla Model X, Chevy Bolt, Electric Car Sales (Cleantech Talk #17) | CleanTechnica","m_szYear":"2016","m_szDocSumamry":"Faraday Future, Tesla Model X, Chevy Bolt, Electric Car Sales (Cleantech Talk #17) January 21st, 2016 by Zachary Shahan   For our 17th episode of Cleantech Talk, we got to dive into a handful of electric vehicle entrances that provided us with very mixed results. Kyle , Matthew , and I also provided our thoughts on electric car sales, which is one of my favorite topics to track, analyze, and discuss. As a reminder, you can subscribe to Cleantech Talk on iTunes and  SoundCloud . You can also download the episodes to listen to them later offline, or you can simply listen via the embedded player ","m_szDocBody":"faraday future tesla model chevy bolt electric car sale cleantech talk zachary shahan episode cleantech talk dive handful electric vehicle entrance provided mixed result kyle matthew ialsoprovided thought electric car sale favourite topic track analyse discuss reminder cleantech talk itune soundcloud download episode listen offline simply listen viathe embedded player below previous month matthew sharing show note offer reader chew form faraday future variable platform architecture sound promising missing and isnt idea automaker common platform vehicle possible example american automaker generally build large suvs truck platform japanese automaker generally build small suvs crossover cuvs car platform clean diesel scandal volkswagen fted feared fact figured standardise vehicle built handful platform allowing share unprecedented number component meant higher volume price supplier combination fatter profit lower price buyer volkswagen mqb modular transverse matrix platform planned used golf jetta polo passat tiguan touran nextgeneration beetle audi good measure hope platform give million sale year diesel scandal theyll doubt scale expectation back alex roy article claim real vehicle faraday future working crossover fullsized suv lot exciting start designing vehicle blank eye connectivity autonomy said launching differentlysized vehicle presumably platform add lot complexity faraday future control car year tesla model add here tesla collect interesting data and create amazing marketing material bioweapon hepa philtre owner polluted areas china zhang wei philtre caught particulate today second health researcher convince grantgiving organisation model commuting purpose erm multiyear study pollution urban centre electric car sale biggest reason optimism electric vehicle modest sale big automaker strongly committed them german luxury brand realise superior drive experience electric propulsion offer determined early leadership waste toyota honda tepid nissan forging ahead nissan appear automaker planning electric vehicle tesla roadster prompted develop chevy volt contrast toyota fully committed hybrid perhap part locked relevant intellectual property critic that eighteen year prius rolled production line hybrid account global auto sale rosier assumption consulting group proponent factually correct contextually flawed all toyota doubled technology toyotas sold hybrid vehicle remember vehicle sold pricesensitive developing country too lot impressive formerlyhigh gas price helped boost hybrid sale somewhat example developed its ahem clean diesel technology late memory serve twenty year later represented worldwide sale sadly havent link stat give dieselgaterelated generalise bit committed automaker technology transformative electric propulsion sale year automaker committed plugin electric vehicle committed hybrid clean diesel market share eventually rise faster hybrid tdi wait decade comparable sale number chevy bolt reiterate podcast risk plugin electric vehicle sale north america sluggish buyer wait chevy bolt arrive deciding purchase lack compatibility supercharging speed mean fit bill family vehicle surely make excellent car fact autocentric north american urban planner generally built carchitecture architecture lot family battery electric vehicle choice least nextgeneration nissan leaf tesla model knock perch cool chevy make bolt debut even provide early delivery generate buzz chelsea sexton noted anniversary cleantechnicas completely free electric car report electric car early adopter follower want youd attend electric vehicle solar power event conducted cleantechnica date hottest cleantech new subscribing free cleantech newsletter eye sectorspecific new also free solar energy newsletter electric vehicle newsletter wind energy newsletter tag chevy bolt cleantech talk sale faraday future podcast tesla tesla model volkswagen zhang wei zachary shahan tryin and specy letter time spend time cleantechnica director chief editor otherwise enthusiastically fulfilling duty obsession gas solar love planetsave bikocity president important media zach recognised globally solar energy electric car energy storage wind energy expert speak related conference event connect social media zacharyshahancom related post ","m_szGeo1":"United States","m_szSourceType":"source_industry","m_szSrcUrl":"http://cleantechnica.com/2016/01/21/faraday-future-tesla-model-x-chevy-bolt-electric-car-sales-cleantech-talk-17/","m_Places":["Tesla","Kyle","China","Toyota","Toyotas","North America"],"m_People":["Chevy Volt","Zachary Shahan","Alex Roy","Zhang Wei","Chelsea Sexton"],"m_Companies":["Cleantech","Soundcloud","Diesel","Volkswagen","Matrix","Audi","Honda","Google"],"m_BiGrams":["electric vehicle","electric car","faraday future","chevy bolt","cleantech talk","tesla model","car sale","clean diesel"],"m_TriGrams":["electric car sale"],"m_SocialTags":[],"m_Topics":[],"m_Industry":[],"m_Technology":[],"m_BiCnt":[8,6,5,4,4,3,3,3],"m_TriCnt":[3],"m_iDocBodyWordCnt":568}
