{"m_szDocID":"252572","m_szDocTitle":"BYD Sells Another 2,200 Electric Buses & Taxis in China  | CleanTechnica","m_szYear":"2014","m_szDocSumamry":"BYD Sells Another 2,200 Electric Buses & Taxis in China March 10th, 2014 by Roy L Hales   Editor’s Note: we’ve been covering BYD’s cost-competitive electric bus for a long time now , and have enthusiastically shared news of many small orders, but orders totaling 1,800 electric buses is huge. Let’s hope we see more such orders soon. Originally published on the ECOreport . Build Your Dreams’ (BYD) sale of 1,800 electric buses and 400 electric taxis this week is the most recent example of how this Chinese company is expanding into the world market. Four days ago, on March 5, the  Nanjing Public T","m_szDocBody":"byd sell electric buse taxis china roy hale editor note weve covering byd costcompetitive electric bus long time enthusiastically shared new small order order totaling electric buse huge let hope order soon originally published ecoreport build dream byd sale electric buse electric taxis week recent chinese company expanding world market day ago nanjing public transportation announced anorder byd electric buse delivered city youth olympic game authority order byd allelectric passenger crossover utility vehicle hit street company announced sale electric buse well delivered city dalian ceremony byd founder ceo chuanfu introduced company milestone r&d capability product including electric bus fully electric suv worldwide fleet application chance talk byd latest consumer offering breakthrough pluginhybrid qin chairman highlighted operational statistic byd electric fleet totaling million travelled million mile revenue service operating city including recent project london england york city key message byd chairman technology environmentally friendly efficient profitable operator witnessed shenzhen fleet zhenggao chen governor liaoning province expressed byd pioneer aspect energy vehicle confident byd seize opportunity develop mastering core technology energy vehicle winning war combating poor air quality byd publiclytraded company investor american warren buffet them berkshire hathaway own byd stock buffett colleague recognise byd breakthrough battery technology electrified hour longrange battery emissionfree silent economic public private transportation the chinese government share byd allelectric zeroemission bus travel hour service charging offpeak hour photo business wire electric company greatest successe china founded byd electric bus assembly line week ago company made announcement bangalore called indias silicon valley bus launching there city huge pollution problem emission existing bus fleet company marketed europe selling fleet zeroemission fullyelectric byd car london electric buse netherland north america tough market windsor ontario signed letter intent purchase electric buse year ago but lengthy negotiation signed electric bus manufacturer proterra meanwhile long beach ordered buse recent city announce trial los angele day spokane month trial run gatineau qubec ottawa ontario the socit transport loutaouais sto avt consortium qubec transit agency recently confirmed bus achieve mile range perform advertised york metropolitan transportation authority zeroemission electric bus subsequently reported deliver mile full charge heavy traffic buss longest trip single charge north america southeast asias largest zeroemission electric bus order malaysia awarded byd photo business wire distance record malaysia sixmonth trial prasarana transit reported buse kilometre charge needless say promptly ordered taking spin governor malacca gave bus thumb electric bus comfortable quiet kind emission bus photo top pagebyd metre foot zeroemission allelectric rapidtransit bus travel hour single nighttime offpeak charge photo business wire cleantechnicas completely free electric car report electric car early adopter follower want youd attend electric vehicle solar power event conducted cleantechnica date hottest cleantech new subscribing free cleantech newsletter eye sectorspecific new also free solar energy newsletter electric vehicle newsletter wind energy newsletter ","m_szGeo1":"United States","m_szSourceType":"source_industry","m_szSrcUrl":"http://cleantechnica.com/2014/03/10/byd-sells-another-2200-electric-buses-taxis-china/","m_Places":["Sells","China","Bus","Nanjing","Dalian","London, England","New York City","Shenzhen","Liaoning","Warren","Bangalore","India","Silicon Valley","Europe","London","North America","Windsor, Ontario","Us","Long Beach","Los Angeles","Spokane","Quebec","Ottawa","Ontario","Southeast Asia","Malaysia","Malacca"],"m_People":["Roy L Hales","Chuanfu Wang","111 Million Miles","Zhenggao Chen","Buffett"],"m_Companies":["Transportation Group","Berkshire Hathaway","Chinese Government","Business Wire","New York Metropolitan Transportation Authority"],"m_BiGrams":["electric buse","electric bus","byd electric","photo business","business wire"],"m_TriGrams":["photo business wire"],"m_SocialTags":[],"m_Topics":[],"m_Industry":[],"m_Technology":[],"m_BiCnt":[7,7,3,3,3],"m_TriCnt":[3],"m_iDocBodyWordCnt":453}
