{"m_szDocID":"253017","m_szDocTitle":"SEIA Calls On Obama To Revaluate Investment Tax Credit Phase Out | CleanTechnica","m_szYear":"2014","m_szDocSumamry":"SEIA Calls On Obama To Revaluate Investment Tax Credit Phase Out March 12th, 2014 by Adam Johnston   Suggestions of ending the Investment Tax Credit (ITC) for US solar energy projects has the industry’s top official wanting the White House to revise its position. President Barack Obama released last week in his 2015 fiscal year budget the phase-out of the ITC by December 31, 2016. In its place is the less lucrative Production Tax Credit (PTC). Image Credit: Solar Panels at Seldom Rest Farms via WikiCommons Rhone Resch, CEO and President of the Solar Energy Industries Association (SEIA), conten","m_szDocBody":"seia call obama revaluate investment tax credit phase adam johnston suggestion ending investment tax credit itc solar energy project industry top official wanting white house revise position president barack obama released week fiscal year budget phaseout itc place lucrative production tax credit ptc image credit solar panel seldom rest farm wikicommon rhone resch ceo president solar energy industry seia contended axing itc replacing ptc huge step backward developing solar policy solar itc law installed solar capacity nationwide grown megawatt megawatt clean reliable affordable electricity power million home resch seia website smart forwardlooking public policy solar itc helped create goodpaying american job pump ten billion dollar economy helping protect environment fight climate change said fruitful ptc compared itc ptc tax break project comparison itc offer developer writeoff operational development cost resch pushed keeping itc order advance future economic growth change tax policy hurt future solar investment ptc simply address upfront cost fuelfree solar project administration sudden degree shift tax policy devastating consequence future development solar energy america said proposed elimination itc hurt future solar project solar capacity continue increase atotal megawatt solar photovoltaic capacity installed year solar produced electricity capacity compared natural gas suggest eliminating itc part solar energy maturing process however compared energy industry past including oil gas solar young strong incentive continue climb energy mountain competing fossil fuel counterpart information cheque section solar energy solar energy newsletter main cleantech newsletter cleantechnicas completely free electric car report electric car early adopter follower want youd attend electric vehicle solar power event conducted cleantechnica date hottest cleantech new subscribing free cleantech newsletter eye sectorspecific new also free solar energy newsletter electric vehicle newsletter wind energy newsletter tag solar energy capacity solar energy capacity rhone resch seia solar energy policy solar energy ptc solar energy ptc itc solar itc credit renewable energy policy solar energy policy adam johnston studying school environment professional development programme renewable energy university toronto adam graduated university winnipeg threeyear combined major economic rhetoric writing communication adam write solar love own part time tax preparation business eventual goal cleantech policy analyst sharpening skill renewable energy writer follow related post solar wind tax credit extension big boost solar wind growth tax credit bad funding mechanism transfer wealth poor rich give monster tax equity fund rid itc great ptc fundamentally bad policy reason subsidise something direct cash transfer equally all disingenuous stupid line administration sudden degree shift tax policy quoted ridicule them bobwallace what difference allowing xyz wind farm pay tax ptc giving grant well difference turn profit order pay tax matt nonprofit community group dont benefit sell tax credit tiny amount back jim smith reducing reducing subsidy oil gas company too sault knowing congress work reduction phaseout solar itc coupled elimination fossil fuel subsidy lobbyist hand solar tax break cut anderlan phase itc set occur sort code harmonisation making solar wind ptc ptc renewable awry think banned bob weve determined previous post fossil fuel subsidy amount production shouldnt eliminated unnecessary subsidy jim smith federal subsidy massive jim smith agree time start cutting oil bank farm foreign aidthey cut bobwallace technology decided support feet ground price competitive expensive expensive wise supporting technology price continue rise continued rise year point start backing winner cut loser loose banned bob elimination fossil fuel subsidy unneeded witnessed ability oil company attract capital oil price inflation past year complain price milk bread keeping context real dollar real libertarian oil price inflation past year complain price milk bread keeping context real dollar adjusted inflation oil then banned bob commodity lose time spite volatility exhibit time time trend time flat real term inflation adjusting market interest rate cpi basket good static real libertarian commodity lose time spite volatility exhibit time time wrong trend time flat real term real defined belief inflation bobwallace happen graph posted yes back century oil expensive century inflation adjusted cost oil rising mds seriously smaller percent argument again sssoooo lame percentage lower fossil fuel century produce power total dollar amount subsidy fossil fuel much greater renewable solar smaller part renewable subsidy fossil fuel subsidy fully mature technology profitable decade fossil fuel subsidy continued subsidise stage coaches steam ship individual lower percent argument fool charlatan pick itc plan solar fine helping increase amount clean energy technology reduce cost fossil fuel out spent remain expensive cheaper fool defend oil coal subsidy profiting theft public dollar charity rich corporation total outrage obviously wakeup smell exhaust matt dont climate health cost external massive subside dropped small subsidy ill number add health external recovery tax last est low ball twh kwh cent kwh wait cent wind year coal year leave cost clean coal chemical spill coal ash spill duke fair pay past damage let pick past year charge fossil electric generation rebate equally deduction not counting double people federal tax twh banned bob youre make argument externality add benefit consumption energy simply cherry pick presumed negative matt math off study kwh ignoring past damage didnt cherry pick benefit matter form generation wind thermal form isnt coal generated special electric power general special coal compare negative health cost climatehawk agree general thrust sceptical calculus benefit energy consumptioni addicted cheap oil polluting fossil fuel source defend defence dollarsthis itc small carrot stick practicallyexchanging itc real sticklike gradual revenue neutral replacement payroll tax carbon tax applaudmy concern adinistration reason suggest dropping itc substantial returnannoyingsimilar abovelikely small ball political move policy wonk notice motivate oneand congress ignoring proposal anywaywhy make concession ","m_szGeo1":"United States","m_szSourceType":"source_industry","m_szSrcUrl":"http://cleantechnica.com/2014/03/12/seia-calls-obama-revaluate-investment-tax-credit-phase/","m_Places":["Us","America","Well","Take"],"m_People":["Barack Obama","Adam Johnston","Jim Smith"],"m_Companies":["Itc","Solar Energy","White House","Solar Energy Industries","Nationwide","University Of Toronto","University Of Winnipeg","Twitter","Congress","Ags","Ball","Fossil"],"m_BiGrams":["solar energy","fossil fuel","tax credit","fuel subsidy","policy solar","solar itc","banned bob","tax policy","energy newsletter","energy policy","renewable energy","solar wind","jim smith","past year"],"m_TriGrams":["fossil fuel subsidy"],"m_SocialTags":[],"m_Topics":[],"m_Industry":[],"m_Technology":[],"m_BiCnt":[13,10,6,5,4,4,4,3,3,3,3,3,3,3],"m_TriCnt":[5],"m_iDocBodyWordCnt":897}
