{"m_szDocID":"254547","m_szDocTitle":"The Cube – New Breakthrough Set to Alter the Energy Landscape Forever | OilPrice.com","m_szYear":"2013","m_szDocSumamry":"The Cube – New Breakthrough Set to Alter the Energy Landscape Forever The Cube – New Breakthrough Set to Alter the Energy Landscape Forever By Charles Kennedy Posted on Thu, 15 August 2013 22:18 | 12 Redox Power Systems has signed a partnership deal with researchers at the University of Maryland in order to develop and bring to commercial market a new distributed electricity generation technology that could change the relationship that many consumers have with the energy market and national grid. Based on the research of Eric Wachsman, the director of the University of Maryland’s Energy Resear","m_szDocBody":"cube breakthrough set alter energy landscape forever cube breakthrough set alter energy landscape forever charle kennedy posted thu redox power system signed partnership deal researcher university maryland order develop bring commercial market distributed electricity generation technology change relationship consumer energy market national grid based research eric wachsman director university maryland energy research centre redox introduce fuel cell onetenth size onetenth cost fuel cell market solid oxide fuel cell provide safe efficient reliable power household businesse local remote price competitive current energy price warren citrin ceo director redox told forbe business home safely generate energy rely vulnerable electrical grid decrease vulnerability distributed energy making energy onsite building system that emphasis efficiency affordability common appliance cube forbe redoxs power serg aka cube connected natural gas supply convert methane usable electricity electrochemical reaction larger dishwasher engine virtually moving part silently create constant supply energy redox boast cube generate electricity system impervious hurricane thunderstorm cyberattack derechos similar danger simultaneously helping environment system efficient operating efficiency create electricity heat produce virtually polluting substance energy source model capacity power moderate grocery store small shopping plaza time redox release model power home model larger installation technical information cube redox solid oxide fuel cell suffered major problem prevented success open market operate temperature degree celsius cost lot manufacture wachsman worked score graduate undergraduate student period year speeding million dollar research funding state art laboratory develop fuel cell operate lower temperature generate power fraction cost explained achieved major advance composition fuel cell material micro nanostructure material putting resulted cell extremely power density order watt square centimetre charle kennedy oilpricecom learn profit offshore oil boom free weekly newsletter youll inside energy market gain investment advice floor trader fund manager top level industry contact information previously reserved hedgefund special report oil energy insider analyst oil gas industry megatrend profit global energy asset telling prepared now oil energy insider analyst floating refinery stock fund retirement company incredible tanker technology eliminate world offshore pipeline oil energy insider analyst end offshore drilling disruptive market grow year discover equipment supplier set profit related article leave comment marc sowven said sound cool marketed backup system protected electrical grid gas supply disrupt attractive lower electricity cost current energy source thomas santilli said impressive nice advance home power generation marc sowven imagine eventually marketed remote area electricity generation model production advantage gas supply disrupted hook gas cylinder power grid back marc sowven said thomas store gas tank simply buy standard fuel based generator fuel easier store higher energy density kilowatt cost advantageous attract market sincerely hope due low pollution device jorge bustamante said liquid fuel tend degrade time compressed gaseous fuel stay good longer fuel cell efficient generator sofc designed properly supply electricity hot water nice bad weather backup solution remote location rely primarily active passive solar solution heat power kind fuel practical hydrogen fuel cell term infrastructure chris lee said difference residential system sale japan year nice finally catching nima sarabi said nice toy showing make fuel cell work thank make work hydrogen people buy compromise carbon tax fraud fiona haye said cost run normal sized house shipped australia gas consumption use average gas consumption day buy energy cube fiona paul said sound great show number price unit clown thing awesome cheap fix issue buy god long fail bill althoff said natural gas create saykw grid selling energy back provider initial cost cube cost natural gas evaluated grid purchase environmentally friendly back source curious data natural gas usage thomson said running electric car power home needed home run electricity well septic refrigeration etc moving part reliable efficient minimum preventive maintenance total cost wiring propane option etc appear doable situation said cube technology year ago offer residential unit corner marketthey googlemicrosoft silicon valley company manufacturer michael seegert said question facility let wastewater treatment plant capture methane burn power generation low effective switch generator produce natural gas industry landfill etc excess energy created fed back grid tied system wind turbine utilise captcha ","m_szGeo1":"United Kingdom","m_szSourceType":"source_industry","m_szSrcUrl":"http://oilprice.com/Alternative-Energy/Fuel-Cells/The-Cube-New-Breakthrough-Set-to-Alter-the-Energy-Landscape-Forever.html","m_Places":["Nice","Japan","Australia","Ie","Silicon Valley"],"m_People":["Charles Kennedy","Eric Wachsman","Warren Citrin","Forbes","Wachsman","He","Mega","Thomas","Marc Sowven","Jorge Bustamante","Chris Lee","Nima Sarabi","Bill Althoff","Michael Seegert"],"m_Companies":["Landscape","University Of Maryland","Research Centre","Forbes","Special Reports","Tanker Technology","Solar Solutions","Sounds","Cube Technology","Google","Microsoft"],"m_BiGrams":["fuel cell","natural gas","gas supply","oil energy","energy insider","insider analyst","marc sowven"],"m_TriGrams":["oil energy insider","energy insider analyst"],"m_SocialTags":[],"m_Topics":[],"m_Industry":[],"m_Technology":[],"m_BiCnt":[9,5,3,3,3,3,3],"m_TriCnt":[3,3],"m_iDocBodyWordCnt":653}
