{"m_szDocID":"254613","m_szDocTitle":"Big Banks Inflate Solar Project Value to Boost Tax Credits | CleanTechnica","m_szYear":"2011","m_szDocSumamry":"Big Banks Inflate Solar Project Value to Boost Tax Credits July 18th, 2011 by John Farrell   Solar leasing has offered thousands of homeowners a “no money down” route to go  solar, broadening participation in the distributed generation  revolution.  Unfortunately, this revolution has been co-opted by high  finance.  Big banks have been able to write off millions in taxes by  over-reporting the cost of financed solar PV projects in what may be the  country’s next banking scandal. In  a phone conversation last month, Jigar Shah of Carbon War Room  (formerly chief of solar-as-a-service company Su","m_szDocBody":"big bank inflate solar project boost tax credit john farrell solar leasing offered thousand homeowner money route solar broadening participation distributed generation revolution unfortunately revolution coopted finance big bank write million taxe overreporting cost financed solar project country banking scandal phone conversation month jigar shah carbon war room formerly chief solarasaservice company sunedison disclosed solar leasing company instal residential solar watt routinely federal tax credit fair market value price high solar tax lawyer confirmed practise apply programme providing cash grant lieu federal investment tax credit equipment financed solar company calculate treasury cash grant fair market system cost wrote week practise boost bank bottom line expense federal taxpayer unnecessarily increase cost public subsidy renewable energy california example percent smallscale project completed party owned code word solar leasing arrangement bank fair market actual system cost tax credit system inflated tax credit totaled million million justified actual project cost tip iceberg million difference reflect onethird residential solar market word overpayment bank financing solar leasing million alone bank announced commitment finance million residential solar problem isnt unknown federal government solar tax lawyer spoke noted treasury pushing back fair market claim high treasury push harder big bank bigger tax credit size solar array homeowner lone bright spot growth solar leasing slowed past year previously solar leasing individual capture federal solar tax credit didnt tax liability alternative big bank provide upfront financing exchange tax credit and opportunity inflate value weve previously discussed tax credit make lousy renewable energy policy however federal tax credit allowed people cash grant instead reducing party ownership end december long that treasury shut practise overestimating project cost fair market value solar energy incentive built american solar market helped drive cost solar bank shouldnt allowed subvert public incentive post originally appeared energy selfreliant state resource institute local selfreliance rule project cleantechnicas completely free electric car report electric car early adopter follower want youd attend electric vehicle solar power event conducted cleantechnica date hottest cleantech new subscribing free cleantech newsletter eye sectorspecific new also free solar energy newsletter electric vehicle newsletter wind energy newsletter tag investment tax credit solar bank solar financing solar financing project solar financing scam solar investment tax credit solar project solar scam solar tax credit john farrell direct democratic energy programme ilsr focuse energy policy development expand benefit local ownership dispersed generation renewable energy seminal paper democratising electricity system describe blast roadblock distributed renewable energy generation smallscale renewable energy project key biggest stride renewable energy development farrell authored landmark report energy selfreliant state serve definitive energy atlas united state detailing statebystate renewable electricity generation potential farrell regularly discussion analysis distributed renewable energy policy blog energy selfreliant state energyselfreliantstatesorg article regularly syndicated grist renewable energy world john farrell found related post ","m_szGeo1":"United States","m_szSourceType":"source_industry","m_szSrcUrl":"http://cleantechnica.com/2011/07/18/big-banks-inflate-solar-project-value-to-boost-tax-credits/","m_Places":["California","U.s.","United States"],"m_People":["John Farrell","Jigar Shah"],"m_Companies":["Revolution","Sunedison","Treasury","U.s. Bank","Solar Energy","Twitter"],"m_BiGrams":["tax credit","renewable energy","solar leasing","fair market","big bank","solar tax","solar project","john farrell","residential solar","cash grant","investment tax","energy policy","energy selfreliant","selfreliant state","solar financing"],"m_TriGrams":["investment tax credit","energy selfreliant state"],"m_SocialTags":[],"m_Topics":[],"m_Industry":[],"m_Technology":[],"m_BiCnt":[13,8,6,5,4,4,3,3,3,3,3,3,3,3,3],"m_TriCnt":[3,3],"m_iDocBodyWordCnt":450}
