{"m_szDocID":"255527","m_szDocTitle":"EPA Ratings Published For Tesla Model X | CleanTechnica","m_szYear":"2015","m_szDocSumamry":"EPA Ratings Published For Tesla Model X Originally published on EV Obsession . The long-awaited Tesla Model X is almost here, and we’ve got another sign that it’s ready to roll. Aside from getting its HOV-lane sticker and EV rebate eligibility from California , the X is also now listed on the US EPA’s website, which shows its official “fuel economy,” range, passenger and cargo space, and other specs. There are just two versions of the Model X listed so far, the P90D X and the 90D X . It’s not clear yet if Tesla will offer Model X SUVs with smaller (or larger) battery packs, but it’s presumed t","m_szDocBody":"epa rating published tesla model originally published obsession longawaited tesla model here weve thatit ready roll hovlane sticker rebate eligibility california listed epas website show official fuel economy range passenger cargo space spec version model listed far clear teslawill offermodel suvs smaller larger battery pack presumed company production ramp bit somescreenshot comparing tesla model tesla model viewing pleasure youre welcome foreasier reference here cheque out mpge mile mpge mile pretty wicked efficiency suv seat quicker sport car produced course expected electric vehicle worth highlighting interest soontobe owner potential owner range wenoted day rated range model recently rose mile from mile design studio signature reservation holder invited configure car see simply changed minute epa rating finalised tesla model range ispredictably bit better sitting mile naturally range vary great deal based drive vehicle external factor temperature interestingly spec tab epa model gas guzzler passenger volume separately electric motor battery size expected charging time explained electric car charging piece electric car onboard charger onboard charger model onboard charger buyer pay extra option onboard dual charger same put term matter average human here point onboard charger electric car add mile driving range hour atv onboard charger electric car add mile driving range hour atv onboard charger electric car add mile driving range hour atv onboard dual charger electric car add mile driving range hour atv big benefit tesla vehicle tesla model new time being day sooner missed recent piece though cheque now tag epa tesla tesla model tesla model tesla model charging tesla model efficiency tesla model mpge tesla model tesla model range zachary shahan tryin and specy letter time spend time cleantechnica director chief editor otherwise enthusiastically fulfilling duty obsession gas solar love planetsave bikocity president important media zach recognised globally solar energy electric car energy storage wind energy expert speak related conference event connect social media zacharyshahancom related post ","m_szGeo1":"United States","m_szSourceType":"source_industry","m_szSrcUrl":"http://cleantechnica.com/2015/09/26/epa-ratings-published-for-tesla-model-x/","m_Places":["Tesla","California"],"m_People":["Zachary Shahan"],"m_Companies":["Epa","Us Epa","Ramps"],"m_BiGrams":["tesla model","electric car","onboard charger","model tesla","charger electric","car add","add mile","mile driving","driving range","range hour","hour atv","atv onboard"],"m_TriGrams":["charger electric car","electric car add","car add mile","add mile driving","mile driving range","driving range hour","range hour atv","onboard charger electric","hour atv onboard"],"m_SocialTags":[],"m_Topics":[],"m_Industry":[],"m_Technology":[],"m_BiCnt":[12,7,6,4,4,4,4,4,4,4,4,3],"m_TriCnt":[4,4,4,4,4,4,4,3,3],"m_iDocBodyWordCnt":307}
