{"m_szDocID":"257162","m_szDocTitle":"#1 Tesla Dominates Large Luxury Car Market In US (Updated Figures) | CleanTechnica","m_szYear":"2016","m_szDocSumamry":"#1 Tesla Dominates Large Luxury Car Market In US (Updated Figures) Originally published on EV Obsession . This is a point that I already highlighted in an article approximately a month ago, “ #1 Large Luxury Car In US = Tesla Model S (2015 Sales Comparison) .” Now, however, Tesla* has provided us with its official numbers! Our estimates for US Tesla Model S sales were a tad high for both 2014 and 2015, and the result is that Tesla’s year-over-year growth was even higher than projected. Either way, though, the story is the same: Tesla crushed the competition in the large luxury car market in 20","m_szDocBody":"tesla dominate large luxury car market updated figure originally published obsession point highlighted approximately month ago large luxury car tesla model sale comparison now however tesla provided official number estimate tesla model sale tad result teslas yearoveryear growth higher projected way though storey same tesla crushed competition large luxury car market here teslas tableand word triumph increased global delivery year year model market share gain continued geographic region year entering market model share incumbent manufacturer number selling comparably priced fourdoor sedan fact model vehicle class growing sale year competitor home turf country government incentive purchase electric vehicle model winning example switzerland model outsold mercede benz sclass bmw sery porsche panamera audi combined full year outsold mercede benz eclass germany model outsold porsche panamera finally europe year model outsold audi combined bmw sery sery combined here data put chart format since love chart much too image zachary shahan obsession cleantechnica available republishing credit ive covered general storey ill repost wrote month for missed refresher and way elon made point model similarly priced competition gasmobile segment quarterly conference call concluded anyhow mybrief word month aiming add context giving conventional automaker bit slack note combined model class mercede bit tesla bmw audi well behind course tesla doesnt extensive dealer network mercede bmw audi have tesla doesnt decade brand building advertising tesla doesnt production capacity giant automaker mercede bmw audi volkswagen bit concerned tesla point tesla model market challenging bmw audi mercede idea didnt mention month fully expect model luxury suv market model large luxury car market elon noted today conference call think model car world agree tesla exec ordered headaches sleepless night due complexity put amazing car planet imho tesla purposefully suppressing demand production constrained now word start there review start published mass media people experience vehicle demand increase tremendous fashion stay tuned update year intro refresher tesla model s&model kick competition rear end hard cheque out way teslas trump electric car full disclosure investor tesla tsla stock company dont intend sell year such biassed ihave enthusiastically covered tesla longer ive shareholder dont aim move stock price word frankly write interesting important teslawill longterm success handful obvious reason fully support mission reason long tsla cleantechnicas completely free electric car report electric car early adopter follower want youd attend electric vehicle solar power event conducted cleantechnica date hottest cleantech new subscribing free cleantech newsletter eye sectorspecific new also free solar energy newsletter electric vehicle newsletter wind energy newsletter tag audi audi audi bmw bmw sery bmw sery sale jaguar jaguar lexus lexus mercede mercede clsclass mercede sclass porsche porsche panamera tesla model tesla model sale tesla sale zachary shahan tryin and specy letter time spend time cleantechnica director chief editor otherwise enthusiastically fulfilling duty obsession gas solar love planetsave bikocity president important media zach recognised globally solar energy electric car energy storage wind energy expert speak related conference event connect social media zacharyshahancom related post ","m_szGeo1":"United States","m_szSourceType":"source_industry","m_szSrcUrl":"http://cleantechnica.com/2016/02/10/tesla-dominates-large-luxury-car-market-in-us-updated-figures/","m_Places":["Tesla","Us","U.s.","Switzerland","Germany","Europe","Teslas"],"m_People":["Zachary Shahan","Mercedes-benz S-class"],"m_Companies":["Bmw","Audi","Audi A8","Slack","Volkswagen","Audi A3","Audi A7"],"m_BiGrams":["tesla model","large luxury","luxury car","bmw audi","electric car","car market","model sale","electric vehicle","model outsold","bmw sery","tesla doesnt"],"m_TriGrams":["large luxury car","luxury car market"],"m_SocialTags":[],"m_Topics":[],"m_Industry":[],"m_Technology":[],"m_BiCnt":[6,4,4,4,4,3,3,3,3,3,3],"m_TriCnt":[4,3],"m_iDocBodyWordCnt":481}
