{"m_szDocID":"257307","m_szDocTitle":"Selling a Bridge to Nowhere: NREL Lithium/Carbon Metric | CleanTechnica","m_szYear":"2011","m_szDocSumamry":"Selling a Bridge to Nowhere: NREL Lithium/Carbon Metric September 20th, 2011 by Breath on the Wind   Back in 2003, for those who know the history of the second coming of electric cars, the California Air Resources Board (CARB) was convinced to rewrite the definition of zero emission vehicles to include hybrids. About the same time, Chevron was suing everyone to keep the nickel-metal-hydride battery out of electric vehicles . However, they became the standard for hybrids . The movie “ Who Killed the Electric Car ” may have been inconclusive but attention did shift to hybrids, which continue to ","m_szDocBody":"selling bridge nowhere nrel metric breath wind back history coming electric car california air resource board carb convinced rewrite definition emission vehicle include hybrid time chevron suing nickelmetalhydride battery electric vehicle however standard hybrid movie killed electric car inconclusive attention shift hybrid continue gasoline crushed mind surprised number recent article promoting hybrid battery electric vehicle due lithium usage nrel study conclude lithium sparingly hybrid car pound carbon saved bill moore world hybrid lithium alternative energy stock mind tom konrad taking slightly pro perspective colleague john peterson perspective way information easy draw inaccurate conclusion nrel study inaccurate lithium scarce resource then lithium mean achieve lower carbon goal saving carbon reason advocating electric car simply promote point view nrel study pursue hybrid technology vehicle operate battery nrel study scope study nrel information narrowly focused weigh variable amount lithium amount carbon offset data inaccurate casual review study give information save time effort assume study accurate conclusion scarcity resource gasoline combination element concerned gasoline scarce energy stored bond element element dont disappear form relationship lower energy level energy concerned losing element lithium element doesnt possess chemical energy itself store electrical energy battery store gasoline cheap fuel tank lithium fuel tank pour fuel electricity constantly reused battery longer container recover element alternative lithium fact mentioned nrel study lithium battery chemistry maximum storage capacity less ultimate goal will year chemistry zincair offer potential study suggest cheapest path vehicle electrification wireless technology electrified roadway system give unlimited range recharge vehicle concern recharging time lithium nrel study project lithium usage year technology remain static conclude lithium meet lithium battery worldwide exercise lithium bring year advanced energy storage year administration propose million electric vehicle road including hybrid suggest practical year nissan leaf battery lithium theoretically million pound lithium year tonne presently produce tonne year battery plenty lithium carbon concern explored petrol vehicle year option transportation widely known electric vehicle key unlock option need efficient vehicle vehicle charged primarily night time shift power usage make grid efficient battery electric vehicle backup power cheaply powered solar panel vehicle lead decentralisation power this turn security foreign energy supply growing debt inflation interest rate bridge study action advocate lithium scarce point rationing remotely understand purpose study adoption battery electric vehicle public policy question action reason rather study substance unusual condition arise conclusion empty initial condition met such study use begin bridge nowhere bridge photo cyanocorax return lithium graphic nrel powerpoint cleantechnicas completely free electric car report electric car early adopter follower want youd attend electric vehicle solar power event conducted cleantechnica date hottest cleantech new subscribing free cleantech newsletter eye sectorspecific new also free solar energy newsletter electric vehicle newsletter wind energy newsletter tag alternative lithium bill moore bridge california air resource board carb carbon carbon dioxide chevron electric car utility electricity public policy hybrid john peterson lithium lithium scarcity national renewable energy laboratory nissan leaf nrel return lithium evaluated tom konrad wireless technology zincair breath wind share world past resource combined future aspiration molecule life passed time space considered breath wind part world consciousness live nyc worked law research construction engineering travelled drawn asia write energy electric vehicle issue forward comment persuade appeal interest intellect benjamin franklin related post ","m_szGeo1":"United States","m_szSourceType":"source_industry","m_szSrcUrl":"http://cleantechnica.com/2011/09/20/selling-a-bridge-to-nowhere-nrel-lithiumcarbon-metric/","m_Places":["Best","Nyc","Asia"],"m_People":["Bill Moore","Tom Konrad","John Peterson"],"m_Companies":["California Air Resources Board","Carb","Chevron","Path","National Renewable Energy Laboratory"],"m_BiGrams":["electric vehicle","electric car","nrel study","battery electric","breath wind"],"m_TriGrams":["battery electric vehicle"],"m_SocialTags":[],"m_Topics":[],"m_Industry":[],"m_Technology":[],"m_BiCnt":[9,6,6,4,3],"m_TriCnt":[4],"m_iDocBodyWordCnt":527}
