{"m_szDocID":"257951","m_szDocTitle":"GM Doubles Down On \"Moon Shot\" Volt EV | CleanTechnica","m_szYear":"2014","m_szDocSumamry":"No problem. CaptD I think Tesla, probably with a partner like Nissan and/or Hero (India) will wiln because they are leading already! Fiat will be a competitor but GM and even Dambler/MB are too slow to shift in a big way. WeaponZero The next volt will not be a 200 mile EV hybrid. It will be a lower cost volt with an improved gas engine. This is for 2016. After that, they plan to introduce a new platform which will be 100 miles + gas hybrid or a 200 mile pure electric(replacing the engine). 200 mile hybrid is not in the works. That said, this is not going to be out any time soon to compete with","m_szDocBody":"problem captd tesla partner nissan hero india wiln leading already fiat competitor slow shift big way weaponzero volt mile hybrid lower cost volt improved gas engine that plan introduce platform mile gas hybrid mile pure electricreplacing engine mile hybrid work said time compete tesla model bobwallace mile phev make sense people hauling ice system time simply rapid charging station volt range option bottom bit higher prius plugin higher today volt break mile range number captd agree bob suggest hauling detachable pod bumper mounted spare battery add additional range needed lower cost coast battery store household generated energy evehicle bobwallace car manufacturer evs space spare battery accessory trailer battery swapping ability assume decent range evs away car manufacturer crackerjack engineer understand battery staff let curtain battery manufacturer act otis prefer generous electric range today evs mile range range extender kick nonideal start motor mile rough engine start stop repeatedly mile people average commute mile mean fully depleting battery hard battery kicking engine mile hard engine design range time engine kick youre driving significantly normal mile starting sufficient mile ideal though even drive frequently most tend drive longer trip prefer mile range kick engine travel city jeffhre rough engine spin firing slosh synthetic fluid motor fire incurring heavy propulsion load ice load prelubricated primary motor electric doesnt matter imo ice through otis thermal expansion stresse part motor heat engine block fully warmed jeffhre seriously foot across water cooled synthetically lubricated maintenance problem coal fired plantbut four otis apparently big thought mechanical engineer make piston cylinder material thermal expansion stresse wear running mes now apparently theyve switched material make coefficient similar way correct material prestart spin lubricate part ive told longer issue correcting outofdate notion jeffhre wow pick information learn run floored youre man sir seriously yeah question lot volt concept put lot engineering making reliable learned time otis see biggest complaint volt thought range needed minimise wear issue ive argument time corrected glad longer issue supported concept volt concerned issue lifecycle taking time clarify bring uptodate captd weaponzero predict public demanding loud clear voice low cost quality commuter seater seater version vehicle think modern eversion bug work shopping buy gasoline stumble ahead maintaining school detroit mindset india china korea european manufacture flood usa version tiny evehicle sell hotcake jeffhre dang weapon crystal ball crushing mine jameswimberley gasoline cushion important car owner trafficcongested areas unexpected delay occasion sort anxiety range anxiety owner sort worry stuck traffic them isnt moving motor idling stopped battery running radio meme misdirection gms mds guessing theyll providing option battery size time captd yes make good sense evehicle designer leave room additional battery driver require extra range safer larger capacity dual fuel tank installed truck vehicle factory larger fuel capacity tank mileage driven low range road plough snow customised evehicle convert small ice pickup truck electric you part pickup bed space provide battery capacity require brainer adding additional battery wiring connect them bus make great econversion vehicle lot space extra battery ground clearance handle extra weigh battery mds nice now make small suv erev small pickup erev volt ground clearance happy there tesla this dont pay option mds mistake tina confusing volt erev spark theyre talking mile tesla make erevs bad drive long distance remote areas time mentioned erev drive allelectric daily basis drive hybridgasoline longer trip remote spot pay that buy car price playing strength pursued erev volt mentality here otis well person forum erev pick preferably tacoma sized interested one tacoma sized sized tacoma sized vehicle year interested truck wont make purchase year time wait fruition bobwallace watching small suv seating four room sleep back seat folded down mile range important dont bother phev driving otis pickup allowing gasoline engine running acceptable solution well aka run engine run switch idk necessary big deal only mile range bare minimum prefered texas spread city regularly drive mile range deal breaker mile range make inconvenient captd equal generation volt give tesla run moneyread history indication machine giving moon shot guarantee dark side moon let compare machine machine spin avoiding fixing defective poorly designed ignition switch knew killed customer worry about tesla hand rank customer loyalty continue grow globally committing building free supercharging station world largest battery manufacturing plant customer electricity have include storing energy rooftop system evehicle additional tesla battery add save pun intended pumping excess generation grid utility make profit from tesla decided cede entry market other expect time unveil hybrid volt tesla introduced evehicle greater range today model thank teslas gigantic battery factory electric eliminate gas station waiting inline price forever btw stock company did tesla mds leapfrogged toyota prius volt erev spectacularly great car reviewer customer agree that give credit this machine volt out theyve learn something isnt dgaetano gasoline cushion important car owner trafficcongested areas unexpected delay occasion sort anxiety range anxiety traffic increase range driving slower increase range dramatically dont idle standing still counter intuitive ice experience year driving leaf san diego dan hue true driving volt here add conscientious waste emission partial stress relief phil mccracken air conditioning hot weather san diego blessed phoenix isnt blessed ive assumed terrible battery drain traffic congestion bobwallace found comment leaf owner forum attest work great based year experience phoenix area worst case ive driven car sat degree heat july cooled quickly gaspowered vehicle ive used situation drawing battery short while settled minute typically degree day heat youre range ronald brakel ill mention solar cell roof bonnet hood logical power air conditioning sound add significant extra cost expensive set process settled machinery set cost produce solar car roof cheap lot cost solar panel backing paid solar panel put not captd ronald brakel short term suggest battery tech result put solar cell roof bonnet add bit overnight charging costeffective panel bobwallace pull initial surge passed stuck hour congestion hot day burn mile range assuming mile extreme heat nissan heat pump compressor type unit captd bob dont exact cost number bet translate nickel day worth electricity cool heavy traffic less tend reduce road rage temper hothead driver down bobwallace minute average daily commute minute day cent cost range loss insignificant live commute range captd bob said make sense remain cool driving evehicle commuting situation keeping window closed add distance evehicle aerodynamic bobwallace move heat pump compressor resistance heater training wheel phase learning electric vehicle improving way lighten vehicle battery motor here coming lighter weight smaller electric motor cheaper rare earth metal the misleading induction motor tesla volt rare earth metal already bobwallace inclusion small amount costly rem smaller lighter motor money spent doug cutler interesting link electric motor make motor shouldnt similar generator wind turbine generator captd great beat question motor generator depend physic jeffhre induction motor rare earth metal note weaponzero noted earlier ronald brakel cent kilowatthour grid electricity feed tariff cent cent brave leader make safe world huff coal solar panel car roof sound good idea current directly electric motor air conditioner car save wear tear battery bobwallace upsidedown land doesnt sun shine night youre parked plugged ronald brakel bend over mds spot solar roof powering nice feature car cooking sunny parking lot burn lot juice cooling car initially left sun nice feature hop cool car add window electronically opaque already home save juice solar roof parked greenhouse effect car hot sun block light car easier cool theyre parked ronald brakel photovoltaic window people working handy car captd yes imagine clear electronically opaque glass window panel generate electricity serve window protect inside car content keeping heat prying eye out btw hot climate allowing heated air inside vehicle escape help vehicle cooler vehicle sealed leaving window bit vent visor window deflector installed provide safe air path heat escape make rvs refrigerator efficient ride cooler hot day mds good point help well thx jeffhre greenhouse effect climate phoenix commuter car sitting hour opaque window delay stop car reaching expected terminal temp mds rate heating terminal temp greater window clear glass opaque simple physic rate verse rate heat out make measurement jeffhre driver finding energy heating existing vehicle hvac configuration power involved comparison propulsion can toss solar panel roof burn alcohol suggested large draw relatively captd live back east house big fuel oil fired boiler electric pump circulate water heated home radiator price gallon fuel oil dollar gallon time heater boiler kicked cringed writing wall installed time efficiency modern natural gas fired boiler tiny size easily replaced larger fuel oil boiler large gallon holding tank boiler space basement caused heating bill plummet meant relax enjoy warmer healthier indoor environment major portion year evehicle inefficient fuel oil boiler time commuter cringing monthly bill roof upgrade evehicle pay penny mile time much commute large distance large rooftop solar system relocate simple doomed remain wage slave money end month dont evehicle yet dont drive mile month cringe pay gallon while norskediv electric vehicle great concern electricity rate roof germany ontario kwh berlin ontario quickly rising bobwallace wholesale price electricity germany rapidly dropping retail customer pay lot electricity due taxe top electricity price renewable line price continue fall captd bob wonderful chart sunshine yellow rate bottom due solar nice touch concept electricity cheap metre day close reality grid charge metre connexion fee evehicle road taxe billed big utility government regulate add taxe everyone monthly billing profit from bobwallace grid cost future peer cost money build maintain road live democracy properly exercising voting right government profiting collecting money spending need clear electricity price fall significantly today forget external cost pay burning fossil fuel cost show metre paying day day out captd bob generation electricial rate start mpg number upward happily rooftop home owner electricity bill long run installed great rate pay panel quickly evehicle chart bet enjoy captd reason instal solar panel roof can paying utility arnenl ditto congestion good exception total gridlock blocked road due accident slowly drain battery running onboard computer hvac moving metre then ronald brakel sound solar roof helpful situation onboard system pretty economical suppose economy mode gridlock minimise power loss running air conditioner surprised sort wasnt place country electric made imagine people driving electric stuck middle traffic jam open window breath fresh air arnenl solar roof country home wsc yes live sun shine gridlock youre lucky direct sunlight small solar panel produce negligible power idea gridlock stinky noisy engine pleasant vision future ronald brakel hear arneni sunshine car mean air conditioning ive looked electric car lose kilometre range hour stop start traffic gasoline mobile fact supposed advantage jeffhre interesting scenario driving emitting pollution evs slowing stopping emitting sound relaxing deal traffic economy mode mile hour economy mode make huge difference closing window tight improve airflow vehicle closing grill vent lowering ride height chart teslas mile range mile hour lower speed economy mode captd great post speak point conversion ice evehicle due education belief longer valid actual experience roadway congested evehicle efficient compared ice vehicle make investment imagine day gridlock cost commuter ice vehicle afford longer jeffhre counter intuitive common sense sitting vehicle minimal motor power battery taxed drive volt start stop technology mean ice slow moving traffic true car equipped type misdirection helpful really engineer make happen gms marketing people phil mccracken current volt overlycomplicated resulting production cost plugin version simple cylinder backup flexfuel power plant vehicle plugin hybrid bobwallace vehicle plugin hybrid oil industry top dog interesting prediction car manufacturer dont agree marketing evs phevs top dog interesting prediction vehicle sold phevs oil usage for vehicle drop driving year newer vehicle oil industry dying dog great dane morphing chihuahua captd placate huge dealer base make competitive tesla international corporation compete commuter market year remember saying dog wont learn trick jimbo jone black guy driving year ago benjamin nead century jimbo hope evs driven everyone jimbo jone invitation offering put money mouth mary put experimental car brought people gave cobolt benjamin nead well original comment responding deleted well disqus system informed poster directed additional tersely worded dont site thankfully basically question validity volt referring experimental car people gave cobolt here reply that mid per wikipedia quickest source locate volt amperas produced car world united state make experimental driven volt local dealer loaned week late attest reliable built vehicle car received universal acclaim automotive press and knowing one personally attest owner satisfaction high nameplate classic and indeed automaker produced fair share dud dont volt them answer jimbos question directly market buy volt driven pure electric vehicle extended period honestly appraising driving criteria hunt plain not phev finance available that diminutive mitsubishi imiev current favourite ive critical and major auto manufacturer matter perilously slow rollout evs phevs general volt phev drivetrain gem gms lineup cadillac elr preferred minivan small suv plugin range extender technology produce pure electric spark california oregon select market hope offer similar small format pure nationwide market jimbo jone jewishfaggott tinacasey know right contrast clunky charging cable today but connected car clarify source photo identified volt concept earlier version judging date matt scale hard metal panel size plug captd mockup eye candy international regulator approve cable design evehicle real world shown promo image automotive scifi best jeffhre original differentinnearlyeverydetail volt concept shown robby wrong image volt concept instead blurry closeup picture usbstyle cable neil blanchard ","m_szGeo1":"United States","m_szSourceType":"source_industry","m_szSrcUrl":"http://cleantechnica.com/2014/04/12/moonshot-gm-volt-in-the-works/","m_Places":["Tesla","India","Most","United States","Us","“detroit’","China","Korea","Usa","Bus","Well","Tacoma","Texas","San Diego","Hue","Burns","Germany","Ontario","Berlin","Chihuahua","California","Oregon"],"m_People":["Ev Drivers","Phil Mccracken","Ronald Brakels","Doug Cutler","Jimbo Jones","Benjamin Nead","Neil Blanchard"],"m_Companies":["Volt","Ices","Phoenix","Phoenix, Az","Daily Us","Path","Wikipedia","Volts","Universal","Indeed","Cadillac","Nationwide","Ul"],"m_BiGrams":["mile range","ronald brakel","solar panel","volt concept","captd bob","solar roof","fuel oil","economy mode","car manufacturer","small suv","tacoma sized","air conditioning","electric vehicle","electric motor","rare earth","earth metal","jimbo jone"],"m_TriGrams":["rare earth metal"],"m_SocialTags":[],"m_Topics":[],"m_Industry":[],"m_Technology":[],"m_BiCnt":[9,7,6,4,4,4,4,4,3,3,3,3,3,3,3,3,3],"m_TriCnt":[3],"m_iDocBodyWordCnt":2175}
