{"m_szDocID":"258772","m_szDocTitle":"Nissan Leaf Taxi Testing Begins | CleanTechnica","m_szYear":"2011","m_szDocSumamry":"Nissan Leaf Taxi Testing Begins November 2nd, 2011 by Zachary Shahan   Nissan Leaf taxis for NYC are moving forward. Will Nissan Leaf taxis be the norm in a few years?     Get CleanTechnica’s 1st (completely free) electric car report — “Electric Cars: What Early Adopters & First Followers Want.” And tell us where you’d like to attend electric vehicle and/or solar power events conducted by CleanTechnica   Keep up to date with all the hottest cleantech news by subscribing to our (free) cleantech newsletter , or keep an eye on sector-specific news by getting our (also free) solar energy newslette","m_szDocBody":"nissan leaf taxi testing begin zachary shahan nissan leaf taxis nyc moving forward nissan leaf taxis norm year cleantechnicas completely free electric car report electric car early adopter follower want youd attend electric vehicle solar power event conducted cleantechnica date hottest cleantech new subscribing free cleantech newsletter eye sectorspecific new also free solar energy newsletter electric vehicle newsletter wind energy newsletter tag york nissan leaf nissan leaf taxis nyc nyc nissan leaf taxis nyc nissan taxis nyc taxis quicky zachary shahan tryin and specy letter time spend time cleantechnica director chief editor otherwise enthusiastically fulfilling duty obsession gas solar love planetsave bikocity president important media zach recognised globally solar energy electric car energy storage wind energy expert speak related conference event connect social media zacharyshahancom related post elijah lynn zach teslas make good cab leaf easier manoeuvre niche market nyc pay eco cab beginning suspect nissan tesla make battery modular swap battery iphone route kill them spoke rep classic car club manhattan day demoing tesla mention tesla candidate modular battery tesla battery take floor panel work future modular battery quick release battery nonissue swap propane tank anonymous tesla swapable battery doubt future swapable battery ive time ill again mile range minute charge make evs fully functional long distance trip drive charge drive charge drive mile driving day stop icev stop fuel people drive mile stopping couple time anyway swapable battery bring sort difficulty table first battery second sort additional cost due establishing swap station expensive equipment keeping ample number spare battery hand battery swapping catch putting money affordable evs range year elijah lynn yeah right catching car standard battery happen car open source while anonymous evs range range limit enforced chevron oil world battery patent prison decade french company bollore type lithium iron polymer battery autolib car paris mile charge feeble nissan leaf normal size nyc cab hold bollore battery time size double range autolib bluecar nissan leaf candidate taxi small enforce small stereotype electric car fact larger vehicle room battery key bigger vehicle smaller nissan leaf worse drive range charge time evs late sell laptop cellphone spec major car brand designed fail part oil mafia people tesla bollore sincere making tech ability forthcoming tesla model top version mile range london blackcab big traditional nyc taxis hold battery mile range suv limo anonymous mile charge put large battery car byd pack mile range nissan pack mile range mile range tesla battery pack battery expensive heavy french invented battery great range metric use cost weigh important battery crude compared today battery arent elijah lynn howard disbelieve statement chevron owning patent battery post source though long public education anonymous paste bit current trend industry development lithiumion liion technology replace nimh electric vehicle manufacturerswho maintain nimh battery important commercialization plugin hybrid electric vehicle phevs battery electric vehicle bevs liion technology functionally superior due higher specific energy specific power prohibitively expensive untested longterm reliability expensive lithiumion battery pound diamond them lithium nissan leaf battery cost platinum catalytic converter gas vehicle cost technology dedicated plant running cranking puppy price fall starting fall couple year back price lithiumion battery reported ive post existing delivery contract set weve battery plant coming line state economy demand low mean price fall quickly plant manager work operation wait market recover scrape minimal margin bankrupt elijah lynn wow read posting anonymous city car dont aerodynamic car regular highway use make body style suited city taxi use bump roof height bit easier access create generous rear area accessible rear door stretch bit offer legroom set fold rearfacing seat driver byd working taxi put mile year service charging rapid level charger mile battery holding well mile range improvement leaf focus mile range ","m_szGeo1":"United States","m_szSourceType":"source_industry","m_szSrcUrl":"http://cleantechnica.com/2011/11/02/nissan-leaf-taxi-testing-begins/","m_Places":["Nyc","Us","New York","Tesla","Manhattan","Paris"],"m_People":["Zachary Shahan","Elijah Lynn"],"m_Companies":["Taxi","Classic Car Club","Chevron","Mafia"],"m_BiGrams":["nissan leaf","mile range","electric vehicle","leaf taxis","taxis nyc","electric car","elijah lynn","swapable battery"],"m_TriGrams":["nissan leaf taxis","leaf taxis nyc"],"m_SocialTags":[],"m_Topics":[],"m_Industry":[],"m_Technology":[],"m_BiCnt":[10,8,5,4,4,4,4,3],"m_TriCnt":[3,3],"m_iDocBodyWordCnt":609}
