{"m_szDocID":"259973","m_szDocTitle":"Who You Are — EV Enthusiast Profile | CleanTechnica","m_szYear":"2015","m_szDocSumamry":"Who You Are — EV Enthusiast Profile January 25th, 2016 by Zachary Shahan   In our third article pulled from  Electric Cars: What Early Adopters & First Followers Want  — a new report from  CleanTechnica ,  EV Obsession , and GAS2  — I’m jumping into who the respondents of the surveys were. Given that our readers were primarily the respondents, this is basically a look at who you are. One of the four surveys was directed only at current EV owners and lessees (also referred to “EV drivers” in parts of of this report). Two of the four surveys were directed at both EV drivers and potential EV buye","m_szDocBody":"enthusiast profile zachary shahan thirdarticle pulled electric car early adopter follower report cleantechnica obsession gas jumping respondent survey were reader primarily respondent basically are survey directed current owner lessee also referred driver part report survey directed driver potential buyer survey directed potential buyer purchase board respondent main survey heavily male wealthy driver male potential buyer male driver annual household income potential same driver annual household income potential same note median household income respondent primarily living united state closely matching cleantechnica obsession gas readership figure were live canada australia potential buyer live canada australia respondent primarily living small town big city rather mediumsized city figure were city million inhabitant town inhabitant potential buyer city million inhabitant town inhabitant driver primarily bought evs year expected historical sale data respondent broke down driver year year year year year more surprisingly respondent stated car seemingly indicating adequate individual car car admittedly identify percentage split owner plugin hybrid electric car which essentially range limitation tesla owner which typically dont notable range limitation owner fully electric nontesla car fully electric car mile range full charge future survey topic response segmented distinctly type evs surprisingly point above though respondent good buying experience meh good buying experience widespread criticism conventional dealer selling evs number horror storey regard expected response negative respondent tesla model roadster nontesla buyer good buying experience and assuming single tesla buyer good buying experience case pretty close colour shocked potential firsttime wouldnt phev erev minimum mile electric range minimum mile electric range respondent intend buy remaining respondent breakdown intend follow year year remaining respondent plan year potential firsttime buyer plan buy fully electric car year general breakdown follow year year remaining respondent plan pure year buying leasing buy potential owner plan buy plan lease plan buy lease existing driver bought evs leased both buying versus used respondent plan plan dont yet question car potential car asked respondent question energy efficiency solar power expected response driver driving electric improve efficiency specifically regard driving efficiency asked make drive efficiently not counting efficiency boost simply driving electric respondent doe werent sure said energy conservation home asked make conserve energy home more people responded yes sure term solar power current driver home solar panel potential driver home solar panel clearly percentage higher populace large download full report cleantechnicas completely free electric car report electric car early adopter follower want youd attend electric vehicle solar power event conducted cleantechnica date hottest cleantech new subscribing free cleantech newsletter eye sectorspecific new also free solar energy newsletter electric vehicle newsletter wind energy newsletter tag australia canada electric car driver electric car early adopter follower driver france germany norway tesla zachary shahan tryin and specy letter time spend time cleantechnica director chief editor otherwise enthusiastically fulfilling duty obsession gas solar love planetsave bikocity president important media zach recognised globally solar energy electric car energy storage wind energy expert speak related conference event connect social media zacharyshahancom related post assuming single tesla buyer good buying experience case pretty close tesla buyer bad buying experience wave anyway surprised buyer bias rich electric car upfront cost moment obvious hope theyll cheaper asap also environmentallyminded people living big city ditch car public transportation lived big city small town option surprised smalltown people electriccarbuyer sample hybridbear respondent primarily living small town big city rather mediumsized city figure were city million inhabitant town inhabitant potential buyer city million inhabitant town inhabitant survey respondent picked answer population entire metro area picked population metro area live million people suburb live inhabitant answered question unsure answer wanted size metro area live size specific suburb live dont remember answer ended choosing survey percentage driver live small town inhabitant part larger metro area also this read entire report yesterday interesting data robwithab question make sense data electric range vehicle drive helped provide context answer julie rosenthal interesting easy understand kvleeuwen survey software research correlation example american range european people bigger city smaller evs zachary shahan doesnt extra manually examine thing unfortunate software future zachary shahan btw survey monkey slick trick above pls drop note here tedkidd gotta careful make leap big surprisingly respondent stated car seemingly indicating adequate individual car adequate dont range handicapped again fortunately option affordable buy internal combustion vehicle suck milliamp driver male potential buyer male women angry guy tech hobby interest similar tech pattern generally male channel focused education viewer male gender test watch programming tutorial aware people passionate robotic create elaborate project pattern college formula sae team team team this people creating shit storm silicon valley women make tech job represent represent interest level related community conference women making people hobbyist group hard fault company female tech workforce seriously zachary shahan yes run deeper hiring department making case that kyle field reason important female stem career direction future exciting women kicking tail field one riely rumfort indeed rare bird functional thinker group growing piece workforce bad seek employment field money college statistical level due field passion passionate worker productive seek cheque today world applicant job hold back person job recieve qouta race sex play apologise this passion ability utmost priority world potential get omega centauri interestingly household male tech wife drive leaf regularly occasionally neroden problem start early girl discouraged joining tech club school girl exerting social pressure honestly eric wadge percentage people interested owning purchase they street parking otis gifting ill tech package winter package smart air suspension ludicrous mode appreciated dont needy expect gifted car realistically give working condition ecstatic hand gco expect gifted car kid point sure leaf otis generous friend parent helped car gifted car knowledge common grew wealthy area brother rebuilt car car shared bit finally passed afford reliable car car back momento afford reliable vehicle significant portion readership falling category wealth reasonable expect gifted car simply odd milliamp thankfully buy leaf something benjamin nead yes sticker imiev taxe registration etc month mile later couldnt happier leaf guess lot mile clean low mileage leaf though jumped late fall price lowest levelled climbing upward again witnessing result survey household annual income exceeding finding good deal inexpensive fairly low priority typical cross section car buying population phenomenon affordable storey worth noting otis true safe reliable car low o&m cost good condition found year ago dont account inflation true year toyota honda accord fit bill good condition newish owner tended replace create abundant hand market leaf zachary shahan cover base yes mind parent giving kid car common gather buy car knew lot people their comment parent planning time time here course way car main considering otis yeah guess understand gco common ability borrow parent car shared car multiple kid car rarer case wealthier area grew understand covering base surprised common base cover though significant affluence covered poll readerbase carl raymond solar panel roof solar panel roof property therefore busy read survey question carefully maxwell erickson ","m_szGeo1":"United States","m_szSourceType":"source_industry","m_szSrcUrl":"http://cleantechnica.com/2016/01/25/who-you-are-ev-enthusiast-profile/","m_Places":["Us","United States","Canada","Uk","Australia","Tesla","France","Germany","Norway","Most","Monkey","Silicon Valley","Well"],"m_People":["Ev Buyers","Zachary Shahan","Ev Drivers","Julie Rosenthal","Eric Wadge","Benjamin Nead","Carl Raymond","Maxwell Erickson"],"m_Companies":["Conserve","Sae","Indeed","Volt","Guess"],"m_BiGrams":["electric car","potential buyer","zachary shahan","buying experience","town inhabitant","good buying","small town","big city","city million","million inhabitant","inhabitant town","solar panel","metro area","gifted car","car early","early adopter","adopter follower","obsession gas","survey directed","household income","respondent primarily","primarily living","figure were","fully electric","buyer good","tesla buyer","electric range","remaining respondent","respondent plan","plan buy","solar power","expect gifted"],"m_TriGrams":["good buying experience","city million inhabitant","million inhabitant town","electric car early","car early adopter","early adopter follower","respondent primarily living","buyer good buying","expect gifted car"],"m_SocialTags":[],"m_Topics":[],"m_Industry":[],"m_Technology":[],"m_BiCnt":[10,7,6,6,5,5,4,4,4,4,4,4,4,4,3,3,3,3,3,3,3,3,3,3,3,3,3,3,3,3,3,3],"m_TriCnt":[5,4,4,3,3,3,3,3,3],"m_iDocBodyWordCnt":1128}
