{"m_szDocID":"260569","m_szDocTitle":"Here Comes the Sun - The Chart Paul Krugman Left Out | CleanTechnica","m_szYear":"2011","m_szDocSumamry":"December 12th, 2011 by John Farrell   This post originally appeared on Energy Self-Reliant States , a resource of the Institute for Local Self-Reliance’s New Rules Project . Nobel economist Paul Krugman made waves last month when his column “ Here Comes the Sun ” noted that the rapidly falling cost of solar electricity – “prices adjusted for inflation falling around 7 percent a year” – meant that “solar is now cost-effective.” It’s close. But it depends on what’s meant by “cost-effective.” The first step is translating solar prices into electricity prices. Installed costs for solar have droppe","m_szDocBody":"john farrell post originally appeared energy selfreliant state resource institute local selfreliance rule project nobel economist paul krugman made wave month column sun noted rapidly falling cost solar electricity price adjusted inflation falling percent year meant solar costeffective close depend what meant costeffective step translating solar price electricity price installed cost solar dropped dramatically watt year ago low watt utilityscale system watt residential system electricity isnt sold watt kilowatthour kwh solar installed watt minneapolis produce electricity cent kwh sunny los angele solar array produce power cent kwh abundant direct sunshine make solar electricity time period place price dont compare favourably average residential retail electricity price cent respectively fact top metropolitan areas country average price electricity cent caveat grid electricity price fixed changing past decade electricity price risen average united state percent year solar electricity price locked panel operating utility timeofuse rate charge electricity peak time hot summer afternoon rise cent kwh solar compete favourably rate federal state utility incentive solar reduce cost federal tax credit example statute end issue matter electricity price inflation make solar competitive electricity price inflation continue apace time solar system halfway expected life year million american roughly cheaper electricity solar installed watt editor note year conservative obsessively conservative lifetime estimate cost solar legitimate lifespan course lower timeofuse pricing make solar competitive timeofuse pricing let utility charge price electricity time day based actual cost delivering power time place higher price coincide hot sunny summer afternoon effectively increase cost electricity time solar panel produce power already million american southern california instal solar watt beat timeofuse pricing grid electricity incentive solar accelerate costeffectiveness solar power crossing costeffectiveness threshold grid price rising reflect true cost electricity incentive capture environmental economic benefit solar finance project sunny southwest million american beat grid price watt solar incentive million american beat grid price federal tax credit market expansion enabled tax incentive driving cost instal solar labour material cost module time make solar winner krugman note falling cost solar make time greatest ally chart illustrate number american top metropolitan areas solar watt beat grid electricity price average residential retail rate year base assumption price solar decline year grid electricity price rise year chart examine solar incentive tax credit utility timeofuse pricing expected boost retail rate solarproducing hour noincentive taxcredit line merge expiration tax credit federal tax incentive favourable timeofuse pricing million american beat utility electricity price solar timeofuse price million tax credit factored half country course chart tend underestimate time greatest population growth largest metropolitan areas with highest electricity price sun indeed cleantechnicas completely free electric car report electric car early adopter follower want youd attend electric vehicle solar power event conducted cleantechnica date hottest cleantech new subscribing free cleantech newsletter eye sectorspecific new also free solar energy newsletter electric vehicle newsletter wind energy newsletter tag cost electricity energy federal tax credit federal tax credit grid grid parity incentive selfreliance solar utility john farrell direct democratic energy programme ilsr focuse energy policy development expand benefit local ownership dispersed generation renewable energy seminal paper democratising electricity system describe blast roadblock distributed renewable energy generation smallscale renewable energy project key biggest stride renewable energy development farrell authored landmark report energy selfreliant state serve definitive energy atlas united state detailing statebystate renewable electricity generation potential farrell regularly discussion analysis distributed renewable energy policy blog energy selfreliant state energyselfreliantstatesorg article regularly syndicated grist renewable energy world john farrell found related post ","m_szGeo1":"United States","m_szSourceType":"source_industry","m_szSrcUrl":"http://cleantechnica.com/2011/12/12/here-comes-the-sun-the-chart-paul-krugman-left-out/","m_Places":["Minneapolis, Mn","Los Angeles","United States","Southern California","Winner","Us"],"m_People":["John Farrell","Paul Krugman"],"m_Companies":["Lifespan","Ally","Indeed","Twitter"],"m_BiGrams":["electricity price","tax credit","renewable energy","federal tax","million american","timeofuse pricing","cost solar","make solar","grid electricity","john farrell","energy selfreliant","selfreliant state","solar electricity","price electricity","cent kwh","electricity time","metropolitan areas","cost electricity","grid price","american beat","beat grid"],"m_TriGrams":["federal tax credit","energy selfreliant state","grid electricity price","million american beat"],"m_SocialTags":[],"m_Topics":[],"m_Industry":[],"m_Technology":[],"m_BiCnt":[12,7,6,5,5,5,4,4,4,3,3,3,3,3,3,3,3,3,3,3,3],"m_TriCnt":[4,3,3,3],"m_iDocBodyWordCnt":562}
