{"m_szDocID":"261341","m_szDocTitle":"US Wind Tower Group Files Dumping Complaint Against Chinese, Vietnamese Manufacturers | CleanTechnica","m_szYear":"2011","m_szDocSumamry":"US Wind Tower Group Files Dumping Complaint Against Chinese, Vietnamese Manufacturers December 30th, 2011 by Andrew   Photo courtesy DMI Industries Trade friction with China is spreading, as a group of four US wind tower manufacturers filed a complaint with the US Dept. of Commerce and International Trade Commission calling on them to investigate and levy punitive duties on Chinese and Vietnamese wind turbine tower manufacturers, The Oregonian’s Ted Sickinger reported earlier today. Calling itself the Wind Tower Trade Coalition, the group comprises Texas-based Trinity Structural Towers , Fargo","m_szDocBody":"wind tower file dumping complaint chinese vietnamese manufacturer andrew photo courtesy dmi industry trade friction china spreading wind tower manufacturer filed complaint dept commerce international trade commission calling investigate levy punitive duty chinese vietnamese wind turbine tower manufacturer oregonian ted sickinger reported earlier today calling wind tower trade coalition comprise texasbased trinity structural tower fargo north dakotas dmi industry wisconsin broadwind tower nebraskas katana summit chinese wind tower manufacturer operation vietnam dumping product cost benefiting chinese government subsidy violate international trade agreement similar complaint recently filed coalition american solar manufacturer casm chinese solar photovoltaic manufacturer undergoing preliminary investigation dept commerce itc initially found complaint wind tower trade coalition list separate chinese government subsidy assistance programme enable adopt predatory pricing detriment domestic manufacturer sickinger report theyre requesting impose countervailing duty reconcile difference price imported wind tower normal market exporting country calculate chinese wind tower wind tower manufactured vietnam response casm complaint chinese solar producer filed complaint alleging polysilicon producer receive improper subsidy dumping product cost china polysilicon raw material production solar cell panel chinese trade authority investigating usbased producer hydro wind energy product dumping product china uschina trade friction limited renewable energy chinas ministry commerce recently decided impose punitive duty large car suvs imported dec cnbc report chinese import gms cadillac esplanade fiatchrysler jeep cherokee luxury suvs made daimler bmw affected itc expect preliminary determination wind tower trade coalition complaint february commerce dept complete preliminary finding month oregonian report cleantechnicas completely free electric car report electric car early adopter follower want youd attend electric vehicle solar power event conducted cleantechnica date hottest cleantech new subscribing free cleantech newsletter eye sectorspecific new also free solar energy newsletter electric vehicle newsletter wind energy newsletter tag china dumping wind tower commerce dept international trade commission itc wind energy industry wind industry uschina trade dispute uschina trade friction wind tower trade coalition wind tower andrew reporting writing wide range topic nexus economic technology year now asiapacific europe americas africa middle east issue related broad topical areas pose tremendous opportunity challenge define quality live relationship natural environment related post ","m_szGeo1":"United States","m_szSourceType":"source_industry","m_szSrcUrl":"http://cleantechnica.com/2011/12/30/us-wind-tower-group-files-dumping-complaint-against-chinese-vietnamese-manufacturers/","m_Places":["Us","China","Texas","Fargo, North Dakota","Nebraska","Vietnam","Asia","Europe","Africa","Middle East"],"m_People":["Ted Sickinger"],"m_Companies":["Tower Group","Dmi Industries","Us Dept. Of Commerce","International Trade Commission","Oregonian","Dmi Industries , Wisconsin","Dept. Of Commerce","Itc","Ministry Of Commerce","Cnbc","Cadillac","Esplanade","Bmw","Commerce Dept.","Us International Trade Commission","Us Itc","Nexus"],"m_BiGrams":["wind tower","tower trade","trade coalition","trade friction","tower manufacturer","international trade","dumping product","wind energy","uschina trade"],"m_TriGrams":["wind tower trade","tower trade coalition"],"m_SocialTags":[],"m_Topics":[],"m_Industry":[],"m_Technology":[],"m_BiCnt":[12,4,4,3,3,3,3,3,3],"m_TriCnt":[4,4],"m_iDocBodyWordCnt":343}
