{"m_szDocID":"261335","m_szDocTitle":"Tough Road Ahead for Nuclear Power | CleanTechnica","m_szYear":"2011","m_szDocSumamry":"Tough Road Ahead for Nuclear Power December 30th, 2011 by Joshua S Hill   Several experts have recently made it clear that they think nuclear power isn’t going to be growing any time soon, and will continue to experience popular criticism and fear, especially in light of the recent damage taken by the Fukushima nuclear reactor in Japan. Nuclear Power Plant in Haifa, Israel In a heavy-handed opening to a press release announcing the publication of a new paper written by Mark Cooper, senior fellow for economic analysis at the Institute for Energy and the Environment (at Vermont Law School), the ","m_szDocBody":"tough road ahead nuclear power joshua hill expert recently made clear nuclear power isnt growing time soon continue experience popular criticism fear light recent damage fukushima nuclear reactor japan nuclear power plant haifa israel heavyhanded opening press release announcing paper written mark cooper senior fellow economic analysis institute energy environment vermont law school nuclear industry past year summed succinctly fukushima disaster earthquakerelated reactor shutdown reactor project cost escalation infighting nuclear regulatory commission nrc cheap natural gas year nuclear power industry prefer quickly possible cooper note similar challenge believe make impossible nuclear power industry expand commissioned but ahead expert continuing challenge make extremely difficult nuclear power industry expand small handful reactor project government agency decide subsidise forcing taxpayer assume risk reactor mandating ratepayer pay construction advance paper written cooper suggest cost nuclear power increase percent due increase safety oversight regulatory delay wake disaster fukushima fukushima mythical nuclear renaissance proven bubble air rapidly leaking fukushima make difficult inflate noted cooper commenting paper entitled nuclear safety nuclear economic fukushima magnifying economic problem nuclear renaissance faced problem plagued nuclear power history nuclear power suffered cost continuous cost escalation risk uncertainty long fukushima nuclear reactor disaster fukushima increase cost undermine economic viability nuclear power country conduct review japanese government recently estimated cost power nuclear reactor percent higher estimated year ago analysis show increase consistent impact mile island chernobyl cooper expert comment future nuclear industry nuclear regulatory commission memberpeter bradford currently adjunct professor nuclear power public policy vermont law school and formerly chair thenew yorkandmainestate utility regulatory commission recently following nuclear regulatory commission recent approval design reactor anticipated approval specific project georgia south carolina written nuclear revival important moment compare happen year industry expectation nuclear renaissance announced decade ago comparison performed properly clear witnessing revival collapse expectation reactor construction forthcoming project remain thirtyone reactor fantasy fleet constitute real nuclear renaissance recently early important understand collapse underway accident fukushima result nuclear power cost compared alternative fukushima unseemly effort nrc commissioner oust chair enhance appeal nuclear power factor vanished tomorrow pace reactor construction increase all carol werner executive director environmental energy study institute eesi piled negative sentiment nuclear energy enjoy considerable support congress significant subsidy escalating cost construction uncertainty adequacy safety design compliance earthquake virginia fostered realisation socalled nuclear renaissance simply choice provide greater certainty lesser cost enormous longterm unresolved problem risk facing nuclear power paper highlight entirety paper written mark cooper pdf viewed detail highlight pulled mood wading page nuclear science economic remainder piece that fukushima stimulated vigorous review world part severity accident part worst accident affecting nuclear reactor market economy part occurred nation assumed standard safety superb technical expertise challenge perceived responsible nuclear safety world wake fukushima accident substantial striking technical issue raised fukushima persistent institutional failure revealed comparison postaccident evaluation mile island tmi fukushima decade nuclear industry plagued failure voluntary selfregulation denial reality risk lack safety culture lack comprehensive consistent regulatory framework challenge continuous change retrofit existing reactor failure resolve important outstanding safety issue failure require existing reactor add safety measure cost complexity confusion chaos response severe accident global nuclear safety institution expressing strong concern advanced industrial nuclear nation aftermath fukushima command attention year extent damage challenge decommissioning unfold issue continue traction review stimulated accident limited safety issue wake fukushima reevaluation energy option nuclear risk economic substantially dimmed prospect construction nuclear reactor major policy review government led nation decide scale back abandon commitment nuclear power including important large industrial national likejapanandgermany financial institution conducted extensive reassessment economic prospect nuclear power concluded cost rise usb utility nuclear plant nation downgraded rating agency major firm advanced industrial nation abandoned sector forced scale back activity shaw group siemen areva cooper paper concludesas stakeholder reexamine aspect energy policy risk nuclear reactor increase attractiveness nuclear power compared option decrease image source chris yunker cleantechnicas completely free electric car report electric car early adopter follower want youd attend electric vehicle solar power event conducted cleantechnica date hottest cleantech new subscribing free cleantech newsletter eye sectorspecific new also free solar energy newsletter electric vehicle newsletter wind energy newsletter ","m_szGeo1":"United States","m_szSourceType":"source_industry","m_szSrcUrl":"http://cleantechnica.com/2011/12/30/tough-road-ahead-for-nuclear-power/","m_Places":["Fukushima","Japan","Haifa","Israel","Mark","Cooper","Us","U.s.","Three Mile Island","Chernobyl","New York","Maine","Georgia","South Carolina","Virginia","Germany"],"m_People":["Joshua S Hill","Peter Bradford","Carol Werner","Chris Yunker"],"m_Companies":["Paper","Vermont Law School","Nuclear Regulatory Commission","Nrc","Japanese Government","Ap","Eesi","Congress","Shaw Group","Areva"],"m_BiGrams":["nuclear power","nuclear reactor","nuclear renaissance","regulatory commission","paper written","nuclear industry","nuclear regulatory","power industry","nuclear safety"],"m_TriGrams":["nuclear power industry"],"m_SocialTags":[],"m_Topics":[],"m_Industry":[],"m_Technology":[],"m_BiCnt":[17,6,5,4,3,3,3,3,3],"m_TriCnt":[3],"m_iDocBodyWordCnt":666}
