{"m_szDocID":"262219","m_szDocTitle":"Tesla Model 3 Or Model Y Will Have Falcon-Wing Doors, Model Xs Recognize Each Other, & 7 Other Elon Musk Tweets | CleanTechnica","m_szYear":"2015","m_szDocSumamry":"Published on October 2nd, 2015 | by Zachary Shahan 145 Tesla Model 3 Or Model Y Will Have Falcon-Wing Doors, Model Xs Recognize Each Other, & 7 Other Elon Musk Tweets Originally published on EV Obsession . As tends to happen with any Tesla announcement, the media has gone a little loopy after the unveiling of the Model X . A lot of mainstream media reporters simply don’t understand some things or get their “facts” all jumbled in epic Fox News style (but inadvertently… rather than part of a massive evil plan). Tesla enthusiasts get loopy as well, of course, jumping into speculation land as they","m_szDocBody":"published zachary shahan tesla model model falconwing door model recognise other elon musk tweet originally published obsession happen tesla announcement media loopy unveiling model lot mainstream media reporter simply dont understand fact jumbled epic fox new style but inadvertently part massive evil plan tesla enthusiast loopy well course jumping speculation land connect dot elon rescue twitter hour ago elon started sending tweet clarify answer question tweet preceded subheading extra textthat spell nontwitter language add bit context tesla model recognise tesla model suvs recognise parked order prevent falconwing door opening other suweet ithink concern situationsin comment article tesla motor club forum supercool scifi solution hoping cautiously assuming wasntthe realworld storey friend brian henderson this anobvious elon answering recognise open elon musk lowerrange model built someday hottest topic ofconcern speculation tesla offer lowerrange model kwh battery similar version rated epa confirmed elon recently tweeted lowercost version planned wasnt super explicit what size battery when dont detail detail arent worked yet kwh something estimated time arrival month now wont start talking tesla time that month longterm reservation finally beunder control bit there tesla justholding higherpriced highermargin demand tesla achieve battery improvement rolling out anyhow here tweet month elon musk falconwing door masse tesla model tesla model recordshattering electric sedan suvs chief aim year accelerate adoption electric vehicle board cornerstone effort affordable tesla model incentive base architecture tesla model usedfor crossover version like model version model weve long tesla trademarked model yandmodel model model read sexy drop model lawsuit threat ford the model written solve existential problem dont recall elon stating crossover version model model maybe missed forgot annnnyyyyhow awesome new planning model wicked falconwing door model model yoohoo model model will elon musk wing dry speaking falcon wing concern people continuously bring but rain btw concern form fake quote super general falconwing door fear rain eat you cheque out door larger opening act umbrella upper interior trim hydrophobic coating elon musk upper interior trim hydrophobic coating elon talking make girl knee chatter damn sexy fancy siin word speaking responding comment driver super tight parking space not elon answer front door short arc interior panel chamfered back elon musk raise hand youve word chamfered past month engineer request you poor lady storage door live people dont model and like course arent pocket doorsbetween seat sticking paper tablet pen phone aruair mcgowan asked storage model elon positive answer storage live again door storage falcon door rubber lining prevent slip lot cabinet floor storage too elon musk roof mentionedpreviously conference call elon mentioned provided extra detail tweet cover base mount rack roof suction cup falcon door work fine guaranteed mph elon musk bioweapon defence philtre elon tweeted this reiteration presented night assume response lame media statement prove elon wrong note reference timeline good idea attemptthat daft chap head guy model bioweapon defence mode philtre viruse btw small one hospital operating room level filtering elon musk quickly came disappeared again sir elon rise again wing falcon wing bird eye peeled tesla magic way elon variously put larry playing joke something def elon musk cleantechnicas completely free electric car report electric car early adopter follower want youd attend electric vehicle solar power event conducted cleantechnica date hottest cleantech new subscribing free cleantech newsletter eye sectorspecific new also free solar energy newsletter electric vehicle newsletter wind energy newsletter tag elon musk tesla tesla model tesla model tesla model air philtre tesla model falconwing door tesla model zachary shahan tryin and specy letter time spend time cleantechnica director chief editor otherwise enthusiastically fulfilling duty obsession gas solar love planetsave bikocity president important media zach recognised globally solar energy electric car energy storage wind energy expert speak related conference event connect social media zacharyshahancom related post tesla autopilot steer car barrier autobahn construction zone robert pollock leased chevy spark year ago chevrolet people disarray didnt fast charging was car doesnt knew week close deal told numerous time dealership listened interest electric car end doesnt matter charge night sleeping pulled back deposit calling credit card company chevy month realise didnt paid level debate recover money bbb theyd switched lease sale manager responded side looked stupid quit all laughable experience chevrolet wanting stay forever happy day world bobnunny pinpointing fox new outlet fact wrong cnn reporting model tax credit plain wrong stick car new please rexseven falcon wing door f%king stupid them wont buy one doesnt will btw fox new new outlet slanted coverage political bias think stupid pay attention xander falcon wing door practicalthey flat koooool fox new doesnt slant newsthey outright lie recognise lack intellectual capacity employ critical thinking reasoning recognise understand credible source encounter rexseven once cool spelled oos thinking kool aid youve drank lot that first practical didnt put front door too practical cool second tesla proven build car work smart build low volume expensive car start with easier build low volume technology expensive expense car door expensive conventional door beside practical emphasise telsa hater buy cheap fit range drive quality compromised cost reduction effort here piece free advice youre big long elaborate sentence reason make smart dont spell word way sentence course started sentence citizen great britain united state citizen recognise did apologise defer dizzying intellect vizzini xander wowwholi schittand hear eye thot wood wus pissed yor koffee luk bin cot practical didnt put front door stooopid question stooopid question sliding door minivan practical didnt put front door too itz vissini vizzini coz recognise aknowlege yor disying intallekt eye defur promis pis yur koffee mor eye gotta spellin difrunt wayz wun sentense rex month that huh stand belief fws effect function negative price concern apologise starting conversation vulgar aggressive way provoke people doesnt accomplish much wuestenblitz buy buy car year build electric car chose decide jump bandwagon screw rest major automaker comprising safety health planet profit year top purchasing model nightmare consumer give crap bolt cheaper stand tesla put vote confidence elon action ethic tesla earned loyalty money willism elodee super easiest nlnee home opportunity all make extra cash month internet connexion computer make extra cashvisit dis profile oddly tall smart guy joe viocoe reliability concern power window out automaker reliability issue those subsequent generation engineering now power window dont break often tesla move fast engineering innovation teslas retractable door handle mechanic complex before yes tesla reliability issue too quick reengineer patch falcon wing door reliability issue yes quickly tesla address fix issue premium vehicle low volume phase quickly benefit risky innovation premium buyer automaker address issue quickly time falcon wing door hit mass market vehicle bug worked out neroden storage space door migrate year model design popular kas flacon wing door model noooooo noooo flacon wing ugly zachary shahan option wont doesnt doe samitha gamalath dont fit falcon wing affordable model sedan fit falcon door upcoming model kind offer normal door you love tesla bobwallace didnt add significant cost pick falcon yesterday town day haul recycle haul back couple week grocery etc easier loading loading stuff door swung way side hinged door lot closing opening order job done block path neroden trunk rear liftgate model bobwallace recognise door make easier falcon door side rich people concerned falcon door dont door design sunny weather concern weather rain sleet hail freezing rain snow wind back seat regular basis due infant toddler simple concept live geography cold wet wet season holding umbrella feet head umbrella all bobwallace youd feet tall order door feet head zachary shahan offering model choose falcon wing plenty would curious split preference samitha gamalath view prefer conventional door cheer xander hear curious problem personally run falcon door far smart phone dont expensive cord forget put then what forget plug battery dead then what least imagine samitha gamalath xander run problem falcon door dont vehicle falcon door main problem foresee dont centre attention public falcon door haha enjoyed reading description phone dont smart phone either nokia wouldnt call smart phone rexxsee give rejecting them please then samitha gamalath inspect work interested aspect tick falcon door fact back door vehicle public made spectacle vicinity stop stare selling point falcon wing joe viocoe new vehicle people wont stop notice price kinda point people pay good money attention samitha gamalath agreed car talking upcoming model joe viocoe time falcon wing door economy car attention grabbing samitha gamalath massmarket car manufacturer follow stick trend but long time people opening closing falcon wing door car normal sight dag johansen model falcon wing door heck model model designed affordable preclude overlycomplex expensive falcondoor bobwallace extra cost falcon door add extra pair hinge door motor sensor big expense modest expense time tesla producing car year assuming there marion offer model smaller annual volume model falcon door doesnt mod sedan roadster falcon door price point knetter dont forget truck truck mile supercharging elon pleeease neroden bev pickup tremendous underutilised market segment anti lord kelvin wait gigafactory full speed cell slightly enduring drivetrain kwh battery mile range half load mile range full load guessing zachary shahan extra cost falcon door add extra pair hinge door motor sensor big expense modest expense yes super curious engineering real hurdle big deal put cheaper vehicle anti lord kelvin extra cost important time put affordable model cost absorbed model sale that reason selling highend vehicle develop putting affordable vehicle ivor oconnor hidden cost ill super surprised door dont huge costly problem year discontinued bobwallace door car door repaired electric motor operate them properly selected motor outlast rest car body windshield wiper motor replace often power window motor replace often operate cycle door motor ivor oconnor door introduce set potential problem people car garage tree limb deal with sensor programming avoid problem sensor work covered dirt mud country road permutation edge case numerous tesla reputation uphold edge case cost tesla dearly bobwallace optimistic kid xander year ago bought car power window father warned danger said break accident car roll window crank sound him ivor oconnor handful window longer worked crank driven power window failed interesting dad rail problem happen tech true auto manufacturer hard time right fail year month take time factor correct obsolescence expect tesla completely overstep xander youve bad luck crank power window problem either radio fail transmission quit buying car causethat made sensewarned son well wouldnt listen ivor oconnor joe viocoe power window out automaker reliability issue those subsequent generation engineering now power window dont break often tesla move fast engineering innovation teslas retractable door handle mechanic complex before yes tesla reliability issue too quick reengineer patch falcon wing door reliability issue yes quickly tesla address fix issue premium vehicle low volume phase quickly benefit risky innovation premium buyer automaker address issue quickly time falcon wing door hit mass market vehicle bug worked out brent jatko heck model left wondering that myself googled photos sport car concept lamborghiniish bobwallace assumed tesla selling camry price completion path evs destroying icevs removing petroleum personal transportation showed ford played jerk made rich guess tesla model smaller version model model cuv built platform model model sedan doesnt stand anything complete acronym sxy michael acronym word sort inverse acronym actually think wait ivor oconnor michael link site initialism either point traditional acronym word made letter predefined existing phrase case word sexy driving dynamic letter dont stand word stand respective letter sort inverse acronym sort word this not tesla innovating ivor oconnor surprised word exist literature major lot time hand rich imo tesla foolish create sport car model platform create cuv small pickup truck market segment size each wouldnt make economic sense qkodiak gathered model iii sport sedan model sporty crossover debut simultaneously concurrently time joe viocoe gather info zachary shahan itll crossover version model zachary shahan strong word elon will decided hed model them larry fox new screwed surprise there reporter fox dont worry reporting fact storey straight prime objective misinform idiocy carolyn hoyt pay cheque working hour week online sister friend averaging monthsnow work hour week howeasy out xus ############################################################# brent jatko agreed read survey fox new watcher negatively impacted watching fox new word true information watching fox rich wasnt sad funny bobwallace agenda reporting toe party line idiocy carefully crafted larry affirmation bob totally agree change tone posting negative cynical hard fox concerned elon musk repeatedly warn development artificial intelligence forefront developing machine increasing decision making ability replace function previously performed human machine carry people mph door object detection sensor collision avoided communication necessary car computer communicate data potentially vulnerability developed mode future vulnerability incorporated owner accustomed car collectively making decision them decision previously made themselve threat artificial intelligence develop incrementally elon musk genuinely concerned development artificial intelligence demonstrate product produced tesla prepared slapped falcon door piss karl brewer word chamfer week ago zachary shahan crafty engineer pun intended riely rumfort random question zachary vendor cut cheque press all ronald brakel random question riely liar random suggesting advertisment reason random question riely rumfort nope wondering fund solely visit scratch back put new did world wouldnt corrupt routine happening capitalism ronald brakel income advertisment side revenue isnt lot labour love advertisment labelled ethically naughty thought suggesting zach unethical reply rude rude correct quick mark assume people troll lot know show claiming global warming human activity effect climate electric car result emission internal combustion engine car tad defensive riely rumfort cool goe crossed troll bridge myself zachary shahan tone hard grasp text nonfamiliar face here tone missed trolling happy wasnt zachary shahan yeah definitely missing question tesla avenue media world travelling down riely rumfort yes inquiry fund directly press release question answered zachary shahan dont tesla good new correction make mistake agree deserve something weve brought positive attention tesla site big site dont huge effect hey storey there anyhow though tesla crazy amount positive press merit happy part clear write sponsored content make clear covered company lot revenue solar leadgeneration ads site enable lot content thankful them send tonne people solar installer happy about defendor falconwing door masse noooooooo epic darth vader nooooooooooooooo didnt care model aspiration dont ruin affordable model them hate thing gimicky slow hell foot snow not live southern california bound endless wrong them imo falcon door easily worse tesla done joe viocoe buy model model falcon wing door making assumption door reviewed independently weve year problem door exist long start building gen vehicle juxxr cleantechnica start list stuff doesnt work foot snow confused brush snow work foot snow them ill start popuptoaster joe viocoe ridiculous people stretch argument foot snow require dig front rear window anyway time frozen morning dont rear door anyway juxxr lived scandinavia illegal drive road foot snow roof blinded car behind legal retardville neroden stupidville regard juxxr nicholas littlejohn foot snowon side car knetter happen wet snow stick martin place live picture clothesline snow picture power telephone line donut several zachary shahan solar panel rexxsee solar panel pronounced angle northern region slope dark colour melting snow clean panel sun ray over ground covered snow albedo hitting panel reach reflexion light power lastly electric device work cold true solar panel bigwu panel dont clear sun ray ambient temperature rise freezing remember panel airspace them typically warm airflow heat glass snow slide off freezing provided isnt wind clear couple hour sunlight light penetrate snow strike panel heat glass freezing bottom layer snow melt creating slick surface voil subfreezing avalanche rexxsee course expression poet clear surprisingly fast though bobwallace freezing provided isnt wind clear couple hour sunlight mine dont temperature freezing remember panel roof mounted snow shedding due escaped building heat mine ground mounted clear sun shining strongly back snow here rexxsee strange documentary solar farm ontario found snow blessing didnt manually clean thousand panel read dust problem array desert areas morroco like texture panel smooth enough karl brewer frivolity radar agree defendor arent assumption door slow hell complex mess open friggen door joe viocoe fair argument bobwallace wait tesla model dfd damned fast door ordinary car luxurious order call luxury car add feature not rexxsee slow car parked normal condition second open michael second pretty slow door heck moving mph amount time qkodiak automatic door minivan slow nonissue finding fault pointless dont problematic junk rexxsee door opening off qkodiak automatic door minivan slow nonissue joe viocoe tesla shown car moving door closed dont speed issue fast back seat passenger egress stand hook shuffle key fob start open door fully walk wont wait ingress either bigwu foot snow golden rule ethic reciprocity other which translated modern parlance dont dck youre travelling children yes youll forced abide golden rule set good example suppose solace fact induce whiteout condition hurl chunk ice unfortunate youre adult passenger the front door open norm totally dckish doable knetter mikedyke foot snow them open door snow rise door turn pushes rest snow side car instant roof clearing dag johansen dont worry model falconwing ghostdawg model them improved smaller kas yehhhh falcon wing ugly dont model model rexxsee hate thing blah blah blah presentation them not idea youre talking about xander defendor silly man ask foot snow falcon wing door live canada car snow roof car sweep off time sweeping front hood wind shield rear window trunk side window headlight tail light safety issue foot snow take longer big deal make sweeper designed good job this live snow zone car couldnt out waiti ityoure lazy clown drive road foot snow car hoping wind blow drive fast putting risk shit sake manjust buy sweeper martin cool clarification number thing one lot money yes wait scale model marion mead gms mile bolt coming hanlee chevrolet davis california end yes year beating teslas model arrival year price netting state rebate fed tax credit brent jatko good country tesla dicked shiny bauble foofoo halo car glitter toy missed mass market corner screw chevrolet vega eveee yeah what chance screw mary earning upto month working online laptop hour daily previously thought job tough contrast opinion easy easy job big money interested visit neroden tesla researched history successful startup car company discovered none started mass market started highprofitmargin highend car exception theyd managed pay r&d factory construction distribution network etc mass market tesla didnt choice startup company wanted avoid bankruptcy business model use company produce electric car mass market elon musk cheer goal rid fuelburning car brent jatko good point hadnt thought thank ivor oconnor researching successful startup basic economic sense learned day economic gravity qkodiak read post bolt wont compete model iii chevy sonic dont compete sport sedan bmw sery model iii techfilled sport sedan size model crossover version called model tesla seat hypercar robert pollock half people meet real detail evs pevs thing discouraging number people ideas head energy ontario canada year ago learned science school physic math chemistry biology geography lot history dropped year public school wife american citizen told classe memphis grade student couldnt read write dont read rich assuming delivery gap model delivery isnt year assume tesla pull delivery date model assume chevy bolt production limited car desirable mile range limited production capability forgiven thinking chevy bolt compliance car cali easily consume car martam based teslas missed deadline marion correct musk send teaser ground breaking super baduper modification model justify delay musk delayed teslas product release rich argument missed deadline tactic stall people report indicating gigafactory ahead schedule tesla model announced preorder make judgement call time model reasonable mass market bev engineered mess give good indicator reasonable timeline knetter gigafactory received occupancy permit thursday supposedly making cell spring bolt drop hat shortly rexxsee intelligent people assume blindly happened model quick growing disruptive unusual company occur future tesla needed money model build model wild success model main reason delaying door two year door silly put energy model main goal audition zachary shahan shecky vegas enjoyed him wondered went gene marion hope embarrass you arriving sorry pleased did built endorsement taking ice good health consumer good industry tesla included car road ice plenty growth evs maker elon stated coming bolt good pleased all car point keanwood source that wikipieda production awesome production end martin problem live canada selection evs bit dismal incentive lot that place incentive john locke false nextgen volt mile charge mpg process shipping state bolt concept car production expected begin rumour begin early qkodiak tesla production model iiis late volume delivery dont care bolt year highly doubt will chevy sonic dont compete bmw sery audi jaguar tesla model iii competitor awesome bobwallace bottom show type car mod competing out midk group qkodiak yes important note similar price competitor make people argue electric make competition mind buy electric couldnt care performance compete bolt nissan leaf chevy volt compliance owner potential citycar owner tesla model iii larger segment small midsize sport sedan suvs anywhere type vehicle charle great sort speed charger network chevy have michael yep afraid mms dropped point back kind assertion source please reliability rating lol robert pollock signed chevy spark jerry brown cash chevy coughed back deposit read previous post that chevy paid month payment gave bosch level charger amount pay car slightly spend month gasoline tacoma mile maintenance front tyre all dont pay electricity use public charging station palm spring niece toronto pay month public transport wife drive car work day far tarpaulin now put mile year ice car saving thousand gasoline less maintenance insurance rate dropped due fewer mile put wife car pay spark advertised ","m_szGeo1":"United Kingdom","m_szSourceType":"source_industry","m_szSrcUrl":"http://cleantechnica.com/2015/10/02/tesla-model-3-or-model-y-will-have-falcon-wing-doors-model-xs-recognize-each-other-7-other-elon-musk-tweets/","m_Places":["Tesla","United States","Most","Barrier","United Kingdom","Southern California","Well","Ontario","Morocco","Canada","California","Memphis, Tn","Cali","Bosch","Tacoma","Springs","Toronto"],"m_People":["Zachary Shahan","Elon Musk","Elon","Brian Henderson","A Ruairí Mcgowan","Robert Pollock","Chevy Volt","Happy Days","Holi Schitt","Coz I","Joe Viocoe","Dag Johansen","Marion Meads","Ivor O’connor","Michael B","Carolyn Hoyt","Ronald Brakels","Nicholas Littlejohn","Shecky Vegas","John Locke"],"m_Companies":["Fox News","Twitter","Epa","Google","Bbb","Cnn","Hinged","Path","Seat","Nokia","Hinges","Lamborghini-ish","Did Indeed Use","Indeed","Damned","Startup* Car Companies","Bmw","Mpg","Audi A4","Jaguar","Palm"],"m_BiGrams":["falcon wing","tesla model","falcon door","elon musk","zachary shahan","wing door","foot snow","joe viocoe","power window","falconwing door","fox new","electric car","mass market","ivor oconnor","reliability issue","samitha gamalath","front door","model iii","model tesla","crossover version","version model","low volume","brent jatko","sport sedan","riely rumfort","door model","electric vehicle","robert pollock","practical didnt","didnt put","put front","door minivan","time falcon","affordable model","door dont","smart phone","extra cost","door motor","mile range","model them","artificial intelligence","random question","solar panel"],"m_TriGrams":["falcon wing door","practical didnt put","didnt put front","put front door","time falcon wing"],"m_SocialTags":[],"m_Topics":[],"m_Industry":[],"m_Technology":[],"m_BiCnt":[17,16,16,14,13,12,10,9,8,7,7,7,7,7,6,6,5,5,4,4,4,4,4,4,4,3,3,3,3,3,3,3,3,3,3,3,3,3,3,3,3,3,3],"m_TriCnt":[11,3,3,3,3],"m_iDocBodyWordCnt":3513}
