{"m_szDocID":"262240","m_szDocTitle":"Wonderful New Tesla Fan Commercial | CleanTechnica","m_szYear":"2015","m_szDocSumamry":"Wonderful New Tesla Fan Commercial Originally published on EV Obsession . It’s hard to call this the best Tesla fan commercial yet since it doesn’t really highlight any of the Tesla Model S’s awesome features (other than it’s cool look). “ Gallons of Light ” was certainly an awesome commercial that is hard to compete with. But hey, it’s not about competing — it’s about putting one block on top of another to build an awesome electric castle… er, something like that (I have a baby and spend a lot of time playing with blocks). Without any more rambling, though, let’s get to the goods: Tesla – Fir","m_szDocBody":"wonderful tesla fan commercial originally published obsession hard call tesla fan commercial doesnt highlight tesla model awesome feature other cool look gallon light awesome commercial hard compete with hey competing putting block top build awesome electric castle baby spend lot time playing block rambling though let good tesla firefly sam ohare vimeo stunning make learn more make touch test model ford learn fan here realfootnote ford freakin fan commercial tesla fan making insanely awesome commercial electric work art free charge tesla league now seriously ford resource compete tesla engineering front full disclosure huge fan firefly theyre favourite thing long tsla obvious reason cleantechnicas completely free electric car report electric car early adopter follower want youd attend electric vehicle solar power event conducted cleantechnica date hottest cleantech new subscribing free cleantech newsletter eye sectorspecific new also free solar energy newsletter electric vehicle newsletter wind energy newsletter tag commercial ads commercial tesla tesla model zachary shahan tryin and specy letter time spend time cleantechnica director chief editor otherwise enthusiastically fulfilling duty obsession gas solar love planetsave bikocity president important media zach recognised globally solar energy electric car energy storage wind energy expert speak related conference event connect social media zacharyshahancom related post awesome gorgeous fred gazillion dollar car powered battery made chinese child labour toxic chemical earth american imperialist machine jameswimberley evidence child labour chinese children cosseted forced work hard school shane but seriously ford resource compete tesla engineering front not taking billion hit struggling pay engineer apple billion cash reserve planning car margin business fewer due confluence autonomous vehicle sharing economy apple cook ego project matt sharing economy thinking driverless way regulation insurance not note software company hardware experience tesla started mind set big car manufacture mechanical software year working software department difference mind set oic tesla model teleported future electric firefly matt thought firefly convert gas station tesla super charger attached dinner tesla pull recharge driver grab burger notice time flying jump back way zachary shahan company owner made commercial own zachary shahan dont recall any mistereman nozzie youtube favourite beautiful sam ohare true artist love newer model design too elon franz note zachary shahan yes car model zachary shahan yeah good forgot about lazy which michael ford compete tesla apple orange tesla absolutely coolest car world question completely totally love but tesla price bracket end porsche mercede ford compete market overhead make money mass market car fact make money truck suvs goody people brand hope theyll move day ford working bug volt energi mass market car remember car sale car volt energi cmax affordable people but tesla wildest dream stop mass market cos compete tesla dog dog cat cat urging cat dog pointless bobwallace sure gold plated see see tesla neenerneener convincing yourself ford depend caddy lincoln theyd business sale ford chevy silverados light bobwallace michael claimed tesla price bracket ford compete market gave multiple example ford vehicle priced high higher teslas offering ford manufacturing car time expensive tesla arent oop youre wrong move michael heaven sake goldplated ford competing porsche mercede wrote ford compete market doesnt dont make occasional car new give engineering dept play draw dad showroom sell mom minivan statement wrote correct bobwallace heaven sake posted incorrect ford sell car price range tesla mean competing market competing buyer spend car furthermore tesla price bracket end porsche mercede expensive tesla cheaper end mercede porsches joseph dubeau ford taurus tesla killer fred grow close car notice model smaller clever giving sneak peak model prototype design base price compete bmw sery affordable larger auto market marvel boehm week bought brand mclaren making week andover pastmunth coolest work began month ago straight started making cool perhour learn ############################# brunurb made random person tesla employee right willism elodee super easiest nlnee home opportunity all make extra cash month internet connexion computer make extra cashvisit dis profile ","m_szGeo1":"United States","m_szSourceType":"source_industry","m_szSrcUrl":"http://cleantechnica.com/2015/10/04/wonderful-new-tesla-fan-commercial/","m_Places":["Tesla","Oranges","Lincoln","Silverados"],"m_People":["Zachary Shahan","Sam O","Michael G","Joseph Dubeau","Marvel Boehm"],"m_Companies":["Vimeo","Audi","Apple","Google","Youtube","Volts","Volt","Bmw 3 Series"],"m_BiGrams":["zachary shahan","compete tesla","ford compete","tesla fan","fan commercial","electric car","tesla price","price bracket","porsche mercede","compete market","mass market"],"m_TriGrams":["tesla price bracket","ford compete market"],"m_SocialTags":[],"m_Topics":[],"m_Industry":[],"m_Technology":[],"m_BiCnt":[5,4,4,3,3,3,3,3,3,3,3],"m_TriCnt":[3,3],"m_iDocBodyWordCnt":635}
