{"m_szDocID":"262245","m_szDocTitle":"Chevy Bolt In Action (Video) | CleanTechnica","m_szYear":"2015","m_szDocSumamry":"Chevy Bolt In Action (Video) Originally published on EV Obsession . Sure, the Tesla Model X is great and everything, but how many of us can actually afford one of them? On that note, a new video of a Chevy Bolt mule in action has come to my attention. (The video is not super new, but this is the first I’ve seen it.) While much still remains unknown about the production version of the Chevrolet Bolt, one thing that we do know is that it is supposed to be fairly “affordable” — and will perhaps be cheap enough to see particularly strong sales (meaning stronger than the Nissan Leaf or Chevy Volt p","m_szDocBody":"chevy bolt action video originally published obsession sure tesla model great everything howmany afford them note video chevy bolt mule action attention the video super new ive remain unknown production version chevrolet bolt supposedto fairly affordable cheap strong sale meaning stronger nissan leaf chevy volt plugin here video enjoy cleantechnicas completely free electric car report electric car early adopter follower want youd attend electric vehicle solar power event conducted cleantechnica date hottest cleantech new subscribing free cleantech newsletter eye sectorspecific new also free solar energy newsletter electric vehicle newsletter wind energy newsletter tag chevy bolt jame ayre background predominantly geopolitic history obsessive interest pretty everything early life spent imperial free city dortmund jame river ruhr cofbuokheim attended university astnide briefly considered entering coal mining business write living broad variety subject ranging science politic military history renewable energy follow work google related post rexxsee agree nuclear stupidest tech human with generate electricity efficiency electric motor time ice make choice case renewable sun wind growing fast eveee word bolt based platform give frame reference trax taller sonic similar length shorter leaf trax sonic nissan leaf this trax shorter taller leaf expect aero similar drag higher compared leaf due increased frontal area passenger space good trax review bolt competition leaf model emphasise performance style bolt wind higher priced leaf similar size mean price drop lower range leaf increase battery performance end competitor mid price area range zachary shahan thank great bobwallace day transition fossil fuel renewable growing fossil fuel decline below watch spread greatly accelerate rexxsee source link graph above bobwallace you kyle field talked rep alt car expo week back left impression not bolt production model great decision truei hate talking inevitable confusion start volt bolt volt car called boltlike lightning bolt zachary shahan omg smart decision eveee notice rear end bustle sticking leaf large fastback rear end aero drag better hurt highway range interior space utilisation good small honda fit size kyle field looked bit smaller fit person looked shorter longer chevy sparkbut small ford fiesta good comparison size eveee trax shared platform bigger fit benjamin nead photo post above showing bolt leaf taller wider nissan joe viocoe camera angle favouring bolt benjamin nead bolt tiny urban legend isnt settled tape measure present brent jatko agreed spec decide knetter bolt angled exposing side making larger slightly taller bet farm smaller benjamin nead large farm eveee picture bolt based trax shared platform though benjamin nead finding real measurement chew expected leaf bolt similar size chevy address reliability concern electric version entry level ice indication link what exactly troublesome sonic engine transmission issue table version late year wife gas burner reliably road phoenix occasion son school decent economical ride town rented small car evaluate there spark felt good freeway air conditioning kind wimpy started reading review noted air underperforming car prone outright failure death arizona car quickly dropped list ended honda fit and year happy side note week wife fit online excitedly called laptop inform fit led explain concept compliance evs etc once finally sunk time explained her eveee benjamin fit nice car bad spark air conditioning forward alternative field choose from desert southwest difficult environment car evs included sonic repair primarily engine electrical bolt bit lower clearance trax heavier post share trax told share sonic sonic trax share other make sense make roomy height brent jatko small honda fit size limit appeal benjamin nead model fanboy obsessive bolt size thing people pissy fit aspect dimension smaller wait out rexxsee polarising debate tesla fanboy making emotional motive rational argument spreading gossip model officially announced period benjamin nead scheduled unveiling model spring ive heard sincerely doubt delivery customer occurring year fanboyism reality explanation point rexxsee mistaking unveiling schedule spring production late bobwallace introduction march production gigafactory producing number needed bobwallace march tesla introduce model then big difference tesla put battery tesla building car ground mod approach battery way freeing lot interior space small exterior good large interior good large safe interior very good eveee introduction date similar time late tesla reveal spring production production beginning late year bolt electric car sale early either model wait joe viocoe tesla dont automaker build concept car early out nimble benjamin nead back not ballyhooed flapping wing door model start breaking year schedule tweak sound real world car maker delay nimble didnt mess that model reality now rexxsee yearsthe delay partly huge success model giving urge cash important publicly marketing suicide benjamin nead year delay current higher end awd iteration tall version flapping door dont slamming tesla succeed incessant cheering tesla internet fanboy bit shrill time rexxsee sir model perfect platform test improve technology found model yeah succeed exaggerated delay door fail dont understand history plan young bold company opposite fanboy hater paid bash tesla threat ice car dont yet benjamin nead tesla hater youre obsessed fanboy youre practically foaming mouth adoration pathetic ive owned apple stuff close decade annoyed apple fanboy well dont live real world and anybody salary promoting dissing anybody make year university job ride bicycle work dont give shit car resent cognoscente telling good buy wont mile charge accelerate mph second tesla build beautiful evs afford model base sticker price lower bolt gen leaf stripped level leave factory door price point more rexxsee insult crystal ball tesla real world zachary shahan comment personal highend car people love them theorise colour tesla bit make conclusion teslas capability aim objective course theory make sense people obsess highperformance car people make them benjamin nead yes electric car good making dent pollution climate change etc happen million ten thousand therefore stand comment electric car dont good write impressive magazine internet copy bobwallace tesla capacity produce mod modx expensive evs year year half million evs road tesla opened assembly line fremont plant assembly plant netherland benjamin nead yeah good dont pegged tesla finally make priced sooner later company build affordable evs possible bobwallace watch new gigafactory progression tesla release battery power interested nissan react couple mile evs dont sell mile evs price closer solid mile real seller zachary shahan dont worked here difference opinion happened tesla why extreme language other weve calm thought situation logical conclusion match place dont other true storey info future along joseph dubeau people short memory joe viocoe model constrained gigafactory model delay dont affect model complexity contributed model delay importantly model tesla grand plan addition model test bed demonstrating innovation people shouldnt feel entitled model timetable zachary shahan underdiscussed model delay tesla production constrained year rolled time serious problem people vehicle ordered timely fashion imagine elon thought well demand serve let knock park this course doubt thought baseball terminology rexxsee now tesla delivered will judging quality sell model wont competition model now difference audi electric corner dont them successful mass car company model awesome them zachary shahan honestly too trying large automaker supercharger network indication partner tesla bobwallace recently hinted thinking rapid charger issue zachary shahan rapid sae combo supercharger operated else call bobwallace short comment interview finding now detail sort provide rapid charging statement zachary shahan thank mentioned time source tell doesnt sound solid plan put thousand superfast charger place world theyll partner tesla swallow pride bobwallace advantage multiple system big advantage system all hate gas station toyota gas station imagine problem drove car low volume manufacturer zachary shahan agree wondering head exec wishing room matter discussed them supercharger network thinking damn compete that clearly lowrange evs market anyway afraid pride partner tesla the nerdy outsider embarrassing them bolt hope wrong alternative bobwallace car company dont throw tesla create generic charger system due akin jealousy musk pretty creating legitimate car company grab significant market share hes establishment hes big car ceos dont skill set accomplish freeze tesla out unlikely tesla clear path competitively priced long range evs teslas demonstrated attitude customer basically dont car manufacturer suspect teslas top level team deep lost musk step front public face tesla general philosophy roadmap baked company now apple cooperated secured significant part market due product innovation quality suspect tesla huge amount market way steve great new advertising come volt fan paint job terrible charging plug huge dont volt tesla plug bobwallace yeah seagull poop wont show paint scheme jeffhre volt plug fast charging added volt charger fastcharge option youre facetious proprietary concealing wrap hide actual configuration bolt mule right nicholas littlejohn volt thought good mph jeffhre mistyped apology omega centauri remind ship camo bet purpose make actual contour hard discern charge port test prototype expect actual production car port nicholas littlejohn confuse dimension measurement sae combo plug adrian spec voltstyle plug maxesout plug maxe said nicknamed frankenplug reason tesla solution elegant benjamin nead sae combo smaller chademo calamityjean paint job terrible what swirling curicue one thought looked cool bad expensive actual car sale rexxsee medium size bolt compact bigger spark price bargain sale strong wide compliance car eveee sharing platform ice doesnt performance optimization marvel boehm week bought brand mclaren making week andover pastmunth coolest work began month ago straight started making cool perhour learn willism elodee super easiest nlnee home opportunity all make extra cash month internet connexion computer make extra cashvisit dis profile benjamin nead bolt tiny photograph leaf appear larger nissan ive hearing year production car take convert shuttered plantsto increase battery production and know telling joe viocoe careful optical illusion angle darker leaf hide longer rear end brightly coloured bolt show all point camera capture bolt slightly broader angle too rexxsee picture discussed dark colour angle sun aero dynamic front make leaf smaller easily sell year benjamin nead hand bolt tiny one yet popular sell time theyre make year here photo combo people standing car leaf closer leaf bolt larger tesla tesla doesnt exist wont rexxsee tiny compact smaller leaf roomier dont potential demand electric sell easily price tag price small car mind tesla bigger step tesla include small car cheap contrary model reason delay model physical building facility money main goal tesla accelerating abandon fossil fuel model massively produce mean energy benjamin nead tiny small car fairly obvious number photos bolt size leaf well nobody complaining leafsized mile charge cost yes mind tesla want due full scale mockup drawing etc spring youre customer delivery car late early ive brooklyn bridge sized chevy sell you and dont small super cheap follow model happen tesla simply company dna speed luxury time ive luxury marque attempt market result enthralling bobwallace dont small super cheap follow model happen tesla simply company dna speed luxury benjamin involved development evs understand teslas game plan stage roadster luxury building battery manufacturing move stage midk long range assume give plan build long range affordable camry benjamin nead actually havent heard projection what tesla past model fairly recent speculation ive site roadster offing guess end performance car cheap tesla pickup truck built model template dont market that tesla article dating blue star common shai agassis place thing discussion tesla forum didnt read post plenty folk coming conclusion model lowbrow tesla market left push lot car door price point japanese korean and increasingly chinese indian concern bobwallace long term plan build wide range model including affordably priced family car overarching purpose tesla motor and reason funding company expedite move mineandburn hydrocarbon economy solar electric economy primary exclusive sustainable solution benjamin nead well sure link back further and affordably priced family car relative term richest people planet all median price car day fairly charitably call affordable realising great car financial stretch model didnt model doesnt direct electric competition honestly compared evs price thousand dollar similar range charge cheap tesla plan earliest crowded field evs price range tech company apple making then tesla sort mercede evs theyre comfortable offering luxury sedan price bracket havent felt compelled offer spartan sery memory serve upper price range back early mercede suddenly car cheap entry level toyota existing clientele baffled disgruntled idea owner dont idea model theyre attracted existing car performance luxury status object idea bobwallace musk rest tesla team touch dont realise affordable family car mean camry corolla arent aware toyota camry largest selling car selling car car musk rest team longer interested changing world drive petroleum fixated luxury brand benjamin nead sounding condescending question off price selling car median price car sold thing appear called earlier put model bolt gen leaf squarely median price category and tesla fully committed electrification car absolutely build cheapest evs road plainly obvious theyre milking cow moving downscale carefully methodically theyre dumb accusing cheap wellmonied investor company management start worried brand damaged bobwallace moving carefully methodically scale step mod youve tesla interested building some cheapest evs road dont finish job electrifying personal transportation obviously company sooner tesla reason expand niche but attempting pound square peg tesla round hole company ignore bobwallace btw there mody version mod mod people car tesla decide make reasonable profit drop price mod cost producing drop charge kwh battery charge thousand battery price drop making gross profit margin dropped price battery price fell cut gpm making difference volume stated repeated goal kill petroleum personal transportation tesla mody coup grce benjamin nead yeah heard day here green car report forget exactly remember elon comment attached falcon door doesnt sound camarykilling price buster said tesla flash dazzle faithful lusting that hope youre right bob dont tesla imiev smart market anytime soon alternate scenario produce budget line smart mercede way doesnt carry tesla nameplate share part supply networking engineering see bobwallace dont reason continuing subcompact sized car moving corolla sized machine wont expensive utility lot higher small person pod urban areas driverless taxis different caught stuff imagine tesla variety evs drawing monitor wont commit model time modx side project wait ample battery supply sell higher volume car mod time theyre cranking large number mod understand manufacturing car battery big boy volume battery lot advanced time start firming move roadster side project bring sweet deep pocket money gain lot free advertising kick butt justjim tesla mercede evs mercede produce smart car line car tesla wont produce car edison division produce low cost car bobwallace suspect people making mistake apply business school thinking tesla appear type beast apparently folk running company sat long list car company run accepted gospel dealership dont them model annually that sell abandon nope sell continue free possible spend megabuck advertising negatory spend advertising avoid weakening luxury brand selling inexpensive car logo wait play out eveee trax interior passenger space generous bobwallace chem appear building battery plant read prediction manufacturer battery pack worth cell year however output spread manufacturer supply limited finishes expansion put price range teslas pack price running price sink icevs bolt lot interior space leaf battery low tesla teslas skateboard lot interior space help provide huge amount protection side impact damage eveee rumour bolt based trax platform give frame reference nissan leaf this trax shorter taller expect aero similar drag higher due increased frontal area rexxsee wheel same bolt smaller trucated ice compartment eveee picture bolt taller leaf expected trax dimension mini suv good marketing move people recognise such eveee tall short package make nose blunt trax intended suv like nose appear blunt stick more bolt nose tapered vertical tall car dont increase drag frontal area greater good range eveee imo bolt wheel larger photo contributed benjamin bolt leaf side side bolt taller thing looked front comparison trax bolt bit more grille part bulbous both bolt appear shorter hood doe windshield longer sloped front more good lowering aero drag trax traditional front windshield make hood longer truncated ice compartment theorising area front wheel ahead passenger compartment same zachary shahan biggest hope car aiming higher cautious public target statement real evidence support theory plenty bobwallace good year number hasnt tesla has created demand evs advertise bolt make public aware theyre force dealer sell them produce assembly line year holding production line demand expand number line year production constrained battery supply year battery manufacturer ramp production needed enable larger number hope produce good attempt knock park zachary shahan here lot good point honestly shaking knee thinking competing model industry hot tesla dominate desire fan cautious target gms shoe aiming surprise pull tonne customer racing bolt too advantage head start ","m_szGeo1":"United States","m_szSourceType":"source_industry","m_szSrcUrl":"http://cleantechnica.com/2015/10/04/chevy-bolt-in-action-video/","m_Places":["Tesla","Us","Free City","Dortmund","Arizona","Well","Toyota","Corolla"],"m_People":["Chevy Volt","James Ayre","Zachary Shahan","Benjamin Nead","Joe Viocoe","Ev I","Joseph Dubeau","Steve N","Nicholas Littlejohn","Marvel Boehm","Shai Agassi"],"m_Companies":["University Of Astnide","Google","Volt","Bustle","Nissan","Phoenix","The Thing","Apple","Audi","Sae","Supercharger Network","Path","Brooklyn Bridge","Guess","Tesla Motors","Grace","Lg Chem","Lg"],"m_BiGrams":["benjamin nead","zachary shahan","electric car","interior space","joe viocoe","small car","car company","chevy bolt","nissan leaf","bolt based","frontal area","fossil fuel","rear end","honda fit","bolt tiny","lot interior","real world","car dont","evs road","evs price","model delay","partner tesla","sae combo","long range","car cheap","family car","median price","price range","selling car"],"m_TriGrams":["lot interior space"],"m_SocialTags":[],"m_Topics":[],"m_Industry":[],"m_Technology":[],"m_BiCnt":[19,11,5,4,4,4,4,3,3,3,3,3,3,3,3,3,3,3,3,3,3,3,3,3,3,3,3,3,3],"m_TriCnt":[3],"m_iDocBodyWordCnt":2663}
