{"m_szDocID":"263184","m_szDocTitle":"Chevy Bolt Battery Cells = $145/kWh, New Chevy Volt With Autonomous Driving | CleanTechnica","m_szYear":"2015","m_szDocSumamry":"Chevy Bolt Battery Cells = $145/kWh, New Chevy Volt With Autonomous Driving Originally published on EV Obsession . GM’s electric vehicle (EV) ambitions seem to be shaping up nicely going on recent comments made at an investor conference. Amongst the interesting comments, one stood out in particular: The company is now claiming that the launch of the Bolt EV will be accompanied by battery cell costs of just $145 kilowatt-hour (kWh) — very low. Impressive numbers if they pan out. While $145/kWh is already low, GM is projecting they will get down to $100/kWh by 2022, as you can see in the graph a","m_szDocBody":"chevy bolt battery cell chevy volt autonomous driving originally published obsession gms electric vehicle ambition shaping nicely recent comment made investor conference interesting comment stood particular company claiming launch bolt accompanied battery cell cost kilowatthour kwh low impressive number pan out low projecting graph above interesting comment include assertion bolt launched end year end note current chevy volt possessing hardware needed autonomous driving mode interesting comment profit margin volt plugin phev higher profit margin generation volt thank bro volt forum this subject future company interest potential autonomous car sector apparently starting heat company deploying fleet autonomous chevy volt warren technical centre campus employee facility book ride autonomous volt carsharing app designed company basically press button app smartphone car pick anton wahlman summarise data gathered deployment aim company autonomous vehicle team note recently revealed super cruise autonomous feature deployed part upcoming cadillac topic ceo mary barra recently stated convergence rapidly improving technology changing consumer preference creating inflexion point transportation industry decade massive change daunting opportunity disruptor decade leadership vehicle connectivity fundamental quest redefine future personal mobility cleantechnicas completely free electric car report electric car early adopter follower want youd attend electric vehicle solar power event conducted cleantechnica date hottest cleantech new subscribing free cleantech newsletter eye sectorspecific new also free solar energy newsletter electric vehicle newsletter wind energy newsletter tag battery cell cost chevy bolt chevy volt lithium ion battery cell cost lithiumion battery cost jame ayre background predominantly geopolitic history obsessive interest pretty everything early life spent imperial free city dortmund jame river ruhr cofbuokheim attended university astnide briefly considered entering coal mining business write living broad variety subject ranging science politic military history renewable energy follow work google related post driver car ice bobwallace guess human driver ice car sense traction loss faster make decision direction turn wheel faster car maintain speed traction possible unlike human engineer smart autonomous vehicle havent figured engineer smart driver americaputfirst hope made usa buick version rawlasvegan great article thank jame cost expectation big new jonathan wankasky drive make cheaper later remember flat panel dollar people bought made current crop flat panel sold cheap hope happen electric car jonathan wankasky battery half cost current evs car dollar bye nissan leaf battery kwh battery quick onstar wifi standard kid love watch netflix back seat standard motor dollar build saving faster production drive train fuel car take min instal electric car min mention fewer part emission sensor belt water pump starter plug rack heat gas fact storey electric car battery make cheap gas car extinct electric car reliable effect middle east gas oil money broke isis sleep night bobwallace sold battery sold battery price drop mile range shorter range mile plain jane pretty kill petroleum people pay bit evs fuel saving covered additional loan payment jenny sommer make bigger time buy compact van kid drive car juxxr bob optimism alway youre oracle purely mathematically involve kwh battery pack that itd kwh that cell cost add pack cost cell cost bobwallace teslas kwh mod epa range rating mile pretty big car smaller lighter sort mileage kwh close that cut vehicle weight cut battery needed cut battery weight cutting battery weight mean fewer battery here throw mix battery capacity increasing energy stored lighter battery mean here interesting read evs battery youre hurry skip model iii knockon effect expectation cell price drop gigafactory running fully tuned make battery pack kwh pack battery econobox mile range kwh battery orical selfappointed scout probe enemy line forward juxxr yep kwh doesnt equate bobwallace didnt start kwh you kwh bit confused detail point let cycle back jonathon battery half cost current evs car dollar bye nissan leaf battery kwh battery quick kwh battery kwh around battery depending size one one around juxxr confused were mikedyke mean kwh powerwall approx battery add bit youre half original selling price liking figure vensonata right thinking kwh powerwall which kwh add electrical conceivable storage cent kwh problem chemistry battery bolt low lifecycle battery price irrelevant question battery maker lifetime cycle karl brewer chem battery interesting compare kwh price manufacturer product work kwh math pant jen stubbe powerwall guaranteed kwh storage capacity reality hold approximately extra cell capacity meet guarantee avoid deep cycling damage battery cell give lower price slightly more steve world wide car market car real shot evs sold world wide add automated driving shrink car market making head way put year pushing market evs let hope rest big car maker forced board start selling oil stock calamityjean start selling oil stock sold mine good riddance put year pushing market evs gas station trouble staying business electric car market number gas station drop rock gasmobile crusher hard fuel for worn out evs dispatchable load promote acceptance renewable electricity generation turning evs charging balance variability wind solar power inexpensive solar wind turn make charging cheaper ricegf ive played model anticipated well changeover smoker evs based disruptive technology succeeded lifetime evs longer reach quarter market problem average life ice vehicle year tipping point mainstream thought begin technology inevitable begin buying hesitation average product lifespan tesla announcement given excellent market reception start shift evs exceed half market putting quarter market trend typically accelerate time however timeline mine hope youre wrong bobwallace car purchaser drive lot people drive older car car driving car year newer mileage driver year benefit fuel saving average driver mean make sense pay extra dont drive market push market people something personally fight climate change pay bit extra forcing factor cool factor driving latest thing leaving sitting red light finally chance year average pushed number car linger year driven little lot churning car average year lot car crusher age breaking forbe average age car year eta exporting lot car evs car sale simply supply limitation major manufacturer toying evs talking limited manufacturing evs year bolt lot concerted effort battery plant capacity million car dont movement manufacturer tesla mile affordable evs road buyer interest proven onehundredbyfifty dont movement manufacturer tesla mile affordable evs road buyer interest proven laying ground work ready ramp market prove out pretty development way challenging figure however agree hard part hitting volume battery tesla positioned scale dont hard scale electric motor leave car company brake styling body glass painting interior marketing battery remember order build gigafactory tesla prepped additional site running pretty quick ramp additional factory needed remember time consuming front approval done add subsequent approval smoothly state missed job pay significant economic boost state longer speculative venture doubt tesla pretty nice option subsequent siting zachary shahan smoker evs love zachary shahan gas station trouble staying business electric car market number gas station drop rock huge doesnt acknowledged enough rexxsee disclosing strategic move pay that justify price hybrid coming bev zachary shahan dont legal false information presentation that bobwallace correct leave company open suit stockholder argue mislead misinformation suffered loss stock based company claimed rexxsee way hide transaction russell guy then illegal true something bobwallace fairly believable fact financially risky make incorrect claim information major research tesla paying panasonic cell ive claim price fallen expected price fall gigafactory running making complete battery pack cell price fit price higher predicted panasonic cell price breakdown material panasonic cell find cost current market price anticipated cell price drop cell price lower large scale manufacturing create drop material cost vensonata kwh bolt battery math reliable mile kwh cell cost minus profit build rest car adrian encore base msrp trax plenty budget rest car sell rebate leave build rest car profit naysayer remember original volt price launch optioned nicely spark battery spend balance fastcharge infrastructure eveee depend aero drag marion mead kudos team cheating involved battery range price extreme qualifier forgot mention overhyping range price car cheating emission either adrian dont marion gms word moment spec havent shared yet target richard foster confused top graphic cost theyre effectively current battery price great price stagnate level year until doesnt make sense current falling price market true cost now expect barrier breached mind marion mead timing related completion gigafactory gms partner partner achieved manufacturing breakthrough reduce price leaking time build competition teslas gigfactory gms invested partner gigafactory push adoption faster faster adrian locked price year lose money make couple year contract richard foster graphic price fixed forecasted case now current trajectory battery price itll lower sure rexxsee disinformation battery entering exponential curve solar panel hit year ago demand soaring price falling solar reached point electricity cost coal demand skyrocketed market nowfull speed ahead richard foster quite supply battery doesnt match demand price fall modulated that rexxsee tesla built gigafactory quickly changing now car maker choice order battery eveee smell marketing graphic here real photo battery production assembly factory easy ship data sheet volume marion mead tweet musk one musk bring price battery sell other tweet lower company them real price war tweet musk benefit all kyle field tesla charging premium battery charging premium car dont model work home storage innovative flexibility time being imagine selling battery externally long volume remain strong devon harris make month onlinee internet connexion computer make extra cashvisit pro file infovdfd eveee said zachary shahan spammer telling cousin made working online that tonne everyday roadkill zachary lie awake night wondering emc lost cos moderator didnt bobwallace hour weve hit work home spam spam arabic guy peddling post professional help slow day roadkill messin bob hope causing grief post this hmmm newnodm butbut dont gigafactory sure read online musk build inexpensive battery rexxsee false giant car maker time mean facility factory build car power order larger quantity battery larger economy scale cost bloated price battery justify priced evs protecting lucrative ice car market electric motor control prooved cheap technology scapegoat battery waynemaster judging name car suvs model parking lot here people building fort moat efficient balanced budget future eveee scepticism justified factory bobwallace chem intend build lithiumion battery plant europe now european market supplied chem korean factory ochang north chungcheong province claimed production capacity battery chem factory holland michigan capacity battery recently increasing workforce there plant construction china car assume battery mean cell battery pack cover bolt expected year production run eveee detail size battery pack bobwallace takeaway large scale manufacturing commenced build cover annual expect time plant running lot construction year tesla deliver mile range evs off bobwallace poor reading part tesla scaling battery manufacturing give expensive battery byd and chem battery manufacturer alevo bmz scaling large order produce inexpensive battery nonev storage zachary shahan chem expanding battery production capability plant planned europe possibly city bring capacity battery year zachary shahan here newnodm sarcastic ive people suggest battery volume problem apple releasing car apple buy million battery month apple order year lead time battery need samsung panasonic chinese firm capable ramping making huge quantity inexpensive battery gigafactory good choice tesla doesnt put unique position simply company talk long term production plan bobwallace apple release car year ahead time contract battery supplier volume year suck extra chem produce couple year panasonic entering storage market europe china putting bit push million evs road zachary shahan apple good position case supplier apple seriously course supplier time land construct factory supplier board etc someplace apple upper hand imho martin autonomous driving city gridlock reduce accident autonomous driving affect insurance rate higher lower neutral bobwallace autonomous driving greatly reduce gridlock accident car drive closer together rear end accident block traffic gradually disappear city street flow quicker selfdriving car park quicker drop passenger zip parking available stuck cruising parking spot waiting car pull out fewer car road car haul worker fetch worker worker insurance rate down insurance company discussing talking change insure auto insurance business shrink radical ignorant interesting insurance company hell carmaker agree pay premium accident probability low depend quality product driver skill bobwallace make car company car insurance company hate youve developed insurance company migrate car company radical ignorant wont assumption risk super small business marginal required law money simple simplification customer service dont deal insurance company dont deal maintaining car itll autonomous agree hour service buy service ask attention dont hate insurance company sincerely dislike forced financial service buraeucracy bobwallace acceptance risk call insurance youre pay premium deal claim pay deductible radical ignorant usle definition insurance life insurance risk shoot street risk ill eating food business risk insurance core maintain risk hedge fund insurance company core business play risk bobwallace suspect benefit spending time thinking missed context ill spell you party agree pay risk party exposed call accepting risk term accepting risk insurance example case party lay risk party radical ignorant car company insurance company argument insurance company because number accident tiny percent current case cheaper pay force additional bureaucracy supporting army agent manufacturer risk opposed driver risk manufacturer responsible case easier judge data easily accessible case bobwallace yes number collision greatly decline auto insurance company openly talking this insurance theft vandalism rock chip flood fire stuff happen company sell car agree fix problem insurance company dont charge premium blend cost selling price car paperwork hassle less karl brewer cycling pleasant bobwallace safe safe pleasant roadkill yes gridlock result folk unable merge sensibly kyle field wow feel bold stance evs nice work curious volume assuming reach higher volume model beat bolt innovation telsa cramming car and model combined supercharing network great couple year adrian buick encore msrp kwh loose battery ice system change floor add drivetrain package cell plenty pricing room make work kish msrp fed rebate make profit depending development tooling cost kyle field buy stretch tiny eco car mile range range make option peopleit doesnt time make sexy big fit family comfortably adrian crossover built buick trax platform compact yes tiny eveee colour same bad didnt make bolt dedicated rexxsee price msrp part removed priced higher infernal pollution engine version ","m_szGeo1":"United States","m_szSourceType":"source_industry","m_szSrcUrl":"http://cleantechnica.com/2015/10/05/chevy-bolt-battery-cells-145kwh-new-chevy-volt-with-autonomous-driving/","m_Places":["Made","Warren","Us","Free City","Dortmund","Most","Usa","Middle East","Tesla","Uk","Europe","North Chungcheong Province","Michigan","China"],"m_People":["Chevy Volts","Chevy Volt","Will Musk","Anton Wahlman","Mary Barra","James Ayre","Jonathan Wankasky","Jenny Sommer","Jens Stubbe","Steve N","Zachary Shahan","Marion Meads","Richard Foster","Devon N. Harris","Tiny Eco","Chevy Trax"],"m_Companies":["Volt","Volts","Cadillac","University Of Astnide","Google","Guess","Seat","Isis","Oracle","Epa","Lg Chem","Lifespan","Forbes","Eta","Ramp","Lg","Panasonic","Apple","Samsung","Ramping"],"m_BiGrams":["insurance company","electric car","zachary shahan","cell cost","battery cell","autonomous driving","kwh battery","battery pack","cell price","car market","chevy volt","battery price","mile range","gas station","car company","radical ignorant","electric vehicle","interesting comment","cost current","evs car","battery kwh","price drop","car maker","car year","evs road","panasonic cell","rest car","marion mead","richard foster","couple year","kyle field","inexpensive battery","capacity battery"],"m_TriGrams":["battery cell cost"],"m_SocialTags":[],"m_Topics":[],"m_Industry":[],"m_Technology":[],"m_BiCnt":[11,8,7,6,5,5,5,5,5,5,4,4,4,4,4,4,3,3,3,3,3,3,3,3,3,3,3,3,3,3,3,3,3],"m_TriCnt":[3],"m_iDocBodyWordCnt":2263}
