{"m_szDocID":"263313","m_szDocTitle":"Bob Lutz Talks Trash About Tesla Model X & EVs... Again | CleanTechnica","m_szYear":"2016","m_szDocSumamry":"And now his VIA truck business is missing in action. Marcel Wasn’t this guy still at GM when they needed to be bailed out? Truth hurts He is right, there is no technology to produce cheap EVs. Thats why they call every EV  luxurious. Bob_Wallace Both you and Lutz must not be keeping up with the news. sjc_1 Clutz should stick to electric trucks. Ed Hey, everybody. Bob has done some good things in his career, so let’s cut him some slack…even though at this stage, he is starting to sounds like my crazy Uncle Bob; suddenly going Luddite on us….with a pulpit! I suggest we ask Bob to: 1) Explain the","m_szDocBody":"truck business missing action marcel wasnt guy needed bailed out truth hurt right technology produce cheap evs call luxurious bobwallace lutz keeping new sjc clutz stick electric truck hey everybody bob good career let cut slackeven stage starting sound crazy uncle bob suddenly luddite uswith pulpit suggest bob explain huge growth tesla model surpassing luxury car market year explain major player mercede bmw porsche audi scrambling create sell electric vehicle explain year model trajectory overtake luxury suvs month projection catch teslas growth storey yesterday sale figure luxury car market tesla sold vehicle increase mercede sclass drop bmw sery drop bmw sery drop audi drop lexus drop mercede cls drop audi drop porsche panamera drop jaguar drop impossible conclude lose luxury car maker tesla duh bob hang therelet marketplace decide dont forget efficient electric car sale offset cafe shortfall bob vittengl bob lutzs recommendation tesla switch hemi similar fisker peter egan sandy munro munro associate good profitable bmw rich bob lutz responsible volt reality watched him interview defend profitability volt hes taking position market general assume arent hoped zachary shahan yeah thought dont rail eveee lutz working rarified atmosphere touch reality tesla outsold luxury car class cratered market large luxury vehicle falling sale compared year including porsches panamera bob lutz working rarified atmosphere philip guy birthday tomorrow give slack senile sane anymore joseph dubeau fuddy duddy halslater agree major accomplishment the volt love mine make person oracle energy debacle show proven oracle like buffett very bad gurus stop looking eric zucker due respect bob lutz credibility subject falcon wing door bold status symbol key success factor chinese market tesla achieved growth year done kid block hurting established manufacturer tesla figured delivering tint depot dont innovate left behind barry pearson lutz table full working side industry evs gas vehicle doubleedged sword indeed though evs end win spite lutzs position bob lutz cigar smoke eye forest threw tree tim dont talking fancy farmer mix metaphor cement truck end doubt youre saying barry pearson made mistake evs early impact hot battery told consider happened caught fire cut practical deal evs decided humvee instead game forcing volt made late game front tesla listened industry tint depot agreed convinced govt give rebate car humvee back barry pearson musk money toss including solar wind power considered plate show react emotion see research depth practical approach tint depot musk working interested experience with full plate company leave wind power people grow jen stubbe heard musk positive respectful wind power building wind power focus chinese showered wind industry subsidy expanded demand chinese copycat wind industry deliver quality free world counterpart chinese wind power cost wind power frank fast efficient read quality turbine improved lot quickly didnt grid connexion ready turbine curtailment coal plant guaranteed minimum production changing too jen stubbe danish government set university china signed agreement teach chinese build wind turbine half price electricity generation build thermal power plant conversion efficiency denmark combined district heating adequate exhaust cleaning manage grid good change avoid mistake good friend mine working chinese company develop energy efficiency test denmark transferred china denmark oecd country positive trade balance china endless foul trick corruption chinese clean act begin opening market real chinese wind turbine manufacturer bridged gap free world wind power lowered lcoe year tim musk considered thought processe legendary research areas thought decade plenty deep dont clarity thought put sentence here industry fix hitting post yes called lazy stupid that barry pearson lutz wrong man doesnt hand left daily arrogance biggest stumbling block adw realise left left year ago fact zorba information lutz inquiringmind supposed pinnochio nose wiener people better kaboom nice one frank dude lutz doubling number car made year doubling reliability time selling made burn damn capital joe viocoe century worth maturity cost expenditure amortised grow freely hard part over tesla toddler burn cash grow frank missed sarcasm mike bolt build them dont fulfil kind state requirement then compliance car lutz doesnt knowledge actual contract written chem hes talking rear end shock mike graph battery capacity graph battery cost kwh convince sane person point evs cheaper ice car fool ignore trend ignoring mean bankruptcy doug cutler dont opec ignoring mike here evolution work individual evolve dead end die remaining population evolve snowshoe rabbit moult white brown global warming white rabbit eaten higher rate lower reproductivity white rabbit die higher reproductivity brown rabbit population population evolve generation population totally brown dead ender white rabbit evolve brown rabbit evolution here dan epigenetic play role activating dormant gene based environment choice gene passed future generation choice affect genetic progeny emotional health inclination reasoning influenced gene point human dna vast history persistence effort tap ancient humanity dna pass improved genetic springboard children word evolution random participate personal gene expressed mike gonna lutz dan wont lutz either brett bob lutz reality robwithab yeah remind grandpa wanting butt conversation topic experience field forty year ago unlike normal person give cent worth word grandpa floor half hour bow superior wisdom experience bob lutz whatever world changed grandpa opinion valuable youd ceo catch fish buy give wrinkly lovin grandma people longer real contribution make society roger lambert hes point dumb door cost tesla lot money time reputation least questioning psychological profile musk let talk tesla heck car development year promised time already tell vaporware meanwhile chevy bolt door today development time less musk latest musk vague include term mention longer term meanwhile back ranch gigafactory construction ground broken back factory folk press release tesla speak battery output term businesse musk overseeing anyway thin sort stretched butter scraped bread mike geometric sale growth loss sale competitor luxury brand guy right spoiler lutz zooba difference arnenl geometry from ancient greek geo earth metron measurement branch mathematic concerned question shape size relative position figure property space geometry deal triangle circle angle line etc exponential function background exponential zooba geometric sery base exponential exponential sery power math major bit pet peeve mine since time hear word geometric growth media invariably meant exponential growth exponential growth overtake geometric growth sound fancier superlative sreehari variar segment shrinking competitor manage positive sale growth number car sold mike solar battery shipped now kerrywebster solar battery stillunderconstructiongigafactory read comment robert make hell guy reading conclusion realise month behind catch robert roger lambert talking roger and giga factory fully operational afaict not zooba operational fully operational gigafactory huge built stage building the pilot plant nearing completion producing cell battery pack roger lambert construction right reason model wont beat bolt market factory isnt ready manufacture right tomk read literally everywhere ahead schedule lot bigger initially planned tesla energy product meant year full production reached its gonna reeeealy big factory know zachary shahan largest building earth footprint bobwallace roger sort prize mile market tesla changed automotive world car manufacturer game lead change hand hand big deal car manufacturer ahead tesla good thing great thing tesla achieved main goal brett door mean buy bolt today order reserve one kerrywebster robert touch read blog doesnt read well roger lambert perry debster gotcha roger lambert final version door ready marketed couple month point beat tesla lot time brett year ago estimate gave year head start tesla tesla superior product year later eveee wrong again late announced already fyi call vehicle difference production time bolt model great lot time exaggeration month hard point meanwhile noticing tesla sold evs introduced model pretend tesla major car company hasnt accomplishment real here roger lambert car tesla sold here lutz wrong door fact lot discussion silliness door standard business plan here autoblog green brought market lot sooner door eveee read gave quote musk overly ambitious complain roger lambert dont read love complain read complaint print selfactualized frank buy one remember slow charging youll one isnt build any tesla higher price desireable car tesla make dual motor performance model significantly more roger lambert afford one hoping buy leaf soon robwithab problem theyre making max year straight mouth ceo recall compliance car although raised bar else strictly car understand there lot bit generic part bin philip ready produce demand strong enough imho compliance car completely ill plan outsell model unit robwithab pretty theyre constrained initially battery supply limit into range push button start placing firm order supplier mid latest nowish theyre year sale data methink bit chickenandegg tend agree general idea theyre dipping toe water happy deeper water right resource general vehicle production goe simply battery existence build gigafactory convince supplier talking gigawatthour battery capacity year sitting hand waiting business strategy tesla link yeah read storey couldnt remember exact detail storey floating made clear capacity scale order magnitude basically theyre saying market awesome affordablelongrangeelectric vehicle talking about first yeah show committed clean green business totally make thing make market want like lot them thousand car market year less actually research people dont buy electric car totally make people want max year totally there aint gonna happen yeah wooo sounded ballstothewall commitment electrification fleet annum highball scenario total vehicle production bobwallace year year robwithab way dont real plan big ramp cleantechnica article gms kevin kelly manager electrification fuel cell technology communication noted topselling electric car market the nissan leaf tesla model barely risen sale year bolt demand rose car year partner chem satisfy demand kevin woohoo apparently big get philip ready build year decent opinion interesting time year scale aggressively reach see demand pretty good already robwithab ive read annum maximum foresee making year demand profitability there change mind gonna secure battery philip think close relationship scaling production heavily ill stay optimistic mike lastly evidence model door problematic theyre different theyre regular door but proof theyre reliable making stuff good argument matt theyre regular door proof either different tesla issue production people dont past dan row seat better watch numerous videos elon demonstrate car seat advantage falcon door allow basically average height person step car door adjusting moving row easier demonstrated double hinged door tighter parking preventing door open door open path exit passenger step directly side close door convenient break mould cookie cutter boring suvs falcon wing door tell zachary shahan block rain open people standing vehicle robwithab youre fan ill hypothetical question extra prepared pay proportion cost vehicle falcon wing door car normal door robwithab good point assist informal survey potential car buyer extra prepared pay proportion cost vehicle option falcon wing door car normal door dan personally cost electric option tesla pretty strapped cash money wasnt obstacle falcon wing door sound reasonable dont base idea cost compared regular door tesla figured engineering side dan mind current car cash hand bought directly previous owner valuing door new cost entire presentday car lol sciguy joan claybrook inadvertently demonstrated primary liability gullwing door million viewer including myself appeared mike douglas talk show talking severe trash automaker door design normal door caused needless injury death gullwing door safer point stepped multimillion dollar safety car gullwing door proceeded fall crack soundly head laugh around poor joan stunned unable finish spiel cogent fashion instant lawyer gullwing door heavy hang sword damocle head customer hundred thousand time day life fleet mechanical imperfection due design material wear prior damage lead injury liability tail mindboggling philip what mindboggling you drive fast tyre loosen drive tree die let face car dangerous robwithab prefer falcon wing door option suggest market innovative technology matter interest extra prepared pay proportion cost vehicle option falcon wing door car normal door philip dont prefer make sense model bad think money goe havent thought that studying university money car tesla anyway bicycle electric public transportation roger lambert door problematic delayed production year jesus christ huge tesla supporter honest fact problem reported teslas supplier failed door tesla fine comparison realise difference size company right robwithab dog deeper issue youll realise struggled supplier deliver exacting requirement actuating mechanism door angle attack hydraulic proved predictably problematic changed tack electromechanical approach predict prove problematic time eagerly awaiting videos showing complete strip door interested tackled problem engineering challenge simple suggested sometime wishful thinking place engineering analysis understand potential customer online fan car tempted simply best struggle understand company decision time iteration transpire industry manage refine basic design falcon wing door boring reliable part car mainstream expensive solution regular door higher maintenance people advantage greater disadvantage happy luxury making decision meantime highrisk strategy manufacture ten hundred thousand car maintenance issue year whilst warranty maintenance issue expensive timeconsuming resolve tesla providing cheaper option model base model regular door ive mentioned before ill mentioning address issue biggie waiting bribed youre supported detractor robwithab surname lutz lot bitterness listen anymore king detroit frank way define problematic concede made late cost money doubt unusual door but dont reason wont sell make year suspect love hard time notion accepting negative part large sum money own cliff evidence delay model cost tesla money fact reason extending time producing model netted tesla money and waiting expanded production absolute total revenue sell model make margin model compared rest industry margin model lower model production while simply take longer produce model model production while repetition improve performance selling price higher extra revenue cover fact vehicle cost tesla build slowing production introduce model cost money waiting added extra production line allowed crank model shutting expansion ramped back expansion extra line allowed expand production model quickly restore revenue slowly ramping production delay cost money higher margin lower volume hard raised price cover substantive shortfall production cliff frank reply roger suggested delay cost tesla delay harmed image irritated customer made money robwithab saying delay harmed image irritated customer made money depending made money tesla stock based fantastic corporate image strong customer loyalty delay cost them current real tesla based normal forward ratio share based expectation future growth low cost customer acquisition low maintenance requirement vehicle thereby avoiding requirement widespread dealer network basically recent drop stock price market whole tesla additional knock market assessed tesla worth billion month ago result fiasco door general investing public think delay and future potential problem related extra complexity cost company zero market billion market correct time tell sure borrowing cost number reservation holder cancelled order number potential customer vehicle spooked due reliability concern delay production delayed production understand time money deferment future income cost significant income growth projected were course actual monetary cost delay salary paid engineer rent overhead paid waiting production start interest significant amount capital equipment standing idle sort thing cost people allowing for cost lot forward unfortunately cost felt point future market protect robwithab pleased mentioned part part large sum money own love idea door say excellent patience congratulation ordering world amazing suv love compelling feature vehicle make technological masterpiece decade ahead time engineer integrated perfected notion electric mobility connectivity passenger safety visually stunning package hold appeal decade come also small additional sum give option completely novel technologically awesome falcon wing door preference unfortunately time offer month guarantee door but small additional sum extend year quibble question asked youll talk town worry decade grand extra congratulation superior taste technological insight company business churning ten thousand easytoassemble highmargin nomaintenanceworry normal model vehicle prefer car boring reliable #optionthedoor frank way now dont model gull wing door distraction tesla laser focused task hand increasing production building mod model building factory churn evs manufacturer slow then time horse around back coming door trouble selling are turnabout fair play dan late superior product early compliance vehicle great car question better regularly improved tesla habit frank late said competition dan bothered read comment noticed petty inaccurate being roger lambert delivered time easiertomanufacture design insisting exotic difficult produce gimmick guy produce fast assembly line delay interpreted costing money dan boring argument door proved difficult expected yeah time wouldve cost back retool revamp assembly line road investment expert stand reason buying cost capital system beginning pay faster equally expensive half measure expensive incrimental improvement maintaining production incurring wrath impatient entitled folk internet falcon wing door made traditional door built door didnt waste time redesigning boring poorer quality door cut corner making rest car outperform class havent specific detail curious functionality folding row seat turned out understand elon threw towel engineering settle working scenario had future model feature folding seat set ooh engineered door mythical model require effort did mac problem supplier sued tesla door themselve reading clear roger lambert problem difficulty producing door design doesnt matter problem inhouse not mac sorry message delivered pat mcdaniel message rejected recipient confidentiality notice message including attachment sole intended recipient confidential privileged information unauthorised review use disclosure distribution prohibited intended recipient contact sender reply destroy copy original message arnenl sorry youre focusing negative perfect exist world teslas execution nearperfect analyst predicted year ago tesla crash burn entire industry shaking proposed concept vehicle tesla fighter fully realise impossible stunt tesla pulled off hasnt successful auto company startup what year dont make niche vehicle car universally acclaimed class true sound football soccer supporter trainer favourite team frank right perfect leo messi magic roger lambert denying thing simply arguing lutz point door made point late based initial estimate company late market compared bolt ill time huge supporter tesla love car hope succeed knetter are roger lambert hey knetter bite excuse speaking mind disappointed you robwithab strange eager people simply problem ceo admitted door problematic kerfuffle german matter public record religious fervour people insist saint elon completely infallible kinda weird disturbing firm supporter company mission support intensely aware potential pitfall bobwallace missed something hydraulic approach didnt work remember door supplier produce door information door experiencing trouble robwithab muttering ive picked sniffing forum far issue seal poor alignment panel remember discussion tmc elon comment staggering complexity face roger lambert you robwithab feedback early customer alignment problem seal which elon alluded absence specific problem ourselve problem future perfectly valid speculate way normal part decision making business based engineering principle statement coming directly tesla surmise problem reliability door absolutely generate significantly problem normal door predict degree confidence complexity spawn unintended consequence joshua mark heck glad asked corner theyre taking reservation teaser reveal musk fully operational gigafactory make model ahead schedule delivery model anticipated corner roger lambert corner beginning remember beginning easily chevy bolt start shipping supposed year ago late controversial position zooba bolt start shipping difference isnt big honestly roger lambert shipping year model zooba understanding otherwise roger lambert careful giga factory fully operational yet slander here evidently eveee gigafactory intended fully operational yet was overcapacity let make sense here fully operational true hinting wrong ingenuous best roger lambert holding construction redesign gigafactory remember promised already eveee fud gigafactory ahead schedule nothing holding battery produced there stop claiming otherwise supposed completed year part peak production output consumption planned start production entire gigafactory completed older estimate model off year updated model reveal introduction quoted musk ambitious resulted delay roger lambert right late gigafactory making battery online ahead schedule late late something onesecond yeah fair comparing startup build scratch year international giant billion dollar state money top behemoth nothing nada compete model model elon musk laid plan couldnt start model deaf listen fault door complain dont work timescale note international behemoth year roll completely model comment bit rich shut better roger lambert chevy make time ice car tesla make car monolithic bureaucracy lot money expertise ice vehicle evs beat tesla money need tesla business making evs talking year late dont unfair comparison house shut face asshole like bobwallace chevy beat tesla tesla mile range car market year coming market small sell lower price good thing dont charging system support doesnt ability produce evs tesla hasnt built battery factory needed limited portion chem production get taking comment down uncivil control eveee knetter point purpose repeating fud onboard decided change comment section verified user farmerdave chevy bolt door theyve shown buy chevy dealer vaporware roger lambert bit vaporware final production car mockup vision car reviewer driving driving vaporware car tricky business ramon cardona compete mile electric car range tesla due free supercharging supercharger everywhere count chevy dealer dedicated evs tesla dollar dollar model car wait for meantime model car avaible used lutz reading market global movement evs due climate change concern philip expect model free supercharging yeah paid supercharging huge selling point bobwallace not room price prepaid rapid charging philip top prepaid hope wrong money huge amount car crowd supercharger good balance letting model owner supercharging limiting bobwallace pay extra supercharger solar supply them bay bay evs give instal bay power service them set upper limit use tesla plan change system pay system produce rangelimited stever dont personally lutz liar touch ","m_szGeo1":"United States","m_szSourceType":"source_industry","m_szSrcUrl":"http://cleantechnica.com/2016/02/11/bob-lutz-talks-trash-about-tesla-model-x-evs-again/","m_Places":["Us","Tesla","Farmer","China","Denmark","Nice","Boring","Douglas","Detroit","Mark"],"m_People":["Bob Lutz","Mercedes-benz S-class","Porsche, Audi","Peter Egan","Sandy Munro","Zachary Shahan","Philip W","Joseph Dubeau","Fuddy Duddy","Eric Zucker","Barry Pearson","Jens Stubbe","Joe Viocoe","Doug Cutler","Roger Lambert","Kevin Kelly","X. Elon Musk","Joan Claybrook","Pat Mcdaniel","Leo Messi","Ramon A. Cardona"],"m_Companies":["Slack","Bmw","Audi A7","Audi A8","I3","Volt","Oracle","Nv Energy","Indeed","“volt”","Danish Government","Oecd","Kaboom!","Lg Chem","Opec","Ramp","Lg","Youtube","Seat","Hinged","Path","Cogent","Ramped","Ramping","Turnabout"],"m_BiGrams":["roger lambert","wing door","falcon wing","wind power","bob lutz","fully operational","car market","regular door","normal door","luxury car","electric car","barry pearson","cost tesla","ahead schedule","car tesla","gullwing door","market year","market tesla","tesla sold","zachary shahan","tint depot","compliance car","white rabbit","chevy bolt","beat tesla","door problematic","door but","extra prepared","prepared pay","pay proportion","proportion cost","cost vehicle","door car","car normal","cost money","tesla money","delay cost","made money"],"m_TriGrams":["falcon wing door","car market year","extra prepared pay","prepared pay proportion","pay proportion cost","proportion cost vehicle","wing door car","door car normal","car normal door"],"m_SocialTags":[],"m_Topics":[],"m_Industry":[],"m_Technology":[],"m_BiCnt":[21,11,10,7,6,6,5,5,5,4,4,4,4,4,4,4,3,3,3,3,3,3,3,3,3,3,3,3,3,3,3,3,3,3,3,3,3,3],"m_TriCnt":[10,3,3,3,3,3,3,3,3],"m_iDocBodyWordCnt":3373}
