{"m_szDocID":"263656","m_szDocTitle":"Uh-Oh! Government Motors Buys Carbon Offsets! | CleanTechnica","m_szYear":"2012","m_szDocSumamry":"Uh-Oh! Government Motors Buys Carbon Offsets! February 1st, 2012 by Susan Kraemer   In a move that almost seems calculated to enrage the Right with its Fox- and Rush-driven rage against the Volt, Chevy has announced it will voluntarily buy “8 million tonnes” worth of carbon offsets for $40 million to help it meet “voluntary emission reduction goals” within five years. Even the spelling in the announcement is sissified. These are not even American tons! (Actually – I quoted European “tonnes” because the news came from the Norwegian-based Point Carbon , that covers carbon trading news from the E","m_szDocBody":"uhoh government motor buy carbon offset susan kraemer move calculated enrage fox rushdriven rage volt chevy announced voluntarily buy million tonne worth carbon offset million tohelp meet voluntary emission reduction goal year spelling announcement sissified american tonne actually quoted european tonne new norwegianbased point carbon cover carbon trading new european commission european trading scheme ets cap trade programme money fatten gore big gummint wallet right actuallythe money generated sale carbon credit directly buy clean energythat carbon credit cap trade plan work polluter pay switch cleaner energy dont chevy volunteering here cap trade plan buy carbon credit offset suv emission chevy million north dakotas basin electric power cooperative buy power clean energy project year capture waste heat gas pipeline convert energy bring wind power grid basin electric power purchase contract buy baseload capacity fueled waste heat recovered exhaust gas turbine compressor station located pipeline north dakota south dakota minnesota montana ormat waste heat recovery unit compressor station amount generating electricity family year chevy basin electric pay power these culbertson montana garvin minnesota waste heat recovery unit piggybacked dirty fuel inside pipeline gas waste heat recovery unit generate emission energy source qualify carbon credit project chevy money aka carbon indulgence buy clean power straightforwardly understood renewable wind farm turbine wind farm basin electric coown rural landowner south dakota turbine wind farm north dakota project size owned rural coop built project generate million carbon credit carefully checked verified carbon standard vcs ensure carbon credit pay project reduce carbon emission vcs widelyused offset authenticator voluntary carbon market carbon credit represent tonne carbon reduced sadly government motor make rush limbaugh ditto head madder clearly sale groundbreaking electric volt impacted irrational rage ty wrong administration nation driven close civil war image nasa eia calculate north dakota gas flared bakken shale gigantic city space cleantechnicas completely free electric car report electric car early adopter follower want youd attend electric vehicle solar power event conducted cleantechnica date hottest cleantech new subscribing free cleantech newsletter eye sectorspecific new also free solar energy newsletter electric vehicle newsletter wind energy newsletter tag chevy government motor ormat volt waste heat recovery susan kraemer write cleantechnica csptoday renewable energy world published wind energy update pvinsider greenprophet ecoseed nrdc onearth matternetwork celsius energynow scientific american serial entrepreneur product design susan bring innovator perspective inventing carbonconstrained civilization necessity mother invention solving climate change mother necessitiesas lover history scifi enjoy chronicling strange future creating interesting time follow susan related post ","m_szGeo1":"United States","m_szSourceType":"source_industry","m_szSrcUrl":"http://cleantechnica.com/2012/02/01/uh-oh-government-motors-buys-carbon-offsets/","m_Places":["North Dakota","South Dakota","Minnesota","Garvin, Minnesota"],"m_People":["Susan Kraemer","Rush Limbaugh"],"m_Companies":["Volt","European Commission","Basin Electric Power Cooperative","Basin Electric Co","Nasa","Scientific American","Twitter"],"m_BiGrams":["carbon credit","waste heat","basin electric","heat recovery","government motor","cap trade","north dakota","recovery unit","wind farm"],"m_TriGrams":["waste heat recovery","heat recovery unit"],"m_SocialTags":[],"m_Topics":[],"m_Industry":[],"m_Technology":[],"m_BiCnt":[7,6,4,4,3,3,3,3,3],"m_TriCnt":[4,3],"m_iDocBodyWordCnt":404}
