{"m_szDocID":"264884","m_szDocTitle":"Clean Links (More News on Solar Energy, Wind Energy, Clean Transportation, & Energy Efficiency) | CleanTechnica","m_szYear":"2012","m_szDocSumamry":"Clean Links (More News on Solar Energy, Wind Energy, Clean Transportation, & Energy Efficiency) February 29th, 2012 by Zachary Shahan     Some more top cleantech news from the past day or so. Solar 1. We’ve written about the large solar boat known as Planetsolar many times in the past. Our good old friend Tim Hurst of Live Oak Media delved into the boats features in good depth in a recent post worth sharing, though, and also jumped into the idea of power the grid with the boat’s excess solar power when docked . 2. Michael Kuhn, President and CEO of ImagineSolar, spoke at a Solar Austin’s press","m_szDocBody":"clean link more new solar energy wind energy clean transportation energy efficiency zachary shahan top cleantech new past day solar weve written large solar boat planetsolar time past good friend tim hurst live oak media delved boat feature good depth recent post worth sharing though jumped idea power grid boat excess solar power docked michael kuhn president ceo ofimaginesolar spoke asolar austin press conference recently austin solar industry employing direct fulltime solar job and job indirectly abound solar announced yesterday stop producing firstgenerationthinfilm cadmium telluride photovoltaic module order accelerate manufacturing process equipment needed production launch generation highefficiency module suspension generation module production result temporary reduction approximately permanent job colorado facilitiesonce manufacturing equipment modified performance tested abound solar expect resume mass production percent efficiency module end abound solar face steep competition arena like solar produce cdte module aka panel intersolar north america largesolar industry exhibition conference announced prestigious innovation prize intersolar award feature category recognise landmark solar project withinnorth america curious win award application intersolar award open untilmarch exhibitor intersolar north america intersolar europe intersolar china intersolar india invited apply wind sauer energy creator homevertical axis wind turbine vawt system weve written number time announced yesterday awarded coveted prestigious project year award institute electrical electronic engineer ieee buenaventura section national engineer week award banquet held ronald reagan presidential simi valley california impressive award company demonstrated technological achievement engineering innovation development promise company note transportation russias yomobile cngelectric hybrid apparently working ona larger crossover vehicle suv video more detail history link above lng viking cruise ship are reportedly cutting global warming emission hence image above national grid utility northeastern united state installed electric vehicle charging station location massachusett station part coulomb chargepoint network largest network independently owned charging station world newthinking city documentary ericsson released month discusse future role smart city sustainability social media network intelligence p&f usa announced yesterday won the energy star efficient designation itsphilip led television pfl pfl pfl pfl word green energyefficient television cheque model above suggested price availability tvs follow pfl tag abound solar austin job cdte cdte module cdte panel cngelectric hybrid electric hybrid energy star ericsson home vertical axis wind turbine home wind turbine hybrid electric ieee imaginesolar institute electrical electronic engineer intersolar intersolar award intersolar north america led led tvs lng viking cruise massachusett massachusett electric vehicle charging station massachusett electric vehicle massachusett charging station efficient efficient tvs national grid p&f p&f usa philip led philip led tvs planetsolar russia sauer energy small wind turbine solar austin solar boat solar job solar power job solar power job austin solar texas texas texas solar thinking city vawt vawt vertical axis wind turbine yomobile zachary shahan tryin and specy letter time spend time cleantechnica director chief editor otherwise enthusiastically fulfilling duty obsession gas solar love planetsave bikocity president important media zach recognised globally solar energy electric car energy storage wind energy expert speak related conference event connect social media zacharyshahancom related post ","m_szGeo1":"United States","m_szSourceType":"source_industry","m_szSrcUrl":"http://cleantechnica.com/2012/02/29/clean-links-more-news-on-solar-energy-wind-energy-clean-transportation-energy-efficiency/","m_Places":["Austin","North America","Most","Europe","China","India","Buenaventura","Simi Valley, California","Russia","Massachusetts","Thinking Cities","Usa","Texas , Texas"],"m_People":["Zachary Shahan","Tim Hurst","Michael Kuhn","Ronald Wilson Reagan"],"m_Companies":["Solar Energy","First Solar","Institute Of Electrical And Electronics Engineers","Ieee","Presidential Library","Viking","Ericsson","Philips"],"m_BiGrams":["wind turbine","abound solar","charging station","solar power","austin solar","announced yesterday","intersolar north","north america","axis wind","electric vehicle"],"m_TriGrams":["intersolar north america","axis wind turbine"],"m_SocialTags":[],"m_Topics":[],"m_Industry":[],"m_Technology":[],"m_BiCnt":[5,4,4,3,3,3,3,3,3,3],"m_TriCnt":[3,3],"m_iDocBodyWordCnt":486}
