{"m_szDocID":"264847","m_szDocTitle":"EPA’s Green Power Partnership Helps Big Corporations Greenwash | CleanTechnica","m_szYear":"2012","m_szDocSumamry":"EPA’s Green Power Partnership Helps Big Corporations Greenwash February 27th, 2012 by John Farrell     While I generally have nothing but praise for the Environmental Protection Agency, its  Green Power Partnership program falls short of the agency’s usual standard.  In particular, the program – providing media recognition for participating companies who procure renewable energy – inflates the activities of large companies at the expense of businesses whose clean energy transformation is much more meaningful. Take Wal-Mart, who appears at #3 in the EPA’s Green Power Partner rankings with an an","m_szDocBody":"epas green power partnership help big corporation greenwash john farrell generally praise environmental protection agency green power partnership programme fall short agency usual standard particular programme providing media recognition participating company procure renewable energy inflate activity large company expense businesse clean energy transformation meaningful walmart appear epas green power partner ranking annual procurement million kilowatthour enough power approximately home year epa inaccurately credit superretailer electricity green power partnership programme walmart cherrypick regional division made stride green energy california texas nationwide walmart electricity renewable energy source walmart green appearance narrowing focus company division truth small businesse town and individual lay significant stride renewable energy example oak park recently signed contract renewable electricity wind power facility state bighorn ace hardware silverthorne electricity solar built top building beat walmart xcel energy windsource electricity wind power truth walmart vast size mean green power step equally vast match renewable energy commitment bighorn hardware percent energy consumption example walmart instal megawatt solar time installed entire united state renewable instal megawatt solar panel make bridge york los angele time over walmart receive good press minor commitment green power bighorn ace hardware oak park make epas top list green power partner epa rank businesse total size purchase relative greenness agency list fortune order electricity consumption honest rank company meaningful metric green power progress green kilowatthour dollar sale shame epa employ wrong measure green company big energy bill small commitment green power great publicity expense city college businesse made real clean energy stride epas green power programme highlight highachiever clean energy methodology change lot entity list green thumb overshadowed enormous energy footprint note excellent sery grist walmart greenwashing effort post originally appeared energy selfreliant state resource institute local selfreliance rule project cleantechnicas completely free electric car report electric car early adopter follower want youd attend electric vehicle solar power event conducted cleantechnica date hottest cleantech new subscribing free cleantech newsletter eye sectorspecific new also free solar energy newsletter electric vehicle newsletter wind energy newsletter tag corporate electricity energy environmental protection agency epa fortune green power greenwash wal mart john farrell direct democratic energy programme ilsr focuse energy policy development expand benefit local ownership dispersed generation renewable energy seminal paper democratising electricity system describe blast roadblock distributed renewable energy generation smallscale renewable energy project key biggest stride renewable energy development farrell authored landmark report energy selfreliant state serve definitive energy atlas united state detailing statebystate renewable electricity generation potential farrell regularly discussion analysis distributed renewable energy policy blog energy selfreliant state energyselfreliantstatesorg article regularly syndicated grist renewable energy world john farrell found related post ","m_szGeo1":"United States","m_szSourceType":"source_industry","m_szSrcUrl":"http://cleantechnica.com/2012/02/27/epas-green-power-partnership-helps-big-corporations-greenwash/","m_Places":["California","Texas","United States","New York","Los Angeles","Us"],"m_People":["John Farrell","Wal Mart"],"m_Companies":["Epa","Environmental Protection Agency","Take Wal-mart","Wal-mart","Nationwide","Ace Hardware","Xcel Energy","Power Partners","Twitter"],"m_BiGrams":["green power","renewable energy","epas green","power partnership","john farrell","clean energy","energy selfreliant","selfreliant state"],"m_TriGrams":["epas green power","green power partnership","energy selfreliant state"],"m_SocialTags":[],"m_Topics":[],"m_Industry":[],"m_Technology":[],"m_BiCnt":[11,10,3,3,3,3,3,3],"m_TriCnt":[3,3,3],"m_iDocBodyWordCnt":424}
