{"m_szDocID":"265334","m_szDocTitle":"Are Gasoline Prices Really Affecting EV Sales? | CleanTechnica","m_szYear":"2015","m_szDocSumamry":"Are Gasoline Prices Really Affecting EV Sales? May 5th, 2015 by Guest Contributor   By Christopher Arcus, Automotive X Prize Competitor, Design Engineer, Dedicated CleanTechnica Reader Headlines say EV owners trade their cars in for SUVs because gas is cheap. But what do the sales numbers say? What’s With the Downer on Earth Day? Is that really true? Lets look beneath the headlines. For 2014, the top plug-in models in terms of sales were the Nissan LEAF , the Tesla Model S , and the Chevy Volt . Chevy Volt sales have been dropping with the anticipation of a new model release . Nissan LEAF sale","m_szDocBody":"gasoline price affecting sale guest contributor christopher arcus automotive prize competitor design engineerdedicated cleantechnica reader headline owner trade car suvs gas cheapbut sale number say what downer earth day true let beneath headline top plugin model term sale nissan leaf tesla model chevy volt chevy volt sale dropping anticipation model release nissan leafsale healthy year quarter match quarter tesla sale sold march sale previous year plugin hybrid rose sale sale purely batteryelectric car rose led nissan leafwhich contributed half car tesla increasing production model unit week number change considerably year overall plugin car sale year year month year reading further model short supply now model sale number determined production availability clearly compliancecar number limited purpose producer againtotal plugin sale year year month owner dumping suvs headline puzzling edmund declared hybrid owner loyalty yet nissan leafwith ihs owner loyalty award polk something gotta give remember plugin vehicle selling large number year hard imagine low owner loyalty tesla buyer owner happiest car busy showing crazy acceleration unsuspecting lady what proof for volt owner happiest car year running model along mean edmund storey thread word finely clue phrase hybrid evs ly part tale sale smaller hybrid despitegrowing steadily hybrid sale dominated prius due refresh lately buying pattern show interest evs hybrid hybrid hand mainstream buyer prius sale dominate hybrid guess thatsome prius sale vehicle prius suv number prius owner trading suv owner loyalty affected gas price good question source declaring hybrid electric vehicle struggling maintain owner loyalty reader response swift negative edmund defended research stating owner loyalty month leaf volt prius notably absent response teslas owner loyalty number missing causality link hybrid sale implied proven part missing early adopter owner loyalty high leading decrease chart gas price versus sale great correlation number example polk hybrid owner dont buy one yet later prius win owner loyalty award secret hidden number prius won owner loyalty award owner loyalty that half prius hybrid owner elect buy else toyota owner loyalty award put way headline flat tyre real facepalm electric suvs expect owner growing family buy electricsuv arent marketon hand volvos recently introduced phev unexpected demand owner loyalty decreased month word struggling colourful doesnt bad evs receiving owner loyalty award stronger owner loyalty pulled examine lumping prius early quarter year anyhow real problem bethat hybrid electricsuvs owner grow into cleantechnicas completely free electric car report electric car early adopter follower want youd attend electric vehicle solar power event conducted cleantechnica date hottest cleantech new subscribing free cleantech newsletter eye sectorspecific new also free solar energy newsletter electric vehicle newsletter wind energy newsletter ","m_szGeo1":"United States","m_szSourceType":"source_industry","m_szSrcUrl":"http://cleantechnica.com/2015/05/05/are-gasoline-prices-really-affecting-ev-sales/","m_Places":["Tesla","Reading","Toyota"],"m_People":["Ev Sales","Cleantechnica Reader","Chevy Volt"],"m_Companies":["X Prize","Downer","Polk","Volt","Guess","Say Anything","Volvo"],"m_BiGrams":["owner loyalty","loyalty award","hybrid owner","electric vehicle"],"m_TriGrams":["owner loyalty award"],"m_SocialTags":[],"m_Topics":[],"m_Industry":[],"m_Technology":[],"m_BiCnt":[15,5,3,3],"m_TriCnt":[5],"m_iDocBodyWordCnt":425}
