{"m_szDocID":"265393","m_szDocTitle":"Clean Car News (10 Stories) | CleanTechnica","m_szYear":"2012","m_szDocSumamry":"Clean Car News (10 Stories) 10 more top clean car stories from the past week (other than our 13 or so clean car and transportation stories): 1. GM has ceased production of its Chevy Volt for 5 weeks. And while some are eager to call the Chevy Volt dead , Chris DeMorro of sister site Gas2 says it is anything but that. He has a long post on that (second link above), but here’s the summary: “In short, the demise of the Chevy Volt has been greatly exaggerated. I’m not saying the Volt isn’t in trouble. It’s image is tarnished, its sales are slow, and its future is uncertain. But I still wouldn’t be","m_szDocBody":"clean car new storey top clean car storey past week other clean car transportation storey ceased production chevy volt week eager call chevy volt dead chris demorro sister gas that long post second link above here summary short demise chevy volt greatly exaggerated volt isnt trouble image tarnished sale slow future uncertain wouldnt bet volt make strong comeback starting year politic tend window gas price image modified ikea image ikea plug electric vehicle charging station something lot past year again blink pedestal electric vehicle charging station ecotality charging station tempe arizona store mitsubishi developed prototype electric vehicle motor system builtin silicon carbide inverter mean motor system half size mitsubishi electric existing motor system external inverter smallest kind expected enable manufacturer develop evs offering passenger space greater energy efficiency company plan commercialise motor system finalising technology cooling downsizing efficiency eos energy storage working refillable flow battery air cathode zinc anode liquid electrolyte mean theoretically eos system fitted standard passenger car costing allowing mile range recharging minute see morgan car manufacturer revealed concept electric sport car manual transmission geneva motor show week nissan leaf reportedly sale dealer european market winning japan car year award coolest car opinion make people happy note leaf nationwide image courtesy nissan nissan coming green suv too hybrid prototype hicross revealed geneva motor show volkswagen tired shamed gamed greenpeace reportedly investing tonne money ecological restructuring third entire billion investment programme exact department energy doe awarded eaton corporation million grant development demonstration efficient commercial electric vehicle charger eaton note project promote smart charging technology manage efficiency availability reliability power peak time popular charging location eaton grant part larger federal research development programme reduce current cost charger percent year support adoption deployment evs liberal democrat london mayoral candidate brian paddick convert buse taxis electric innovative financing approach elected mayor revealed current mayor london failed make progress clean taxi fund annouced year ago image credit noted above nissan leaf courtesy shutterstock gong courtesy greenpeace eaton charger courtesy eaton cleantechnicas completely free electric car report electric car early adopter follower want youd attend electric vehicle solar power event conducted cleantechnica date hottest cleantech new subscribing free cleantech newsletter eye sectorspecific new also free solar energy newsletter electric vehicle newsletter wind energy newsletter tag blink pedestal blink pedestal charging station brian paddick chevy volt department energy doe eaton corporation eaton electric vehicle charger eaton charger ecotality electric buse electric taxis eos energy storage battery charger general motor ike electric vehicle charging station ikea ikea charging station leaf london mitsubishi mitsubishi electric morgan morgan electric car nisaan leaf europe nissan nissan green suv nissan leaf nissan suv electric car volkswagen volt zachary shahan tryin and specy letter time spend time cleantechnica director chief editor otherwise enthusiastically fulfilling duty obsession gas solar love planetsave bikocity president important media zach recognised globally solar energy electric car energy storage wind energy expert speak related conference event connect social media zacharyshahancom related post ","m_szGeo1":"United States","m_szSourceType":"source_industry","m_szSrcUrl":"http://cleantechnica.com/2012/03/09/clean-car-news-10-stories/","m_Places":["Uk","Geneva","Japan","U.s.","London","Europe"],"m_People":["Chevy Volt","Chris Demorro","London Mayoral","Brian Paddick","Zachary Shahan"],"m_Companies":["Volt","Ikea","Volkswagen","Vw","Greenpeace","Department Of Energy","Doe","Eaton Corporation","Eaton","General Motors"],"m_BiGrams":["electric vehicle","charging station","electric car","chevy volt","motor system","clean car","vehicle charging","blink pedestal","energy storage","nissan leaf"],"m_TriGrams":["electric vehicle charging","vehicle charging station"],"m_SocialTags":[],"m_Topics":[],"m_Industry":[],"m_Technology":[],"m_BiCnt":[8,6,5,4,4,3,3,3,3,3],"m_TriCnt":[3,3],"m_iDocBodyWordCnt":485}
