{"m_szDocID":"265612","m_szDocTitle":"Europe Electric Car Sales Booming | CleanTechnica","m_szYear":"2015","m_szDocSumamry":"Europe Electric Car Sales Booming Originally published on EV Obsession . The European electric vehicle (EV) market is continuing to see strong growth, based on registrations during March — with roughly 18,000 units registered, blowing past the old monthly record (set in December 2013) for the old continent. The old record was 14,197 units registered. As it stands, more than 36,000 EVs have been registered in the European market this year — putting the market (if things continue this way) roughly on track to top 150,000 units in 2015. Note that these numbers are not perfect. They don’t actually","m_szDocBody":"europe electric car sale booming originally published obsession european electric vehicle market continuing strong growth based registrationsduring roughly unit registered blowing past monthly record set continent record unit registered stand evs registered european market year putting market continue way roughly track top unit note number perfect dont cover european country include lot ofestimate data isvery usefully gathered estimated painstaking work jos ponte ithelp show european market market market dominated mitsubishi outlander plugin unit sold vehicle isnt market nissan leaf good continuing sale well unit sold less record unit sold single month european market purely electric vehicle tesla model continued well personal record unit sold registered march renault zoe volkswagen egolf good sale unit sold respectively altogether rise nissan leaf tesla model notable managing gain market share rise ranking leaf spot model yeartodate number again sale blog similar storey position identical additionally bmw managed rise position audi etron interestingly nissan rose spot position half yeartodate sale month march cleantechnicas completely free electric car report electric car early adopter follower want youd attend electric vehicle solar power event conducted cleantechnica date hottest cleantech new subscribing free cleantech newsletter eye sectorspecific new also free solar energy newsletter electric vehicle newsletter wind energy newsletter tag audi audi etron bmw bmw bmw bollore bollore bluecar citroen citroen czero daimler electric van europe sale sale europe kia kia soul mercede mercede bclass electric mercede plugin mitsubishi mitsubishi imiev mitsubishi outlander phev mitsubishi outlander plugin nissan nissan env nissan leaf peugeot peugeot ion porsche porsche cayenne ehybrid porsche panamera ehybrid renault renault kangoo renault twizy renault zoe smart electric drive tesla tesla model toyota toyota prius plug volkswagen volkswagen volkswagen egolf volkswagen golf gte volvo volvo plugin jame ayre background predominantly geopolitic history obsessive interest pretty everything early life spent imperial free city dortmund jame river ruhr cofbuokheim attended university astnide briefly considered entering coal mining business write living broad variety subject ranging science politic military history renewable energy follow work google related post mandate carbon taxe teslas quarterly conference call cleantech talk martin canada toyota supply highlander hybrid model market higher price kerry carter build quickcharger infrastructure put comparison graph havent bought yet infrastructure roll cdric ive put number excel file multiply sale figure battery size kwh amount rolling energy storage sold tesla sold kwh nissan leaf kwh mitsubishi outlander phev kwh renault zoe kwh nissan env kwh total kwh kwh sold model outsell nissan leaf mitsubishi outlander phev renault zoe egolf bmw nissan env combined donald zenga sale europe outselling month tesla sold lot more wonderful chart interesting philip renault germany slashed price renault zoe bringing battery rent valid june zachary shahan wow thank worth storey philip renault sell evs now offer free test ride zoe twizzy kangoo gaining momentum slowly steadily sola leaf sale double montly sale higher price zachary shahan norway decent sale country france germany safe charge wonderful fantastic growth rate electric vehicle europe worldwide consumer embracing reason including great environment fact fun drive shiggity mitsubishi rocking hard research basically good suv version chevy volt plugin hybrid hybrid suv kind sucked compared sedan michael jameson bmw flew autobahna weekend cool shiggity nice expressway chicago week theyre future philip nice speed yet lot gotta something perk living bmw city zachary shahan wow haha city that munich philip car bmw and mini day that time front back part covered week covered zachary shahan ive pretty fun video featuring germany moving publish long stefano tapper what growth quarter compared course quarter car sold europe evs car sold evs zachary shahan honestly excluded jose number developed time gathered source dont affect growth additionally awhile original data germany france netherland norway country offer comprehensive for model data close lump electric version gasmobile gasmobile egolf golf germany include breakdown awhile stopped year ago forget now long storey short number broad stroke hinting general reality very regard dont trust number accurate itd trust growth rate reporting specific record growth number fairly accurate large market missing good guidance shouldnt looked absolute number perfect statistic great publish article journalistic integrity inaccurate number commenter fill gap number considered uncertain fact cheque good work usual writer cleantechnica reach standard spec crazy mitz selling outlander phev usa production constrained big hit usa too zachary shahan ","m_szGeo1":"United States","m_szSourceType":"source_industry","m_szSrcUrl":"http://cleantechnica.com/2015/05/06/europe-electric-car-sales-booming/","m_Places":["Europe","Us","Tesla","Toyota","Free City","Dortmund","Canada","Norway","France","Uk","Germany","Nice","Chicago","Perks","Munich","Most","Usa"],"m_People":["Ev Sales","Jose Pontes","Mercedes-benz B-class","Kangoo Ze","James Ayre","Kerry Carter","Renault Zoe","Donald Zenga","Philip W","Renault Germany","Zachary Shahan","Chevy Volt","Michael Jameson","Stefano Tapper"],"m_Companies":["Renault","Zoe","Volkswagen","Bmw","I3","Audi A3","Nissan","Cleantech","Citroen","Peugeot","Volvo","University Of Astnide","Google","Excel","Eu"],"m_BiGrams":["zachary shahan","electric vehicle","mitsubishi outlander","unit sold","nissan leaf","renault zoe","outlander phev","electric car","record unit","european market"],"m_TriGrams":["mitsubishi outlander phev"],"m_SocialTags":[],"m_Topics":[],"m_Industry":[],"m_Technology":[],"m_BiCnt":[6,5,5,5,5,5,4,3,3,3],"m_TriCnt":[3],"m_iDocBodyWordCnt":701}
