{"m_szDocID":"266462","m_szDocTitle":"Renewable Energy Facts --- 6 Things to Know","m_szYear":"2012","m_szDocSumamry":"March 30th, 2012 by Zachary Shahan Â  Adam Jones, Special Assistant for Energy Policy at American Progress, wrote a great post on Climate Progress this week on 6 things you really need to know about the value of renewable energy . They are all things that we have covered many, many times here on CleanTechnica, but they are still worth seeing again, especially in a focused, list format. So, here they are: Clean energy is competitive with other types of energy Clean energy creates three times more jobs than fossil fuels Clean energy improves grid reliability Clean energy investment has surpassed ","m_szDocBody":"zachary shahan adam jone special assistant energy policy american progress wrote great post climate progress week renewable energy covered many time cleantechnica worth again focused list format are clean energy competitive type energy clean energy create time job fossil fuel clean energy improve grid reliability clean energy investment surpassed investment fossil fuel investment clean energy cost effective fossil fuel time subsidy clean energy jone give detail point listing tonne renewable energy fact great job detail the remainder post jone climate progress piece add note initial clean energy competitive type energy renewable energy cheap today california solar developer signed contract power projected price natural gas combinedcycle power plant wind developer signing longterm powerpurchase agreement the cent kilowatthour range cheaper power source analysis bloomberg energy finance project wind fully competitive energy produced combinedcycle gas turbine fair wind condition renewable energy compete natural gas unsustainably low price natural gas largescale renewable energy nipping heel case keeping pace health cost grid cost externality account solar power grid parity competitive solar panel lifespan cost analyse wind power wind turbine also solar power hit grid parity taking externality solar panel lifespan account country germany italy brazil wind country well clean energy create time job fossil fuel national study showed job creation clean energy outdoe fossil fuel margin dollar put clean energy create time job putting dollar oil gas europe million people employed renewable energy report bureau labour statistic brooking institute show kind employment started hold show enormous promise potential future clean energy improve grid reliability texas power emergency averted due state commitment wind farm picked slack failing power plant prevented catastrophe tripp doggett chief executive nonprofit electricity reliability council texas responsible controlling flow electricity million consumer texas thanked wind industry contribution reach point percent energy wind negative impact electric grid reliability wind power easier manage case point energy predictably delivered german wind farm showing renewable managed effect consumer spreading wind farm wider geographic areas united state increase predictability more country proving largescale integration renewable possible percent denmark electricity coming wind time wind power fulfil percent demand western denmark additional cost integration small balancing cost cost provide backup power resource wind percent total wind generation cost effect consumer power price close zero clean energy investment surpassed investment fossil fuel year time global investment renewable energy surpassed investment fossil fuel global market clean energy worth whopping billion united state leading corporate r&d venture capital investment clean energy globally year retook top spot investment percent increase billion investment clean energy cost effective government investment clean energy vital meeting goal keeping america cutting edge innovation competitiveness globally added risk loan guarantee programme brought important clean energy project valley death apt description financing gap creating product commercialising helped create vibrant valuable market production tax credit successfully lowered cost wind power percent independent report conducted herb allison exnational finance chairman john mccain found department energy loan guarantee programme cost billion initially expected state solar wind installed capacity lowest rise electricity price rate increase state cent year national average cent additionally societal level numerous studiesby investor worldleading economist shown cost climate action much lower cost climate inaction fossil fuel time subsidy clean energy date oilandgas industry received billion adjusted inflation cumulative energy subsidy renewable energy source received billion adjusted inflation renewable energy investment put proper historical perspective energy information agency focusing single year data capture imbedded effect subsidy occurred year energy fuel technology government showing smaller commitment renewable showed early year oilandgas industry study showed early year oil gas industry federal subsidy producer averaged half percent federal budget contrast current support renewable barely size onetenth percent federal spending conclusion renewable energy engine economic growth prosperity year come opposition leader policy business american empowered renewable power work overcome market barrier false information fact seize opportunity put american back work maintain place cutting edge innovation competitiveness image credit wind turbine solar panel globe courtesy shutterstock cleantechnicas completely free electric car report electric car early adopter follower want youd attend electric vehicle solar power event conducted cleantechnica date hottest cleantech new subscribing free cleantech newsletter eye sectorspecific new also free solar energy newsletter electric vehicle newsletter wind energy newsletter tag clean energy benefit clean energy investment clean energy job clean energy fossil fuel fossil fuel investment fossil fuel job fossil fuel job quicky renewable energy benefit renewable energy job renewable energy zachary shahan tryin and specy letter time spend time cleantechnica director chief editor otherwise enthusiastically fulfilling duty obsession gas solar love planetsave bikocity president important media zach recognised globally solar energy electric car energy storage wind energy expert speak related conference event connect social media zacharyshahancom related post ","m_szGeo1":"United States","m_szSourceType":"source_industry","m_szSrcUrl":"http://cleantechnica.com/2012/03/30/renewable-energy-facts/","m_Places":["California","U.s.","Germany","Italy","Brazil","Europe","Texas","United States","Denmark","America"],"m_People":["Zachary Shahan","Adam Jones","Tripp Doggett","Herb Allison","John Mccain"],"m_Companies":["Lifespan","Bureau Of Labor Statistics","Brookings Institute","Slack","U.s. Government","Gap","Department Of Energy","Information Agency"],"m_BiGrams":["clean energy","renewable energy","fossil fuel","investment clean","energy investment","investment fossil","wind power","energy create","create time","time job","job fossil","grid reliability","surpassed investment","natural gas","solar power","solar panel","wind farm","electric car"],"m_TriGrams":["investment clean energy","create time job","job fossil fuel","clean energy investment"],"m_SocialTags":[],"m_Topics":[],"m_Industry":[],"m_Technology":[],"m_BiCnt":[22,13,12,5,4,4,4,3,3,3,3,3,3,3,3,3,3,3],"m_TriCnt":[5,3,3,3],"m_iDocBodyWordCnt":763}
