{"m_szDocID":"267069","m_szDocTitle":"Mitsubishi Outlander Plug-In Now #2 In UK Electric Car Sales | CleanTechnica","m_szYear":"2015","m_szDocSumamry":"Mitsubishi Outlander Plug-In Now #2 In UK Electric Car Sales Originally published on EV Obsession . Despite the Nissan LEAF’s apparently strong top position in the UK electric vehicle (EV) market, the Mitsubishi Outlander plug-in hybrid (PHEV) has managed to make significant gains since its release last year. As of the most recent figures (via RAC Foundation analysis of DVLA data), there were 5,273 Outlander PHEVs in the UK at the end of 2014 , as compared to 6,838 Nissan LEAFs. That’s quite impressive considering that the LEAF first went on sale in the UK market back in 2011, and Mitsubishi’s","m_szDocBody":"mitsubishi outlander plugin electric car sale originally published obsession nissan leaf apparently strong top position electric vehicle market mitsubishi outlander plugin hybrid phev managed make significant gain release year recent figure via rac foundation analysis dvla data outlander phevs end compared nissan leaf impressive leaf sale market back mitsubishis offering released year guess brit suvs lot sale number impression outlander phev top spot soon clear frontrunner bmw place registration end way nissan mitsubishi offering bad three thposition tesla model unit sold doubt ceo elon musk figure again guess teslas recent success battery pack unveiling company good regardless additionally remember tesla supply limited globally electric vehicle sale momentum building phenomenal rate benefit allelectric driving widely rapid charging infrastructure grow country stated paul oneill manager nissan motor delighted awardwinning nissan leaf continue dominate pure market break sale record year progresse true enough rapid growth market late guess manufacturer involved feeling pretty decent image credit mitsubishi cleantechnicas completely free electric car report electric car early adopter follower want youd attend electric vehicle solar power event conducted cleantechnica date hottest cleantech new subscribing free cleantech newsletter eye sectorspecific new also free solar energy newsletter electric vehicle newsletter wind energy newsletter tag mitsubishi mitsubishi outlander mitsubishi outlander plugin mitsubishi outlander plugin electric car jame ayre background predominantly geopolitic history obsessive interest pretty everything early life spent imperial free city dortmund jame river ruhr cofbuokheim attended university astnide briefly considered entering coal mining business write living broad variety subject ranging science politic military history renewable energy follow work google related post ","m_szGeo1":"United States","m_szSourceType":"source_industry","m_szSrcUrl":"http://cleantechnica.com/2015/05/11/mitsubishi-outlander-plug-in-now-2-in-uk-electric-car-sales/","m_Places":["Uk","Tesla","Free City","Dortmund"],"m_People":["Elon Musk","Paul O’neill","James Ayre"],"m_Companies":["Rac Foundation","Dvla","Guess","Bmw","I3","Nissan","Nissan Motor","University Of Astnide","Google"],"m_BiGrams":["mitsubishi outlander","outlander plugin","electric car","electric vehicle","nissan leaf"],"m_TriGrams":["mitsubishi outlander plugin"],"m_SocialTags":[],"m_Topics":[],"m_Industry":[],"m_Technology":[],"m_BiCnt":[4,4,4,4,3],"m_TriCnt":[3],"m_iDocBodyWordCnt":255}
