{"m_szDocID":"268592","m_szDocTitle":"Most-Polluted Cities in US (American Lung Association Infographic), & Find Out Your City's Grade | CleanTechnica","m_szYear":"2012","m_szDocSumamry":"May 9th, 2012 by Zachary Shahan     The American Lung Association (ALA)recently released its latest State of the Air report, State of the Air 2012. To go along with the report, it also published an infographic on the most-polluted cities and the “cleanest city” in the US. That’s below, followed by a guest post from Dr. Albert Rizzo, pulmonologist and Chair of the American Lung Association. But first… in case your city isn’t on the infographic below and you’re curious about what grade it got, you can enter your zipcode in the widget below and find out your city’s grade.   Now, on to the infogra","m_szDocBody":"zachary shahan american lung alarecently released lateststate air report state air report published infographic mostpolluted city cleanest city below guest post fromdr albert rizzo pulmonologist chair american lung association case city isnt infographic youre curious grade got enter zipcode widget city grade now infographic guest post hold ctrl command key enlarge infographic good new air and notsogood too safe air breathe live pulmonologist chair american lung association national board director pleased share tool answering question american lung association state air report released this annual report card latest report found mix good notsogoodnew first give quick reason healthy air matter toyou children teenager air pollution affect lung grow function roughly percent lung develop born continue grow adolescence lower lung function mean higher risk developing lung diseaseand needing doctor metheir entirelive family lung diseaselike asthma air pollution make worse study show air pollution aggravate asthma making harder breathe increasing likelihood emergencyroom family cardiovascular disease diabete particle pollution increase risk heart attack increase risk emergency room hospitaladmission enjoy working exercising outdoorsyour lung harmed pollution realising healthy lifeguard police officer hiker mountain measurable reduction lung function active outdoor pollutionday criticallyair pollution increase risk dying early yes level pollution united state ozone particle pollution cankill state air report cover year recent qualityreviewed data available find here goodnew breathing cleaner air nation clean air act that lifesaving public health law led clean major air pollution source including coalfired power plant diesel engine suvs pickuptruck eighteen city polluted ozone including city los angele lowest smog level firststate airreport released seventeen city worst annual particle pollution level including los angele pittsburgh cincinnati enjoyed lowest everlevel now notsogoodnew million peoplelive areas received ffor unhealthy level ozone particlepollution million live areas failed pollution test unhealthy level ozone yearround particle pollution shortterm particlepollution air quality standard set epa remain outdated mean clean pollution based current research protect family healthand member congress continue effort dismantle clean air actand block ability protect yourhealth see plenty work ensure american breathe clean healthyair people continue develop lifethreatening health condition die prematurely result inhaling dirty air unfortunately congress steadfast effort weaken clean airact urge join fight healthy air start finding grade community lateststate airreport type zip code report card above contact member congress support clean air actincluding standing action weaken block delay full implementation lifesavinglaw hear healthy air share healthy air mean family learn air pollution impact community visiting together healthy air future depend action today forward hearing fromyou albert rizzo american lung national boardchair cleantechnicas completely free electric car report electric car early adopter follower want youd attend electric vehicle solar power event conducted cleantechnica date hottest cleantech new subscribing free cleantech newsletter eye sectorspecific new also free solar energy newsletter electric vehicle newsletter wind energy newsletter tag ala american lung infographic polluted air polluted city polluted city polluted city state air state air zachary shahan tryin and specy letter time spend time cleantechnica director chief editor otherwise enthusiastically fulfilling duty obsession gas solar love planetsave bikocity president important media zach recognised globally solar energy electric car energy storage wind energy expert speak related conference event connect social media zacharyshahancom related post ","m_szGeo1":"United States","m_szSourceType":"source_industry","m_szSrcUrl":"http://cleantechnica.com/2012/05/09/most-polluted-cities-in-us-american-lung-association-infographic-find-out-your-citys-grade/","m_Places":["Most","United States","Us","Los Angeles","Pittsburgh","Cincinnati"],"m_People":["Zachary Shahan","Albert Rizzo"],"m_Companies":["American Lung Association","Ala","Epa","Congress"],"m_BiGrams":["american lung","state air","healthy air","air pollution","air report","particle pollution","lung association","increase risk","clean air","city polluted","electric car","polluted city"],"m_TriGrams":["state air report","american lung association"],"m_SocialTags":[],"m_Topics":[],"m_Industry":[],"m_Technology":[],"m_BiCnt":[6,5,5,5,4,4,3,3,3,3,3,3],"m_TriCnt":[3,3],"m_iDocBodyWordCnt":517}
