{"m_szDocID":"269818","m_szDocTitle":"Indian Wind Energy World Leader Fights for Survival - CleanTechnica","m_szYear":"2012","m_szDocSumamry":"Indian Wind Energy World Leader Fights for Survival May 28th, 2012 by Andrew   Photo courtesy: Suzlon Wind, solar, and other renewable energy markets and industries continue to grow at faster rates than those of their respective national economies. Yet, in large part, continued development of their businesses, their staying power, or financial sustainability — whether they are involved in wind, solar, geothermal or other industry segments — remains in doubt. This poses serious problems for customers and market demand. Wind turbines, solar panels, and other clean technologies are built to provi","m_szDocBody":"indian wind energy world leader fight survival andrew photo courtesy suzlon wind solar renewable energy market industry continue grow faster rate respective national economy yet large part continued development businesse staying power financial sustainability involved wind solar geothermal industry segment remain doubt pose problem customer market demand wind turbine solar panel clean technology built provide decade worth clean renewable energy issuing warranty product common practise confident customer vendor long product warranty vexing problem case leading leading name respective businesse indias leading wind turbine manufacturer suzlon instance indias wind power market renewable energy industry grown tremendously recent year driven enactment renewable energy legislation target incentive establishment toplevel government ministry renewable energy largely dependent imported fossil fuel indias wind energy market largest world wind power expected installed adding accumulated total end year suzlon prime beneficiary yet company verge default insolvency back financial brink fortunately suzlon recent operating financial performance improved banker investor confidence bank stepped pledged loan company million facing convertible bond redemption million round redemption october loan bring suzlon back brink suzlon reported fiscal year revenue grew billion cash flow measured ebitda earning interest taxe depreciation amortisation jumped basis point jump ebitda due change accounting policy however management decided align revenue recognition policy repower main international subsidiary parent company ebitda margin growth shrunk economic time india reported forward wind turbine manufacturer order book grew billion highest level ever management expect revenue billion improving ebit cash flow margin addition securing loan pledge management additional step taken however april suzlon announced generate million cash sale block wind energy asset majority located southern indian state tamil nadu pleased announce divesting noncore asset set raise approximately usmn plan outlined year modest important step forward strategy optimise capital structure meet repayment obligation year commented cfo kirti vagadia addition divesting noncore asset consistently improving business performance outlook strong revenue visibility put strong position begin fiscal wind energy world leader struggle financial survival suzlon quickly forged major player global wind power market announcement loan pledge recent performance doubt prove reassuring growing customer base directly indirectly extend national government india south africa embarking ambitious renewable energy development programme week suzlon chosen preferred wind turbine supplier cennergi wind power project joint venture south africas exxaro resource tata power ltd indias largest utility term unfinalized engineering procurement construction epc contract suzlon supply smw wind turbine project scheduled start construction south africas eastern cape province early year nonetheless suzlon remain fine edge dividing financial sustainability default bankruptcy debt burden totaled billion end march management continue pursue variety option restructure capital base including selling noncore asset issuing equity additional debt hence economic time wrote investor bondholder anxiously waiting eventually manage fulfil commitment growing number wind renewable energy company international landscape europe world leader installing wind renewable energy instituting innovative marketbased mechanism stimulate foster demand facing recession european country pulling back feedin tariff rate key growth factor however midst debt problem slow fragile recovery congress appear unable unwilling extend key wind renewable energy investment production tax credit economy largest export market weakening concerned rising inflation growth slowed china result worse better economic carnage expected renewable energy marketscape barring significant impetus stimulate demand cleantechnicas completely free electric car report electric car early adopter follower want youd attend electric vehicle solar power event conducted cleantechnica date hottest cleantech new subscribing free cleantech newsletter eye sectorspecific new also free solar energy newsletter electric vehicle newsletter wind energy newsletter tag affordable wind energy cennergi clean energy policy emission reduction ghg emission reduction india ministry renewable energy india renewable energy india renewable energy growth india renewable energy target india wind energy india wind energy capacity reducing emission renewable energy finance renewable energy policy south africa wind energy suzlon suzlon finance suzlon new suzlon south africa wind energy finance wind energy new andrew reporting writing wide range topic nexus economic technology year now asiapacific europe americas africa middle east issue related broad topical areas pose tremendous opportunity challenge define quality live relationship natural environment related post ","m_szGeo1":"United States","m_szSourceType":"source_industry","m_szSrcUrl":"http://cleantechnica.com/2012/05/28/indian-wind-energy-world-leader-fights-for-survival/","m_Places":["Take","India","Us","South Africa","Eastern Cape Province","Europe","China","Asia","Africa","Middle East"],"m_People":["Kirti Vagadia"],"m_Companies":["Economic Times","Tata Power Co. Ltd.","U.s. Congress","Nexus"],"m_BiGrams":["renewable energy","wind energy","wind turbine","wind power","world leader","noncore asset","south africa","wind renewable","energy india","india renewable"],"m_TriGrams":["wind renewable energy","india renewable energy"],"m_SocialTags":[],"m_Topics":[],"m_Industry":[],"m_Technology":[],"m_BiCnt":[16,11,5,4,3,3,3,3,3,3],"m_TriCnt":[3,3],"m_iDocBodyWordCnt":656}
