{"m_szDocID":"271446","m_szDocTitle":"5 Things We Learned about Day 1 of the Australia Carbon Price... | CleanTechnica","m_szYear":"2012","m_szDocSumamry":"July 3rd, 2012 by Giles Parkinson     If you are reading this item now then it means that the world did not end with the introduction of the carbon price. Sadly, neither did the political posturing. The government said it was an economic reform that reflected fundamental Labor values. Prime Minister Julia Gillard said the government didn’t do it for opinion polls (clearly not), but for the nation’s future, even though it is clear to most that were it not for the independents and the greens and a hung parliament we would still be sitting in a tent listening to a People’s Assembly. So, while Lab","m_szDocBody":"gile parkinson reading item mean world end introduction carbon price sadly political posturing government economic reform reflected fundamental labour value prime minister julia gillard government didnt opinion poll clearly not nation future clear independent green hung parliament sitting tent listening people assembly labour minister whyalla cringeworthy stunt prove city exist coalition launched advertising campaign suggested armegeddon drawn minisery single biblical event radio shockjock alan jone told strong crowd melbourne climate science witchcraft businesse carbon price terrific essential reform economy afford mineral industry lamented fact job exist exist future statement existential seemed industry commitment cost job reduction automation driverless truck anticipate innovation software programme manage lobbying effort make peak body redundant treasurer wayne swan issued press release featuring useless statistic carbon abatement cutting australias emission million tonne the cent target taking million car road matter australia doesnt million car reduction place overseas lot car and cheap emission reduction project point statement mean driving windpowered electric vehicle riding solar charged bus dont sell bicycle policy debate semantic debate climate change policy australia semantic alliteration axe tax ditch witch carbon pricing emission reduction target julia gillard blundered describing carbon price emission trading scheme fixed price start tax promised implement tony abbott vowed axe tax question put ice price chance wont cant number make hes acting protect job cost living stuff wouldnt government lead slashing fixed price accelerating move emission trading scheme move guaranteed bring price half remove tax label wont ice price business wont him finding price working assumption carbon price introduced encourage clean investment labour lose power price needed long term astute observer policy politic deutsche bank tim jordan suggest australia forced seriousy managed price create reliable signal lowcarbon investment forward carbon price determine success jordan australias carbon policy confused twin goal originally meet australias emission reduction target flexible costeffective way put put price greenhouse gas emission encourage investment clean energy jordan objective conflict important remember clean energy investment necessary needed ensure future abatement cheap emission reduction target end and renewable energy target matter locking higher carbon path simply mean costly adjustment track like future prime minister wyatt roy carbon bailout day financial year dubbed carbon sunday surely working day financial year bailout friday first federal government announced disbursing money alcoas point henry smelter ensure job protected year and floor didnt fall wholesale electricity market making handout energy brix ostensibly protect job possibly ensure company year government pay money close contract closure scheme signal buyout confusing government handing compensation hand ensure generator stay open making offer buy another ensure close down unhappily compensation package caused generator inflated worth friday however government hand latest forecast aemo suggest stick business model process month project benefit extension surprise surprise billion solar thermal project solar dawn lost funding state government failed obtain power purchase agreement statefunded utility this turn forced hand federal government back solar flagship project total predictable farce thankfully funding hand independent australian renewable energy agency carbon price compare mobile phone spending taxe wee bit context help graph australia institute highlight carbon price compare revenue gst fuel excise taxe compare household spending mobile phone fast food thing fairly selfexplanatory originally published renew economy cleantechnicas completely free electric car report electric car early adopter follower want youd attend electric vehicle solar power event conducted cleantechnica date hottest cleantech new subscribing free cleantech newsletter eye sectorspecific new also free solar energy newsletter electric vehicle newsletter wind energy newsletter ","m_szGeo1":"United States","m_szSourceType":"source_industry","m_szSrcUrl":"http://cleantechnica.com/2012/07/03/5-things-we-learned-about-day-1-of-the-australia-carbon-price/","m_Places":["Melbourne","Australia","Jordan"],"m_People":["Giles Parkinson","Julia Gillard","Alan Jones","Wayne","Tony Abbott","Tim Jordan","Wyatt Roy"],"m_Companies":["The Greens","Target","Deutsche Bank","Signal","Path","Alcoa","Brix","Energy Agency","Australia Institute"],"m_BiGrams":["carbon price","emission reduction","electric vehicle","reduction target"],"m_TriGrams":["emission reduction target"],"m_SocialTags":[],"m_Topics":[],"m_Industry":[],"m_Technology":[],"m_BiCnt":[7,4,3,3],"m_TriCnt":[3],"m_iDocBodyWordCnt":562}
