{"m_szDocID":"272025","m_szDocTitle":"Conservatives Concerned about Climate Change Stepping It Up | CleanTechnica","m_szYear":"2012","m_szDocSumamry":"Conservatives Concerned about Climate Change Stepping It Up July 15th, 2012 by Zachary Shahan     Former Republican Congressman Bob Inglis (who was ousted by the Tea Party) is, as far as I can tell, a true climate hawk. Some of the best speeches I’ve seen on climate change have come from him. Unfortunately, he’s essentially been kicked out of Republican national-level politics as a result of this. But he’s doing all he can to allow more conservatives the space and freedom to educate themselves about global warming and climate change and stimulate action from that side of the aisle. After all, ","m_szDocBody":"conservative concerned climate change stepping zachary shahan republican congressman bob inglis who ousted tea party tell true climate hawk speeches ive climate change him unfortunately hes essentially kicked republican nationallevel politic result this hes conservative space freedom educate global warming climate change stimulate action side aisle all screwed dont water drink house burned down extremely large megastorm tearing city disease wreaking havoc society here projectthe energy enterprise initiative e&eia nationwide public engagement campaign sister red green blue sane conservative end climate denial dirty energy via red green blue george mason university announced today formation energy enterprise initiative e&ei nationwide public engagement campaign led congressman bob inglis explore promote conservative solution americas energy climate challengese&ei operate more connect google zacharyshahancom cleantechnicas completely free electric car report electric car early adopter follower want youd attend electric vehicle solar power event conducted cleantechnica date hottest cleantech new subscribing free cleantech newsletter eye sectorspecific new also free solar energy newsletter electric vehicle newsletter wind energy newsletter tag bob inglis climate hawk congress e&ei energy enterprise initiative gop quicky republican zachary shahan tryin and specy letter time spend time cleantechnica director chief editor otherwise enthusiastically fulfilling duty obsession gas solar love planetsave bikocity president important media zach recognised globally solar energy electric car energy storage wind energy expert speak related conference event connect social media zacharyshahancom related post pingback carolina republican nationwide clean energy plan cleantechnica captivation left understand science issue reframed way appeal wing psychology rugged individualism solar panel contrasted domination oil industry issue national defence family value captured renewable energy framework issue climate justice rainforest back seat dont matter target audience doesnt term bobwallace emphasise individual freedom utility company foreign oil emphasise saving money put saving money first captivation hit nested reply limit thread betcha fantastic choice movie dialogue delivery pretty good deliver problematic idea liberal drive modern car western ideal mind country folk ride horse costume separated historic modern create great cognitive cognitive dissonance eras not culture forced engage sarah ride north covered waggon liberate err bestow freedom upon suffering townspeople again plot wacky target audience pan modern car foreign luxury import horse good american ford truck government motor job avoid closeup tundra twit shes speaking tina fay tolipsyncher line spelled lipsink time perhap point timmy fall well give manly name mit wont work rick newt rickynewt chuck norris cameo rescue him working ross message own havent bought thoseargument yet gun bible toting belief inglis theyll relate nicholas republican republican democrat partially contradict republican view captivation translation software advanced year build app facilitate leftspeak rightspeak translating hand ive moderate success simply keeping syllable count low throwing occasional misspell aint yet ross government tea partier solar panel wind turbine hydro property threaten them thatd worked captivation great idea wouldnt happen make movie theyd difference showdown windy ridge newest update western youve thinkn ross feed output translation software script writing programme bobwallace let write script ofhardscrabblegun tottin folk pool retirement money put turbine windy ridge turbine start chopping lot rock dove evil epa youngster pull lexus suvs threaten pull down write grizzly mama heroine ive idea cast long dialogue zachary shahan lol blog stick photo there zachary shahan lol guy killing here zachary shahan zachary shahan exactly wind industry republican governor helm industry association talking language opportunity respect arena simply label connexion that reason conserving ability live earth leftist matter vandamme writing bob inglis president nov bobwallace vote romney scrape jim corcoran environmental science advanced apparent human appetite animal flesh driving force virtually major category environmental damage threatening human future deforestation erosion fresh water scarcity air water pollution climate change biodiversity loss social injustice destabilisation community spread disease worldwatch institute meat sustainable livestock sector emerge top contributor environmental problem scale local global finding report suggest major policy focus dealing problem land degradation climate change air pollution water shortage water pollution loss biodiversity livestock contribution environmental problem massive scale potential contribution solution equally large impact significant addressed urgency food agricultural organisation report livestock long shadow american skipped meal chicken week substituted vegetable grain carbon dioxide saving taking half million car road environmental defence fund choose vegan slow global warming one uplifting videos understand people making life affirming choice thomasgerke important understand left rightconservative liberal republican democrate people concerned longterm developement future children people caught daybyday politic role politic representative economic interesst include republican support natural gas oil lobby democrate political ally big coalsolution arise state level bipartisan efford moving germany decade ago politican decide change game favour renewable sustainable energy source understand consequence room exxon chevron big coal basicly decide end business create massive counter reaction energyall private enterprise drive market adequate option choose consumer drive market method effectively engage effetive climate change remediation programme cleaner option them allowing private enterprise rule area viable option dominant energy method sector desireable money wage successful campaign attrition establised technology make drawing board sound good surface viable option change private enterprise established financial technical domination areas programme caveat technology existing technology respect supplant existing inferior technology mean compliance epa ruling everyone interest healthy environment perspective irresponsible private enterprise lead brink climate change tipping point tell thisoldman conservative answer energy climate challenge inglis said correcting market distortion setting economic right stop retreating denial start stepping forward competition ideasthat odd majority socalled liberal who scared weve atmosphere saying dont regard liberal progressive contrast regressive robert reich call them house proclaiming top lung government doesnt work happily proceeding prove point long state union continue substance done carbon pollution else zachary shahan ","m_szGeo1":"United States","m_szSourceType":"source_industry","m_szSrcUrl":"http://cleantechnica.com/2012/07/15/conservatives-concerned-about-climate-change-stepping-it-up/","m_Places":["Best","America","Us","Inglis","Romney","U.s.","Germany"],"m_People":["Zachary Shahan","Bob Inglis","S. Carolina","Tina Fay","Chuck Norris","Jim Corcoran","Robert Reich"],"m_Companies":["Nationwide","George Mason University","Google","Congress","Going Nationwide","Seat","Target","No Government","Nicholas","Democrats","Us Government","Pool","Epa","Un","Food And Agricultural Organization","Environmental Defense Fund","Exxon","Chevron","New Technologies","Progressive","House"],"m_BiGrams":["climate change","zachary shahan","bob inglis","private enterprise","energy enterprise","enterprise initiative","electric car"],"m_TriGrams":["energy enterprise initiative"],"m_SocialTags":[],"m_Topics":[],"m_Industry":[],"m_Technology":[],"m_BiCnt":[7,7,4,4,3,3,3],"m_TriCnt":[3],"m_iDocBodyWordCnt":910}
