{"m_szDocID":"272417","m_szDocTitle":"Tesla Model X Signature Series Deliveries Begin! | CleanTechnica","m_szYear":"2015","m_szDocSumamry":"Tesla Model X Signature Series Deliveries Begin! Originally published on EV Obsession . Update: VIN #s aren’t truly representative of when vehicles are produced, so implications of VINs in the #600s getting shipped this week don’t necessarily include hundreds of Xs being delivered in the coming week or so. But we’ll find out more details soon enough. Update #2: See this:  Tesla Model X Production Kicks Into High Gear (CleanTechnica Exclusive) Update #3: Tesla Model X Signature Series VIN #1 was indeed delivered yesterday . The long, long wait is about to be over for the first people who put do","m_szDocBody":"tesla model signature sery delivery begin originally published obsession update vin arent representative vehicle produced implication vin shipped week dont necessarily include hundred delivered coming week detail enough update this tesla model production kick gear cleantechnica exclusive update tesla model signature sery vin delivered yesterday long long wait people whoput year ago reserve signature tesla model teslas electric suv quicker sport car road seat people approximately efficient toyota prius tow pound eyecatching convenient falconwing door founder sery model delivery began month ago tesla slowly delivering rest small number founder sery model carefully cheque detail finished vehicle watches issue doesnt retain production ramp acquire build part signature model supplier hard time ramping ship suv part case wednesday posted tesla motor club forum that person sig delivery date pickup factory respectively thread soft delivery date subject change today time signature reservation holder bonnie norman tweeted delivery scheduled weekend meaning floodgate opening model sig delivery factory pickup weekend thx #teslamotor team #cantwait #earlyxmas #xcited bonnie norman case lastminute issue hundred model tentatively scheduled delivery coming week tesla deliver hundred model end year christmas for reservation holder hoping present matches elon tentative guidance teslas quarter conference call tesla aimed producing hundred model week end year posted week signature model vin spotted york see picture below shipping plastic sticker spot apparently prepped tesla staff humorously soontobe owner model found arrival york spy shot emily wrote future owner red sig pretty bizarre learn car thread forum today car sit software didnt malfunction great reach final inspection software instal week firm delivery that finger crossed end year emily added signature model vin service centre stopped bit focused beauty yep bit dirty transport pic clean well signature tesla model reservation holder noted yesterday tesla motor club forum soft delivery date bonnie tesla planned deliver together bonny enthusiastic confirmation hour that sig hasnt chimed publicly tweet receiving weekendas announced delivered floodgate opening beware mercede bmw audi ready fly related cleantechnicas completely free electric car report electric car early adopter follower want youd attend electric vehicle solar power event conducted cleantechnica date hottest cleantech new subscribing free cleantech newsletter eye sectorspecific new also free solar energy newsletter electric vehicle newsletter wind energy newsletter tag tesla tesla model tesla model delivery tesla model founder sery tesla model production tesla model sale tesla model signature sery zachary shahan tryin and specy letter time spend time cleantechnica director chief editor otherwise enthusiastically fulfilling duty obsession gas solar love planetsave bikocity president important media zach recognised globally solar energy electric car energy storage wind energy expert speak related conference event connect social media zacharyshahancom related post replace windscreen standard price list approved aftermarket supplier glass local fitment centre supposed replace hepa philtre clog earlier remarkably tiny pore has philtre robwithab wouldnt sad turned answer killed electric car turned elon reeve musk tesla succeed success continue accelerate transition concerned business perspective level novelty contained model potential sink company door recall waiting happen unforeseen and unforeseeable wrong slightest order assure success product simpler car complete nobrainer fly lot measured headtohead ice suv offer people lack option rear door seating panoramic glass make inclined buy vehicle imho folk beijing chongqing hepa philtre lot people smaller city rural euro areas wont unhappy surprise service cost replace thing falcon door great option soccer mom wanting cooler version minivan lot outdoorsy people meh them realise put kayas windsurfer hangglider plus lot people outside usa mostly dont show wealth door shout money louder fake boob chandelier mcmansion imagine number potential european customer discretely avoid overthetop ostentation falcon door represent people innovative feature pay extra them super sound system sunroof obeche trim bigger battery ludicrous upgrade the ridiculously large windscreen people car offroad incline stuff lift wheel ground due compromised rigidity upper body result double hinge falcon door foresee torsion cabin superstructure foresee tension fracture suddenly appearing windscreen hope wrong right listening robwithab was driving road guy front patch gravel flicked stone nicked windscreen crack here big windscreen doctor guy fill special mix replace phoned insurance broker glass isnt covered policy shopping bit online replacement stock thing ill tesla service centre tomorrow morning worried havent give proper quote much surely robwithab finally here hope announcement option expensive difficulttosourceandmanufacture unnecessary bit add significantly cost production potential recall accelerated depreciation which pose big risk guaranteed buyback programme big windscreen cost fortune replace arent necessary one mean order car lot people prefer bothered signature configuration flagship catch eye drive publicity sold potential liability company sell cheaper version but higher profit margin lower potential future complication here idea upmarket suv obliterate market low maintenance cost great resale value eyewatering acceleration faultless safety record comfortable seating adult ample towing capacity long range millisecondresponse traction control emission infotainment system available automatic ota update priced frighten german right that cool wait hmmm know let waste year improve weird door ridiculously large windscreen sculptural seat hospital philtre add grand selling price adding bottom line fact back haunt future mass recall smh elon smh nice zach kyle field love ready fly christmasfor big kid aka adult zachary shahan ","m_szGeo1":"United States","m_szSourceType":"source_industry","m_szSrcUrl":"http://cleantechnica.com/2015/12/18/tesla-model-x-signature-series-deliveries-begin/","m_Places":["Tesla","New York","Ny","Us","Beijing","Chongqing","Usa","Best","Ota","Nice"],"m_People":["Bonnie Norman","X Vin","Zachary Shahan"],"m_Companies":["#1 Was Indeed Delivered Yesterday","Ramps","Ramping","Are Indeed Opening","Tesla Staff","Bmw","Audi","Hinge","Tesla Service Center"],"m_BiGrams":["tesla model","electric car","model signature","signature sery","founder sery","signature model","delivery date","reservation holder","hundred model","end year","lot people","falcon door"],"m_TriGrams":["tesla model signature","model signature sery"],"m_SocialTags":[],"m_Topics":[],"m_Industry":[],"m_Technology":[],"m_BiCnt":[10,4,3,3,3,3,3,3,3,3,3,3],"m_TriCnt":[3,3],"m_iDocBodyWordCnt":837}
