{"m_szDocID":"272582","m_szDocTitle":"US Solar Tax Credit Generates Green Jobs and Investment, and Pays for Itself - CleanTechnica","m_szYear":"2012","m_szDocSumamry":"Federal Solar Tax Credit Generates Green Jobs, Investment and Healthy Taxpayer Returns July 24th, 2012 by Andrew     Contrary to erroneous, misleading assertions to the contrary, the federal government’s Solar Investment Tax Credit (ITC) is proving to be an excellent investment for US taxpayers and the federal budget. The Solar ITC can boast of yielding a 10% internal rate of return (IRR) to taxpayers on the government’s initial investment, according to a study conducted by the US Partnership for Renewable Finance (US PREF). An American Council on Renewable Energy (ACORE) program, US PREF’s st","m_szDocBody":"federal solar tax credit generate green job investment healthy taxpayer return andrew contrary erroneous misleading assertion contrary federal government solar investment tax credit itc proving excellent investment taxpayer federal budget solar itc boast yielding internal rate return irr taxpayer government initial investment study conducted partnership renewable finance pref american council renewable energy acore programme pref study paid full based model developed solarcity multinational business tax consultancy kpmg examine cash flow generated tax revenue solar lease power purchase agreement ppas show tax credit residential system provide nominal benefit government scenarios life solar asset acore press release commercial solar project federal solar itc yield nominal benefit not adjusted inflation similar time frame clean energy policy correcting erroneous misleading assertion course acore analysis federal solar itc omit additional significant benefit residential commercial solar use reduction carbon greenhouse gas emission fossil fuel production consumption enhanced energy security possibility avoiding billion trillion dollar not mention live lost overseas military foray secure fossil fuel supply calculus well acore study midst presidential election year bankruptcy solar company received federal loan guarantee qualified solar itc timing release highlight bitter division congress obama administration support renewable clean energy misconception promulgated result federal programme and broadly commercial viability solar renewable energy project businesse acore understand solar power lead cleaner air greater independence fossil fuel commented solarcity ceo lyndon rive fewer people realise solar incentive pay themselve solar power political football election year investment tax credit beneficial bipartisan energy policy generation federal solar itc provided incentive private sector businesse investor led significant growth green job creation solar energy system installation roughly solar generation capacity installed itc expanded gtm solar market insight report acore note report showed solar installation increased yeartoyear itc effective stimulating private sector investment solar energy enhancing nation energy economic security diversifying energy mix improving quality life cleaner environment acore ceo dennis mcginn stated solarcity demonstrate model pay itself policy effective fiscally prudent cleantechnicas completely free electric car report electric car early adopter follower want youd attend electric vehicle solar power event conducted cleantechnica date hottest cleantech new subscribing free cleantech newsletter eye sectorspecific new also free solar energy newsletter electric vehicle newsletter wind energy newsletter tag acore affordable solar clean energy economy federal solar itc green energy economy kpmg clean energy obama clean energy policy presidential election presidential race seia solar energy economic solar itc solar loan guaranty solar subsidy solar tax credit sustainable development clean energy policy emission reduction solar energy investment solar investment solar job solar market insight andrew reporting writing wide range topic nexus economic technology year now asiapacific europe americas africa middle east issue related broad topical areas pose tremendous opportunity challenge define quality live relationship natural environment related post ","m_szGeo1":"United States","m_szSourceType":"source_industry","m_szSrcUrl":"http://cleantechnica.com/2012/07/24/federal-solar-tax-credit-generates-green-jobs-investment-and-healthy-taxpayer-returns/","m_Places":["U.s.","Us","Asia","Europe","Africa","Middle East"],"m_People":["Lyndon Rive","Dennis V. Mcginn"],"m_Companies":["Itc","American Council","Solarcity","Kpmg","Congress","Obama Administration","Nexus"],"m_BiGrams":["solar itc","clean energy","federal solar","tax credit","solar energy","energy policy","fossil fuel","solar power","investment solar"],"m_TriGrams":["federal solar itc","clean energy policy"],"m_SocialTags":[],"m_Topics":[],"m_Industry":[],"m_Technology":[],"m_BiCnt":[7,6,5,5,5,4,3,3,3],"m_TriCnt":[4,3],"m_iDocBodyWordCnt":446}
