{"m_szDocID":"280566","m_szDocTitle":"Obama Appeasement of China, Japan Wrecking Recovery - TheStreet","m_szYear":"2013","m_szDocSumamry":"textArticle -------------------- TheStreet Markets Today Obama Appeasement of China, Japan Wrecking Recovery The Obama's ill-conceived energy policies and appeasement of China and Japan are responsible for jump in the trade gap. Peter Morici Jun 3, 2013 12:00 PM EDT NEW YORK ( TheStreet ) -- Tuesday, the Commerce Department is expected to report the April deficit on international trade in goods and services was $41.2 billion, up from $24.9 billion when the economic recovery began. The Obama Administration's ill-conceived energy policies and appeasement of China and Japan are responsible for th","m_szDocBody":"thestreet market today obama appeasement china japan wrecking recovery obamas illconceived energy policy appeasement china japan responsible jump trade gap peter morici edt york thestreet tuesday commerce department expected report deficit international trade good service billion billion economic recovery began obama administration illconceived energy policy appeasement china japan responsible jump trade gap slow pace economic recovery household spending recovered consumer dollar pay imported oil consumer good car china japan consumer spending trade gap jumped businesse consequently remain pessimistic demand market reluctant invest majority businesse subject higher personal opposed corporate rate onerous costly regulation paying employee health care remain reluctant hire continue offshore job sequestration subtract billion actual government spending fiscal year impact pale comparison billion increase trade deficit billion tax jolt fracking lower delivered oil full push potential gulf atlantic pacific coast alaska cut import dependence half shifting federal subsidy electric car wind solar fuel efficient internal combustion engine plugin hybrid vehicle liquefied natural gas rail trucking slice import lower natural gas price substantially improve international competitiveness industry petrochemical fertiliser plastic primary metal however department energy push boost liquefied gas export handicap growth create million fewer job keeping gas home manufacturing alternative diesel transportation see company rank poorly paid vacation china systematically undervalue currency dollar good cheap china steal technology subsidise export impose tariff import effectively distracting obama administration commercial issue measured intransience cybersecurity nuclear issue north korea datemeta ","m_szGeo1":"United States","m_szSourceType":"source_investments","m_szSrcUrl":"https://www.thestreet.com/story/11939450/1/obama-appeasement-of-china-japan-wrecking-recovery.html","m_Places":["China","Japan","New York","United States","Alaska","North Korea"],"m_People":["Peter Morici"],"m_Companies":["Gap","Commerce Department","Obama Administration","Atlantic","Slice","Department Of Energy","Diesel","U.s. Companies"],"m_BiGrams":["china japan","appeasement china","trade gap"],"m_TriGrams":["appeasement china japan"],"m_SocialTags":[],"m_Topics":[],"m_Industry":[],"m_Technology":[],"m_BiCnt":[4,3,3],"m_TriCnt":[3],"m_iDocBodyWordCnt":229}
