{"m_szDocID":"28519","m_szDocTitle":"White water rafting with Sir John Major | Daily Mail Online","m_szYear":"1997","m_szDocSumamry":"White water rafting with Sir John Major   comments Sir John Major: Trips to New York, Chicago, Manila, Zurich, Seoul and Jamaica so far this year Officers protecting Sir John Major ran up a £120,000 bill for hotels and fine dining last year as the former Tory Prime Minister flew around the world to pursue his lucrative business interests. Sir John, who resigned as Conservative leader following his 1997 General Election defeat, has built up a portfolio of international directorships. Until 2005 he was a highly-paid adviser to the American private equity Carlyle Group and has also worked for US ","m_szDocBody":"white water rafting sir john major comment sir john major trip york chicago manila zurich seoul jamaica year officer protecting sir john major ran bill hotel fine dining year tory prime minister flew world pursue lucrative business interest sir john resigned conservative leader general election defeat built portfolio international directorship highlypaid adviser american private equity carlyle worked firm emerson electric car component bus firm mayflower recent commitment welldocumented year taxpayerfunded protection team york chicago manila zurich seoul jamaica busy schedule singapore stockholm back london home huntingdon cambridgeshire movement reflected expense claim armed protection team included night historic raffle hotel singapore total cost bill included officer treating sir john dinner elegant raffle grill include bill twonight stay fivestar grand hotel stockholm trip officer fly sir john miami seoul jamaica officer submitting raffle hotel singapore officer treated sir john dinner include river tubing safari officer accompanied sir john jamaica unclear sir john attendance trip threemile ride white river related article share share officer advance sir john miami section trip cheque security scotland yard account questioned stay cheaper comfort inn hotel superior wrote back authorising stay marriott occasion wrong type people utilise chain beef wellington sea bass rack lamb awaiting principal movement year eve american colony hotel jerusalem tony blair below stay tony blair role global businessman international peace envoy mean team elite firearm officer scotland yard standby join world short notice rota involving officer constantly move blair fly middle east week america next great public expense month year officer diplomatic protection team flown country prime minister time advance proposed trip ensure left chance personal security moneymaking trip blair personal fortune believed grown million swelled speaking engagement business enterprise globe year protection officer accompanied blair trip south east asia expense claim officer show stayed region hotel mandarin oriental kuala lumpur season singapore night season officer submitted singapore dollar about laundry charge singapore dollar hotel business centre total charge stay hotel blair made speeches trip place general election labour receiving drubbing poll paid astonishing sum address meeting national achiever congress organise forum young entrepreneur blair told wouldbe millionaire gathered vast shopping mall kuala lumpur power shifting east guy cutting edge malaysia night city blair protection officer cost taxpayer hotel expense blair protection officer put bill meal including beef wellington year eve oxford year eve year member blair protection team deployed oxford awaiting principal movement bosse query officer bill meal including pheasant beef wellington sea bass rack lamb bread butter pudding sticky toffee pudding soft drink brown restaurant pointed police account department cost meal strict limit dining response officer wrote attended brown restaurant dinner required book table due unusually large demand night there limited availability area set cost person due obvious additional staffing cost incurred year eve officer claimed night malmaison hotel oxford cost taxpayer receipt limousine hire accompanying blair trip america officer deployed york stayed historic elegant carlyle hotel manhattan upper east side cost taxpayer night scotland yard protection command expense team queried missing receipt limousine hire trip yale university haven connecticut blair visiting lecturer faith response officer blair begun journey yale helicopter land fog made enquire limousine service taxi destination levin president yale immediately offered service vehicle hired yale official order maintain control principal movement hired accredited limousine night jeddah officer travelled jerusalem jeddah saudi arabia kuala lumpur malaysia indonesia singapore washington billing taxpayer process stayed world finest expensive hotel night jeddah hilton cost told scotland yard official booked hilton hotel jeddah checkin handed credit card receptionist processed point asked room rate riyal equate stated mistake asked normal room told hotel full pilgrim unable leave hotel due volcanic ash situation stranded volcanic ash cloud volcanic ash cloud caused problem officer credit card bill claim questioned wrote period volcanic ash trouble happened whilst overseas fiveday deployment end overseas day incurred laundry charge due clothes period officer colleague forced stay anight american colony hotel jerusalem regularly dining hotel cellar bar travelling anight mandarin oriental kuala lumpur anight singapore season hotel ","m_szGeo1":"United Kingdom","m_szSourceType":"source_news","m_szSrcUrl":"http://www.dailymail.co.uk/news/article-1291838/White-water-rafting-Sir-John-Major.html","m_Places":["New York","Chicago","Manila, Zurich","Seoul","Jamaica","Uk","Singapore","Stockholm","London","Huntingdon","Miami","Jerusalem","Middle East","America","South East Asia","Kuala Lumpur","Malaysia","Oxford","Browns","Manhattan","Upper East Side","New Haven, Connecticut","Jeddah","Saudi Arabia","Indonesia","Washington Dc","Singapore Four Seasons Hotel"],"m_People":["John","Marriott","Levin"],"m_Companies":["Carlyle Group","Emerson Electric","Raffles Hotel","Raffles","Grand Hotel","Scotland Yard","American Colony Hotel","Envoy","Four Seasons","Carlyle Hotel","Yale University","Taxi","Hilton Hotel","Singapore Four Seasons Hotel"],"m_BiGrams":["sir john","protection team","scotland yard","year eve","kuala lumpur","volcanic ash","john major","seoul jamaica","beef wellington","principal movement","protection officer","blair protection","cost taxpayer"],"m_TriGrams":["sir john major"],"m_SocialTags":[],"m_Topics":[],"m_Industry":[],"m_Technology":[],"m_BiCnt":[10,4,4,4,4,4,3,3,3,3,3,3,3],"m_TriCnt":[3],"m_iDocBodyWordCnt":655}
