{"m_szDocID":"293205","m_szDocTitle":"Nuclear Power—Not Electric Cars—Will Change Our World (Sorry Elon) | Observer","m_szYear":"2016","m_szDocSumamry":"News & Politics | Arts & Entertainment | Style & Design | Business & Technology | Search for: Submit Observer Business & Tech News & Politics Editorials International National New York Politics Arts & Entertainment Art Movies Music Performing Arts TV Style & Design Fashion Food & Drink Health & Wellness Home Design Style Real Estate Travel Business & Technology Deals Innovators Internet Culture Media Startups About Advertise Subscribe Careers Masthead Contact Privacy Terms Follow Us Sign Up for Newsletters Opinion Nuclear Power—Not Electric Cars—Will Change Our World (Sorry Elon) By Richard Mu","m_szDocBody":"new politic art entertainment style design business technology for submit observer business tech new politic editorial international national york politic art entertainment art movy music performing art style design fashion food drink health wellness home design style real estate travel business technology deal innovator internet culture media startup advertise career masthead contact privacy term follow newsletter opinion nuclear powernot electric carswill change world sorry elon richard muller flux isotope reactor gamma blue glow post originally appeared quorawhat biggest way world year today biggest factor change probable huge twenty year nuclear power rapidly expanding world top environmentalist embracing nuclear part slowing stopping global warming include jame hanson stewart brand see examplescientific american remarkable movie pandoras promise stronger driver nuclear power developing world horrific air pollution killing million year china india turkey eastern europe see air pollution overview berkeley earth nuclear widely misinterpreted expensive cost construction construction cost artificially inflated regulatory delay cost nuclear power plant south korea nuclear developing world clean inexpensive alternative coal running nuclear fuel industry kilowatt hour cost uranium cost double amount economically extractable uranium world increase contribution cost electric power negligible shortage uranium shortage foreseeable future see example scientific american generation nuclear power plant see generation reactor make technology attractive world version plant require essentially maintenance structured nuclear battery operator electricity draw dont reactor naturally shut down spent fuel nuclear waste extracted factory small modular nuclear reactor dug shipped factory typically year fuel replacement yes design exist commercially built reactor based physic principle prevent meltdown mechanical safety mechanism needed reactor overheat reflectivity moderator drop turn chain reaction draw power temperature cool back operating range chain reaction turn back this prediction future generation plant designed year country africa generation nuclear power plant brag country reliable power clock children light led lamp night homework unlike children nonnuclear community public opposition nuclear power fade effective method nuclear waste isolation developed and development event chernobyl fading memory attributed stupid design russian consensus death tsunami fukushima tragedy fewer cancer death caused radioactivity leak you read book energy future president nuclear power generally accepted cheaper reliable deliver power clock clean renewable dont expect thorium reactor play big role india active development bulwark terrorism people think process thorium reactor convert thorium bomb thorium abundant uranium uranium plenty abundant stay cheap thorium reactor fewer longlived transuranic element waste isolation technology developing rapidly year dont expect waste impediment uranium plant nuclear power make electric automobile clean currently operate electric auto china produce gasoline engine running car coal nuclear future electric autos clean alternative plausible united state lag development regulatory impediment lingering public opposition drive technology originally developed country twenty year remote region africa recall unreliable electricity resident local modular nuclear power plant refer nuclear battery underground main component expected remain untouched year electricity connexion stick small building cable extend carrying power children carry ordinary chemical battery plant recharged for free illuminate book night power plant installed year earlier dust label say english made china related link industry greatest redesign innovation popular are boost intelligence insanely creative innovative logical thinker richard muller cofounder berkeley earth climate change air pollution research previously work experimental theoretical physic cosmology anisotropy dark energy particle physic geophysic impact geomagnetic reversal created physic future president berkeley hes physic future president instant physicistand sixother book including nowthe physic time published nortonhes acontributor quorayou follow quora twitter facebook google comment filed under nuclear power trending world largest rocket launch tomorrow top secret mission business tech deep space atomic clock key future space exploration business tech hack brain radically confident fearful business tech elon musk chart path colonising mar decade business tech observer advertise career contact privacy term powered wordpresscom vip","m_szGeo1":"United States","m_szSourceType":"source_general","m_szSrcUrl":"http://observer.com/2016/04/nuclear-power-not-electric-cars-will-change-our-world-sorry-elon/","m_Places":["New York","United States","Brand","China","India","Turkey","Europe","South Korea","Africa","Chernobyl","Fukushima","Made"],"m_People":["Elon Musk","Richard Muller","James Hanson"],"m_Companies":["Blue Glow","Quora","Scientific American","Pandora","Will Indeed Become Clean","Twitter","Facebook","Google","Path"],"m_BiGrams":["nuclear power","business tech","power plant","air pollution","future president","thorium reactor"],"m_TriGrams":["nuclear power plant"],"m_SocialTags":[],"m_Topics":[],"m_Industry":[],"m_Technology":[],"m_BiCnt":[10,5,5,3,3,3],"m_TriCnt":[4],"m_iDocBodyWordCnt":604}
