{"m_szDocID":"297871","m_szDocTitle":"CES 2016 gets underway in Las Vegas – in pictures | The National","m_szYear":"2016","m_szDocSumamry":"textArticle -------------------- CES 2016 gets underway in Las Vegas – in pictures January 7, 2016 The world’s largest annual consumer technology trade show, runs through January 9 and will feature about 3,600 exhibitors showing off their latest products and services to more than 150,000 attendees. The Toyota FCV Plus, a hydrogen fuel cell concept vehicle which capable to generate electricity directly from hydrogen stored outside and operate as a stable source of electric power for use at home or on the go. Alex Wong / Getty Images / AFP Reed Hastings, co-founder and CEO of Netflix, delivers a","m_szDocBody":"ces underway las vegas picture world largest annual consumer technology trade show run feature exhibitor showing latest product service attendee toyota fcv plus hydrogen fuel cell concept vehicle capable generate electricity directly hydrogen stored operate stable source electric power home alex wong getty image afp reed hasting cofounder ceo netflix deliver keynote address steve marcus reuter general motor chairman ceo mary barra deliver keynote address alex wong getty image afp faraday future ffzero concept performance electric vehicle built ffs variable platform architecture vpa modular engineering system optimised electric vehicle alex wong getty image afp dylan hixon augmented reality system business communication development ricoh david mcnew afp polaroid izone mini wifi digital camera displayed ces david becker getty image afp guitarist sampling ware inside gibson musical instrument tent mark damon epa mcor arke fullcolor desktop printer ecofriendly printer launched today ethan miller getty image afp model wear ifit monitor performance ifit booth ifit coach app gather information ifit wearable furniture exercise equipment monitor exercise activity nutrition sleep give personalised recommendation robyn beck afp sensorwake olfactory alarm clock selling promotional ces diffuse particle contained packet dry air give whiff espresso hot croissant lush jungle chocolate pepper mint gregory bull photo casios smart outdoor watch wsdf david becker getty image afp qualcomm booth day consumer electronic show lvnb epa samsung welt smart belt monitor user waistline app david becker getty image afp show attendee cheque nvidia drive autonomous driving system alex wong getty image afp dog cleverpet hub game console david paul morris bloomberg show attendee experience autonomous driving mode hyundai mobis icockpit car experiential simulator future car driving alex wong getty image afp spokesperson demostrate styler household clothing care machine upright machine remove wrinkle sanitise clothing david becker getty image afp sharad bachani merlin digital show headset photo courtesy peter nowak ","m_szGeo1":"United Arab Emirates","m_szSourceType":"source_news","m_szSrcUrl":"http://www.thenational.ae/business/technology/ces-2016-gets-underway-in-las-vegas--in-pictures","m_Places":["Las Vegas","Toyota","Hub"],"m_People":["Alex Wong","Reed Hastings","Steve Marcus","Mary Barra","Dylan Hixon","David Mcnew","David Becker","Mark Damon","Ethan Miller","Robyn Beck","David Paul","Peter Nowak"],"m_Companies":["Getty Images","Afp","Netflix","Reuters","General Motors","Ricoh","Polaroid","Epa","Coach","Gregory Bull","Ap","Qualcomm","Consumer Electronics Show","Samsung","Nvidia","Hyundai Mobis","Lg"],"m_BiGrams":["getty image","image afp","alex wong","wong getty","david becker","becker getty"],"m_TriGrams":["getty image afp","alex wong getty","wong getty image","david becker getty","becker getty image"],"m_SocialTags":[],"m_Topics":[],"m_Industry":[],"m_Technology":[],"m_BiCnt":[10,10,5,5,4,4],"m_TriCnt":[10,5,5,4,4],"m_iDocBodyWordCnt":299}
