{"m_szDocID":"298408","m_szDocTitle":"8 tech breakthroughs in 2015 that could help power the world, Opinion News & Top Stories - The Straits Times","m_szYear":"2015","m_szDocSumamry":"textArticle -------------------- The Straits Times ePaper 8 tech breakthroughs in 2015 that could help power the world The winning solar home design by the Stevens Institute of Technology submitted for the US Department of Energy's Solar Decathlon. PHOTO: THOMAS KELSEY An undated handout photo of Google's self-driving car in Mountain View, California. PHOTO: GORDON DE LOS SANTOS/GOOGLE VIA Toyota’s Mirai fuel-cell car – which converts hydrogen into electricity – being charged at Iwatani's hydrogen station in Tokyo. PHOTO: AGENCE FRANCE-PRESSE MIT researchers believe this smaller reactor could ","m_szDocBody":"strait time epaper tech breakthrough power world winning solar home design steven institute technology submitted department energy solar decathlon photo thomas kelsey undated handout photo google selfdriving car mountain view california photo gordon los toyotas mirai fuelcell car convert hydrogen electricity charged iwatanis hydrogen station tokyo photo agence francepresse mit researcher smaller reactor make longsought nuclear holy grail fusion reality illustration mit arc team published copy company worldwide racing put technology cleaner efficient energy market wendy koch car drive itself watch remotely turn light off home produce power neighbour blackout belong jetsonslike future arrived part tech era scientist entrepreneur rapidly bold ideas save energy provide cleaner alternative discovery country meet goal month historic united nation climate accord aimed slashing greenhouse gas emission public acceptance lawmaker approval funding avoid innovation oftencited valley death were problem solver here great challenge professor robert armstrong director massachusett institute technology mit energy initiative mit climate change priority involving thousand student faculty startup university national laboratory stepping billionaire club breakthrough energy coalition microsoft founder bill gate created ideas lab marketplace investor work country including united state china double spending clean energy research development selfdriving vehicle world biggest company investing big buck build electric vehicle partly drive themselve push proponent car reduce traffic accident save energy efficient routing ridesharing alphabet inc parent company google grabbed public fascination far cute fully selfdriving prototype police cruiser disney car movy road mountain view california austin texas outdone apple reportedly working car ridesharing giant uber partnered carnegie mellon university develop prototype appeared pittsburgh may tesla elon musk luxury electricvehicle maker step further october unveiled autopilot mode model sedan automatically adjust speed change lane park month later hong kong lawmaker warned tesla owner function illegal california unveiled preliminary rule month autonomous car require consumer special stateissued driver certificate receiving training car company vehicle traditional carmaker competing too ford pursuing deal build selfdriving car media report toyota joined company backing million million testing facility dubbed mcity opened university michigan announced plan spend billion year build robotic artificial intelligence research centre silicon valley stanford university secondary facility mit fuelcell car toyota maker prius bestselling hybrid car moving ahead massproduction fuelcell sedan mirai convert hydrogen electricity emit drop water made debut california rolled year european country mirai japanese word mean future single tank range greater electric car market even tesla current hydrogenpowered competitor honda fcx clarity hyundai tucson fuel cell car pricey costing subsidy obstacle lack station dispense compressed hydrogen gas california dozen filling location creating chickenandegg problem customer car station station opening car infrastructure starting expand california europe notably denmark britain germany shell hydrogen fuel station germany announced add location country installed existing gas station pump refuel car minute zeroemission electric fuel cell buse hitting road advanced nuclear reactor controversial environmentalist nuclear power caught eye tech titan dazzled potential provide abundant energy planetwarming emission pursuing holy grail fusion power source sun star scientist sought decade harness company lockheed martin general atomic funding smallscale project expect cheaper simpler amazon jeff bezos example backing general fusion vancouver company hightech hammer trigger fusion paypal cofounder peter thiel invested washingtonbased helium energy building trucksize reactor microsoft cofounder paul allen betting trialpha wellfinanced company reported milestone year held ball superheated gas steady millisecond longer effort summer mit researcher proposed doughnutshaped design small modular reactor commercially superconductor create stronger magnetic field they small fusion reactor running decade multiple decade mit prof armstrong that real game changer startup working safer cheaper efficient fission reactor today nuclear power plant derive heat splitting rather fusing atom portable prefabricated innovative fuel coolant mit alumni leslie dewan mark massie designed wasteannihilating molten salt reactor run nuclear waste bill gate funded terrapower usbased startup inked deal china codevelop advanced reactor travelling wave reactor run depleted uranium produce nuclear waste china planning rapid expansion nuclear power reactor year provide energy exacerbate air pollution choking city this significant john gilleland terrapower chief technical officer interview startup gate working chinese year reach agreement expect reactor operational decade fast timeframe type nuclear reactor power year marked launch world multimachine grid connected wave energy project carnegie wave energy coast australia technology development decade unique operate underwater safe large storm buoy tethered seabed pump move motion wave drive turbine produce power home national geographic channel breakthrough sery showed project work finale water apocalypse aired month wave power project completed deployment coast australia million biowave pilot unit biopower system mtall oscillating structure sway back beneath ocean swell capturing converting wave energy electricity fed grid undersea cable department energy doe marine hydrokinetic industry early development produce power meet half electricity usage doe spent million develop project august selected team advance phase million wave energy prize device tested meet doe goal doubling amount energy captured efficient solar solar taking price plummeted estimated cent report lawrence berkeley national laboratory plunge occur researcher way make solar smaller seethrough sticky road golf course landfill efficient panasonic solarcity largest residential solar installer debuted rooftop panel year world efficient panel continue improve march mit stanford researcher developed kind tandem solar cell boost efficiency lower cost connected layer photovoltaic material silicon basis today panel perovskite absorb higherenergy particle light mit researcher unveiled system year indias village create solarpowered microgrid built device smaller shoebox regulate power solar panel phone charging battery use developed world solarpowered house withstand storm debuted year solar decathlon competition recalling hurricane sandy damage student jersey steven institute technology won place building house islanding solar array produce power blackout neighbour charge phone highaltitude wind wind renewable declining cost tech advance allowing soar literally year keystone tower system built wind tower quick fully automated welding system received doe fund build onsite wind farm allowing tower taller transported highaltitude wind technology boost altaeros energy announced financial backing japan mitsubishi heavy industry altaeros developed buoyant airborne turbine huge balloon heliumfilled shell lift turbine ground high wind gain strength higher height blow faster blade highaltitude wind turbine kite generate electricity tallest towermounted one fact study estimate produce time power potentially meet time world current electricity demand altaeros half dozen competitor race capitalise potential bought them californiabased makani power added moonshot project kitelike competitor kitegen nts xwind powerplane ampyx power battery solar wind power seemingly limitless potential intermittent source energy stored race build battery lithiumion standard bearer introduced sony twoplus deade ago personal electronic pricey large flammable week announcement idea harvard researcher unveiled flow battery made cheap nontoxic highperformance material catch fire huge step forward open use professor michael aziz harvard university engineering lecturer coauthor study science year mit doe announced promising advance make battery cheaper battery push lab may teslas musk unveiled battery product plan massproduce billion gigafactory nevada product include sleek mountable powerwall unit solarcity company chair putting home month offering utility vermont green mountain power began selling leasing powerwall customer company challenging musk pittsburghbased aquion energy spinoff carnegie mellon university began selling saltwater battery stack year german storage developer sonnen month ramping production lithiumion battery facility san jose california home home automation battery part accelerated push make home smarter versatile key trend automation year debut apple watch level wearable electronic remotely operate led cfl smart thermostat compatible apple homekit suite product talk other siri example turn light open kitchen shade learning thermostat nest bought year billion nest cam motion sensor night vision eye home keen smart vent wifi maintain ideal room temperature automatically opening closing vent amazon echo sirilike personal assistant control connected home device consumer save energy smart gear research find reduce cent home energy lowcost behavioural change there inexpensive technology home conserve energy immediately called light switch recent carnegie mellon report convincing teenager light switch time leave room however social science challenge technology challenge national geographic distributed york time syndicate choose amazing gift plus stand win trip world luxurious stay resort world sentosa version appeared print edition time headline tech breakthrough power world print edition topic publishedjan sgt","m_szGeo1":"Australia","m_szSourceType":"source_news","m_szSrcUrl":"http://www.straitstimes.com/opinion/8-tech-breakthroughs-in-2015-that-could-help-power-the-world","m_Places":["Mountain View, California","Toyota","Tokyo","Jetsons","United States","China","Austin, Texas","Pittsburgh","Tesla","Hong Kong","California","Silicon Valley","Europe","Denmark","Britain","Germany","Vancouver","Washington","Australia","India","New Jersey","Japan","Nevada","Vermont","San Jose, California"],"m_People":["Thomas Kelsey","Gordon De Los Santos","Wendy Koch","Professor Robert","Bill Gates","Elon Musk","Jeff Bezos","Peter Thiel","Paul Allen","Leslie Dewan","Mark Massie","John Gilleland","Professor Michael","Aziz"],"m_Companies":["Stevens Institute Of Technology","Us Department Of Energy","Google","Agence France-presse","United Nations","Massachusetts Institute Of Technology","Microsoft Founder","Alphabet Inc","Disney","Apple","Uber","Carnegie Mellon University","University Of Michigan","Stanford University","Honda","Hyundai Tucson","Shell","Lockheed Martin","General Atomics","Amazon","Paypal","Microsoft Co-founder","Ball","National Geographic Channel","Doe","Lawrence Berkeley National Laboratory","Panasonic","Solarcity","Doe Funds","Mitsubishi Heavy Industries","Sony","Harvard University","Green Mountain Power","Aquion Energy","Sonnen","Ramping","Conserve","Carnegie Mellon","National Geographic Society","New York Times Syndicate","Sunday Times"],"m_BiGrams":["produce power","wave energy","institute technology","mit researcher","save energy","carnegie mellon","nuclear power","highaltitude wind"],"m_TriGrams":[],"m_SocialTags":[],"m_Topics":[],"m_Industry":[],"m_Technology":[],"m_BiCnt":[4,4,3,3,3,3,3,3],"m_TriCnt":[],"m_iDocBodyWordCnt":1298}
