{"m_szDocID":"298688","m_szDocTitle":"Uranium News: Fission Retail Shareholder Group Prepares for Proxy Fight - Investing News Network","m_szYear":"2015","m_szDocSumamry":"UraniumInvesting News Your trusted source for investing success Uranium Member? Login Menu Daily News Resource Investing Precious Metals Gold Silver Platinum Palladium Base Metals Copper Nickel Iron Lead Zinc Critical Metals Graphite Tungsten Tantalum Scandium Cobalt Magnesium Manganese Tellurium Rare Earth Industrial Metals Molybendum Coal Tin Aluminum Vanadium Chromium Energy Uranium Oil Gas Oil and Gas Lithium Gem Diamond Agriculture Potash Phosphate Cannabis About Resource Investing Technology Investing 3D Printing Cleantech Cloud Data Cybersecurity Fintech Graphene Mobile Web Nanotech Abo","m_szDocBody":"uraniuminvesting new trusted source investing success uranium member menu daily new resource investing precious metal gold silver platinum palladium base metal copper nickel iron lead zinc critical metal graphite tungsten tantalum scandium cobalt magnesium manganese tellurium rare earth industrial metal molybendum coal tin aluminium vanadium chromium energy uranium oil gas oil gas lithium gem diamond agriculture potash phosphate cannabis resource investing technology investing printing cleantech cloud data cybersecurity fintech graphene mobile web nanotech technology investing life science investing biotech pharmaceutical medical device genetic life science investing free investor report resource free report technology free report life science free report outlook free report stock resource investing technology investing life science investing uranium investing uranium new fission retail shareholder prepare proxy fight uranium new cantor fitzgerald positive uranium price nexgen energy hit radioactivity final hole summer drill programme kivalliq energy ceo jim top canadian uranium reso kristen moran add comment published fission uranium released update press release here uranium new week centred onthepossible merger fission uranium tsxfcu denison mine tsxdmlnysemktdnn arrangement shareholder arm dispute company aretail shareholder fcu oversight reached height announcedplan launch proxy fight mergerand havecertain fissionboard member removed based group recent press release appear ceo dev randhawa targeted fission board director reacted threat amending bylaw adopting advancenotice provisionthat force shareholder give company day notice theywant director annual general meeting scheduled fcu oversight founder jim gifford hired lawyer blair lockhart special adviser dissident director nominee meet fastapproaching advancenotice deadlineaccording afinancial post article dispute brewedfor month finally public week expert guide uranium investing free download free special reporturanium future outlook uranium price forecast top uranium stock watch fission taking seriously dundee capital market analyst david talbot see threat fcu oversight fading away majority fission shareholder voted favour merger said fcu oversight wasnt official didnt impact outcome votewhat more talbot shareholder asked randhawa fission board meeting contrary oversight press release similarly fuel cycle week editor andrea jennetta newsletter clear lot scene know adding likelihood fcu oversight success slim worth noting rumour circulating gifford leading fcu oversight aim gaining seat fission board support shareholder interest however gifford told investing new network design board director seat added thatfcu oversight bringingadequate director nominee theadvancenotice deadline saidthat alwaysknown highestquality board directornominee stand scrutiny retail institutional shareholder interesting whatmanifest overthe couple week end day thursday fission share price percent closeat yeartodate company percent uranium future outlook uranium price forecast onward analyst uranium price moving short long term read thefull article uranium new nexgen final radioactivity result uranium new nexgen energy tsxvnxe released radioactivity result final hole asummer drill programme rook returning offscale radioactivity what more hole arc shear intersected offscale radioactivity hole drilled date arrow exciting development shear hole metre summer drill programme awaiting assay theyare expected back coming month company focus rest compile data included maiden resource estimate due half nexgen preparing winter drill programme scheduled begin assay pending expect upcoming new flow add million pound uoresource estimate depositnexgen energy remain top pick cantor fitzgerald analyst rob chang research note estimate arrow million pound uoat average grade percentas close translate insitu valuation pound uranium new uranium price expected move higher finally uranium price week promising new thursday whencantor fitzgerald released quarterly commodity outlook firm see pricemoving higher utility cover current percent shortfall said firm lowered price forecast percent believe uptick occur violent increase price uranium occur month utility rush cover uranium forced operate reactor capacity state report moment utility refraining buying uranium premise ample supply expert guide uranium investing free download free special reporturanium future outlook uranium price forecast top uranium stock watch security disclosure kristen moran hold direct investment interest company mentioned article related reading uranium new china connect reactor uranium resource anatolia energy merger approval uranium new japan restart reactor denison fission terminate plan merge uranium new india criticised cigar lake start production latest uranium investing stock information latest information company uranium investing delivered directly inbox uraniumanfield resourcesenergy fuelsforum uraniumkivalliq energypeninsula energyplateau uraniumwestern uraniumselect select selecting company company above giving consent receive company remember unsubscribe time uranium future outlook uranium price forecast onward analyst uranium price moving short long term read thefull article return uranium investing index meta data kivalliq energy ceo jim top canadian uranium reso related post top uranium stock yeartodate nexgen announce appointment charle scorer special advisor uranium marketing uranium export legislation passed greenland denmark solid foundation set asx listed greenland mineral energy forum uranium wellpositioned athabasca highgrade uranium discovery nexgen energy announce assay result tag anatolia energy cantor fitzgerald china david talbot denison mine dundee capital market fcu fission uranium india investing new network nexgen energy price uranium rob chang uranium uranium price comment leave reply cancel reply required will published required comment market top resource storey uranium ready run view top tsx stock gold mining sto view silver mining canada view cobalt ready boom view lithium ontario view mesothermal vein gold deposit view top technology storey bitcoin price surge view datawind ceo talk mobile data view electric vehicle drive cleant view big bioprin view cybersecurity venture release view printing material driv view top life science storey top nasdaq biotech stock cell view invest life science view invest biotech view medx health corp announce ontar view marina biotech announce resignat view delmar pharmaceutical present view popular stock galaxy resource view nemaska lithium view danakali ltd view formation metal view dajin resource view brixton metal view tweet download free report resource investing resource forecast expert opinion covering precious metal energy critical metal gold trend gold outlook key highlight investor base metal opinion expert ceos lithium stock price analyst ceos graphite new graphite mining graphite stock buy lme copper copper etf understanding today copper price investing copper rare earth new rare earth metal price investing lithium stock post rockwood lithium potash stock potash new agriculture investing opportunity investing today critical metal context lynas new molycorp new silver highest price silver come potash type potash potash stock uranium price forecast top uranium stock watch invest platinum stock future hold lonmin amcu south african platinum production investing opportunity lme price base metal new investing tungsten tungsten price tungsten demand tungsten company glance zinc commodity new zinc market outlook coal price forecast type coal coal price coal stock forecasting oil price investing wisely top oil producing country palladium price forecast palladium investment opportunity investing medical cannabis information cannabis legal cannabis stock investing stornoway diamond canadian diamond mine diamond price calculator gold good investment gold price today future gold price prediction kitco mint sold out top article resource investing new gold trend gold outlook key highlight investor lithium stock price analyst ceos resource forecast expert opinion covering precious metal energy critical metal industrial metal oversupply market base metal opinion expert ceos energy investing outlook moving carbon agriculture investing opportunity forecast precious metal outlook ceos analyst gold silver platinum palladium critical metal outlook potential lme copper copper etf understanding today copper price investing copper kitco mint sold out top article resource investing new gold good investment gold price today future gold price prediction investing lithium stock post rockwood lithium free lithium investing newsletter free uranium investing newsletter life science investing life science investing primer finding opportunity medtronic ariad pharmaceutical pharmacyte investing pharmaceutical company pharmaceutical new top pharmaceutical stock buy biotech investing new top biotech company biotech stock life science investing ethic app revolution tech investing understanding bitcoin bitcoin mining bitcoin rate nanotechnology nanotech application nanotech investing investing graphene company graphene cost graphene property graphene market future printing company printing stock buy tech investing primer bitcoin rate printing company instagram stock cleantech investing clean technology investor technology investing trend outlook successful technology investing browse topic resource investing agriculture investing cannabis investing phosphate investing potash investing base metal investing copper investing iron investing lead investing nickel investing zinc investing critical metal investing cobalt investing graphite investing magnesium investing manganese investing rare earth investing scandium investing tantalum investing tellurium investing tungsten investing energy investing gas investing lithium investing oil gas investing oil investing uranium investing gem investing diamond investing industrial metal investing aluminium investing chromium investing coal investing molybdenum investing tin investing vanadium investing precious metal investing gold investing palladium investing platinum investing silver investing tech investing printing investing app investing cleantech investing cloud investing cybersecurity investing data investing fintech investing graphene investing mobile web investing nanotech investing life science investing biotech investing genetic investing longevity investing medical device investing pharmaceutical investing featured stock plateau uraniumemerging uranium district peru peninsula energy featured stock enter log credential remember lost password create password manage account contact privacy policy stock index keyword index browsetopic advertise free report event glossary press release copyright dig media inc investing new network daily new resource investing precious metal gold silver platinum palladium back base metal copper nickel iron lead zinc back critical metal graphite tungsten tantalum scandium cobalt magnesium manganese tellurium rare earth back industrial metal molybendum coal tin aluminium vanadium chromium back energy uranium oil gas oil gas lithium back gem diamond back agriculture potash phosphate cannabis back resource investing back technology investing printing cleantech cloud data back cybersecurity fintech graphene mobile web nanotech technology investing back life science investing biotech pharmaceutical medical device genetic life science investing back free investor report resource free report technology free report life science free report outlook free report back stock resource investing technology investing life science investing back","m_szGeo1":"Canada","m_szSourceType":"source_general","m_szSrcUrl":"http://investingnews.com/daily/resource-investing/energy-investing/uranium-investing/uranium-news-fission-proxy-fight-nexgen-cantor-fitzgerald-uranium-price-outlook/","m_Places":["Tin","Mobile","Outlook","Denison","Talbot","Best","Most","China","Japan","India","Meta","Greenland","Denmark","Well","Canada","Ontario","Delmar","United States","Rockwood","Outlooks","Uranium District","Peru","Enter"],"m_People":["Diamond Price","Jim","Kristen Moran","Diamond Mines","Dev Randhawa","Jim Gifford","Blair Lockhart","David Talbot","Andrea Jennetta","Rob Chang"],"m_Companies":["Daily News","Palladium","Cleantech","Fintech","Shareholder Group","Financial Post","Special Report","Dundee Capital Markets","Cycle","Seat","Anatolia","Top Technology","Datawind","Top Nasdaq","Medx Health Corp.","Danakali Ltd.","Lonmin","Tungsten Companies","Us Mint","Medtronic","Ariad Pharmaceuticals","Top Biotech Companies","Revolution","Graphene Companies","Printing Companies","Dig Media Inc."],"m_BiGrams":["life science","resource investing","science investing","free report","uranium price","uranium new","technology investing","uranium investing","price forecast","critical metal","precious metal","base metal","fcu oversight","investing new","rare earth","oil gas","investing life","industrial metal","nexgen energy","drill programme","press release","future outlook","outlook uranium","top uranium","uranium stock","lithium stock","price investing","gold price","metal investing","investing back","investing precious","metal gold","gold silver","silver platinum","platinum palladium","investing technology","investing printing","mobile web","investing biotech","medical device","investing free","report resource","investing uranium","cantor fitzgerald","fission uranium","fission board","download free","forecast top","stock watch","new network","view top","stock buy","investing copper","investing lithium","agriculture investing","investing opportunity","tech investing"],"m_TriGrams":["life science investing","uranium price forecast","future outlook uranium","outlook uranium price","top uranium stock","investing precious metal","gold silver platinum","silver platinum palladium","resource investing technology","science investing biotech","price forecast top","forecast top uranium","uranium stock watch","investing new network"],"m_SocialTags":[],"m_Topics":[],"m_Industry":[],"m_Technology":[],"m_BiCnt":[14,10,10,10,10,9,8,8,8,7,6,6,6,6,5,5,5,4,4,4,4,4,4,4,4,4,4,4,4,4,3,3,3,3,3,3,3,3,3,3,3,3,3,3,3,3,3,3,3,3,3,3,3,3,3,3,3],"m_TriCnt":[10,5,4,4,4,3,3,3,3,3,3,3,3,3],"m_iDocBodyWordCnt":1537}
