{"m_szDocID":"298691","m_szDocTitle":"Uranium News: China and France Strengthen Nuclear Partnership - Investing News Network","m_szYear":"2015","m_szDocSumamry":"UraniumInvesting News Your trusted source for investing success Uranium Member? Login Menu Daily News Resource Investing Precious Metals Gold Silver Platinum Palladium Base Metals Copper Nickel Iron Lead Zinc Critical Metals Graphite Tungsten Tantalum Scandium Cobalt Magnesium Manganese Tellurium Rare Earth Industrial Metals Molybendum Coal Tin Aluminum Vanadium Chromium Energy Uranium Oil Gas Oil and Gas Lithium Gem Diamond Agriculture Potash Phosphate Cannabis About Resource Investing Technology Investing 3D Printing Cleantech Cloud Data Cybersecurity Fintech Graphene Mobile Web Nanotech Abo","m_szDocBody":"uraniuminvesting new trusted source investing success uranium member menu daily new resource investing precious metal gold silver platinum palladium base metal copper nickel iron lead zinc critical metal graphite tungsten tantalum scandium cobalt magnesium manganese tellurium rare earth industrial metal molybendum coal tin aluminium vanadium chromium energy uranium oil gas oil gas lithium gem diamond agriculture potash phosphate cannabis resource investing technology investing printing cleantech cloud data cybersecurity fintech graphene mobile web nanotech technology investing life science investing biotech pharmaceutical medical device genetic life science investing free investor report resource free report technology free report life science free report outlook free report stock resource investing technology investing life science investing uranium investing uranium new china france strengthen nuclear partnership country signed industrial cooperation agreement nuclear waste recycling meanwhile potential partnership areva cnnc alter landscape uranium industry top canadian uranium reso salman partner uranium kristen moran add comment usual week filled exciting uranium new interest isthe potential partnership areva epaareva andchina national nuclear cnnc deal alter landscape uranium industry monday company signed memorandum understandingthat cnnc minority stake french nuclear power company deal doesnt includearevas reactor business sold edf epaedf announcement cnnc purchase unknown number areva share may reaction deal positive far recapitalization significant ramification arevas mining business positive spillover sector dundee capital market analyst david talbot research note increased funding escalate spending m&a activity enhanced security supply tension spur long term contracting minority interest result future uranium delivery largely redirected france china reduce supply rest world increase competition nuclear utility added expert guide uranium investing free download free special reporturanium future outlook uranium price forecast top uranium stock watch significant deal struck france china week country signed anindustrial cooperation agreement nuclear waste recycling french president francois hollande visit beijing monday deal worth billion talbot seesthe recycling agreement aspositive significant potential cnnc gaining stake areva addedto aforementioned concern industry tension security supply risk uranium new anfield sell interest wate project energy fuel anfield resourcestsxvaryotcqbanldf announced ithasclosed transaction subsidiary ofenergy fuelstsxefrnysemktuuuu sale percent interest wate breccia pipe millioncashandstock transaction energy fuel own control percentinterest wate project extremely pleased acquire anfield interest nearlypermitted wate project wate project wellknown highgrade breccia pipe deposit fit nicely existing uranium portfolio due highgrade deposit generally represent lowestcost source uranium production portfolio energy fuel president ceo stephen antony apress release uranium future outlook uranium price forecast onward analyst uranium price moving short long term read thefull article uranium newsberkeley update pfs berkeley energy asxbky announced updatedprefeasibility study pfs include highgrade zona deposit transformed economic itssalamanca projectthe project net million internal rate return percentbased discount rate percentand longterm uranium price pound potential exist discovery zona style deposit finalising exploration programme commence year follow number surface grade drill intersection located kilometre plant fully evaluated berkeley managing director paul atherley said definitive feasibility study shouldbe completed construction salamanca project expected start mid talbot opinion project good one salamanca mine built million cash suggest construction project financing required shortly remain schedule part salamancas appeal low capital intensity hesaid research note security disclosure kristen moran hold direct investment interest company mentioned article editorial disclosure anfield resource energy fuel client investing new network paidfor content related reading uranium new fission retail shareholder prepare proxy fight uranium new china connect reactor uranium resource anatolia energy merger approval uranium new japan restart reactor denison fission terminate plan merge latest uranium investing stock information latest information company uranium investing delivered directly inbox uraniumanfield resourcesenergy fuelsforum uraniumkivalliq energypeninsula energyplateau uraniumwestern uraniumselect select selecting company company above giving consent receive company remember unsubscribe time expert guide uranium investing free download free special reporturanium future outlook uranium price forecast top uranium stock watch return uranium investing index meta data top canadian uranium reso salman partner uranium related post top uranium stock yeartodate nexgen announce appointment charle scorer special advisor uranium marketing uranium export legislation passed greenland denmark solid foundation set asx listed greenland mineral energy forum uranium wellpositioned athabasca highgrade uranium discovery nexgen energy announce assay result tag anatolia energy anfield resource areva ary china cnnc david talbot dundee capital market efr energy fuel investing new network mining nuclear power nysemktuuuu prefeasibility prefeasibility study tsx tsxefr tsxv tsxvary uranium uranium industry uranium new uranium new japan uranium price waste comment leave reply cancel reply required will published required comment market top resource storey uranium ready run view top tsx stock gold mining sto view silver mining canada view cobalt ready boom view lithium ontario view mesothermal vein gold deposit view top technology storey bitcoin price surge view datawind ceo talk mobile data view electric vehicle drive cleant view big bioprin view cybersecurity venture release view printing material driv view top life science storey top nasdaq biotech stock cell view invest life science view invest biotech view medx health corp announce ontar view marina biotech announce resignat view delmar pharmaceutical present view popular stock galaxy resource view nemaska lithium view danakali ltd view formation metal view dajin resource view brixton metal view tweet download free report resource investing resource forecast expert opinion covering precious metal energy critical metal gold trend gold outlook key highlight investor base metal opinion expert ceos lithium stock price analyst ceos graphite new graphite mining graphite stock buy lme copper copper etf understanding today copper price investing copper rare earth new rare earth metal price investing lithium stock post rockwood lithium potash stock potash new agriculture investing opportunity investing today critical metal context lynas new molycorp new silver highest price silver come potash type potash potash stock uranium price forecast top uranium stock watch invest platinum stock future hold lonmin amcu south african platinum production investing opportunity lme price base metal new investing tungsten tungsten price tungsten demand tungsten company glance zinc commodity new zinc market outlook coal price forecast type coal coal price coal stock forecasting oil price investing wisely top oil producing country palladium price forecast palladium investment opportunity investing medical cannabis information cannabis legal cannabis stock investing stornoway diamond canadian diamond mine diamond price calculator gold good investment gold price today future gold price prediction kitco mint sold out top article resource investing new gold trend gold outlook key highlight investor lithium stock price analyst ceos resource forecast expert opinion covering precious metal energy critical metal industrial metal oversupply market base metal opinion expert ceos energy investing outlook moving carbon agriculture investing opportunity forecast precious metal outlook ceos analyst gold silver platinum palladium critical metal outlook potential lme copper copper etf understanding today copper price investing copper kitco mint sold out top article resource investing new gold good investment gold price today future gold price prediction investing lithium stock post rockwood lithium free lithium investing newsletter free uranium investing newsletter life science investing life science investing primer finding opportunity medtronic ariad pharmaceutical pharmacyte investing pharmaceutical company pharmaceutical new top pharmaceutical stock buy biotech investing new top biotech company biotech stock life science investing ethic app revolution tech investing understanding bitcoin bitcoin mining bitcoin rate nanotechnology nanotech application nanotech investing investing graphene company graphene cost graphene property graphene market future printing company printing stock buy tech investing primer bitcoin rate printing company instagram stock cleantech investing clean technology investor technology investing trend outlook successful technology investing browse topic resource investing agriculture investing cannabis investing phosphate investing potash investing base metal investing copper investing iron investing lead investing nickel investing zinc investing critical metal investing cobalt investing graphite investing magnesium investing manganese investing rare earth investing scandium investing tantalum investing tellurium investing tungsten investing energy investing gas investing lithium investing oil gas investing oil investing uranium investing gem investing diamond investing industrial metal investing aluminium investing chromium investing coal investing molybdenum investing tin investing vanadium investing precious metal investing gold investing palladium investing platinum investing silver investing tech investing printing investing app investing cleantech investing cloud investing cybersecurity investing data investing fintech investing graphene investing mobile web investing nanotech investing life science investing biotech investing genetic investing longevity investing medical device investing pharmaceutical investing featured stock plateau uraniumemerging uranium district peru peninsula energy featured stock enter log credential remember lost password create password manage account contact privacy policy stock index keyword index browsetopic advertise free report event glossary press release copyright dig media inc investing new network daily new resource investing precious metal gold silver platinum palladium back base metal copper nickel iron lead zinc back critical metal graphite tungsten tantalum scandium cobalt magnesium manganese tellurium rare earth back industrial metal molybendum coal tin aluminium vanadium chromium back energy uranium oil gas oil gas lithium back gem diamond back agriculture potash phosphate cannabis back resource investing back technology investing printing cleantech cloud data back cybersecurity fintech graphene mobile web nanotech technology investing back life science investing biotech pharmaceutical medical device genetic life science investing back free investor report resource free report technology free report life science free report outlook free report back stock resource investing technology investing life science investing back","m_szGeo1":"Canada","m_szSourceType":"source_general","m_szSrcUrl":"http://investingnews.com/daily/resource-investing/energy-investing/uranium-investing/uranium-news-china-and-france-strengthen-nuclear-partnership/","m_Places":["Tin","Mobile","Outlook","China","France","Beijing","Talbot","Ary","Salamanca","United States","Japan","Denison","Meta","Greenland","Denmark","Well","Canada","Ontario","Delmar","Most","Best","Rockwood","Outlooks","Uranium District","Peru","Enter"],"m_People":["Kristen Moran","David Talbot","Diamond Price","Francois Hollande","Stephen Antony","Paul Atherley","Diamond Mines"],"m_Companies":["Daily News","Palladium","Energy","Cleantech","Fintech","Areva","Salman Partners","Epa","Dundee Capital Markets","Special Report","Shareholder Group","Anatolia","Top Technology","Datawind","Top Nasdaq","Medx Health Corp.","Danakali Ltd.","Lonmin","Tungsten Companies","Us Mint","Medtronic","Ariad Pharmaceuticals","Top Biotech Companies","Revolution","Graphene Companies","Printing Companies","Dig Media Inc."],"m_BiGrams":["life science","resource investing","science investing","free report","technology investing","uranium investing","uranium new","critical metal","uranium price","precious metal","base metal","price forecast","investing new","rare earth","oil gas","investing life","energy fuel","industrial metal","top uranium","uranium stock","wate project","lithium stock","price investing","gold price","metal investing","investing back","investing precious","metal gold","gold silver","silver platinum","platinum palladium","investing technology","investing printing","mobile web","investing biotech","medical device","investing free","report resource","investing uranium","download free","future outlook","outlook uranium","forecast top","stock watch","new network","view top","stock buy","investing copper","investing lithium","agriculture investing","investing opportunity","tech investing"],"m_TriGrams":["life science investing","uranium price forecast","top uranium stock","investing precious metal","gold silver platinum","silver platinum palladium","resource investing technology","science investing biotech","future outlook uranium","outlook uranium price","price forecast top","forecast top uranium","uranium stock watch","investing new network"],"m_SocialTags":[],"m_Topics":[],"m_Industry":[],"m_Technology":[],"m_BiCnt":[14,10,10,10,8,8,8,7,7,6,6,6,6,5,5,5,5,4,4,4,4,4,4,4,4,4,3,3,3,3,3,3,3,3,3,3,3,3,3,3,3,3,3,3,3,3,3,3,3,3,3,3],"m_TriCnt":[10,4,4,3,3,3,3,3,3,3,3,3,3,3],"m_iDocBodyWordCnt":1473}
