{"m_szDocID":"298658","m_szDocTitle":"David Sadowski News - Investing News Network","m_szYear":"2016","m_szDocSumamry":"Your trusted source for investing success Member? Login Menu Daily News Resource Investing Precious Metals Gold Silver Platinum Palladium Base Metals Copper Nickel Iron Lead Zinc Critical Metals Graphite Tungsten Tantalum Scandium Cobalt Magnesium Manganese Tellurium Rare Earth Industrial Metals Molybendum Coal Tin Aluminum Vanadium Chromium Energy Uranium Oil Gas Oil and Gas Lithium Gem Diamond Agriculture Potash Phosphate Cannabis About Resource Investing Technology Investing 3D Printing Cleantech Cloud Data Cybersecurity Fintech Graphene Mobile Web Nanotech About Technology Investing Life S","m_szDocBody":"trusted source investing success member menu daily new resource investing precious metal gold silver platinum palladium base metal copper nickel iron lead zinc critical metal graphite tungsten tantalum scandium cobalt magnesium manganese tellurium rare earth industrial metal molybendum coal tin aluminium vanadium chromium energy uranium oil gas oil gas lithium gem diamond agriculture potash phosphate cannabis resource investing technology investing printing cleantech cloud data cybersecurity fintech graphene mobile web nanotech technology investing life science investing biotech pharmaceutical medical device genetic life science investing free investor report resource free report technology free report life science free report outlook free report stock resource investing technology investing life science investing tag david sadowski guide gold concise clear authoritative download free special report gold good investment gold price today future gold price prediction orezone gold environmental approval bombor investing new network orezone gold hit major milestone bombor project burkina faso week receipt final environmental approval project nexgen energy make game changing discovery teresa matich nexgen energy announced discovered potential zone highgrade uranium mineralization rook property saskatchewan athabasca basin denison mine release strong maiden pea wheeler river teresa matich highlight maiden pea denison percentowned wheeler river project include pretax net million internal rate return percent price pound top tsxv stock nexgen energy rise percent arrow new teresa matich nexgen energy topgaining stock mining sector week mitra energy focus graphite lupaka gold largo resource nexgen energy arrow world largest undeveloped highgrade uranium deposit vivien diniz nexgen maiden resource arrow show inferred resource million pound contained uranium million tonne mineralization grading percent nex big thing nexgen energy assay result point worldclass resource vivien diniz nexgen energy released remaining assay result highly successful summer drill programme rook top uranium article vivien diniz investing new network back year topperforming uranium article energy defying weak uranium market northern miner teresa matich urenergy tsxurenyse mkturg recently featured northern miner subscription noted company recently recorded net profit quarter weak uranium price raymond jame analyst david sadowski noted urenergy lost creek project lowestcost uranium producer quebec plan nord exclude uranium mining strateco resource continue lawsuit kristen moran quebec government moving forward revised plan nord project uranium mining left equation head strateco resource weigh uranium price flat market watches japan china investing new network uranium price remained unchanged pound week orezone gold bombore project feature scalable optionality lowcost production charlotte mcleod raymond jame analyst david sadowski believe orezone attractive stock think company takeover target moving forward good new japan move uranium stock investing new network positive new japan week helped offset negative sentiment uranium market recent setback takahama reactor here company positive share price reaction japanese court block reactor restart safety concern investing new network uranium market dealt heavy hit week japanese court issued injunction block restart reactor reactor restart key psychological catalyst uranium market new expected negative impact space uranium price holding ground market move investing new network uranium spot price percent rise holding steady pound sound disheartening raymond jame analyst david sadowski pointed recent note spot market healthy activity march analyst expect big move uranium price investing new network accident week world biggest uranium mine analyst expecting uranium spot price climb pound range week sitting unchanged week pound david sadowski bullish future uranium investing new network pretty attractive supply demand storey sadowski ame mineral exploration roundup added based expect uranium price move pound year order support badly needed project robust economic urenergy shirley basin pea vivien diniz week wyomingbased insitu uranium producer urenergy released preliminary economic assessment wholly owned shirley basin insitu leach operation whole betterthanexpected result consolidation uranium market future investing new network uranium investing new take possibility consolidation trend uranium space breaking uranerz energy fuel merger investing new network energy fuel uranerz energy announced theyll merging move drawn muted praise analyst tsx top uranium company lead investing new network tsxlisted uranium company mega uranium azaraga uranium pushed week uranium positive price action ivanhoe mine lithium americas made top five project generator join webinar discussion moderated rick rule president ceo sprott holding featuring eurasian mineral emxv lara exploration lrav transition metal xtmv space limited now market top resource storey uranium ready run view top tsx stock gold mining sto view silver mining canada view cobalt ready boom view lithium ontario view mesothermal vein gold deposit view top technology storey bitcoin price surge view datawind ceo talk mobile data view electric vehicle drive cleant view big bioprin view cybersecurity venture release view printing material driv view top life science storey top nasdaq biotech stock cell view invest life science view invest biotech view medx health corp announce ontar view marina biotech announce resignat view delmar pharmaceutical present view popular stock galaxy resource view nemaska lithium view danakali ltd view formation metal view dajin resource view brixton metal view download free report resource investing resource forecast expert opinion covering precious metal energy critical metal gold trend gold outlook key highlight investor base metal opinion expert ceos lithium stock price analyst ceos graphite new graphite mining graphite stock buy lme copper copper etf understanding today copper price investing copper rare earth new rare earth metal price investing lithium stock post rockwood lithium potash stock potash new agriculture investing opportunity investing today critical metal context lynas new molycorp new silver highest price silver come potash type potash potash stock uranium price forecast top uranium stock watch invest platinum stock future hold lonmin amcu south african platinum production investing opportunity lme price base metal new investing tungsten tungsten price tungsten demand tungsten company glance zinc commodity new zinc market outlook coal price forecast type coal coal price coal stock forecasting oil price investing wisely top oil producing country palladium price forecast palladium investment opportunity investing medical cannabis information cannabis legal cannabis stock investing stornoway diamond canadian diamond mine diamond price calculator gold good investment gold price today future gold price prediction kitco mint sold out top article resource investing new gold trend gold outlook key highlight investor lithium stock price analyst ceos resource forecast expert opinion covering precious metal energy critical metal industrial metal oversupply market base metal opinion expert ceos energy investing outlook moving carbon agriculture investing opportunity forecast precious metal outlook ceos analyst gold silver platinum palladium critical metal outlook potential lme copper copper etf understanding today copper price investing copper kitco mint sold out top article resource investing new gold good investment gold price today future gold price prediction investing lithium stock post rockwood lithium free lithium investing newsletter free uranium investing newsletter life science investing life science investing primer finding opportunity medtronic ariad pharmaceutical pharmacyte investing pharmaceutical company pharmaceutical new top pharmaceutical stock buy biotech investing new top biotech company biotech stock life science investing ethic app revolution tech investing understanding bitcoin bitcoin mining bitcoin rate nanotechnology nanotech application nanotech investing investing graphene company graphene cost graphene property graphene market future printing company printing stock buy tech investing primer bitcoin rate printing company instagram stock cleantech investing clean technology investor technology investing trend outlook successful technology investing browse topic resource investing agriculture investing cannabis investing phosphate investing potash investing base metal investing copper investing iron investing lead investing nickel investing zinc investing critical metal investing cobalt investing graphite investing magnesium investing manganese investing rare earth investing scandium investing tantalum investing tellurium investing tungsten investing energy investing gas investing lithium investing oil gas investing oil investing uranium investing gem investing diamond investing industrial metal investing aluminium investing chromium investing coal investing molybdenum investing tin investing vanadium investing precious metal investing gold investing palladium investing platinum investing silver investing tech investing printing investing app investing cleantech investing cloud investing cybersecurity investing data investing fintech investing graphene investing mobile web investing nanotech investing life science investing biotech investing genetic investing longevity investing medical device investing pharmaceutical investing featured stock mettrum health leader canadas growing cannabis market komet resource american manganese stria lithium houston lake mining featured stock enter log credential remember lost password create password manage account contact privacy policy stock index keyword index browsetopic advertise free report event glossary press release copyright dig media inc investing new network daily new resource investing precious metal gold silver platinum palladium back base metal copper nickel iron lead zinc back critical metal graphite tungsten tantalum scandium cobalt magnesium manganese tellurium rare earth back industrial metal molybendum coal tin aluminium vanadium chromium back energy uranium oil gas oil gas lithium back gem diamond back agriculture potash phosphate cannabis back resource investing back technology investing printing cleantech cloud data back cybersecurity fintech graphene mobile web nanotech technology investing back life science investing biotech pharmaceutical medical device genetic life science investing back free investor report resource free report technology free report life science free report outlook free report back stock resource investing technology investing life science investing back","m_szGeo1":"Canada","m_szSourceType":"source_general","m_szSrcUrl":"http://investingnews.com/tag/david-sadowski/","m_Places":["Tin","Mobile","Outlook","Burkina Faso","Saskatchewan","Denison","Wheeler","United States","Largo","Ur","Quebec","Japan","China","Takahama","Wyoming","Americas","Canada","Ontario","Delmar","Most","Best","Rockwood","Outlooks","Enter"],"m_People":["David Sadowski","Diamond Price","Teresa Matich","Diamond Mines","Lupaka Gold","Vivien Diniz","Kristen Moran","Charlotte Mcleod","Houston Lake"],"m_Companies":["Daily News","Palladium","Cleantech","Fintech","Special Report","Orezone Gold","Wheeler River Project","Raymond James","Quebec Government","Orezone","Target","Uranium Companies","U.s. Sprott Holdings Inc","Space Is Limited","Top Technology","Datawind","Top Nasdaq","Medx Health Corp.","Danakali Ltd.","Lonmin","Tungsten Companies","Us Mint","Medtronic","Ariad Pharmaceuticals","Top Biotech Companies","Revolution","Graphene Companies","Printing Companies","Dig Media Inc."],"m_BiGrams":["investing new","life science","new network","resource investing","science investing","free report","technology investing","critical metal","nexgen energy","uranium price","precious metal","base metal","gold price","rare earth","oil gas","investing life","david sadowski","uranium market","price investing","industrial metal","teresa matich","vivien diniz","network uranium","uranium investing","lithium stock","metal investing","investing back","investing precious","metal gold","gold silver","silver platinum","platinum palladium","investing technology","investing printing","mobile web","investing biotech","medical device","report resource","gold good","good investment","investment gold","price today","today future","future gold","price prediction","orezone gold","top uranium","raymond jame","jame analyst","analyst david","view top","stock buy","investing copper","investing lithium","agriculture investing","investing opportunity","price forecast","tech investing"],"m_TriGrams":["investing new network","life science investing","new network uranium","investing precious metal","gold silver platinum","silver platinum palladium","resource investing technology","science investing biotech","gold good investment","good investment gold","investment gold price","gold price today","price today future","today future gold","future gold price","gold price prediction","raymond jame analyst","jame analyst david","analyst david sadowski"],"m_SocialTags":[],"m_Topics":[],"m_Industry":[],"m_Technology":[],"m_BiCnt":[16,14,12,10,10,10,8,7,7,7,6,6,6,5,5,5,5,5,5,4,4,4,4,4,4,4,4,3,3,3,3,3,3,3,3,3,3,3,3,3,3,3,3,3,3,3,3,3,3,3,3,3,3,3,3,3,3,3],"m_TriCnt":[12,10,4,3,3,3,3,3,3,3,3,3,3,3,3,3,3,3,3],"m_iDocBodyWordCnt":1447}
