{"m_szDocID":"298626","m_szDocTitle":"NYSE:CCJ News - Investing News Network","m_szYear":"2016","m_szDocSumamry":"Your trusted source for investing success Member? Login Menu Daily News Resource Investing Precious Metals Gold Silver Platinum Palladium Base Metals Copper Nickel Iron Lead Zinc Critical Metals Graphite Tungsten Tantalum Scandium Cobalt Magnesium Manganese Tellurium Rare Earth Industrial Metals Molybendum Coal Tin Aluminum Vanadium Chromium Energy Uranium Oil Gas Oil and Gas Lithium Gem Diamond Agriculture Potash Phosphate Cannabis About Resource Investing Technology Investing 3D Printing Cleantech Cloud Data Cybersecurity Fintech Graphene Mobile Web Nanotech About Technology Investing Life S","m_szDocBody":"trusted source investing success member menu daily new resource investing precious metal gold silver platinum palladium base metal copper nickel iron lead zinc critical metal graphite tungsten tantalum scandium cobalt magnesium manganese tellurium rare earth industrial metal molybendum coal tin aluminium vanadium chromium energy uranium oil gas oil gas lithium gem diamond agriculture potash phosphate cannabis resource investing technology investing printing cleantech cloud data cybersecurity fintech graphene mobile web nanotech technology investing life science investing biotech pharmaceutical medical device genetic life science investing free investor report resource free report technology free report life science free report outlook free report stock resource investing technology investing life science investing tag nyseccj expert guide uranium investing free download free special reporturanium future outlook uranium price forecast top uranium stock watch nexgen energy make game changing discovery teresa matich nexgen energy announced discovered potential zone highgrade uranium mineralization rook property saskatchewan athabasca basin forum uranium rio tinto highlight promise athabasca basin vivien diniz forum uranium announced joint venture partner rio tinto spending time money henday project northern saskatchewan cameco approve dividend vivien diniz cameco tsxcco nyseccj announced board director approved quarterly cash dividend common share uranium new india criticised cigar lake start production kristen moran india faced criticism week cameco began production cigar lake mine latest drill result fission uranium nexgen energy cameco areva start production cigar lake kristen moran cameco corp tsxcconyseccj areva announced cigar lake uranium mine mcclean lake mill officially began production uranium price finally make upward move vivien diniz price managed claw time late spring top uranium mine world investing new network top uraniumproducing mine world uranium industry crisis silver lining uranium stock melissa pistilli improving stock price face depressed uranium price bullish signal savvy investor unionised employee camecos port hope conversion facility vote favour collective agreement investing new network cameco tsxcconyseccj announced unionised employee port hope conversion facility voted support collective agreement camecos profit slump percent investing new network mining weekly reported saskatchewanbased miner cameco corp tsxcconyseccj suffered percent drop firstquarter profit rising operational cost falling sale price pdac speaker long investing new network annual mining conference opened expert predicting mixed nearterm outlook resource stating underlying trend fuel demand long run uranium outlook rebound horizon melissa pistilli industry analyst early sign crucial turnaround uranium spot price uranium mining share market head supply deficit upside deferred uranium production melissa pistilli increasing likelihood future nuclear fuel shortage present upside uranium exploration development company quality project prime location paragon uranium demand expected increase investing new network paragonreportcom announced finding uranium demand expected pick emerging market junior miner rising wyoming uranium renaissance melissa pistilli wyoming midst uranium mining renaissance time government federal local level backing domestic energy production uranium industry rising star gaining strong foothold cowboy state cameco stock downgraded hold investing new network globe mail reported uranium price continue flounder pushing security downgrade cameco tsxcconyseccj hold buy nuclear power critical role world energy mix boost uranium demand melissa pistilli government big money understand nuclear power crucial part solution rising world energy demand analyst forecasting uranium market turnaround horizon cameco buy western australia uranium mine investing new network cameco tsxcconyseccj announced purchased yeelirrie uranium project western australia million bhp billiton nysebhp delay olympic dam kintyre signal coming uranium supply deficit melissa pistilli bhp billiton cameco recently announced delay largescale uranium project uranium market higher price supply deficit result morgan cameco uranium overweight status investing new network globe mail reported share cameco tsxcconyseccj uranium tsxuuu increased sharply morgan announced giving company overwieght rating uranium future outlook uranium price forecast onward analyst uranium price moving short long term read thefull article market top resource storey uranium ready run view top tsx stock gold mining sto view silver mining canada view cobalt ready boom view lithium ontario view mesothermal vein gold deposit view top technology storey bitcoin price surge view datawind ceo talk mobile data view electric vehicle drive cleant view big bioprin view cybersecurity venture release view printing material driv view top life science storey top nasdaq biotech stock cell view invest life science view invest biotech view medx health corp announce ontar view marina biotech announce resignat view delmar pharmaceutical present view popular stock galaxy resource view nemaska lithium view danakali ltd view formation metal view dajin resource view brixton metal view download free report resource investing resource forecast expert opinion covering precious metal energy critical metal gold trend gold outlook key highlight investor base metal opinion expert ceos lithium stock price analyst ceos graphite new graphite mining graphite stock buy lme copper copper etf understanding today copper price investing copper rare earth new rare earth metal price investing lithium stock post rockwood lithium potash stock potash new agriculture investing opportunity investing today critical metal context lynas new molycorp new silver highest price silver come potash type potash potash stock uranium price forecast top uranium stock watch invest platinum stock future hold lonmin amcu south african platinum production investing opportunity lme price base metal new investing tungsten tungsten price tungsten demand tungsten company glance zinc commodity new zinc market outlook coal price forecast type coal coal price coal stock forecasting oil price investing wisely top oil producing country palladium price forecast palladium investment opportunity investing medical cannabis information cannabis legal cannabis stock investing stornoway diamond canadian diamond mine diamond price calculator gold good investment gold price today future gold price prediction kitco mint sold out top article resource investing new gold trend gold outlook key highlight investor lithium stock price analyst ceos resource forecast expert opinion covering precious metal energy critical metal industrial metal oversupply market base metal opinion expert ceos energy investing outlook moving carbon agriculture investing opportunity forecast precious metal outlook ceos analyst gold silver platinum palladium critical metal outlook potential lme copper copper etf understanding today copper price investing copper kitco mint sold out top article resource investing new gold good investment gold price today future gold price prediction investing lithium stock post rockwood lithium free lithium investing newsletter free uranium investing newsletter life science investing life science investing primer finding opportunity medtronic ariad pharmaceutical pharmacyte investing pharmaceutical company pharmaceutical new top pharmaceutical stock buy biotech investing new top biotech company biotech stock life science investing ethic app revolution tech investing understanding bitcoin bitcoin mining bitcoin rate nanotechnology nanotech application nanotech investing investing graphene company graphene cost graphene property graphene market future printing company printing stock buy tech investing primer bitcoin rate printing company instagram stock cleantech investing clean technology investor technology investing trend outlook successful technology investing browse topic resource investing agriculture investing cannabis investing phosphate investing potash investing base metal investing copper investing iron investing lead investing nickel investing zinc investing critical metal investing cobalt investing graphite investing magnesium investing manganese investing rare earth investing scandium investing tantalum investing tellurium investing tungsten investing energy investing gas investing lithium investing oil gas investing oil investing uranium investing gem investing diamond investing industrial metal investing aluminium investing chromium investing coal investing molybdenum investing tin investing vanadium investing precious metal investing gold investing palladium investing platinum investing silver investing tech investing printing investing app investing cleantech investing cloud investing cybersecurity investing data investing fintech investing graphene investing mobile web investing nanotech investing life science investing biotech investing genetic investing longevity investing medical device investing pharmaceutical investing featured stock mettrum health leader canadas growing cannabis market komet resource american manganese stria lithium houston lake mining featured stock enter log credential remember lost password create password manage account contact privacy policy stock index keyword index browsetopic advertise free report event glossary press release copyright dig media inc investing new network daily new resource investing precious metal gold silver platinum palladium back base metal copper nickel iron lead zinc back critical metal graphite tungsten tantalum scandium cobalt magnesium manganese tellurium rare earth back industrial metal molybendum coal tin aluminium vanadium chromium back energy uranium oil gas oil gas lithium back gem diamond back agriculture potash phosphate cannabis back resource investing back technology investing printing cleantech cloud data back cybersecurity fintech graphene mobile web nanotech technology investing back life science investing biotech pharmaceutical medical device genetic life science investing back free investor report resource free report technology free report life science free report outlook free report back stock resource investing technology investing life science investing back","m_szGeo1":"Canada","m_szSourceType":"source_general","m_szSrcUrl":"http://investingnews.com/tag/nyse-ccj/","m_Places":["Tin","Mobile","Outlook","Saskatchewan","Northern Saskatchewan","India","Take","Wyoming","Western Australia","Dam","Canada","Ontario","Delmar","Most","United States","Best","Rockwood","Outlooks","Enter"],"m_People":["Diamond Price","Teresa Matich","Vivien Diniz","Houston Lake","Kristen Moran","Diamond Mines","Melissa Pistilli"],"m_Companies":["Daily News","Palladium","Cleantech","Fintech","Special Report","Rio Tinto","Areva","Cameco Corp","Mcclean Lake Mill","Signal","Rebound","Renaissance","Globe And Mail","Td Securities","Bhp Billiton","Kintyre Signal","Jp Morgan","Top Technology","Datawind","Top Nasdaq","Medx Health Corp.","Danakali Ltd.","Lonmin","Tungsten Companies","Us Mint","Medtronic","Ariad Pharmaceuticals","Top Biotech Companies","Revolution","Graphene Companies","Printing Companies","Dig Media Inc."],"m_BiGrams":["life science","investing new","resource investing","science investing","free report","new network","technology investing","critical metal","uranium price","precious metal","base metal","melissa pistilli","rare earth","oil gas","investing life","price forecast","industrial metal","cigar lake","cameco tsxcconyseccj","lithium stock","price investing","gold price","metal investing","investing back","investing precious","metal gold","gold silver","silver platinum","platinum palladium","investing technology","investing printing","mobile web","investing biotech","medical device","report resource","uranium investing","top uranium","uranium stock","nexgen energy","vivien diniz","uranium mine","stock price","supply deficit","uranium demand","view top","stock buy","investing copper","investing lithium","agriculture investing","investing opportunity","tech investing"],"m_TriGrams":["life science investing","investing new network","investing precious metal","gold silver platinum","silver platinum palladium","resource investing technology","science investing biotech","uranium price forecast"],"m_SocialTags":[],"m_Topics":[],"m_Industry":[],"m_Technology":[],"m_BiCnt":[14,12,10,10,10,9,8,7,7,6,6,6,5,5,5,5,4,4,4,4,4,4,4,4,3,3,3,3,3,3,3,3,3,3,3,3,3,3,3,3,3,3,3,3,3,3,3,3,3,3,3],"m_TriCnt":[10,9,3,3,3,3,3,3],"m_iDocBodyWordCnt":1369}
