{"m_szDocID":"298644","m_szDocTitle":"denison mines News - Investing News Network","m_szYear":"2016","m_szDocSumamry":"Your trusted source for investing success Member? Login Menu Daily News Resource Investing Precious Metals Gold Silver Platinum Palladium Base Metals Copper Nickel Iron Lead Zinc Critical Metals Graphite Tungsten Tantalum Scandium Cobalt Magnesium Manganese Tellurium Rare Earth Industrial Metals Molybendum Coal Tin Aluminum Vanadium Chromium Energy Uranium Oil Gas Oil and Gas Lithium Gem Diamond Agriculture Potash Phosphate Cannabis About Resource Investing Technology Investing 3D Printing Cleantech Cloud Data Cybersecurity Fintech Graphene Mobile Web Nanotech About Technology Investing Life S","m_szDocBody":"trusted source investing success member menu daily new resource investing precious metal gold silver platinum palladium base metal copper nickel iron lead zinc critical metal graphite tungsten tantalum scandium cobalt magnesium manganese tellurium rare earth industrial metal molybendum coal tin aluminium vanadium chromium energy uranium oil gas oil gas lithium gem diamond agriculture potash phosphate cannabis resource investing technology investing printing cleantech cloud data cybersecurity fintech graphene mobile web nanotech technology investing life science investing biotech pharmaceutical medical device genetic life science investing free investor report resource free report technology free report life science free report outlook free report stock resource investing technology investing life science investing tag denison mine expert guide uranium investing free download free special reporturanium future outlook uranium price forecast top uranium stock watch top holding global uranium etf vivien diniz company make top globe uranium etf invest uranium vivien diniz investor invest uranium stock etf uranium future denison goviex combine african uranium asset investing new network toronto ontariomarketwired denison mine corp tsxdmlnyse mktdnn denison pleased announce execution definitive share purchase agreement the agreement goviex uranium inc csegxu goviex combine respective african uranium mineral interest the transaction create leading africanfocused uranium development denison mine intersect additional highgrade mineralization gryphon vivien diniz denison mine intersected highgrade uranium mineralization gryphon zone percentowned wheeler river property denison announce execution year management service agreement uranium participation corporation vivien diniz denison mine corptsxdml nyse mktdnn announced wholly owned subsidiary denison mine inc entered year agreement provide management service uranium participation corporation tsxu msa effect conclusion current msa upc athabasca basin uranium company outline plan vivien diniz athabasca basin uranium company cameco denison mine nexgen energy laid plan year china india nuclear power expansion vivien diniz uranium price performing poorly nuclear power continue attract interest china india canalaska option uranium property denison mine vivien diniz canalaska uranium ltd tsxvcvvotcqbcvvuffwbdhn announced denison mine corp tsxdmlnysemktdnn optioned part moon uranium project saskatchewan top tsx stock orocobre percent charlotte mcleod company released statement unaware caused spike share price denison report quarter financial operational result kristen moran denison mine tsxdmlnysemktdnn announced quarter financial operational result including result month ended uranium new fission retail shareholder prepare proxy fight kristen moran uranium new cantor fitzgerald positive uranium price nexgen energy hit radioactivity final hole summer drill programme denison mine complete summer exploration wheeler river teresa matich denison mine tsxdml reported completion summer exploration wheeler river property saskatchewan athabasca basin company expect complete resource estimate wheeler river end denison fission terminate arrangement merge kristen moran denison mine tsxdml fission uranium tsxfcu announced terminated previously announced arrangement combine businesse independent advisory firm recommend denison shareholder vote favour merger kristen moran denison mine tsxdml announced independent proxy advisory firm institutional shareholder service inc glass lewis llc recommended shareholder denison fission uranium tsxfcu vote favour planned business combination special meeting drill tracker weekly fission drill metre grading percent wayne hewgill fission uranium announced initial assay result summer drilling patterson lake south project saskatchewan athabasca basin denion mine report quarter result kristen moran denison mine corp tsxdmlnysemktdnn announced result month period ended showed net loss million share denison mine sell noncore asset mongolia ahead merger kristen moran denison mine plan sell interest gurvan saihan joint venture mongolia uranium industry czech company denison complete definitive drilling gryphon identify mineralization murphy lake kristen moran denison mine corp tsxdmlnysemktdnn announced completion definitive drilling summer exploration programme gryphon zone wheeler river property company reported discover uranium mineralization murphy lake property denison fission definitive arrangement agreement merger kristen moran denison mine corp tsxdmlnysemktdnn fission uranium corp tsxfcu announced entered definitive arrangement agreement replace previously announced binding letter agreement arrangement company combine courtapproved plan quebec plan nord exclude uranium mining strateco resource continue lawsuit kristen moran quebec government moving forward revised plan nord project uranium mining left equation head strateco resource weigh uranium future outlook uranium price forecast onward analyst uranium price moving short long term read thefull article market top resource storey uranium ready run view top tsx stock gold mining sto view silver mining canada view cobalt ready boom view lithium ontario view mesothermal vein gold deposit view top technology storey bitcoin price surge view datawind ceo talk mobile data view electric vehicle drive cleant view big bioprin view cybersecurity venture release view printing material driv view top life science storey top nasdaq biotech stock cell view invest life science view invest biotech view medx health corp announce ontar view marina biotech announce resignat view delmar pharmaceutical present view popular stock galaxy resource view nemaska lithium view danakali ltd view formation metal view dajin resource view brixton metal view download free report resource investing resource forecast expert opinion covering precious metal energy critical metal gold trend gold outlook key highlight investor base metal opinion expert ceos lithium stock price analyst ceos graphite new graphite mining graphite stock buy lme copper copper etf understanding today copper price investing copper rare earth new rare earth metal price investing lithium stock post rockwood lithium potash stock potash new agriculture investing opportunity investing today critical metal context lynas new molycorp new silver highest price silver come potash type potash potash stock uranium price forecast top uranium stock watch invest platinum stock future hold lonmin amcu south african platinum production investing opportunity lme price base metal new investing tungsten tungsten price tungsten demand tungsten company glance zinc commodity new zinc market outlook coal price forecast type coal coal price coal stock forecasting oil price investing wisely top oil producing country palladium price forecast palladium investment opportunity investing medical cannabis information cannabis legal cannabis stock investing stornoway diamond canadian diamond mine diamond price calculator gold good investment gold price today future gold price prediction kitco mint sold out top article resource investing new gold trend gold outlook key highlight investor lithium stock price analyst ceos resource forecast expert opinion covering precious metal energy critical metal industrial metal oversupply market base metal opinion expert ceos energy investing outlook moving carbon agriculture investing opportunity forecast precious metal outlook ceos analyst gold silver platinum palladium critical metal outlook potential lme copper copper etf understanding today copper price investing copper kitco mint sold out top article resource investing new gold good investment gold price today future gold price prediction investing lithium stock post rockwood lithium free lithium investing newsletter free uranium investing newsletter life science investing life science investing primer finding opportunity medtronic ariad pharmaceutical pharmacyte investing pharmaceutical company pharmaceutical new top pharmaceutical stock buy biotech investing new top biotech company biotech stock life science investing ethic app revolution tech investing understanding bitcoin bitcoin mining bitcoin rate nanotechnology nanotech application nanotech investing investing graphene company graphene cost graphene property graphene market future printing company printing stock buy tech investing primer bitcoin rate printing company instagram stock cleantech investing clean technology investor technology investing trend outlook successful technology investing browse topic resource investing agriculture investing cannabis investing phosphate investing potash investing base metal investing copper investing iron investing lead investing nickel investing zinc investing critical metal investing cobalt investing graphite investing magnesium investing manganese investing rare earth investing scandium investing tantalum investing tellurium investing tungsten investing energy investing gas investing lithium investing oil gas investing oil investing uranium investing gem investing diamond investing industrial metal investing aluminium investing chromium investing coal investing molybdenum investing tin investing vanadium investing precious metal investing gold investing palladium investing platinum investing silver investing tech investing printing investing app investing cleantech investing cloud investing cybersecurity investing data investing fintech investing graphene investing mobile web investing nanotech investing life science investing biotech investing genetic investing longevity investing medical device investing pharmaceutical investing featured stock mettrum health leader canadas growing cannabis market komet resource american manganese stria lithium houston lake mining featured stock enter log credential remember lost password create password manage account contact privacy policy stock index keyword index browsetopic advertise free report event glossary press release copyright dig media inc investing new network daily new resource investing precious metal gold silver platinum palladium back base metal copper nickel iron lead zinc back critical metal graphite tungsten tantalum scandium cobalt magnesium manganese tellurium rare earth back industrial metal molybendum coal tin aluminium vanadium chromium back energy uranium oil gas oil gas lithium back gem diamond back agriculture potash phosphate cannabis back resource investing back technology investing printing cleantech cloud data back cybersecurity fintech graphene mobile web nanotech technology investing back life science investing biotech pharmaceutical medical device genetic life science investing back free investor report resource free report technology free report life science free report outlook free report back stock resource investing technology investing life science investing back","m_szGeo1":"Canada","m_szSourceType":"source_general","m_szSrcUrl":"http://investingnews.com/tag/denison-mines/","m_Places":["Tin","Mobile","Outlook","Denison","Toronto, Ontario","“denison”","Wheeler","China","India","Saskatchewan","Mongolia","Czech","Quebec","Canada","Ontario","Delmar","Most","United States","Best","Rockwood","Outlooks","Enter"],"m_People":["Diamond Mines","Diamond Price","Vivien Diniz","Charlotte Mcleod","Kristen Moran","Teresa Matich","Wayne Hewgill","Houston Lake"],"m_Companies":["Daily News","Palladium","Cleantech","Fintech","Special Report","Marketwired","Denison Mines Corp.","Goviex Uranium Inc.","Participation Corporation","Denison Mines Inc.","Upc","Uranium Companies","Canalaska Uranium Ltd.","Shareholder Group","Institutional Shareholder Services Inc.","Patterson","Denison Mines Corp","Fission Uranium Corp.","Quebec Government","Top Technology","Datawind","Top Nasdaq","Medx Health Corp.","Danakali Ltd.","Lonmin","Tungsten Companies","Us Mint","Medtronic","Ariad Pharmaceuticals","Top Biotech Companies","Revolution","Graphene Companies","Printing Companies","Dig Media Inc."],"m_BiGrams":["denison mine","life science","resource investing","science investing","free report","kristen moran","technology investing","critical metal","vivien diniz","moran denison","precious metal","base metal","uranium price","rare earth","oil gas","investing life","price forecast","investing new","mine corp","wheeler river","industrial metal","athabasca basin","corp tsxdmlnysemktdnn","fission uranium","lithium stock","price investing","gold price","metal investing","investing back","investing precious","metal gold","gold silver","silver platinum","platinum palladium","investing technology","investing printing","mobile web","investing biotech","medical device","report resource","uranium investing","uranium stock","river property","property denison","tsxdmlnysemktdnn announced","summer exploration","mine tsxdml","denison fission","merger kristen","view top","stock buy","investing copper","investing lithium","agriculture investing","investing opportunity","tech investing"],"m_TriGrams":["life science investing","kristen moran denison","moran denison mine","denison mine corp","mine corp tsxdmlnysemktdnn","investing precious metal","gold silver platinum","silver platinum palladium","resource investing technology","science investing biotech","uranium price forecast","wheeler river property","denison mine tsxdml","merger kristen moran"],"m_SocialTags":[],"m_Topics":[],"m_Industry":[],"m_Technology":[],"m_BiCnt":[19,14,10,10,10,9,8,7,7,7,6,6,6,5,5,5,5,5,5,5,4,4,4,4,4,4,4,4,4,3,3,3,3,3,3,3,3,3,3,3,3,3,3,3,3,3,3,3,3,3,3,3,3,3,3,3],"m_TriCnt":[10,7,7,5,4,3,3,3,3,3,3,3,3,3],"m_iDocBodyWordCnt":1423}
