{"m_szDocID":"298648","m_szDocTitle":"kivalliq News - Investing News Network","m_szYear":"2016","m_szDocSumamry":"Your trusted source for investing success Member? Login Menu Daily News Resource Investing Precious Metals Gold Silver Platinum Palladium Base Metals Copper Nickel Iron Lead Zinc Critical Metals Graphite Tungsten Tantalum Scandium Cobalt Magnesium Manganese Tellurium Rare Earth Industrial Metals Molybendum Coal Tin Aluminum Vanadium Chromium Energy Uranium Oil Gas Oil and Gas Lithium Gem Diamond Agriculture Potash Phosphate Cannabis About Resource Investing Technology Investing 3D Printing Cleantech Cloud Data Cybersecurity Fintech Graphene Mobile Web Nanotech About Technology Investing Life S","m_szDocBody":"trusted source investing success member menu daily new resource investing precious metal gold silver platinum palladium base metal copper nickel iron lead zinc critical metal graphite tungsten tantalum scandium cobalt magnesium manganese tellurium rare earth industrial metal molybendum coal tin aluminium vanadium chromium energy uranium oil gas oil gas lithium gem diamond agriculture potash phosphate cannabis resource investing technology investing printing cleantech cloud data cybersecurity fintech graphene mobile web nanotech technology investing life science investing biotech pharmaceutical medical device genetic life science investing free investor report resource free report technology free report life science free report outlook free report stock resource investing technology investing life science investing tag kivalliq expert guide diamond investing free download free special report investing stornoway diamond canadian diamond mine diamond price calculator dunnedin venture make commitment nunavut community matthew spizziri dunnedin venture inc tsxvdvi announced company representative held sery successful meeting community member local regional territorial government representative chesterfield inlet rankin inlet dunnedin venture head nunavut nirb decision charlotte mcleod company representative nunavut decision nunavut impact review board caused confusion week kivalliq energy announce airborne gravity survey commence genesis property saskatchewan matthew spizziri kivalliq energy corporation tsxvkiv announced commencement linekilometre fixedwing falcon airborne gravity gradiometer survey genesis uranium property northeastern saskatchewan kivalliq roughrider amend genesis uranium property option matthew spizziri kivalliq energy corporation tsxvkiv roughrider exploration ltd announced mutually agreed amend option agreement genesis property roughrider granted reduction minimum exploration expenditure oneyear extension phase agreement exchange commensurate salman partner uranium price rise kristen moran raymond goldie salman partner expect uranium spot price rise early kivalliq energy sample uranium angilak property matthew spizziri kivalliq energy corporation tsxvkiv released result soil sample collected dipolerib trend rock sample collected yat target area kivalliqs percentowned hectare acrea angilak property nunavut territory canada top canadian uranium resource held junior miner kristen moran top mineral resource estimate undeveloped uranium property owned junior explorer canada kivalliq energy ceo jim paterson talk drill result step kristen moran paterson discusse recent drill result hatchet lake property saskatchewan dipole discovery nunavut kivalliq energy drill angilak matthew spizziri kivalliq energy corporation tsxvkiv released complete assay result drill programme recent dipole discovery kivalliq energy grab sample hatchet lake matthew spizziri kivalliq energy corporation tsxvkiv announced released result summer exploration programme percentowned hatchet lake property athabasca region saskatchewan brien lundin hold kivalliq energy corp matthew spizziri september edition gold newsletter brien lundin hold kivalliq energy corporation tsxvkiv kivalliq energy appoint jonathan singh corporate secretary matthew spizziri kivalliq energy corporation tsxvkiv announced today appointment jonathan singh interim corporate secretary effective immediately latest uranium new kivalliq intersect offscale radioactivity dipole target kristen moran latest uranium new kivalliq energy announced result exploration drilling previously untested dipole target angilak property kivalliq energy begin exploration programme angilak property kristen moran kivalliq energy corporation tsxvkiv announced commenced drilling angilak property nunavut main focus programme drill testing priority dipole target advancing multiple uranium target dipolerib trend geochemical surveying kivalliq energy complete summer programme hatchet lake advance priority target areas kristen moran kivalliq energy corporation tsxvkiv announced completed summer exploration programme hatchet lake property athabasca region kivalliq energy winter exploration programme refine jurgen target genesis property teresa matich kivalliq energy corporation tsxvkiv reported result ground magnetometer low frequency vlf electromagnetic geophysical biogeochemical sampling survey completed jurgen uranium target areas genesis property genesis property located eastern athabasca basin kilometre camecos tsxcco kivalliq begin summer exploration programme hatchet lake saskatchewan investing new network kivalliq energy tsxvkiv announced start cdn summer exploration programme hatchet lake property saskatchewan crew mobilised point area work focused multiple unconformityrelated basement target kivalliq energy announce fully funded summer exploration programme angilak hatchet lake property kristen moran kivalliq energy corporation tsxvkiv announced plan summer exploration programme angilak property nunavut hatchet lake property saskatchewan fully funded kivalliq energy close final tranche million private placement teresa matich kivalliq energy corporation tsxvkiv closed final tranche private placement gross proceed roughly million proceed placement corporate purpose fund mineral exploration saskatchewan canadas nunavut territory kivalliqroughrider joint venture athabasca basin featured northern miner investing new network kivalliq energy tsxvkiv joint venture roughrider exploration tsxvrel genesis athabasca basin featured northern miner kivalliq roughrider middle planning summer exploration programme uranium future outlook uranium price forecast onward analyst uranium price moving short long term read thefull article market top resource storey uranium ready run view top tsx stock gold mining sto view silver mining canada view cobalt ready boom view lithium ontario view mesothermal vein gold deposit view top technology storey bitcoin price surge view datawind ceo talk mobile data view electric vehicle drive cleant view big bioprin view cybersecurity venture release view printing material driv view top life science storey top nasdaq biotech stock cell view invest life science view invest biotech view medx health corp announce ontar view marina biotech announce resignat view delmar pharmaceutical present view popular stock galaxy resource view nemaska lithium view danakali ltd view formation metal view dajin resource view brixton metal view download free report resource investing resource forecast expert opinion covering precious metal energy critical metal gold trend gold outlook key highlight investor base metal opinion expert ceos lithium stock price analyst ceos graphite new graphite mining graphite stock buy lme copper copper etf understanding today copper price investing copper rare earth new rare earth metal price investing lithium stock post rockwood lithium potash stock potash new agriculture investing opportunity investing today critical metal context lynas new molycorp new silver highest price silver come potash type potash potash stock uranium price forecast top uranium stock watch invest platinum stock future hold lonmin amcu south african platinum production investing opportunity lme price base metal new investing tungsten tungsten price tungsten demand tungsten company glance zinc commodity new zinc market outlook coal price forecast type coal coal price coal stock forecasting oil price investing wisely top oil producing country palladium price forecast palladium investment opportunity investing medical cannabis information cannabis legal cannabis stock investing stornoway diamond canadian diamond mine diamond price calculator gold good investment gold price today future gold price prediction kitco mint sold out top article resource investing new gold trend gold outlook key highlight investor lithium stock price analyst ceos resource forecast expert opinion covering precious metal energy critical metal industrial metal oversupply market base metal opinion expert ceos energy investing outlook moving carbon agriculture investing opportunity forecast precious metal outlook ceos analyst gold silver platinum palladium critical metal outlook potential lme copper copper etf understanding today copper price investing copper kitco mint sold out top article resource investing new gold good investment gold price today future gold price prediction investing lithium stock post rockwood lithium free lithium investing newsletter free uranium investing newsletter life science investing life science investing primer finding opportunity medtronic ariad pharmaceutical pharmacyte investing pharmaceutical company pharmaceutical new top pharmaceutical stock buy biotech investing new top biotech company biotech stock life science investing ethic app revolution tech investing understanding bitcoin bitcoin mining bitcoin rate nanotechnology nanotech application nanotech investing investing graphene company graphene cost graphene property graphene market future printing company printing stock buy tech investing primer bitcoin rate printing company instagram stock cleantech investing clean technology investor technology investing trend outlook successful technology investing browse topic resource investing agriculture investing cannabis investing phosphate investing potash investing base metal investing copper investing iron investing lead investing nickel investing zinc investing critical metal investing cobalt investing graphite investing magnesium investing manganese investing rare earth investing scandium investing tantalum investing tellurium investing tungsten investing energy investing gas investing lithium investing oil gas investing oil investing uranium investing gem investing diamond investing industrial metal investing aluminium investing chromium investing coal investing molybdenum investing tin investing vanadium investing precious metal investing gold investing palladium investing platinum investing silver investing tech investing printing investing app investing cleantech investing cloud investing cybersecurity investing data investing fintech investing graphene investing mobile web investing nanotech investing life science investing biotech investing genetic investing longevity investing medical device investing pharmaceutical investing featured stock mettrum health leader canadas growing cannabis market komet resource american manganese stria lithium houston lake mining featured stock enter log credential remember lost password create password manage account contact privacy policy stock index keyword index browsetopic advertise free report event glossary press release copyright dig media inc investing new network daily new resource investing precious metal gold silver platinum palladium back base metal copper nickel iron lead zinc back critical metal graphite tungsten tantalum scandium cobalt magnesium manganese tellurium rare earth back industrial metal molybendum coal tin aluminium vanadium chromium back energy uranium oil gas oil gas lithium back gem diamond back agriculture potash phosphate cannabis back resource investing back technology investing printing cleantech cloud data back cybersecurity fintech graphene mobile web nanotech technology investing back life science investing biotech pharmaceutical medical device genetic life science investing back free investor report resource free report technology free report life science free report outlook free report back stock resource investing technology investing life science investing back","m_szGeo1":"Canada","m_szSourceType":"source_general","m_szSrcUrl":"http://investingnews.com/tag/kivalliq/","m_Places":["Tin","Mobile","Outlook","Chesterfield","Gravity","Saskatchewan","Canada","Paterson","Ontario","Delmar","Most","United States","Best","Rockwood","Outlooks","Enter"],"m_People":["Diamond Mines","Diamond Price","Matthew Spizziri","Charlotte Mcleod","Kristen Moran","Raymond Goldie","Jim Paterson","Houston Lake","Brien Lundin","Jonathan Singh","Teresa Matich"],"m_Companies":["Daily News","Palladium","Cleantech","Fintech","Special Report","Dunnedin Ventures Inc.","Energy Corporation","Roughrider Exploration Ltd.","Salman Partners","Target","Hold Kivalliq Energy Corp","Priority Target Areas","Top Technology","Datawind","Top Nasdaq","Medx Health Corp.","Danakali Ltd.","Lonmin","Tungsten Companies","Us Mint","Medtronic","Ariad Pharmaceuticals","Top Biotech Companies","Revolution","Graphene Companies","Printing Companies","Dig Media Inc."],"m_BiGrams":["kivalliq energy","life science","energy corporation","corporation tsxvkiv","resource investing","science investing","free report","hatchet lake","exploration programme","technology investing","matthew spizziri","critical metal","tsxvkiv announced","kristen moran","summer exploration","precious metal","base metal","spizziri kivalliq","angilak property","lake property","investing new","rare earth","oil gas","investing life","genesis property","industrial metal","property saskatchewan","uranium price","programme hatchet","price forecast","lithium stock","price investing","gold price","metal investing","investing back","investing precious","metal gold","gold silver","silver platinum","platinum palladium","investing technology","investing printing","mobile web","investing biotech","medical device","report resource","dunnedin venture","uranium property","property nunavut","dipole target","programme angilak","moran kivalliq","athabasca basin","new network","view top","stock buy","investing copper","investing lithium","agriculture investing","investing opportunity","tech investing"],"m_TriGrams":["kivalliq energy corporation","energy corporation tsxvkiv","life science investing","summer exploration programme","matthew spizziri kivalliq","spizziri kivalliq energy","corporation tsxvkiv announced","hatchet lake property","programme hatchet lake","investing precious metal","gold silver platinum","silver platinum palladium","resource investing technology","science investing biotech","angilak property nunavut","lake property saskatchewan","exploration programme angilak","kristen moran kivalliq","moran kivalliq energy","exploration programme hatchet","investing new network"],"m_SocialTags":[],"m_Topics":[],"m_Industry":[],"m_Technology":[],"m_BiCnt":[27,14,12,12,10,10,10,9,9,8,8,7,7,7,7,6,6,6,6,6,6,5,5,5,5,4,4,4,4,4,4,4,4,4,4,3,3,3,3,3,3,3,3,3,3,3,3,3,3,3,3,3,3,3,3,3,3,3,3,3,3],"m_TriCnt":[12,12,10,7,6,6,6,6,4,3,3,3,3,3,3,3,3,3,3,3,3],"m_iDocBodyWordCnt":1476}
