{"m_szDocID":"298665","m_szDocTitle":"cameco News - Investing News Network","m_szYear":"2016","m_szDocSumamry":"Your trusted source for investing success Member? Login Menu Daily News Resource Investing Precious Metals Gold Silver Platinum Palladium Base Metals Copper Nickel Iron Lead Zinc Critical Metals Graphite Tungsten Tantalum Scandium Cobalt Magnesium Manganese Tellurium Rare Earth Industrial Metals Molybendum Coal Tin Aluminum Vanadium Chromium Energy Uranium Oil Gas Oil and Gas Lithium Gem Diamond Agriculture Potash Phosphate Cannabis About Resource Investing Technology Investing 3D Printing Cleantech Cloud Data Cybersecurity Fintech Graphene Mobile Web Nanotech About Technology Investing Life S","m_szDocBody":"trusted source investing success member menu daily new resource investing precious metal gold silver platinum palladium base metal copper nickel iron lead zinc critical metal graphite tungsten tantalum scandium cobalt magnesium manganese tellurium rare earth industrial metal molybendum coal tin aluminium vanadium chromium energy uranium oil gas oil gas lithium gem diamond agriculture potash phosphate cannabis resource investing technology investing printing cleantech cloud data cybersecurity fintech graphene mobile web nanotech technology investing life science investing biotech pharmaceutical medical device genetic life science investing free investor report resource free report technology free report life science free report outlook free report stock resource investing technology investing life science investing tag cameco expert guide uranium investing free download free special reporturanium future outlook uranium price forecast top uranium stock watch forum uranium wellpositioned athabasca highgrade uranium discovery melissa pistilli forum uranium corp tsxvfdc focused making highgrade uranium discovery canadas athabasca basin cameco update production outlook cigar lake jocelyn aspa cameco tsxcco announced canadian nuclear safety commission approved application areva resource canada increase annual licenced production capacity mcclean lake milling operation million pound uranium concentrate quoted press release ore camecos cigar lake mine milled callinex expand pine bay east zone intersect zinc equivalent investing new network vancouver british columbiamarketwired highlight stepout hole pbm initial discovery hole intersected zinc equivalent total hole intersected mineralization approximate strike length plan complete deep hole testing downplunge extension uranium deposit exploration india jocelyn aspa nuclear demand rise india prompting country explore develop uranium deposit border cameco kazatomprom agreement restrict inkai jocelyn aspa cameco corporation tsxcco signed agreement joint stock company national atomic company kazatomprom joint venture inkai llp restrict enhance inkai quoted press release inkai operation situ recovery uranium mine south kazakhstan owned operated forum uranium acquire interest wham property north key lake mine mill matthew spizziri forum uranium corp tsxvfdc announced acquired interest claim totaling hectare russell lake area kilometre northeast key lake mine mill eastern athabasca basin purepoint uranium hook lake partner budget additional drilling jocelyn aspa purepoint uranium tsxptu announced hook lake partner reallocated fund continued drilling spitfire zone hook lake project jointly owned cameco corp percent areva resource canada percent purepoint uranium percent quoted press uranium spot price update jocelyn aspa uranium spot price declined past year higher nuclear demand china india uae expected give metal boost price top holding global uranium etf vivien diniz company make top globe uranium etf cameco purchase waterbury west canalaska uranium vivien diniz canalaska uranium ltd company tsxv cvv otcqb cvvuf frankfurt dhn canalaska company pleased announce reached agreement sell waterbury claim cameco corporation tsx cco nyse ccj sale agreement waterbury west claim upa call dept energy cease uranium transfer market recover vivien diniz uranium producer america upa called department energy cease transfer federal excess uranium inventory uranium market recover oversupplied market persistent low price department energy continue sell million pound uranium year invest uranium vivien diniz investor invest uranium stock etf uranium future energy fuel announce appointment mark chalmer chief operating officer matthew spizziri energy fuel inc tsxefrnysemktuuuu announce appointment ofmark chalmer chief operating officer chalmer join energy fuel management team oversee company conventional situ isr uranium production operation nexgen energy make game changing discovery teresa matich nexgen energy announced discovered potential zone highgrade uranium mineralization rook property saskatchewan athabasca basin cameco stock watch list teresa matich cameco largest uranium producer world company watch list denison mine release strong maiden pea wheeler river teresa matich highlight maiden pea denison percentowned wheeler river project include pretax net million internal rate return percent price pound denison goviex combine african uranium asset investing new network toronto ontariomarketwired denison mine corp tsxdmlnyse mktdnn denison pleased announce execution definitive share purchase agreement the agreement goviex uranium inc csegxu goviex combine respective african uranium mineral interest the transaction create leading africanfocused uranium development purepoint uranium expand spitfire zone grade intercept teresa matich purepoint uranium tsxvptuv reported result hole drilled spitfire zone hook lake joint venture drilling confirmed continuous uranium mineralization metre downdip graphitic shear zone beginning unconformity european commission recommend billion euro investment nuclear power teresa matich european commission set release report nuclear industry coming week german newspaper handelsblatt reported advance copy document major uranium producer hesitant build mine charlotte mcleod reuter reported number world biggest uranium miner taking cautious approach building mine cut cost wait higher uranium price production now uranium future outlook uranium price forecast onward analyst uranium price moving short long term read thefull article market top resource storey uranium ready run view top tsx stock gold mining sto view silver mining canada view cobalt ready boom view lithium ontario view mesothermal vein gold deposit view top technology storey bitcoin price surge view datawind ceo talk mobile data view electric vehicle drive cleant view big bioprin view cybersecurity venture release view printing material driv view top life science storey top nasdaq biotech stock cell view invest life science view invest biotech view medx health corp announce ontar view marina biotech announce resignat view delmar pharmaceutical present view popular stock galaxy resource view nemaska lithium view danakali ltd view formation metal view dajin resource view brixton metal view download free report resource investing resource forecast expert opinion covering precious metal energy critical metal gold trend gold outlook key highlight investor base metal opinion expert ceos lithium stock price analyst ceos graphite new graphite mining graphite stock buy lme copper copper etf understanding today copper price investing copper rare earth new rare earth metal price investing lithium stock post rockwood lithium potash stock potash new agriculture investing opportunity investing today critical metal context lynas new molycorp new silver highest price silver come potash type potash potash stock uranium price forecast top uranium stock watch invest platinum stock future hold lonmin amcu south african platinum production investing opportunity lme price base metal new investing tungsten tungsten price tungsten demand tungsten company glance zinc commodity new zinc market outlook coal price forecast type coal coal price coal stock forecasting oil price investing wisely top oil producing country palladium price forecast palladium investment opportunity investing medical cannabis information cannabis legal cannabis stock investing stornoway diamond canadian diamond mine diamond price calculator gold good investment gold price today future gold price prediction kitco mint sold out top article resource investing new gold trend gold outlook key highlight investor lithium stock price analyst ceos resource forecast expert opinion covering precious metal energy critical metal industrial metal oversupply market base metal opinion expert ceos energy investing outlook moving carbon agriculture investing opportunity forecast precious metal outlook ceos analyst gold silver platinum palladium critical metal outlook potential lme copper copper etf understanding today copper price investing copper kitco mint sold out top article resource investing new gold good investment gold price today future gold price prediction investing lithium stock post rockwood lithium free lithium investing newsletter free uranium investing newsletter life science investing life science investing primer finding opportunity medtronic ariad pharmaceutical pharmacyte investing pharmaceutical company pharmaceutical new top pharmaceutical stock buy biotech investing new top biotech company biotech stock life science investing ethic app revolution tech investing understanding bitcoin bitcoin mining bitcoin rate nanotechnology nanotech application nanotech investing investing graphene company graphene cost graphene property graphene market future printing company printing stock buy tech investing primer bitcoin rate printing company instagram stock cleantech investing clean technology investor technology investing trend outlook successful technology investing browse topic resource investing agriculture investing cannabis investing phosphate investing potash investing base metal investing copper investing iron investing lead investing nickel investing zinc investing critical metal investing cobalt investing graphite investing magnesium investing manganese investing rare earth investing scandium investing tantalum investing tellurium investing tungsten investing energy investing gas investing lithium investing oil gas investing oil investing uranium investing gem investing diamond investing industrial metal investing aluminium investing chromium investing coal investing molybdenum investing tin investing vanadium investing precious metal investing gold investing palladium investing platinum investing silver investing tech investing printing investing app investing cleantech investing cloud investing cybersecurity investing data investing fintech investing graphene investing mobile web investing nanotech investing life science investing biotech investing genetic investing longevity investing medical device investing pharmaceutical investing featured stock mettrum health leader canadas growing cannabis market komet resource american manganese stria lithium houston lake mining featured stock enter log credential remember lost password create password manage account contact privacy policy stock index keyword index browsetopic advertise free report event glossary press release copyright dig media inc investing new network daily new resource investing precious metal gold silver platinum palladium back base metal copper nickel iron lead zinc back critical metal graphite tungsten tantalum scandium cobalt magnesium manganese tellurium rare earth back industrial metal molybendum coal tin aluminium vanadium chromium back energy uranium oil gas oil gas lithium back gem diamond back agriculture potash phosphate cannabis back resource investing back technology investing printing cleantech cloud data back cybersecurity fintech graphene mobile web nanotech technology investing back life science investing biotech pharmaceutical medical device genetic life science investing back free investor report resource free report technology free report life science free report outlook free report back stock resource investing technology investing life science investing back","m_szGeo1":"Canada","m_szSourceType":"source_general","m_szSrcUrl":"http://investingnews.com/tag/cameco/","m_Places":["Tin","Mobile","Outlook","Well","Canada","Pine Bay","Vancouver, British Columbia","India","Kazakhstan","China","Waterbury","Frankfurt","America","Saskatchewan","Denison","Wheeler","United States","Toronto, Ontario","“denison”","Ontario","Delmar","Most","Best","Rockwood","Outlooks","Enter"],"m_People":["Diamond Price","Melissa Pistilli","Russell Lake","Jocelyn Aspa","Matthew Spizziri","Hook Lake","Vivien Diniz","Mark Chalmers","Teresa Matich","Diamond Mines","Charlotte Mcleod","Houston Lake"],"m_Companies":["Daily News","Palladium","Cleantech","Fintech","Special Report","Forum Uranium Corp.","Canadian Nuclear Safety Commission","Areva","Marketwired","Cameco Corporation","Inkai Llp","Mill","Uranium Group","Cameco Corp","Areva Resources Canada Inc","Canalaska Uranium Ltd.","Dept. Of Energy","Department Of Energy","Energy Fuels Inc.","Wheeler River Project","Denison Mines Corp.","Goviex Uranium Inc.","European Commission","Handelsblatt","Reuters","Top Technology","Datawind","Top Nasdaq","Medx Health Corp.","Danakali Ltd.","Lonmin","Tungsten Companies","Us Mint","Medtronic","Ariad Pharmaceuticals","Top Biotech Companies","Revolution","Graphene Companies","Printing Companies","Dig Media Inc."],"m_BiGrams":["life science","resource investing","science investing","free report","technology investing","critical metal","precious metal","base metal","investing new","rare earth","oil gas","investing life","uranium price","price forecast","jocelyn aspa","purepoint uranium","teresa matich","industrial metal","forum uranium","hook lake","vivien diniz","lithium stock","price investing","gold price","metal investing","investing back","investing precious","metal gold","gold silver","silver platinum","platinum palladium","investing technology","investing printing","mobile web","investing biotech","medical device","report resource","uranium investing","uranium stock","stock watch","highgrade uranium","athabasca basin","quoted press","press release","lake mine","new network","spitfire zone","uranium producer","energy fuel","view top","stock buy","investing copper","investing lithium","agriculture investing","investing opportunity","tech investing"],"m_TriGrams":["life science investing","investing precious metal","gold silver platinum","silver platinum palladium","resource investing technology","science investing biotech","uranium price forecast","investing new network"],"m_SocialTags":[],"m_Topics":[],"m_Industry":[],"m_Technology":[],"m_BiCnt":[14,10,10,10,8,7,6,6,6,5,5,5,5,5,5,5,5,4,4,4,4,4,4,4,4,4,3,3,3,3,3,3,3,3,3,3,3,3,3,3,3,3,3,3,3,3,3,3,3,3,3,3,3,3,3,3],"m_TriCnt":[10,3,3,3,3,3,3,3],"m_iDocBodyWordCnt":1507}
