{"m_szDocID":"298618","m_szDocTitle":"patterson lake south News - Investing News Network","m_szYear":"2016","m_szDocSumamry":"Your trusted source for investing success Member? Login Menu Daily News Resource Investing Precious Metals Gold Silver Platinum Palladium Base Metals Copper Nickel Iron Lead Zinc Critical Metals Graphite Tungsten Tantalum Scandium Cobalt Magnesium Manganese Tellurium Rare Earth Industrial Metals Molybendum Coal Tin Aluminum Vanadium Chromium Energy Uranium Oil Gas Oil and Gas Lithium Gem Diamond Agriculture Potash Phosphate Cannabis About Resource Investing Technology Investing 3D Printing Cleantech Cloud Data Cybersecurity Fintech Graphene Mobile Web Nanotech About Technology Investing Life S","m_szDocBody":"trusted source investing success member menu daily new resource investing precious metal gold silver platinum palladium base metal copper nickel iron lead zinc critical metal graphite tungsten tantalum scandium cobalt magnesium manganese tellurium rare earth industrial metal molybendum coal tin aluminium vanadium chromium energy uranium oil gas oil gas lithium gem diamond agriculture potash phosphate cannabis resource investing technology investing printing cleantech cloud data cybersecurity fintech graphene mobile web nanotech technology investing life science investing biotech pharmaceutical medical device genetic life science investing free investor report resource free report technology free report life science free report outlook free report stock resource investing technology investing life science investing tag patterson lake south expert guide uranium investing free download free special reporturanium future outlook uranium price forecast top uranium stock watch top holding global uranium etf vivien diniz company make top globe uranium etf alx uranium complete ground radon survey teresa matich alx uranium tsxval reported followup radoninwater sampling completed lazy edward bay property southern margin saskatchewan athabasca basin alx complete geophysical programme hookcarter property patterson lake south area vivien diniz alx uranium corp tsxval fwblln otcqxalxef announced geophysical programme complete hookcarter propertylocated patterson lake south area southwestern athabasca basin saskatchewan alx uranium enter strategic partnership holystone energy charlotte mcleod alx uranium corp tsxvalotcqxalxef announced entered agreement holystone energy company ltd threeyear strategic partnership pls world class standard fission uranium coo ross mcelroy vivien diniz mcelroy discusse fission continued success today tough market shedding light what company top canadian uranium resource held junior miner kristen moran top mineral resource estimate undeveloped uranium property owned junior explorer canada uranium new japan restart reactor denison fission terminate plan merge kristen moran meanwhile toro energy increased mineral resource kivalliq nexgen reported result respective project top uraniumproducing company world kristen moran list top publicly traded uraniumproducing company investor interested space look drill tracker weekly fission drill metre grading percent wayne hewgill fission uranium announced initial assay result summer drilling patterson lake south project saskatchewan athabasca basin uranium new india criticised cigar lake start production kristen moran india faced criticism week cameco began production cigar lake mine latest drill result fission uranium nexgen energy fission uranium release pea triple deposit kristen moran study show posttax npv billion posttax irr percent payback period set year fission uranium release triple pea opex percent posttax irr billion posttax npv teresa matich fission uranium tsxfcu released result preliminary economic assessment triple deposit patterson lake south property highlight included posttax billion npv posttax irr percent year payback period athabasca basin uranium company watch kristen moran uranium company working world highestgrade uranium district denion mine report quarter result kristen moran denison mine corp tsxdmlnysemktdnn announced result month period ended showed net loss million share denison mine sell noncore asset mongolia ahead merger kristen moran denison mine plan sell interest gurvan saihan joint venture mongolia uranium industry czech company denison fission definitive arrangement agreement merger kristen moran denison mine corp tsxdmlnysemktdnn fission uranium corp tsxfcu announced entered definitive arrangement agreement replace previously announced binding letter agreement arrangement company combine courtapproved plan uranium future outlook restart japan uranium junior kristen moran uranium demand slow recover postfukushima watching space know japan working hard nuclear power plant back track step reflected positively uranium stock uranium future outlook denison mine fission uranium merge teresa matich market close monday denison mine fission uranium announced merge create uranium company called denison energy drill tracker weekly fission discover parallel zone depth zone wayne hewgill fission uranium announced discovery zone depth metre north additional result hole zone expanded footprint filled gap highgrade core zone highlight cantor fitzgerald annual global uranium conference kristen moran cantor fitzgerald annual global uranium conference featured lineup noteworthy uranium company event investing new network chance catch senior analyst rob chang rundown went uranium future outlook uranium price forecast onward analyst uranium price moving short long term read thefull article market top resource storey uranium ready run view top tsx stock gold mining sto view silver mining canada view cobalt ready boom view lithium ontario view mesothermal vein gold deposit view top technology storey bitcoin price surge view datawind ceo talk mobile data view electric vehicle drive cleant view big bioprin view cybersecurity venture release view printing material driv view top life science storey top nasdaq biotech stock cell view invest life science view invest biotech view medx health corp announce ontar view marina biotech announce resignat view delmar pharmaceutical present view popular stock galaxy resource view nemaska lithium view danakali ltd view formation metal view dajin resource view brixton metal view download free report resource investing resource forecast expert opinion covering precious metal energy critical metal gold trend gold outlook key highlight investor base metal opinion expert ceos lithium stock price analyst ceos graphite new graphite mining graphite stock buy lme copper copper etf understanding today copper price investing copper rare earth new rare earth metal price investing lithium stock post rockwood lithium potash stock potash new agriculture investing opportunity investing today critical metal context lynas new molycorp new silver highest price silver come potash type potash potash stock uranium price forecast top uranium stock watch invest platinum stock future hold lonmin amcu south african platinum production investing opportunity lme price base metal new investing tungsten tungsten price tungsten demand tungsten company glance zinc commodity new zinc market outlook coal price forecast type coal coal price coal stock forecasting oil price investing wisely top oil producing country palladium price forecast palladium investment opportunity investing medical cannabis information cannabis legal cannabis stock investing stornoway diamond canadian diamond mine diamond price calculator gold good investment gold price today future gold price prediction kitco mint sold out top article resource investing new gold trend gold outlook key highlight investor lithium stock price analyst ceos resource forecast expert opinion covering precious metal energy critical metal industrial metal oversupply market base metal opinion expert ceos energy investing outlook moving carbon agriculture investing opportunity forecast precious metal outlook ceos analyst gold silver platinum palladium critical metal outlook potential lme copper copper etf understanding today copper price investing copper kitco mint sold out top article resource investing new gold good investment gold price today future gold price prediction investing lithium stock post rockwood lithium free lithium investing newsletter free uranium investing newsletter life science investing life science investing primer finding opportunity medtronic ariad pharmaceutical pharmacyte investing pharmaceutical company pharmaceutical new top pharmaceutical stock buy biotech investing new top biotech company biotech stock life science investing ethic app revolution tech investing understanding bitcoin bitcoin mining bitcoin rate nanotechnology nanotech application nanotech investing investing graphene company graphene cost graphene property graphene market future printing company printing stock buy tech investing primer bitcoin rate printing company instagram stock cleantech investing clean technology investor technology investing trend outlook successful technology investing browse topic resource investing agriculture investing cannabis investing phosphate investing potash investing base metal investing copper investing iron investing lead investing nickel investing zinc investing critical metal investing cobalt investing graphite investing magnesium investing manganese investing rare earth investing scandium investing tantalum investing tellurium investing tungsten investing energy investing gas investing lithium investing oil gas investing oil investing uranium investing gem investing diamond investing industrial metal investing aluminium investing chromium investing coal investing molybdenum investing tin investing vanadium investing precious metal investing gold investing palladium investing platinum investing silver investing tech investing printing investing app investing cleantech investing cloud investing cybersecurity investing data investing fintech investing graphene investing mobile web investing nanotech investing life science investing biotech investing genetic investing longevity investing medical device investing pharmaceutical investing featured stock mettrum health leader canadas growing cannabis market komet resource american manganese stria lithium houston lake mining featured stock enter log credential remember lost password create password manage account contact privacy policy stock index keyword index browsetopic advertise free report event glossary press release copyright dig media inc investing new network daily new resource investing precious metal gold silver platinum palladium back base metal copper nickel iron lead zinc back critical metal graphite tungsten tantalum scandium cobalt magnesium manganese tellurium rare earth back industrial metal molybendum coal tin aluminium vanadium chromium back energy uranium oil gas oil gas lithium back gem diamond back agriculture potash phosphate cannabis back resource investing back technology investing printing cleantech cloud data back cybersecurity fintech graphene mobile web nanotech technology investing back life science investing biotech pharmaceutical medical device genetic life science investing back free investor report resource free report technology free report life science free report outlook free report back stock resource investing technology investing life science investing back","m_szGeo1":"Canada","m_szSourceType":"source_general","m_szSrcUrl":"http://investingnews.com/tag/patterson-lake-south/","m_Places":["Tin","Mobile","Outlook","Lazy Edward Bay","Saskatchewan","Hook-carter","Lake South Area","Canada","Japan","Denison","India","United States","Mongolia","Czech","Fukushima","Ontario","Delmar","Most","Best","Rockwood","Outlooks","Enter"],"m_People":["Houston Lake","Diamond Price","Vivien Diniz","Teresa Matich","Hook-carter Propertylocated","Charlotte Mcleod","Ross Mcelroy","Kristen Moran","Wayne Hewgill","Diamond Mines","Rob Chang"],"m_Companies":["Daily News","Palladium","Cleantech","Fintech","Patterson","Special Report","Alx Uranium Corp.","Holystone Energy Company Ltd.","Toro","Uranium Companies","Denison Mines Corp.","Denison Mines Corp","Fission Uranium Corp.","Juniors","Top Technology","Datawind","Top Nasdaq","Medx Health Corp.","Danakali Ltd.","Lonmin","Tungsten Companies","Us Mint","Medtronic","Ariad Pharmaceuticals","Top Biotech Companies","Revolution","Graphene Companies","Printing Companies","Dig Media Inc."],"m_BiGrams":["life science","kristen moran","resource investing","science investing","free report","fission uranium","technology investing","critical metal","precious metal","base metal","denison mine","rare earth","oil gas","investing life","patterson lake","lake south","price forecast","alx uranium","investing new","industrial metal","future outlook","uranium price","athabasca basin","uranium company","lithium stock","price investing","gold price","metal investing","investing back","investing precious","metal gold","gold silver","silver platinum","platinum palladium","investing technology","investing printing","mobile web","investing biotech","medical device","report resource","uranium investing","uranium stock","global uranium","vivien diniz","teresa matich","uranium corp","uranium announced","posttax irr","moran denison","uranium future","view top","stock buy","investing copper","investing lithium","agriculture investing","investing opportunity","tech investing"],"m_TriGrams":["life science investing","patterson lake south","investing precious metal","gold silver platinum","silver platinum palladium","resource investing technology","science investing biotech","uranium price forecast","fission uranium announced","kristen moran denison","moran denison mine"],"m_SocialTags":[],"m_Topics":[],"m_Industry":[],"m_Technology":[],"m_BiCnt":[14,11,10,10,10,10,8,7,6,6,6,5,5,5,5,5,5,5,5,4,4,4,4,4,4,4,4,4,4,3,3,3,3,3,3,3,3,3,3,3,3,3,3,3,3,3,3,3,3,3,3,3,3,3,3,3,3],"m_TriCnt":[10,5,3,3,3,3,3,3,3,3,3],"m_iDocBodyWordCnt":1414}
