{"m_szDocID":"298679","m_szDocTitle":"Uranium Outlook: 2014 Will Be the Year of Uranium - Investing News Network","m_szYear":"2014","m_szDocSumamry":"UraniumInvesting News Your trusted source for investing success Uranium Member? Login Menu Daily News Resource Investing Precious Metals Gold Silver Platinum Palladium Base Metals Copper Nickel Iron Lead Zinc Critical Metals Graphite Tungsten Tantalum Scandium Cobalt Magnesium Manganese Tellurium Rare Earth Industrial Metals Molybendum Coal Tin Aluminum Vanadium Chromium Energy Uranium Oil Gas Oil and Gas Lithium Gem Diamond Agriculture Potash Phosphate Cannabis About Resource Investing Technology Investing 3D Printing Cleantech Cloud Data Cybersecurity Fintech Graphene Mobile Web Nanotech Abo","m_szDocBody":"uraniuminvesting new trusted source investing success uranium member menu daily new resource investing precious metal gold silver platinum palladium base metal copper nickel iron lead zinc critical metal graphite tungsten tantalum scandium cobalt magnesium manganese tellurium rare earth industrial metal molybendum coal tin aluminium vanadium chromium energy uranium oil gas oil gas lithium gem diamond agriculture potash phosphate cannabis resource investing technology investing printing cleantech cloud data cybersecurity fintech graphene mobile web nanotech technology investing life science investing biotech pharmaceutical medical device genetic life science investing free investor report resource free report technology free report life science free report outlook free report stock resource investing technology investing life science investing uranium investing uranium outlook year uranium usec expect file uranium stock watch vivien diniz comment move over youve taunted promise resurgence uranium youve good new year deliver week uranium market flurry activity acquisition financing supply disruption impending start ups uranium market ready shift gear price main catalyst price movement start reactor japan unfortunately japan didnt restart reactor timeline hoping for delay setting independent nuclear regulatory body japan uranium delivery contract deferred continue deferred led supply introduced market raymond jame analyst david sadowski told uranium investing new simply put market flushed excess material utility fairly covered led limited nondiscretionary buying softer price believe persist japan restart reactor playing role keeping price making bull run feeding enricher hoped department energy amping uranium disposition market expect reactor online japan reactor waiting restarted catalyst reached consensus matter time uranium market take off question japan fire reactor sadowski reactor back online end starting midyear expect price ball finally start rolling uranium rob chang analyst cantor fitzgerald expect significant dramatic move price based firm current supply demand model unavoidable supply deficit wont covered point chang said adding youre deficit period matter start chang expect uranium market satisfy impending demand result reactor uranium operate what happen start buying inflexion point youre big pile utility buying chang told uranium investing new side that sadowski utility riskbased approach inventory management explaining they hold amount material advance need feel security supply waiting looming global shortfall situation quickly pile market current market however sadowski believe potential dramatic rise longterm price gradual meteoric run year ago spot price sadowski potential move quickly financial entity trading material influence price quicker pace spot price concerned cantor fitzgerald forecast uranium spot price average that however mean spot price enjoy extended stay order reach average chang believe outcome price closer end head start cantor fitzgerald forecasting stop price showing belief uranium market moving forward longterm price chang firm conservative pound raymond jame slightly bullish uranium spot price forecast however raymond jame expecting spot price slip uranium market barometer investor stay ahead uranium market company eye uranium participation tsxu reason accurately reflect market sentiment upc physically backed uranium fund provide investor exposure uranium price exposure exploration development mining risk equity chang explained inception upc historically flat average fukushima average negative percent however week trading percent premium net asset nav range pretty high chang late positive uranium translating higher price upc trading ahead nav importance uranium exploration uranium exploration important investor aware importance exploration appear shortage primary uranium supply future finding deposit bringing production inevitably impact global market helping understand importance uranium exploration jim paterson ceo kivalliq energy tsxvkiv explained utility diversification key plenty uranium athabasca basin utility world arent buy region paterson explained adding risk imperative youre big utility inventory diversity supply may need relate exploration well simple bubble market mine offline entire system strained paterson said apply uranium mining commodity transportation network type buyer risk avoid critical dont supplier critical healthy supplier profit margin good buyer work supplier mine company make profit sustainable production said exploration critical create supply option supply option critical long term success market security disclosure vivien diniz hold direct investment interest company mentioned article latest uranium investing stock information latest information company uranium investing delivered directly inbox uraniumanfield resourcesenergy fuelsforum uraniumkivalliq energypeninsula energyplateau uraniumwestern uraniumselect select selecting company company above giving consent receive company remember unsubscribe time expert guide uranium investing free download free special reporturanium future outlook uranium price forecast top uranium stock watch return uranium investing index meta data usec expect file uranium stock watch related post top uranium stock yeartodate nexgen announce appointment charle scorer special advisor uranium marketing uranium export legislation passed greenland denmark solid foundation set asx listed greenland mineral energy forum uranium wellpositioned athabasca highgrade uranium discovery nexgen energy announce assay result tag athabasca basin cantor fitzgerald david sadowski mining raymond jame rise uranium uranium exploration uranium investing new uranium market uranium price uranium spot uranium supply zinc supply comment leave reply cancel reply required will published required comment market top resource storey uranium ready run view top tsx stock gold mining sto view silver mining canada view cobalt ready boom view lithium ontario view mesothermal vein gold deposit view top technology storey bitcoin price surge view datawind ceo talk mobile data view electric vehicle drive cleant view big bioprin view cybersecurity venture release view printing material driv view top life science storey top nasdaq biotech stock cell view invest life science view invest biotech view medx health corp announce ontar view marina biotech announce resignat view delmar pharmaceutical present view popular stock galaxy resource view nemaska lithium view danakali ltd view formation metal view dajin resource view brixton metal view tweet download free report resource investing resource forecast expert opinion covering precious metal energy critical metal gold trend gold outlook key highlight investor base metal opinion expert ceos lithium stock price analyst ceos graphite new graphite mining graphite stock buy lme copper copper etf understanding today copper price investing copper rare earth new rare earth metal price investing lithium stock post rockwood lithium potash stock potash new agriculture investing opportunity investing today critical metal context lynas new molycorp new silver highest price silver come potash type potash potash stock uranium price forecast top uranium stock watch invest platinum stock future hold lonmin amcu south african platinum production investing opportunity lme price base metal new investing tungsten tungsten price tungsten demand tungsten company glance zinc commodity new zinc market outlook coal price forecast type coal coal price coal stock forecasting oil price investing wisely top oil producing country palladium price forecast palladium investment opportunity investing medical cannabis information cannabis legal cannabis stock investing stornoway diamond canadian diamond mine diamond price calculator gold good investment gold price today future gold price prediction kitco mint sold out top article resource investing new gold trend gold outlook key highlight investor lithium stock price analyst ceos resource forecast expert opinion covering precious metal energy critical metal industrial metal oversupply market base metal opinion expert ceos energy investing outlook moving carbon agriculture investing opportunity forecast precious metal outlook ceos analyst gold silver platinum palladium critical metal outlook potential lme copper copper etf understanding today copper price investing copper kitco mint sold out top article resource investing new gold good investment gold price today future gold price prediction investing lithium stock post rockwood lithium free lithium investing newsletter free uranium investing newsletter life science investing life science investing primer finding opportunity medtronic ariad pharmaceutical pharmacyte investing pharmaceutical company pharmaceutical new top pharmaceutical stock buy biotech investing new top biotech company biotech stock life science investing ethic app revolution tech investing understanding bitcoin bitcoin mining bitcoin rate nanotechnology nanotech application nanotech investing investing graphene company graphene cost graphene property graphene market future printing company printing stock buy tech investing primer bitcoin rate printing company instagram stock cleantech investing clean technology investor technology investing trend outlook successful technology investing browse topic resource investing agriculture investing cannabis investing phosphate investing potash investing base metal investing copper investing iron investing lead investing nickel investing zinc investing critical metal investing cobalt investing graphite investing magnesium investing manganese investing rare earth investing scandium investing tantalum investing tellurium investing tungsten investing energy investing gas investing lithium investing oil gas investing oil investing uranium investing gem investing diamond investing industrial metal investing aluminium investing chromium investing coal investing molybdenum investing tin investing vanadium investing precious metal investing gold investing palladium investing platinum investing silver investing tech investing printing investing app investing cleantech investing cloud investing cybersecurity investing data investing fintech investing graphene investing mobile web investing nanotech investing life science investing biotech investing genetic investing longevity investing medical device investing pharmaceutical investing featured stock plateau uraniumemerging uranium district peru peninsula energy featured stock enter log credential remember lost password create password manage account contact privacy policy stock index keyword index browsetopic advertise free report event glossary press release copyright dig media inc investing new network daily new resource investing precious metal gold silver platinum palladium back base metal copper nickel iron lead zinc back critical metal graphite tungsten tantalum scandium cobalt magnesium manganese tellurium rare earth back industrial metal molybendum coal tin aluminium vanadium chromium back energy uranium oil gas oil gas lithium back gem diamond back agriculture potash phosphate cannabis back resource investing back technology investing printing cleantech cloud data back cybersecurity fintech graphene mobile web nanotech technology investing back life science investing biotech pharmaceutical medical device genetic life science investing back free investor report resource free report technology free report life science free report outlook free report back stock resource investing technology investing life science investing back","m_szGeo1":"Canada","m_szSourceType":"source_general","m_szSrcUrl":"http://investingnews.com/daily/resource-investing/energy-investing/uranium-investing/uranium-outlook-2014-will-be-the-year-of-uranium/","m_Places":["Tin","Mobile","Outlook","United States","Japan","Most","Well","Fukushima","Paterson","Meta","Greenland","Denmark","Canada","Ontario","Delmar","Best","Rockwood","Outlooks","Uranium District","Peru","Enter"],"m_People":["Vivien Diniz","Diamond Price","David Sadowski","Rob Chang","Jim Paterson","Diamond Mines"],"m_Companies":["Daily News","Palladium","Cleantech","Fintech","Usec","Raymond James","Bull","Us Department Of Energy","Ball","Upc","Special Report","Top Technology","Datawind","Top Nasdaq","Medx Health Corp.","Danakali Ltd.","Lonmin","Tungsten Companies","Us Mint","Medtronic","Ariad Pharmaceuticals","Top Biotech Companies","Revolution","Graphene Companies","Printing Companies","Dig Media Inc."],"m_BiGrams":["life science","resource investing","science investing","free report","uranium investing","technology investing","uranium market","critical metal","investing new","precious metal","base metal","spot price","rare earth","oil gas","investing life","uranium stock","price forecast","industrial metal","stock watch","raymond jame","cantor fitzgerald","uranium price","lithium stock","price investing","gold price","metal investing","investing back","investing precious","metal gold","gold silver","silver platinum","platinum palladium","investing technology","investing printing","mobile web","investing biotech","medical device","report resource","investing uranium","uranium spot","uranium exploration","top uranium","view top","stock buy","investing copper","investing lithium","agriculture investing","investing opportunity","tech investing"],"m_TriGrams":["life science investing","uranium stock watch","investing precious metal","gold silver platinum","silver platinum palladium","resource investing technology","science investing biotech","uranium investing new","top uranium stock"],"m_SocialTags":[],"m_Topics":[],"m_Industry":[],"m_Technology":[],"m_BiCnt":[14,10,10,10,10,8,8,7,7,6,6,6,5,5,5,5,5,4,4,4,4,4,4,4,4,4,4,3,3,3,3,3,3,3,3,3,3,3,3,3,3,3,3,3,3,3,3,3,3],"m_TriCnt":[10,4,3,3,3,3,3,3,3],"m_iDocBodyWordCnt":1538}
