{"m_szDocID":"298750","m_szDocTitle":"Should Cameco Stock Be on Your Watch List? - Investing News Network","m_szYear":"2016","m_szDocSumamry":"UraniumInvesting News Your trusted source for investing success Uranium Member? Login Menu Daily News Resource Investing Precious Metals Gold Silver Platinum Palladium Base Metals Copper Nickel Iron Lead Zinc Critical Metals Graphite Tungsten Tantalum Scandium Cobalt Magnesium Manganese Tellurium Rare Earth Industrial Metals Molybendum Coal Tin Aluminum Vanadium Chromium Energy Uranium Oil Gas Oil and Gas Lithium Gem Diamond Agriculture Potash Phosphate Cannabis About Resource Investing Technology Investing 3D Printing Cleantech Cloud Data Cybersecurity Fintech Graphene Mobile Web Nanotech Abo","m_szDocBody":"uraniuminvesting new trusted source investing success uranium member menu daily new resource investing precious metal gold silver platinum palladium base metal copper nickel iron lead zinc critical metal graphite tungsten tantalum scandium cobalt magnesium manganese tellurium rare earth industrial metal molybendum coal tin aluminium vanadium chromium energy uranium oil gas oil gas lithium gem diamond agriculture potash phosphate cannabis resource investing technology investing printing cleantech cloud data cybersecurity fintech graphene mobile web nanotech technology investing life science investing biotech pharmaceutical medical device genetic life science investing free investor report resource free report technology free report life science free report outlook free report stock resource investing technology investing life science investing uranium investing cameco stock watch list cameco stock price movement important uranium investor watch top tsxv stock nulega nexgen energy make anoth teresa matich add comment cameco tsxcconyseccj largest uranium producing companiesin world produced million pound uranium million year earlier plan continue growing overall miner responsible roughly percent world production million pound proven probable reserve project canada australia percent owned mcarthur river mine largest uranium mine world responsible percent global production light make sense uranium investor eye cameco stock price movement market participant areinterested injunior miner developer large producer cameco stock activity valuable indicator market doing expert guide uranium investing free download free special reporturanium future outlook uranium price forecast top uranium stock watch cameco stock uranium price camecos share price downtrendso lost percentsince percent past year trading toronto stock exchange york cameco stock hasfared better gaining percent start year trade past year cameco lost toronto percent york sound bad new stock however company uranium space loss largely driven fukushima nuclear disaster japan ensuing drop uranium price tsunami triggered earthquake caused nuclear meltdown led thecountry put entire nuclear capacity hold move coupled broader commodity price rout began couple year later brought uranium price pound roughly pound today reactor restart japanhad investor predicting higher uranium price early far price remainedunder pressure still market participant calling higher demand lack supply coming online boost uranium price inthe year what cameco meantime cameco makedue current price result preliminary economic assessment pea recently released wheeler river project northern saskatchewan indicating strong result base case price pounddavid sadowski raymond jame noted figurerefreshingly wasinline current posted longterm price cameco own percent interest project jcu canada exploration owning percent interest anddenison minestsxdmlnysemktdnn own percent importantly cameco recently released updated technical report percentowned cigar lake mine thing report included revised mine plan development method higher capital cost sadowski stated note client increase speak complexity cigar lake orebody difficulty bringingon highgrade uranium production general deposit uranium future outlook uranium price forecast onward analyst uranium price moving short long term read thefull article themotley foolpoint cameco battling canada revenue agency cra tax issue notesthat cameco hold highest grade deposit world arguing miner positioned benefit recovery price hand sadowski suggested simple hesitant project camecos pipeline latest note companyraymond jame overweight rating cameco stock lowered price target share case fair return stock sitting andas mentioned above camecois largest uranium producer world watch keeping eye uranium market cameco market capitalization billion traded week average share dont forget follow realtime new update security disclosure teresa matich hold direct investment interest company mentioned article latest uranium investing stock information latest information company uranium investing delivered directly inbox uraniumanfield resourcesenergy fuelsforum uraniumkivalliq energypeninsula energyplateau uraniumwestern uraniumselect select selecting company company above giving consent receive company remember unsubscribe time expert guide uranium investing free download free special reporturanium future outlook uranium price forecast top uranium stock watch return uranium investing index meta data top tsxv stock nulega nexgen energy make anoth related post top uranium stock yeartodate nexgen announce appointment charle scorer special advisor uranium marketing uranium export legislation passed greenland denmark solid foundation set asx listed greenland mineral energy forum uranium wellpositioned athabasca highgrade uranium discovery nexgen energy announce assay result tag cameco cameco stock cameco stock price canada largest uranium producer mcarthur river raymond jame uranium uranium investor uranium price comment leave reply cancel reply required will published required comment market top resource storey uranium ready run view top tsx stock gold mining sto view silver mining canada view cobalt ready boom view lithium ontario view mesothermal vein gold deposit view top technology storey bitcoin price surge view datawind ceo talk mobile data view electric vehicle drive cleant view big bioprin view cybersecurity venture release view printing material driv view top life science storey top nasdaq biotech stock cell view invest life science view invest biotech view medx health corp announce ontar view marina biotech announce resignat view delmar pharmaceutical present view popular stock galaxy resource view nemaska lithium view danakali ltd view formation metal view dajin resource view brixton metal view tweet download free report resource investing resource forecast expert opinion covering precious metal energy critical metal gold trend gold outlook key highlight investor base metal opinion expert ceos lithium stock price analyst ceos graphite new graphite mining graphite stock buy lme copper copper etf understanding today copper price investing copper rare earth new rare earth metal price investing lithium stock post rockwood lithium potash stock potash new agriculture investing opportunity investing today critical metal context lynas new molycorp new silver highest price silver come potash type potash potash stock uranium price forecast top uranium stock watch invest platinum stock future hold lonmin amcu south african platinum production investing opportunity lme price base metal new investing tungsten tungsten price tungsten demand tungsten company glance zinc commodity new zinc market outlook coal price forecast type coal coal price coal stock forecasting oil price investing wisely top oil producing country palladium price forecast palladium investment opportunity investing medical cannabis information cannabis legal cannabis stock investing stornoway diamond canadian diamond mine diamond price calculator gold good investment gold price today future gold price prediction kitco mint sold out top article resource investing new gold trend gold outlook key highlight investor lithium stock price analyst ceos resource forecast expert opinion covering precious metal energy critical metal industrial metal oversupply market base metal opinion expert ceos energy investing outlook moving carbon agriculture investing opportunity forecast precious metal outlook ceos analyst gold silver platinum palladium critical metal outlook potential lme copper copper etf understanding today copper price investing copper kitco mint sold out top article resource investing new gold good investment gold price today future gold price prediction investing lithium stock post rockwood lithium free lithium investing newsletter free uranium investing newsletter life science investing life science investing primer finding opportunity medtronic ariad pharmaceutical pharmacyte investing pharmaceutical company pharmaceutical new top pharmaceutical stock buy biotech investing new top biotech company biotech stock life science investing ethic app revolution tech investing understanding bitcoin bitcoin mining bitcoin rate nanotechnology nanotech application nanotech investing investing graphene company graphene cost graphene property graphene market future printing company printing stock buy tech investing primer bitcoin rate printing company instagram stock cleantech investing clean technology investor technology investing trend outlook successful technology investing browse topic resource investing agriculture investing cannabis investing phosphate investing potash investing base metal investing copper investing iron investing lead investing nickel investing zinc investing critical metal investing cobalt investing graphite investing magnesium investing manganese investing rare earth investing scandium investing tantalum investing tellurium investing tungsten investing energy investing gas investing lithium investing oil gas investing oil investing uranium investing gem investing diamond investing industrial metal investing aluminium investing chromium investing coal investing molybdenum investing tin investing vanadium investing precious metal investing gold investing palladium investing platinum investing silver investing tech investing printing investing app investing cleantech investing cloud investing cybersecurity investing data investing fintech investing graphene investing mobile web investing nanotech investing life science investing biotech investing genetic investing longevity investing medical device investing pharmaceutical investing featured stock plateau uraniumemerging uranium district peru peninsula energy featured stock enter log credential remember lost password create password manage account contact privacy policy stock index keyword index browsetopic advertise free report event glossary press release copyright dig media inc investing new network daily new resource investing precious metal gold silver platinum palladium back base metal copper nickel iron lead zinc back critical metal graphite tungsten tantalum scandium cobalt magnesium manganese tellurium rare earth back industrial metal molybendum coal tin aluminium vanadium chromium back energy uranium oil gas oil gas lithium back gem diamond back agriculture potash phosphate cannabis back resource investing back technology investing printing cleantech cloud data back cybersecurity fintech graphene mobile web nanotech technology investing back life science investing biotech pharmaceutical medical device genetic life science investing back free investor report resource free report technology free report life science free report outlook free report back stock resource investing technology investing life science investing back","m_szGeo1":"Canada","m_szSourceType":"source_general","m_szSrcUrl":"http://investingnews.com/daily/resource-investing/energy-investing/uranium-investing/cameco-stock-watch-list/","m_Places":["Tin","Mobile","Outlook","Canada","United States","Australia","Mcarthur","New York","Toronto","Fukushima","Japan","Best","Northern Saskatchewan","Denison","Well","Meta","Greenland","Denmark","Ontario","Delmar","Most","Rockwood","Outlooks","Uranium District","Peru","Enter"],"m_People":["Diamond Price","Teresa Matich","David Sadowski","Diamond Mines"],"m_Companies":["Daily News","Palladium","Cleantech","Fintech","Special Report","Toronto Stock Exchange","Tsunami","Wheeler River Project","Raymond James","Motley Fool","Target","Top Technology","Datawind","Top Nasdaq","Medx Health Corp.","Danakali Ltd.","Lonmin","Tungsten Companies","Us Mint","Medtronic","Ariad Pharmaceuticals","Top Biotech Companies","Revolution","Graphene Companies","Printing Companies","Dig Media Inc."],"m_BiGrams":["life science","uranium price","resource investing","science investing","free report","technology investing","uranium investing","cameco stock","critical metal","precious metal","base metal","price forecast","rare earth","oil gas","investing life","stock price","industrial metal","stock watch","largest uranium","top uranium","uranium stock","lithium stock","price investing","gold price","investing new","metal investing","investing back","investing precious","metal gold","gold silver","silver platinum","platinum palladium","investing technology","investing printing","mobile web","investing biotech","medical device","investing free","report resource","nexgen energy","download free","future outlook","outlook uranium","forecast top","view top","stock buy","investing copper","investing lithium","agriculture investing","investing opportunity","tech investing"],"m_TriGrams":["life science investing","uranium price forecast","top uranium stock","investing precious metal","gold silver platinum","silver platinum palladium","resource investing technology","science investing biotech","future outlook uranium","outlook uranium price","price forecast top","forecast top uranium","uranium stock watch"],"m_SocialTags":[],"m_Topics":[],"m_Industry":[],"m_Technology":[],"m_BiCnt":[14,11,10,10,10,8,8,8,7,6,6,6,5,5,5,5,4,4,4,4,4,4,4,4,4,4,4,3,3,3,3,3,3,3,3,3,3,3,3,3,3,3,3,3,3,3,3,3,3,3,3],"m_TriCnt":[10,4,4,3,3,3,3,3,3,3,3,3,3],"m_iDocBodyWordCnt":1429}
