{"m_szDocID":"298725","m_szDocTitle":"NexGen Energy Makes Another Game Changing Discovery - Investing News Network","m_szYear":"2016","m_szDocSumamry":"UraniumInvesting News Your trusted source for investing success Uranium Member? Login Menu Daily News Resource Investing Precious Metals Gold Silver Platinum Palladium Base Metals Copper Nickel Iron Lead Zinc Critical Metals Graphite Tungsten Tantalum Scandium Cobalt Magnesium Manganese Tellurium Rare Earth Industrial Metals Molybendum Coal Tin Aluminum Vanadium Chromium Energy Uranium Oil Gas Oil and Gas Lithium Gem Diamond Agriculture Potash Phosphate Cannabis About Resource Investing Technology Investing 3D Printing Cleantech Cloud Data Cybersecurity Fintech Graphene Mobile Web Nanotech Abo","m_szDocBody":"uraniuminvesting new trusted source investing success uranium member menu daily new resource investing precious metal gold silver platinum palladium base metal copper nickel iron lead zinc critical metal graphite tungsten tantalum scandium cobalt magnesium manganese tellurium rare earth industrial metal molybendum coal tin aluminium vanadium chromium energy uranium oil gas oil gas lithium gem diamond agriculture potash phosphate cannabis resource investing technology investing printing cleantech cloud data cybersecurity fintech graphene mobile web nanotech technology investing life science investing biotech pharmaceutical medical device genetic life science investing free investor report resource free report technology free report life science free report outlook free report stock resource investing technology investing life science investing uranium investing nexgen energy make game changing discovery result hole arc included intercept metre offscale mineralization shear cameco stock top tsx stock golden teresa matich add comment nexgen energy tsxvnxe announced discovered potential zone highgrade uranium mineralization rook property saskatchewan athabasca basin new based preliminary result single hole untested area property nexgen stated hole represent strongest uranium intercept shear zone date analyst pegging new game changer company result hole arc includedan intercept metre offscale mineralization shear nexgen reported substantial intersection offscale radioactivity highgrade domain including metre total composite mineralization expert guide uranium investing free download free special reporturanium future outlook uranium price forecast top uranium stock watch importance discovery grade mineralization shear evident drill hole arc encountered strongest widest mineralization shear date saidgarrett ainsworth vice president exploration development nexgen statement grade intercept hole large untested area shear potential host grade subzone explained hole infilled confirmed grade continuous subvertical nature grade domain rob chang cantor fitzgerald agreed result significant today release nexgen announce discovery grade intercept lead identification grade zone similar emailed statement turn case arrow move closer level mcarthur river cigar lake david sadowski raymond jamesalso see potential shear zone host alike highgrade mineralization statingthat hole gamechanger company raise target total contained metal possibility added analyst upside nexgen certainly uranium investor wondering time nexgen share company gained impressive percent start percent past yearhowever bothchang sadowski stock upside potential momentum continue stock arrow increasingly appear oneinacycle discovery sadowski said giving nexgen strong buy rating target price nexgen trading admitted easy cautious nexgen share price technical perspective price jump year notedthat nexgen sitting roughly percent hathor exploration takeout value hathor discovered roughrider uranium deposit saskatchewan acquired riotinto nyseriolserio million uranium future outlook uranium price forecast onward analyst uranium price moving short long term read thefull article furthermore raymond jamess analysis suggest acquire nexgen percent premium company current share price build arrow project make accretive deal uranium price pound uranium firm believe percent premium justified note released earlier month sadowski made case nexgen acquisition target forcameco tsxcconyseccj order producer reduce technical risk production pipeline rob chang stated nexgen remain cantor top pick buy rating target price what next course nexgen plenty work term exploring potential zone company continue drilling northwestazimuth scissor hole zone part metre spring breakup drilling programme investor doubt watching closely result that nexgen stated remain track release updated resource estimate arrow deposit half year mentioned nexgen trading share company gained percent thursday new expert guide uranium investing free download free special reporturanium future outlook uranium price forecast top uranium stock watch dont forget follow realtime new update security disclosure teresa matich hold direct investment interest company mentioned article latest uranium investing stock information latest information company uranium investing delivered directly inbox uraniumanfield resourcesenergy fuelsforum uraniumkivalliq energypeninsula energyplateau uraniumwestern uraniumselect select selecting company company above giving consent receive company remember unsubscribe time uranium future outlook uranium price forecast onward analyst uranium price moving short long term read thefull article return uranium investing index meta data cameco stock top tsx stock golden related post top uranium stock yeartodate nexgen announce appointment charle scorer special advisor uranium marketing uranium export legislation passed greenland denmark solid foundation set asx listed greenland mineral energy forum uranium wellpositioned athabasca highgrade uranium discovery nexgen energy announce assay result tag athabasca basin cameco cantor fitzgerald ccj david sadowski lead lserio mcarthur river nexgen energy nxe nyseccj nyserio raymond jame rio tinto riolse rob chang saskatchewan tsx tsxcco tsxv tsxvnxe uranium uranium investor uranium price zinc supply comment leave reply cancel reply required will published required comment market top resource storey uranium ready run view top tsx stock gold mining sto view silver mining canada view cobalt ready boom view lithium ontario view mesothermal vein gold deposit view top technology storey bitcoin price surge view datawind ceo talk mobile data view electric vehicle drive cleant view big bioprin view cybersecurity venture release view printing material driv view top life science storey top nasdaq biotech stock cell view invest life science view invest biotech view medx health corp announce ontar view marina biotech announce resignat view delmar pharmaceutical present view popular stock galaxy resource view nemaska lithium view danakali ltd view formation metal view dajin resource view brixton metal view tweet download free report resource investing resource forecast expert opinion covering precious metal energy critical metal gold trend gold outlook key highlight investor base metal opinion expert ceos lithium stock price analyst ceos graphite new graphite mining graphite stock buy lme copper copper etf understanding today copper price investing copper rare earth new rare earth metal price investing lithium stock post rockwood lithium potash stock potash new agriculture investing opportunity investing today critical metal context lynas new molycorp new silver highest price silver come potash type potash potash stock uranium price forecast top uranium stock watch invest platinum stock future hold lonmin amcu south african platinum production investing opportunity lme price base metal new investing tungsten tungsten price tungsten demand tungsten company glance zinc commodity new zinc market outlook coal price forecast type coal coal price coal stock forecasting oil price investing wisely top oil producing country palladium price forecast palladium investment opportunity investing medical cannabis information cannabis legal cannabis stock investing stornoway diamond canadian diamond mine diamond price calculator gold good investment gold price today future gold price prediction kitco mint sold out top article resource investing new gold trend gold outlook key highlight investor lithium stock price analyst ceos resource forecast expert opinion covering precious metal energy critical metal industrial metal oversupply market base metal opinion expert ceos energy investing outlook moving carbon agriculture investing opportunity forecast precious metal outlook ceos analyst gold silver platinum palladium critical metal outlook potential lme copper copper etf understanding today copper price investing copper kitco mint sold out top article resource investing new gold good investment gold price today future gold price prediction investing lithium stock post rockwood lithium free lithium investing newsletter free uranium investing newsletter life science investing life science investing primer finding opportunity medtronic ariad pharmaceutical pharmacyte investing pharmaceutical company pharmaceutical new top pharmaceutical stock buy biotech investing new top biotech company biotech stock life science investing ethic app revolution tech investing understanding bitcoin bitcoin mining bitcoin rate nanotechnology nanotech application nanotech investing investing graphene company graphene cost graphene property graphene market future printing company printing stock buy tech investing primer bitcoin rate printing company instagram stock cleantech investing clean technology investor technology investing trend outlook successful technology investing browse topic resource investing agriculture investing cannabis investing phosphate investing potash investing base metal investing copper investing iron investing lead investing nickel investing zinc investing critical metal investing cobalt investing graphite investing magnesium investing manganese investing rare earth investing scandium investing tantalum investing tellurium investing tungsten investing energy investing gas investing lithium investing oil gas investing oil investing uranium investing gem investing diamond investing industrial metal investing aluminium investing chromium investing coal investing molybdenum investing tin investing vanadium investing precious metal investing gold investing palladium investing platinum investing silver investing tech investing printing investing app investing cleantech investing cloud investing cybersecurity investing data investing fintech investing graphene investing mobile web investing nanotech investing life science investing biotech investing genetic investing longevity investing medical device investing pharmaceutical investing featured stock plateau uraniumemerging uranium district peru peninsula energy featured stock enter log credential remember lost password create password manage account contact privacy policy stock index keyword index browsetopic advertise free report event glossary press release copyright dig media inc investing new network daily new resource investing precious metal gold silver platinum palladium back base metal copper nickel iron lead zinc back critical metal graphite tungsten tantalum scandium cobalt magnesium manganese tellurium rare earth back industrial metal molybendum coal tin aluminium vanadium chromium back energy uranium oil gas oil gas lithium back gem diamond back agriculture potash phosphate cannabis back resource investing back technology investing printing cleantech cloud data back cybersecurity fintech graphene mobile web nanotech technology investing back life science investing biotech pharmaceutical medical device genetic life science investing back free investor report resource free report technology free report life science free report outlook free report back stock resource investing technology investing life science investing back","m_szGeo1":"Canada","m_szSourceType":"source_general","m_szSrcUrl":"http://investingnews.com/daily/resource-investing/energy-investing/uranium-investing/nexgen-energy-new-high-grade-zone/","m_Places":["Tin","Mobile","Outlook","Saskatchewan","Mcarthur","United States","Meta","Greenland","Denmark","Well","Canada","Ontario","Delmar","Most","Best","Rockwood","Outlooks","Uranium District","Peru","Enter"],"m_People":["Teresa Matich","Diamond Price","Garrett Ainsworth","Rob Chang","David Sadowski","Diamond Mines"],"m_Companies":["Daily News","Palladium","Cleantech","Fintech","Special Report","Raymond James","Target","Rio Tinto","Top Technology","Datawind","Top Nasdaq","Medx Health Corp.","Danakali Ltd.","Lonmin","Tungsten Companies","Us Mint","Medtronic","Ariad Pharmaceuticals","Top Biotech Companies","Revolution","Graphene Companies","Printing Companies","Dig Media Inc."],"m_BiGrams":["life science","resource investing","science investing","free report","uranium price","technology investing","uranium investing","critical metal","price forecast","precious metal","base metal","rare earth","oil gas","investing life","industrial metal","nexgen energy","mineralization shear","future outlook","outlook uranium","top uranium","uranium stock","lithium stock","price investing","gold price","investing new","metal investing","investing back","investing precious","metal gold","gold silver","silver platinum","platinum palladium","investing technology","investing printing","mobile web","investing biotech","medical device","investing free","report resource","hole arc","top tsx","tsx stock","download free","forecast top","stock watch","rob chang","view top","stock buy","investing copper","investing lithium","agriculture investing","investing opportunity","tech investing"],"m_TriGrams":["life science investing","uranium price forecast","future outlook uranium","outlook uranium price","top uranium stock","investing precious metal","gold silver platinum","silver platinum palladium","resource investing technology","science investing biotech","top tsx stock","price forecast top","forecast top uranium","uranium stock watch"],"m_SocialTags":[],"m_Topics":[],"m_Industry":[],"m_Technology":[],"m_BiCnt":[14,10,10,10,9,8,8,7,7,6,6,5,5,5,4,4,4,4,4,4,4,4,4,4,4,4,4,3,3,3,3,3,3,3,3,3,3,3,3,3,3,3,3,3,3,3,3,3,3,3,3,3,3],"m_TriCnt":[10,5,4,4,4,3,3,3,3,3,3,3,3,3],"m_iDocBodyWordCnt":1463}
