{"m_szDocID":"30251","m_szDocTitle":"Drivers urged to hire electric cars in new scheme planned by London Mayor | Daily Mail Online","m_szYear":"2004","m_szDocSumamry":"Drivers urged to hire electric cars in new scheme planned by London Mayor Â  comments Boris Johnson is planning an electric car hire scheme for London in which users pick up a battery-powered vehicle in one part of the city and drop it off in another. The Mayor said today he wanted to make London a 'world leader' in the promotion of the environmentally-friendly vehicles. He added: 'At this stage it is important to ensure we fully understand the potential market for electric vehicles in London so that we can trigger a demand for this type of technology. My goal is for London to become the electr","m_szDocBody":"driver urged hire electric car scheme planned london mayor comment boris johnson planning electric car hire scheme london user pick batterypowered vehicle part city drop another mayor today wanted make london world leader promotion environmentallyfriendly vehicle added stage important ensure fully understand potential market electric vehicle london trigger demand type technology goal london electric vehicle capital europe plan mirror paris scheme place end year boris johnson london electric vehicle capital europe autolib car programme modelled highly successful bicyclehire scheme electric car sited french capital suburb driver time brainchildof socialist mayor bertrand delanoe pickup point established city underground delanoe scheme system individual journey completely clean car released credit card preordered subscription card johnson announced plan bring bicycle capital year run similar paris bicycle hire scheme mayor pledged extra funding network car recharging point westminster set forum aimed increasing number electric car sale electric car small biggest problem scheme installing electric charging point cost each westminster council charging point street point car park however londonwide blueprint expert hundred charging bay needed common written answer transport minister jim fitzpatrick total batterypowered vehicle registered total batterypowered car uks road year commenting plan london caroline watson energy saving trust said this brilliant idea kind innovative leadership need electric vehicle new untested technology great people test technology londoner car hire scheme easy need paris price month suggested drive mile day delanoe doubled projected number car expanded target area ring road electric car expected bigger smart car delanoe said there computerised system collect car announce drop off parking space available target young couple children occasionally car shop travel afford run own tourist enjoy freedom car worry use green party councillor paris warned encouraging public type car giving incentive stick bike public transport bad move denis baupin green party deputy mayor said scheme encourage people pick car day work back bike metro crowding road changing habit problem meeting london electric vehicle partnership late year representative motor energy industry london borough agreed plan sharply increase electric car city ","m_szGeo1":"United Kingdom","m_szSourceType":"source_news","m_szSrcUrl":"http://www.dailymail.co.uk/news/article-1158470/Drivers-urged-hire-electric-cars-new-scheme-planned-London-Mayor.html","m_Places":["London","Europe","Paris","Westminster","Uk"],"m_People":["Drivers","Boris Johnson","Bertrand Delanoe","Delanoe","Johnson","Jim Fitzpatrick","London, Caroline","Denis Baupin"],"m_Companies":["Watson","Target","Green Party"],"m_BiGrams":["electric car","electric vehicle","hire scheme","london electric"],"m_TriGrams":["london electric vehicle"],"m_SocialTags":[],"m_Topics":[],"m_Industry":[],"m_Technology":[],"m_BiCnt":[7,5,3,3],"m_TriCnt":[3],"m_iDocBodyWordCnt":329}
