{"m_szDocID":"31876","m_szDocTitle":"Network Rail electrifies station car parks | Next Green Car","m_szYear":"2015","m_szDocSumamry":"clear all 4.7.2013Network Rail electrifies station car parks ChargePoint Services and Network Rail have today announced the installation of an eight vehicle electric charging facility at its public car parks at Euston and Victoria railway stations in central London. The installation is part of Network Rail's on-going sustainability strategy, which aims to make commuting via the rail network the greenest way to travel. ChargePoint Services worked alongside Network Rail to help develop this initiative and install a solution to meet Network Rail's specific EV charging requirements. The solution i","m_szDocBody":"clear network rail electrify station car park chargepoint service network rail today announced installation vehicle electric charging facility public car park euston victoria railway station central london installation part network rail ongoing sustainability strategy aim make commuting rail network greenest travel chargepoint service worked alongside network rail develop initiative instal solution meet network rail specific charging requirement solution installed include dual socket durastation pedestal unit euston victoria station car park providing amp type mode fast charging electric vehicle unit gpr networked rfid compliant source london pip scheme monitored managed chargepoint back office system liz ratcliffe account manager car parking network rail said rail greenest form travel strategy aim make greener still providing charge point electric vehicle car park boost rail user chosen environmentally cleaner vehicle journey station enabling user recharge electric vehicle station car park facilitate choice environmentally cleaner vehicle commute train part journey doortodoor recharging vehicle station obvious choice driver electric hybrid vehicle pleased network rail provide facility customer part drive reduce doortodoor carbon emission alex bamberg managing director chargepoint service ltd said were pleased charge point supplier instal public charge point railway station network rail great understanding joining journey provide totally green solution customer forward continuing work alongside rolling round site offering public charging john mason transport london director responsible source london said these charge point addition source london scheme publicly accessible point capital provide option member travelling london rail service guarantee charge point one growth electric vehicle market encouraging building infrastructure support vehicle expect accessible half million rail user travelling london terminal morning evening begun journey car trip local station network rail aim reduce carbon footprint journey encourage this offer reduced price parking season ticket month driver electric vehicle leaving vehicle network rail car park charging point publicly accessible electric vehicle charging point visit green car zapmap ","m_szGeo1":"United Kingdom","m_szSourceType":"source_news","m_szSrcUrl":"http://www.nextgreencar.com/news/6259/network-rail-electrifies-station-car-parks/","m_Places":["Victoria","London","Victoria Station","Bamberg","Uk"],"m_People":["Euston","Liz Ratcliffe","Alex","John Mason"],"m_Companies":["Transport For London","Zap"],"m_BiGrams":["network rail","car park","electric vehicle","charge point","station car","chargepoint service","source london"],"m_TriGrams":["station car park"],"m_SocialTags":[],"m_Topics":[],"m_Industry":[],"m_Technology":[],"m_BiCnt":[10,6,6,5,3,3,3],"m_TriCnt":[3],"m_iDocBodyWordCnt":300}
