{"m_szDocID":"34803","m_szDocTitle":"Silent electric car knocks over pedestrian because she 'didn't hear it coming' | Daily Mail Online","m_szYear":"2016","m_szDocSumamry":"Silent electric car knocks over pedestrian because she 'didn't hear it coming' Â  Whoops! Silent electric car knocks over pedestrian because she 'didn't hear it coming' just hours after launch of vehicle-sharing scheme Woman struck on day Autolib' scheme starts in Paris Injured hip, shoulder and face, but not life-threatening Ironically, program aims to cut NOISE pollution comments It was launched to great fanfare as the much-sought-after solution to noise and air pollution on the streets of Paris. But the French capital's new car-sharing programme was dealt a rather embarrassing blow when one ","m_szDocBody":"silent electric car knock pedestrian didnt hear coming whoop silent electric car knock pedestrian didnt hear coming hour launch vehiclesharing scheme woman struck day autolib scheme start paris injured hip shoulder face lifethreatening ironically programme aim cut noise pollution comment launched great fanfare muchsoughtafter solution noise air pollution street paris french capital carsharing programme dealt embarrassing blow silent electric car knocked pedestrian apparently hear coming police woman struck crossed rue taine city arrondissement yesterday hour autolib programme running quiet car autolib vehiclesharing programme paris knocked pedestrian apparently hear unfortunate accident happened pedestrian stepped road rue taine pictured arrondissement believed pedestrian walked road light saintantoine hospital pain hip shoulder bruise face injury lifethreatening related article share share mayor paris bertrand delanoe launched autolib programme unfortunate accident evidence suggest connexion crash fact car silent autolib built success city bike rental scheme boris bike london attempt reduce noise air pollution paris claim biggest programme kind vehicle street yesterday expected summer year smile vincent bollore second left ceo investment bollore paris mayor bertrand delanoe right inauguration autolib service paris yesterday fourseat bluecar called powered lithium metal polymer battery product collaboration italian car designer pininfarina french conglomerate groupe bollore user valid driver licence credit card online videoconference customer service representative special glassedin shelter paris standard subscription cost euros day euros week euros year ","m_szGeo1":"United Kingdom","m_szSourceType":"source_news","m_szSrcUrl":"http://www.dailymail.co.uk/news/article-2070812/Silent-electric-car-knocks-pedestrian-didnt-hear-coming.html","m_Places":["Paris","London","Id"],"m_People":["Rue Taine","Antoine","Bertrand Delanoe","Boris","Vincent Bollore","Bollore","Pininfarina"],"m_Companies":["Police","Seat"],"m_BiGrams":["silent electric","electric car","hear coming"],"m_TriGrams":["silent electric car"],"m_SocialTags":[],"m_Topics":[],"m_Industry":[],"m_Technology":[],"m_BiCnt":[3,3,3],"m_TriCnt":[3],"m_iDocBodyWordCnt":218}
