{"m_szDocID":"36417","m_szDocTitle":"Honda Kicks Off 'Year of Honda' Innovations at 2015 North American International Auto... -- DETROIT, Jan. 13, 2015 /PRNewswire/ --","m_szYear":"2015","m_szDocSumamry":"Pinterest × Honda Display at the 2015 North American International Auto Show features the HondaJet, FCV Concept, past and new Honda Formula 1 cars and more Honda Logo. DETROIT, Jan. 13, 2015 /PRNewswire/ -- Calling 2015 the \"Year of Honda,\" the company is showcasing multiple innovative products and technologies on the international stage at the 2015 North American International Auto Show that will make 2015 an extraordinary year for the company and its customers. Making its first North American appearance, the Honda FCV Concept demonstrates the company's continued evolution of its next-generat","m_szDocBody":"pinterest honda display north american international auto show feature hondajet fcv concept past honda formula car honda logo detroit jan calling year honda company showcasing multiple innovative product technology international stage north american international auto show make extraordinary year company customer making north american appearance honda fcv concept demonstrate company continued evolution nextgeneration fuel cell car slated introduction effort showcase hondas numerous innovative technology wideranging mobility prowess automaker showcased hondajet advanced light jet global unveiling highly anticipated acura nsx midengine supercar unicub personal mobility device return honda formula racing automaker world depth r&d knowhow experience create diverse array advanced technology product bring market john mendel executive vice president american honda motor inc these allnew product technology represent significant advancement customer future mobility everywhere innovation comprehensive mobility company honda achieve year honda marked introduction iconic innovative product expression hondas racing spirit customer delivery north carolinamade hondajet advanced light jet powered gehonda turbofan engine begin year federal aviation administration type certification achieved nextgeneration acura nsx supercar begin order late summer customer delivery expected year honda racing power form power unit litre turbocharged engine hybridtype kinetic thermal energy recovery system return formula hondas partnership mclaren driver fernando alonso jenson button beginning opening race sery melbourne australia company announced aggressive plan future product technology introduction including introduction hondas nextgeneration fuel cell vehicle highlighted stunning design spacious interior honda fcv concept allnew battery electric vehicle allnew plugin hybrid vehicle application hondas two threemotor hybrid system part phase hondas commitment advanced powertrain technology enable ultralow carbon mobility spring launch allnew hrv crossover introduction summer fully redesigned pilot passenger suv ridgeline pickup truck part stepbystep strengthening honda light truck lineup fuel future growth end year honda begin introduce cylinder vtec turbo engine extension earth dream technology powertrain lineup deliver funtodrive performance fuel efficiency level production vtec turbo engine begin year hondas anna ohio engine plant largest automobile engine plant hondas global production network honda investing million anna engine plant produce vtec turbo cylinder engine assembly line production cylinder engine additional manufacturing innovation american honda honda established operation america employ associate north american sale r&d manufacturing operation total capital investment north america exceeding billion based longstanding commitment build product close customer honda operate major manufacturing facility north america producing wide range honda acura automobile automobile engine transmission honda allterrain vehicle power equipment product lawn mower minitiller general purpose engine hondajet advanced light jet honda auto plant region including capacity produce million automobile year percent honda acura automobile sold produced north america plant today manufacture model including passenger car light truck domestic globally sourced partsa auto plant performance manufacturing centre construction marysville ohio exclusive global production location generation nsx supercar honda operate major research development centre capacity fully design develop engineer product honda produce north america ","m_szGeo1":"United States","m_szSourceType":"source_news","m_szSrcUrl":"http://www.prnewswire.com/news-releases/honda-kicks-off-year-of-honda-innovations-at-2015-north-american-international-auto-show-300019948.html","m_Places":["Detroit","Uni","North Carolina","Melbourne, Australia","Ohio","America","North America","Marysville, Ohio"],"m_People":["John Mendel","Mclaren","Fernando Alonso","Jenson","Turbo"],"m_Companies":["Pinterest","Honda","International Auto Show","Logo","Formula One","American Honda Motor Co","Federal Aviation Administration"],"m_BiGrams":["north american","year honda","north america","fcv concept","product technology","hondajet advanced","advanced light","light jet","vtec turbo","engine plant"],"m_TriGrams":["hondajet advanced light","advanced light jet"],"m_SocialTags":[],"m_Topics":[],"m_Industry":[],"m_Technology":[],"m_BiCnt":[4,4,4,3,3,3,3,3,3,3],"m_TriCnt":[3,3],"m_iDocBodyWordCnt":457}
