{"m_szDocID":"43599","m_szDocTitle":"News:Archive:2014:February - PESWiki","m_szYear":"2014","m_szDocSumamry":"textArticle -------------------- News:Archive:2014:February Click here for most recent news. 2014 News:Archive:2014:March - going forward in time February Friday, February 28, 2014 The Ultimate Power Grab - ...\"power grabs\" by the powers that be, including new road taxes to extract money from electric vehicle drivers that are not buying gas. They also address the \"smart grid\" that isn't so smart and doesn't save money. (Free Energy Blog; February 28, 2014) Featured : News > SmartScarecrow > This Week in Free Energy™ > This Week in Free Energy™: February 27, 2014: Last Smartscarecrow Episode - ","m_szDocBody":"newsarchivefebruary recent new newsarchivemarch forward time friday ultimate power grab power grab power including road taxe extract money electric vehicle driver buying gas address smart grid smart save money free energy blog featured new smartscarecrow week free energy week free energy smartscarecrow episode jerry smith modern benjamin franklin smart scarecrow show close lattice energy lenr process create gold platinum raul melendre free energy cell phone charger skycollection close loop les kraut instruction crystal battery generator freeenergynew michael tellinger tour europe this spring tour france holland germany austria switzerland information electronic measurement stone circle adam calendar pyramid close devising newera free energy device based ancient technology free energy blog thursday featured electromagnetic qmogen raul melendre free energy cell phone charger philippine inventor malendre posted video description charge cell phone unlimited power free energy cellphone charger anytime place planet tiny qmogen pesn wednesday epic extreme earth change event line weather control compilation extreme weather event worst ever worst year event point mantra weather controller youre awful job stop mother nature thing help free energy blog featured nuclear lenr lattice energy llc lenr process create gold platinum metal specialist kitco report chicago company headed lewis larsen widomlarsen theory moving forward r&d process creating energy creating precious metal time peswiki tuesday world largest solar thermal power tower open mojave desert significant development renewable energy free energy blog simple way clean air plant room recommended local nursery produce oxygen remove toxin air philtre switch cleaning supply remove chemicalbased air freshener free energy blog photos gilman rar energia rar energia posted couple photos gilman facility website there ahead photos posted week earlier design amazing quest free energy blog les kraut instruction crystal battery generator add water simply put make small copper container insert rod magnesium fill space magnesium copper solution borax form crystalline matrix connect magnesium copper simple joule thief circuit long crystal solution hydrated produce small amount electricity free energy blog monday donation surreal gate dia amazing synchronistic symbolism arisen conjunction fundriaser donation drive pes free energy blog saturday featured billion dollar budget versus grocery money plea wondering loan money make end meet putting donation hat cusp energy solution world need pesn friday featured top electromagnetic qmogen platinum invest explanation battery shown palladium demo motor shipped air wfe exhibition abu dhabi hydromagnetic deemed insert battery motor facilitate transport custom clearance reason battery needed start recharged system running pesn wednesday prolonging battery life make solar plausible earthship let begin small system comparison charge discharge battery time destroy circuit separate battery loaded free energy blog free energy nehilo free energy matter harvesting wheelwork nature lot way that free energy refer fact pay wheelwork nature provide energy plug free energy blog tuesday featured top electromagnetic qmogen platinum invest palladium magnetic engine display licencing abu dhabi palladium released back started demonstration potential agent exclusive import distribution partner coming signing position emphasise selling direct client pesn monday onering phone scam bank people curiosity nationwide surge scam show thieve prey people curiosity scammer call random cell phone number ring once bait call back face huge fee free energy blog tpu website progress website subscriber forum free energy blog jet stream extreme weather warmer arctic permanently affect pattern highaltitude polar jet stream resulting longer colder winter north america northern europe scientist say free energy blog meg demo lee kenny link fixed the motionless electromagnetic generator meg device consist sery specialised permanent magnet collector coil switching circuitry alternate concentration magnetic flux apparatus extract usable electric energy free energy blog sunday mike kantz announce electromagnetic resonance regenerative power looping kit link fixed mike introduce disruptive capacitive discharge circuit unexpected result holding tight vest month making announcement kit personally experiment input primary coil resonance output secondary coil free energy blog auroratek post product investor plan jetson scooter retail price msrp imagine attaching battery charger recharge electric scooter again technology plan make size battery charger selfsustainable power supply ssp free energy blog saturday mclass flare hour watch continuation extreme weather event rapid temperature shift wind increased earthquake volcanic activity free energy blog hutchison effect mahabharata acoustic levitation there war talking war fan father electromagnetic theory thomas edison nikola tesla free energy blog friday featured new smartscarecrow week free energy week free energy keppe motor universe ceiling fan certification platinum invest booth world future energy summit abu dhabi rar energia post gilman photos midtech dominator video price list meet seimen turbine design streven transfusor nuclear variant kapanadze spitzauer trial postponed chemtrail sky writing phish freeenergynew hot fusion finally break far cold fusion meanwhile cold fusion lenr frequently called mislabeled junk science mainstream science achieved overunity long ago leading companing bringing market region free energy blog thursday christopher streven transfusor nuclear variant kapanadze kapanadze device take energy nuclear reaction nuclear fusion deuterium air attempting construct similar device air ntp huge coil generating conducting plasma inside winding low pressure air ionised plasma generator turned reaction start neutron generated hen reaction free energy blog wednesday midtech turbine design turbine doug myer midtech the big boss siemen coming week turn ebay midtech design free energy blog featured electromagnetic keppe keppe motor universe ceiling fan certification efficient certification company testtech laboratory verified universe keppe motor ceiling fan are efficient economical brazilian market category certification ceiling fan fully ready massproduction commercial rollout worldwide pesn big phish storey minute phone legitimate verizon upgrade offer got iphone received message allegedy verizon wasnt macbook pro free energy blog tuesday featured electromagnetic qmogen platinuminvest platinum invest booth world future energy summit abu dhabi wfe world foremost event dedicated renewable energy energy efficiency clean technology palladium generator unit displayed conference providing presently confidential reason day understand appreciate pesn monday midtech poised meet seimen turbine doug meet big boss siemen week turbine them also dialogue black box dominator spec free energy blog sunday featured conspiracy chemtrail chemtrail sky writing prove contrail link fixed sky writing videos circulating presently classical methodology smoke happen jetliner wrote message tool denied exist chemtrail snowden level whistle blowing world ignore pesn rar energia post gilman photos folk posted photos gilman illinois usa installation progressing rapidly porto alegrer brazil facility did free energy blog midtech release black box dominator price list offer unit wind solar primary power source plugin rapid efficient recharing battery grid power available system run include dominator box charger watt air shark turbine watt solar panel battery free energy blog midtech post black box dominator video motorgenerator operation still require plugin selflooped bit quiet window air conditioner unit output hurried customer pennsylvania power outage recent storm purchase free energy blog saturday spitzauer trial postponed spitzauer remain federal custody district judge granted request spitzauer federal prosecutor postpone trial prepare complex case discovery document expected exceed page free energy blog friday featured new smartscarecrow week free energy week free energy blacklight power demo video lenrtomarket digest midtech wasif kahloon magnet motor challenge open source nathan larson orbital magnetic engine keshe solution fukushima bedinilindemann conf lpp nyc public event infinite energy interview alan francoeur freeenergynew alex jone the free energy scam versus real player responding caller alex bemoan scam there including clean energy project supported government real player free energy blog thursday featured pes network loan pes network opportunity exotic free energy destined emerge network key player facilitating process worldwide way pes benefit financially include finder fee commission sale open source involvement increased revenue increased traffic sponsorship pesn midtech release feel completely ready releasing supplement box completely compatible black box completion free energy blog master terror alex jone full documentary documentary produced lot excellent material lot documentation inside job planning execution subsequent coverup free energy blog wednesday youth contest invent make world place youth visit leonardo vinci you minimum opportunity bring needed awareness exotic free energy doubt inventor mind sketched variation invention contest free energy blog featured exotic nuclear lenr lenrtomarket digest highlight week include nanor availability announced cold fusion mit blackligh power demo video justin church hcat passing sven kullander founding sceptic john huizenga inquiring mind revisit cold fusion pesn lpp nyc public event lpp focus fusion organising raise spring small contributor money final year research focus fusion approach fusion energy free energy blog interview alan francoeur magnetic energy system righthandrule key factor wound synchronise winding polarity maximum energy coil minimal losse nature doe ema power supply running free energy blog redflex bribing city instal surveillance cameras redflex traffic system embroiled million bribery scandal chicago year top exec aaron rosenberg fired amidst scandal now working fed expose company regularly bribing city official nation encourage instal stop light camera system free energy blog tuesday cold fusion magazine infinite energy magazine infinite energy conceptual unification energy mass gravity duncan move scientific commercial overview iccf fundamental process energy transmutation experiment nuclear fusion schrdinger equation nature fundamental change world book review life centre energy crisis model atomic nucleus blacklight power demo video posted hour video demonstration event jersey free energy blog wasif kahloon open source magnet motor examine open sourced are interested examining simply give answer question first watch free energy blog latest midtech starting begin building demo model supplement black box picture video building plug play backup power supply black box black box technology multiple charge option wall outlet turbine solar panel vehicle charger complete package turbine solar panel included free energy blog monday featured magnet motor nathan larson orbital magnetic engine nathan prototype achieved full continuous rotation controlled rpm torque gear ratio made totally indexable part testing purpose peswiki monsanto gmo cross polination documentary documentary show power monsanto treat farmer gmo seed destroy food supply monsanto promised gmo seed world reject gmo food good free energy blog sunday wasif kahloon issue magnet motor challenge engineer wasif posted video showing side magnet motor load array showing hidden component though inserted wood base free energy blog saturday week snowden interview traitor media amazing interview snowden hint extent nsas eavesdropping capability espionage talk dismay corruption admire life threatened presstitute america cover free energy blog newsarchivefebruary newsarchivemarch friday ","m_szGeo1":"United States","m_szSourceType":"source_industry","m_szSrcUrl":"http://peswiki.com/index.php/News:Archive:2014:February","m_Places":["Europe","France","Germany","Austria","Switzerland","Philippines","Along","Chicago","Gilman","United States","Abu Dhabi","North America","Jetson","Gilman, Il","Gilman, Illinois","Porto Alegre","Pennsylvania","United States District","Fukushima","Nyc","Best","Gravity","Mo","New Jersey","Starting","America"],"m_People":["Jerry Smith","Benjamin Franklin","Raul Melendres","Michael Tellinger","Lewis Larsen","Lee Kenny","Mike Kantz","Thomas Edison","Christopher Strevens","Even -- Far","Doug Myers","Wasif Kahloon","Nathan Larson","Alan L. Francoeur","Alex Jones","Leonardo Da Vinci","Sven Kullander","John R. Huizenga","Aaron Rosenberg"],"m_Companies":["Lattice Energy Llc","Clean The Air","Dr. Group","Matrix","Dia","Palladium","Us Nationwide","Ul","Ebay","Verizon","Orbital","Keshe Solutions","Google","Fusion Society","Redflex Traffic Systems","Facebook","Monsanto","Nsa"],"m_BiGrams":["free energy","energy blog","black box","week free","cold fusion","magnet motor","blog featured","cell phone","electromagnetic qmogen","rar energia","blog saturday","platinum invest","abu dhabi","ceiling fan","featured new","new smartscarecrow","smartscarecrow week","energy week","blog thursday","featured electromagnetic","extreme weather","energy free","photos gilman","friday featured","blog tuesday","magnetic engine","link fixed","blog sunday","power supply","sky writing","box dominator","solar panel","power demo","demo video","wasif kahloon","open source","infinite energy"],"m_TriGrams":["free energy blog","week free energy","energy blog featured","energy blog saturday","featured new smartscarecrow","new smartscarecrow week","smartscarecrow week free","free energy week","energy week free","energy blog thursday","energy blog tuesday","black box dominator","power demo video"],"m_SocialTags":[],"m_Topics":[],"m_Industry":[],"m_Technology":[],"m_BiCnt":[56,40,7,6,5,5,4,4,4,4,4,4,4,4,3,3,3,3,3,3,3,3,3,3,3,3,3,3,3,3,3,3,3,3,3,3,3],"m_TriCnt":[37,6,4,4,3,3,3,3,3,3,3,3,3],"m_iDocBodyWordCnt":1638}
