{"m_szDocID":"44723","m_szDocTitle":"3 of Our Wildest Predictions for 2015 - NASDAQ.com","m_szYear":"2014","m_szDocSumamry":"Search 3 of Our Wildest Predictions for 2015 December 27, 2014, 04:00:03 PM EDT By Travis Hoium, John Rosevear, and Steve Heller, The Motley Fool, Motley Fool This has been a wild year for those following the stock   market. We've seen new record highs, oil crumble in a matter of   months, and the U.S. economy power along, driven by new   innovations that seemed impossible just a few years ago (think   electric vehicles, solar energy, and Uber). Next year will surely bring its fair share of surprises as   well, so we've rounded up a few predictions about what could happen in 2015. China's econ","m_szDocBody":"wildest prediction edt travis hoium john rosevear steve heller motley fool motley fool wild year stock market record high oil crumble matter month economy power along driven innovation impossible year ago think electric vehicle solar energy uber year surely bring fair share surprise well rounded prediction happen chinas economy grown crazy decade eventually slow doe danger lurk image owned motley fool travis hoium wild but realistic prediction china market crash people risk bubbling chinese economy central government control staterun bank fuel economic growth decade bubble burst spectacular fashion eventually bubble begin burst yearand government scramble increase highquality lending boost economy prop market wall street crash china country economic growth end crack thesis roil market china transparent itseconomic lending data number analyse show alarming credit trend ceic total social financing measure bank loan shadow banking grown chinese gdp gdp today stephen green standard chartered earlier year chinas total social financingtogdp ratio compared debttogdp figure low world reserve currency stable economy handle higher debt load china risk chinas growing credit bubble burst real estate price recently turned negative economic growth slowing chinas government reinin risky lending led credit boom place factor consumer businesse lose confidence asset price fall drop credit market dramatic credit crunch china style predicting financial crisis impossible predict chinas credit bubble burst deflate impact global economy happen bad looming china market beating light printing improved dramatically profit hard image owned motley fool steve heller dprinted crystal ball predict printing company profit difficult spite strong industry growth rate industry insight firm wohler associate printing industry expected grow year compounded eventually generate billion annual revenue worldwide robust industry growth trajectory make investor salivate prospect owning printing stock clear date robust industry growth show bottom line form profit publicly traded printing company granted established player stratasy system represented onethird worldwide printing revenue undergone rapid investment phase depressed profitability short term imply profitability horizon stratasy system pace investment normalise investor mind promise guaranteed company forthe industry large all printing attractive growth potential attracted lot competition hewlettpackard included create pricing pressure difficulttomanage headwind sap future profitability potential industry player fact system major printing company consistently turn profit generally accepted accounting principle basis recent year profit industry notcurrently easy revenue prove problematic long term profit eventually determine printing company sustainable longterm investment meantime investor caught excitement printing impressive growth potential chevy volt supercharged image owned motley fool john rosevear wild prediction general motor yes general motor blow mind crazy recall scandal big push forward technology surprise lot folk watch auto industry closely form take job watch auto industry closely struck relentless flow hint big brewing noise recall mess know midapril allnew chevy volt expected significant leap forward technology big plush cadillac sedan incorporate technology yes confirmed big cadillac plugin hybrid more ceo mary barra company super cruise system selfdriving car folk circumstance ready production time put model advanced electric car development advanced give tesla motor run money long told yet general drop technological bombshell two year jolt industry great stock buy shaping great year stock make investing year ever start motley fool chief investment officer published brandnew research report reveal top stock year ahead full storey year stock completely free simply interactive chart default setting note make selection apply future visit nasdaqcom time interested reverting default setting select default setting above question encounter issue changing default setting closex confirm selection selected change default setting quote search default target page change configuration again delete cooky change setting ","m_szGeo1":"United States","m_szSourceType":"source_news","m_szSrcUrl":"http://www.nasdaq.com/article/3-of-our-wildest-predictions-for-2015-cm427577?utm_source=feedburner&utm_medium=feed&utm_campaign=Feed%3A+nasdaq%2Fcategories+%28Articles+by+Category%29","m_Places":["Travis","China","Wall Street"],"m_People":["John Rosevear","Steve Heller","Stephen Green","Wohlers","Mary Barra"],"m_Companies":["Motley Fool","Uber","Stratasys","Hewlett-packard","Volt","General Motors","Cadillac","Tesla Motors","Nasdaq","Target"],"m_BiGrams":["motley fool","default setting","printing company","year stock","image owned","owned motley","economic growth","bubble burst","industry growth"],"m_TriGrams":["image owned motley","owned motley fool"],"m_SocialTags":[],"m_Topics":[],"m_Industry":[],"m_Technology":[],"m_BiCnt":[6,5,4,3,3,3,3,3,3],"m_TriCnt":[3,3],"m_iDocBodyWordCnt":571}
