{"m_szDocID":"4522","m_szDocTitle":"Growth in renewable energy is likely to slow | Albuquerque Journal","m_szYear":"2015","m_szDocSumamry":"Growth in renewable energy is likely to slow Tweet .......... .......... .......... .......... .......... .......... .......... .......... .......... .......... .......... .......... .......... .......... .......... .......... .......... .......... For hydrocarbon doomsayers, thereâ€™s good news and bad news. In 2015, there were record investments in renewable energy, and record capacity was added, much of it in emerging economies. Yet despite the huge investment, the global share of fossil fuels is not shrinking very fast. Renewables such as wind, solar and geothermal still account for a tiny s","m_szDocBody":"growth renewable energy slow tweet hydrocarbon doomsayer good new bad new record investment renewable energy record capacity added emerging economy huge investment global share fossil fuel shrinking fast renewable wind solar geothermal account tiny share energy production factor inhibit growth year ren international renewable energy backed united nation environment programme summarised impressive development sector total investment renewable power fuel reached billion alltime record renewable power capacity including hydropower increased gigawatt record terawatt advertisement continue reading sixth consecutive year investment renewable capacity higher hydrocarbonburning power plant increase developing world china place second added solar wind capacity country turkey added geothermal generation narrative environmentally conscious rich nation laggard poor obsolete mauritania invested biggest share economic output sustainable energy honduras uruguay morocco bangladesh biggest market homebased solar system energy revolution fast displacing fossil fuel really investment renewable oil industry comparable magnitude billion invested oil year sustainable energy growing low base wind solar biomass geothermal power power generation area government concentrated sustainable energy effort account percent global energy consumption read big successe costa rica percent energy generated renewable source uruguay percent german state energy coming wind weaning world fossil fuel uphill battle reason regulator understandable fixation generation wind solar installation easy promote technology there government subsidise levying additional taxe feedin tariff harder set equally effective mechanism transportation lion share oil product advertisement continue reading solar wind generation pricecompetitive fossil fuel country modern electric vehicle pricey clunky yes teslas gaspowered competitor term driving range expensive proposition government subsidise degree make popular now oil cheap global market moving car gas suvs global oil consumption grew fastest rate year year growth set continue increase renewable capacity hit obstacle soon year expansion additional wind solar capacity country germany poland added lot wind power government end direct subsidy move tendering programme lowest bidder build power plant fair european government nursed sustainable energy producer hard compete traditional generation price time marketbased approach policy shift however investment slowdown starting solar photovoltaic generation problem market large established share europe solar penetrate electricity system harder recoup project cost ren report say important shift way race costcompetitive fossil fuel adequately remunerate solar market advertisement continue reading market too eventually reach point government support scaled back harder justify huge investment today harder recoup current investment growth rate renewable natural last major technological breakthrough energy storage grid vehicle ensure leap sustainable energy use breakthrough make traditional generation powertrain vastly inferior modern one demand fossil fuel remain strong decade international energy agency projection based current growth rate renewable share natural gas power generation roughly level today doesnt predict drop oil demand predicted end petrostate permanently low oil price long wait fortune made fossil fuel oil dictatorship squabbling menacing neighbour remaining lifetime leonid bershidsky bloomberg contributor berlinbased writer ","m_szGeo1":"United States","m_szSourceType":"source_news","m_szSrcUrl":"http://www.abqjournal.com/785681/growth-in-renewable-energy-is-likely-to-slow.html","m_Places":["China","United States","Turkey","Most","Mauritania","Honduras","Uruguay","Morocco","Bangladesh","Costa Rica","Teslas","Germany","Europe","Berlin"],"m_People":["Leonid Bershidsky"],"m_Companies":["United Nations Environment Program","Revolution","International Energy Agency"],"m_BiGrams":["fossil fuel","sustainable energy","investment renewable","wind solar","renewable energy","advertisement continue"],"m_TriGrams":["advertisement continue reading"],"m_SocialTags":[],"m_Topics":[],"m_Industry":[],"m_Technology":[],"m_BiCnt":[7,5,4,4,3,3],"m_TriCnt":[3],"m_iDocBodyWordCnt":450}
