{"m_szDocID":"46123","m_szDocTitle":"Hurun Report: China's Most Valuable Brand Is Bank ICBC | Global News - AdAge","m_szYear":"2011","m_szDocSumamry":"Adage Aleady a member? Sign in Get More From Ad Age Register to become a member today. You'll get the essential information you need to do your job better, including 7 free articles per month on Ad Age and Creativity Ability to comment on articles and creative work Access to 9 custom e-newsletters like Ad Age Daily, Ad Age Digital and CMO Strategy To get unlimited content and more benefits, check out our Membership page Register Now Want more Access, Content & Connections? We are glad you are enjoying Advertising Age. To get uninterrupted access and additional benefits, become a member today. ","m_szDocBody":"adage aleady member age member today essential information job better including free article month age creativity ability comment article creative work custom enewsletter age daily age digital cmo strategy unlimited benefit cheque membership access connexion glad enjoying advertising age uninterrupted additional benefit member today member log back homepage watch video hurun report chinas valuable brand bank icbc nonchinese heard country leading brand posing challenge international growth normandy madden published chinas valuable brand bank foreigner heard highlighting enormous size strength chinas domestic market challenge facing chinese company international industrial commercial bank china icbc toppled china mobile valuable brand china annual ranking chinas valuable domestic brand hurun report icbc brand worth billion china mobile held top spot year big day icbc rupert hoogewerf hurun chairman chief researcher appeared week episode thoughtful china online marketing affair talk show produced shanghai hurun ranking based combination research consumer brand preference carried international market research firm gmi brand analysis economic data dollar assigned brand directtoconsumer brand created mainland china evaluated businesstobusiness brand huawei increasingly international giant communication service company assessed china mobile largest telecommunication company world million cellphone subscriber china dropped place billion china construction bank billion giant baidu billion bank china billion baidu highestranking privatelyowned brand benefited pulling mainland chinas market year increased share chinas market the big surprise point top internet company shooting hoogewerf said baidu broken topfive valuable brand china today phenomenal achievement china brand worth billion top are china life billion tencent instant messaging service billion agricultural bank china billion insurance company pingan billion real estate financial service apparel internet brand showed significant growth past year top tier chinese company adept building brand home brand overseas strong desire government support western consumer difficult chinese brand tsingtao local beer sold chinese restaurant worldwide privatelyowned company move faster focus lot cost saving compared governmentowned company elan shou ruder finn senior managing director china staterun enterprise tend move faster abroad its government initiative chinas leader chinese company overseas shou said chinas successful local company built strong domestic distribution network savvy understanding local consumer low costsadvantage local company lose leave china chinas domestic market doe terrible job preparing brand world almost all brand china working overseas selling based value early stage brandbuilding black thoughtful chinas senior creative director shanghai challenge jonathan chajet interbrand shanghaibased executive strategy director asiapacific local company figured difference low price value big difference brand toyota lowpriced low price reliability dell low price personalization chinese company equation big mind shift company china produce worldclass brand future yes sportswear marketer ning whitegood maker haier air china have made fantastic progress tim schlick ddb group head strategic planning greater china innovation product development black singled beveragemaker wahaha midea white good company apparel retailer metersbonwe automotive brand chery geely byd electric car company warren buffet stake are overseas time change equation similar electronic company japan south korea year ago chajet said normandy madden senior vpcontent development thoughtful china age asia editor earlier episode thoughtful china here article ","m_szGeo1":"China","m_szSourceType":"source_news","m_szSrcUrl":"http://adage.com/article/global-news/hurun-report-china-s-valuable-brand-bank-icbc/229546/","m_Places":["Shanghai","Asia","Toyota","Japan","South Korea"],"m_People":["Ad Age","Rupert Hoogewerf","Baidu","Hoogewerf","Shou","Jonathan Chajet","Li Ning","Haier","Tim Schlick","Chery","Warren Buffet"],"m_Companies":["Like Ad Age Daily","Cmo","Advertising Age","Brand Is Bank Icbc","Chinese Companies","Industrial And Commercial Bank Of China","China Mobile","Gmi","China Construction Bank","Bank Of China","Google","Agricultural Bank Of China","Ruder Finn","Local Companies","Interbrand","Dell","Air China","Ddb Group","Wahaha","Geely"],"m_BiGrams":["valuable brand","chinese company","chinas valuable","bank china","china mobile","brand china","thoughtful china","local company","low price"],"m_TriGrams":[],"m_SocialTags":[],"m_Topics":[],"m_Industry":[],"m_Technology":[],"m_BiCnt":[4,4,3,3,3,3,3,3,3],"m_TriCnt":[],"m_iDocBodyWordCnt":491}
