{"m_szDocID":"47854","m_szDocTitle":"3-D-printed car could hit streets next year","m_szYear":"2015","m_szDocSumamry":"FacebookEmail Twitter Google+ LinkedIn Pinterest 3-D-printed car could hit streets next year The 3-D-printed car, a thermoplastic car made one at a time by machine, could be hitting the streets as soon as next year. Post to Facebook 3-D-printed car could hit streets next year The 3-D-printed car, a thermoplastic car made one at a time by machine, could be hitting the streets as soon as next year. Check out this story on USATODAY.com: http://usat.ly/1NIncNg CancelSend A link has been sent to your friend's email address. Posted! A link has been posted to your Facebook feed. 3-D-printed car could","m_szDocBody":"facebookemail google linkedin pinterest dprinted car hit street year dprinted car thermoplastic car made time machine hitting street year post dprinted car hit street year dprinted car thermoplastic car made time machine hitting street year cheque storey usatodaycom cancelsend link friend address posted link posted feed dprinted car hit street year chris woodyard usa today est showgoer sema trade show las vegas peek local motor dprinted car swim company sell printed car year chris today printed surf concept car local motor complete local motor surf concept surfboard top chriis today detail rear printed concept swim chris today prototype printed car shown sema aftermarket auto part show las vegas chris today interior surf concept car pretty basic chris today weave printing apparent front rear seat chris today raw material making plastic printed car chris today detail extruding machine make printed car local motor printed car take shape nyko peyer surf printed car nyko peyer topic photo gallery replay local motor hope start selling surferinspired dprinted car year photo chris today connect tweet linkedin emailmore las vegas dprinted car thermoplastic car made time machine hitting street year local motor chandler ariz company revealed design lowerspeed electric car sema automotive trade show week dprinted car dubbed lmd swim dune buggy intended fun car cruise neighbourhood speed limited law than mile hour expected robust highway version sale late year breakthrough chassis printed machine shoot ribbon carbonfiber reinforced thermoplastic toothpaste coming tube previously shown car prove concept local motor ceo jay roger company ready start making car masse seeking open additional plant knoxville tenn national harbour section prince george county design swim competition design winner stanford university graduate kevin spare time design car acknowledge entry suvs wanted classic basic say chris woodyard twitter read share storey top videos ","m_szGeo1":"United States","m_szSourceType":"source_news","m_szSrcUrl":"http://www.usatoday.com/story/money/cars/2015/11/10/3d-printed-car-local-motors-swim/75530830/?utm_source=feedblitz&utm_medium=FeedBlitzRss&utm_campaign=usatodaycommoney-topstories","m_Places":["Las Vegas","Chandler, Ariz.","Knoxville, Tenn.","Md"],"m_People":["Chris Woodyard","Chriis Woodyard","Jay Rogers","Kevin Lo"],"m_Companies":["Twitter","Google","Linkedin","Pinterest","Facebook","Usatoday.com","Usa Today","Nyko","Prince George's County","Stanford University"],"m_BiGrams":["dprinted car","local motor","chris today","street year","printed car","car hit","hit street","car thermoplastic","thermoplastic car","car made","made time","time machine","machine hitting","hitting street","las vegas","surf concept"],"m_TriGrams":["dprinted car hit","car hit street","hit street year","dprinted car thermoplastic","made time machine","time machine hitting","machine hitting street","hitting street year"],"m_SocialTags":[],"m_Topics":[],"m_Industry":[],"m_Technology":[],"m_BiCnt":[9,7,7,6,6,3,3,3,3,3,3,3,3,3,3,3],"m_TriCnt":[3,3,3,3,3,3,3,3],"m_iDocBodyWordCnt":293}
