{"m_szDocID":"51844","m_szDocTitle":"Obama Administration Launches Competition for Three New Manufacturing Innovation Institutes | whitehouse.gov","m_szYear":"2013","m_szDocSumamry":"May 09, 2013 Obama Administration Launches Competition for Three New Manufacturing Innovation Institutes WASHINGTON, DC – The Obama Administration today announced that it is launching competitions to create three new manufacturing innovation institutes with a Federal commitment of $200 million across five Federal agencies – Defense, Energy, Commerce, NASA, and the National Science Foundation.  To build off the initial success of a pilot institute headquartered in Youngstown, Ohio, the President announced in the State of the Union that his Administration would move forward and launch three new ","m_szDocBody":"obama administration launches competition manufacturing innovation institute washington obama administration today announced launching competition create manufacturing innovation institute federal commitment million federal agency defence energy commerce nasa national science foundation build initial success pilot institute headquartered youngstown ohio president announced state union administration move forward launch manufacturing innovation institute year president continue call congress act proposal onetime billion investment create network manufacturing innovation institute country president obama committed making america magnet job manufacturing continue build rest world buy shedding job decade manufacturer added past year manufacturing production grown end recession fastest pace decade build momentum president outlined concrete comprehensive agenda invest american manufacturing president manufacturing agenda start vision national network manufacturing innovation nnmi president budget include billion investment department commerce create nnmi model based approaches country successfully deployed institute serve regional hub designed bridge gap basic research product development bringing company university community college federal agency coinvest technology areas encourage investment production type innovation infrastructure unique teaching factory education training student worker level providing shared asset company importantly small manufacturer cuttingedge capability equipment design test pilot product manufacturing processe department defence lead institute focused digital manufacturing design innovation lightweight modern metal manufacturing department energy leading institute generation power electronic manufacturing institute selected open competitive process led department energy defence review multiagency team technical expert winning team selected announced year federal fund matched industry coinvestment support state local government source pilot institute institute expected financially selfsustaining plan achieve objective critical evaluation criterion selection process dod doe opening competition institute immediately information additional background president obamas plan make america magnet job investing manufacturing state union address administration released president plan investing manufacturing comprehensive agenda build momentum manufacturing sector national network manufacturing innovation administration released report detail president proposal national network manufacturing innovation technology areas institute consistent existing authority federal agency selected technology areas broad commercial application meet critical mission need selected technology areas build existing multiagency priority initiative material genome initiative topic areas are digital manufacturing design innovation advanced design manufacturing tool digitally integrated networked supply chain lead factory future forming agile industrial base significant speed market advantage national institute focusing development modelbased design methodology virtual manufacturing tool sensor robotic based manufacturing network accelerate innovation digital manufacturing increasing competitiveness lightweight modern metal manufacturing advanced lightweight metal possess mechanical electrical property comparable traditional material enabling lighter component product national institute make competitive scalingup research accelerate market expansion product wind turbine medical device engine armoured combat vehicle airframe lead significant reduction manufacturing energy cost generation power electronic wide bandgap semiconductor based power electronic device represent major platform silicon based device driven major technological advance economy decade wide bandgap technology enable dramatically compact efficient power electronic device electric vehicle renewable power interconnection industrialscale variable speed drive motor smarter flexible grid addition highperformance defence application reducing size substation suit case pilot institute administration announced winner initial million federal award create pilot institute national additive manufacturing innovation institute namii headquartered youngstown ohio namii consist consortium manufacturing firm university community college nonprofit organisation primarily ohiopennsylvaniawest virginia tech belt namii selected twelve team country applied award member namii coinvest million initial federal award additive manufacturing referred printing making product component digital model implication wide range industry including defence aerospace automotive metal manufacturing office printer put digital file piece paper printer create component depositing thin layer material digital blueprint exact component required created department defence envision customising part operational system expensive make ship department energy anticipate additive processe save energy compared today subtractive manufacturing processe ","m_szGeo1":"United States","m_szSourceType":"source_news","m_szSrcUrl":"https://www.whitehouse.gov/the-press-office/2013/05/09/obama-administration-launches-competition-three-new-manufacturing-innova","m_Places":["Washington, Dc","Ohio","America","Pennsylvania","West Virginia"],"m_People":["Obama"],"m_Companies":["Nasa","National Science Foundation","National Network","Department Of Commerce","Department Of Defense","Department Of Energy","Innovation Institute","Namii"],"m_BiGrams":["manufacturing innovation","innovation institute","pilot institute","network manufacturing","technology areas","power electronic","federal agency","national network","digital manufacturing","metal manufacturing","department energy"],"m_TriGrams":["manufacturing innovation institute","network manufacturing innovation","national network manufacturing"],"m_SocialTags":[],"m_Topics":[],"m_Industry":[],"m_Technology":[],"m_BiCnt":[],"m_TriCnt":[],"m_iDocBodyWordCnt":575}
