{"m_szDocID":"53439","m_szDocTitle":"Why Molycorp (MCP) Is Gaining Today - TheStreet","m_szYear":"2016","m_szDocSumamry":"TheStreet Why Molycorp (MCP) Is Gaining Today By Lindsay Ingram | 01/02/14 - 12:30 PM EST Reprint NEW YORK ( TheStreet ) --Â Molycorp ( MCP ) rose 3.9% in Thursday trading after analyst firm DA Davidson lifted the company's price target to $8 from $6. Analyst Avinash Kant believes the mining company is \"uniquely positioned\" to become a \"dominant low-cost supplier of critical rare earth materials.\" As one of the few rare earth material suppliers outside of China, Kant believes the Colorado-based company has room for growth as companies look for suppliers outside the country's export quota and wi","m_szDocBody":"thestreet molycorp mcp gaining today lindsay ingram est reprint york thestreet molycorp mcp rose trading analyst firm davidson lifted company price target analyst avinash kant believe mining company uniquely positioned dominant lowcost supplier critical rare earth material rare earth material supplier china kant believe coloradobased company room growth company supplier country export quota wildly varying price analyst expect molycorp benefit significantly trend company seeking rare earth material source china year rare earth material electronic including semiconductor hybrid electric car wind turbine demand material expected increase compound annual growth rate kant thestreet rating team rate molycorp sell rating score thestreet rating team recommendation rate molycorp mcp sell driven concern greater impact strength make difficult investor achieve positive result compared stock cover company weaknesse multiple areas deteriorating net income disappointing return equity weak operating cash flow generally debt management risk generally disappointing historical performance stock itself read century fox foxa today highlight analysis thestreet rating team follow company basis change net income quarter year ago significantly underperformed compared s&p metal mining industry net income significantly decreased compared quarter year ago falling million million return equity greatly decreased compared roe quarter year prior signal major weakness corporation compared company metal mining industry market molycorp inc return equity significantly trail industry average s&p net operating cash flow significantly decreased million compared quarter year addition comparing industry average firm growth rate lower debttoequity ratio compared industry average suggesting debt level management debttoequity ratio weak mcp quick ratio strong demonstrating ability handle shortterm liquidity need intermediate fluctuation bad new report stock performance year tumbled worse s&p performance consistent plunge stock price company earning share compared yearearlier quarter naturally market trend bound significant factor however sense stock sharp decline year positive future investor making cheaper proportion earning past year stock industry due concern stock good buy now full analysis report here mcp rating report cheque service investor ","m_szGeo1":"United States","m_szSourceType":"source_news","m_szSrcUrl":"http://www.thestreet.com/story/12198184/1/why-molycorp-mcp-is-gaining-today.html?cm_ven=RSSFeed","m_Places":["New York","Davidson","Colorado"],"m_People":["Mcp","Lindsay Ingram","Davidson","Avinash Kant"],"m_Companies":["Target","Molycorp Inc","21st Century Fox","Foxa","Signal"],"m_BiGrams":["rare earth","earth material","quarter year","molycorp mcp","thestreet rating","rating team","net income","return equity","industry average"],"m_TriGrams":["rare earth material","thestreet rating team"],"m_SocialTags":[],"m_Topics":[],"m_Industry":[],"m_Technology":[],"m_BiCnt":[4,4,4,3,3,3,3,3,3],"m_TriCnt":[4,3],"m_iDocBodyWordCnt":310}
