{"m_szDocID":"57326","m_szDocTitle":"Tesla Motors (TSLA) Stock Hits Five-Month High After Deutsche Upgrade - TheStreet","m_szYear":"2015","m_szDocSumamry":"Tesla Motors (TSLA) Stock Hits Five-Month High After Deutsche Upgrade By Andrew Meola | 08/11/14 - 04:16 PM EDT Reprint NEW YORK ( TheStreet ) -- Tesla Motors ( TSLA - Get Report ) hit a five-month high of $263.74 on Monday after Deutsche upgraded the electric car maker to \"buy\" and set a $310 price target, up from $220. The firm believes Elon Musk's company can deliver steeper growth. “Tesla suggested that their growth trajectory will be much steeper, their mix will be much richer and their costs will ultimately be much lower than we previously assumed,” Deutsche wrote in a research note. The","m_szDocBody":"tesla motor tsla stock hit fivemonth deutsche upgrade andrew meola edt reprint york thestreet tesla motor tsla report hit fivemonth afterdeutscheupgraded electric car maker buy set price target firm believeselon muskscompany deliver steeper growthtesla suggested growth trajectory steeper mix richer cost ultimately lower previously assumed deutsche wrote research note firm addedtesla deliver car more respectively deutsche previously expected tesla plan ramp upit annual production capacity car end double unit late company intend increase sale expanding shipment model sedan china international market adding model electric sportutility vehicle early exclusive offer inside jim cramer multimillion dollar charitable trust portfolio stock stephanie link potentially huge winner holding free stock closedup highest endofday price separately thestreet rating team rate tesla motor hold rating score thestreet rating team recommendation rate tesla motor tsla hold primary factor impacted rating mixed indicating strength showing weaknesse evidence justify expectation positive negative performance stock relative stock company strength multiple areas robust revenue growth solid stock price performance notable return equity however counter strength weaknesse including unimpressive growth net income generally higher debt management risk poor profit margin highlight analysis thestreet rating team follow tslas impressive revenue growth greatly exceeded industry average quarter year prior revenue leaped growth revenue trickled company bottom line displayed decline earning share compared closing price year ago tslas share price jumped exceeding performance broader market time frame stock future course hold rating recommend additional investment stock gain past year tesla motor experienced steep decline earning share recent quarter comparison performance quarter year ago company reported volatile earning recently but poised eps growth coming year past fiscal year tesla motor continued lose money earning versus prior year year market expect improvement earning versus company basis change net income quarter year ago significantly underperformed compared s&p automobile industry net income significantly decreased compared quarter year ago falling million million debttoequity ratio higher industry average implying increased risk management debt level company full analysis report here tsla rating report ","m_szGeo1":"United States","m_szSourceType":"source_news","m_szSrcUrl":"http://www.thestreet.com/story/12840627/1/tesla-motors-tsla-stock-hits-five-month-high-after-deutsche-upgrade.html?cm_ven=RSSFeed&utm_source=feedburner&utm_medium=feed&utm_campaign=Feed%3A+tsc%2Ffeeds%2Frss%2Flatest-stories+%28TheStreet.com+Latest+Headlines%29","m_Places":["New York","Tesla"],"m_People":["Deutsche","Andrew Meola","Elon","Jim Cramer","Stephanie Link"],"m_Companies":["Tesla Motors","Target","Tesla Motors Inc"],"m_BiGrams":["tesla motor","quarter year","motor tsla","thestreet rating","rating team","net income"],"m_TriGrams":["tesla motor tsla","thestreet rating team","quarter year ago"],"m_SocialTags":[],"m_Topics":[],"m_Industry":[],"m_Technology":[],"m_BiCnt":[6,4,3,3,3,3],"m_TriCnt":[3,3,3],"m_iDocBodyWordCnt":321}
