{"m_szDocID":"57935","m_szDocTitle":"Air Force Scores Biggest Ever Military Solar Power Plant","m_szYear":"2014","m_szDocSumamry":"February 22nd, 2014 by Tina Casey   It looks like the Air Force wins the week in terms of military renewable energy projects. The biggest military solar power plant in the US has just been completed at Davis-Monthan Air Force Base in Arizona, a 16.4 megawatt installation that is expected to save about $500,000 in electricity costs yearly and provide about 35 percent of the base’s electricity needs. If you’re keeping score at home, the new military solar power plant nudges the Air Force ahead of the Army, at least for now. Earlier this week, the Army Corps of Engineers and Energy Initiatives Ta","m_szDocBody":"tina casey air force win week term military renewable energy project biggest military solar power plant completed davismonthan air force base arizona megawatt installation expected save electricity cost yearly provide percent base electricity need youre keeping score home military solar power plant nudge air force ahead army now earlier week army corp engineer energy initiative task force announced contract military solar power pretty impressive preliminary step involving formation pool eligible bidder future project davismonthan afb green desert courtesy usaf chevronthere here interesting winning army contract chevron energy solution part publicprivate partnership building solar power plant davismonthan afb chevron energy solution chevron umbrella chevron recently made new giving free pizza coupon massive gas line explosion pennsylvania chevron energy solution running hard solar track focus government school facility partner project macquarie infrastructure company fossil fuel interest range infrastructure operation chevron diversified renewable energy mic solar energy holding familiar solar business sunedison constructed manage solar power plant contract mic solar record installation consist sunedison memc silvantis solar module mounted singleaxis tracker pivot advantage sun position day record project financed north american development bank set mexico develop infrastructure project benefit environment border project enable davismonthan avoid metric tonne carbon dioxide metric tonne nitrogen oxide metric tonne sulphur dioxide annually built power purchase agreement upfront cost air force taxpayer harmed making renewable energy project air force solar power let solar installation play davismonthan mission this deploy employ support sustain attack airpower support combatant commander world moment notice train finest attack pilot combat air force provide member team responsive tailored missionfocused base support glance overlap there davismonthan vision premier fighter wing comprised resilient warrior airmen armed precise tool training powered culture leadership innovation prepared provide responsive combat airpower exceed combatant command expectation excellence snippet base green desert programme demonstrating culture leadership innovation dovetail clean energy energy team begun redeveloping base strategy hightech solution meet air force wide mandate areas technology strategic partnership energy awareness focus basic innovation energy consciousness airman life meet air force goal green build green fly blue worth noting davismonthan military facility transitioning coal power renewable energy natural gas fossil source fort drum york recent example follow google latest clean tech new cleantechnica newsletter youd attend cleantechnica solar event date hottest cleantech new subscribing free cleantech newsletter eye sectorspecific new also free solar energy newsletter electric vehicle newsletter wind energy newsletter ","m_szGeo1":"United States","m_szSourceType":"source_news","m_szSrcUrl":"http://cleantechnica.com/2014/02/22/air-force-scores-biggest-ever-military-solar-power-plant/?utm_source=feedburner&utm_medium=feed&utm_campaign=Feed%3A+IM-cleantechnica+%28CleanTechnica%29","m_Places":["Arizona","Pennsylvania","Mexico","New York"],"m_People":["Tina Casey","Mic Solar"],"m_Companies":["Air Force","Davis-monthan Air Force Base","Army","Army Corps Of Engineers","Pool","Usaf","Chevron","Macquarie","Infrastructure Company","Solar Energy","Sunedison","Development Bank","Air Forces","Twitter","Google"],"m_BiGrams":["air force","solar power","renewable energy","power plant","military solar","chevron energy","energy solution","metric tonne"],"m_TriGrams":["solar power plant","military solar power","chevron energy solution"],"m_SocialTags":[],"m_Topics":[],"m_Industry":[],"m_Technology":[],"m_BiCnt":[],"m_TriCnt":[],"m_iDocBodyWordCnt":388}
