{"m_szDocID":"60945","m_szDocTitle":"Public Utilities & Private Companies In Mexico Teaming Up To Promote Renewables | CleanTechnica","m_szYear":"2014","m_szDocSumamry":"Public Utilities & Private Companies In Mexico Teaming Up To Promote Renewables March 24th, 2014 by James Ayre   The Federal Electricity Commission — the general director of Mexico’s state-owned electric utility — recently announced its plans to further promote renewable energy production within the populous country by teaming up with a number of notable private companies. These new strategic public-private partnerships are intended as a sort of ‘reform’ of the country’s electric industry — with the aim being to maximize the potential of renewable energy projects there. Photo Credit: austinhk ","m_szDocBody":"public utility private company mexico teaming promote renewable jame ayre federal electricity commission general director mexicos stateowned electric utility recently announced plan promote renewable energy production populous country teaming number notable private company strategic publicprivate partnership intended sort reform country electric industry aim maximise potential renewable energy project there photo credit austinhk fotercom byncnd federal electricity commission cfe director enrique ochoa reza reform assist achievement mexicos goal energy generate renewable source year comment made speaking inauguration aura solar plant baja california sur aura solar installed gauss energia company cfe interested working with there ochoa reza noted commission head interested encouraging development state baja california sur regard aura solar plant baja california sur covered topic indepth year construction note power plant provide electricity estimated household design feature module installed singleaxis tracker project utilityscale solar project power purchase agreement contract year long private company cfe isnt company end part strategic publicprivate partnership cleantechnica follow storey informed date latest new solar energy cleantechnica free solar energy newsletter cleantech newsletter miss storey youd attend cleantechnica solar event date hottest cleantech new subscribing free cleantech newsletter eye sectorspecific new also free solar energy newsletter electric vehicle newsletter wind energy newsletter tag aura solar power plant cfe federal electricity commission gauss energia mexico mexico solar energy jame ayre background predominantly geopolitic history obsessive interest pretty everything early life spent imperial free city dortmund jame river ruhr cofbuokheim attended university astnide briefly considered entering coal mining business write living broad variety subject ranging science politic military history renewable energy follow work google related post ","m_szGeo1":"Mexico","m_szSourceType":"source_news","m_szSrcUrl":"http://cleantechnica.com/2014/03/24/public-utilities-private-companies-mexico-teaming-promote-renewables/?utm_source=feedburner&utm_medium=feed&utm_campaign=Feed%3A+IM-cleantechnica+%28CleanTechnica%29","m_Places":["Mexico","Nc","Nd","Baja California Sur","Free City","Dortmund"],"m_People":["James Ayre","Enrique Ochoa Reza","Aura Solar","Ochoa Reza","Aura I Pv"],"m_Companies":["Private Companies","Electricity Commission","First Utility","Astnide","Google"],"m_BiGrams":["aura solar","solar energy","private company","federal electricity","electricity commission","renewable energy","baja california","california sur","energy newsletter"],"m_TriGrams":["federal electricity commission","baja california sur"],"m_SocialTags":[],"m_Topics":[],"m_Industry":[],"m_Technology":[],"m_BiCnt":[4,4,3,3,3,3,3,3,3],"m_TriCnt":[3,3],"m_iDocBodyWordCnt":257}
