{"m_szDocID":"63079","m_szDocTitle":"Tesla Motors (TSLA) Stock Declines Today on Higher Quarterly Loss Expectations - TheStreet","m_szYear":"2016","m_szDocSumamry":"TheStreet Tesla Motors (TSLA) Stock Declines Today on Higher Quarterly Loss Expectations By Tony Owusu | 04/14/15 - 01:14 PM EDT Reprint NEW YORK ( TheStreet ) -- Tesla Motors ( TSLA - Get Report ) shares are down 1.09% to $206.92 in afternoon trading on Tuesday after analysts at Morgan Stanley ( MS ) lowered their earnings forecast for the electric vehicle manufacturer today. Morgan Stanley analyst Adam Jonas, who has previously written consistently bullish notes on the company, said that he now expects the company to report a non-GAAP net loss of 77 cents per share versus the consensus estim","m_szDocBody":"thestreet tesla motor tsla stock decline today higher quarterly loss expectation tony owusu edt reprint york thestreet tesla motor tsla report share afternoon trading analyst morgan stanley lowered earning forecast electric vehicle manufacturertoday morgan stanley analyst adam jonas previously written consistently bullish note company expect company report nongaap net loss cent share versus consensus estimate cent share loss firm widened full year loss expectation share versus consensus estimate net lossof cent share tomarket watch heading earning call continue detail surrounding model execution particular launch timing speed ramp order back loggiven significance launch expect tesla cut corner elon musk management fully sacrifice shortterm profitability via higherthanexpected upfront cost ensure successful debut jonas thestreet rating team rate tesla motor sell rating score thestreet rating team recommendation rate tesla motor tsla sell driven concern greater impact strength make difficult investor achieve positive result compared stock cover company weaknesse multiple areas deteriorating net income disappointing return equity weak operating cash flow poor profit margin generally debt management risk highlight analysis thestreet rating team follow company basis change net income quarter year ago significantly underperformed compared s&p automobile industry net income significantly decreased compared quarter year ago falling million million return equity greatly decreased compared roe quarter year prior signal major weakness corporation compared company automobile industry market tesla motor inc return equity significantly trail industry average s&p net operating cash flow significantly decreased million compared quarter year addition comparing industry average firm growth rate lower gross profit margin tesla motor lower desirable coming tslas low profit margin managed increase period year mixed result gross profit margin tslas net profit margin significantly underperformed compared industry average debttoequity ratio higher industry average implying increased risk management debt level company debttoequity ratio weak tslas quick ratio strong demonstrating ability handle shortterm liquidity need full analysis report here tsla rating report ","m_szGeo1":"United States","m_szSourceType":"source_news","m_szSrcUrl":"http://www.thestreet.com/story/13111904/1/tesla-motors-tsla-stock-declines-today-on-higher-quarterly-loss-expectations.html?cm_ven=RSSFeed&utm_source=feedburner&utm_medium=feed&utm_campaign=Feed%3A+tsc%2Ffeeds%2Frss%2Flatest-stories+%28TheStreet.com+Latest+Headlines%29","m_Places":["New York","Tesla"],"m_People":["Tony Owusu","Adam Jonas","Elon"],"m_Companies":["Tesla Motors","Morgan Stanley","Ms","Market Watch","Ramp","Tesla Motors Inc","Signal"],"m_BiGrams":["tesla motor","profit margin","quarter year","industry average","motor tsla","cent share","thestreet rating","rating team","net income","return equity"],"m_TriGrams":["tesla motor tsla","thestreet rating team"],"m_SocialTags":[],"m_Topics":[],"m_Industry":[],"m_Technology":[],"m_BiCnt":[6,5,4,4,3,3,3,3,3,3],"m_TriCnt":[3,3],"m_iDocBodyWordCnt":303}
