{"m_szDocID":"63277","m_szDocTitle":"Tesla (TSLA) Stock Rallying Today Following Positive Deutsche Bank Note - TheStreet","m_szYear":"2015","m_szDocSumamry":"TheStreet Tesla (TSLA) Stock Rallying Today Following Positive Deutsche Bank Note By Kurumi Fukushima | 04/22/15 - 09:33 AM EDT Reprint NEW YORK ( TheStreet ) -- Shares of Tesla Motors ( TSLA - Get Report ) are rallying, higher by 1.45% to $212.44 in early market trading Wednesday, after analysts at Deutsche Bank issued a positive note on the electric car maker. The firm said energy storage represents a \"significant\" opportunity for Tesla, while maintaining its \"buy\" rating with a price target of $245. On April 30, the company is expected to announce the launch of its new battery storage syste","m_szDocBody":"thestreet tesla tsla stock rallying today positive deutsche bank note kurumi fukushima edt reprint york thestreet share tesla motor tsla report are rallying higher earlymarket trading wednesday analyst deutsche bankissued positive note electric car maker firmsaid energy storage represent significant opportunity tesla maintaining buy rating price target company expected announce launch battery storage system home commercial market powered battery model firm noted thatevery solarcity scty unit bundled battery storagedeutsche analystsestimate equipping solarcity customer annual revenue between billion and billion tesla read warren buffett top stock palo alto cabased tesla design develop manufacture sell electric vehicle advanced electric vehicle powertrain component tesla own sale service network separately thestreet rating team rate tesla motor sell rating score thestreet rating team recommendation rate tesla motor tsla sell driven notable weaknesse greater impact strength make difficult investor achieve positive result compared stock cover company weaknesse multiple areas deteriorating net income disappointing return equity weak operating cash flow poor profit margin generally debt management risk highlight analysis thestreet rating team follow company basis change net income quarter year ago significantly underperformed compared s&p automobile industry net income significantly decreased compared quarter year ago falling million million return equity greatly decreased compared roe quarter year prior signal major weakness corporation compared company automobile industry market tesla motor inc return equity significantly trail industry average s&p net operating cash flow significantly decreased million compared quarter year addition comparing industry average firm growth rate lower gross profit margin tesla motor lower desirable coming tslas low profit margin managed increase period year mixed result gross profit margin tslas net profit margin significantly underperformed compared industry average debttoequity ratio higher industry average implying increased risk management debt level company debttoequity ratio weak tslas quick ratio strong demonstrating ability handle shortterm liquidity need full analysis report here tsla rating report cheque service investor ","m_szGeo1":"United States","m_szSourceType":"source_news","m_szSrcUrl":"http://www.thestreet.com/story/13121784/1/tesla-tsla-stock-rallying-today-following-positive-deutsche-bank-note.html?cm_ven=RSSFeed&utm_source=feedburner&utm_medium=feed&utm_campaign=Feed%3A+tsc%2Ffeeds%2Frss%2Flatest-stories+%28TheStreet.com+Latest+Headlines%29","m_Places":["Tesla","New York","Palo Alto, Ca"],"m_People":["Kurumi Fukushima","Deutsche","Warren Buffett"],"m_Companies":["Deutsche Bank","Tesla Motors","Target","Solarcity","Scty","Tesla Motors Inc","Signal"],"m_BiGrams":["tesla motor","profit margin","quarter year","industry average","thestreet rating","rating team","net income","return equity"],"m_TriGrams":["thestreet rating team"],"m_SocialTags":[],"m_Topics":[],"m_Industry":[],"m_Technology":[],"m_BiCnt":[5,5,4,4,3,3,3,3],"m_TriCnt":[3],"m_iDocBodyWordCnt":302}
