{"m_szDocID":"63486","m_szDocTitle":"Tesla Motors (TSLA) Stock Falling Before Battery Launch Event - TheStreet","m_szYear":"2016","m_szDocSumamry":"TheStreet Tesla Motors (TSLA) Stock Falling Before Battery Launch Event By Amanda Schiavo | 04/30/15 - 03:07 PM EDT Reprint NEW YORK ( TheStreet ) -- Shares of Tesla Motors ( TSLA - Get Report ) are down by 2.24% to $227.24 in mid-afternoon trading on Thursday, as the company is set to release its residential and commercial-scale batteries at an event scheduled for later tonight. The stock is lower as the initial excitement over the announcement wears off, MarketWatch reports, adding that Wall Street is split as to whether or not the electric car maker's stock will dip further as tends to be t","m_szDocBody":"thestreet tesla motor tsla stock falling battery launch event amanda schiavo edt reprint york thestreet share tesla motor tsla report midafternoon trading thursday company set release residential commercialscale battery event scheduled tonight stock lower initial excitement announcement wear off marketwatch report adding wall street split electric car maker stock dip case big tesla announcement event place pacific time los angele suburb tesla detail marketing pricing aspect battery business marketwatch noted additionally thestreet jim cramer portfolio manager action alert charitable trust portfolio answered question floor nyse earlier today asked tesla cramer stock cold overvalued car buy stock fine recommend metric make inexpensive cramer q&a watch video separately thestreet rating team rate tesla motor sell rating score thestreet rating team recommendation rate tesla motor tsla sell driven weaknesse greater impact strength make difficult investor achieve positive result compared stock cover company weaknesse multiple areas deteriorating net income disappointing return equity weak operating cash flow poor profit margin generally debt management risk highlight analysis thestreet rating team follow company basis change net income quarter year ago significantly underperformed compared s&p automobile industry net income significantly decreased compared quarter year ago falling million million return equity greatly decreased compared roe quarter year prior signal major weakness corporation compared company automobile industry market tesla motor inc return equity significantly trail industry average s&p net operating cash flow significantly decreased million compared quarter year addition comparing industry average firm growth rate lower gross profit margin tesla motor lower desirable coming tslas low profit margin managed increase period year mixed result gross profit margin tslas net profit margin significantly underperformed compared industry average debttoequity ratio higher industry average implying increased risk management debt level company debttoequity ratio weak tslas quick ratio strong demonstrating ability handle shortterm liquidity need full analysis report here tsla rating report cheque service investor ","m_szGeo1":"United States","m_szSourceType":"source_news","m_szSrcUrl":"http://www.thestreet.com/story/13133807/1/tesla-motors-tsla-stock-falling-before-battery-launch-event.html?cm_ven=RSSFeed&utm_source=feedburner&utm_medium=feed&utm_campaign=Feed%3A+tsc%2Ffeeds%2Frss%2Flatest-stories+%28TheStreet.com+Latest+Headlines%29","m_Places":["New York","Wall Street","Tesla","Los Angeles"],"m_People":["Amanda Schiavo","Jim Cramer"],"m_Companies":["Tesla Motors","Marketwatch","Pacific Time","Los Angeles","Twitter","Nyse","Tesla Motors Inc","Signal"],"m_BiGrams":["tesla motor","profit margin","quarter year","industry average","motor tsla","thestreet rating","rating team","net income","return equity"],"m_TriGrams":["tesla motor tsla","thestreet rating team"],"m_SocialTags":[],"m_Topics":[],"m_Industry":[],"m_Technology":[],"m_BiCnt":[6,5,4,4,3,3,3,3,3],"m_TriCnt":[3,3],"m_iDocBodyWordCnt":301}
