{"m_szDocID":"63718","m_szDocTitle":"Tesla (TSLA) Stock Gaining After Winning Approval For Direct Car Sales in Maryland - TheStreet","m_szYear":"2015","m_szDocSumamry":"TheStreet Tesla (TSLA) Stock Gaining After Winning Approval For Direct Car Sales in Maryland By Kurumi Fukushima | 05/12/15 - 03:16 PM EDT Reprint NEW YORK ( TheStreet ) -- Shares of Tesla Motors Inc ( TSLA - Get Report ) are up 2.02% to $244.33 in Tuesday's trading session, after Maryland Governor Larry Hogan signed a bill allowing the electric-car maker to sell directly to consumers, Bloomberg reports. Tesla can now bypass auto dealers starting Oct. 1, and operate as many as four locations, according to the new law. About 5.45 million shares of Tesla exchanged hands as of 3:14 p.m. ET today,","m_szDocBody":"thestreet tesla tsla stock gaining winning approval direct car sale maryland kurumi fukushima edt reprint york thestreet share tesla motor tsla report tuesday trading session aftermaryland governor larry hogan signed bill allowing electriccar maker sell directly consumer bloomberg report tesla bypass auto dealer startingoct andoperate location law million share tesla exchanged hand today compared average trading volume million share day tesladesign develop manufacture sell electric vehicle advanced electric vehicle powertrain component own sale service network read warren buffett top stock separately thestreet rating team rate tesla motor hold rating score thestreet rating team recommendation rate tesla motor tsla hold primary factor impacted rating mixed indicating strength showing weaknesse evidence justify expectation positive negative performance stock relative stock company strength multiple areas robust revenue growth expanding profit margin solid stock price performance however counter strength weaknesse including deteriorating net income generally higher debt management risk disappointing return equity highlight analysis thestreet rating team follow tslas impressive revenue growth greatly exceeded industry average quarter year prior revenue leaped growth revenue trickled company bottom line displayed decline earning share gross profit margin tesla motor strong increased quarter previous year strong result gross profit margin net profit margin inline industry average stock today compared year ago higher outperformed rise s&p period company weak earning result fact risen past year conclusive evidence warrant purchase sale stock return equity greatly decreased compared roe quarter year prior signal major weakness corporation compared company automobile industry market tesla motor inc return equity significantly trail industry average s&p net operating cash flow significantly decreased million compared quarter year addition comparing industry average firm growth rate lower full analysis report here tsla rating report cheque service investor ","m_szGeo1":"United States","m_szSourceType":"source_news","m_szSrcUrl":"http://www.thestreet.com/story/13148780/1/tesla-tsla-stock-gaining-after-winning-approval-for-direct-car-sales-in-maryland.html?cm_ven=RSSFeed&utm_source=feedburner&utm_medium=feed&utm_campaign=Feed%3A+tsc%2Ffeeds%2Frss%2Flatest-stories+%28TheStreet.com+Latest+Headlines%29","m_Places":["Tesla","Maryland","New York"],"m_People":["Kurumi Fukushima","Larry Hogan","Warren Buffett"],"m_Companies":["Tesla Motors Inc","Signal"],"m_BiGrams":["tesla motor","profit margin","industry average","thestreet rating","rating team","return equity","quarter year"],"m_TriGrams":["thestreet rating team"],"m_SocialTags":[],"m_Topics":[],"m_Industry":[],"m_Technology":[],"m_BiCnt":[5,4,4,3,3,3,3],"m_TriCnt":[3],"m_iDocBodyWordCnt":277}
