{"m_szDocID":"65797","m_szDocTitle":"Tesla Motors (TSLA) Stock Price Target Raised at Morgan Stanley - TheStreet","m_szYear":"2016","m_szDocSumamry":"TheStreet Tesla Motors (TSLA) Stock Price Target Raised at Morgan Stanley By Rachel Graf | 08/17/15 - 09:24 AM EDT NEW YORK ( TheStreet ) -- Tesla Motors' ( TSLA - Get Report )  price target was hiked to $465 from $280 at Morgan Stanley on Monday morning. The firm said that the future of electric vehicles is shifting toward an autonomous, shared mobility model in which smart technology propels shared transportation, and Morgan Stanley would be \"surprised\" if Tesla didn't announce formal business plans on shared mobility within 12 to 18 months. Tesla could then possibly commercially introduce i","m_szDocBody":"thestreet tesla motor tsla stock price target raised morgan stanley rachel graf edt york thestreet tesla motor tsla report price target hiked atmorgan stanleyon morning firm future electric vehiclesis shifting autonomous shared mobility model whichsmart technology propel shared transportation morgan stanley surprised tesla announce formal business plan shared mobility month tesla possiblycommercially introduce product morgan stanley business opportunity potentially additive teslas existing model selling humandriven car private owner potential model conceivably triple company potential revenue firm analyst note morgan stanley noted tesla wellsuited shared mobility model company car electric connected learn firmware update feat established automaker accomplished share company gaining% premarket trading monday thestreet jim cramer portfolio manager action alert charitable trust portfolio commented tesla morning saying excessive price tag excessive hope thought idea tesla shared economy good one good merited kind price increase separately thestreet rating team rate tesla motor hold rating score thestreet rating team recommendation rate tesla motor tsla hold primary factor impacted rating mixed indicating strength showing weaknesse evidence justify expectation positive negative performance stock relative stock primary strength company robust revenue growth recent period previous quarter well time however weaknesse including deteriorating net income generally higher debt management risk disappointing return equity highlight analysis thestreet rating team follow revenue growth greatly exceeded industry average quarter year prior revenue rose growth revenue trickled company bottom line displayed decline earning share tesla motor experienced steep decline earning share recent quarter comparison performance quarter year ago company reported trend declining earning share past year however consensus estimate suggest trend reverse coming year past fiscal year tesla motor reported poor result versus prior year year market expect improvement earning versus share price tesla motor well underperformed s&p part reflecting company sharply declining earning share compared yearearlier quarter fact stock selling industry relation current earning reason justify buy rating time gross profit margin tesla motor lower desirable coming decreased quarter previous year this net profit margin significantly industry average net operating cash flow significantly decreased million compared quarter year addition comparing industry average firm growth rate lower full analysis report here tsla rating report cheque service investor ","m_szGeo1":"United States","m_szSourceType":"source_news","m_szSrcUrl":"http://www.thestreet.com/story/13257306/1/tesla-motors-tsla-stock-price-target-raised-at-morgan-stanley.html?cm_ven=RSSFeed&utm_source=feedburner&utm_medium=feed&utm_campaign=Feed%3A+tsc%2Ffeeds%2Frss%2Flatest-stories+%28TheStreet.com+Latest+Headlines%29","m_Places":["New York","Tesla"],"m_People":["Rachel Graf","Jim Cramer"],"m_Companies":["Tesla Motors","Target","Morgan Stanley","Tesla Motors Inc"],"m_BiGrams":["tesla motor","morgan stanley","earning share","motor tsla","shared mobility","thestreet rating","rating team","industry average","quarter year"],"m_TriGrams":["tesla motor tsla","thestreet rating team"],"m_SocialTags":[],"m_Topics":[],"m_Industry":[],"m_Technology":[],"m_BiCnt":[8,4,4,3,3,3,3,3,3],"m_TriCnt":[3,3],"m_iDocBodyWordCnt":347}
