{"m_szDocID":"66275","m_szDocTitle":"Will Tesla (TSLA) Stock Be Hurt by Audi, Porsche Competition? - TheStreet","m_szYear":"2016","m_szDocSumamry":"TheStreet Will Tesla (TSLA) Stock Be Hurt by Audi, Porsche Competition? By Amanda Gomez | 09/14/15 - 11:25 AM EDT Reprint NEW YORK ( TheStreet ) --Â Tesla ( TSLA - Get Report ) is facing new competition from Audi and Porsche, both owned by Volkswagen ( VLKAY ), after the luxury carmakers unveiled battery-powered vehicles at an auto show in Frankfurt, Germany on Monday. Tesla had benefitted from being the innovator of battery-powered cars, increasing their driving range and reducing costs, Reuters reports. Analysts are split on how the new battery-powered Audi and Porsche will affect Tesla. The ","m_szDocBody":"thestreet tesla tsla stock hurt audi porsche competition amanda gomez edt reprint york thestreet tesla tsla report facing competition audi porsche owned volkswagen vlkay luxury carmaker unveiled batterypowered vehicle auto show frankfurt germany monday tesla benefitted innovator batterypowered car increasing driving range reducing cost reuter report analyst split batterypowered audi porsche affect tesla model create larger market electric vehicle challenge tesla audi porsche brand highly soughtafter reuter added sharpen public focus electric vehicle raise awareness consumer set gain growing offering electric car performance segment commerzbank analyst sascha gommel told reuter audi porsche expected begin selling electronic vehicle tesla stock rising late morning trading monday separately thestreet rating team rate tesla motor hold rating score thestreet rating team recommendation rate tesla motor tsla hold primary factor impacted rating mixed indicating strength showing weaknesse evidence justify expectation positive negative performance stock relative stock primary strength company robust revenue growth recent period previous quarter well time however weaknesse including deteriorating net income generally higher debt management risk disappointing return equity highlight analysis thestreet rating team follow revenue growth greatly exceeded industry average quarter year prior revenue rose growth revenue trickled company bottom line displayed decline earning share tesla motor experienced steep decline earning share recent quarter comparison performance quarter year ago company reported trend declining earning share past year however consensus estimate suggest trend reverse coming year past fiscal year tesla motor reported poor result versus prior year year market expect improvement earning versus share price tesla motor well underperformed s&p part reflecting company sharply declining earning share compared yearearlier quarter fact stock selling industry relation current earning reason justify buy rating time gross profit margin tesla motor lower desirable coming decreased quarter previous year this net profit margin significantly industry average net operating cash flow significantly decreased million compared quarter year addition comparing industry average firm growth rate lower full analysis report here tsla rating report cheque service investor ","m_szGeo1":"United States","m_szSourceType":"source_news","m_szSrcUrl":"http://www.thestreet.com/story/13287153/1/will-tesla-tsla-stock-be-hurt-by-audi-porsche-competition.html?cm_ven=RSSFeed&utm_source=feedburner&utm_medium=feed&utm_campaign=Feed%3A+tsc%2Ffeeds%2Frss%2Flatest-stories+%28TheStreet.com+Latest+Headlines%29","m_Places":["New York","Tesla","Frankfurt","Germany"],"m_People":["Will Tesla","Audi, Porsche","Amanda Gomez","Porsche","Sascha Gommel"],"m_Companies":["Audi","Volkswagen","Reuters","Commerzbank","Tesla Motors Inc"],"m_BiGrams":["tesla motor","audi porsche","earning share","thestreet rating","rating team","industry average","quarter year"],"m_TriGrams":["thestreet rating team"],"m_SocialTags":[],"m_Topics":[],"m_Industry":[],"m_Technology":[],"m_BiCnt":[6,5,4,3,3,3,3],"m_TriCnt":[3],"m_iDocBodyWordCnt":317}
