{"m_szDocID":"66319","m_szDocTitle":"Tesla (TSLA) Stock Down in Pre-Market Trading as Competitors Launch Electric Cars - TheStreet","m_szYear":"2016","m_szDocSumamry":"Tesla (TSLA) Stock Down in Pre-Market Trading as Competitors Launch Electric Cars By Amanda Gomez | 09/16/15 - 08:53 AM EDT Reprint NEW YORK ( TheStreet ) -- Tesla ( TSLA - Get Report ) stock is falling by 0.11% to $253.28 in pre-market trading on Wednesday, after reports confirmed Mercedes-Benz is working on an electric vehicle that could be available in 2018, Automotive News said. Mercedes-Benz, a Daimler ( DDAIF ) brand, is working on a vehicle that will have a range of 250 to 310 miles, Daimler board member Thomas Weber told Automotive News. The new electric vehicle will not compete with M","m_szDocBody":"tesla tsla stock premarket trading competitor launch electric car amanda gomez edt reprint york thestreet tesla tsla report stock falling premarket trading wednesday report confirmed mercedesbenz working electric vehicle automotive newssaid mercedesbenz daimler ddaif brand working vehicle range mile daimler board member thomas weber told automotive new electric vehicle compete mercedesbenzs current electric vehicle biggerto house larger battery weber added tesla facing increased competition batterypowered vehicle luxury car brand earlier week audi porsche owned volkswagen vlkay introduced batterypowered vehicle auto show frankfurt germany model analyst tesla benefit electric vehicle pioneer larger market struggle compete wellknown brand audi porsche reuter report separately thestreet rating team rate tesla motor hold rating score thestreet rating team recommendation rate tesla motor tsla hold primary factor impacted rating mixed indicating strength showing weaknesse evidence justify expectation positive negative performance stock relative stock primary strength company robust revenue growth recent period previous quarter well time however weaknesse including deteriorating net income generally higher debt management risk disappointing return equity highlight analysis thestreet rating team follow revenue growth greatly exceeded industry average quarter year prior revenue rose growth revenue trickled company bottom line displayed decline earning share tesla motor experienced steep decline earning share recent quarter comparison performance quarter year ago company reported trend declining earning share past year however consensus estimate suggest trend reverse coming year past fiscal year tesla motor reported poor result versus prior year year market expect improvement earning versus share price tesla motor well underperformed s&p part reflecting company sharply declining earning share compared yearearlier quarter fact stock selling industry relation current earning reason justify buy rating time gross profit margin tesla motor lower desirable coming decreased quarter previous year this net profit margin significantly industry average net operating cash flow significantly decreased million compared quarter year addition comparing industry average firm growth rate lower full analysis report here tsla rating report cheque service investor ","m_szGeo1":"United States","m_szSourceType":"source_news","m_szSrcUrl":"http://www.thestreet.com/story/13290359/1/tesla-tsla-stock-down-in-pre-market-trading-as-competitors-launch-electric-cars.html?cm_ven=RSSFeed&utm_source=feedburner&utm_medium=feed&utm_campaign=Feed%3A+tsc%2Ffeeds%2Frss%2Flatest-stories+%28TheStreet.com+Latest+Headlines%29","m_Places":["Tesla","New York","Frankfurt","Germany"],"m_People":["Amanda Gomez","Thomas Weber","Audi","Porsche"],"m_Companies":["Mercedes-benz","Automotive News","Volkswagen","Reuters","Tesla Motors Inc"],"m_BiGrams":["tesla motor","electric vehicle","earning share","thestreet rating","rating team","industry average","quarter year"],"m_TriGrams":["thestreet rating team"],"m_SocialTags":[],"m_Topics":[],"m_Industry":[],"m_Technology":[],"m_BiCnt":[6,4,4,3,3,3,3],"m_TriCnt":[3],"m_iDocBodyWordCnt":313}
