{"m_szDocID":"67376","m_szDocTitle":"SAITH unveils a helicopter - NewsDay Zimbabwe","m_szYear":"2015","m_szDocSumamry":"You are here: Home › Business › SAITH unveils a helicopter SAITH unveils a helicopter SAITH Technology has unveiled its latest technologies including an electric car and hybrid helicopter, but said it was waiting government approval to sell the products. BY TARISAI MANDIZHA Speaking at the official unveiling of SAITH Technologies in Harare yesterday, founder and inventor Sangulani Max Chikumbutso said the government had shown interest in the hybrid helicopter which can be used by the army, police patrol, surveying and border patrols among others. “This event means that we are now ready for the","m_szDocBody":"here home business saith unveil helicopter saith unveil helicopter saith technology unveiled latest technology including electric car hybrid helicopter waiting government approval sell product tarisai mandizha speaking official unveiling saith technology harare yesterday founder inventor sangulani max chikumbutso government shown interest hybrid helicopter army police patrol surveying border patrol other event mean ready market showing technology world said waiting licenced government start moving product country chikumbutso company world largest car manufacturer electric vehicle technology humbled form drop world inventor green power machine electric vehicle other hybrid helicopter run fuel making adjustment engine fully powered electric vehicle powered microsonic energy device msed msed renewable emission green power machine designed revolutionise energy sector powered msed generate electrical power converting radio frequency energy directly electricity saith launched sdhdmi transmitter receiver mobile surveillance transmit receive wireless definition video audio signal saithhdmi transmitter receiving sensitivity speaking event saith technology shareholder teddy almeida company received enquiry investor world sealed number deal company almeida company forward working government publicprivatepartnership initiative saith advisor farai katsande company ready place confident product market storm katsande chikumbutso passionate zimbabwe plan build car manufacturing plant country newsletter receive update related post response saith unveil helicopter marvellous fantastic sound good true patent ideas asap duke make haasati aita patent higg bosson physicist exhibition naturally intrested technology intrested greener machine inventor machine work converting electricity volt battery radio wave radio wave apparently interact special material max chikumbutso produce electricity albeit higher voltage amperage system source power electric motor vehicle drone system demonstrated electric motor connected reduction gearbox generator system small electric charge drive electric motor inturn drive generator producing upto volt max explained arrangement special magnet generator jump volt volt volt explained low rpm generator minimise heat losse observe system greener machine scientific community long time natural occuring quartz interact radio wave produce voltage albeit nano volt range radio wave ultra low frequency long wavelength propagate long distance max claim greener machine develop kilovolt electricity volt input interaction volt produced radio wave physically machine creating energy law thermodyanamic energy created destroyed greener machine violation proven physical law essentially claiming created extraodinary power ability material previously exist case validated subjected material peer review rigorous testing greater scientific community electric motor transformer system machine convert volt charge volt incredible impossibility break law law thermodynamic oblitarate newton law motion forgetting law conservation energy closed system contraption make similar claim perpetual motion machine throughly discredited create energy nothing universe splendour glory surely max well tgfredwsa nhai veduwe kare possibility flying impossiblegwazh renyu hatirisvore thnk potential law brokenthey man made law broken chatoda true wat claim give time toona kuty howfarkare chaiyo cure malaria find toona kuty howfar maguy amazed achieve somehw sme white man gna discover buy alter human dna ryt nwwat possiblei hope alive proved wrong world chabva ryt zim panace marvellous celebrate today saith congrad mafirekureva patented already speaking negatively here electric car decade country adventure geez patent refer exclusive protect inventor idea reproduced other electric car jus general exclusive solely produce patented design technology used shape name trademark car george sebedebe remember israel united state western country programme kill scientist country kill young man people stupid give protection son daughter satan kill young man micdeez patented protected patented zimbabwe fair game copy technology china developed reverse engineering pple patent perfectly legal often anxious amazingkeep chiko poor reporting sound absolute nonsense reporter inventor head examined suspect hypomania ruled simbi congrat guy dont listen hatersndovanokuona uchifamaba pamusoro pemvura voti becoz swim wadadisa nyika yedu waal electric car technology highbrid helicopter deal united kingdom started testing electric copter week guy ready sell ahead competition patent invention hasnt geez amazing job guy done hope full support government ray guy electric car recharged move point charging outletthis groundbreaking invention world overwish success brother god bless you bernard muchabaiwa selfcharge dear sound proverbial perpetual energy machine law physic that energy created form source electricity electric car run tot decoy limited law physic taught discovered note window invention closed closed mind heart specifically coming nasa german engineer people readily accept god samaita again lunatic think pure diesel drip rock claim empty shallow suspect guy imported knocked kit assembled locally utter perfection model shown good shore true guy attract zim media cnn bbc etc amazing verdict dont fishy good true true ndoro hope time government wont obsticle positive developmentover year celebrating level literacy africa show worldit oportunity explore make invested human resource past yearsthis local&need home support expect world itthe state poticize projectbut give green light fly can& surely wil inspire potential inventer scaterd invester institution specialise traininglet support home grown ideas solve problem especialy wen oportunity arise one samanyika chaiye haiz taisek ere iyi ndiri kurasika apa ndoo chikopokopo chachingoma ere chaakuda kumera mapapiro toti makorokoto ere mhondoro yemvura dumisani saith unveiling harare bulawayo tsholotsho london york government approvalis needed make product electric kettle market sell unlessit reglated mining explosive weapon understand journalist exposing mediocrity journalist asked question common sense government approval people want market product good product bee wake day decide make plane sell bro product concern public safety commercialised government certify government people journalist mentioned harare company approved operate location apply coz registered gitsa uverenge shaa hanzi kuharare wekwa whir approval gvt involve human safety air space restricted radar gvt approve thou idea suppressing inventor mwana waprophet makandiwa iyeye ehe chitaurai tinzwe mwana waprophet emmanuel makandiwa iyeye staff reporter mwana wamakandiwa pakuita seiko iwe unongotisembura nesu chokwadi ndiye ted vacho great children god good thing behold give power harare mwana wamakandiwa stupid incredibly dumb bikita iwe ndege hachisi chingoro mhani chaunongogadzira wototakurisa manyuwa akatengesera vanhi kanhu kanodonha minute handiti anodungwa hurumende inotanga yagutsikana ozonzi ngaachitengesa bikita iwe ndege hachisi chingoro mhani chaunongogadzira wototakurisa manyuwa akatengesera vanhi kanhu kanodonha minute handiti anosungwa hurumende inotanga yagutsikana ozonzi ngaachitengesa justin mwana waprophet iyeye conman justin what next diesel rock guy didi mutasa nolonger gvt wit man guy move forward chibaba hey guy what negativityam bitter mansaith good work pano itwa chakanaka pese hapashaikwe type iyoyi bernard muchabaiwa nxaaa ado nothing frame mind fly helicopter craft adequately tested ideas uprooted somewhere invention write home there patent foot zonkejobscom great work good new entire nation zimbabwe job creation mhofela salute guy finally making world dure wrnt yhrough hard time uou reached tis far dont discouraged dome peoplr copied product elsewhere important copied bring employment country eventually imput product manufactured locally done bongani brian great storey lack photos make storey vague completely storey fidza son prophet remember prophe ecy marvel hakuna zvakadaro year year and lot people band benz madza toyoya stage dont play mind manenji long awaited reality remember prophet makandiwa highlighted church service reassured congregant school dropout place elude guy coming world class generator world seen year memory line rizza awww amaihwe gulliblei lost faith zimbabwe whole tinevimbo good job let support stop jap business friend advise automotive giant france germany japan risk durability product international objective thinking chibaba thot daniel zimbabwean opressed couldnt support helicopter suppossed developed saith hahahahaha black pple vamwe vakutiwo mwana waprophet hmmmmmmmm zvakaoma muafrica mudhara hope true dont forget desiel pachinhoyi zimbabwean dont hurry congratulating let helicopter car make noise congratulate car big saith technology doesnt website formed sudden appear newspaper nowhere big joe chose chinhu chinotanga website inotogadzirwa zviri kuunganidzwa coming justin clever guy exploit support new read inductive charging also wireless charging electromagnetic field transfer energy object charging station energy inductive coupling electrical device energy charge battery run device induction charger typically induction coil create alternating electromagnetic field charging base station induction coil portable device take power electromagnetic field convert back electric current charge battery induction coil proximity combine form electrical transformer electric toothbrush recharge battery metal contact toothbrush base commercial website howstuffwork inc howstuffworkscom retrieved patentussery resonant inductive charging circuitnot important greater distance sender receiver coil achieved inductive charging system resonant inductive coupling recent improvement resonant system include movable transmission coil mounted elevating platform arm material receiver coil made silver plated copper aluminium minimise weight decrease electrical resistanceresistance due skin effect advantage protected connexion corrosion electronic enclosed water oxygen atmosphere safer medical implant embedded medical device skin wire penetrate skin increase risk infection durability constantly plug unplug device significantly wear tear socket device attaching cable non radiative energy transfer can convenient messy cable disadvantage lower efficiency waste heat main disadvantage inductive charging lower efficiency increased resistive heating comparison direct contact implementation lower frequency older drive technology charge slowly generate heat portable electronicscitation neededdateaugust slower charging due lower efficiency device longer charge supplied power amount expensive inductive charging require drive electronic coil device charger increasing complexity cost manufacturing newer approaches reduce transfer losse ultra thin coil higher frequency optimised drive electronic result efficient compact charger receiver facilitating integration mobile device battery minimal required rewayi zwanunoda brain brain common dont common saith faith invention zim changosara kuti tione tibelive responsible authority back him bidzo akapenga mfana wepa lawez tathokoza bambo chauta akutsogoleleni koma tifuna kuyamba tapenyetsetsa ndekeyo akawanda land diesel flow rock smell rat tawanda god bless brother putting zimbabwe map proud big joe mwari anonakidza wena chikumbutso haaaaa ndatenda jehova vanokuda piwa dzimwe njere futi blessed people perform shocking miracle invention brought land ukaona anokugumbukira zvizive kuti establishment wakasimbiswa kare vanonzwa masvosve okushatirwa vanenge vachikusimudzira conclude god bless blessed aaaaaaa ndanakidzwawo pakufara kwauri kuita ndakadzidziswa kufara nevanofara happy you mafirakurehwa smoked sock dropped form understand physic electronic kwirai ndege dzenyu pana magent stick baa saa inventyour car invented guy byd bought byd put tumasticker twavo chasarachii utopia frog eat maize chikopokopo wandiuraya ndatambudzwa zanupf adapted technology called invention chinese kit material single originality redefine originality usual synonymous zanupf deceptive guy history shocking technology gurus website rob davy storey fiction scam harare scam finger burnt tafirenyika mukiwa awesome development zimbabwe engineer support require realise dream establishing car manufacturing plant jay personally scumthe guy produced product short period time potole comment hey people jealous good job budiriro munyikasaka munodeionly miracleman hero industry mechanic blessed stay blessed technology tingatodzoka kumusha moving manwe industry back country miiro david wonderful disaprove european african dull peter made year working online full time student online business opportunity heard made great money friendly happy found here doing ndhlovu true storey started back heard car camera generator year met advising management confirmed reading paper confirm true perpetual energy physic law carefully crafted stop thing cellular found movy today way yithroh word cross folly perishing saved power god written destroy wisdom wise discernment discerning thwart wise scribe debater age god made foolish wisdom world since wisdom god world god wisdom pleased god folly preach save believe jew demand sign greek seek wisdom preach christ crucified stumbling block jew folly gentile called jew greek christ power god wisdom god foolishness god wiser men weakness god stronger men mark haha scam car production china year helicopter kit unit assemble drone video transmission gear built china alltech people fame ethel pliz give contact detail person ideas invent south africa moment struggling funding pliz ","m_szGeo1":"Zimbabwe","m_szSourceType":"source_news","m_szSrcUrl":"https://www.newsday.co.zw/2015/07/22/saith-unveils-a-helicopter/","m_Places":["Harare","Zimbabwe","Zim","Israel","United States","China","United Kingdom","Guys","Africa","Bulawayo","London","New York","Justin","Ado","France","Germany","Japan","Utopia","South Africa"],"m_People":["Sangulani Max Chikumbutso","Teddy Almeida","Justin M July","Wat Else","Mafirekureva","George Sebedebe","Toti","Makandiwa","Waprophet Emmanuel Makandiwa","Didi Mutasa","Bongani Brian","Safer","Saa","Robbery Davies","Miiro","David","Heres","Dk"],"m_Companies":["Sounds","Volt","Wish","Old Technology","Nasa","Diesel","Cnn","Bbc","Ndoro","Good News","Prophet","Howstuffworks, Inc.","Brains","Utopia","Alltech"],"m_BiGrams":["electric car","radio wave","inductive charging","saith technology","greener machine","electric motor","mwana waprophet","saith unveil","unveil helicopter","hybrid helicopter","electric vehicle","god bless","electromagnetic field","induction coil","lower efficiency"],"m_TriGrams":["saith unveil helicopter"],"m_SocialTags":[],"m_Topics":[],"m_Industry":[],"m_Technology":[],"m_BiCnt":[6,5,5,4,4,4,4,3,3,3,3,3,3,3,3],"m_TriCnt":[3],"m_iDocBodyWordCnt":1813}
