{"m_szDocID":"72439","m_szDocTitle":"Will Hydrogen Cars Finally Hit the Road?","m_szYear":"2014","m_szDocSumamry":"Will Hydrogen Cars Finally Hit the Road? By Kat Kerlin , UC Davis | August 30, 2014 Last Updated: August 30, 2014 12:55 pm Automakers have spent more than $9 billion on fuel cell development. Toyota, whose fuel cell vehicles are set to hit the market next year, is investing in hydrogen fueling infrastructure in California. (John Lloyd/Flickr) A number of factors are converging to make hydrogen fuel cell vehicles more attractive to investors and consumers, according to a new report. “We seem to be tantalizingly close to the beginning of a hydrogen transition,” says Joan Ogden, professor of envi","m_szDocBody":"hydrogen car finally hit road kat kerlin davis updated automaker spent billion fuel cell development toyota fuel cell vehicle set hit market year investing hydrogen fueling infrastructure california john number factor converging make hydrogen fuel cell vehicle attractive investor consumer report tantalisingly close beginning hydrogen transition joan ogden professor environmental science university california davis lead study year critical determining hydrogen vehicle year electric vehicle decade odgen colleague strategy developing fuel station infrastructure falling cost fuel cell vehicle hydrogen station component array sporty hydrogen car market major car maker ample lowcost natural gas making hydrogen creating favourable condition fueling station sufficient hydrogen fueling location major challenge chicken egg dilemma automaker reluctant market car infrastructure station provider reluctant build station car recently however regional publicprivate partnership emerging develop smart comprehensive buildout strategy location globe researcher calculated targeted regional investment million support station fcvs make hydrogen costcompetitive gasoline costpermile basis level investment poised happen place california germany japan california toyota california state recently awarded million build hydrogen fuel station hyundai leasing tucson fcvs select consumer car makershonda toyota bmw nissan daimlerexpect production vehicle road year toyota fuel cell vehicle set hit market year investing hydrogen fueling infrastructure state respect hydrogen fuel cell car offer consumer similar superior today gasoline car ogden say technology readily enable large vehicle size driving range mile fast refuelling time minute hydrogen fuel cell vehicle achieve low carbon futurewithout compromising consumer expectation plugin electric efficient internal combustion engine vehicle hydrogen important part portfolio approach sustainable transportation california hydrogen part fuel mix integral state reaching twin goal million zeroemission vehicle road percent reduction level greenhouse gas emission hydrogen fcvs increasingly critical technology reaching longterm climate goal potential capturing major fraction world light duty passenger car fleet however hydrogen transition certain hydrogen face range challenge economic societal implemented large scale transportation fuel ogden say question isnt fuel cell vehicle technically ready are build confidence hydrogen future investor fuel supplier automaker and course consumer ","m_szGeo1":"United States","m_szSourceType":"source_news","m_szSrcUrl":"http://www.theepochtimes.com/n3/924268-will-hydrogen-cars-finally-hit-the-road/","m_Places":["Toyota","California","Germany","Japan","Tucson"],"m_People":["Kat Kerlin","John Lloyd","Joan Ogden","Odgen","Honda"],"m_Companies":["Uc Davis","Flickr","University Of California","Hyundai","Bmw"],"m_BiGrams":["fuel cell","cell vehicle","hydrogen fuel","hydrogen fueling"],"m_TriGrams":["fuel cell vehicle","hydrogen fuel cell"],"m_SocialTags":[],"m_Topics":[],"m_Industry":[],"m_Technology":[],"m_BiCnt":[8,6,4,3],"m_TriCnt":[6,3],"m_iDocBodyWordCnt":322}
