{"m_szDocID":"73262","m_szDocTitle":"Boeing, SpaceX win contracts to build 'space taxis' for NASA | Reuters","m_szYear":"2016","m_szDocSumamry":"Boeing, SpaceX win contracts to build 'space taxis' for NASA CAPE CANAVERAL/WASHINGTON | By Irene Klotz and Andrea Shalal NASA astronaut Randy Bresnik prepares to enter Boeing's CST-100 spacecraft for a fit check evaluation at the company's Houston Product Support Center in this undated image. NASA will partner with Boeing and SpaceX to build commercially owned and operated 'space taxis' to fly... Reuters/NASA/Handout via Reuters 1 of 4 right An interior view of Boeing's CST-100 spacecraft, which features LED lighting and tablet technology, is seen in an undated NASA handout image. Reuters/NAS","m_szDocBody":"boeing spacex win contract build space taxis nasa cape irene klotz andrea shalal nasa astronaut randy bresnik prepare enter boeing cst spacecraft fit cheque evaluation company houston product support centre undated image nasa partner boeing spacex build commercially owned operated space taxis fly reuter interior boeing cst spacecraft feature led lighting tablet technology undated nasa handout image nasa public affair officer stephanie schierholz nasa administrator charle bolden astronaut bob cabana director nasas kennedy space centre kathy lueder programme manager nasas commercial crew programme astronaut mike fincke commander the ingall kathy lueder programme manager nasas commercial crew programme speak astronaut bob cabana director nasas kennedy space centre astronaut mike fincke commander international space station new conference nasas ingall cape nasa partner boeing spacex build commercially owned operated space taxis fly astronaut international space station ending dependence russia ride official tuesday space agency considered bid privately owned sierra nevada corp opted award longtime aerospace contractor boeing californias spacex contract valued combined billion develop certify fly sevenperson capsule boeing awarded billion spacexs billion spacex run technology entrepreneur elon musk chief executive officer electric car manufacturer tesla motor spacex deeply honoured trust nasa musk south africaborn canadian american billionaire vital step journey ultimately star make humanity multiplanet specy award position boeing spacex ready commercial flight service kathy leuder manager nasas commercial crew programme contract requirement the company proposed work government accepted that leuder told reporter conference call contract urgency rising tension united state russia annexation crimea region ukraine support rebel eastern ukraine boeing cst spaceship launch aboard atlas rocket built united launch alliance partnership lockheed martin corp boeing spacex billion nasa contract fly cargo space station intend upgrade dragon freighter carry astronaut nasa addition test flight award include option operational mission flying astronaut commercially united state nasa end russias monopoly space station crew transport agency pay million person ride russian soyuz capsule flight astronaut retirement space shuttle fleet china country fly people orbit united state russia member nation space station partnership nasa spent billion investing partner company commercial crew programme boeing spacex won nasas development fund company retain ownership vehicle sell ride customer nasa including private tourist work underway making possibility someday planet earth space kennedy space centre director astronaut bob cabana lot cheering success commercial crew programme mean nasa mean human spaceflight everyone programme based publicprivate partnership created cargo line station research laboratory fly mile earth addition spacex nasa billion contract orbital science corp resupply mission boeing win space important symbolically christian maye industrial analyst edward jone louis rate boeing stock hold but financially people back earth maye boeing space network businesse contribute percent total revenue billion contract multiple year move needle added boeing share closed percent higher ","m_szGeo1":"United States","m_szSourceType":"source_news","m_szSrcUrl":"http://www.reuters.com/article/us-usa-boeing-spacetaxi-idUSKBN0HB2B120140916?feedType=RSS&feedName=scienceNews","m_Places":["Washington","Houston","Washington Nasa","Russia","California","South Africa","United States","Ukraine","St. Louis"],"m_People":["Irene Klotz","Andrea Shalal","Randy Bresnik","Robert Markowitz","Stephanie Schierholz","Charles Bolden","Bob Cabana","Kathy Lueders","Mike Fincke","Bill Ingalls","Elon","Kathy Leuders","Christian Mayes"],"m_Companies":["Boeing","Spacex","Nasa","Support Center","Reuters","Public Affairs","Kennedy Space Center","International Space Station","Sierra Nevada Corp","Tesla Motors","United","Alliance","Lockheed Martin Corp","Orbital Sciences Corp","Edward Jones"],"m_BiGrams":["boeing spacex","commercial crew","crew programme","space station","space taxis","boeing cst","astronaut bob","bob cabana","kennedy space","space centre","manager nasas","nasas commercial","united state"],"m_TriGrams":["commercial crew programme","astronaut bob cabana","manager nasas commercial","nasas commercial crew"],"m_SocialTags":[],"m_Topics":[],"m_Industry":[],"m_Technology":[],"m_BiCnt":[],"m_TriCnt":[],"m_iDocBodyWordCnt":445}
