{"m_szDocID":"73290","m_szDocTitle":"Solar-Powered Car From Netherlands Comes To US (Stella)","m_szYear":"2013","m_szDocSumamry":"You may remember a lovely “family-sized” solar-powered electric car named Stella . She raced in last year’s World Solar Challenge and won in the Michelin Cruiser Class . Reportedly, the Eindhoven crew behind the solar-powered car is looking to commercialize it within 5–10 years. Perhaps the US trip is aimed at connecting with potential investors. Below are a bunch of photos of Stella at PlugShare’s offices in Venice, California, to launch National Drive Electric Event. Following the pictures is a lot more info on Stella. Thanks to Zan Dubin Scott of Plug In America for passing along the pictur","m_szDocBody":"remember lovely familysized solarpowered electric car named stella raced lastyear world solar challenge won michelin cruiser class reportedly eindhoven crew solarpowered car commercialise year trip aimed atconnecting potential investor bunch photos stella plugshare office venice california launchnational drive electric event picture lot info stella zan dubin scott plug america passing picture plugshare initially taking sharing them zan attended day national drive electric week tuesdayatucla couple picture day bottom well uclaevent zan wrote great event ucla yesterday hundred attended heat wave los angele gave test drive dozen evs stella front chevy volt behind stella front chevy volt behind tesla model ucla national drive electric week event byd electric bus ucla national drive electric week event passed plug america solar panel car dont plug charge mile range speed mph kwh lithionion battery solar array size small home dutch government eindhoven university technology student designed built raced stella win world solar challenge birthplace storied launched eras resurgence average stella generate electricity typical day student expect car commercialised year packaged deal energy car lex hoefsloot leader stellas eindhoven student team lex added frustrated solarpowered car oneseater hadnt technology evolve year thought dont ittheir bigger goal counter climate change hope car encourage solar car company build similar solarpowered car here info eindhoven team leader stella year conception roadready driving coast national drive electric week event cupertino saturday solar panel commonly home special lightweight coating avoided heavy glass average person holland drive mile day stella day roughly what needed eindhoven student developing plan commercialise car stella prototype market year easy try hoefsloot said stella consist existing technology common solar panel panasonic lithiumion battery peter van deventer diplomatic liaison director consulate general netherland coast coast emobility programme stella brought publicprivate partnership dutch government public partner stella officially kicked national drive electric week drive cupertinos national drive electric week event parade break world record receive guinness world recordstm certificate stella officially conclude national drive electric week capitola photos plugshare courtesy plug america youd attend cleantechnica solar event date hottest cleantech new subscribing free cleantech newsletter eye sectorspecific new also free solar energy newsletter electric vehicle newsletter wind energy newsletter tag national drive electric week plug america plugshare stella ucla zan dubinscott zachary shahan tryin and specy letter time spend time cleantechnica director chief editor otherwise enthusiastically fulfilling duty obsession gas solar love planetsave bikocity president important media zach recognised globally solar energy electric car energy storage wind energy expert speak related conference event connect social media zacharyshahancom related post ","m_szGeo1":"United States","m_szSourceType":"source_news","m_szSrcUrl":"http://cleantechnica.com/2014/09/17/solar-powered-car-netherlands-us/?utm_source=feedburner&utm_medium=feed&utm_campaign=Feed%3A+IM-cleantechnica+%28CleanTechnica%29","m_Places":["Eindhoven","California","America","Los Angeles","Cupertino","Capitola, Ca."],"m_People":["Lex","Peter Van Deventer","Zachary Shahan","Zach"],"m_Companies":["Michelin","Volt","Eindhoven University Of Technology","Panasonic","Guinness World Records","Capitola, Ca."],"m_BiGrams":["drive electric","national drive","electric week","plug america","week event","solarpowered car","solar panel"],"m_TriGrams":["national drive electric","drive electric week","electric week event"],"m_SocialTags":[],"m_Topics":[],"m_Industry":[],"m_Technology":[],"m_BiCnt":[9,8,8,4,4,3,3],"m_TriCnt":[8,8,4],"m_iDocBodyWordCnt":411}
