{"m_szDocID":"73301","m_szDocTitle":"Honda Clarity Fuel Cell Sedan Makes North American Debut at 2015 Los... -- LOS ANGELES, Nov. 18, 2015 /PRNewswire/ --","m_szYear":"2015","m_szDocSumamry":"Honda Clarity Fuel Cell Sedan Makes North American Debut at 2015 Los Angeles Auto Show Honda Logo. LOS ANGELES, Nov. 18, 2015 /PRNewswire/ --Â The Honda Clarity Fuel Cell sedan makes its North American debut at the 2015 Los Angeles Auto Show today as Honda announced additional details for its most advanced zero-emissions vehicle in the U.S. market. Serving as the next evolution of Honda's fuel cell technology, the Clarity Fuel Cell leverages two decades of advancement in Honda fuel cell technology, showcasing significant gains in packaging, interior space, efficiency and real-world performance.","m_szDocBody":"honda clarity fuel cell sedan make north american debut los angele auto show honda logo los angele nov the honda clarity fuel cell sedan make north american debut los angele auto show today honda announced additional detail advanced zeroemission vehicle market serving evolution hondas fuel cell technology clarity fuel cell leverage decade advancement honda fuel cell technology showcasing significant gain packaging interior space efficiency realworld performance additionally honda announced platform underpinning clarity fuel cell serve foundation nextgeneration honda plugin hybrid electric vehicle phev launch nationwide triple allelectric range accord plugin hybrid sedan honda begin delivery clarity fuel cell customer late select fuel cell dealer select california market starting los angele orange county san francisco bay area sacramento eventually honda expand scope marketing additional california market state including northeast hydrogen refuelling network expand clarity fuel cell priced competitively segment honda expect generation environmental vehicle include clarity fuel cell serve volume pillar honda hydrogen fuel cell vehicle emission technology honda believe worked advance year john mendel executive vice president american honda motor inc vehicle clarity fuel cell potential game changer offer uncompromising emission customer experience utility range refuelling time par today gasolinepowered car customer interested clarity fuel cell encouraged receive information opportunity future clarity fuel cell customer honda clarity fuel cell technological innovation clarity fuel cell created fuel cell stack percent compact predecessor percent increase power density compared outgoing honda fcx clarity compact fuel cell powertrain comparable size engine fit hood car allowing spacious cabin seating passenger honda clarity fuel cell feature driving range estimated exceed mile anticipated refuelling time approximately minute pressure mpa progression hondas dynamic fcv styling honda clarity fuel cell feature low wide aerodynamic body clean character line interior strive achieve refined harmonious experience rich material intuitive streamlined control additional feature include honda sensing suite safety driver assistive technology support apple carplay android auto led exterior lighting inch aluminium alloy wheel clarity fuel cell black white signature red exterior paint scheme honda see hydrogen hydrogen fuel cell vehicle promising pathway address climate change reducing emission transportation honda announced companywide goal reducing emission percent clarity fuel cell sery bold step achieving goal nextgeneration plugin hybrid addition platform underpinning clarity fuel cell serve foundation nextgeneration phev honda launch volume production vehicle honda line nationwide featuring iteration twomotor hybrid plugin system offering significant improvement battery capacity power nextgeneration honda phev offer triple mile allelectric range accord plugin hybrid sedan range enable emission commute average american increase power enable operation highway speed honda fuelcell vehicle leadership honda led industry decade development deployment fuelcell technology extensive realworld testing customer deployment including government fleet customer firstever retail customer leasing programme introduction firstgeneration fuel cell vehicle fcx honda made significant technological advancement fuelcell vehicle operation hot freezing weather meeting customer expectation safety regulation honda deployed vehicle japan including fcx clarity named world green car company delivered vehicle individual retail consumer collected valuable feedback realworld fuelcell vehicle public hydrogen refuelling station hondas secondgeneration fuelcell vehicle fcx clarity launched quickly heralded technological breakthrough areas design packaging efficiency world dedicated platform fuelcell vehicle fcx clarity powered honda vflow fuel cell stack positioned centre tunnel vehicle electric motor located low front vehicle providing performance par gasoline powered sedan including mile driving range effort speed advancement refuelling infrastructure california american honda joined publicprivate partnership husa bring togetherautomaker government agency hydrogen supplier hydrogen fuelcell industry coordinate research identify costeffective solution deploy infrastructure deliver affordable clean hydrogen fuel united state additionally effort support wider introduction fuelcell vehicle honda pledged million financial support firstelement fuel build additional hydrogen refuelling station state california honda entered longterm collaborative agreement general motor codevelop nextgeneration fuelcell system hydrogen storage technology aiming timeframe collaboration expect succeed sharing technological expertise economy scale benefit honda fuelcell vehicle first original fcx epa carbcertified fuelcell vehicle fcx world production fuelcell vehicle introduced japan additional honda fuel cell technology first include fuelcell vehicle start operate subfreezing temperature fuelcell vehicle leased individual customer july manufacturer build produce dedicated fuelcell vehicle fcx clarity production line specifically made fuelcell vehicle manufacturer create fuelcell vehicle dealer network honda environmental leadership based vision blue sky children honda taking comprehensive approach reducing environmental impact product advancing fuel efficiency low emission funtodrive performance powertrain technology including fuelefficient engine transmission advanced electromotive technology honda offer nextgeneration advanced powertrain vehicle including launch honda clarity fuel cell sedan allnew honda plugin hybrid model honda expand advanced two threemotor hybrid system year come together vehicle offer significant sale volume enabling honda bring ultralow carbon transportation consumer ","m_szGeo1":"United States","m_szSourceType":"source_news","m_szSrcUrl":"http://www.prnewswire.com/news-releases/honda-clarity-fuel-cell-sedan-makes-north-american-debut-at-2015-los-angeles-auto-show-300181241.html","m_Places":["Los Angeles","California","Sacramento","Japan","United States"],"m_People":["John Mendel","Fcx Clarity","Phev Honda","Carb"],"m_Companies":["Honda","Logo","Nationwide","Orange Counties","American Honda Motor Co","Apple","Cell Technology","State Of California","General Motors","Epa"],"m_BiGrams":["fuel cell","clarity fuel","fuelcell vehicle","honda clarity","plugin hybrid","fcx clarity","vehicle fcx","los angele","cell sedan","honda announced","cell technology","cell serve","hydrogen refuelling","cell vehicle"],"m_TriGrams":["clarity fuel cell","honda clarity fuel","fuelcell vehicle fcx","fuel cell sedan","fuel cell technology","fuel cell serve","fuel cell vehicle","vehicle fcx clarity"],"m_SocialTags":[],"m_Topics":[],"m_Industry":[],"m_Technology":[],"m_BiCnt":[],"m_TriCnt":[],"m_iDocBodyWordCnt":741}
