{"m_szDocID":"74594","m_szDocTitle":"Denmark & New York City Fight Climate Change","m_szYear":"2012","m_szDocSumamry":"October 14th, 2014 by Guest Contributor   By Mark Watts, Executive Director of C40 In September, all eyes were on New York City, which hosted the UN Secretary General’s Climate Summit. As part of Climate Week NYC, the summit provided space for several major announcements around the important role that cities have to play in reducing global greenhouse gas emissions , including a global Compact of Mayors . City leaders from around the world attended the summit to share both ambitious plans and on-the-ground successes, establishing a high bar for their counterparts in national governments. Althou","m_szDocBody":"guest contributor mark watt executive director september eye york city hosted secretary general climate summit part climate week nyc summit provided space major announcement important role city play reducing global greenhouse gas emission including global compact mayor city leader world attended summit share ambitious plan ontheground successe establishing bar counterpart national government plan programme aim combat climate change international level smaller individual successe teach valuable lesson city work together danish cleantech hub publicprivate partnership denmark york city accelerate solution sharing single point entry cleantech activity programme designed york capitalise denmark technological savvy born decade experience cleantech company physical headquarter york give local entrepreneur leader organisation danish knowhow providing danish company entree york marketplace lord mayor copenhagen frank jensen emphasise city bring other copenhagen york shared focus sustainable solution achieve economic growth tackling climate change critical city collaborate another fact city credit successful urban sustainability project collaboration sharing ideas city recent siemen city climate leadership award lord mayor melbourne robert doyle told assembled mayor promise ill stealing ideas shamelessly cooperation process city climate leadership aim facilitate member megacity including york copenhagen represent million people percent global gdp case danish cleantech hub confederation danish industry city york connected green growth network active working helping city realise sustainable growth innovation technology climate change global challenge biggest impact local level network bridge gap impeccably allowing city share information work best kyle kimball president york city economic development corporation thrilled danish cleantech hub urban future lab york city pioneer resiliency technology incubator direct result process collaboration nyc danish company solve climate challenge knowledge expertise europe forward thinking resiliency expert york city recently embraced major investment clean tech solution part city sustainability initiative city ramped resiliency effort wake super storm sandy author mark watt serve executive director city climate leadership group prior joining mark director arup energy consulting team based london focused city sustainability lead arup partnership city committed tackling climate change prior joining arup director climate change sustainable transport adviser mayor london role london evening standard intellectual force ken livingstone drive make london leading light battle global warming led development london groundbreaking climate change action plan programme project reduce london carbon emission youd attend cleantechnica solar event date hottest cleantech new subscribing free cleantech newsletter eye sectorspecific new also free solar energy newsletter electric vehicle newsletter wind energy newsletter ","m_szGeo1":"United States","m_szSourceType":"source_news","m_szSrcUrl":"http://cleantechnica.com/2014/10/14/denmark-new-york-city-fight-climate-change-cleantech-partnership/?utm_source=feedburner&utm_medium=feed&utm_campaign=Feed%3A+IM-cleantechnica+%28CleanTechnica%29","m_Places":["C40","New York City","Nyc","Denmark","New York","Copenhagen","Siemens City","Melbourne","New York City Economic Development Corporation","Europe","London"],"m_People":["Mark Watts","Frank Jensen","Robert Doyle","Kyle Kimball","Ken Livingstone"],"m_Companies":["Un","Danish Cleantech","Leadership Group","Gap","New York City Economic Development Corporation","Ramped","Arup","London Evening Standard"],"m_BiGrams":["climate change","york city","danish cleantech","cleantech hub","city climate","climate leadership"],"m_TriGrams":["danish cleantech hub","city climate leadership"],"m_SocialTags":[],"m_Topics":[],"m_Industry":[],"m_Technology":[],"m_BiCnt":[6,5,3,3,3,3],"m_TriCnt":[3,3],"m_iDocBodyWordCnt":384}
