{"m_szDocID":"75182","m_szDocTitle":"Global Carbon Markets Through Private-Government Partnership | CleanTechnica","m_szYear":"2016","m_szDocSumamry":"Global Carbon Markets Through Private-Government Partnership January 3rd, 2016 by Mridul Chadha   Editor’s Note: This article is one submission in a live Masdar blogging contest . Very simply, the focus of the contest submissions is to answer the question: “In your view, what are the policies that governments should take to encourage public-private partnership and enable the private sector to develop the goods and services necessary for a global transition to a low-carbon economy by 2030?” The Paris climate change agreement has paved the way for a comprehensive reduction in greenhouse gas emis","m_szDocBody":"global carbon market privategovernment partnership mridul chadha editor note submission live masdar blogging contest simply focus contest submission answer question view policy government encourage publicprivate partnership enable private sector develop good service global transition lowcarbon economy paris climate change agreement paved comprehensive reduction greenhouse gas emission ultimate target restrict rise global temperature degree huge target however achieved action government alone bureaucracy move slowly yield timely efficient result thus equal greater responsibility fall private sector number country implemented direct policy programme industry reduce ghg emission mostwell european union zealand emission trading scheme capandtrade programme jurisdiction operational year now varying degree success reducing ghg emission however programme scheme implemented year discussion argument jurisdiction disagreement future respective programme continue global disagreement inclusion international aviation industry european union emission trading scheme prime example difference opinion approaches lead delay effective implementation lowcarbon initiative delay expansion improvement capandtrade scheme led push selfregulation industry already number company sector started taking initiative reduce direct indirect ghg emission private sector company microsoft introduced internal carbon price initiative inspire employee track cheque emission activity fund bank financial institution announced plan reduce exposure investment carbonintensive asset decision funding agency push company increase investment lowcarbon asset increasing number company monitoring reporting ghg emission carbon disclosure project company voluntarily sharing data emission energy consumption parameter carbon disclosure project rank company thebasis transparency effort reduce emission year industrial association play major role encouraging company monitor report measure reduce ghg emission international civil aviation organisation international maritime organisation long opposed unbacked action reduce ghg emission implemented measure improve energy efficiency however world expect implement marketlinked measure directly reduce ghg emission paris climate change agreement proposed emission reduction target programme aviation shipping sector industrial association proactively propose measure implement price carbon acting ghg emission private sector company playing pioneering role increasing renewable energy company set inhouse power generation capacity based renewable energy reduce carbon footprint reduce energy dependence fossil fuel leading global company google apple amazon facebook announced grand plan increase renewable energy measure private sector expected medium term clear government world partner private company achieve lowcarbon goal youd attend cleantechnica solar event date hottest cleantech new subscribing free cleantech newsletter eye sectorspecific new also free solar energy newsletter electric vehicle newsletter wind energy newsletter ","m_szGeo1":"New Zealand","m_szSourceType":"source_news","m_szSrcUrl":"https://cleantechnica.com/2016/01/03/global-carbon-markets-private-government-partnership/","m_Places":["Paris","New Zealand"],"m_People":["Mridul Chadha"],"m_Companies":["Target","European Union","Microsoft","Maritime","Un","Google","Apple","Amazon","Facebook"],"m_BiGrams":["ghg emission","private sector","reduce ghg","renewable energy"],"m_TriGrams":["reduce ghg emission"],"m_SocialTags":[],"m_Topics":[],"m_Industry":[],"m_Technology":[],"m_BiCnt":[],"m_TriCnt":[],"m_iDocBodyWordCnt":369}
