{"m_szDocID":"75180","m_szDocTitle":"Charting India’s Renewable Energy Future Through Public-Private Partnership | CleanTechnica","m_szYear":"2016","m_szDocSumamry":"Charting India’s Renewable Energy Future Through Public-Private Partnership January 3rd, 2016 by Smiti Mittal   Editor’s Note: This article is one submission in a live Masdar blogging contest . Very simply, the focus of the contest submissions is to answer the question: “In your view, what are the policies that governments should take to encourage public-private partnership and enable the private sector to develop the goods and services necessary for a global transition to a low-carbon economy by 2030?” India will soon be one of the world’s largest renewable energy markets. The Indian governme","m_szDocBody":"charting indias renewable energy future publicprivate partnership smiti mittal editor note submission live masdar blogging contest simply focus contest submission answer question view policy government encourage publicprivate partnership enable private sector develop good service global transition lowcarbon economy india world largest renewable energy market indian government announced massive capacity addition target which achieved put india top renewable energy market world alongside china india announced plan solar power wind energy capacity operational marchend current combined wind solar power capacity installed india thus tremendous effort required achieve stated target indian government plan implement largescale smallscale solar wind energy project country competitive auction auction started government set project unprecedented size open sector central government auctioned project national solar mission government plan add solar power capacity ultra mega solar power project project capacity ultra mega solar power project set state number state announced respective renewable energy capacity addition target special emphasis solar power largescale solar power project auction place national state solar power policy real heroe auction private sector project developer initially indian company leading participant auction however capacity addition target increased number volume auction which turn attracted international company increased competition tariff bid slipped unprecedented level year weighted average bid solar power project fallen compete cost power generation coalbased power plant aggressive grid parity largescale participation national international private sector company company leading indian solar power market include sunedison solar skypower global other year auction clear that aggressive participation private sector steep rise indias renewable energy market possible private sector company played important role expanding indias wind energy capacity suzlon energy emerged largest wind turbine manufacturer world acquisition europebased repower indias conducive wind energy market attracted international company including vestas gamesa now company competing set indias offshore wind energy project suzlon energy invested million set project western india company expected participate firstever auction offshore wind energy project india continued participation private sector company essential achieving seemingly impossible capacity addition target set indian government aggressive participation private company set strong foundation lowcarbon growth indias economy youd attend cleantechnica solar event date hottest cleantech new subscribing free cleantech newsletter eye sectorspecific new also free solar energy newsletter electric vehicle newsletter wind energy newsletter ","m_szGeo1":"India","m_szSourceType":"source_news","m_szSrcUrl":"https://cleantechnica.com/2016/01/03/charting-indias-renewable-energy-future-public-private-partnership/","m_Places":["India","Europe","Vestas"],"m_People":["Smiti Mittal"],"m_Companies":["Energy Future","Indian Government","Indian Companies","Sunedison","First Solar"],"m_BiGrams":["solar power","wind energy","private sector","renewable energy","energy market","capacity addition","addition target","power project","indian government","energy capacity","energy project","sector company","participation private"],"m_TriGrams":["capacity addition target","solar power project","renewable energy market","wind energy project","private sector company"],"m_SocialTags":[],"m_Topics":[],"m_Industry":[],"m_Technology":[],"m_BiCnt":[10,7,6,5,4,4,4,4,3,3,3,3,3],"m_TriCnt":[4,4,3,3,3],"m_iDocBodyWordCnt":358}
