{"m_szDocID":"85842","m_szDocTitle":"Apple Unveils New Products, and Stephen Colbert Returns to Late Night - The New York Times","m_szYear":"2015","m_szDocSumamry":"The New York Times International Business |Apple Unveils New Products, and Stephen Colbert Returns to Late Night Advertisement International Business | The Week Ahead Apple Unveils New Products, and Stephen Colbert Returns to Late Night By THE NEW YORK TIMES SEPT. 6, 2015 Continue reading the main story China’s Bill of Health China reports a basket of monthly data this week that is expected to provide a clearer picture of how much its economic growth is slowing. On Tuesday, it will release trade figures for August; exports have been flat so far this year, and imports declined 15 percent in the","m_szDocBody":"york time international business apple unveil product stephen colbert return late night international business week ahead apple unveil product stephen colbert return late night york time sept continue reading main storey chinas bill health china report basket monthly data week expected provide clearer picture economic growth slowing tuesday release trade figure august export flat year import declined percent month report include inflation figure industrial output investment retail sale saturday investor watching data chinas foreign exchange reserve world largest chinas reserve expected declined surprise devaluation month currency renminbi raised concern capital outflow neil gough puerto rico debt plan puerto rico government planning complete debt restructuring plan tuesday muchawaited plan expected include moratorium bond payment structural commonwealth budget plan work gov alejandro garca padilla announced island billion debt payable completion plan postponed week government busy dealing tropical storm michael corkery debut prius photo credit kazuhiro francepresse getty image toyota motor scheduled unveil generation prius hybrid leader sale alternativefuel vehicle electric car drawing attention prius continue dominate market vehicle powered solely gasoline engine auto research firm edmundscom estimate prius account percent sale alternativefuel vehicle united state model shown event las vegas expected mileage feature technology toyota seek reestablish credential innovator environmentally friendly vehicle bill vlasic colbert return late night photo credit richard press era latenight television begin stephen colbert officially take duty host late show cbs colbert reintroduce viewer shed abrasive satirical character played year comedy central latenight programme colbert report list guest week suggest late show eclectic include hollywood royalty george clooney scarlett johansson writer stephen king tech star elon musk tesla motor travis kalanick uber presidential hopeful jeb bush john koblin apple show gadget apple plan unveil host product event held bill graham civic auditorium downtown san francisco product revamped iphone company crucial product iphone higherquality camera feature called force touch let user gain phone function pressing hard screen people briefed product upgraded apple support video game accentuate apple desire bigger presence living room apple fan expect updated ipad too katie benner continue reading main storey bank england rate decision thursday bank england announce monthly decision raise main interest rate monetary policy committee expected leave benchmark rate steady percent committee meeting mark carney bank england governor told reporter timing rate increase drawing closer expert committee raise rate half year minute committee meeting member ian mccafferty central bank needed begin process gradually raising rate face possibility increase rate sharply chad bray snapshot consumer attitude preliminary thomson michigan survey consumer sentiment released morning providing early snapshot consumer attitude month wall street expect change final reading analyst watching recent sharp stock market selloff made consumer anxious survey stable year big rise employment rose energy price fell recent market volatility economic data positive big drop consumer sentiment catch trader surprise nelson schwartz ruling gealstom deal european commission scheduled rule block general electric billion bid alstom power business antitrust ground negotiating commission month proposing sale asset allay competitor fear proposed combination french company give sway market heavy gas turbine jeffrey immelt boss expect win approval agree remedy maintained commercial logic deal david jolly version appear print york edition headline apple unveil product stephen colbert return late night order reprint today paper ","m_szGeo1":"United States","m_szSourceType":"source_news","m_szSrcUrl":"http://www.nytimes.com/2015/09/07/business/international/apple-unveils-new-products-and-stephen-colbert-returns-to-late-night.html","m_Places":["China","Puerto Rico","United States","Las Vegas","Toyota","Colbert","Hollywood","San Francisco","Wall Street","New York"],"m_People":["Stephen Colbert","Neil Gough","Alejandro García Padilla","Michael Corkery","Kazuhiro Nogi","Bill Vlasic","Richard Shotwell","George Clooney","Scarlett Johansson","Stephen King","Elon","Travis Kalanick","John Koblin","Bill Graham","Katie Benner","Mark Carney","Ian Mccafferty","Chad Bray","Nelson D. Schwartz","Jeffrey R. Immelt","David Jolly"],"m_Companies":["New York Times","International Business","Apple","Agence France-presse","Getty Images","Toyota Motor","Edmunds.com","Associated Press","Cbs","Comedy Central","Tesla Motors","Uber","Bank Of England","Policy Committee","Thomson Reuters","University Of Michigan","Nelson D. Schwartz","Alstom","European Commission","General Electric"],"m_BiGrams":["stephen colbert","colbert return","return late","late night","apple unveil","unveil product","product stephen","bank england"],"m_TriGrams":["colbert return late","return late night","apple unveil product","unveil product stephen","product stephen colbert","stephen colbert return"],"m_SocialTags":[],"m_Topics":[],"m_Industry":[],"m_Technology":[],"m_BiCnt":[4,4,4,4,3,3,3,3],"m_TriCnt":[4,4,3,3,3,3],"m_iDocBodyWordCnt":525}
