{"m_szDocID":"91626","m_szDocTitle":"Market turmoil: Wall Street hit after European shares hit 16-month low – as it happened | Business | The Guardian","m_szYear":"2016","m_szDocSumamry":"Market turmoil: Wall Street hit after European shares hit 16-month low – as it happened Worries over the world economy and the outlook for banks have sent global stock markets tumbling again Latest: Dow Jones down 177 points at the close Monday 8 February 2016 16.21 EST Last modified on Monday 8 February 2016 18.25 EST That’s all from us until tomorrow, after another day dominated by wild swings in the markets and angst over the global economy. Will Tuesday be different? Come back tomorrow and find out. Goodnight! GW US stocks close in the red Wall Street has closed for the night, after a day ","m_szDocBody":"market turmoil wall street hit european share hit month low happened worry world economy outlook bank global stock market tumbling latest dow jone point close est modified est tomorrow day dominated wild swing market angst global economy different back tomorrow out goodnight stock close red wall street closed night day turmoil major stock market dow jone industrial finished point gloom global growth hit financial stock s&p index cover stock dow shed nasdaq finished phew closing wall street bell rung photograph bloomberg losse lowest point day wall street dragged late rally energy stock credit card firm visa biggest faller dow goldman sach biggest riser faller dow tonight photograph bloomberg tech firm bad day social media network dropping record low weve covering hour hefty losse europe ftse plunged point wiping bluechip london index european market fell further hit fear banking sector global economy owen callan senior analyst cantor fitzgerald investor increasingly anxious fundamental picture world economy callan said people worried global economy beginning bank people saying again severe worrying banking sector risk asset bigger level here new storey today selloff hello stock market staging late rally bouncing earlier low dow point point couple hour ago dow jone today photograph thomson reuter big name leading wall street faller minute closing bell rung investment bank goldman sach mirroring selloff global banking stock visa close behind nike home depot boeing updated here photos wall street today trader faced day chunky losse trader steven gohl work floor york stock exchange morning photograph richard trader fred demarco left greg mulligan confer york trading floor photograph richard trader edward curran left robert arciero work photograph richard good new hour wall street close manic over bad new stock market heavily red dow point bad s&p nasdaq deeper trouble photograph marketwatch deutsche calm coco fear newsflash deutsche bank issued statement meet crucial debt repayment april frankfurtbased bank heart today market turmoil payment capacity cover due coco bond debt convert share wiped out bank hit financial problem default covered morning detail analyst fear deutsche miss coco payment economic condition worsen deutsche payment capacity year depending operating performance year here deutsches statement ifs warn market turmoil leave black hole george osborne plan stock market turmoil risk blowing multibillion pound black hole government fiscal plan warning ifs thinktank published green budget today month ahead official budget here storey britain leading expert public finance warning turmoil global stock market threaten leave black hole george osborne deficitreduction plan force chancellor raise taxe make fresh cut spending hit budget target day share price crashed europe institute fiscal study osborne plan put back black end current parliament vulnerable protracted financial market panic ifs tumbling share price wiped company quoted ftse index number factor blow chancellor plan year forecast wage growth lower previously expected knock hole budget thinktank said here full storey telegraph mehreen kahn point european banking sector lost sixth month here today market mayhem global stock gripped fresh bout panic selling raising fear health world banking system time financial crisis european market slumped lowest level year amid unremittingly bleak outlook global economy concern resilience world biggest lender euro stoxx index leading bank share fell monday trading closing plumbing depth continent lender lost day gold hit anxious investor continuing pile gold sending ounce time month holger zschaepitz trouble gold briefly jumped time june updated chart dow bank index wfc bac jpm biotech boom speedily unwound too sign yet wall street recover early selloff dow stubbornly point point broader s&p tech stockpacked nasdaq shed bad european selloff suggest facing market turbulence #dax #ftse #ibex #dow god pancake day tomorrow #shrovetuesday cnbc breaking share yelp halted earning report unexpectedly released cnbc breaking yelp announce cfo transition company intend begin cfo cnbc breaking yelp eps adj est revs est cnbc breaking share yelp resume trading slide earning unexpectedly released early announcing cfo transition technology stock hit hard today tesla electric car company slumped today dropping time year tesla share year photograph marketwatch european share slump growth bank fear global market suffered bad start week chinese year proving turbulent slump early day january chinese market closed end recent spate volatility facing investor fear slowdown global growth returned vengeance banking share poorest performer worry outlook effect negative interest rate business top cocktail concern prospect britain leaving european union concern review greek progress meeting bailout target rout widespread greek market lowest year eurofirst dropped half year low final score showed ftse fell point germany dax dropped deutsche bank lower france cac closed lower italy ftse mib fell spain ibex ended greece athen market lost wall street dow jone industrial average point justification day slump banking share laith khalaf senior analyst hargreave lansdown market worried global economic downturn time central bank dry powder left fight recessionary force table turned stock market today recent winner suffering profittaking miner virtually stock head water collapse oil price big shock financial system effect absorbed international stock market implication global demand financial badly hit late dire got european bank trading lower depth financial crisis doesnt justification dismal outlook market stuck negative feedback loop moment worth wray global stock lost trillion sense panic setting increase oil price market tony cross trustnet direct equity globe kicked week deeply downbeat mood london ftse posted selloff pushing benchmark index squarely back bearmarket territory losse mainland europe pronounced fact wti crude tested territory matter weve overriding fear global slow imminent investor adjusting portfolios suit theme risk aversion buoying precious metal gold eye break ounce time month stock ftse are sporting losse excess day underlying sense panic creeping economic data remain thin ground tomorrow downside stock attributed renewed weakness oil remain metric worth watching closely fundamentally impact supply take instil confidence market absence new bear remain control reason current market problem federal reserve ending quantitative easing programme bank america merrill lynch bloomberg storey federal reserve began withdraw monetary stimulus liquidity steadily drying ly crux broader stress financial market bank america merrill lynch violent selloff occur surprise revaluation currency switzerland china japan introduction negative interest rate head mortgage chris flanagan strategist mao ding dont necessarily lay blame market dislocation squarely monetary policymaker observe however early when fed began winding openended asset purchasesliquidity stress persistently risen served proximate episodic spike merrill lynch global financial stress index occurred they said persistence suggest deteriorating liquidity heart primary driver broader rising financial stress full storey here turbulence banking sector worry negative interest rate outlook profit slowing global growth trading barclay share halted briefly volatile movement resumed share updated slaughter deutsche bank trading germany greece bailout chinas market closed year holiday worrying share price continue tumble chris beauchamp senior market analyst selling began morning gathered pace globe afternoon join oneway move chinese investor relieved market week off absence volatility provided shanghai send worrying message investor europe worried thing current interest rate outlook recent survey fund manager rising cash balance remaining side line pulling rug remain bull market week economic data light increasingly apparent investor struggling positive new create rally bank jasper lawler cmc market said banking share europe buckled pressure global growth concern concert ugly spectre negative interest rate weak earning european bank notably deutsche bank investor significantly reassess chance earning turnaround year regulatory fine past misdeed disappointing earning sector big firm credit suisse chief executive asked bonus cut refocusing investor attention bad loan book addressed european crisis day deutsche bank issued surprise profit warning credit default swap spread ballooned investor started question bank ability fund itself cds jump caused sharp drop deutsche bank share market continue slide dow jone industrial average point greece athen market closed lowest level year bank biggest faller case bank biggest faller greece photograph reuter greece finance minister euclid tsakalotos expected review country bailout programme restart week conclude week later worry planned pension tax reform major protest recent day unnerved investor manos hatzidakis beta security told reuter market pricing financial political instability delay review updated sterling hit week low falling amid worry outlook bank concern effect vote britain leave european union month low euro updated recent move central bank push interest rate negative territory bold uncoordinated lead race bottom standard poor rating agency said european central banksin switzerland denmark sweden european central bankhave adopted negative policy rate japan surprisingly joined club year bank japan decision follow suit negative rate reinforce trend shrinking yield core government bond market yield spread japan europe standard poor economist sophie tahiri bold venture negative interest rate signal market participant central bank tool disposal meet inflation target tahiri problem developed market central bank face deflationary pressure weak commodity price incentive exchange rate combat pressure increasing competition developed market central bank stem currency appreciation signal phase extended aftermath global financial crisis independent attempt weaken exchange rate lead undesirable race bottom central bank amid current worry global economy europe start moving list strategist graham secker morgan stanley note say struggle remember occasion investor sentiment bearish widespread feel today sure worse global financial crisis fear global depression created panic market today cool disdain risk asset take beating asked client week reason bullish investor citing optimism confess couldnt answer hadnt met recent time collective noun bear sleuth doesnt detective work identify investor concerned about concern revolve usual suspect china emerging market dollar oil added fact central bank moving negative interest rate positive equity market secker feared move higher stock market prompted relief rally positive new prove shortlived investor increasingly question effectiveness central bank action europe recent investor caution focus fear excess dollar strength low oil price china plausible europe move back pecking order usual place say move uks forthcoming referendum membership place june plausible catalyst short term raise regional risk premia ongoing migrant risk eroding political cohesion medium term political uncertainty rising periphery greece daunting debt repayment due summer spain government european regulation preventing italy adopting effective bad bank solution recently elected socialist government portugal reversing prior austerity competitiveness improvement cyclical upswing market prone overlook concern opposite true growth start relapse ","m_szGeo1":"United Kingdom","m_szSourceType":"source_news","m_szSrcUrl":"http://www.theguardian.com/business/live/2016/feb/08/uk-business-confidence-falls-global-recession-fears-markets-business-live","m_Places":["Wall Street","Europe","London","New York","Frankfurt","Uk","Britain","Tesla","Germany","France","Italy","Spain","Greece","Athens","Switzerland","Japan","Shanghai","Denmark","Sweden","Portugal"],"m_People":["Goodnight","Dow","Owen Callan","Fitzgerald","Steven Gohl","Richard Drew","Fred Demarco","Greg Mulligan","Edward Curran","Robert Arciero","Deutsche","George Osborne","Mehreen Kahn","Holger Zschaepitz","Dax","Laith Khalaf","Worth W. Wray","Tony Cross","Chris Flanagan","Mao","Chris Beauchamp","Jasper Lawler","Manos","Sophie Tahiri","Tahiri","Graham Secker"],"m_Companies":["Dow Jones","Nasdaq","Goldman Sachs","Twitter","Thomson Reuters","Bank Goldman Sachs","Nike","Home Depot","Boeing","Wall Street Today","New York Stock Exchange","Ap","Good News","Marketwatch","Deutsche Bank","European Banking","Dow Bank Index","Cnbc","Yelp","European Union","Central Banks","European Banks","Us Federal Reserve","Bank Of America","Merrill Lynch","Ig","Cmc","Credit Suisse","Reuters","Standard & Poor","European Central Banks","European Central Bank","Bank Of Japan","Morgan Stanley","Central Bank"],"m_BiGrams":["wall street","stock market","interest rate","central bank","deutsche bank","negative interest","dow jone","global economy","market turmoil","global stock","global growth","banking sector","financial crisis","cnbc breaking","jone industrial","biggest faller","photograph richard","black hole","share price","fear global","market closed","banking share","oil price","merrill lynch","global financial"],"m_TriGrams":["negative interest rate","dow jone industrial"],"m_SocialTags":[],"m_Topics":[],"m_Industry":[],"m_Technology":[],"m_BiCnt":[9,9,8,8,6,6,5,5,4,4,4,4,4,4,3,3,3,3,3,3,3,3,3,3,3],"m_TriCnt":[6,3],"m_iDocBodyWordCnt":1635}
