{"m_szDocID":"92271","m_szDocTitle":"Next-generation smartphones, tablet may be 'safer' - Times of India","m_szYear":"2016","m_szDocSumamry":"‘Pepper’ humanoid robot Next-generation smartphones, tablet may be 'safer' Scientists have designed a new battery component that is far less likely to catch fire, paving the way for safer smartphones and tablets. PTI | May 16, 2014, 11.40 AM IST Scientists have designed a new battery component that is far less likely to catch fire, paving the way for saf... Read More WASHINGTON: Scientists have designed a new lithium battery component that is far less likely to catch fire and promises effective performance, paving the way for safer smartphones and tablets. \"As news reports of Lithium-Ion batte","m_szDocBody":"pepper humanoid robot nextgeneration smartphone tablet safer scientist designed battery component catch fire paving safer smartphone tablet pti ist scientist designed battery component catch fire paving saf read washington scientist designed lithium battery component catch fire promise effective performance paving safer smartphone tablet new report lithiumion battery lib fire boeing dreamliner plane tesla electric car remind battery everyday portable device tablet smartphone downside researcher said lynden archer geoffrey coate colleague cornell university explain danger lib originate electrolyte substance ion flow electrode battery electrolyte flammable liquid minimise fire hazard researcher developing stable solid electrolyte solid electrolyte fuel fire ability transport ion fallen short room temperature coatess team set tackle issue safer highperformance battery component archer team studied electrochemical characteristic material team effort led family solid polymer electrolyte good conducting lithium ion room temperature minimising risk fire material safer liquid counterpart lib highenergy lithiummetal battery promising lithiumsulphur lithiumair battery finding published american chemical society related ","m_szGeo1":"India","m_szSourceType":"source_news","m_szSrcUrl":"http://timesofindia.indiatimes.com/tech/computing/Next-generation-smartphones-tablet-may-be-safer/articleshow/35197471.cms","m_Places":["Washington","Tesla"],"m_People":["Lynden Archer","Geoffrey Coates"],"m_Companies":["Boeing","Remind","Cornell University","Archer","Journal Of The American Chemical Society"],"m_BiGrams":["battery component","smartphone tablet","scientist designed","component catch","catch fire"],"m_TriGrams":["battery component catch","component catch fire"],"m_SocialTags":[],"m_Topics":[],"m_Industry":[],"m_Technology":[],"m_BiCnt":[4,3,3,3,3],"m_TriCnt":[3,3],"m_iDocBodyWordCnt":153}
