{"m_szDocID":"97295","m_szDocTitle":"Futuristic copper foam batteries get more bang for the buck -- ScienceDaily","m_szYear":"2013","m_szDocSumamry":"Your source for the latest research news Mobile Follow Subscribe Breaking News: 5-D Black Hole Could 'Break' General Relativity Core Symptom of Schizophrenia Eliminated in Mice Prehistoric Village Links Old and New Stone Ages Mapping the World for Climate Sensitivity Longest-Lasting Stellar Eclipse Preventing Collapse in Complex Systems Climate Change: Depletion of Western Groundwater Is Salt Really Bad for You? Jury Still Out Light-To-Moderate Drinking Good for Your Heart Sauropod Swimmers or Walkers? Science News from research organizations Futuristic copper foam batteries get more bang for ","m_szDocBody":"source latest research new mobile follow breaking new black hole break general relativity core symptom schizophrenia eliminated mice prehistoric village link stone age mapping world climate sensitivity longestlasting stellar eclipse preventing collapse complex system climate change depletion western groundwater salt bad you jury lighttomoderate drinking good heart sauropod swimmer walker science new research organisation futuristic copper foam battery bang buck date source american institute physic summary scientist report step safer cheaper longerlasting fastercharging solidstate battery share full storey people gps app cameras mobile internet navigate strange city good coffee record selfie commentary wait line upload videos directly social media site sip latte amount hightech savvy save wellloved device dying battery drained smartphone suffer basic ailment plague solar power plant wind farm lack cheap reliable longlife battery store large amount energy sun down wind stop blowing device unplugged long time application technology limited battery amy prieto chemist colorado state university lead startup company goal developing energy storage device nearing prototype phase lithium ion battery safer cheaper fastercharging environmentally friendly conventional battery market latest result upcoming avs international symposium exhibition held oct nov long beach calif battery today number unsolved problem including cost heat output limited lifespan toxic corrosive material manufacture main issue limit functionality modern battery prieto said low energy density low power density low energy density mean conventional smartphone battery hold energy small volume power phone longer day low power density mean battery hour recharge minute prietos tackled challenge making list desired property main battery component team developed component time starting copper foam structure team purchased serve current collector anode side battery foam easy manufacture prieto structure increase surface area electrode bring closer together turn increase power density battery term energy density foam bang buck intricate structure utilise electrode material efficiently flat surface top copper foam researcher electroplate anode made material called copper antimonide kind bootstrap battery building anode serve electrode electrochemical polymerization reaction deposit battery solid electrolyte finally team fill space foam slurry dried form cathode aluminium mesh structure collect current cathode side electroplating equipment team inexpensive compared equipment needed make type battery prieto estimate cost manufacture copper foam battery half conventional lithium ion battery made china team calculate foam battery store amount energy conventional battery twothird volume charge time faster time longer research team battery promise number safety environmental benefit solid electrolyte team chose reduce risk fire posed conventional liquid electrolyte addition team relied waterbased nontoxic chemistry manufacture battery this personal dream prieto work will design process team develop way make material copper antimonide anode make material polymer electrolyte team tested individual component successfully built full battery copper plate researcher process integrating component electric bike portable electronic test application team plan foam battery year prototype party testing prieto were aiming low volume early market beta testing shortly that storey source post reprinted material provided american institute physic note material edited length cite page mla apa chicago american institute physic futuristic copper foam battery bang buck sciencedaily sciencedaily american institute physic futuristic copper foam battery bang buck sciencedaily retrieved american institute physic futuristic copper foam battery bang buck sciencedaily accessed share page related topic matter energy battery energy resource fuel cell energy technology wind energy solar energy related term evaporation fuel cell battery electric vehicle quantum entanglement scientific method earth science matter energy new black hole break general relativity mindcontrolled prosthetic arm move finger microwave train electron quantum computing printing replacement tissue latest headline updated chemistry trick pave safer diabete medication feb research point approach designing insulinbased pharmaceutical approach open door personalised medication fewer read mammography improve cancer detection cut call back year feb increased cancer detection reduced call back mammography digital breast tomosynthesis dbt read wearable robotic exoskelton science fiction meet multiple sclerosis feb walking wearable robotic exoskeleton enable people multiple sclerosis walk efficiently reducing energy muscle activity needed walk read robotic exoskelton aid poststroke motor skill rehabilitaion feb motor skill training robotic arm exoskeleton beneficial people suffering poststroke weakness affecting entire side body read organic waste sustainable battery feb carbonbased active material produced apple leftover material layered oxide reduce cost future energy storage system found read batflight inspire unique design micro air vehicle feb researcher designed innovative membrane wing inspired bat paving breed unmanned micro air vehicle mavs improved aerodynamic read physic application antiferromagnet uncovered feb researcher studied control magnetization current applied heterostructure comprising antiferromagnet found current rise read material deformation atomic scale resemble avalanches feb rearrangement particle material deformation spoon bent doesnt occur independently resemble highly collective avalanches read supercomputer probe depth biofuel biggest barrier feb cellulosic ethanol fuel derived woody plant waste biomass potential affordable renewable transportation fuel rival gasoline read researcher devise efficient material solar fuel cell feb chemist developed highperforming material cell harness sunlight split carbon dioxide water usable fuel methanol hydrogen gas green fuel read chemistry trick pave safer diabete mammography improve cancer detection wearable robotic exoskelton robotic exoskelton aid poststroke motor organic waste sustainable battery batinspired design micro air vehicle application antiferromagnet uncovered avalanche material deformation atomic scale supercomputer probe biofuel biggest barrier efficient material solar fuel cell storey latest videos new service tricorder bring diagnosis home leap motion put hand inside virtual reality closeddoor car safety tech talk raise concern researcher print living tissue videos print share related storey key quick battery charging time researcher discovered structure transport property intermediate state lithiumion battery key understanding mechanism charge discharge read wake highprofile battery fire safer approach emerge new report lithiumion battery fire boeing dreamliner plane tesla electric car remind battery everyday portable device tablet smartphone read battery made wood sliver wood coated tin make tiny longlasting efficient environmentally friendly battery read salt power watt rechargeable battery oct sodium effective inexpensive virtually inexhaustible substitute lithium drawback researcher hope read strange offbeat space time fivedimensional black hole break general relativity longestlasting stellar eclipse threeandahalf year eclipse binary system puzzling asteroid observation explained destruction asteroid close sun detection gase superearth show lightweight dry atmosphere hint carbon too matter energy batflight inspire unique design micro air vehicle mindcontrolled prosthetic arm move individual finger form frozen water metal behave water computer math storey teach human value artificial agent glass technology discovered window doubling huge power walk footstep charge mobile electronic youve heard string theory knot theory new newsdaily science china reward academic innovation drive economic growth africa arm neanderthal europe launches satellite track global warming dog read human emotion health american adult sleep cdc brazil researcher join force battle zika virus seek million zika brazil microcephaly case rise children breastfeeding birthday vitamin environment los angelesarea methane leak declared permanently sealed drought end brazil sao paulo future uncertain china power crack polluter minister south africas zuma million household hit drought technology key lawmaker suggest openness encryption legislation apple order privacy versus security heart apple phone decrypt order top york law official call apple encryption stance irresponsible fcc approve proposal boost settop box competition print share toggle navigation menu full home top science new top science videos latest new latest videos home home top science new top science videos latest new latest videos health latest top new top videos health science browse topic below health medicine allergy alternative medicine birth control cancer diabete disease heart disease hiv aid obesity stem cell topic mind brain add adhd addiction alzheimer autism depression headaches intelligence psychology relationship schizophrenia topic living parenting pregnancy sexual health skin care men health women health nutrition diet weight loss fitness healthy ageing topic latest top new top videos physical science technology browse topic below matter energy aviation chemistry electronic fossil fuel nanotechnology physic quantum physic solar energy technology wind energy topic space time astronomy black hole dark matter extrasolar planet mar moon solar system space telescope star sun topic computer math artificial intelligence communication computer science hacking mathematic quantum computer robotic software video game virtual reality topic environment latest top new top videos environmental science browse topic below plant animal agriculture food animal biology biotechnology endangered animal extinction genetically modified microbe specy zoology topic earth climate climate earthquake environment geography geology global warming hurricane ozone hole pollution weather topic fossil ruin ancient civilization anthropology archaeology dinosaur early human early mammal evolution lost treasure origin life palaeontology topic latest top new top videos social science education browse topic below science art culture consumerism economic political science privacy issue public health racial disparity religion sport world development topic business industry biotechnology bioengineering computer internet energy resource engineering medical technology pharmaceutical transportation topic education learning animal learning intelligence creativity educational psychology educational technology infant preschool learning learning disorder stem education topic quirky top new top videos human quirk odd creature bizarre weird world full free subscription latest science new sciencedaily free newsletter updated daily weekly hourly updated newsfeed reader newsletter feed follow date latest new sciencedaily social network google linkedin mobile app latest new sciencedaily free mobile app download platform android feedback sciencedaily positive negative comment problem site question leave feedback contact editorial staff award review contribute advertise privacy policy term copyright sciencedaily party indicated right controlled respective owner website information only intended provide medical professional advice view expressed necessarily reflect sciencedaily staff contributor partner","m_szGeo1":"","m_szSourceType":"source_news","m_szSrcUrl":"https://www.sciencedaily.com/releases/2013/10/131023131822.htm","m_Places":["Mobile","Walkers","Well","Long Beach, Calif.","Made","China","Chicago","Barrier","Tesla","United States","Africa","Europe","Brazil","Los Angeles","Sao Paulo","South Africa","New York"],"m_People":["Amy Prieto"],"m_Companies":["Science News","American Institute Of Physics","Colorado State University","Lifespans","Apa","Solar Energy","Apple","Mavs","Avalanches","Avalanche","Leap Motion","Boeing","Remind","Asteroid","Asteroids","New Glass Technology","Theory","Knot","Cdc","Parenting","Men's Health","Women's Health","Fossils","Humans","Facebook","Twitter","Google","Linkedin"],"m_BiGrams":["copper foam","foam battery","new top","bang buck","american institute","institute physic","top new","top videos","black hole","science new","futuristic copper","battery bang","matter energy","fuel cell","robotic exoskelton","micro air","air vehicle","top science","latest new","latest top","browse topic","topic below","hole break","break general","general relativity","energy density","power density","physic futuristic","buck sciencedaily","cancer detection","wearable robotic","design micro","material deformation","latest videos","new sciencedaily"],"m_TriGrams":["copper foam battery","american institute physic","futuristic copper foam","foam battery bang","battery bang buck","micro air vehicle","latest top new","browse topic below","black hole break","hole break general","break general relativity","institute physic futuristic","physic futuristic copper","bang buck sciencedaily","design micro air"],"m_SocialTags":[],"m_Topics":[],"m_Industry":[],"m_Technology":[],"m_BiCnt":[7,7,7,5,5,5,5,5,4,4,4,4,4,4,4,4,4,4,4,4,4,4,3,3,3,3,3,3,3,3,3,3,3,3,3],"m_TriCnt":[5,5,4,4,4,4,4,4,3,3,3,3,3,3,3],"m_iDocBodyWordCnt":1505}
