{"m_szDocID":"97296","m_szDocTitle":"Copper Foam Batteries -- Increased Energy Storage, Faster Charge Times, & Decreased Production Costs | CleanTechnica","m_szYear":"2013","m_szDocSumamry":"Surprise Article! Electric Cars Solar Power Wind Power 100% Renewable Energy? RSS Sponsor A Post Advertise CleanTechnica is the #1 cleantech-focused news & analysis site in the world. Subscribe today! The future is now. About About Our Team CleanTechnica Comment Policy Use Of Our Content Important Media Network Important Media Jobs Contact Us Sponsor A Post Buy Banner Ad Space Local Solar Discounts Exclusives All Exclusives CleanTechnica Reports CleanTechnica Reviews CleanTechnica Videos CT Reviews (New) Audi A3 e-tron Review BMW i3 Review BMW i3 vs Mercedes B-Class Electric BMW i3 vs Nissan L","m_szDocBody":"surprise article electric car solar power wind power renewable energy sponsor post advertise cleantechnica the# cleantechfocused new analysis sitein world today future now team cleantechnica comment policy important media network important media job contact sponsor post buy banner space local solar discount exclusive exclusive cleantechnica report cleantechnica review cleantechnica videos review new audi etron review bmw review bmw mercede bclass electric bmw nissan leaf chevy volt bmw tesla model bmw tesla model cadillac elr porsche panamera ehybrid bmw chevy spark review chevy volt review chevy volt cost ownership review mercede bclass electric drive mitsubishi outlander phev review nissan leaf longterm review renault twizy review renault zoe review smart electric drive review smart electric drive camaro tesla model review volkswagen egolf review volkswagen eup review power solar energy new local solar discount solar solar energy wind energy new wind energy energy efficiency lighting led energy storage smart grid geothermal energy hydroelectricy marine energy biomass transport electric vehicle electric vehicle new electric car sale electric car greener tesla motor bicycle benefit bicycling biofuel car boat mass transit public transit train rail aviation shipping surprise navigation surprise article electric car solar power wind power renewable energy sponsor post advertise battery published jame ayre copper foam battery increased energy storage faster charge time decreased production cost jame ayre originally published obsession copper foam battery new cheapertomanufacture fastertocharge longerlasting alternative battery common today headed commercial market result effort startup created researcher colorado state university prototype finished year researcher thirdparty testing that researcher that limitation current battery technology market copper foam battery application technology limited battery explain amy prieto chemist colorado state university leader startup main issue limit functionality modern battery low energy density low power density image credit prieto battery address issue other researcher set create ideal battery making list desired property main battery component set develop component time utilising copper foam structure purchased serve current collector anode side battery foam easy manufacture state prieto structure increase surface area electrode bring closer together turn increase power density battery term energy density foam bang buck intricate structure utilise electrode material efficiently flat surface american institute physic more top copper foam researcher electroplate anode made material called copper antimonide kind bootstrap battery building anode serve electrode electrochemical polymerization reaction deposit battery solid electrolyte finally team fill space foam slurry dried form cathode aluminium mesh structure collect current cathode side electroplating equipment team inexpensive compared equipment needed make type battery prieto estimate cost manufacture copper foam battery half conventional lithiumion battery made china team calculate foam battery store amount energy conventional battery twothird volume charge time faster time longer battery possesse number significant advantage conventional battery regard safety environment waterbased nontoxic chemistry manufacture battery personal dream explain prieto didnt work will application researcher mind battery electric bike portable electronic technology benefit greatly improved battery technology year prototype party testing prieto aiming low volume early market beta testing shortly that cleantechnicas completely free electric car report electric car early adopter follower want date hottest cleantech new subscribing free cleantech newsletter eye sectorspecific new also free solar energy newsletter electric vehicle newsletter wind energy newsletter share reddit open window share google open window share linkedin open window share open window share pinterest open window share open window share tumblr open window friend open window print open window share pocket open window press this open window tag colorado state university colorado state university copper foam battery copper foam battery copper foam battery charge time copper foam battery cost copper foam battery manufacturing jame ayre background predominantly geopolitic history obsessive interest pretty everything early life spent imperial free city dortmund jame river ruhr cofbuokheim attended university astnide briefly considered entering coal mining business write living broad variety subject ranging science politic military history renewable energy follow work google related post lesson frankenstorm investing future power disruption radically technique produce hydrogen fuel water tracking pending energy legislation place nrel arpae team improve battery management william tabaro spec please energy density cell voltage cycle life etc help comparisson liion trontek good time save world energy nature safety point humanbeing wayne williamson hope work outjust wondering didnt aluminium foam cathode ivor oconnor suspect surface area excellent making ideal energy density solution film chemically washed cycle youll buy battery curious turn arnenl film wash chemically ivor oconnor reason battery acid corrosive material fall bottom battery capable season energy weight ratio low battery great energy weight storage battery arnenl dont scale recompress image lowre version illegible back top contact sponsoring cleantechnica brand front million reader month top post page top reason tesla model reservation starting store make sense wind turbine construction video wind energy top electric capacity dont count hydropower wind tower set reach metre cleantechnica electric car report required address advertisement connect follow cleantechnica solar event network cleantechnica cleantechfocused website world part important media network blog working make world better greener place produced entertainment purpose only opinion comment published sanctioned necessarily represent view sustainable enterprise media inc owner sponsor affiliate subsidiary sustainable enterprise media inc surprise article electric car solar power wind power renewable energy sponsor post advertise back top share send address address cancel post cheque addresse cheque failed sorry share post email","m_szGeo1":"","m_szSourceType":"source_news","m_szSrcUrl":"http://cleantechnica.com/2013/10/30/copper-foam-batteries-increased-energy-storage-faster-charge-times-decreased-production-costs/","m_Places":["United States","Banner","China","Free City","Dortmund","Tesla","Starting"],"m_People":["Cleantechnica Solar","Mercedes-benz B-class","Chevy Volt","Renault Zoe","Are Greener","James Ayre","Amy Prieto","William Tabaro","Wayne Williamson","Ivor O’connor"],"m_Companies":["Audi A3","Bmw","I3","Cadillac","Volkswagen","Solar Energy","Tesla Motors","Colorado State University","American Institute Of Physics","Reddit","Google","Linkedin","Twitter","Pinterest","Facebook","University Of Astnide","Future Power","Im Network"],"m_BiGrams":["copper foam","open window","foam battery","electric car","window share","renewable energy","sponsor post","tesla model","wind energy","colorado state","state university","energy density","surprise article","article electric","car solar","solar power","power wind","wind power","power renewable","energy sponsor","post advertise","important media","chevy volt","electric drive","electric vehicle","jame ayre","charge time"],"m_TriGrams":["copper foam battery","open window share","colorado state university","article electric car","electric car solar","car solar power","solar power wind","renewable energy sponsor","energy sponsor post","sponsor post advertise"],"m_SocialTags":[],"m_Topics":[],"m_Industry":[],"m_Technology":[],"m_BiCnt":[11,11,10,8,7,4,4,4,4,4,4,4,3,3,3,3,3,3,3,3,3,3,3,3,3,3,3],"m_TriCnt":[9,7,4,3,3,3,3,3,3,3],"m_iDocBodyWordCnt":857}
