{"m_szDocID":"97758","m_szDocTitle":"How Soon Till Your Favorite Advanced Material (Graphene, Quantum Dots, etc) Is Commercialized? Lux Research May Know | CleanTechnica","m_szYear":"2014","m_szDocSumamry":"Surprise Article! Electric Cars Solar Power Wind Power 100% Renewable Energy? RSS Sponsor A Post Advertise CleanTechnica is the #1 cleantech-focused news & analysis site in the world. Subscribe today! The future is now. About About Our Team CleanTechnica Comment Policy Use Of Our Content Important Media Network Important Media Jobs Contact Us Sponsor A Post Buy Banner Ad Space Local Solar Discounts Exclusives All Exclusives CleanTechnica Reports CleanTechnica Reviews CleanTechnica Videos CT Reviews (New) Audi A3 e-tron Review BMW i3 Review BMW i3 vs Mercedes B-Class Electric BMW i3 vs Nissan L","m_szDocBody":"surprise article electric car solar power wind power renewable energy sponsor post advertise cleantechnica the# cleantechfocused new analysis sitein world today future now team cleantechnica comment policy important media network important media job contact sponsor post buy banner space local solar discount exclusive exclusive cleantechnica report cleantechnica review cleantechnica videos review new audi etron review bmw review bmw mercede bclass electric bmw nissan leaf chevy volt bmw tesla model bmw tesla model cadillac elr porsche panamera ehybrid bmw chevy spark review chevy volt review chevy volt cost ownership review mercede bclass electric drive mitsubishi outlander phev review nissan leaf longterm review renault twizy review renault zoe review smart electric drive review smart electric drive camaro tesla model review volkswagen egolf review volkswagen eup review power solar energy new local solar discount solar solar energy wind energy new wind energy energy efficiency lighting led energy storage smart grid geothermal energy hydroelectricy marine energy biomass transport electric vehicle electric vehicle new electric car sale electric car greener tesla motor bicycle benefit bicycling biofuel car boat mass transit public transit train rail aviation shipping surprise navigation surprise article electric car solar power wind power renewable energy sponsor post advertise green economy published guest contributor till favourite advanced material graphene quantum dot etc commercialised lux research guest contributor originally published lux research website advanced material mof metal organic framework advanced highstrength steel carbon nanotube potential enable product disrupt existing businesse however material commercialization timeline notoriously long unpredictable nowlux researchanalyst designed tool predict commercial development trajectory future material rising pressure developer bring material market quickly efficiently material fail meet hype disappoint investor unrealistic timeline expectation anthony vicari lux research associate lead report titled planning ripe fruit material innovation lifecycle predictive scouting tool big thing technology scout venture capitalist big require patience allow meaning clever planning crucial added lux research analyst assessed inventiontocommercialization pathway material identified key variable strongly influence commercialization path compared specific emerging material mature material classification predict major commercial milestone emerging material major finding quantum dot ready takeoff startup vision andnanosyshave developed scalable solution production processe partnered large oem quantum dot nanometerscale crystal semiconductor material display comparing quantum dot path piezoelectric material pzt suggest commercial takeoff imminent sheet magnesium plas trajectorymagnesium lighter aluminium cheaper carbon fibre reinforced polymer cfrp making highly attractive auto industry todayposcoand thyssenkrupp sheet magnesium cargill dow forpolylacticacid pla expect sheet magnesium grapheneto peak grapheneis attracting lot attention face challenge production cost dispersion issue comparinggrapheneto highperformance polymer peek suggest thatgraphenesmajor commercial inflexion point future expectgrapheneto begin widespread battery electrode conductive composite report titled planning ripe fruit material innovation lifecycle predictive scouting tool part lux researchadvanced material intelligenceservice lux research lux research strategic advice ongoing intelligence emerging technology leader business finance government rely make informed strategic decision unique research approach focused primary research extensive global network deliver insight connexion competitive advantage client visit information cleantechnicas completely free electric car report electric car early adopter follower want date hottest cleantech new subscribing free cleantech newsletter eye sectorspecific new also free solar energy newsletter electric vehicle newsletter wind energy newsletter share reddit open window share google open window share linkedin open window share open window share pinterest open window share open window share tumblr open window friend open window print open window share pocket open window press this open window tag graphene magnesium metalorganic framework mof quantum dot sheet magnesium guest contributor many people publish number guest post expert large variety field contributor account special people related post grapheneglass combo power spontaneous solar cell solar cell breakthrough perfect white graphene researcher cook energy storage stew hydrogen graphene siliconsulfurgraphene lithiumion battery boost arnenl carbon nanotube material future graphene crown time cost interested replacement copper electrical wiring copper heavy fragile increasingly scarce research promising production process simple scalable jameswimberley peek tough mechanical polymer nylon wikipedia extensively aerospace automotive teletronic chemical process industry doesnt highgrowth sector graphene potential application include overcoming roadblock solar battery sector explosive growth characteristic target market impact speed adoption material real libertarian graphene potential application include overcoming roadblock solar battery sector explosive growth dont forget computer back top contact sponsoring cleantechnica brand front million reader month top post page top reason tesla model reservation starting store make sense wind turbine construction video wind energy top electric capacity dont count hydropower wind tower set reach metre cleantechnica electric car report required address advertisement connect follow cleantechnica solar event network cleantechnica cleantechfocused website world part important media network blog working make world better greener place produced entertainment purpose only opinion comment published sanctioned necessarily represent view sustainable enterprise media inc owner sponsor affiliate subsidiary sustainable enterprise media inc surprise article electric car solar power wind power renewable energy sponsor post advertise back top share send address address cancel post cheque addresse cheque failed sorry blog share post email","m_szGeo1":"","m_szSourceType":"source_news","m_szSrcUrl":"http://cleantechnica.com/2014/02/01/soon-till-favorite-advanced-material-graphene-quantum-dots-etc-commercialized-lux-research-may-know/","m_Places":["United States","Banner","Tesla","Starting"],"m_People":["Cleantechnica Solar","Mercedes-benz B-class","Chevy Volt","Renault Zoe","Are Greener","Anthony Vicari"],"m_Companies":["Audi A3","Bmw","I3","Cadillac","Volkswagen","Solar Energy","Tesla Motors","Ups","Path","Thyssenkrupp","Cargill","Reddit","Google","Linkedin","Twitter","Pinterest","Facebook","Crown","Wikipedia","Target","Im Network"],"m_BiGrams":["open window","electric car","window share","lux research","quantum dot","sponsor post","tesla model","wind energy","sheet magnesium","surprise article","article electric","car solar","solar power","power wind","wind power","power renewable","renewable energy","energy sponsor","post advertise","important media","chevy volt","electric drive","electric vehicle","guest contributor"],"m_TriGrams":["open window share","article electric car","electric car solar","car solar power","solar power wind","renewable energy sponsor","energy sponsor post","sponsor post advertise"],"m_SocialTags":[],"m_Topics":[],"m_Industry":[],"m_Technology":[],"m_BiCnt":[11,8,7,6,5,4,4,4,4,3,3,3,3,3,3,3,3,3,3,3,3,3,3,3],"m_TriCnt":[7,3,3,3,3,3,3,3],"m_iDocBodyWordCnt":793}
